Workbook
Name A2325846C: Data1!$B$1:$B$10,Data1!$B$11:$B$320
Name A2325846C_Data: Data1!$B$11:$B$320
Name A2325846C_Latest: Data1!$B$320
Name A2325850V: Data1!$ED$1:$ED$10,Data1!$ED$12:$ED$320
Name A2325850V_Data: Data1!$ED$12:$ED$320
Name A2325850V_Latest: Data1!$ED$320
Name A2325891R: Data1!$C$1:$C$10,Data1!$C$107:$C$320
Name A2325891R_Data: Data1!$C$107:$C$320
Name A2325891R_Latest: Data1!$C$320
Name A2325895X: Data1!$EE$1:$EE$10,Data1!$EE$108:$EE$320
Name A2325895X_Data: Data1!$EE$108:$EE$320
Name A2325895X_Latest: Data1!$EE$320
Name A2325936J: Data1!$AQ$1:$AQ$10,Data1!$AQ$107:$AQ$320
Name A2325936J_Data: Data1!$AQ$107:$AQ$320
Name A2325936J_Latest: Data1!$AQ$320
Name A2325940X: Data1!$FS$1:$FS$10,Data1!$FS$108:$FS$320
Name A2325940X_Data: Data1!$FS$108:$FS$320
Name A2325940X_Latest: Data1!$FS$320
Name A2325981V: Data1!$BC$1:$BC$10,Data1!$BC$107:$BC$320
Name A2325981V_Data: Data1!$BC$107:$BC$320
Name A2325981V_Latest: Data1!$BC$320
Name A2325985C: Data1!$GE$1:$GE$10,Data1!$GE$108:$GE$320
Name A2325985C_Data: Data1!$GE$108:$GE$320
Name A2325985C_Latest: Data1!$GE$320
Name A2326026R: Data1!$BO$1:$BO$10,Data1!$BO$107:$BO$320
Name A2326026R_Data: Data1!$BO$107:$BO$320
Name A2326026R_Latest: Data1!$BO$320
Name A2326030F: Data1!$GQ$1:$GQ$10,Data1!$GQ$108:$GQ$320
Name A2326030F_Data: Data1!$GQ$108:$GQ$320
Name A2326030F_Latest: Data1!$GQ$320
Name A2326071A: Data1!$CO$1:$CO$10,Data1!$CO$107:$CO$320
Name A2326071A_Data: Data1!$CO$107:$CO$320
Name A2326071A_Latest: Data1!$CO$320
Name A2326075K: Data1!$HQ$1:$HQ$10,Data1!$HQ$108:$HQ$320
Name A2326075K_Data: Data1!$HQ$108:$HQ$320
Name A2326075K_Latest: Data1!$HQ$320
Name A2326116V: Data1!$AJ$1:$AJ$10,Data1!$AJ$107:$AJ$320
Name A2326116V_Data: Data1!$AJ$107:$AJ$320
Name A2326116V_Latest: Data1!$AJ$320
Name A2326120K: Data1!$FL$1:$FL$10,Data1!$FL$108:$FL$320
Name A2326120K_Data: Data1!$FL$108:$FL$320
Name A2326120K_Latest: Data1!$FL$320
Name A2326161F: Data1!$P$1:$P$10,Data1!$P$107:$P$320
Name A2326161F_Data: Data1!$P$107:$P$320
Name A2326161F_Latest: Data1!$P$320
Name A2326165R: Data1!$ER$1:$ER$10,Data1!$ER$108:$ER$320
Name A2326165R_Data: Data1!$ER$108:$ER$320
Name A2326165R_Latest: Data1!$ER$320
Name A2326206X: Data1!$D$1:$D$10,Data1!$D$107:$D$320
Name A2326206X_Data: Data1!$D$107:$D$320
Name A2326206X_Latest: Data1!$D$320
Name A2326210R: Data1!$EF$1:$EF$10,Data1!$EF$108:$EF$320
Name A2326210R_Data: Data1!$EF$108:$EF$320
Name A2326210R_Latest: Data1!$EF$320
Name A2326251K: Data1!$I$1:$I$10,Data1!$I$107:$I$320
Name A2326251K_Data: Data1!$I$107:$I$320
Name A2326251K_Latest: Data1!$I$320
Name A2326255V: Data1!$EK$1:$EK$10,Data1!$EK$108:$EK$320
Name A2326255V_Data: Data1!$EK$108:$EK$320
Name A2326255V_Latest: Data1!$EK$320

Sheet Index
B2: Time Series Workbook
B5: 6401.0 Consumer Price Index, Australia
B6: TABLE 18. CPI: Quarterly Group, Sub-group and Expenditure Class, Weighted Average of Eight Capital Cities
D8: Enquiries
A10: Data Item Description | D10: Series Type | E10: Series ID | F10: Series Start | G10: Series End | H10: No. Obs. | I10: Unit | J10: Data Type | K10: Freq. | L10: Collection Month
A12: Index Numbers ; All groups CPI ; Australia ; | D12: Original | E12: A2325846C | F12: 17777 | G12: 45992 | H12: 310 | I12: Index Numbers | J12: INDEX | K12: Quarter | L12: 3
A13: Index Numbers ; Food and non-alcoholic beverages ; Australia ; | D13: Original | E13: A2325891R | F13: 26543 | G13: 45992 | H13: 214 | I13: Index Numbers | J13: INDEX | K13: Quarter | L13: 3
A14: Index Numbers ; Bread and cereal products ; Australia ; | D14: Original | E14: A2326206X | F14: 26543 | G14: 45992 | H14: 214 | I14: Index Numbers | J14: INDEX | K14: Quarter | L14: 3
A15: Index Numbers ; Bread ; Australia ; | D15: Original | E15: A2327061R | F15: 29465 | G15: 45992 | H15: 182 | I15: Index Numbers | J15: INDEX | K15: Quarter | L15: 3
A16: Index Numbers ; Cakes and biscuits ; Australia ; | D16: Original | E16: A2327106J | F16: 29465 | G16: 45992 | H16: 182 | I16: Index Numbers | J16: INDEX | K16: Quarter | L16: 3
A17: Index Numbers ; Breakfast cereals ; Australia ; | D17: Original | E17: A2327151V | F17: 29465 | G17: 45992 | H17: 182 | I17: Index Numbers | J17: INDEX | K17: Quarter | L17: 3
A18: Index Numbers ; Other cereal products ; Australia ; | D18: Original | E18: A2327196X | F18: 29465 | G18: 45992 | H18: 182 | I18: Index Numbers | J18: INDEX | K18: Quarter | L18: 3
A19: Index Numbers ; Meat and seafoods ; Australia ; | D19: Original | E19: A2326251K | F19: 26543 | G19: 45992 | H19: 214 | I19: Index Numbers | J19: INDEX | K19: Quarter | L19: 3
A20: Index Numbers ; Beef and veal ; Australia ; | D20: Original | E20: A2327241X | F20: 26543 | G20: 45992 | H20: 214 | I20: Index Numbers | J20: INDEX | K20: Quarter | L20: 3
A21: Index Numbers ; Pork ; Australia ; | D21: Original | E21: A3604358R | F21: 29465 | G21: 45992 | H21: 182 | I21: Index Numbers | J21: INDEX | K21: Quarter | L21: 3
A22: Index Numbers ; Lamb and goat ; Australia ; | D22: Original | E22: A2327286C | F22: 26543 | G22: 45992 | H22: 214 | I22: Index Numbers | J22: INDEX | K22: Quarter | L22: 3
A23: Index Numbers ; Poultry ; Australia ; | D23: Original | E23: A2327376J | F23: 26543 | G23: 45992 | H23: 214 | I23: Index Numbers | J23: INDEX | K23: Quarter | L23: 3
... A407: Contribution to Total CPI ; Other financial services ; Australia ; | D407: Original | E407: A3603555J | F407: 45992 | G407: 45992 | H407: 1 | I407: Index Points | J407: INDEX | K407: Quarter | L407: 3
A409: © Commonwealth of Australia 2026

Sheet Energy Prices
A1: Energy Prices in Australia — Growth Over Time
A2: Source: ABS 6401.0 Consumer Price Index, Australia — Table 18 (Weighted Average of Eight Capital Cities). Reference period: Sep 2025 = 100.0.
A3: Series: Electricity (A2328141J, from Sep 1980) and Gas & other household fuels (A2331921F, from Sep 1989). All Groups CPI (A2325846C) shown as a reference.
A5: Headline growth rates | F5: Quarterly index values (Sep 2025 = 100) | N5: Annual snapshot (September quarter each year)
A7: Period | B7: Electricity | C7: Gas & household fuels | D7: All Groups CPI | F7: Quarter | G7: All Groups CPI | H7: Electricity | I7: Gas & household fuels | J7: Electricity YoY % | K7: Gas YoY % | L7: CPI YoY % | N7: Year | O7: Electricity index | P7: Gas index | Q7: CPI index | R7: Electricity annual % | S7: Gas annual % | T7: CPI annual % | V7: Quarter | W7: Electricity YoY % | X7: Gas YoY % | Y7: CPI YoY %
A8: Latest year (Sep 2024 → Sep 2025) | B8: =Data1!BM320/Data1!BM316-1 -> 0.25575174 | C8: =Data1!BN320/Data1!BN316-1 -> 0.045859873 | D8: =Data1!B320/Data1!B316-1 -> 0.036256585 | F8: =Data1!A139 -> 29465 | G8: =Data1!B139 -> 18.48 | H8: =Data1!BM139 -> 10.46 | I8: =IF(ISBLANK(Data1!BN139),NA(),Data1!BN139) -> #N/A | J8: =IFERROR(Data1!BM139/Data1!BM135-1,NA()) -> #N/A | K8: =IFERROR(IF(OR(ISBLANK(Data1!BN139),ISBLANK(Data1!BN135)),NA(),Data1!BN139/Data1!BN135-1),NA()) -> #N/A | L8: =IFERROR(Data1!B139/Data1!B135-1,NA()) -> 0.10131108 | N8: 1980 | O8: {=INDEX(Data1!BM:BM,140+($N8-1980)*4)} -> 10.53 | P8: {=IF($N8<1989,NA(),INDEX(Data1!BN:BN,140+($N8-1980)*4))} -> #N/A | Q8: {=INDEX(Data1!B:B,140+($N8-1980)*4)} -> 18.87 | V8: =F8 -> 29465 | W8: =J8 -> #N/A | X8: =K8 -> #N/A | Y8: =L8 -> 0.10131108
A9: Last 5 years (Sep 2020 → Sep 2025) — cumulative | B9: =Data1!BM320/Data1!BM300-1 -> 0.15402581 | C9: =Data1!BN320/Data1!BN300-1 -> 0.49317975 | D9: =Data1!B320/Data1!B300-1 -> 0.23243243 | F9: =Data1!A140 -> 29556 | G9: =Data1!B140 -> 18.87 | H9: =Data1!BM140 -> 10.53 | I9: =IF(ISBLANK(Data1!BN140),NA(),Data1!BN140) -> #N/A | J9: =IFERROR(Data1!BM140/Data1!BM136-1,NA()) -> #N/A | K9: =IFERROR(IF(OR(ISBLANK(Data1!BN140),ISBLANK(Data1!BN136)),NA(),Data1!BN140/Data1!BN136-1),NA()) -> #N/A | L9: =IFERROR(Data1!B140/Data1!B136-1,NA()) -> 0.092013889 | N9: =N8+1 -> 1981 | O9: {=INDEX(Data1!BM:BM,140+($N9-1980)*4)} -> 12.31 | P9: {=IF($N9<1989,NA(),INDEX(Data1!BN:BN,140+($N9-1980)*4))} -> #N/A | Q9: {=INDEX(Data1!B:B,140+($N9-1980)*4)} -> 20.99 | R9: =IFERROR(O9/O8-1,NA()) -> 0.16904084 | S9: =IFERROR(IF(OR(ISNA(P9),ISNA(P8)),NA(),P9/P8-1),NA()) -> #N/A | T9: =IFERROR(Q9/Q8-1,NA()) -> 0.11234764 | V9: =F9 -> 29556 | W9: =J9 -> #N/A | X9: =K9 -> #N/A | Y9: =L9 -> 0.092013889
A10: Last 5 years — annualised (CAGR) | B10: =(Data1!BM320/Data1!BM300)^(1/5)-1 -> 0.029065704 | C10: =(Data1!BN320/Data1!BN300)^(1/5)-1 -> 0.08348379 | D10: =(Data1!B320/Data1!B300)^(1/5)-1 -> 0.042683794 | F10: =Data1!A141 -> 29646 | G10: =Data1!B141 -> 19.33 | H10: =Data1!BM141 -> 11.47 | I10: =IF(ISBLANK(Data1!BN141),NA(),Data1!BN141) -> #N/A | J10: =IFERROR(Data1!BM141/Data1!BM137-1,NA()) -> #N/A | K10: =IFERROR(IF(OR(ISBLANK(Data1!BN141),ISBLANK(Data1!BN137)),NA(),Data1!BN141/Data1!BN137-1),NA()) -> #N/A | L10: =IFERROR(Data1!B141/Data1!B137-1,NA()) -> 0.093944539 | N10: =N9+1 -> 1982 | O10: {=INDEX(Data1!BM:BM,140+($N10-1980)*4)} -> 16.53 | P10: {=IF($N10<1989,NA(),INDEX(Data1!BN:BN,140+($N10-1980)*4))} -> #N/A | Q10: {=INDEX(Data1!B:B,140+($N10-1980)*4)} -> 23.31 | R10: =IFERROR(O10/O9-1,NA()) -> 0.34281072 | S10: =IFERROR(IF(OR(ISNA(P10),ISNA(P9)),NA(),P10/P9-1),NA()) -> #N/A | T10: =IFERROR(Q10/Q9-1,NA()) -> 0.11052882 | V10: =F10 -> 29646 | W10: =J10 -> #N/A | X10: =K10 -> #N/A | Y10: =L10 -> 0.093944539
A11: Last 10 years (Sep 2015 → Sep 2025) — cumulative | B11: =Data1!BM320/Data1!BM280-1 -> 0.21213686 | C11: =Data1!BN320/Data1!BN280-1 -> 0.67209776 | D11: =Data1!B320/Data1!B280-1 -> 0.33280191 | F11: =Data1!A142 -> 29738 | G11: =Data1!B142 -> 19.76 | H11: =Data1!BM142 -> 11.57 | I11: =IF(ISBLANK(Data1!BN142),NA(),Data1!BN142) -> #N/A | J11: =IFERROR(Data1!BM142/Data1!BM138-1,NA()) -> #N/A | K11: =IFERROR(IF(OR(ISBLANK(Data1!BN142),ISBLANK(Data1!BN138)),NA(),Data1!BN142/Data1!BN138-1),NA()) -> #N/A | L11: =IFERROR(Data1!B142/Data1!B138-1,NA()) -> 0.087506879 | N11: =N10+1 -> 1983 | O11: {=INDEX(Data1!BM:BM,140+($N11-1980)*4)} -> 17.88 | P11: {=IF($N11<1989,NA(),INDEX(Data1!BN:BN,140+($N11-1980)*4))} -> #N/A | Q11: {=INDEX(Data1!B:B,140+($N11-1980)*4)} -> 25.32 | R11: =IFERROR(O11/O10-1,NA()) -> 0.081669691 | S11: =IFERROR(IF(OR(ISNA(P11),ISNA(P10)),NA(),P11/P10-1),NA()) -> #N/A | T11: =IFERROR(Q11/Q10-1,NA()) -> 0.086229086 | V11: =F11 -> 29738 | W11: =J11 -> #N/A | X11: =K11 -> #N/A | Y11: =L11 -> 0.087506879
A12: Last 10 years — annualised (CAGR) | B12: =(Data1!BM320/Data1!BM280)^(1/10)-1 -> 0.019424732 | C12: =(Data1!BN320/Data1!BN280)^(1/10)-1 -> 0.052752221 | D12: =(Data1!B320/Data1!B280)^(1/10)-1 -> 0.029144982 | F12: =Data1!A143 -> 29830 | G12: =Data1!B143 -> 20.14 | H12: =Data1!BM143 -> 12.05 | I12: =IF(ISBLANK(Data1!BN143),NA(),Data1!BN143) -> #N/A | J12: =IFERROR(Data1!BM143/Data1!BM139-1,NA()) -> 0.15200765 | K12: =IFERROR(IF(OR(ISBLANK(Data1!BN143),ISBLANK(Data1!BN139)),NA(),Data1!BN143/Data1!BN139-1),NA()) -> #N/A | L12: =IFERROR(Data1!B143/Data1!B139-1,NA()) -> 0.08982684 | N12: =N11+1 -> 1984 | O12: {=INDEX(Data1!BM:BM,140+($N12-1980)*4)} -> 18.39 | P12: {=IF($N12<1989,NA(),INDEX(Data1!BN:BN,140+($N12-1980)*4))} -> #N/A | Q12: {=INDEX(Data1!B:B,140+($N12-1980)*4)} -> 25.98 | R12: =IFERROR(O12/O11-1,NA()) -> 0.02852349 | S12: =IFERROR(IF(OR(ISNA(P12),ISNA(P11)),NA(),P12/P11-1),NA()) -> #N/A | T12: =IFERROR(Q12/Q11-1,NA()) -> 0.026066351 | V12: =F12 -> 29830 | W12: =J12 -> 0.15200765 | X12: =K12 -> #N/A | Y12: =L12 -> 0.08982684
A13: Last 20 years (Sep 2005 → Sep 2025) — cumulative | B13: =Data1!BM320/Data1!BM240-1 -> 1.5359265 | C13: =Data1!BN320/Data1!BN240-1 -> 2.1893817 | D13: =Data1!B320/Data1!B240-1 -> 0.7231192 | F13: =Data1!A144 -> 29921 | G13: =Data1!B144 -> 20.99 | H13: =Data1!BM144 -> 12.31 | I13: =IF(ISBLANK(Data1!BN144),NA(),Data1!BN144) -> #N/A | J13: =IFERROR(Data1!BM144/Data1!BM140-1,NA()) -> 0.16904084 | K13: =IFERROR(IF(OR(ISBLANK(Data1!BN144),ISBLANK(Data1!BN140)),NA(),Data1!BN144/Data1!BN140-1),NA()) -> #N/A | L13: =IFERROR(Data1!B144/Data1!B140-1,NA()) -> 0.11234764 | N13: =N12+1 -> 1985 | O13: {=INDEX(Data1!BM:BM,140+($N13-1980)*4)} -> 19.54 | P13: {=IF($N13<1989,NA(),INDEX(Data1!BN:BN,140+($N13-1980)*4))} -> #N/A | Q13: {=INDEX(Data1!B:B,140+($N13-1980)*4)} -> 28.11 | R13: =IFERROR(O13/O12-1,NA()) -> 0.062533986 | S13: =IFERROR(IF(OR(ISNA(P13),ISNA(P12)),NA(),P13/P12-1),NA()) -> #N/A | T13: =IFERROR(Q13/Q12-1,NA()) -> 0.081986143 | V13: =F13 -> 29921 | W13: =J13 -> 0.16904084 | X13: =K13 -> #N/A | Y13: =L13 -> 0.11234764
A14: Last 20 years — annualised (CAGR) | B14: =(Data1!BM320/Data1!BM240)^(1/20)-1 -> 0.047627363 | C14: =(Data1!BN320/Data1!BN240)^(1/20)-1 -> 0.059705833 | D14: =(Data1!B320/Data1!B240)^(1/20)-1 -> 0.027580292 | F14: =Data1!A145 -> 30011 | G14: =Data1!B145 -> 21.38 | H14: =Data1!BM145 -> 13.42 | I14: =IF(ISBLANK(Data1!BN145),NA(),Data1!BN145) -> #N/A | J14: =IFERROR(Data1!BM145/Data1!BM141-1,NA()) -> 0.17000872 | K14: =IFERROR(IF(OR(ISBLANK(Data1!BN145),ISBLANK(Data1!BN141)),NA(),Data1!BN145/Data1!BN141-1),NA()) -> #N/A | L14: =IFERROR(Data1!B145/Data1!B141-1,NA()) -> 0.10605277 | N14: =N13+1 -> 1986 | O14: {=INDEX(Data1!BM:BM,140+($N14-1980)*4)} -> 20.75 | P14: {=IF($N14<1989,NA(),INDEX(Data1!BN:BN,140+($N14-1980)*4))} -> #N/A | Q14: {=INDEX(Data1!B:B,140+($N14-1980)*4)} -> 30.85 | R14: =IFERROR(O14/O13-1,NA()) -> 0.061924258 | S14: =IFERROR(IF(OR(ISNA(P14),ISNA(P13)),NA(),P14/P13-1),NA()) -> #N/A | T14: =IFERROR(Q14/Q13-1,NA()) -> 0.097474208 | V14: =F14 -> 30011 | W14: =J14 -> 0.17000872 | X14: =K14 -> #N/A | Y14: =L14 -> 0.10605277
A15: Since series start — cumulative | B15: =Data1!BM320/Data1!BM139-1 -> 7.9751434 | C15: =Data1!BN320/Data1!BN175-1 -> 4.8330373 | D15: =Data1!B320/Data1!B139-1 -> 4.4285714 | F15: =Data1!A146 -> 30103 | G15: =Data1!B146 -> 21.88 | H15: =Data1!BM146 -> 14.07 | I15: =IF(ISBLANK(Data1!BN146),NA(),Data1!BN146) -> #N/A | J15: =IFERROR(Data1!BM146/Data1!BM142-1,NA()) -> 0.21607606 | K15: =IFERROR(IF(OR(ISBLANK(Data1!BN146),ISBLANK(Data1!BN142)),NA(),Data1!BN146/Data1!BN142-1),NA()) -> #N/A | L15: =IFERROR(Data1!B146/Data1!B142-1,NA()) -> 0.10728745 | N15: =N14+1 -> 1987 | O15: {=INDEX(Data1!BM:BM,140+($N15-1980)*4)} -> 22.07 | P15: {=IF($N15<1989,NA(),INDEX(Data1!BN:BN,140+($N15-1980)*4))} -> #N/A | Q15: {=INDEX(Data1!B:B,140+($N15-1980)*4)} -> 33.05 | R15: =IFERROR(O15/O14-1,NA()) -> 0.063614458 | S15: =IFERROR(IF(OR(ISNA(P15),ISNA(P14)),NA(),P15/P14-1),NA()) -> #N/A | T15: =IFERROR(Q15/Q14-1,NA()) -> 0.071312804 | V15: =F15 -> 30103 | W15: =J15 -> 0.21607606 | X15: =K15 -> #N/A | Y15: =L15 -> 0.10728745
A16: Since series start — annualised (CAGR) | B16: =(Data1!BM320/Data1!BM139)^(1/((2025-1980)))-1 -> 0.049974369 | C16: =(Data1!BN320/Data1!BN175)^(1/((2025-1989)))-1 -> 0.050206868 | D16: =(Data1!B320/Data1!B139)^(1/((2025-1980)))-1 -> 0.038308348 | F16: =Data1!A147 -> 30195 | G16: =Data1!B147 -> 22.65 | H16: =Data1!BM147 -> 15.45 | I16: =IF(ISBLANK(Data1!BN147),NA(),Data1!BN147) -> #N/A | J16: =IFERROR(Data1!BM147/Data1!BM143-1,NA()) -> 0.28215768 | K16: =IFERROR(IF(OR(ISBLANK(Data1!BN147),ISBLANK(Data1!BN143)),NA(),Data1!BN147/Data1!BN143-1),NA()) -> #N/A | L16: =IFERROR(Data1!B147/Data1!B143-1,NA()) -> 0.12462761 | N16: =N15+1 -> 1988 | O16: {=INDEX(Data1!BM:BM,140+($N16-1980)*4)} -> 23.23 | P16: {=IF($N16<1989,NA(),INDEX(Data1!BN:BN,140+($N16-1980)*4))} -> #N/A | Q16: {=INDEX(Data1!B:B,140+($N16-1980)*4)} -> 35.57 | R16: =IFERROR(O16/O15-1,NA()) -> 0.052560036 | S16: =IFERROR(IF(OR(ISNA(P16),ISNA(P15)),NA(),P16/P15-1),NA()) -> #N/A | T16: =IFERROR(Q16/Q15-1,NA()) -> 0.076248109 | V16: =F16 -> 30195 | W16: =J16 -> 0.28215768 | X16: =K16 -> #N/A | Y16: =L16 -> 0.12462761
F17: =Data1!A148 -> 30286 | G17: =Data1!B148 -> 23.31 | H17: =Data1!BM148 -> 16.53 | I17: =IF(ISBLANK(Data1!BN148),NA(),Data1!BN148) -> #N/A | J17: =IFERROR(Data1!BM148/Data1!BM144-1,NA()) -> 0.34281072 | K17: =IFERROR(IF(OR(ISBLANK(Data1!BN148),ISBLANK(Data1!BN144)),NA(),Data1!BN148/Data1!BN144-1),NA()) -> #N/A | L17: =IFERROR(Data1!B148/Data1!B144-1,NA()) -> 0.11052882 | N17: =N16+1 -> 1989 | O17: {=INDEX(Data1!BM:BM,140+($N17-1980)*4)} -> 24.12 | P17: {=IF($N17<1989,NA(),INDEX(Data1!BN:BN,140+($N17-1980)*4))} -> 17.24 | Q17: {=INDEX(Data1!B:B,140+($N17-1980)*4)} -> 38.35 | R17: =IFERROR(O17/O16-1,NA()) -> 0.038312527 | S17: =IFERROR(IF(OR(ISNA(P17),ISNA(P16)),NA(),P17/P16-1),NA()) -> #N/A | T17: =IFERROR(Q17/Q16-1,NA()) -> 0.078155749 | V17: =F17 -> 30286 | W17: =J17 -> 0.34281072 | X17: =K17 -> #N/A | Y17: =L17 -> 0.11052882
F18: =Data1!A149 -> 30376 | G18: =Data1!B149 -> 23.81 | H18: =Data1!BM149 -> 16.63 | I18: =IF(ISBLANK(Data1!BN149),NA(),Data1!BN149) -> #N/A | J18: =IFERROR(Data1!BM149/Data1!BM145-1,NA()) -> 0.23919523 | K18: =IFERROR(IF(OR(ISBLANK(Data1!BN149),ISBLANK(Data1!BN145)),NA(),Data1!BN149/Data1!BN145-1),NA()) -> #N/A | L18: =IFERROR(Data1!B149/Data1!B145-1,NA()) -> 0.11365762 | N18: =N17+1 -> 1990 | O18: {=INDEX(Data1!BM:BM,140+($N18-1980)*4)} -> 25.3 | P18: {=IF($N18<1989,NA(),INDEX(Data1!BN:BN,140+($N18-1980)*4))} -> 18.46 | Q18: {=INDEX(Data1!B:B,140+($N18-1980)*4)} -> 40.98 | R18: =IFERROR(O18/O17-1,NA()) -> 0.048922056 | S18: =IFERROR(IF(OR(ISNA(P18),ISNA(P17)),NA(),P18/P17-1),NA()) -> 0.070765661 | T18: =IFERROR(Q18/Q17-1,NA()) -> 0.068578879 | V18: =F18 -> 30376 | W18: =J18 -> 0.23919523 | X18: =K18 -> #N/A | Y18: =L18 -> 0.11365762
A19: Annualised growth by decade (CAGR) | F19: =Data1!A150 -> 30468 | G19: =Data1!B150 -> 24.32 | H19: =Data1!BM150 -> 16.6 | I19: =IF(ISBLANK(Data1!BN150),NA(),Data1!BN150) -> #N/A | J19: =IFERROR(Data1!BM150/Data1!BM146-1,NA()) -> 0.17981521 | K19: =IFERROR(IF(OR(ISBLANK(Data1!BN150),ISBLANK(Data1!BN146)),NA(),Data1!BN150/Data1!BN146-1),NA()) -> #N/A | L19: =IFERROR(Data1!B150/Data1!B146-1,NA()) -> 0.11151737 | N19: =N18+1 -> 1991 | O19: {=INDEX(Data1!BM:BM,140+($N19-1980)*4)} -> 26.53 | P19: {=IF($N19<1989,NA(),INDEX(Data1!BN:BN,140+($N19-1980)*4))} -> 19.15 | Q19: {=INDEX(Data1!B:B,140+($N19-1980)*4)} -> 41.6 | R19: =IFERROR(O19/O18-1,NA()) -> 0.048616601 | S19: =IFERROR(IF(OR(ISNA(P19),ISNA(P18)),NA(),P19/P18-1),NA()) -> 0.037378115 | T19: =IFERROR(Q19/Q18-1,NA()) -> 0.015129331 | V19: =F19 -> 30468 | W19: =J19 -> 0.17981521 | X19: =K19 -> #N/A | Y19: =L19 -> 0.11151737
F20: =Data1!A151 -> 30560 | G20: =Data1!B151 -> 24.74 | H20: =Data1!BM151 -> 17.11 | I20: =IF(ISBLANK(Data1!BN151),NA(),Data1!BN151) -> #N/A | J20: =IFERROR(Data1!BM151/Data1!BM147-1,NA()) -> 0.10744337 | K20: =IFERROR(IF(OR(ISBLANK(Data1!BN151),ISBLANK(Data1!BN147)),NA(),Data1!BN151/Data1!BN147-1),NA()) -> #N/A | L20: =IFERROR(Data1!B151/Data1!B147-1,NA()) -> 0.092273731 | N20: =N19+1 -> 1992 | O20: {=INDEX(Data1!BM:BM,140+($N20-1980)*4)} -> 27.64 | P20: {=IF($N20<1989,NA(),INDEX(Data1!BN:BN,140+($N20-1980)*4))} -> 19.83 | Q20: {=INDEX(Data1!B:B,140+($N20-1980)*4)} -> 41.71 | R20: =IFERROR(O20/O19-1,NA()) -> 0.041839427 | S20: =IFERROR(IF(OR(ISNA(P20),ISNA(P19)),NA(),P20/P19-1),NA()) -> 0.035509138 | T20: =IFERROR(Q20/Q19-1,NA()) -> 0.0026442308 | V20: =F20 -> 30560 | W20: =J20 -> 0.10744337 | X20: =K20 -> #N/A | Y20: =L20 -> 0.092273731
A21: Decade | B21: Electricity | C21: Gas & household fuels | D21: All Groups CPI | F21: =Data1!A152 -> 30651 | G21: =Data1!B152 -> 25.32 | H21: =Data1!BM152 -> 17.88 | I21: =IF(ISBLANK(Data1!BN152),NA(),Data1!BN152) -> #N/A | J21: =IFERROR(Data1!BM152/Data1!BM148-1,NA()) -> 0.081669691 | K21: =IFERROR(IF(OR(ISBLANK(Data1!BN152),ISBLANK(Data1!BN148)),NA(),Data1!BN152/Data1!BN148-1),NA()) -> #N/A | L21: =IFERROR(Data1!B152/Data1!B148-1,NA()) -> 0.086229086 | N21: =N20+1 -> 1993 | O21: {=INDEX(Data1!BM:BM,140+($N21-1980)*4)} -> 28.24 | P21: {=IF($N21<1989,NA(),INDEX(Data1!BN:BN,140+($N21-1980)*4))} -> 20.62 | Q21: {=INDEX(Data1!B:B,140+($N21-1980)*4)} -> 42.53 | R21: =IFERROR(O21/O20-1,NA()) -> 0.02170767 | S21: =IFERROR(IF(OR(ISNA(P21),ISNA(P20)),NA(),P21/P20-1),NA()) -> 0.039838628 | T21: =IFERROR(Q21/Q20-1,NA()) -> 0.019659554 | V21: =F21 -> 30651 | W21: =J21 -> 0.081669691 | X21: =K21 -> #N/A | Y21: =L21 -> 0.086229086
A22: 1980s (1980–1990) | B22: =(VLOOKUP(1990,$N$8:$Q$53,2,FALSE)/VLOOKUP(1980,$N$8:$Q$53,2,FALSE))^(1/10)-1 -> 0.091614297 | C22: n/a | D22: =(VLOOKUP(1990,$N$8:$Q$53,4,FALSE)/VLOOKUP(1980,$N$8:$Q$53,4,FALSE))^(1/10)-1 -> 0.080637428 | F22: =Data1!A153 -> 30742 | G22: =Data1!B153 -> 25.21 | H22: =Data1!BM153 -> 17.66 | I22: =IF(ISBLANK(Data1!BN153),NA(),Data1!BN153) -> #N/A | J22: =IFERROR(Data1!BM153/Data1!BM149-1,NA()) -> 0.06193626 | K22: =IFERROR(IF(OR(ISBLANK(Data1!BN153),ISBLANK(Data1!BN149)),NA(),Data1!BN153/Data1!BN149-1),NA()) -> #N/A | L22: =IFERROR(Data1!B153/Data1!B149-1,NA()) -> 0.058798824 | N22: =N21+1 -> 1994 | O22: {=INDEX(Data1!BM:BM,140+($N22-1980)*4)} -> 28.26 | P22: {=IF($N22<1989,NA(),INDEX(Data1!BN:BN,140+($N22-1980)*4))} -> 21.1 | Q22: {=INDEX(Data1!B:B,140+($N22-1980)*4)} -> 43.61 | R22: =IFERROR(O22/O21-1,NA()) -> 0.0007082153 | S22: =IFERROR(IF(OR(ISNA(P22),ISNA(P21)),NA(),P22/P21-1),NA()) -> 0.023278371 | T22: =IFERROR(Q22/Q21-1,NA()) -> 0.02539384 | V22: =F22 -> 30742 | W22: =J22 -> 0.06193626 | X22: =K22 -> #N/A | Y22: =L22 -> 0.058798824
A23: 1990s (1990–2000) | B23: =(VLOOKUP(2000,$N$8:$Q$53,2,FALSE)/VLOOKUP(1990,$N$8:$Q$53,2,FALSE))^(1/10)-1 -> 0.021835326 | C23: =(VLOOKUP(2000,$N$8:$Q$53,3,FALSE)/VLOOKUP(1990,$N$8:$Q$53,3,FALSE))^(1/10)-1 -> 0.027104331 | D23: =(VLOOKUP(2000,$N$8:$Q$53,4,FALSE)/VLOOKUP(1990,$N$8:$Q$53,4,FALSE))^(1/10)-1 -> 0.021633125 | F23: =Data1!A154 -> 30834 | G23: =Data1!B154 -> 25.28 | H23: =Data1!BM154 -> 17.33 | I23: =IF(ISBLANK(Data1!BN154),NA(),Data1!BN154) -> #N/A | J23: =IFERROR(Data1!BM154/Data1!BM150-1,NA()) -> 0.043975904 | K23: =IFERROR(IF(OR(ISBLANK(Data1!BN154),ISBLANK(Data1!BN150)),NA(),Data1!BN154/Data1!BN150-1),NA()) -> #N/A | L23: =IFERROR(Data1!B154/Data1!B150-1,NA()) -> 0.039473684 | N23: =N22+1 -> 1995 | O23: {=INDEX(Data1!BM:BM,140+($N23-1980)*4)} -> 28.34 | P23: {=IF($N23<1989,NA(),INDEX(Data1!BN:BN,140+($N23-1980)*4))} -> 21.48 | Q23: {=INDEX(Data1!B:B,140+($N23-1980)*4)} -> 45.81 | R23: =IFERROR(O23/O22-1,NA()) -> 0.0028308563 | S23: =IFERROR(IF(OR(ISNA(P23),ISNA(P22)),NA(),P23/P22-1),NA()) -> 0.018009479 | T23: =IFERROR(Q23/Q22-1,NA()) -> 0.050447145 | V23: =F23 -> 30834 | W23: =J23 -> 0.043975904 | X23: =K23 -> #N/A | Y23: =L23 -> 0.039473684
A24: 2000s (2000–2010) | B24: =(VLOOKUP(2010,$N$8:$Q$53,2,FALSE)/VLOOKUP(2000,$N$8:$Q$53,2,FALSE))^(1/10)-1 -> 0.062991676 | C24: =(VLOOKUP(2010,$N$8:$Q$53,3,FALSE)/VLOOKUP(2000,$N$8:$Q$53,3,FALSE))^(1/10)-1 -> 0.05966764 | D24: =(VLOOKUP(2010,$N$8:$Q$53,4,FALSE)/VLOOKUP(2000,$N$8:$Q$53,4,FALSE))^(1/10)-1 -> 0.028545539 | F24: =Data1!A155 -> 30926 | G24: =Data1!B155 -> 25.59 | H24: =Data1!BM155 -> 17.9 | I24: =IF(ISBLANK(Data1!BN155),NA(),Data1!BN155) -> #N/A | J24: =IFERROR(Data1!BM155/Data1!BM151-1,NA()) -> 0.046171829 | K24: =IFERROR(IF(OR(ISBLANK(Data1!BN155),ISBLANK(Data1!BN151)),NA(),Data1!BN155/Data1!BN151-1),NA()) -> #N/A | L24: =IFERROR(Data1!B155/Data1!B151-1,NA()) -> 0.034357316 | N24: =N23+1 -> 1996 | O24: {=INDEX(Data1!BM:BM,140+($N24-1980)*4)} -> 28.7 | P24: {=IF($N24<1989,NA(),INDEX(Data1!BN:BN,140+($N24-1980)*4))} -> 21.95 | Q24: {=INDEX(Data1!B:B,140+($N24-1980)*4)} -> 46.51 | R24: =IFERROR(O24/O23-1,NA()) -> 0.012702893 | S24: =IFERROR(IF(OR(ISNA(P24),ISNA(P23)),NA(),P24/P23-1),NA()) -> 0.021880819 | T24: =IFERROR(Q24/Q23-1,NA()) -> 0.015280506 | V24: =F24 -> 30926 | W24: =J24 -> 0.046171829 | X24: =K24 -> #N/A | Y24: =L24 -> 0.034357316
A25: 2010s (2010–2020) | B25: =(VLOOKUP(2020,$N$8:$Q$53,2,FALSE)/VLOOKUP(2010,$N$8:$Q$53,2,FALSE))^(1/10)-1 -> 0.034696374 | C25: =(VLOOKUP(2020,$N$8:$Q$53,3,FALSE)/VLOOKUP(2010,$N$8:$Q$53,3,FALSE))^(1/10)-1 -> 0.043599419 | D25: =(VLOOKUP(2020,$N$8:$Q$53,4,FALSE)/VLOOKUP(2010,$N$8:$Q$53,4,FALSE))^(1/10)-1 -> 0.019264162 | F25: =Data1!A156 -> 31017 | G25: =Data1!B156 -> 25.98 | H25: =Data1!BM156 -> 18.39 | I25: =IF(ISBLANK(Data1!BN156),NA(),Data1!BN156) -> #N/A | J25: =IFERROR(Data1!BM156/Data1!BM152-1,NA()) -> 0.02852349 | K25: =IFERROR(IF(OR(ISBLANK(Data1!BN156),ISBLANK(Data1!BN152)),NA(),Data1!BN156/Data1!BN152-1),NA()) -> #N/A | L25: =IFERROR(Data1!B156/Data1!B152-1,NA()) -> 0.026066351 | N25: =N24+1 -> 1997 | O25: {=INDEX(Data1!BM:BM,140+($N25-1980)*4)} -> 28.94 | P25: {=IF($N25<1989,NA(),INDEX(Data1!BN:BN,140+($N25-1980)*4))} -> 22.36 | Q25: {=INDEX(Data1!B:B,140+($N25-1980)*4)} -> 46.39 | R25: =IFERROR(O25/O24-1,NA()) -> 0.0083623693 | S25: =IFERROR(IF(OR(ISNA(P25),ISNA(P24)),NA(),P25/P24-1),NA()) -> 0.018678815 | T25: =IFERROR(Q25/Q24-1,NA()) -> -0.0025800903 | V25: =F25 -> 31017 | W25: =J25 -> 0.02852349 | X25: =K25 -> #N/A | Y25: =L25 -> 0.026066351
A26: 2020s so far (2020–2025) | B26: =(VLOOKUP(2025,$N$8:$Q$53,2,FALSE)/VLOOKUP(2020,$N$8:$Q$53,2,FALSE))^(1/5)-1 -> 0.029065704 | C26: =(VLOOKUP(2025,$N$8:$Q$53,3,FALSE)/VLOOKUP(2020,$N$8:$Q$53,3,FALSE))^(1/5)-1 -> 0.08348379 | D26: =(VLOOKUP(2025,$N$8:$Q$53,4,FALSE)/VLOOKUP(2020,$N$8:$Q$53,4,FALSE))^(1/5)-1 -> 0.042683794 | F26: =Data1!A157 -> 31107 | G26: =Data1!B157 -> 26.33 | H26: =Data1!BM157 -> 18.96 | I26: =IF(ISBLANK(Data1!BN157),NA(),Data1!BN157) -> #N/A | J26: =IFERROR(Data1!BM157/Data1!BM153-1,NA()) -> 0.073612684 | K26: =IFERROR(IF(OR(ISBLANK(Data1!BN157),ISBLANK(Data1!BN153)),NA(),Data1!BN157/Data1!BN153-1),NA()) -> #N/A | L26: =IFERROR(Data1!B157/Data1!B153-1,NA()) -> 0.044426815 | N26: =N25+1 -> 1998 | O26: {=INDEX(Data1!BM:BM,140+($N26-1980)*4)} -> 27.95 | P26: {=IF($N26<1989,NA(),INDEX(Data1!BN:BN,140+($N26-1980)*4))} -> 22.36 | Q26: {=INDEX(Data1!B:B,140+($N26-1980)*4)} -> 47.11 | R26: =IFERROR(O26/O25-1,NA()) -> -0.034208708 | S26: =IFERROR(IF(OR(ISNA(P26),ISNA(P25)),NA(),P26/P25-1),NA()) -> 0 | T26: =IFERROR(Q26/Q25-1,NA()) -> 0.015520586 | V26: =F26 -> 31107 | W26: =J26 -> 0.073612684 | X26: =K26 -> #N/A | Y26: =L26 -> 0.044426815
F27: =Data1!A158 -> 31199 | G27: =Data1!B158 -> 26.95 | H27: =Data1!BM158 -> 19.04 | I27: =IF(ISBLANK(Data1!BN158),NA(),Data1!BN158) -> #N/A | J27: =IFERROR(Data1!BM158/Data1!BM154-1,NA()) -> 0.098672822 | K27: =IFERROR(IF(OR(ISBLANK(Data1!BN158),ISBLANK(Data1!BN154)),NA(),Data1!BN158/Data1!BN154-1),NA()) -> #N/A | L27: =IFERROR(Data1!B158/Data1!B154-1,NA()) -> 0.066060127 | N27: =N26+1 -> 1999 | O27: {=INDEX(Data1!BM:BM,140+($N27-1980)*4)} -> 28.26 | P27: {=IF($N27<1989,NA(),INDEX(Data1!BN:BN,140+($N27-1980)*4))} -> 21.9 | Q27: {=INDEX(Data1!B:B,140+($N27-1980)*4)} -> 47.97 | R27: =IFERROR(O27/O26-1,NA()) -> 0.011091234 | S27: =IFERROR(IF(OR(ISNA(P27),ISNA(P26)),NA(),P27/P26-1),NA()) -> -0.020572451 | T27: =IFERROR(Q27/Q26-1,NA()) -> 0.018255148 | V27: =F27 -> 31199 | W27: =J27 -> 0.098672822 | X27: =K27 -> #N/A | Y27: =L27 -> 0.066060127
F28: =Data1!A159 -> 31291 | G28: =Data1!B159 -> 27.56 | H28: =Data1!BM159 -> 19.37 | I28: =IF(ISBLANK(Data1!BN159),NA(),Data1!BN159) -> #N/A | J28: =IFERROR(Data1!BM159/Data1!BM155-1,NA()) -> 0.082122905 | K28: =IFERROR(IF(OR(ISBLANK(Data1!BN159),ISBLANK(Data1!BN155)),NA(),Data1!BN159/Data1!BN155-1),NA()) -> #N/A | L28: =IFERROR(Data1!B159/Data1!B155-1,NA()) -> 0.076983197 | N28: =N27+1 -> 2000 | O28: {=INDEX(Data1!BM:BM,140+($N28-1980)*4)} -> 31.4 | P28: {=IF($N28<1989,NA(),INDEX(Data1!BN:BN,140+($N28-1980)*4))} -> 24.12 | Q28: {=INDEX(Data1!B:B,140+($N28-1980)*4)} -> 50.76 | R28: =IFERROR(O28/O27-1,NA()) -> 0.11111111 | S28: =IFERROR(IF(OR(ISNA(P28),ISNA(P27)),NA(),P28/P27-1),NA()) -> 0.10136986 | T28: =IFERROR(Q28/Q27-1,NA()) -> 0.058161351 | V28: =F28 -> 31291 | W28: =J28 -> 0.082122905 | X28: =K28 -> #N/A | Y28: =L28 -> 0.076983197
F29: =Data1!A160 -> 31382 | G29: =Data1!B160 -> 28.11 | H29: =Data1!BM160 -> 19.54 | I29: =IF(ISBLANK(Data1!BN160),NA(),Data1!BN160) -> #N/A | J29: =IFERROR(Data1!BM160/Data1!BM156-1,NA()) -> 0.062533986 | K29: =IFERROR(IF(OR(ISBLANK(Data1!BN160),ISBLANK(Data1!BN156)),NA(),Data1!BN160/Data1!BN156-1),NA()) -> #N/A | L29: =IFERROR(Data1!B160/Data1!B156-1,NA()) -> 0.081986143 | N29: =N28+1 -> 2001 | O29: {=INDEX(Data1!BM:BM,140+($N29-1980)*4)} -> 32.5 | P29: {=IF($N29<1989,NA(),INDEX(Data1!BN:BN,140+($N29-1980)*4))} -> 24.41 | Q29: {=INDEX(Data1!B:B,140+($N29-1980)*4)} -> 52.35 | R29: =IFERROR(O29/O28-1,NA()) -> 0.035031847 | S29: =IFERROR(IF(OR(ISNA(P29),ISNA(P28)),NA(),P29/P28-1),NA()) -> 0.012023217 | T29: =IFERROR(Q29/Q28-1,NA()) -> 0.031323877 | V29: =F29 -> 31382 | W29: =J29 -> 0.062533986 | X29: =K29 -> #N/A | Y29: =L29 -> 0.081986143
F30: =Data1!A161 -> 31472 | G30: =Data1!B161 -> 28.76 | H30: =Data1!BM161 -> 20 | I30: =IF(ISBLANK(Data1!BN161),NA(),Data1!BN161) -> #N/A | J30: =IFERROR(Data1!BM161/Data1!BM157-1,NA()) -> 0.054852321 | K30: =IFERROR(IF(OR(ISBLANK(Data1!BN161),ISBLANK(Data1!BN157)),NA(),Data1!BN161/Data1!BN157-1),NA()) -> #N/A | L30: =IFERROR(Data1!B161/Data1!B157-1,NA()) -> 0.092290163 | N30: =N29+1 -> 2002 | O30: {=INDEX(Data1!BM:BM,140+($N30-1980)*4)} -> 33.36 | P30: {=IF($N30<1989,NA(),INDEX(Data1!BN:BN,140+($N30-1980)*4))} -> 25.81 | Q30: {=INDEX(Data1!B:B,140+($N30-1980)*4)} -> 53.92 | R30: =IFERROR(O30/O29-1,NA()) -> 0.026461538 | S30: =IFERROR(IF(OR(ISNA(P30),ISNA(P29)),NA(),P30/P29-1),NA()) -> 0.057353544 | T30: =IFERROR(Q30/Q29-1,NA()) -> 0.029990449 | V30: =F30 -> 31472 | W30: =J30 -> 0.054852321 | X30: =K30 -> #N/A | Y30: =L30 -> 0.092290163
F31: =Data1!A162 -> 31564 | G31: =Data1!B162 -> 29.23 | H31: =Data1!BM162 -> 20.12 | I31: =IF(ISBLANK(Data1!BN162),NA(),Data1!BN162) -> #N/A | J31: =IFERROR(Data1!BM162/Data1!BM158-1,NA()) -> 0.056722689 | K31: =IFERROR(IF(OR(ISBLANK(Data1!BN162),ISBLANK(Data1!BN158)),NA(),Data1!BN162/Data1!BN158-1),NA()) -> #N/A | L31: =IFERROR(Data1!B162/Data1!B158-1,NA()) -> 0.084601113 | N31: =N30+1 -> 2003 | O31: {=INDEX(Data1!BM:BM,140+($N31-1980)*4)} -> 35.07 | P31: {=IF($N31<1989,NA(),INDEX(Data1!BN:BN,140+($N31-1980)*4))} -> 27.66 | Q31: {=INDEX(Data1!B:B,140+($N31-1980)*4)} -> 55.22 | R31: =IFERROR(O31/O30-1,NA()) -> 0.051258993 | S31: =IFERROR(IF(OR(ISNA(P31),ISNA(P30)),NA(),P31/P30-1),NA()) -> 0.071677644 | T31: =IFERROR(Q31/Q30-1,NA()) -> 0.024109792 | V31: =F31 -> 31564 | W31: =J31 -> 0.056722689 | X31: =K31 -> #N/A | Y31: =L31 -> 0.084601113
F32: =Data1!A163 -> 31656 | G32: =Data1!B163 -> 30 | H32: =Data1!BM163 -> 20.46 | I32: =IF(ISBLANK(Data1!BN163),NA(),Data1!BN163) -> #N/A | J32: =IFERROR(Data1!BM163/Data1!BM159-1,NA()) -> 0.056272586 | K32: =IFERROR(IF(OR(ISBLANK(Data1!BN163),ISBLANK(Data1!BN159)),NA(),Data1!BN163/Data1!BN159-1),NA()) -> #N/A | L32: =IFERROR(Data1!B163/Data1!B159-1,NA()) -> 0.088534107 | N32: =N31+1 -> 2004 | O32: {=INDEX(Data1!BM:BM,140+($N32-1980)*4)} -> 36.04 | P32: {=IF($N32<1989,NA(),INDEX(Data1!BN:BN,140+($N32-1980)*4))} -> 29.43 | Q32: {=INDEX(Data1!B:B,140+($N32-1980)*4)} -> 56.63 | R32: =IFERROR(O32/O31-1,NA()) -> 0.027658968 | S32: =IFERROR(IF(OR(ISNA(P32),ISNA(P31)),NA(),P32/P31-1),NA()) -> 0.063991323 | T32: =IFERROR(Q32/Q31-1,NA()) -> 0.025534227 | V32: =F32 -> 31656 | W32: =J32 -> 0.056272586 | X32: =K32 -> #N/A | Y32: =L32 -> 0.088534107
F33: =Data1!A164 -> 31747 | G33: =Data1!B164 -> 30.85 | H33: =Data1!BM164 -> 20.75 | I33: =IF(ISBLANK(Data1!BN164),NA(),Data1!BN164) -> #N/A | J33: =IFERROR(Data1!BM164/Data1!BM160-1,NA()) -> 0.061924258 | K33: =IFERROR(IF(OR(ISBLANK(Data1!BN164),ISBLANK(Data1!BN160)),NA(),Data1!BN164/Data1!BN160-1),NA()) -> #N/A | L33: =IFERROR(Data1!B164/Data1!B160-1,NA()) -> 0.097474208 | N33: =N32+1 -> 2005 | O33: {=INDEX(Data1!BM:BM,140+($N33-1980)*4)} -> 37.02 | P33: {=IF($N33<1989,NA(),INDEX(Data1!BN:BN,140+($N33-1980)*4))} -> 30.89 | Q33: {=INDEX(Data1!B:B,140+($N33-1980)*4)} -> 58.22 | R33: =IFERROR(O33/O32-1,NA()) -> 0.027192009 | S33: =IFERROR(IF(OR(ISNA(P33),ISNA(P32)),NA(),P33/P32-1),NA()) -> 0.049609242 | T33: =IFERROR(Q33/Q32-1,NA()) -> 0.028076991 | V33: =F33 -> 31747 | W33: =J33 -> 0.061924258 | X33: =K33 -> #N/A | Y33: =L33 -> 0.097474208
F34: =Data1!A165 -> 31837 | G34: =Data1!B165 -> 31.47 | H34: =Data1!BM165 -> 20.87 | I34: =IF(ISBLANK(Data1!BN165),NA(),Data1!BN165) -> #N/A | J34: =IFERROR(Data1!BM165/Data1!BM161-1,NA()) -> 0.0435 | K34: =IFERROR(IF(OR(ISBLANK(Data1!BN165),ISBLANK(Data1!BN161)),NA(),Data1!BN165/Data1!BN161-1),NA()) -> #N/A | L34: =IFERROR(Data1!B165/Data1!B161-1,NA()) -> 0.094228095 | N34: =N33+1 -> 2006 | O34: {=INDEX(Data1!BM:BM,140+($N34-1980)*4)} -> 38.13 | P34: {=IF($N34<1989,NA(),INDEX(Data1!BN:BN,140+($N34-1980)*4))} -> 32.33 | Q34: {=INDEX(Data1!B:B,140+($N34-1980)*4)} -> 60.11 | R34: =IFERROR(O34/O33-1,NA()) -> 0.029983793 | S34: =IFERROR(IF(OR(ISNA(P34),ISNA(P33)),NA(),P34/P33-1),NA()) -> 0.046617028 | T34: =IFERROR(Q34/Q33-1,NA()) -> 0.032463071 | V34: =F34 -> 31837 | W34: =J34 -> 0.0435 | X34: =K34 -> #N/A | Y34: =L34 -> 0.094228095
F35: =Data1!A166 -> 31929 | G35: =Data1!B166 -> 31.93 | H35: =Data1!BM166 -> 20.92 | I35: =IF(ISBLANK(Data1!BN166),NA(),Data1!BN166) -> #N/A | J35: =IFERROR(Data1!BM166/Data1!BM162-1,NA()) -> 0.039761431 | K35: =IFERROR(IF(OR(ISBLANK(Data1!BN166),ISBLANK(Data1!BN162)),NA(),Data1!BN166/Data1!BN162-1),NA()) -> #N/A | L35: =IFERROR(Data1!B166/Data1!B162-1,NA()) -> 0.092370852 | N35: =N34+1 -> 2007 | O35: {=INDEX(Data1!BM:BM,140+($N35-1980)*4)} -> 40.32 | P35: {=IF($N35<1989,NA(),INDEX(Data1!BN:BN,140+($N35-1980)*4))} -> 33.65 | Q35: {=INDEX(Data1!B:B,140+($N35-1980)*4)} -> 61.89 | R35: =IFERROR(O35/O34-1,NA()) -> 0.05743509 | S35: =IFERROR(IF(OR(ISNA(P35),ISNA(P34)),NA(),P35/P34-1),NA()) -> 0.040828951 | T35: =IFERROR(Q35/Q34-1,NA()) -> 0.029612377 | V35: =F35 -> 31929 | W35: =J35 -> 0.039761431 | X35: =K35 -> #N/A | Y35: =L35 -> 0.092370852
F36: =Data1!A167 -> 32021 | G36: =Data1!B167 -> 32.47 | H36: =Data1!BM167 -> 21.9 | I36: =IF(ISBLANK(Data1!BN167),NA(),Data1!BN167) -> #N/A | J36: =IFERROR(Data1!BM167/Data1!BM163-1,NA()) -> 0.070381232 | K36: =IFERROR(IF(OR(ISBLANK(Data1!BN167),ISBLANK(Data1!BN163)),NA(),Data1!BN167/Data1!BN163-1),NA()) -> #N/A | L36: =IFERROR(Data1!B167/Data1!B163-1,NA()) -> 0.082333333 | N36: =N35+1 -> 2008 | O36: {=INDEX(Data1!BM:BM,140+($N36-1980)*4)} -> 44.42 | P36: {=IF($N36<1989,NA(),INDEX(Data1!BN:BN,140+($N36-1980)*4))} -> 36.88 | Q36: {=INDEX(Data1!B:B,140+($N36-1980)*4)} -> 64.16 | R36: =IFERROR(O36/O35-1,NA()) -> 0.10168651 | S36: =IFERROR(IF(OR(ISNA(P36),ISNA(P35)),NA(),P36/P35-1),NA()) -> 0.095988113 | T36: =IFERROR(Q36/Q35-1,NA()) -> 0.036677977 | V36: =F36 -> 32021 | W36: =J36 -> 0.070381232 | X36: =K36 -> #N/A | Y36: =L36 -> 0.082333333
F37: =Data1!A168 -> 32112 | G37: =Data1!B168 -> 33.05 | H37: =Data1!BM168 -> 22.07 | I37: =IF(ISBLANK(Data1!BN168),NA(),Data1!BN168) -> #N/A | J37: =IFERROR(Data1!BM168/Data1!BM164-1,NA()) -> 0.063614458 | K37: =IFERROR(IF(OR(ISBLANK(Data1!BN168),ISBLANK(Data1!BN164)),NA(),Data1!BN168/Data1!BN164-1),NA()) -> #N/A | L37: =IFERROR(Data1!B168/Data1!B164-1,NA()) -> 0.071312804 | N37: =N36+1 -> 2009 | O37: {=INDEX(Data1!BM:BM,140+($N37-1980)*4)} -> 51.39 | P37: {=IF($N37<1989,NA(),INDEX(Data1!BN:BN,140+($N37-1980)*4))} -> 40.21 | Q37: {=INDEX(Data1!B:B,140+($N37-1980)*4)} -> 65.51 | R37: =IFERROR(O37/O36-1,NA()) -> 0.1569113 | S37: =IFERROR(IF(OR(ISNA(P37),ISNA(P36)),NA(),P37/P36-1),NA()) -> 0.090292842 | T37: =IFERROR(Q37/Q36-1,NA()) -> 0.021041147 | V37: =F37 -> 32112 | W37: =J37 -> 0.063614458 | X37: =K37 -> #N/A | Y37: =L37 -> 0.071312804
F38: =Data1!A169 -> 32203 | G38: =Data1!B169 -> 33.63 | H38: =Data1!BM169 -> 22.14 | I38: =IF(ISBLANK(Data1!BN169),NA(),Data1!BN169) -> #N/A | J38: =IFERROR(Data1!BM169/Data1!BM165-1,NA()) -> 0.060852899 | K38: =IFERROR(IF(OR(ISBLANK(Data1!BN169),ISBLANK(Data1!BN165)),NA(),Data1!BN169/Data1!BN165-1),NA()) -> #N/A | L38: =IFERROR(Data1!B169/Data1!B165-1,NA()) -> 0.068636797 | N38: =N37+1 -> 2010 | O38: {=INDEX(Data1!BM:BM,140+($N38-1980)*4)} -> 57.84 | P38: {=IF($N38<1989,NA(),INDEX(Data1!BN:BN,140+($N38-1980)*4))} -> 43.06 | Q38: {=INDEX(Data1!B:B,140+($N38-1980)*4)} -> 67.26 | R38: =IFERROR(O38/O37-1,NA()) -> 0.1255108 | S38: =IFERROR(IF(OR(ISNA(P38),ISNA(P37)),NA(),P38/P37-1),NA()) -> 0.070877891 | T38: =IFERROR(Q38/Q37-1,NA()) -> 0.026713479 | V38: =F38 -> 32203 | W38: =J38 -> 0.060852899 | X38: =K38 -> #N/A | Y38: =L38 -> 0.068636797
... F53: =Data1!A184 -> 33573 | G53: =Data1!B184 -> 41.6 | H53: =Data1!BM184 -> 26.53 | I53: =IF(ISBLANK(Data1!BN184),NA(),Data1!BN184) -> 19.15 | J53: =IFERROR(Data1!BM184/Data1!BM180-1,NA()) -> 0.048616601 | K53: =IFERROR(IF(OR(ISBLANK(Data1!BN184),ISBLANK(Data1!BN180)),NA(),Data1!BN184/Data1!BN180-1),NA()) -> 0.037378115 | L53: =IFERROR(Data1!B184/Data1!B180-1,NA()) -> 0.015129331 | N53: =N52+1 -> 2025 | O53: {=INDEX(Data1!BM:BM,140+($N53-1980)*4)} -> 93.88 | P53: {=IF($N53<1989,NA(),INDEX(Data1!BN:BN,140+($N53-1980)*4))} -> 98.52 | Q53: {=INDEX(Data1!B:B,140+($N53-1980)*4)} -> 100.32 | R53: =IFERROR(O53/O52-1,NA()) -> 0.25575174 | S53: =IFERROR(IF(OR(ISNA(P53),ISNA(P52)),NA(),P53/P52-1),NA()) -> 0.045859873 | T53: =IFERROR(Q53/Q52-1,NA()) -> 0.036256585 | V53: =F53 -> 33573 | W53: =J53 -> 0.048616601 | X53: =K53 -> 0.037378115 | Y53: =L53 -> 0.015129331
F54: =Data1!A185 -> 33664 | G54: =Data1!B185 -> 41.6 | H54: =Data1!BM185 -> 26.55 | I54: =IF(ISBLANK(Data1!BN185),NA(),Data1!BN185) -> 19.24 | J54: =IFERROR(Data1!BM185/Data1!BM181-1,NA()) -> 0.046511628 | K54: =IFERROR(IF(OR(ISBLANK(Data1!BN185),ISBLANK(Data1!BN181)),NA(),Data1!BN185/Data1!BN181-1),NA()) -> 0.032188841 | L54: =IFERROR(Data1!B185/Data1!B181-1,NA()) -> 0.017114914 | V54: =F54 -> 33664 | W54: =J54 -> 0.046511628 | X54: =K54 -> 0.032188841 | Y54: =L54 -> 0.017114914
F55: =Data1!A186 -> 33756 | G55: =Data1!B186 -> 41.48 | H55: =Data1!BM186 -> 26.58 | I55: =IF(ISBLANK(Data1!BN186),NA(),Data1!BN186) -> 19.19 | J55: =IFERROR(Data1!BM186/Data1!BM182-1,NA()) -> 0.046456693 | K55: =IFERROR(IF(OR(ISBLANK(Data1!BN186),ISBLANK(Data1!BN182)),NA(),Data1!BN186/Data1!BN182-1),NA()) -> 0.035617917 | L55: =IFERROR(Data1!B186/Data1!B182-1,NA()) -> 0.012201074 | V55: =F55 -> 33756 | W55: =J55 -> 0.046456693 | X55: =K55 -> 0.035617917 | Y55: =L55 -> 0.012201074
F56: =Data1!A187 -> 33848 | G56: =Data1!B187 -> 41.52 | H56: =Data1!BM187 -> 27.13 | I56: =IF(ISBLANK(Data1!BN187),NA(),Data1!BN187) -> 19.27 | J56: =IFERROR(Data1!BM187/Data1!BM183-1,NA()) -> 0.027262401 | K56: =IFERROR(IF(OR(ISBLANK(Data1!BN187),ISBLANK(Data1!BN183)),NA(),Data1!BN187/Data1!BN183-1),NA()) -> 0.0062663185 | L56: =IFERROR(Data1!B187/Data1!B183-1,NA()) -> 0.007522446 | V56: =F56 -> 33848 | W56: =J56 -> 0.027262401 | X56: =K56 -> 0.0062663185 | Y56: =L56 -> 0.007522446
F57: =Data1!A188 -> 33939 | G57: =Data1!B188 -> 41.71 | H57: =Data1!BM188 -> 27.64 | I57: =IF(ISBLANK(Data1!BN188),NA(),Data1!BN188) -> 19.83 | J57: =IFERROR(Data1!BM188/Data1!BM184-1,NA()) -> 0.041839427 | K57: =IFERROR(IF(OR(ISBLANK(Data1!BN188),ISBLANK(Data1!BN184)),NA(),Data1!BN188/Data1!BN184-1),NA()) -> 0.035509138 | L57: =IFERROR(Data1!B188/Data1!B184-1,NA()) -> 0.0026442308 | V57: =F57 -> 33939 | W57: =J57 -> 0.041839427 | X57: =K57 -> 0.035509138 | Y57: =L57 -> 0.0026442308
F58: =Data1!A189 -> 34029 | G58: =Data1!B189 -> 42.1 | H58: =Data1!BM189 -> 27.88 | I58: =IF(ISBLANK(Data1!BN189),NA(),Data1!BN189) -> 20.57 | J58: =IFERROR(Data1!BM189/Data1!BM185-1,NA()) -> 0.050094162 | K58: =IFERROR(IF(OR(ISBLANK(Data1!BN189),ISBLANK(Data1!BN185)),NA(),Data1!BN189/Data1!BN185-1),NA()) -> 0.069126819 | L58: =IFERROR(Data1!B189/Data1!B185-1,NA()) -> 0.012019231 | V58: =F58 -> 34029 | W58: =J58 -> 0.050094162 | X58: =K58 -> 0.069126819 | Y58: =L58 -> 0.012019231
F59: =Data1!A190 -> 34121 | G59: =Data1!B190 -> 42.25 | H59: =Data1!BM190 -> 27.9 | I59: =IF(ISBLANK(Data1!BN190),NA(),Data1!BN190) -> 20.55 | J59: =IFERROR(Data1!BM190/Data1!BM186-1,NA()) -> 0.0496614 | K59: =IFERROR(IF(OR(ISBLANK(Data1!BN190),ISBLANK(Data1!BN186)),NA(),Data1!BN190/Data1!BN186-1),NA()) -> 0.070870245 | L59: =IFERROR(Data1!B190/Data1!B186-1,NA()) -> 0.018563163 | V59: =F59 -> 34121 | W59: =J59 -> 0.0496614 | X59: =K59 -> 0.070870245 | Y59: =L59 -> 0.018563163
F60: =Data1!A191 -> 34213 | G60: =Data1!B191 -> 42.45 | H60: =Data1!BM191 -> 28.22 | I60: =IF(ISBLANK(Data1!BN191),NA(),Data1!BN191) -> 20.57 | J60: =IFERROR(Data1!BM191/Data1!BM187-1,NA()) -> 0.040176926 | K60: =IFERROR(IF(OR(ISBLANK(Data1!BN191),ISBLANK(Data1!BN187)),NA(),Data1!BN191/Data1!BN187-1),NA()) -> 0.067462377 | L60: =IFERROR(Data1!B191/Data1!B187-1,NA()) -> 0.022398844 | V60: =F60 -> 34213 | W60: =J60 -> 0.040176926 | X60: =K60 -> 0.067462377 | Y60: =L60 -> 0.022398844
F61: =Data1!A192 -> 34304 | G61: =Data1!B192 -> 42.53 | H61: =Data1!BM192 -> 28.24 | I61: =IF(ISBLANK(Data1!BN192),NA(),Data1!BN192) -> 20.62 | J61: =IFERROR(Data1!BM192/Data1!BM188-1,NA()) -> 0.02170767 | K61: =IFERROR(IF(OR(ISBLANK(Data1!BN192),ISBLANK(Data1!BN188)),NA(),Data1!BN192/Data1!BN188-1),NA()) -> 0.039838628 | L61: =IFERROR(Data1!B192/Data1!B188-1,NA()) -> 0.019659554 | V61: =F61 -> 34304 | W61: =J61 -> 0.02170767 | X61: =K61 -> 0.039838628 | Y61: =L61 -> 0.019659554
F62: =Data1!A193 -> 34394 | G62: =Data1!B193 -> 42.68 | H62: =Data1!BM193 -> 28.26 | I62: =IF(ISBLANK(Data1!BN193),NA(),Data1!BN193) -> 20.62 | J62: =IFERROR(Data1!BM193/Data1!BM189-1,NA()) -> 0.013629842 | K62: =IFERROR(IF(OR(ISBLANK(Data1!BN193),ISBLANK(Data1!BN189)),NA(),Data1!BN193/Data1!BN189-1),NA()) -> 0.0024307244 | L62: =IFERROR(Data1!B193/Data1!B189-1,NA()) -> 0.013776722 | V62: =F62 -> 34394 | W62: =J62 -> 0.013629842 | X62: =K62 -> 0.0024307244 | Y62: =L62 -> 0.013776722
F63: =Data1!A194 -> 34486 | G63: =Data1!B194 -> 42.99 | H63: =Data1!BM194 -> 28.29 | I63: =IF(ISBLANK(Data1!BN194),NA(),Data1!BN194) -> 20.55 | J63: =IFERROR(Data1!BM194/Data1!BM190-1,NA()) -> 0.013978495 | K63: =IFERROR(IF(OR(ISBLANK(Data1!BN194),ISBLANK(Data1!BN190)),NA(),Data1!BN194/Data1!BN190-1),NA()) -> 0 | L63: =IFERROR(Data1!B194/Data1!B190-1,NA()) -> 0.017514793 | V63: =F63 -> 34486 | W63: =J63 -> 0.013978495 | X63: =K63 -> 0 | Y63: =L63 -> 0.017514793
F64: =Data1!A195 -> 34578 | G64: =Data1!B195 -> 43.26 | H64: =Data1!BM195 -> 28.26 | I64: =IF(ISBLANK(Data1!BN195),NA(),Data1!BN195) -> 21.02 | J64: =IFERROR(Data1!BM195/Data1!BM191-1,NA()) -> 0.0014174344 | K64: =IFERROR(IF(OR(ISBLANK(Data1!BN195),ISBLANK(Data1!BN191)),NA(),Data1!BN195/Data1!BN191-1),NA()) -> 0.021876519 | L64: =IFERROR(Data1!B195/Data1!B191-1,NA()) -> 0.019081272 | V64: =F64 -> 34578 | W64: =J64 -> 0.0014174344 | X64: =K64 -> 0.021876519 | Y64: =L64 -> 0.019081272
F65: =Data1!A196 -> 34669 | G65: =Data1!B196 -> 43.61 | H65: =Data1!BM196 -> 28.26 | I65: =IF(ISBLANK(Data1!BN196),NA(),Data1!BN196) -> 21.1 | J65: =IFERROR(Data1!BM196/Data1!BM192-1,NA()) -> 0.0007082153 | K65: =IFERROR(IF(OR(ISBLANK(Data1!BN196),ISBLANK(Data1!BN192)),NA(),Data1!BN196/Data1!BN192-1),NA()) -> 0.023278371 | L65: =IFERROR(Data1!B196/Data1!B192-1,NA()) -> 0.02539384 | V65: =F65 -> 34669 | W65: =J65 -> 0.0007082153 | X65: =K65 -> 0.023278371 | Y65: =L65 -> 0.02539384
... F189: =Data1!A320 -> 45992 | G189: =Data1!B320 -> 100.32 | H189: =Data1!BM320 -> 93.88 | I189: =IF(ISBLANK(Data1!BN320),NA(),Data1!BN320) -> 98.52 | J189: =IFERROR(Data1!BM320/Data1!BM316-1,NA()) -> 0.25575174 | K189: =IFERROR(IF(OR(ISBLANK(Data1!BN320),ISBLANK(Data1!BN316)),NA(),Data1!BN320/Data1!BN316-1),NA()) -> 0.045859873 | L189: =IFERROR(Data1!B320/Data1!B316-1,NA()) -> 0.036256585 | V189: =F189 -> 45992 | W189: =J189 -> 0.25575174 | X189: =K189 -> 0.045859873 | Y189: =L189 -> 0.036256585

Sheet Data1
B1: Index Numbers ; All groups CPI ; Australia ; | C1: Index Numbers ; Food and non-alcoholic beverages ; Australia ; | D1: Index Numbers ; Bread and cereal products ; Australia ; | E1: Index Numbers ; Bread ; Australia ; | F1: Index Numbers ; Cakes and biscuits ; Australia ; | G1: Index Numbers ; Breakfast cereals ; Australia ; | H1: Index Numbers ; Other cereal products ; Australia ; | I1: Index Numbers ; Meat and seafoods ; Australia ; | J1: Index Numbers ; Beef and veal ; Australia ; | K1: Index Numbers ; Pork ; Australia ; | L1: Index Numbers ; Lamb and goat ; Australia ; | M1: Index Numbers ; Poultry ; Australia ; | N1: Index Numbers ; Other meats ; Australia ; | O1: Index Numbers ; Fish and other seafood ; Australia ; | P1: Index Numbers ; Dairy and related products ; Australia ; | Q1: Index Numbers ; Milk ; Australia ; | R1: Index Numbers ; Cheese ; Australia ; | S1: Index Numbers ; Ice cream and other dairy products ; Australia ; | T1: Index Numbers ; Fruit and vegetables ; Australia ; | U1: Index Numbers ; Fruit ; Australia ; | V1: Index Numbers ; Vegetables ; Australia ; | W1: Index Numbers ; Food products n.e.c. ; Australia ; | X1: Index Numbers ; Eggs ; Australia ; | Y1: Index Numbers ; Jams, honey and spreads ; Australia ; | Z1: Index Numbers ; Food additives and condiments ; Australia ; | AA1: Index Numbers ; Oils and fats ; Australia ; | AB1: Index Numbers ; Snacks and confectionery ; Australia ; | AC1: Index Numbers ; Other food products n.e.c. ; Australia ; | AD1: Index Numbers ; Non-alcoholic beverages ; Australia ; | AE1: Index Numbers ; Coffee, tea and cocoa ; Australia ; | AF1: Index Numbers ; Waters, soft drinks and juices ; Australia ; | AG1: Index Numbers ; Meals out and take away foods ; Australia ; | AH1: Index Numbers ; Restaurant meals ; Australia ; | AI1: Index Numbers ; Take away and fast foods ; Australia ; | AJ1: Index Numbers ; Alcohol and tobacco ; Australia ; | AK1: Index Numbers ; Alcoholic beverages ; Australia ; | AL1: Index Numbers ; Spirits ; Australia ; | AM1: Index Numbers ; Wine ; Australia ; | AN1: Index Numbers ; Beer ; Australia ; | AO1: Index Numbers ; Tobacco ; Australia ; | AP1: Index Numbers ; Tobacco ; Australia ; | AQ1: Index Numbers ; Clothing and footwear ; Australia ; | AR1: Index Numbers ; Garments ; Australia ; | AS1: Index Numbers ; Garments for men ; Australia ; | AT1: Index Numbers ; Garments for women ; Australia ; | AU1: Index Numbers ; Garments for infants and children ; Australia ; | AV1: Index Numbers ; Footwear ; Australia ; | AW1: Index Numbers ; Footwear for men ; Australia ; | AX1: Index Numbers ; Footwear for women ; Australia ; | AY1: Index Numbers ; Footwear for infants and children ; Australia ; | AZ1: Index Numbers ; Accessories and clothing services ; Australia ; | BA1: Index Numbers ; Accessories ; Australia ; | BB1: Index Numbers ; Cleaning, repair and hire of clothing and footwear ; Australia ; | BC1: Index Numbers ; Housing ; Australia ; | BD1: Index Numbers ; Rents ; Australia ; | BE1: Index Numbers ; Rents ; Australia ; | BF1: Index Numbers ; New dwelling purchase by owner-occupiers ; Australia ; | BG1: Index Numbers ; New dwelling purchase by owner-occupiers ; Australia ; | BH1: Index Numbers ; Other housing ; Australia ; | BI1: Index Numbers ; Maintenance and repair of the dwelling ; Australia ; | BJ1: Index Numbers ; Property rates and charges ; Australia ; | BK1: Index Numbers ; Utilities ; Australia ; | BL1: Index Numbers ; Water and sewerage ; Australia ; | BM1: Index Numbers ; Electricity ; Australia ; | BN1: Index Numbers ; Gas and other household fuels ; Australia ; | BO1: Index Numbers ; Furnishings, household equipment and services ; Australia ; | BP1: Index Numbers ; Furniture and furnishings ; Australia ; | BQ1: Index Numbers ; Furniture ; Australia ; | BR1: Index Numbers ; Carpets and other floor coverings ; Australia ; | BS1: Index Numbers ; Household textiles ; Australia ; | BT1: Index Numbers ; Household textiles ; Australia ; | BU1: Index Numbers ; Household appliances, utensils and tools ; Australia ; | BV1: Index Numbers ; Major household appliances ; Australia ; | BW1: Index Numbers ; Small electric household appliances ; Australia ; | BX1: Index Numbers ; Glassware, tableware and household utensils ; Australia ; | BY1: Index Numbers ; Tools and equipment for house and garden ; Australia ; | BZ1: Index Numbers ; Non-durable household products ; Australia ; | CA1: Index Numbers ; Cleaning and maintenance products ; Australia ; | CB1: Index Numbers ; Personal care products ; Australia ; | CC1: Index Numbers ; Other non-durable household products ; Australia ; | CD1: Index Numbers ; Domestic and household services ; Australia ; | CE1: Index Numbers ; Child care ; Australia ; | CF1: Index Numbers ; Hairdressing and personal grooming services ; Australia ; | CG1: Index Numbers ; Other household services ; Australia ; | CH1: Index Numbers ; Health ; Australia ; | CI1: Index Numbers ; Medical products, appliances and equipment ; Australia ; | CJ1: Index Numbers ; Pharmaceutical products ; Australia ; | CK1: Index Numbers ; Therapeutic appliances and equipment ; Australia ; | CL1: Index Numbers ; Medical, dental and hospital services ; Australia ; | CM1: Index Numbers ; Medical and hospital services ; Australia ; | CN1: Index Numbers ; Dental services ; Australia ; | CO1: Index Numbers ; Transport ; Australia ; | CP1: Index Numbers ; Private motoring ; Australia ; | CQ1: Index Numbers ; Motor vehicles ; Australia ; | CR1: Index Numbers ; Spare parts and accessories for motor vehicles ; Australia ; | CS1: Index Numbers ; Automotive fuel ; Australia ; | CT1: Index Numbers ; Maintenance and repair of motor vehicles ; Australia ; | CU1: Index Numbers ; Other services in respect of motor vehicles ; Australia ; | CV1: Index Numbers ; Urban transport fares ; Australia ; | CW1: Index Numbers ; Urban transport fares ; Australia ; | CX1: Index Numbers ; Communication ; Australia ; | CY1: Index Numbers ; Communication ; Australia ; | CZ1: Index Numbers ; Postal services ; Australia ; | DA1: Index Numbers ; Telecommunication equipment and services ; Australia ; | DB1: Index Numbers ; Recreation and culture ; Australia ; | DC1: Index Numbers ; Audio, visual and computing equipment and services ; Australia ; | DD1: Index Numbers ; Audio, visual and computing equipment ; Australia ; | DE1: Index Numbers ; Audio, visual and computing media and services ; Australia ; | DF1: Index Numbers ; Newspapers, books and stationery ; Australia ; | DG1: Index Numbers ; Books ; Australia ; | DH1: Index Numbers ; Newspapers, magazines and stationery ; Australia ; | DI1: Index Numbers ; Holiday travel and accommodation ; Australia ; | DJ1: Index Numbers ; Domestic holiday travel and accommodation ; Australia ; | DK1: Index Numbers ; International holiday travel and accommodation ; Australia ; | DL1: Index Numbers ; Other recreation, sport and culture ; Australia ; | DM1: Index Numbers ; Equipment for sports, camping and open-air recreation ; Australia ; | DN1: Index Numbers ; Games, toys and hobbies ; Australia ; | DO1: Index Numbers ; Pets and related products ; Australia ; | DP1: Index Numbers ; Veterinary and other services for pets ; Australia ; | DQ1: Index Numbers ; Sports participation ; Australia ; | DR1: Index Numbers ; Other recreational, sporting and cultural services ; Australia ; | DS1: Index Numbers ; Education ; Australia ; | DT1: Index Numbers ; Education ; Australia ; | DU1: Index Numbers ; Preschool and primary education ; Australia ; | DV1: Index Numbers ; Secondary education ; Australia ; | DW1: Index Numbers ; Tertiary education ; Australia ; | DX1: Index Numbers ; Insurance and financial services ; Australia ; | DY1: Index Numbers ; Insurance ; Australia ; | DZ1: Index Numbers ; Insurance ; Australia ; | EA1: Index Numbers ; Financial services ; Australia ; | EB1: Index Numbers ; Deposit and loan facilities (direct charges) ; Australia ; | EC1: Index Numbers ; Other financial services ; Australia ; | ED1: Percentage Change from Previous Period ; All groups CPI ; Australia ; | EE1: Percentage Change from Previous Period ; Food and non-alcoholic beverages ; Australia ; | EF1: Percentage Change from Previous Period ; Bread and cereal products ; Australia ; | EG1: Percentage Change from Previous Period ; Bread ; Australia ; | EH1: Percentage Change from Previous Period ; Cakes and biscuits ; Australia ; | EI1: Percentage Change from Previous Period ; Breakfast cereals ; Australia ; | EJ1: Percentage Change from Previous Period ; Other cereal products ; Australia ; | EK1: Percentage Change from Previous Period ; Meat and seafoods ; Australia ; | EL1: Percentage Change from Previous Period ; Beef and veal ; Australia ; | EM1: Percentage Change from Previous Period ; Pork ; Australia ; | EN1: Percentage Change from Previous Period ; Lamb and goat ; Australia ; | EO1: Percentage Change from Previous Period ; Poultry ; Australia ; | EP1: Percentage Change from Previous Period ; Other meats ; Australia ; | EQ1: Percentage Change from Previous Period ; Fish and other seafood ; Australia ; | ER1: Percentage Change from Previous Period ; Dairy and related products ; Australia ; | ES1: Percentage Change from Previous Period ; Milk ; Australia ; | ET1: Percentage Change from Previous Period ; Cheese ; Australia ; | EU1: Percentage Change from Previous Period ; Ice cream and other dairy products ; Australia ; | EV1: Percentage Change from Previous Period ; Fruit and vegetables ; Australia ; | EW1: Percentage Change from Previous Period ; Fruit ; Australia ; | EX1: Percentage Change from Previous Period ; Vegetables ; Australia ; | EY1: Percentage Change from Previous Period ; Food products n.e.c. ; Australia ; | EZ1: Percentage Change from Previous Period ; Eggs ; Australia ; | FA1: Percentage Change from Previous Period ; Jams, honey and spreads ; Australia ; | FB1: Percentage Change from Previous Period ; Food additives and condiments ; Australia ; | FC1: Percentage Change from Previous Period ; Oils and fats ; Australia ; | FD1: Percentage Change from Previous Period ; Snacks and confectionery ; Australia ; | FE1: Percentage Change from Previous Period ; Other food products n.e.c. ; Australia ; | FF1: Percentage Change from Previous Period ; Non-alcoholic beverages ; Australia ; | FG1: Percentage Change from Previous Period ; Coffee, tea and cocoa ; Australia ; | FH1: Percentage Change from Previous Period ; Waters, soft drinks and juices ; Australia ; | FI1: Percentage Change from Previous Period ; Meals out and take away foods ; Australia ; | FJ1: Percentage Change from Previous Period ; Restaurant meals ; Australia ; | FK1: Percentage Change from Previous Period ; Take away and fast foods ; Australia ; | FL1: Percentage Change from Previous Period ; Alcohol and tobacco ; Australia ; | FM1: Percentage Change from Previous Period ; Alcoholic beverages ; Australia ; | FN1: Percentage Change from Previous Period ; Spirits ; Australia ; | FO1: Percentage Change from Previous Period ; Wine ; Australia ; | FP1: Percentage Change from Previous Period ; Beer ; Australia ; | FQ1: Percentage Change from Previous Period ; Tobacco ; Australia ; | FR1: Percentage Change from Previous Period ; Tobacco ; Australia ; | FS1: Percentage Change from Previous Period ; Clothing and footwear ; Australia ; | FT1: Percentage Change from Previous Period ; Garments ; Australia ; | FU1: Percentage Change from Previous Period ; Garments for men ; Australia ; | FV1: Percentage Change from Previous Period ; Garments for women ; Australia ; | FW1: Percentage Change from Previous Period ; Garments for infants and children ; Australia ; | FX1: Percentage Change from Previous Period ; Footwear ; Australia ; | FY1: Percentage Change from Previous Period ; Footwear for men ; Australia ; | FZ1: Percentage Change from Previous Period ; Footwear for women ; Australia ; | GA1: Percentage Change from Previous Period ; Footwear for infants and children ; Australia ; | GB1: Percentage Change from Previous Period ; Accessories and clothing services ; Australia ; | GC1: Percentage Change from Previous Period ; Accessories ; Australia ; | GD1: Percentage Change from Previous Period ; Cleaning, repair and hire of clothing and footwear ; Australia ; | GE1: Percentage Change from Previous Period ; Housing ; Australia ; | GF1: Percentage Change from Previous Period ; Rents ; Australia ; | GG1: Percentage Change from Previous Period ; Rents ; Australia ; | GH1: Percentage Change from Previous Period ; New dwelling purchase by owner-occupiers ; Australia ; | GI1: Percentage Change from Previous Period ; New dwelling purchase by owner-occupiers ; Australia ; | GJ1: Percentage Change from Previous Period ; Other housing ; Australia ; | GK1: Percentage Change from Previous Period ; Maintenance and repair of the dwelling ; Australia ; | GL1: Percentage Change from Previous Period ; Property rates and charges ; Australia ; | GM1: Percentage Change from Previous Period ; Utilities ; Australia ; | GN1: Percentage Change from Previous Period ; Water and sewerage ; Australia ; | GO1: Percentage Change from Previous Period ; Electricity ; Australia ; | GP1: Percentage Change from Previous Period ; Gas and other household fuels ; Australia ; | GQ1: Percentage Change from Previous Period ; Furnishings, household equipment and services ; Australia ; | GR1: Percentage Change from Previous Period ; Furniture and furnishings ; Australia ; | GS1: Percentage Change from Previous Period ; Furniture ; Australia ; | GT1: Percentage Change from Previous Period ; Carpets and other floor coverings ; Australia ; | GU1: Percentage Change from Previous Period ; Household textiles ; Australia ; | GV1: Percentage Change from Previous Period ; Household textiles ; Australia ; | GW1: Percentage Change from Previous Period ; Household appliances, utensils and tools ; Australia ; | GX1: Percentage Change from Previous Period ; Major household appliances ; Australia ; | GY1: Percentage Change from Previous Period ; Small electric household appliances ; Australia ; | GZ1: Percentage Change from Previous Period ; Glassware, tableware and household utensils ; Australia ; | HA1: Percentage Change from Previous Period ; Tools and equipment for house and garden ; Australia ; | HB1: Percentage Change from Previous Period ; Non-durable household products ; Australia ; | HC1: Percentage Change from Previous Period ; Cleaning and maintenance products ; Australia ; | HD1: Percentage Change from Previous Period ; Personal care products ; Australia ; | HE1: Percentage Change from Previous Period ; Other non-durable household products ; Australia ; | HF1: Percentage Change from Previous Period ; Domestic and household services ; Australia ; | HG1: Percentage Change from Previous Period ; Child care ; Australia ; | HH1: Percentage Change from Previous Period ; Hairdressing and personal grooming services ; Australia ; | HI1: Percentage Change from Previous Period ; Other household services ; Australia ; | HJ1: Percentage Change from Previous Period ; Health ; Australia ; | HK1: Percentage Change from Previous Period ; Medical products, appliances and equipment ; Australia ; | HL1: Percentage Change from Previous Period ; Pharmaceutical products ; Australia ; | HM1: Percentage Change from Previous Period ; Therapeutic appliances and equipment ; Australia ; | HN1: Percentage Change from Previous Period ; Medical, dental and hospital services ; Australia ; | HO1: Percentage Change from Previous Period ; Medical and hospital services ; Australia ; | HP1: Percentage Change from Previous Period ; Dental services ; Australia ; | HQ1: Percentage Change from Previous Period ; Transport ; Australia ; | HR1: Percentage Change from Previous Period ; Private motoring ; Australia ; | HS1: Percentage Change from Previous Period ; Motor vehicles ; Australia ; | HT1: Percentage Change from Previous Period ; Spare parts and accessories for motor vehicles ; Australia ; | HU1: Percentage Change from Previous Period ; Automotive fuel ; Australia ; | HV1: Percentage Change from Previous Period ; Maintenance and repair of motor vehicles ; Australia ; | HW1: Percentage Change from Previous Period ; Other services in respect of motor vehicles ; Australia ; | HX1: Percentage Change from Previous Period ; Urban transport fares ; Australia ; | HY1: Percentage Change from Previous Period ; Urban transport fares ; Australia ; | HZ1: Percentage Change from Previous Period ; Communication ; Australia ; | IA1: Percentage Change from Previous Period ; Communication ; Australia ; | IB1: Percentage Change from Previous Period ; Postal services ; Australia ; | IC1: Percentage Change from Previous Period ; Telecommunication equipment and services ; Australia ; | ID1: Percentage Change from Previous Period ; Recreation and culture ; Australia ; | IE1: Percentage Change from Previous Period ; Audio, visual and computing equipment and services ; Australia ; | IF1: Percentage Change from Previous Period ; Audio, visual and computing equipment ; Australia ; | IG1: Percentage Change from Previous Period ; Audio, visual and computing media and services ; Australia ; | IH1: Percentage Change from Previous Period ; Newspapers, books and stationery ; Australia ; | II1: Percentage Change from Previous Period ; Books ; Australia ; | IJ1: Percentage Change from Previous Period ; Newspapers, magazines and stationery ; Australia ; | IK1: Percentage Change from Previous Period ; Holiday travel and accommodation ; Australia ; | IL1: Percentage Change from Previous Period ; Domestic holiday travel and accommodation ; Australia ; | IM1: Percentage Change from Previous Period ; International holiday travel and accommodation ; Australia ; | IN1: Percentage Change from Previous Period ; Other recreation, sport and culture ; Australia ; | IO1: Percentage Change from Previous Period ; Equipment for sports, camping and open-air recreation ; Australia ; | IP1: Percentage Change from Previous Period ; Games, toys and hobbies ; Australia ; | IQ1: Percentage Change from Previous Period ; Pets and related products ; Australia ;
A2: Unit | B2: Index Numbers | C2: Index Numbers | D2: Index Numbers | E2: Index Numbers | F2: Index Numbers | G2: Index Numbers | H2: Index Numbers | I2: Index Numbers | J2: Index Numbers | K2: Index Numbers | L2: Index Numbers | M2: Index Numbers | N2: Index Numbers | O2: Index Numbers | P2: Index Numbers | Q2: Index Numbers | R2: Index Numbers | S2: Index Numbers | T2: Index Numbers | U2: Index Numbers | V2: Index Numbers | W2: Index Numbers | X2: Index Numbers | Y2: Index Numbers | Z2: Index Numbers | AA2: Index Numbers | AB2: Index Numbers | AC2: Index Numbers | AD2: Index Numbers | AE2: Index Numbers | AF2: Index Numbers | AG2: Index Numbers | AH2: Index Numbers | AI2: Index Numbers | AJ2: Index Numbers | AK2: Index Numbers | AL2: Index Numbers | AM2: Index Numbers | AN2: Index Numbers | AO2: Index Numbers | AP2: Index Numbers | AQ2: Index Numbers | AR2: Index Numbers | AS2: Index Numbers | AT2: Index Numbers | AU2: Index Numbers | AV2: Index Numbers | AW2: Index Numbers | AX2: Index Numbers | AY2: Index Numbers | AZ2: Index Numbers | BA2: Index Numbers | BB2: Index Numbers | BC2: Index Numbers | BD2: Index Numbers | BE2: Index Numbers | BF2: Index Numbers | BG2: Index Numbers | BH2: Index Numbers | BI2: Index Numbers | BJ2: Index Numbers | BK2: Index Numbers | BL2: Index Numbers | BM2: Index Numbers | BN2: Index Numbers | BO2: Index Numbers | BP2: Index Numbers | BQ2: Index Numbers | BR2: Index Numbers | BS2: Index Numbers | BT2: Index Numbers | BU2: Index Numbers | BV2: Index Numbers | BW2: Index Numbers | BX2: Index Numbers | BY2: Index Numbers | BZ2: Index Numbers | CA2: Index Numbers | CB2: Index Numbers | CC2: Index Numbers | CD2: Index Numbers | CE2: Index Numbers | CF2: Index Numbers | CG2: Index Numbers | CH2: Index Numbers | CI2: Index Numbers | CJ2: Index Numbers | CK2: Index Numbers | CL2: Index Numbers | CM2: Index Numbers | CN2: Index Numbers | CO2: Index Numbers | CP2: Index Numbers | CQ2: Index Numbers | CR2: Index Numbers | CS2: Index Numbers | CT2: Index Numbers | CU2: Index Numbers | CV2: Index Numbers | CW2: Index Numbers | CX2: Index Numbers | CY2: Index Numbers | CZ2: Index Numbers | DA2: Index Numbers | DB2: Index Numbers | DC2: Index Numbers | DD2: Index Numbers | DE2: Index Numbers | DF2: Index Numbers | DG2: Index Numbers | DH2: Index Numbers | DI2: Index Numbers | DJ2: Index Numbers | DK2: Index Numbers | DL2: Index Numbers | DM2: Index Numbers | DN2: Index Numbers | DO2: Index Numbers | DP2: Index Numbers | DQ2: Index Numbers | DR2: Index Numbers | DS2: Index Numbers | DT2: Index Numbers | DU2: Index Numbers | DV2: Index Numbers | DW2: Index Numbers | DX2: Index Numbers | DY2: Index Numbers | DZ2: Index Numbers | EA2: Index Numbers | EB2: Index Numbers | EC2: Index Numbers | ED2: Percent | EE2: Percent | EF2: Percent | EG2: Percent | EH2: Percent | EI2: Percent | EJ2: Percent | EK2: Percent | EL2: Percent | EM2: Percent | EN2: Percent | EO2: Percent | EP2: Percent | EQ2: Percent | ER2: Percent | ES2: Percent | ET2: Percent | EU2: Percent | EV2: Percent | EW2: Percent | EX2: Percent | EY2: Percent | EZ2: Percent | FA2: Percent | FB2: Percent | FC2: Percent | FD2: Percent | FE2: Percent | FF2: Percent | FG2: Percent | FH2: Percent | FI2: Percent | FJ2: Percent | FK2: Percent | FL2: Percent | FM2: Percent | FN2: Percent | FO2: Percent | FP2: Percent | FQ2: Percent | FR2: Percent | FS2: Percent | FT2: Percent | FU2: Percent | FV2: Percent | FW2: Percent | FX2: Percent | FY2: Percent | FZ2: Percent | GA2: Percent | GB2: Percent | GC2: Percent | GD2: Percent | GE2: Percent | GF2: Percent | GG2: Percent | GH2: Percent | GI2: Percent | GJ2: Percent | GK2: Percent | GL2: Percent | GM2: Percent | GN2: Percent | GO2: Percent | GP2: Percent | GQ2: Percent | GR2: Percent | GS2: Percent | GT2: Percent | GU2: Percent | GV2: Percent | GW2: Percent | GX2: Percent | GY2: Percent | GZ2: Percent | HA2: Percent | HB2: Percent | HC2: Percent | HD2: Percent | HE2: Percent | HF2: Percent | HG2: Percent | HH2: Percent | HI2: Percent | HJ2: Percent | HK2: Percent | HL2: Percent | HM2: Percent | HN2: Percent | HO2: Percent | HP2: Percent | HQ2: Percent | HR2: Percent | HS2: Percent | HT2: Percent | HU2: Percent | HV2: Percent | HW2: Percent | HX2: Percent | HY2: Percent | HZ2: Percent | IA2: Percent | IB2: Percent | IC2: Percent | ID2: Percent | IE2: Percent | IF2: Percent | IG2: Percent | IH2: Percent | II2: Percent | IJ2: Percent | IK2: Percent | IL2: Percent | IM2: Percent | IN2: Percent | IO2: Percent | IP2: Percent | IQ2: Percent
A3: Series Type | B3: Original | C3: Original | D3: Original | E3: Original | F3: Original | G3: Original | H3: Original | I3: Original | J3: Original | K3: Original | L3: Original | M3: Original | N3: Original | O3: Original | P3: Original | Q3: Original | R3: Original | S3: Original | T3: Original | U3: Original | V3: Original | W3: Original | X3: Original | Y3: Original | Z3: Original | AA3: Original | AB3: Original | AC3: Original | AD3: Original | AE3: Original | AF3: Original | AG3: Original | AH3: Original | AI3: Original | AJ3: Original | AK3: Original | AL3: Original | AM3: Original | AN3: Original | AO3: Original | AP3: Original | AQ3: Original | AR3: Original | AS3: Original | AT3: Original | AU3: Original | AV3: Original | AW3: Original | AX3: Original | AY3: Original | AZ3: Original | BA3: Original | BB3: Original | BC3: Original | BD3: Original | BE3: Original | BF3: Original | BG3: Original | BH3: Original | BI3: Original | BJ3: Original | BK3: Original | BL3: Original | BM3: Original | BN3: Original | BO3: Original | BP3: Original | BQ3: Original | BR3: Original | BS3: Original | BT3: Original | BU3: Original | BV3: Original | BW3: Original | BX3: Original | BY3: Original | BZ3: Original | CA3: Original | CB3: Original | CC3: Original | CD3: Original | CE3: Original | CF3: Original | CG3: Original | CH3: Original | CI3: Original | CJ3: Original | CK3: Original | CL3: Original | CM3: Original | CN3: Original | CO3: Original | CP3: Original | CQ3: Original | CR3: Original | CS3: Original | CT3: Original | CU3: Original | CV3: Original | CW3: Original | CX3: Original | CY3: Original | CZ3: Original | DA3: Original | DB3: Original | DC3: Original | DD3: Original | DE3: Original | DF3: Original | DG3: Original | DH3: Original | DI3: Original | DJ3: Original | DK3: Original | DL3: Original | DM3: Original | DN3: Original | DO3: Original | DP3: Original | DQ3: Original | DR3: Original | DS3: Original | DT3: Original | DU3: Original | DV3: Original | DW3: Original | DX3: Original | DY3: Original | DZ3: Original | EA3: Original | EB3: Original | EC3: Original | ED3: Original | EE3: Original | EF3: Original | EG3: Original | EH3: Original | EI3: Original | EJ3: Original | EK3: Original | EL3: Original | EM3: Original | EN3: Original | EO3: Original | EP3: Original | EQ3: Original | ER3: Original | ES3: Original | ET3: Original | EU3: Original | EV3: Original | EW3: Original | EX3: Original | EY3: Original | EZ3: Original | FA3: Original | FB3: Original | FC3: Original | FD3: Original | FE3: Original | FF3: Original | FG3: Original | FH3: Original | FI3: Original | FJ3: Original | FK3: Original | FL3: Original | FM3: Original | FN3: Original | FO3: Original | FP3: Original | FQ3: Original | FR3: Original | FS3: Original | FT3: Original | FU3: Original | FV3: Original | FW3: Original | FX3: Original | FY3: Original | FZ3: Original | GA3: Original | GB3: Original | GC3: Original | GD3: Original | GE3: Original | GF3: Original | GG3: Original | GH3: Original | GI3: Original | GJ3: Original | GK3: Original | GL3: Original | GM3: Original | GN3: Original | GO3: Original | GP3: Original | GQ3: Original | GR3: Original | GS3: Original | GT3: Original | GU3: Original | GV3: Original | GW3: Original | GX3: Original | GY3: Original | GZ3: Original | HA3: Original | HB3: Original | HC3: Original | HD3: Original | HE3: Original | HF3: Original | HG3: Original | HH3: Original | HI3: Original | HJ3: Original | HK3: Original | HL3: Original | HM3: Original | HN3: Original | HO3: Original | HP3: Original | HQ3: Original | HR3: Original | HS3: Original | HT3: Original | HU3: Original | HV3: Original | HW3: Original | HX3: Original | HY3: Original | HZ3: Original | IA3: Original | IB3: Original | IC3: Original | ID3: Original | IE3: Original | IF3: Original | IG3: Original | IH3: Original | II3: Original | IJ3: Original | IK3: Original | IL3: Original | IM3: Original | IN3: Original | IO3: Original | IP3: Original | IQ3: Original
A4: Data Type | B4: INDEX | C4: INDEX | D4: INDEX | E4: INDEX | F4: INDEX | G4: INDEX | H4: INDEX | I4: INDEX | J4: INDEX | K4: INDEX | L4: INDEX | M4: INDEX | N4: INDEX | O4: INDEX | P4: INDEX | Q4: INDEX | R4: INDEX | S4: INDEX | T4: INDEX | U4: INDEX | V4: INDEX | W4: INDEX | X4: INDEX | Y4: INDEX | Z4: INDEX | AA4: INDEX | AB4: INDEX | AC4: INDEX | AD4: INDEX | AE4: INDEX | AF4: INDEX | AG4: INDEX | AH4: INDEX | AI4: INDEX | AJ4: INDEX | AK4: INDEX | AL4: INDEX | AM4: INDEX | AN4: INDEX | AO4: INDEX | AP4: INDEX | AQ4: INDEX | AR4: INDEX | AS4: INDEX | AT4: INDEX | AU4: INDEX | AV4: INDEX | AW4: INDEX | AX4: INDEX | AY4: INDEX | AZ4: INDEX | BA4: INDEX | BB4: INDEX | BC4: INDEX | BD4: INDEX | BE4: INDEX | BF4: INDEX | BG4: INDEX | BH4: INDEX | BI4: INDEX | BJ4: INDEX | BK4: INDEX | BL4: INDEX | BM4: INDEX | BN4: INDEX | BO4: INDEX | BP4: INDEX | BQ4: INDEX | BR4: INDEX | BS4: INDEX | BT4: INDEX | BU4: INDEX | BV4: INDEX | BW4: INDEX | BX4: INDEX | BY4: INDEX | BZ4: INDEX | CA4: INDEX | CB4: INDEX | CC4: INDEX | CD4: INDEX | CE4: INDEX | CF4: INDEX | CG4: INDEX | CH4: INDEX | CI4: INDEX | CJ4: INDEX | CK4: INDEX | CL4: INDEX | CM4: INDEX | CN4: INDEX | CO4: INDEX | CP4: INDEX | CQ4: INDEX | CR4: INDEX | CS4: INDEX | CT4: INDEX | CU4: INDEX | CV4: INDEX | CW4: INDEX | CX4: INDEX | CY4: INDEX | CZ4: INDEX | DA4: INDEX | DB4: INDEX | DC4: INDEX | DD4: INDEX | DE4: INDEX | DF4: INDEX | DG4: INDEX | DH4: INDEX | DI4: INDEX | DJ4: INDEX | DK4: INDEX | DL4: INDEX | DM4: INDEX | DN4: INDEX | DO4: INDEX | DP4: INDEX | DQ4: INDEX | DR4: INDEX | DS4: INDEX | DT4: INDEX | DU4: INDEX | DV4: INDEX | DW4: INDEX | DX4: INDEX | DY4: INDEX | DZ4: INDEX | EA4: INDEX | EB4: INDEX | EC4: INDEX | ED4: PERCENT | EE4: PERCENT | EF4: PERCENT | EG4: PERCENT | EH4: PERCENT | EI4: PERCENT | EJ4: PERCENT | EK4: PERCENT | EL4: PERCENT | EM4: PERCENT | EN4: PERCENT | EO4: PERCENT | EP4: PERCENT | EQ4: PERCENT | ER4: PERCENT | ES4: PERCENT | ET4: PERCENT | EU4: PERCENT | EV4: PERCENT | EW4: PERCENT | EX4: PERCENT | EY4: PERCENT | EZ4: PERCENT | FA4: PERCENT | FB4: PERCENT | FC4: PERCENT | FD4: PERCENT | FE4: PERCENT | FF4: PERCENT | FG4: PERCENT | FH4: PERCENT | FI4: PERCENT | FJ4: PERCENT | FK4: PERCENT | FL4: PERCENT | FM4: PERCENT | FN4: PERCENT | FO4: PERCENT | FP4: PERCENT | FQ4: PERCENT | FR4: PERCENT | FS4: PERCENT | FT4: PERCENT | FU4: PERCENT | FV4: PERCENT | FW4: PERCENT | FX4: PERCENT | FY4: PERCENT | FZ4: PERCENT | GA4: PERCENT | GB4: PERCENT | GC4: PERCENT | GD4: PERCENT | GE4: PERCENT | GF4: PERCENT | GG4: PERCENT | GH4: PERCENT | GI4: PERCENT | GJ4: PERCENT | GK4: PERCENT | GL4: PERCENT | GM4: PERCENT | GN4: PERCENT | GO4: PERCENT | GP4: PERCENT | GQ4: PERCENT | GR4: PERCENT | GS4: PERCENT | GT4: PERCENT | GU4: PERCENT | GV4: PERCENT | GW4: PERCENT | GX4: PERCENT | GY4: PERCENT | GZ4: PERCENT | HA4: PERCENT | HB4: PERCENT | HC4: PERCENT | HD4: PERCENT | HE4: PERCENT | HF4: PERCENT | HG4: PERCENT | HH4: PERCENT | HI4: PERCENT | HJ4: PERCENT | HK4: PERCENT | HL4: PERCENT | HM4: PERCENT | HN4: PERCENT | HO4: PERCENT | HP4: PERCENT | HQ4: PERCENT | HR4: PERCENT | HS4: PERCENT | HT4: PERCENT | HU4: PERCENT | HV4: PERCENT | HW4: PERCENT | HX4: PERCENT | HY4: PERCENT | HZ4: PERCENT | IA4: PERCENT | IB4: PERCENT | IC4: PERCENT | ID4: PERCENT | IE4: PERCENT | IF4: PERCENT | IG4: PERCENT | IH4: PERCENT | II4: PERCENT | IJ4: PERCENT | IK4: PERCENT | IL4: PERCENT | IM4: PERCENT | IN4: PERCENT | IO4: PERCENT | IP4: PERCENT | IQ4: PERCENT
A5: Frequency | B5: Quarter | C5: Quarter | D5: Quarter | E5: Quarter | F5: Quarter | G5: Quarter | H5: Quarter | I5: Quarter | J5: Quarter | K5: Quarter | L5: Quarter | M5: Quarter | N5: Quarter | O5: Quarter | P5: Quarter | Q5: Quarter | R5: Quarter | S5: Quarter | T5: Quarter | U5: Quarter | V5: Quarter | W5: Quarter | X5: Quarter | Y5: Quarter | Z5: Quarter | AA5: Quarter | AB5: Quarter | AC5: Quarter | AD5: Quarter | AE5: Quarter | AF5: Quarter | AG5: Quarter | AH5: Quarter | AI5: Quarter | AJ5: Quarter | AK5: Quarter | AL5: Quarter | AM5: Quarter | AN5: Quarter | AO5: Quarter | AP5: Quarter | AQ5: Quarter | AR5: Quarter | AS5: Quarter | AT5: Quarter | AU5: Quarter | AV5: Quarter | AW5: Quarter | AX5: Quarter | AY5: Quarter | AZ5: Quarter | BA5: Quarter | BB5: Quarter | BC5: Quarter | BD5: Quarter | BE5: Quarter | BF5: Quarter | BG5: Quarter | BH5: Quarter | BI5: Quarter | BJ5: Quarter | BK5: Quarter | BL5: Quarter | BM5: Quarter | BN5: Quarter | BO5: Quarter | BP5: Quarter | BQ5: Quarter | BR5: Quarter | BS5: Quarter | BT5: Quarter | BU5: Quarter | BV5: Quarter | BW5: Quarter | BX5: Quarter | BY5: Quarter | BZ5: Quarter | CA5: Quarter | CB5: Quarter | CC5: Quarter | CD5: Quarter | CE5: Quarter | CF5: Quarter | CG5: Quarter | CH5: Quarter | CI5: Quarter | CJ5: Quarter | CK5: Quarter | CL5: Quarter | CM5: Quarter | CN5: Quarter | CO5: Quarter | CP5: Quarter | CQ5: Quarter | CR5: Quarter | CS5: Quarter | CT5: Quarter | CU5: Quarter | CV5: Quarter | CW5: Quarter | CX5: Quarter | CY5: Quarter | CZ5: Quarter | DA5: Quarter | DB5: Quarter | DC5: Quarter | DD5: Quarter | DE5: Quarter | DF5: Quarter | DG5: Quarter | DH5: Quarter | DI5: Quarter | DJ5: Quarter | DK5: Quarter | DL5: Quarter | DM5: Quarter | DN5: Quarter | DO5: Quarter | DP5: Quarter | DQ5: Quarter | DR5: Quarter | DS5: Quarter | DT5: Quarter | DU5: Quarter | DV5: Quarter | DW5: Quarter | DX5: Quarter | DY5: Quarter | DZ5: Quarter | EA5: Quarter | EB5: Quarter | EC5: Quarter | ED5: Quarter | EE5: Quarter | EF5: Quarter | EG5: Quarter | EH5: Quarter | EI5: Quarter | EJ5: Quarter | EK5: Quarter | EL5: Quarter | EM5: Quarter | EN5: Quarter | EO5: Quarter | EP5: Quarter | EQ5: Quarter | ER5: Quarter | ES5: Quarter | ET5: Quarter | EU5: Quarter | EV5: Quarter | EW5: Quarter | EX5: Quarter | EY5: Quarter | EZ5: Quarter | FA5: Quarter | FB5: Quarter | FC5: Quarter | FD5: Quarter | FE5: Quarter | FF5: Quarter | FG5: Quarter | FH5: Quarter | FI5: Quarter | FJ5: Quarter | FK5: Quarter | FL5: Quarter | FM5: Quarter | FN5: Quarter | FO5: Quarter | FP5: Quarter | FQ5: Quarter | FR5: Quarter | FS5: Quarter | FT5: Quarter | FU5: Quarter | FV5: Quarter | FW5: Quarter | FX5: Quarter | FY5: Quarter | FZ5: Quarter | GA5: Quarter | GB5: Quarter | GC5: Quarter | GD5: Quarter | GE5: Quarter | GF5: Quarter | GG5: Quarter | GH5: Quarter | GI5: Quarter | GJ5: Quarter | GK5: Quarter | GL5: Quarter | GM5: Quarter | GN5: Quarter | GO5: Quarter | GP5: Quarter | GQ5: Quarter | GR5: Quarter | GS5: Quarter | GT5: Quarter | GU5: Quarter | GV5: Quarter | GW5: Quarter | GX5: Quarter | GY5: Quarter | GZ5: Quarter | HA5: Quarter | HB5: Quarter | HC5: Quarter | HD5: Quarter | HE5: Quarter | HF5: Quarter | HG5: Quarter | HH5: Quarter | HI5: Quarter | HJ5: Quarter | HK5: Quarter | HL5: Quarter | HM5: Quarter | HN5: Quarter | HO5: Quarter | HP5: Quarter | HQ5: Quarter | HR5: Quarter | HS5: Quarter | HT5: Quarter | HU5: Quarter | HV5: Quarter | HW5: Quarter | HX5: Quarter | HY5: Quarter | HZ5: Quarter | IA5: Quarter | IB5: Quarter | IC5: Quarter | ID5: Quarter | IE5: Quarter | IF5: Quarter | IG5: Quarter | IH5: Quarter | II5: Quarter | IJ5: Quarter | IK5: Quarter | IL5: Quarter | IM5: Quarter | IN5: Quarter | IO5: Quarter | IP5: Quarter | IQ5: Quarter
A6: Collection Month | B6: 3 | C6: 3 | D6: 3 | E6: 3 | F6: 3 | G6: 3 | H6: 3 | I6: 3 | J6: 3 | K6: 3 | L6: 3 | M6: 3 | N6: 3 | O6: 3 | P6: 3 | Q6: 3 | R6: 3 | S6: 3 | T6: 3 | U6: 3 | V6: 3 | W6: 3 | X6: 3 | Y6: 3 | Z6: 3 | AA6: 3 | AB6: 3 | AC6: 3 | AD6: 3 | AE6: 3 | AF6: 3 | AG6: 3 | AH6: 3 | AI6: 3 | AJ6: 3 | AK6: 3 | AL6: 3 | AM6: 3 | AN6: 3 | AO6: 3 | AP6: 3 | AQ6: 3 | AR6: 3 | AS6: 3 | AT6: 3 | AU6: 3 | AV6: 3 | AW6: 3 | AX6: 3 | AY6: 3 | AZ6: 3 | BA6: 3 | BB6: 3 | BC6: 3 | BD6: 3 | BE6: 3 | BF6: 3 | BG6: 3 | BH6: 3 | BI6: 3 | BJ6: 3 | BK6: 3 | BL6: 3 | BM6: 3 | BN6: 3 | BO6: 3 | BP6: 3 | BQ6: 3 | BR6: 3 | BS6: 3 | BT6: 3 | BU6: 3 | BV6: 3 | BW6: 3 | BX6: 3 | BY6: 3 | BZ6: 3 | CA6: 3 | CB6: 3 | CC6: 3 | CD6: 3 | CE6: 3 | CF6: 3 | CG6: 3 | CH6: 3 | CI6: 3 | CJ6: 3 | CK6: 3 | CL6: 3 | CM6: 3 | CN6: 3 | CO6: 3 | CP6: 3 | CQ6: 3 | CR6: 3 | CS6: 3 | CT6: 3 | CU6: 3 | CV6: 3 | CW6: 3 | CX6: 3 | CY6: 3 | CZ6: 3 | DA6: 3 | DB6: 3 | DC6: 3 | DD6: 3 | DE6: 3 | DF6: 3 | DG6: 3 | DH6: 3 | DI6: 3 | DJ6: 3 | DK6: 3 | DL6: 3 | DM6: 3 | DN6: 3 | DO6: 3 | DP6: 3 | DQ6: 3 | DR6: 3 | DS6: 3 | DT6: 3 | DU6: 3 | DV6: 3 | DW6: 3 | DX6: 3 | DY6: 3 | DZ6: 3 | EA6: 3 | EB6: 3 | EC6: 3 | ED6: 3 | EE6: 3 | EF6: 3 | EG6: 3 | EH6: 3 | EI6: 3 | EJ6: 3 | EK6: 3 | EL6: 3 | EM6: 3 | EN6: 3 | EO6: 3 | EP6: 3 | EQ6: 3 | ER6: 3 | ES6: 3 | ET6: 3 | EU6: 3 | EV6: 3 | EW6: 3 | EX6: 3 | EY6: 3 | EZ6: 3 | FA6: 3 | FB6: 3 | FC6: 3 | FD6: 3 | FE6: 3 | FF6: 3 | FG6: 3 | FH6: 3 | FI6: 3 | FJ6: 3 | FK6: 3 | FL6: 3 | FM6: 3 | FN6: 3 | FO6: 3 | FP6: 3 | FQ6: 3 | FR6: 3 | FS6: 3 | FT6: 3 | FU6: 3 | FV6: 3 | FW6: 3 | FX6: 3 | FY6: 3 | FZ6: 3 | GA6: 3 | GB6: 3 | GC6: 3 | GD6: 3 | GE6: 3 | GF6: 3 | GG6: 3 | GH6: 3 | GI6: 3 | GJ6: 3 | GK6: 3 | GL6: 3 | GM6: 3 | GN6: 3 | GO6: 3 | GP6: 3 | GQ6: 3 | GR6: 3 | GS6: 3 | GT6: 3 | GU6: 3 | GV6: 3 | GW6: 3 | GX6: 3 | GY6: 3 | GZ6: 3 | HA6: 3 | HB6: 3 | HC6: 3 | HD6: 3 | HE6: 3 | HF6: 3 | HG6: 3 | HH6: 3 | HI6: 3 | HJ6: 3 | HK6: 3 | HL6: 3 | HM6: 3 | HN6: 3 | HO6: 3 | HP6: 3 | HQ6: 3 | HR6: 3 | HS6: 3 | HT6: 3 | HU6: 3 | HV6: 3 | HW6: 3 | HX6: 3 | HY6: 3 | HZ6: 3 | IA6: 3 | IB6: 3 | IC6: 3 | ID6: 3 | IE6: 3 | IF6: 3 | IG6: 3 | IH6: 3 | II6: 3 | IJ6: 3 | IK6: 3 | IL6: 3 | IM6: 3 | IN6: 3 | IO6: 3 | IP6: 3 | IQ6: 3
A7: Series Start | B7: 17777 | C7: 26543 | D7: 26543 | E7: 29465 | F7: 29465 | G7: 29465 | H7: 29465 | I7: 26543 | J7: 26543 | K7: 29465 | L7: 26543 | M7: 26543 | N7: 29465 | O7: 28004 | P7: 26543 | Q7: 29465 | R7: 29465 | S7: 29465 | T7: 32752 | U7: 32752 | V7: 32752 | W7: 32752 | X7: 29465 | Y7: 29465 | Z7: 32752 | AA7: 32752 | AB7: 32752 | AC7: 29465 | AD7: 32752 | AE7: 29465 | AF7: 32752 | AG7: 28004 | AH7: 29465 | AI7: 29465 | AJ7: 26543 | AK7: 26543 | AL7: 29465 | AM7: 29465 | AN7: 26543 | AO7: 26543 | AP7: 26543 | AQ7: 26543 | AR7: 32752 | AS7: 32752 | AT7: 32752 | AU7: 32752 | AV7: 26543 | AW7: 29465 | AX7: 29465 | AY7: 29465 | AZ7: 35947 | BA7: 35947 | BB7: 26543 | BC7: 26543 | BD7: 26543 | BE7: 26543 | BF7: 35947 | BG7: 35947 | BH7: 35947 | BI7: 29465 | BJ7: 35947 | BK7: 26543 | BL7: 35947 | BM7: 29465 | BN7: 32752 | BO7: 26543 | BP7: 26543 | BQ7: 29465 | BR7: 29465 | BS7: 26543 | BT7: 26543 | BU7: 32752 | BV7: 26543 | BW7: 26543 | BX7: 32752 | BY7: 29465 | BZ7: 32752 | CA7: 29465 | CB7: 29465 | CC7: 32752 | CD7: 32752 | CE7: 30011 | CF7: 26543 | CG7: 32752 | CH7: 32752 | CI7: 31747 | CJ7: 29465 | CK7: 31747 | CL7: 29465 | CM7: 29465 | CN7: 29465 | CO7: 26543 | CP7: 26543 | CQ7: 26543 | CR7: 29465 | CS7: 26543 | CT7: 29465 | CU7: 29465 | CV7: 26543 | CW7: 26543 | CX7: 26543 | CY7: 26543 | CZ7: 29465 | DA7: 29465 | DB7: 32752 | DC7: 32752 | DD7: 29465 | DE7: 32752 | DF7: 32752 | DG7: 35947 | DH7: 35947 | DI7: 30011 | DJ7: 30011 | DK7: 30011 | DL7: 32752 | DM7: 35947 | DN7: 35947 | DO7: 29465 | DP7: 31747 | DQ7: 35947 | DR7: 35947 | DS7: 30011 | DT7: 30011 | DU7: 36678 | DV7: 36678 | DW7: 36678 | DX7: 38504 | DY7: 32752 | DZ7: 32752 | EA7: 40695 | EB7: 40695 | EC7: 38504 | ED7: 17868 | EE7: 26634 | EF7: 26634 | EG7: 29556 | EH7: 29556 | EI7: 29556 | EJ7: 29556 | EK7: 26634 | EL7: 26634 | EM7: 29556 | EN7: 26634 | EO7: 26634 | EP7: 29556 | EQ7: 28095 | ER7: 26634 | ES7: 29556 | ET7: 29556 | EU7: 29556 | EV7: 32843 | EW7: 32843 | EX7: 32843 | EY7: 32843 | EZ7: 29556 | FA7: 29556 | FB7: 32843 | FC7: 32843 | FD7: 32843 | FE7: 29556 | FF7: 32843 | FG7: 29556 | FH7: 32843 | FI7: 28095 | FJ7: 29556 | FK7: 29556 | FL7: 26634 | FM7: 26634 | FN7: 29556 | FO7: 29556 | FP7: 26634 | FQ7: 26634 | FR7: 26634 | FS7: 26634 | FT7: 32843 | FU7: 32843 | FV7: 32843 | FW7: 32843 | FX7: 26634 | FY7: 29556 | FZ7: 29556 | GA7: 29556 | GB7: 36039 | GC7: 36039 | GD7: 26634 | GE7: 26634 | GF7: 26634 | GG7: 26634 | GH7: 36039 | GI7: 36039 | GJ7: 36039 | GK7: 29556 | GL7: 36039 | GM7: 26634 | GN7: 36039 | GO7: 29556 | GP7: 32843 | GQ7: 26634 | GR7: 26634 | GS7: 29556 | GT7: 29556 | GU7: 26634 | GV7: 26634 | GW7: 32843 | GX7: 26634 | GY7: 26634 | GZ7: 32843 | HA7: 29556 | HB7: 32843 | HC7: 29556 | HD7: 29556 | HE7: 32843 | HF7: 32843 | HG7: 30103 | HH7: 26634 | HI7: 32843 | HJ7: 32843 | HK7: 31837 | HL7: 29556 | HM7: 31837 | HN7: 29556 | HO7: 29556 | HP7: 29556 | HQ7: 26634 | HR7: 26634 | HS7: 26634 | HT7: 29556 | HU7: 26634 | HV7: 29556 | HW7: 29556 | HX7: 26634 | HY7: 26634 | HZ7: 26634 | IA7: 26634 | IB7: 29556 | IC7: 29556 | ID7: 32843 | IE7: 32843 | IF7: 29556 | IG7: 32843 | IH7: 32843 | II7: 36039 | IJ7: 36039 | IK7: 30103 | IL7: 30103 | IM7: 30103 | IN7: 32843 | IO7: 36039 | IP7: 36039 | IQ7: 29556
A8: Series End | B8: 45992 | C8: 45992 | D8: 45992 | E8: 45992 | F8: 45992 | G8: 45992 | H8: 45992 | I8: 45992 | J8: 45992 | K8: 45992 | L8: 45992 | M8: 45992 | N8: 45992 | O8: 45992 | P8: 45992 | Q8: 45992 | R8: 45992 | S8: 45992 | T8: 45992 | U8: 45992 | V8: 45992 | W8: 45992 | X8: 45992 | Y8: 45992 | Z8: 45992 | AA8: 45992 | AB8: 45992 | AC8: 45992 | AD8: 45992 | AE8: 45992 | AF8: 45992 | AG8: 45992 | AH8: 45992 | AI8: 45992 | AJ8: 45992 | AK8: 45992 | AL8: 45992 | AM8: 45992 | AN8: 45992 | AO8: 45992 | AP8: 45992 | AQ8: 45992 | AR8: 45992 | AS8: 45992 | AT8: 45992 | AU8: 45992 | AV8: 45992 | AW8: 45992 | AX8: 45992 | AY8: 45992 | AZ8: 45992 | BA8: 45992 | BB8: 45992 | BC8: 45992 | BD8: 45992 | BE8: 45992 | BF8: 45992 | BG8: 45992 | BH8: 45992 | BI8: 45992 | BJ8: 45992 | BK8: 45992 | BL8: 45992 | BM8: 45992 | BN8: 45992 | BO8: 45992 | BP8: 45992 | BQ8: 45992 | BR8: 45992 | BS8: 45992 | BT8: 45992 | BU8: 45992 | BV8: 45992 | BW8: 45992 | BX8: 45992 | BY8: 45992 | BZ8: 45992 | CA8: 45992 | CB8: 45992 | CC8: 45992 | CD8: 45992 | CE8: 45992 | CF8: 45992 | CG8: 45992 | CH8: 45992 | CI8: 45992 | CJ8: 45992 | CK8: 45992 | CL8: 45992 | CM8: 45992 | CN8: 45992 | CO8: 45992 | CP8: 45992 | CQ8: 45992 | CR8: 45992 | CS8: 45992 | CT8: 45992 | CU8: 45992 | CV8: 45992 | CW8: 45992 | CX8: 45992 | CY8: 45992 | CZ8: 45992 | DA8: 45992 | DB8: 45992 | DC8: 45992 | DD8: 45992 | DE8: 45992 | DF8: 45992 | DG8: 45992 | DH8: 45992 | DI8: 45992 | DJ8: 45992 | DK8: 45992 | DL8: 45992 | DM8: 45992 | DN8: 45992 | DO8: 45992 | DP8: 45992 | DQ8: 45992 | DR8: 45992 | DS8: 45992 | DT8: 45992 | DU8: 45992 | DV8: 45992 | DW8: 45992 | DX8: 45992 | DY8: 45992 | DZ8: 45992 | EA8: 45992 | EB8: 45992 | EC8: 45992 | ED8: 45992 | EE8: 45992 | EF8: 45992 | EG8: 45992 | EH8: 45992 | EI8: 45992 | EJ8: 45992 | EK8: 45992 | EL8: 45992 | EM8: 45992 | EN8: 45992 | EO8: 45992 | EP8: 45992 | EQ8: 45992 | ER8: 45992 | ES8: 45992 | ET8: 45992 | EU8: 45992 | EV8: 45992 | EW8: 45992 | EX8: 45992 | EY8: 45992 | EZ8: 45992 | FA8: 45992 | FB8: 45992 | FC8: 45992 | FD8: 45992 | FE8: 45992 | FF8: 45992 | FG8: 45992 | FH8: 45992 | FI8: 45992 | FJ8: 45992 | FK8: 45992 | FL8: 45992 | FM8: 45992 | FN8: 45992 | FO8: 45992 | FP8: 45992 | FQ8: 45992 | FR8: 45992 | FS8: 45992 | FT8: 45992 | FU8: 45992 | FV8: 45992 | FW8: 45992 | FX8: 45992 | FY8: 45992 | FZ8: 45992 | GA8: 45992 | GB8: 45992 | GC8: 45992 | GD8: 45992 | GE8: 45992 | GF8: 45992 | GG8: 45992 | GH8: 45992 | GI8: 45992 | GJ8: 45992 | GK8: 45992 | GL8: 45992 | GM8: 45992 | GN8: 45992 | GO8: 45992 | GP8: 45992 | GQ8: 45992 | GR8: 45992 | GS8: 45992 | GT8: 45992 | GU8: 45992 | GV8: 45992 | GW8: 45992 | GX8: 45992 | GY8: 45992 | GZ8: 45992 | HA8: 45992 | HB8: 45992 | HC8: 45992 | HD8: 45992 | HE8: 45992 | HF8: 45992 | HG8: 45992 | HH8: 45992 | HI8: 45992 | HJ8: 45992 | HK8: 45992 | HL8: 45992 | HM8: 45992 | HN8: 45992 | HO8: 45992 | HP8: 45992 | HQ8: 45992 | HR8: 45992 | HS8: 45992 | HT8: 45992 | HU8: 45992 | HV8: 45992 | HW8: 45992 | HX8: 45992 | HY8: 45992 | HZ8: 45992 | IA8: 45992 | IB8: 45992 | IC8: 45992 | ID8: 45992 | IE8: 45992 | IF8: 45992 | IG8: 45992 | IH8: 45992 | II8: 45992 | IJ8: 45992 | IK8: 45992 | IL8: 45992 | IM8: 45992 | IN8: 45992 | IO8: 45992 | IP8: 45992 | IQ8: 45992
A9: No. Obs | B9: 310 | C9: 214 | D9: 214 | E9: 182 | F9: 182 | G9: 182 | H9: 182 | I9: 214 | J9: 214 | K9: 182 | L9: 214 | M9: 214 | N9: 182 | O9: 198 | P9: 214 | Q9: 182 | R9: 182 | S9: 182 | T9: 146 | U9: 146 | V9: 146 | W9: 146 | X9: 182 | Y9: 182 | Z9: 146 | AA9: 146 | AB9: 146 | AC9: 182 | AD9: 146 | AE9: 182 | AF9: 146 | AG9: 198 | AH9: 182 | AI9: 182 | AJ9: 214 | AK9: 214 | AL9: 182 | AM9: 182 | AN9: 214 | AO9: 214 | AP9: 214 | AQ9: 214 | AR9: 146 | AS9: 146 | AT9: 146 | AU9: 146 | AV9: 214 | AW9: 182 | AX9: 182 | AY9: 182 | AZ9: 111 | BA9: 111 | BB9: 214 | BC9: 214 | BD9: 214 | BE9: 214 | BF9: 111 | BG9: 111 | BH9: 111 | BI9: 182 | BJ9: 111 | BK9: 214 | BL9: 111 | BM9: 182 | BN9: 146 | BO9: 214 | BP9: 214 | BQ9: 182 | BR9: 182 | BS9: 214 | BT9: 214 | BU9: 146 | BV9: 214 | BW9: 214 | BX9: 146 | BY9: 182 | BZ9: 146 | CA9: 182 | CB9: 182 | CC9: 146 | CD9: 146 | CE9: 176 | CF9: 214 | CG9: 146 | CH9: 146 | CI9: 157 | CJ9: 182 | CK9: 157 | CL9: 182 | CM9: 182 | CN9: 182 | CO9: 214 | CP9: 214 | CQ9: 214 | CR9: 182 | CS9: 214 | CT9: 182 | CU9: 182 | CV9: 214 | CW9: 214 | CX9: 214 | CY9: 214 | CZ9: 182 | DA9: 182 | DB9: 146 | DC9: 146 | DD9: 182 | DE9: 146 | DF9: 146 | DG9: 111 | DH9: 111 | DI9: 176 | DJ9: 176 | DK9: 176 | DL9: 146 | DM9: 111 | DN9: 111 | DO9: 182 | DP9: 157 | DQ9: 111 | DR9: 111 | DS9: 176 | DT9: 176 | DU9: 103 | DV9: 103 | DW9: 103 | DX9: 83 | DY9: 146 | DZ9: 146 | EA9: 59 | EB9: 59 | EC9: 83 | ED9: 309 | EE9: 213 | EF9: 213 | EG9: 181 | EH9: 181 | EI9: 181 | EJ9: 181 | EK9: 213 | EL9: 213 | EM9: 181 | EN9: 213 | EO9: 213 | EP9: 181 | EQ9: 197 | ER9: 213 | ES9: 181 | ET9: 181 | EU9: 181 | EV9: 145 | EW9: 145 | EX9: 145 | EY9: 145 | EZ9: 181 | FA9: 181 | FB9: 145 | FC9: 145 | FD9: 145 | FE9: 181 | FF9: 145 | FG9: 181 | FH9: 145 | FI9: 197 | FJ9: 181 | FK9: 181 | FL9: 213 | FM9: 213 | FN9: 181 | FO9: 181 | FP9: 213 | FQ9: 213 | FR9: 213 | FS9: 213 | FT9: 145 | FU9: 145 | FV9: 145 | FW9: 145 | FX9: 213 | FY9: 181 | FZ9: 181 | GA9: 181 | GB9: 110 | GC9: 110 | GD9: 213 | GE9: 213 | GF9: 213 | GG9: 213 | GH9: 110 | GI9: 110 | GJ9: 110 | GK9: 181 | GL9: 110 | GM9: 213 | GN9: 110 | GO9: 181 | GP9: 145 | GQ9: 213 | GR9: 213 | GS9: 181 | GT9: 181 | GU9: 213 | GV9: 213 | GW9: 145 | GX9: 213 | GY9: 213 | GZ9: 145 | HA9: 181 | HB9: 145 | HC9: 181 | HD9: 181 | HE9: 145 | HF9: 145 | HG9: 175 | HH9: 213 | HI9: 145 | HJ9: 145 | HK9: 156 | HL9: 181 | HM9: 156 | HN9: 181 | HO9: 181 | HP9: 181 | HQ9: 213 | HR9: 213 | HS9: 213 | HT9: 181 | HU9: 213 | HV9: 181 | HW9: 181 | HX9: 213 | HY9: 213 | HZ9: 213 | IA9: 213 | IB9: 181 | IC9: 181 | ID9: 145 | IE9: 145 | IF9: 181 | IG9: 145 | IH9: 145 | II9: 110 | IJ9: 110 | IK9: 175 | IL9: 175 | IM9: 175 | IN9: 145 | IO9: 110 | IP9: 110 | IQ9: 181
A10: Series ID | B10: A2325846C | C10: A2325891R | D10: A2326206X | E10: A2327061R | F10: A2327106J | G10: A2327151V | H10: A2327196X | I10: A2326251K | J10: A2327241X | K10: A3604358R | L10: A2327286C | M10: A2327376J | N10: A2327466L | O10: A2327511L | P10: A2326161F | Q10: A2326926W | R10: A2326971J | S10: A2327016C | T10: A2330886T | U10: A2330931T | V10: A2330976W | W10: A3604363J | X10: A2327646W | Y10: A2327691J | Z10: A2329491A | AA10: A2329536V | AB10: A2331741W | AC10: A2327781L | AD10: A3604418F | AE10: A2327736A | AF10: A2331786A | AG10: A2326296R | AH10: A2327556T | AI10: A2327601T | AJ10: A2326116V | AK10: A2326746L | AL10: A2328951K | AM10: A2328906X | AN10: A2328861F | AO10: A2326791X | AP10: A2328996R | AQ10: A2325936J | AR10: A3604368V | AS10: A2329581F | AT10: A2329716C | AU10: A2329761R | AV10: A2326386V | AW10: A2327916K | AX10: A2327961W | AY10: A2328006T | AZ10: A2329806J | BA10: A2329851V | BB10: A2328051C | BC10: A2325981V | BD10: A2331876F | BE10: A2326431V | BF10: A3604373L | BG10: A2329941X | BH10: A3604413V | BI10: A2328096J | BJ10: A2329986C | BK10: A2326521X | BL10: A2329896X | BM10: A2328141J | BN10: A2331921F | BO10: A2326026R | BP10: A3604403R | BQ10: A2328186L | BR10: A3604433C | BS10: A3604428K | BT10: A3604383T | BU10: A2330031K | BV10: A2328276T | BW10: A2331021X | BX10: A2331066C | BY10: A2328321T | BZ10: A2330076R | CA10: A2328366W | CB10: A2329221A | CC10: A2330121R | CD10: A2330166V | CE10: A2331606F | CF10: A2329266F | CG10: A2331696W | CH10: A2331111C | CI10: A3604438R | CJ10: A2329176A | CK10: A2329086W | CL10: A3604388C | CM10: A2329041T | CN10: A2329131W | CO10: A2326071A | CP10: A2326656J | CQ10: A2328591T | CR10: A2328726R | CS10: A2328636K | CT10: A2328771A | CU10: A2328681W | CV10: A2326701J | CW10: A2328816V | CX10: A2331201J | CY10: A2326611C | CZ10: A2328501A | DA10: A2328546F | DB10: A2331246L | DC10: A3604423X | DD10: A2329311F | DE10: A3604443J | DF10: A3604408A | DG10: A2330211V | DH10: A3604393W | DI10: A2326881C | DJ10: A2329356K | DK10: A2329401K | DL10: A2331381C | DM10: A2330346C | DN10: A2330391R | DO10: A2328456A | DP10: A2328411W | DQ10: A2330436J | DR10: A2330481V | DS10: A2331426W | DT10: A2329446R | DU10: A2331471J | DV10: A2331516A | DW10: A2331561L | DX10: A2332596F | DY10: A3602833C | DZ10: A3602878J | EA10: A3604453L | EB10: A3604448V | EC10: A2332776R | ED10: A2325850V | EE10: A2325895X | EF10: A2326210R | EG10: A2327065X | EH10: A2327110X | EI10: A2327155C | EJ10: A2327200C | EK10: A2326255V | EL10: A2327245J | EM10: A3604362F | EN10: A2327290V | EO10: A2327380X | EP10: A2327470C | EQ10: A2327515W | ER10: A2326165R | ES10: A2326930L | ET10: A2326975T | EU10: A2327020V | EV10: A2330890J | EW10: A2330935A | EX10: A2330980L | EY10: A3604367T | EZ10: A2327650L | FA10: A2327695T | FB10: A2329495K | FC10: A2329540K | FD10: A2331745F | FE10: A2327785W | FF10: A3604422W | FG10: A2327740T | FH10: A2331790T | FI10: A2326300V | FJ10: A2327560J | FK10: A2327605A | FL10: A2326120K | FM10: A2326750C | FN10: A2328955V | FO10: A2328910R | FP10: A2328865R | FQ10: A2326795J | FR10: A2329000W | FS10: A2325940X | FT10: A3604372K | FU10: A2329585R | FV10: A2329720V | FW10: A2329765X | FX10: A2326390K | FY10: A2327920A | FZ10: A2327965F | GA10: A2328010J | GB10: A2329810X | GC10: A2329855C | GD10: A2328055L | GE10: A2325985C | GF10: A2331880W | GG10: A2326435C | GH10: A3604377W | GI10: A2329945J | GJ10: A3604417C | GK10: A2328100L | GL10: A2329990V | GM10: A2326525J | GN10: A2329900C | GO10: A2328145T | GP10: A2331925R | GQ10: A2326030F | GR10: A3604407X | GS10: A2328190C | GT10: A3604437L | GU10: A3604432A | GV10: A3604387A | GW10: A2330035V | GX10: A2328280J | GY10: A2331025J | GZ10: A2331070V | HA10: A2328325A | HB10: A2330080F | HC10: A2328370L | HD10: A2329225K | HE10: A2330125X | HF10: A2330170K | HG10: A2331610W | HH10: A2329270W | HI10: A2331700A | HJ10: A2331115L | HK10: A3604442F | HL10: A2329180T | HM10: A2329090L | HN10: A3604392V | HO10: A2329045A | HP10: A2329135F | HQ10: A2326075K | HR10: A2326660X | HS10: A2328595A | HT10: A2328730F | HU10: A2328640A | HV10: A2328775K | HW10: A2328685F | HX10: A2326705T | HY10: A2328820K | HZ10: A2331205T | IA10: A2326615L | IB10: A2328505K | IC10: A2328550W | ID10: A2331250C | IE10: A3604427J | IF10: A2329315R | IG10: A3604447T | IH10: A3604412T | II10: A2330215C | IJ10: A3604397F | IK10: A2326885L | IL10: A2329360A | IM10: A2329405V | IN10: A2331385L | IO10: A2330350V | IP10: A2330395X | IQ10: A2328460T
A11: 17777 | B11: 2.59
A12: 17868 | B12: 2.63 | ED12: 1.5
A13: 17958 | B13: 2.71 | ED13: 3
A14: 18050 | B14: 2.74 | ED14: 1.1
A15: 18142 | B15: 2.82 | ED15: 2.9
A16: 18233 | B16: 2.86 | ED16: 1.4
A17: 18323 | B17: 2.9 | ED17: 1.4
A18: 18415 | B18: 3.02 | ED18: 4.1
A19: 18507 | B19: 3.05 | ED19: 1
A20: 18598 | B20: 3.17 | ED20: 3.9
A21: 18688 | B21: 3.32 | ED21: 4.7
A22: 18780 | B22: 3.52 | ED22: 6
A23: 18872 | B23: 3.71 | ED23: 5.4
... A106: 26451 | B106: 7.58 | ED106: 1.1
A107: 26543 | B107: 7.69 | C107: 7.24 | D107: 7.03 | I107: 8.5 | J107: 7.19 | L107: 4.78 | M107: 25.66 | P107: 9.15 | AJ107: 2.61 | AK107: 7.04 | AN107: 5.15 | AO107: 0.49 | AP107: 0.49 | AQ107: 18.84 | AV107: 22.55 | BB107: 4.32 | BC107: 6.51 | BD107: 7.07 | BE107: 7.07 | BK107: 4.33 | BO107: 14.01 | BP107: 11.89 | BS107: 18.54 | BT107: 18.54 | BV107: 44.33 | BW107: 50.57 | CF107: 3.92 | CO107: 8.66 | CP107: 8.81 | CQ107: 19.86 | CS107: 5.3 | CV107: 6.46 | CW107: 6.46 | CX107: 37.26 | CY107: 37.26 | ED107: 1.5
A108: 26634 | B108: 7.77 | C108: 7.35 | D108: 7.03 | I108: 8.63 | J108: 7.3 | L108: 4.88 | M108: 25.89 | P108: 9.19 | AJ108: 2.63 | AK108: 7.11 | AN108: 5.23 | AO108: 0.49 | AP108: 0.49 | AQ108: 19.11 | AV108: 22.77 | BB108: 4.41 | BC108: 6.62 | BD108: 7.18 | BE108: 7.18 | BK108: 4.33 | BO108: 14.13 | BP108: 12.07 | BS108: 18.64 | BT108: 18.64 | BV108: 44.53 | BW108: 50.79 | CF108: 4.07 | CO108: 8.71 | CP108: 8.81 | CQ108: 19.86 | CS108: 5.3 | CV108: 6.46 | CW108: 6.46 | CX108: 37.26 | CY108: 37.26 | ED108: 1 | EE108: 1.5 | EF108: 0 | EK108: 1.5 | EL108: 1.5 | EN108: 2.1 | EO108: 0.9 | ER108: 0.4 | FL108: 0.8 | FM108: 1 | FP108: 1.6 | FQ108: 0 | FR108: 0 | FS108: 1.4 | FX108: 1 | GD108: 2.1 | GE108: 1.7 | GF108: 1.6 | GG108: 1.6 | GM108: 0 | GQ108: 0.9 | GR108: 1.5 | GU108: 0.5 | GV108: 0.5 | GX108: 0.5 | GY108: 0.4 | HH108: 3.8 | HQ108: 0.6 | HR108: 0 | HS108: 0 | HU108: 0 | HX108: 0 | HY108: 0 | HZ108: 0 | IA108: 0
A109: 26724 | B109: 7.93 | C109: 7.68 | D109: 7.14 | I109: 9.33 | J109: 7.74 | L109: 5.79 | M109: 25.74 | P109: 9.38 | AJ109: 2.68 | AK109: 7.14 | AN109: 5.25 | AO109: 0.5 | AP109: 0.5 | AQ109: 19.38 | AV109: 23.44 | BB109: 4.47 | BC109: 6.69 | BD109: 7.29 | BE109: 7.29 | BK109: 4.35 | BO109: 14.26 | BP109: 12.42 | BS109: 18.96 | BT109: 18.96 | BV109: 44.53 | BW109: 50.79 | CF109: 4.19 | CO109: 8.75 | CP109: 8.85 | CQ109: 19.86 | CS109: 5.27 | CV109: 6.52 | CW109: 6.53 | CX109: 37.26 | CY109: 37.26 | ED109: 2.1 | EE109: 4.5 | EF109: 1.6 | EK109: 8.1 | EL109: 6 | EN109: 18.6 | EO109: -0.6 | ER109: 2.1 | FL109: 1.9 | FM109: 0.4 | FP109: 0.4 | FQ109: 2 | FR109: 2 | FS109: 1.4 | FX109: 2.9 | GD109: 1.4 | GE109: 1.1 | GF109: 1.5 | GG109: 1.5 | GM109: 0.5 | GQ109: 0.9 | GR109: 2.9 | GU109: 1.7 | GV109: 1.7 | GX109: 0 | GY109: 0 | HH109: 2.9 | HQ109: 0.5 | HR109: 0.5 | HS109: 0 | HU109: -0.6 | HX109: 0.9 | HY109: 1.1 | HZ109: 0 | IA109: 0
A110: 26816 | B110: 8.2 | C110: 8.08 | D110: 7.29 | I110: 10.36 | J110: 8.48 | L110: 6.71 | M110: 27.76 | P110: 9.61 | AJ110: 2.77 | AK110: 7.61 | AN110: 5.58 | AO110: 0.5 | AP110: 0.5 | AQ110: 20.19 | AV110: 24.34 | BB110: 4.65 | BC110: 6.88 | BD110: 7.4 | BE110: 7.4 | BK110: 4.35 | BO110: 14.57 | BP110: 12.89 | BS110: 21.29 | BT110: 21.29 | BV110: 44.72 | BW110: 51.01 | CF110: 4.22 | CO110: 8.8 | CP110: 8.9 | CQ110: 19.95 | CS110: 5.24 | CV110: 6.59 | CW110: 6.59 | CX110: 37.26 | CY110: 37.26 | ED110: 3.4 | EE110: 5.2 | EF110: 2.1 | EK110: 11 | EL110: 9.6 | EN110: 15.9 | EO110: 7.8 | ER110: 2.5 | FL110: 3.4 | FM110: 6.6 | FP110: 6.3 | FQ110: 0 | FR110: 0 | FS110: 4.2 | FX110: 3.8 | GD110: 4 | GE110: 2.8 | GF110: 1.5 | GG110: 1.5 | GM110: 0 | GQ110: 2.2 | GR110: 3.8 | GU110: 12.3 | GV110: 12.3 | GX110: 0.4 | GY110: 0.4 | HH110: 0.7 | HQ110: 0.6 | HR110: 0.6 | HS110: 0.5 | HU110: -0.6 | HX110: 1.1 | HY110: 0.9 | HZ110: 0 | IA110: 0
A111: 26908 | B111: 8.47 | C111: 8.56 | D111: 7.51 | I111: 11.1 | J111: 8.96 | L111: 7.48 | M111: 29.56 | P111: 9.76 | AJ111: 2.77 | AK111: 7.64 | AN111: 5.58 | AO111: 0.5 | AP111: 0.5 | AQ111: 20.73 | AV111: 25.79 | BB111: 5.01 | BC111: 7.02 | BD111: 7.55 | BE111: 7.55 | BK111: 4.56 | BO111: 15.01 | BP111: 13.18 | BS111: 22.35 | BT111: 22.35 | BV111: 45.41 | BW111: 51.79 | CF111: 4.64 | CO111: 9.02 | CP111: 9.13 | CQ111: 20.34 | CS111: 5.42 | CV111: 6.68 | CW111: 6.68 | CX111: 37.26 | CY111: 37.26 | ED111: 3.3 | EE111: 5.9 | EF111: 3 | EK111: 7.1 | EL111: 5.7 | EN111: 11.5 | EO111: 6.5 | ER111: 1.6 | FL111: 0 | FM111: 0.4 | FP111: 0 | FQ111: 0 | FR111: 0 | FS111: 2.7 | FX111: 6 | GD111: 7.7 | GE111: 2 | GF111: 2 | GG111: 2 | GM111: 4.8 | GQ111: 3 | GR111: 2.2 | GU111: 5 | GV111: 5 | GX111: 1.5 | GY111: 1.5 | HH111: 10 | HQ111: 2.5 | HR111: 2.6 | HS111: 2 | HU111: 3.4 | HX111: 1.4 | HY111: 1.4 | HZ111: 0 | IA111: 0
A112: 26999 | B112: 8.78 | C112: 8.88 | D112: 7.66 | I112: 11.56 | J112: 9.3 | L112: 7.62 | M112: 29.71 | P112: 10.07 | AJ112: 2.93 | AK112: 7.64 | AN112: 5.58 | AO112: 0.56 | AP112: 0.56 | AQ112: 21.63 | AV112: 26.46 | BB112: 5.1 | BC112: 7.28 | BD112: 7.8 | BE112: 7.8 | BK112: 4.56 | BO112: 15.26 | BP112: 13.71 | BS112: 23.2 | BT112: 23.2 | BV112: 45.9 | BW112: 52.35 | CF112: 4.82 | CO112: 9.28 | CP112: 9.49 | CQ112: 20.82 | CS112: 6.02 | CV112: 6.74 | CW112: 6.74 | CX112: 37.26 | CY112: 37.26 | ED112: 3.7 | EE112: 3.7 | EF112: 2 | EK112: 4.1 | EL112: 3.8 | EN112: 1.9 | EO112: 0.5 | ER112: 3.2 | FL112: 5.8 | FM112: 0 | FP112: 0 | FQ112: 12 | FR112: 12 | FS112: 4.3 | FX112: 2.6 | GD112: 1.8 | GE112: 3.7 | GF112: 3.3 | GG112: 3.3 | GM112: 0 | GQ112: 1.7 | GR112: 4 | GU112: 3.8 | GV112: 3.8 | GX112: 1.1 | GY112: 1.1 | HH112: 3.9 | HQ112: 2.9 | HR112: 3.9 | HS112: 2.4 | HU112: 11.1 | HX112: 0.9 | HY112: 0.9 | HZ112: 0 | IA112: 0
A113: 27089 | B113: 9.01 | C113: 9.17 | D113: 7.92 | I113: 12.42 | J113: 9.67 | L113: 8.69 | M113: 31.59 | P113: 10.3 | AJ113: 2.93 | AK113: 7.68 | AN113: 5.61 | AO113: 0.56 | AP113: 0.56 | AQ113: 22.08 | AV113: 27.35 | BB113: 5.33 | BC113: 7.47 | BD113: 7.91 | BE113: 7.91 | BK113: 4.72 | BO113: 15.69 | BP113: 14.29 | BS113: 24.58 | BT113: 24.58 | BV113: 46.39 | BW113: 52.91 | CF113: 5.12 | CO113: 9.5 | CP113: 9.71 | CQ113: 21.5 | CS113: 6.08 | CV113: 6.77 | CW113: 6.77 | CX113: 37.26 | CY113: 37.26 | ED113: 2.6 | EE113: 3.3 | EF113: 3.4 | EK113: 7.4 | EL113: 4 | EN113: 14 | EO113: 6.3 | ER113: 2.3 | FL113: 0 | FM113: 0.5 | FP113: 0.5 | FQ113: 0 | FR113: 0 | FS113: 2.1 | FX113: 3.4 | GD113: 4.5 | GE113: 2.6 | GF113: 1.4 | GG113: 1.4 | GM113: 3.5 | GQ113: 2.8 | GR113: 4.2 | GU113: 5.9 | GV113: 5.9 | GX113: 1.1 | GY113: 1.1 | HH113: 6.2 | HQ113: 2.4 | HR113: 2.3 | HS113: 3.3 | HU113: 1 | HX113: 0.4 | HY113: 0.4 | HZ113: 0 | IA113: 0
A114: 27181 | B114: 9.39 | C114: 9.54 | D114: 8.25 | I114: 12.63 | J114: 9.54 | L114: 8.76 | M114: 32.44 | P114: 10.6 | AJ114: 3.08 | AK114: 8.24 | AN114: 6.07 | AO114: 0.57 | AP114: 0.57 | AQ114: 23.7 | AV114: 28.25 | BB114: 5.84 | BC114: 7.84 | BD114: 8.17 | BE114: 8.17 | BK114: 4.9 | BO114: 16.26 | BP114: 15.06 | BS114: 26.8 | BT114: 26.8 | BV114: 46.87 | BW114: 53.47 | CF114: 5.21 | CO114: 9.72 | CP114: 9.98 | CQ114: 21.69 | CS114: 6.14 | CV114: 6.83 | CW114: 6.83 | CX114: 37.26 | CY114: 37.26 | ED114: 4.2 | EE114: 4 | EF114: 4.2 | EK114: 1.7 | EL114: -1.3 | EN114: 0.8 | EO114: 2.7 | ER114: 2.9 | FL114: 5.1 | FM114: 7.3 | FP114: 8.2 | FQ114: 1.8 | FR114: 1.8 | FS114: 7.3 | FX114: 3.3 | GD114: 9.6 | GE114: 5 | GF114: 3.3 | GG114: 3.3 | GM114: 3.8 | GQ114: 3.6 | GR114: 5.4 | GU114: 9 | GV114: 9 | GX114: 1 | GY114: 1.1 | HH114: 1.8 | HQ114: 2.3 | HR114: 2.8 | HS114: 0.9 | HU114: 1 | HX114: 0.9 | HY114: 0.9 | HZ114: 0 | IA114: 0
A115: 27273 | B115: 9.86 | C115: 9.76 | D115: 8.84 | I115: 11.97 | J115: 8.76 | L115: 7.95 | M115: 32.91 | P115: 11.21 | AJ115: 3.29 | AK115: 8.64 | AN115: 6.26 | AO115: 0.62 | AP115: 0.62 | AQ115: 24.79 | AV115: 31.59 | BB115: 6.31 | BC115: 8.21 | BD115: 8.5 | BE115: 8.5 | BK115: 5.08 | BO115: 17.2 | BP115: 16.23 | BS115: 27.65 | BT115: 27.65 | BV115: 49.52 | BW115: 56.48 | CF115: 6.18 | CO115: 10.51 | CP115: 10.8 | CQ115: 23.33 | CS115: 6.42 | CV115: 7.11 | CW115: 7.11 | CX115: 37.26 | CY115: 37.26 | ED115: 5 | EE115: 2.3 | EF115: 7.2 | EK115: -5.2 | EL115: -8.2 | EN115: -9.2 | EO115: 1.4 | ER115: 5.8 | FL115: 6.8 | FM115: 4.9 | FP115: 3.1 | FQ115: 8.8 | FR115: 8.8 | FS115: 4.6 | FX115: 11.8 | GD115: 8 | GE115: 4.7 | GF115: 4 | GG115: 4 | GM115: 3.7 | GQ115: 5.8 | GR115: 7.8 | GU115: 3.2 | GV115: 3.2 | GX115: 5.7 | GY115: 5.6 | HH115: 18.6 | HQ115: 8.1 | HR115: 8.2 | HS115: 7.6 | HU115: 4.6 | HX115: 4.1 | HY115: 4.1 | HZ115: 0 | IA115: 0
A116: 27364 | B116: 10.21 | C116: 9.76 | D116: 9.5 | I116: 11.18 | J116: 7.98 | L116: 6.78 | M116: 32.44 | P116: 11.9 | AJ116: 3.34 | AK116: 8.92 | AN116: 6.45 | AO116: 0.62 | AP116: 0.62 | AQ116: 26.59 | AV116: 33.16 | BB116: 6.81 | BC116: 8.65 | BD116: 8.83 | BE116: 8.83 | BK116: 5.19 | BO116: 18.2 | BP116: 17.05 | BS116: 28.81 | BT116: 28.81 | BV116: 50.79 | BW116: 57.93 | CF116: 6.54 | CO116: 11 | CP116: 11.29 | CQ116: 25.16 | CS116: 6.42 | CV116: 7.61 | CW116: 7.61 | CX116: 45.4 | CY116: 45.4 | ED116: 3.5 | EE116: 0 | EF116: 7.5 | EK116: -6.6 | EL116: -8.9 | EN116: -14.7 | EO116: -1.4 | ER116: 6.2 | FL116: 1.5 | FM116: 3.2 | FP116: 3 | FQ116: 0 | FR116: 0 | FS116: 7.3 | FX116: 5 | GD116: 7.9 | GE116: 5.4 | GF116: 3.9 | GG116: 3.9 | GM116: 2.2 | GQ116: 5.8 | GR116: 5.1 | GU116: 4.2 | GV116: 4.2 | GX116: 2.6 | GY116: 2.6 | HH116: 5.8 | HQ116: 4.7 | HR116: 4.5 | HS116: 7.8 | HU116: 0 | HX116: 7 | HY116: 7 | HZ116: 21.8 | IA116: 21.8
A117: 27454 | B117: 10.59 | C117: 9.87 | D117: 9.98 | I117: 11.1 | J117: 7.6 | L117: 7.01 | M117: 32.05 | P117: 12.43 | AJ117: 3.52 | AK117: 9.2 | AN117: 6.64 | AO117: 0.68 | AP117: 0.68 | AQ117: 26.95 | AV117: 34.05 | BB117: 7.02 | BC117: 8.91 | BD117: 9.12 | BE117: 9.12 | BK117: 5.66 | BO117: 18.88 | BP117: 17.4 | BS117: 29.45 | BT117: 29.45 | BV117: 51.57 | BW117: 58.83 | CF117: 7.02 | CO117: 11.48 | CP117: 11.84 | CQ117: 24.2 | CS117: 7.14 | CV117: 7.76 | CW117: 7.76 | CX117: 45.4 | CY117: 45.4 | ED117: 3.7 | EE117: 1.1 | EF117: 5.1 | EK117: -0.7 | EL117: -4.8 | EN117: 3.4 | EO117: -1.2 | ER117: 4.5 | FL117: 5.4 | FM117: 3.1 | FP117: 2.9 | FQ117: 9.7 | FR117: 9.7 | FS117: 1.4 | FX117: 2.7 | GD117: 3.1 | GE117: 3 | GF117: 3.3 | GG117: 3.3 | GM117: 9.1 | GQ117: 3.7 | GR117: 2.1 | GU117: 2.2 | GV117: 2.2 | GX117: 1.5 | GY117: 1.6 | HH117: 7.3 | HQ117: 4.4 | HR117: 4.9 | HS117: -3.8 | HU117: 11.2 | HX117: 2 | HY117: 2 | HZ117: 0 | IA117: 0
A118: 27546 | B118: 10.98 | C118: 10.19 | D118: 10.31 | I118: 11.56 | J118: 7.6 | L118: 7.67 | M118: 34.39 | P118: 12.7 | AJ118: 3.59 | AK118: 9.35 | AN118: 6.75 | AO118: 0.69 | AP118: 0.69 | AQ118: 28.12 | AV118: 35.28 | BB118: 7.61 | BC118: 9.39 | BD118: 9.48 | BE118: 9.48 | BK118: 5.98 | BO118: 19.51 | BP118: 17.75 | BS118: 30.83 | BT118: 30.83 | BV118: 52.35 | BW118: 59.72 | CF118: 7.14 | CO118: 11.83 | CP118: 12.24 | CQ118: 25.45 | CS118: 7.33 | CV118: 7.76 | CW118: 7.76 | CX118: 45.4 | CY118: 45.4 | ED118: 3.7 | EE118: 3.2 | EF118: 3.3 | EK118: 4.1 | EL118: 0 | EN118: 9.4 | EO118: 7.3 | ER118: 2.2 | FL118: 2 | FM118: 1.6 | FP118: 1.7 | FQ118: 1.5 | FR118: 1.5 | FS118: 4.3 | FX118: 3.6 | GD118: 8.4 | GE118: 5.4 | GF118: 3.9 | GG118: 3.9 | GM118: 5.7 | GQ118: 3.3 | GR118: 2 | GU118: 4.7 | GV118: 4.7 | GX118: 1.5 | GY118: 1.5 | HH118: 1.7 | HQ118: 3 | HR118: 3.4 | HS118: 5.2 | HU118: 2.7 | HX118: 0 | HY118: 0 | HZ118: 0 | IA118: 0
A119: 27638 | B119: 11.06 | C119: 10.34 | D119: 10.64 | I119: 11.64 | J119: 7.5 | L119: 7.8 | M119: 35.41 | P119: 13.04 | AJ119: 3.67 | AK119: 9.6 | AN119: 6.89 | AO119: 0.7 | AP119: 0.7 | AQ119: 28.75 | AV119: 37.06 | BB119: 8.29 | BC119: 9.72 | BD119: 9.92 | BE119: 9.92 | BK119: 6.11 | BO119: 19.95 | BP119: 18.4 | BS119: 31.99 | BT119: 31.99 | BV119: 52.35 | BW119: 59.72 | CF119: 7.77 | CO119: 12.45 | CP119: 12.83 | CQ119: 27.47 | CS119: 7.26 | CV119: 8.38 | CW119: 8.38 | CX119: 45.4 | CY119: 45.4 | ED119: 0.7 | EE119: 1.5 | EF119: 3.2 | EK119: 0.7 | EL119: -1.3 | EN119: 1.7 | EO119: 3 | ER119: 2.7 | FL119: 2.2 | FM119: 2.7 | FP119: 2.1 | FQ119: 1.4 | FR119: 1.4 | FS119: 2.2 | FX119: 5 | GD119: 8.9 | GE119: 3.5 | GF119: 4.6 | GG119: 4.6 | GM119: 2.2 | GQ119: 2.3 | GR119: 3.7 | GU119: 3.8 | GV119: 3.8 | GX119: 0 | GY119: 0 | HH119: 8.8 | HQ119: 5.2 | HR119: 4.8 | HS119: 7.9 | HU119: -1 | HX119: 8 | HY119: 8 | HZ119: 0 | IA119: 0
... A122: 27912 | B122: 12.29 | C122: 11.25 | D122: 11.71 | I122: 12.42 | J122: 8.21 | L122: 7.95 | M122: 37.12 | P122: 13.84 | AJ122: 4.56 | AK122: 11.94 | AN122: 8.85 | AO122: 0.87 | AP122: 0.87 | AQ122: 32.99 | AV122: 40.75 | BB122: 9.06 | BC122: 10.98 | BD122: 10.9 | BE122: 10.9 | BK122: 6.57 | BO122: 22.39 | BP122: 20.86 | BS122: 35.17 | BT122: 35.17 | BV122: 54.31 | BW122: 61.95 | CF122: 8.95 | CO122: 13.68 | CP122: 14.14 | CQ122: 31.14 | CS122: 7.92 | CV122: 9 | CW122: 9 | CX122: 64.19 | CY122: 64.19 | ED122: 2.6 | EE122: 0.4 | EF122: 2.5 | EK122: 0.6 | EL122: 0.9 | EN122: -0.3 | EO122: 0.2 | ER122: 0.8 | FL122: 2.5 | FM122: 3 | FP122: 3.5 | FQ122: 1.2 | FR122: 1.2 | FS122: 5.8 | FX122: 4 | GD122: 3 | GE122: 4.2 | GF122: 2.7 | GG122: 2.7 | GM122: 2.2 | GQ122: 2.6 | GR122: 5.7 | GU122: 5.1 | GV122: 5.1 | GX122: 0.7 | GY122: 0.7 | HH122: 8.9 | HQ122: 1.3 | HR122: 1.3 | HS122: 2.9 | HU122: -3.4 | HX122: 0 | HY122: 0 | HZ122: 0.3 | IA122: 0.3
A123: 28004 | B123: 12.6 | C123: 11.61 | D123: 11.86 | I123: 12.92 | J123: 8.59 | L123: 8.71 | M123: 36.58 | O123: 12.46 | P123: 14 | AG123: 10.18 | AJ123: 4.56 | AK123: 11.91 | AN123: 8.79 | AO123: 0.87 | AP123: 0.87 | AQ123: 33.53 | AV123: 42.2 | BB123: 9.24 | BC123: 11.31 | BD123: 11.38 | BE123: 11.38 | BK123: 6.59 | BO123: 22.76 | BP123: 21.44 | BS123: 36.23 | BT123: 36.23 | BV123: 54.61 | BW123: 62.29 | CF123: 9.31 | CO123: 13.94 | CP123: 14.5 | CQ123: 32 | CS123: 8.07 | CV123: 8.69 | CW123: 8.69 | CX123: 64.19 | CY123: 64.19 | ED123: 2.5 | EE123: 3.2 | EF123: 1.3 | EK123: 4 | EL123: 4.6 | EN123: 9.6 | EO123: -1.5 | ER123: 1.2 | FL123: 0 | FM123: -0.3 | FP123: -0.7 | FQ123: 0 | FR123: 0 | FS123: 1.6 | FX123: 3.6 | GD123: 2 | GE123: 3 | GF123: 4.4 | GG123: 4.4 | GM123: 0.3 | GQ123: 1.7 | GR123: 2.8 | GU123: 3 | GV123: 3 | GX123: 0.6 | GY123: 0.5 | HH123: 4 | HQ123: 1.9 | HR123: 2.5 | HS123: 2.8 | HU123: 1.9 | HX123: -3.4 | HY123: -3.4 | HZ123: 0 | IA123: 0
A124: 28095 | B124: 13.34 | C124: 12.05 | D124: 12.08 | I124: 13.37 | J124: 8.86 | L124: 9.33 | M124: 37.04 | O124: 13.13 | P124: 14.11 | AG124: 10.38 | AJ124: 4.62 | AK124: 12.08 | AN124: 8.93 | AO124: 0.89 | AP124: 0.89 | AQ124: 35.78 | AV124: 42.76 | BB124: 9.51 | BC124: 11.68 | BD124: 11.71 | BE124: 11.71 | BK124: 6.66 | BO124: 23.14 | BP124: 22.2 | BS124: 36.33 | BT124: 36.33 | BV124: 55 | BW124: 62.73 | CF124: 9.61 | CO124: 14.16 | CP124: 14.73 | CQ124: 32.68 | CS124: 8.07 | CV124: 8.75 | CW124: 8.75 | CX124: 64.74 | CY124: 64.74 | ED124: 5.9 | EE124: 3.8 | EF124: 1.9 | EK124: 3.5 | EL124: 3.1 | EN124: 7.1 | EO124: 1.3 | EQ124: 5.4 | ER124: 0.8 | FI124: 2 | FL124: 1.3 | FM124: 1.4 | FP124: 1.6 | FQ124: 2.3 | FR124: 2.3 | FS124: 6.7 | FX124: 1.3 | GD124: 2.9 | GE124: 3.3 | GF124: 2.9 | GG124: 2.9 | GM124: 1.1 | GQ124: 1.7 | GR124: 3.5 | GU124: 0.3 | GV124: 0.3 | GX124: 0.7 | GY124: 0.7 | HH124: 3.2 | HQ124: 1.6 | HR124: 1.6 | HS124: 2.1 | HU124: 0 | HX124: 0.7 | HY124: 0.7 | HZ124: 0.9 | IA124: 0.9
A125: 28185 | B125: 13.65 | C125: 12.27 | D125: 12.37 | I125: 13.7 | J125: 8.89 | L125: 9.31 | M125: 40.16 | O125: 14.46 | P125: 14.61 | AG125: 10.74 | AJ125: 4.65 | AK125: 12.15 | AN125: 9.01 | AO125: 0.89 | AP125: 0.89 | AQ125: 36.32 | AV125: 44.43 | BB125: 9.66 | BC125: 11.94 | BD125: 12 | BE125: 12 | BK125: 7.04 | BO125: 23.82 | BP125: 22.73 | BS125: 38.45 | BT125: 38.45 | BV125: 55.68 | BW125: 63.51 | CF125: 10.06 | CO125: 14.56 | CP125: 15.22 | CQ125: 33.55 | CS125: 8.39 | CV125: 8.75 | CW125: 8.75 | CX125: 64.74 | CY125: 64.74 | ED125: 2.3 | EE125: 1.8 | EF125: 2.4 | EK125: 2.5 | EL125: 0.3 | EN125: -0.2 | EO125: 8.4 | EQ125: 10.1 | ER125: 3.5 | FI125: 3.5 | FL125: 0.6 | FM125: 0.6 | FP125: 0.9 | FQ125: 0 | FR125: 0 | FS125: 1.5 | FX125: 3.9 | GD125: 1.6 | GE125: 2.2 | GF125: 2.5 | GG125: 2.5 | GM125: 5.7 | GQ125: 2.9 | GR125: 2.4 | GU125: 5.8 | GV125: 5.8 | GX125: 1.2 | GY125: 1.2 | HH125: 4.7 | HQ125: 2.8 | HR125: 3.3 | HS125: 2.7 | HU125: 4 | HX125: 0 | HY125: 0 | HZ125: 0 | IA125: 0
A126: 28277 | B126: 13.96 | C126: 12.63 | D126: 12.56 | I126: 14.4 | J126: 9.37 | L126: 10.15 | M126: 40.63 | O126: 15.32 | P126: 15.03 | AG126: 11.13 | AJ126: 4.71 | AK126: 12.3 | AN126: 9.12 | AO126: 0.9 | AP126: 0.9 | AQ126: 37.58 | AV126: 45.77 | BB126: 10.01 | BC126: 12.27 | BD126: 12.25 | BE126: 12.25 | BK126: 7.06 | BO126: 24.39 | BP126: 23.67 | BS126: 41.31 | BT126: 41.31 | BV126: 56.95 | BW126: 64.97 | CF126: 10.45 | CO126: 14.82 | CP126: 15.49 | CQ126: 34.51 | CS126: 8.26 | CV126: 8.78 | CW126: 8.78 | CX126: 64.74 | CY126: 64.74 | ED126: 2.3 | EE126: 2.9 | EF126: 1.5 | EK126: 5.1 | EL126: 5.4 | EN126: 9 | EO126: 1.2 | EQ126: 5.9 | ER126: 2.9 | FI126: 3.6 | FL126: 1.3 | FM126: 1.2 | FP126: 1.2 | FQ126: 1.1 | FR126: 1.1 | FS126: 3.5 | FX126: 3 | GD126: 3.6 | GE126: 2.8 | GF126: 2.1 | GG126: 2.1 | GM126: 0.3 | GQ126: 2.4 | GR126: 4.1 | GU126: 7.4 | GV126: 7.4 | GX126: 2.3 | GY126: 2.3 | HH126: 3.9 | HQ126: 1.8 | HR126: 1.8 | HS126: 2.9 | HU126: -1.5 | HX126: 0.3 | HY126: 0.3 | HZ126: 0 | IA126: 0
A127: 28369 | B127: 14.23 | C127: 13.14 | D127: 12.85 | I127: 14.49 | J127: 9.4 | L127: 10.12 | M127: 41.57 | O127: 15.7 | P127: 15.33 | AG127: 11.46 | AJ127: 4.77 | AK127: 12.44 | AN127: 9.26 | AO127: 0.91 | AP127: 0.91 | AQ127: 38.21 | AV127: 47 | BB127: 10.22 | BC127: 12.5 | BD127: 12.51 | BE127: 12.51 | BK127: 7.13 | BO127: 24.76 | BP127: 23.84 | BS127: 42.58 | BT127: 42.58 | BV127: 56.86 | BW127: 64.85 | CF127: 10.84 | CO127: 15.04 | CP127: 15.77 | CQ127: 35.28 | CS127: 8.39 | CV127: 8.87 | CW127: 8.88 | CX127: 64.74 | CY127: 64.74 | ED127: 1.9 | EE127: 4 | EF127: 2.3 | EK127: 0.6 | EL127: 0.3 | EN127: -0.3 | EO127: 2.3 | EQ127: 2.5 | ER127: 2 | FI127: 3 | FL127: 1.3 | FM127: 1.1 | FP127: 1.5 | FQ127: 1.1 | FR127: 1.1 | FS127: 1.7 | FX127: 2.7 | GD127: 2.1 | GE127: 1.9 | GF127: 2.1 | GG127: 2.1 | GM127: 1 | GQ127: 1.5 | GR127: 0.7 | GU127: 3.1 | GV127: 3.1 | GX127: -0.2 | GY127: -0.2 | HH127: 3.7 | HQ127: 1.5 | HR127: 1.8 | HS127: 2.2 | HU127: 1.6 | HX127: 1 | HY127: 1.1 | HZ127: 0 | IA127: 0
A128: 28460 | B128: 14.57 | C128: 13.4 | D128: 13.15 | I128: 14.57 | J128: 9.4 | L128: 9.78 | M128: 42.27 | O128: 16.41 | P128: 16.09 | AG128: 11.65 | AJ128: 4.83 | AK128: 12.69 | AN128: 9.42 | AO128: 0.91 | AP128: 0.91 | AQ128: 39.48 | AV128: 47.78 | BB128: 10.6 | BC128: 12.83 | BD128: 12.84 | BE128: 12.84 | BK128: 7.45 | BO128: 25.39 | BP128: 24.31 | BS128: 43.96 | BT128: 43.96 | BV128: 57.93 | BW128: 66.08 | CF128: 11.15 | CO128: 15.48 | CP128: 16.26 | CQ128: 35.76 | CS128: 9.17 | CV128: 8.97 | CW128: 8.97 | CX128: 65.62 | CY128: 65.62 | ED128: 2.4 | EE128: 2 | EF128: 2.3 | EK128: 0.6 | EL128: 0 | EN128: -3.4 | EO128: 1.7 | EQ128: 4.5 | ER128: 5 | FI128: 1.7 | FL128: 1.3 | FM128: 2 | FP128: 1.7 | FQ128: 0 | FR128: 0 | FS128: 3.3 | FX128: 1.7 | GD128: 3.7 | GE128: 2.6 | GF128: 2.6 | GG128: 2.6 | GM128: 4.5 | GQ128: 2.5 | GR128: 2 | GU128: 3.2 | GV128: 3.2 | GX128: 1.9 | GY128: 1.9 | HH128: 2.9 | HQ128: 2.9 | HR128: 3.1 | HS128: 1.4 | HU128: 9.3 | HX128: 1.1 | HY128: 1 | HZ128: 1.4 | IA128: 1.4
A129: 28550 | B129: 14.77 | C129: 13.47 | D129: 13.48 | I129: 15.06 | J129: 9.64 | L129: 10.72 | M129: 42.04 | O129: 16.74 | P129: 16.28 | AG129: 11.85 | AJ129: 4.89 | AK129: 12.79 | AN129: 9.47 | AO129: 0.93 | AP129: 0.93 | AQ129: 39.93 | AV129: 48.68 | BB129: 10.69 | BC129: 12.98 | BD129: 13.06 | BE129: 13.06 | BK129: 7.49 | BO129: 25.64 | BP129: 24.66 | BS129: 44.6 | BT129: 44.6 | BV129: 58.52 | BW129: 66.75 | CF129: 11.54 | CO129: 15.74 | CP129: 16.44 | CQ129: 36.73 | CS129: 9.07 | CV129: 9.52 | CW129: 9.52 | CX129: 65.51 | CY129: 65.51 | ED129: 1.4 | EE129: 0.5 | EF129: 2.5 | EK129: 3.4 | EL129: 2.6 | EN129: 9.6 | EO129: -0.5 | EQ129: 2 | ER129: 1.2 | FI129: 1.7 | FL129: 1.2 | FM129: 0.8 | FP129: 0.5 | FQ129: 2.2 | FR129: 2.2 | FS129: 1.1 | FX129: 1.9 | GD129: 0.8 | GE129: 1.2 | GF129: 1.7 | GG129: 1.7 | GM129: 0.5 | GQ129: 1 | GR129: 1.4 | GU129: 1.5 | GV129: 1.5 | GX129: 1 | GY129: 1 | HH129: 3.5 | HQ129: 1.7 | HR129: 1.1 | HS129: 2.7 | HU129: -1.1 | HX129: 6.1 | HY129: 6.1 | HZ129: -0.2 | IA129: -0.2
A130: 28642 | B130: 15.08 | C130: 13.87 | D130: 13.66 | I130: 15.64 | J130: 10.18 | L130: 11.41 | M130: 42.27 | O130: 16.79 | P130: 16.4 | AG130: 11.98 | AJ130: 4.9 | AK130: 12.9 | AN130: 9.56 | AO130: 0.92 | AP130: 0.92 | AQ130: 40.92 | AV130: 49.35 | BB130: 10.87 | BC130: 13.2 | BD130: 13.27 | BE130: 13.27 | BK130: 7.81 | BO130: 26.2 | BP130: 24.96 | BS130: 45.87 | BT130: 45.87 | BV130: 59.01 | BW130: 67.31 | CF130: 11.78 | CO130: 15.92 | CP130: 16.67 | CQ130: 37.6 | CS130: 9.1 | CV130: 9.52 | CW130: 9.52 | CX130: 65.51 | CY130: 65.51 | ED130: 2.1 | EE130: 3 | EF130: 1.3 | EK130: 3.9 | EL130: 5.6 | EN130: 6.4 | EO130: 0.5 | EQ130: 0.3 | ER130: 0.7 | FI130: 1.1 | FL130: 0.2 | FM130: 0.9 | FP130: 1 | FQ130: -1.1 | FR130: -1.1 | FS130: 2.5 | FX130: 1.4 | GD130: 1.7 | GE130: 1.7 | GF130: 1.6 | GG130: 1.6 | GM130: 4.3 | GQ130: 2.2 | GR130: 1.2 | GU130: 2.8 | GV130: 2.8 | GX130: 0.8 | GY130: 0.8 | HH130: 2.1 | HQ130: 1.1 | HR130: 1.4 | HS130: 2.4 | HU130: 0.3 | HX130: 0 | HY130: 0 | HZ130: 0 | IA130: 0
A131: 28734 | B131: 15.35 | C131: 14.27 | D131: 13.88 | I131: 16.43 | J131: 11.17 | L131: 11.73 | M131: 41.65 | O131: 17.08 | P131: 16.59 | AG131: 12.24 | AJ131: 4.94 | AK131: 13.04 | AN131: 9.66 | AO131: 0.93 | AP131: 0.93 | AQ131: 41.37 | AV131: 50.24 | BB131: 11.11 | BC131: 13.38 | BD131: 13.57 | BE131: 13.57 | BK131: 7.85 | BO131: 26.51 | BP131: 25.25 | BS131: 46.5 | BT131: 46.5 | BV131: 59.69 | BW131: 68.09 | CF131: 12.14 | CO131: 16.27 | CP131: 17.03 | CQ131: 38.85 | CS131: 9.1 | CV131: 9.62 | CW131: 9.62 | CX131: 66.94 | CY131: 66.94 | ED131: 1.8 | EE131: 2.9 | EF131: 1.6 | EK131: 5.1 | EL131: 9.7 | EN131: 2.8 | EO131: -1.5 | EQ131: 1.7 | ER131: 1.2 | FI131: 2.2 | FL131: 0.8 | FM131: 1.1 | FP131: 1 | FQ131: 1.1 | FR131: 1.1 | FS131: 1.1 | FX131: 1.8 | GD131: 2.2 | GE131: 1.4 | GF131: 2.3 | GG131: 2.3 | GM131: 0.5 | GQ131: 1.2 | GR131: 1.2 | GU131: 1.4 | GV131: 1.4 | GX131: 1.2 | GY131: 1.2 | HH131: 3.1 | HQ131: 2.2 | HR131: 2.2 | HS131: 3.3 | HU131: 0 | HX131: 1.1 | HY131: 1.1 | HZ131: 2.2 | IA131: 2.2
A132: 28825 | B132: 15.7 | C132: 14.74 | D132: 13.99 | I132: 16.88 | J132: 11.54 | L132: 11.51 | M132: 42.97 | O132: 17.84 | P132: 17.2 | AG132: 12.57 | AJ132: 5.79 | AK132: 15.39 | AN132: 11.38 | AO132: 1.07 | AP132: 1.07 | AQ132: 42.36 | AV132: 51.02 | BB132: 11.32 | BC132: 13.64 | BD132: 13.86 | BE132: 13.86 | BK132: 8.08 | BO132: 26.89 | BP132: 25.43 | BS132: 47.35 | BT132: 47.35 | BV132: 59.89 | BW132: 68.31 | CF132: 12.5 | CO132: 16.8 | CP132: 17.66 | CQ132: 37.6 | CS132: 11 | CV132: 9.62 | CW132: 9.62 | CX132: 67.71 | CY132: 67.71 | ED132: 2.3 | EE132: 3.3 | EF132: 0.8 | EK132: 2.7 | EL132: 3.3 | EN132: -1.9 | EO132: 3.2 | EQ132: 4.4 | ER132: 3.7 | FI132: 2.7 | FL132: 17.2 | FM132: 18 | FP132: 17.8 | FQ132: 15.1 | FR132: 15.1 | FS132: 2.4 | FX132: 1.6 | GD132: 1.9 | GE132: 1.9 | GF132: 2.1 | GG132: 2.1 | GM132: 2.9 | GQ132: 1.4 | GR132: 0.7 | GU132: 1.8 | GV132: 1.8 | GX132: 0.3 | GY132: 0.3 | HH132: 3 | HQ132: 3.3 | HR132: 3.7 | HS132: -3.2 | HU132: 20.9 | HX132: 0 | HY132: 0 | HZ132: 1.2 | IA132: 1.2
A133: 28915 | B133: 15.97 | C133: 15.18 | D133: 14.33 | I133: 18.78 | J133: 13.54 | L133: 13.07 | M133: 43.6 | O133: 17.79 | P133: 17.35 | AG133: 12.89 | AJ133: 5.78 | AK133: 15.32 | AN133: 11.22 | AO133: 1.07 | AP133: 1.07 | AQ133: 42.54 | AV133: 51.24 | BB133: 11.58 | BC133: 13.79 | BD133: 14.15 | BE133: 14.15 | BK133: 8.46 | BO133: 27.33 | BP133: 25.6 | BS133: 48.09 | BT133: 48.09 | BV133: 60.48 | BW133: 68.98 | CF133: 12.89 | CO133: 17.2 | CP133: 18.02 | CQ133: 38.46 | CS133: 11.32 | CV133: 10.02 | CW133: 10.02 | CX133: 67.16 | CY133: 67.16 | ED133: 1.7 | EE133: 3 | EF133: 2.4 | EK133: 11.3 | EL133: 17.3 | EN133: 13.6 | EO133: 1.5 | EQ133: -0.3 | ER133: 0.9 | FI133: 2.5 | FL133: -0.2 | FM133: -0.5 | FP133: -1.4 | FQ133: 0 | FR133: 0 | FS133: 0.4 | FX133: 0.4 | GD133: 2.3 | GE133: 1.1 | GF133: 2.1 | GG133: 2.1 | GM133: 4.7 | GQ133: 1.6 | GR133: 0.7 | GU133: 1.6 | GV133: 1.6 | GX133: 1 | GY133: 1 | HH133: 3.1 | HQ133: 2.4 | HR133: 2 | HS133: 2.3 | HU133: 2.9 | HX133: 4.2 | HY133: 4.2 | HZ133: -0.8 | IA133: -0.8
A134: 29007 | B134: 16.39 | C134: 15.91 | D134: 14.44 | I134: 22.37 | J134: 17.61 | L134: 15.27 | M134: 44.3 | O134: 18.55 | P134: 17.66 | AG134: 13.29 | AJ134: 5.85 | AK134: 15.53 | AN134: 11.41 | AO134: 1.08 | AP134: 1.08 | AQ134: 43.8 | AV134: 52.92 | BB134: 11.85 | BC134: 14.05 | BD134: 14.4 | BE134: 14.4 | BK134: 8.62 | BO134: 27.64 | BP134: 25.6 | BS134: 48.09 | BT134: 48.09 | BV134: 60.87 | BW134: 69.43 | CF134: 13.22 | CO134: 17.72 | CP134: 18.66 | CQ134: 38.85 | CS134: 12.44 | CV134: 10.02 | CW134: 10.02 | CX134: 67.16 | CY134: 67.16 | ED134: 2.6 | EE134: 4.8 | EF134: 0.8 | EK134: 19.1 | EL134: 30.1 | EN134: 16.8 | EO134: 1.6 | EQ134: 4.3 | ER134: 1.8 | FI134: 3.1 | FL134: 1.2 | FM134: 1.4 | FP134: 1.7 | FQ134: 0.9 | FR134: 0.9 | FS134: 3 | FX134: 3.3 | GD134: 2.3 | GE134: 1.9 | GF134: 1.8 | GG134: 1.8 | GM134: 1.9 | GQ134: 1.1 | GR134: 0 | GU134: 0 | GV134: 0 | GX134: 0.6 | GY134: 0.7 | HH134: 2.6 | HQ134: 3 | HR134: 3.6 | HS134: 1 | HU134: 9.9 | HX134: 0 | HY134: 0 | HZ134: 0 | IA134: 0
A135: 29099 | B135: 16.78 | C135: 16.38 | D135: 14.8 | I135: 23.19 | J135: 18.63 | L135: 14.31 | M135: 46.17 | O135: 19.12 | P135: 17.85 | AG135: 13.77 | AJ135: 5.93 | AK135: 15.67 | AN135: 11.54 | AO135: 1.11 | AP135: 1.11 | AQ135: 44.43 | AV135: 54.59 | BB135: 12.29 | BC135: 14.27 | BD135: 14.7 | BE135: 14.7 | BK135: 8.93 | BO135: 28.26 | BP135: 26.25 | BS135: 49.47 | BT135: 49.47 | BV135: 61.26 | BW135: 69.88 | CF135: 13.47 | CO135: 18.43 | CP135: 19.33 | CQ135: 39.62 | CS135: 13.5 | CV135: 10.48 | CW135: 10.48 | CX135: 67.16 | CY135: 67.16 | ED135: 2.4 | EE135: 3 | EF135: 2.5 | EK135: 3.7 | EL135: 5.8 | EN135: -6.3 | EO135: 4.2 | EQ135: 3.1 | ER135: 1.1 | FI135: 3.6 | FL135: 1.4 | FM135: 0.9 | FP135: 1.1 | FQ135: 2.8 | FR135: 2.8 | FS135: 1.4 | FX135: 3.2 | GD135: 3.7 | GE135: 1.6 | GF135: 2.1 | GG135: 2.1 | GM135: 3.6 | GQ135: 2.2 | GR135: 2.5 | GU135: 2.9 | GV135: 2.9 | GX135: 0.6 | GY135: 0.6 | HH135: 1.9 | HQ135: 4 | HR135: 3.6 | HS135: 2 | HU135: 8.5 | HX135: 4.6 | HY135: 4.6 | HZ135: 0 | IA135: 0
... A138: 29373 | B138: 18.17 | C138: 17.87 | D138: 15.91 | I138: 25.05 | J138: 19.68 | L138: 16.73 | M138: 48.59 | O138: 21.21 | P138: 19.34 | AG138: 14.92 | AJ138: 6.22 | AK138: 16.45 | AN138: 12.22 | AO138: 1.16 | AP138: 1.16 | AQ138: 46.78 | AV138: 58.28 | BB138: 13.3 | BC138: 15.19 | BD138: 15.35 | BE138: 15.35 | BK138: 9.95 | BO138: 30.39 | BP138: 27.89 | BS138: 52.43 | BT138: 52.43 | BV138: 64.49 | BW138: 73.56 | CF138: 14.31 | CO138: 20.1 | CP138: 21.1 | CQ138: 41.16 | CS138: 16.65 | CV138: 11.66 | CW138: 11.66 | CX138: 69.58 | CY138: 69.58 | ED138: 2.8 | EE138: 2.5 | EF138: 1.9 | EK138: 2 | EL138: 0.7 | EN138: 6 | EO138: 5.2 | EQ138: 0.2 | ER138: 4.1 | FI138: 2.3 | FL138: 1.6 | FM138: 1.7 | FP138: 2 | FQ138: 1.8 | FR138: 1.8 | FS138: 3 | FX138: 3 | GD138: 4.6 | GE138: 2.2 | GF138: 1.7 | GG138: 1.7 | GM138: 2.1 | GQ138: 2.5 | GR138: 2.4 | GU138: 2 | GV138: 2 | GX138: 1.5 | GY138: 1.5 | HH138: 3 | HQ138: 4.8 | HR138: 5.4 | HS138: 0.7 | HU138: 14.4 | HX138: 0.5 | HY138: 0.5 | HZ138: 1.6 | IA138: 1.6
A139: 29465 | B139: 18.48 | C139: 18.24 | D139: 16.5 | E139: 14.52 | F139: 16.73 | G139: 21.3 | H139: 22.34 | I139: 24.93 | J139: 19.72 | K139: 26.46 | L139: 16.44 | M139: 47.34 | N139: 20.98 | O139: 21.64 | P139: 19.79 | Q139: 22.73 | R139: 16.48 | S139: 22.19 | X139: 21.28 | Y139: 18.98 | AC139: 23.24 | AE139: 26.75 | AG139: 15.28 | AH139: 16.32 | AI139: 14.06 | AJ139: 6.34 | AK139: 16.77 | AL139: 13.98 | AM139: 32.1 | AN139: 12.5 | AO139: 1.18 | AP139: 1.18 | AQ139: 47.32 | AV139: 59.28 | AW139: 71.06 | AX139: 52.74 | AY139: 57.28 | BB139: 13.45 | BC139: 15.6 | BD139: 15.72 | BE139: 15.72 | BI139: 18.82 | BK139: 10.33 | BM139: 10.46 | BO139: 31.45 | BP139: 28.77 | BQ139: 30.59 | BR139: 22.08 | BS139: 53.92 | BT139: 53.92 | BV139: 66.84 | BW139: 76.24 | BY139: 29.15 | CA139: 29.95 | CB139: 36.2 | CF139: 14.49 | CJ139: 21.51 | CL139: 7.8 | CM139: 7.42 | CN139: 10.91 | CO139: 20.14 | CP139: 21.01 | CQ139: 41.16 | CR139: 29.19 | CS139: 15.99 | CT139: 19.3 | CU139: 11.82 | CV139: 12.59 | CW139: 12.59 | CX139: 69.58 | CY139: 69.58 | CZ139: 17.61 | DA139: 77.21 | DD139: 2276.45 | DO139: 19.84 | ED139: 1.7 | EE139: 2.1 | EF139: 3.7 | EK139: -0.5 | EL139: 0.2 | EN139: -1.7 | EO139: -2.6 | EQ139: 2 | ER139: 2.3 | FI139: 2.4 | FL139: 1.9 | FM139: 1.9 | FP139: 2.3 | FQ139: 1.7 | FR139: 1.7 | FS139: 1.2 | FX139: 1.7 | GD139: 1.1 | GE139: 2.7 | GF139: 2.4 | GG139: 2.4 | GM139: 3.8 | GQ139: 3.5 | GR139: 3.2 | GU139: 2.8 | GV139: 2.8 | GX139: 3.6 | GY139: 3.6 | HH139: 1.3 | HQ139: 0.2 | HR139: -0.4 | HS139: 0 | HU139: -4 | HX139: 8 | HY139: 8 | HZ139: 0 | IA139: 0
A140: 29556 | B140: 18.87 | C140: 18.75 | D140: 17.12 | E140: 15.15 | F140: 17.34 | G140: 21.87 | H140: 22.86 | I140: 24.85 | J140: 19.58 | K140: 27.82 | L140: 15.15 | M140: 50.93 | N140: 21.43 | O140: 22.16 | P140: 20.75 | Q140: 23.98 | R140: 17.23 | S140: 22.85 | X140: 21.81 | Y140: 19.8 | AC140: 24.31 | AE140: 27.2 | AG140: 15.64 | AH140: 16.72 | AI140: 14.43 | AJ140: 6.4 | AK140: 17.02 | AL140: 14.1 | AM140: 32.91 | AN140: 12.66 | AO140: 1.18 | AP140: 1.18 | AQ140: 48.4 | AV140: 60.96 | AW140: 72.25 | AX140: 55.06 | AY140: 57.99 | BB140: 13.72 | BC140: 16.01 | BD140: 15.94 | BE140: 15.94 | BI140: 19.03 | BK140: 10.42 | BM140: 10.53 | BO140: 32.14 | BP140: 29.76 | BQ140: 31.72 | BR140: 22.61 | BS140: 56.14 | BT140: 56.14 | BV140: 66.84 | BW140: 76.24 | BY140: 30.47 | CA140: 31.94 | CB140: 37.41 | CF140: 14.94 | CJ140: 21.87 | CL140: 7.8 | CM140: 7.39 | CN140: 11.07 | CO140: 20.54 | CP140: 21.28 | CQ140: 41.93 | CR140: 29.78 | CS140: 16.4 | CT140: 19.58 | CU140: 11.82 | CV140: 13.39 | CW140: 13.39 | CX140: 69.47 | CY140: 69.47 | CZ140: 17.61 | DA140: 76.98 | DD140: 2233.46 | DO140: 19.77 | ED140: 2.1 | EE140: 2.8 | EF140: 3.8 | EG140: 4.3 | EH140: 3.6 | EI140: 2.7 | EJ140: 2.3 | EK140: -0.3 | EL140: -0.7 | EM140: 5.1 | EN140: -7.8 | EO140: 7.6 | EP140: 2.1 | EQ140: 2.4 | ER140: 4.9 | ES140: 5.5 | ET140: 4.6 | EU140: 3 | EZ140: 2.5 | FA140: 4.3 | FE140: 4.6 | FG140: 1.7 | FI140: 2.4 | FJ140: 2.5 | FK140: 2.6 | FL140: 0.9 | FM140: 1.5 | FN140: 0.9 | FO140: 2.5 | FP140: 1.3 | FQ140: 0 | FR140: 0 | FS140: 2.3 | FX140: 2.8 | FY140: 1.7 | FZ140: 4.4 | GA140: 1.2 | GD140: 2 | GE140: 2.6 | GF140: 1.4 | GG140: 1.4 | GK140: 1.1 | GM140: 0.9 | GO140: 0.7 | GQ140: 2.2 | GR140: 3.4 | GS140: 3.7 | GT140: 2.4 | GU140: 4.1 | GV140: 4.1 | GX140: 0 | GY140: 0 | HA140: 4.5 | HC140: 6.6 | HD140: 3.3 | HH140: 3.1 | HL140: 1.7 | HN140: 0 | HO140: -0.4 | HP140: 1.5 | HQ140: 2 | HR140: 1.3 | HS140: 1.9 | HT140: 2 | HU140: 2.6 | HV140: 1.5 | HW140: 0 | HX140: 6.4 | HY140: 6.4 | HZ140: -0.2 | IA140: -0.2 | IB140: 0 | IC140: -0.3 | IF140: -1.9 | IQ140: -0.4
A141: 29646 | B141: 19.33 | C141: 19.15 | D141: 17.6 | E141: 15.69 | F141: 17.72 | G141: 21.98 | H141: 24.01 | I141: 25.22 | J141: 19.55 | K141: 28.71 | L141: 15.59 | M141: 53.81 | N141: 21.98 | O141: 22.35 | P141: 21.32 | Q141: 24.66 | R141: 17.68 | S141: 23.26 | X141: 22.73 | Y141: 20.07 | AC141: 24.7 | AE141: 26.65 | AG141: 16.03 | AH141: 17.02 | AI141: 14.87 | AJ141: 6.54 | AK141: 17.45 | AL141: 14.22 | AM141: 33.08 | AN141: 13.09 | AO141: 1.19 | AP141: 1.19 | AQ141: 48.85 | AV141: 61.74 | AW141: 74.27 | AX141: 55.28 | AY141: 58.6 | BB141: 14.28 | BC141: 16.38 | BD141: 16.23 | BE141: 16.23 | BI141: 19.54 | BK141: 11.14 | BM141: 11.47 | BO141: 33.02 | BP141: 30.05 | BQ141: 32.03 | BR141: 22.79 | BS141: 56.67 | BT141: 56.67 | BV141: 67.52 | BW141: 77.02 | BY141: 31.58 | CA141: 32.9 | CB141: 38.41 | CF141: 15.33 | CJ141: 22.54 | CL141: 7.83 | CM141: 7.39 | CN141: 11.41 | CO141: 21.29 | CP141: 22.09 | CQ141: 42.9 | CR141: 29.88 | CS141: 17.61 | CT141: 19.9 | CU141: 12.5 | CV141: 13.54 | CW141: 13.54 | CX141: 69.47 | CY141: 69.47 | CZ141: 17.61 | DA141: 76.98 | DD141: 2240.94 | DO141: 19.52 | ED141: 2.4 | EE141: 2.1 | EF141: 2.8 | EG141: 3.6 | EH141: 2.2 | EI141: 0.5 | EJ141: 5 | EK141: 1.5 | EL141: -0.2 | EM141: 3.2 | EN141: 2.9 | EO141: 5.7 | EP141: 2.6 | EQ141: 0.9 | ER141: 2.7 | ES141: 2.8 | ET141: 2.6 | EU141: 1.8 | EZ141: 4.2 | FA141: 1.4 | FE141: 1.6 | FG141: -2 | FI141: 2.5 | FJ141: 1.8 | FK141: 3 | FL141: 2.2 | FM141: 2.5 | FN141: 0.9 | FO141: 0.5 | FP141: 3.4 | FQ141: 0.8 | FR141: 0.8 | FS141: 0.9 | FX141: 1.3 | FY141: 2.8 | FZ141: 0.4 | GA141: 1.1 | GD141: 4.1 | GE141: 2.3 | GF141: 1.8 | GG141: 1.8 | GK141: 2.7 | GM141: 6.9 | GO141: 8.9 | GQ141: 2.7 | GR141: 1 | GS141: 1 | GT141: 0.8 | GU141: 0.9 | GV141: 0.9 | GX141: 1 | GY141: 1 | HA141: 3.6 | HC141: 3 | HD141: 2.7 | HH141: 2.6 | HL141: 3.1 | HN141: 0.4 | HO141: 0 | HP141: 3.1 | HQ141: 3.7 | HR141: 3.8 | HS141: 2.3 | HT141: 0.3 | HU141: 7.4 | HV141: 1.6 | HW141: 5.8 | HX141: 1.1 | HY141: 1.1 | HZ141: 0 | IA141: 0 | IB141: 0 | IC141: 0 | IF141: 0.3 | IQ141: -1.3
A142: 29738 | B142: 19.76 | C142: 19.4 | D142: 18.01 | E142: 15.94 | F142: 18.18 | G142: 22.71 | H142: 24.82 | I142: 25.22 | J142: 19.45 | K142: 28.88 | L142: 15.82 | M142: 54.44 | N142: 22.05 | O142: 21.64 | P142: 21.93 | Q142: 25.26 | R142: 18.32 | S142: 23.92 | X142: 23.86 | Y142: 20.22 | AC142: 24.89 | AE142: 26.15 | AG142: 16.32 | AH142: 17.29 | AI142: 15.18 | AJ142: 6.65 | AK142: 17.73 | AL142: 14.3 | AM142: 33.78 | AN142: 13.34 | AO142: 1.21 | AP142: 1.21 | AQ142: 50.29 | AV142: 63.75 | AW142: 75.22 | AX142: 58.04 | AY142: 60.12 | BB142: 14.78 | BC142: 16.82 | BD142: 16.56 | BE142: 16.56 | BI142: 19.82 | BK142: 11.24 | BM142: 11.57 | BO142: 33.52 | BP142: 30.58 | BQ142: 32.47 | BR142: 23.45 | BS142: 57.84 | BT142: 57.84 | BV142: 68.7 | BW142: 78.36 | BY142: 32.14 | CA142: 32.9 | CB142: 38.91 | CF142: 15.66 | CJ142: 22.96 | CL142: 7.88 | CM142: 7.41 | CN142: 11.67 | CO142: 22.12 | CP142: 23.04 | CQ142: 43.67 | CR142: 30.52 | CS142: 19.3 | CT142: 20.26 | CU142: 12.59 | CV142: 13.54 | CW142: 13.54 | CX142: 68.81 | CY142: 68.81 | CZ142: 17.57 | DA142: 76.04 | DD142: 2244.67 | DO142: 19.7 | ED142: 2.2 | EE142: 1.3 | EF142: 2.3 | EG142: 1.6 | EH142: 2.6 | EI142: 3.3 | EJ142: 3.4 | EK142: 0 | EL142: -0.5 | EM142: 0.6 | EN142: 1.5 | EO142: 1.2 | EP142: 0.3 | EQ142: -3.2 | ER142: 2.9 | ES142: 2.4 | ET142: 3.6 | EU142: 2.8 | EZ142: 5 | FA142: 0.7 | FE142: 0.8 | FG142: -1.9 | FI142: 1.8 | FJ142: 1.6 | FK142: 2.1 | FL142: 1.7 | FM142: 1.6 | FN142: 0.6 | FO142: 2.1 | FP142: 1.9 | FQ142: 1.7 | FR142: 1.7 | FS142: 2.9 | FX142: 3.3 | FY142: 1.3 | FZ142: 5 | GA142: 2.6 | GD142: 3.5 | GE142: 2.7 | GF142: 2 | GG142: 2 | GK142: 1.4 | GM142: 0.9 | GO142: 0.9 | GQ142: 1.5 | GR142: 1.8 | GS142: 1.4 | GT142: 2.9 | GU142: 2.1 | GV142: 2.1 | GX142: 1.7 | GY142: 1.7 | HA142: 1.8 | HC142: 0 | HD142: 1.3 | HH142: 2.2 | HL142: 1.9 | HN142: 0.6 | HO142: 0.3 | HP142: 2.3 | HQ142: 3.9 | HR142: 4.3 | HS142: 1.8 | HT142: 2.1 | HU142: 9.6 | HV142: 1.8 | HW142: 0.7 | HX142: 0 | HY142: 0 | HZ142: -1 | IA142: -1 | IB142: -0.2 | IC142: -1.2 | IF142: 0.2 | IQ142: 0.9
A143: 29830 | B143: 20.14 | C143: 20.1 | D143: 18.45 | E143: 16.31 | F143: 18.6 | G143: 23.75 | H143: 24.77 | I143: 25.63 | J143: 19.51 | K143: 29.94 | L143: 16.59 | M143: 55.68 | N143: 22.15 | O143: 21.69 | P143: 22.54 | Q143: 25.83 | R143: 18.76 | S143: 24.58 | X143: 23.86 | Y143: 19.73 | AC143: 25.96 | AE143: 25.7 | AG143: 16.71 | AH143: 17.7 | AI143: 15.49 | AJ143: 6.85 | AK143: 18.27 | AL143: 14.69 | AM143: 34.07 | AN143: 13.78 | AO143: 1.26 | AP143: 1.26 | AQ143: 50.74 | AV143: 63.86 | AW143: 75.57 | AX143: 58.37 | AY143: 59.51 | BB143: 15.37 | BC143: 17.23 | BD143: 16.99 | BE143: 16.99 | BI143: 20.32 | BK143: 11.69 | BM143: 12.05 | BO143: 34.33 | BP143: 30.82 | BQ143: 32.72 | BR143: 23.67 | BS143: 59.11 | BT143: 59.11 | BV143: 69.87 | BW143: 79.7 | BY143: 32.76 | CA143: 34.18 | CB143: 39.48 | CF143: 15.97 | CJ143: 23.37 | CL143: 7.92 | CM143: 7.42 | CN143: 11.93 | CO143: 22.12 | CP143: 22.9 | CQ143: 44.73 | CR143: 30.47 | CS143: 18.14 | CT143: 20.7 | CU143: 12.69 | CV143: 14.01 | CW143: 14.01 | CX143: 70.35 | CY143: 70.35 | CZ143: 19.09 | DA143: 76.04 | DD143: 2235.33 | DO143: 19.74 | ED143: 1.9 | EE143: 3.6 | EF143: 2.4 | EG143: 2.3 | EH143: 2.3 | EI143: 4.6 | EJ143: -0.2 | EK143: 1.6 | EL143: 0.3 | EM143: 3.7 | EN143: 4.9 | EO143: 2.3 | EP143: 0.5 | EQ143: 0.2 | ER143: 2.8 | ES143: 2.3 | ET143: 2.4 | EU143: 2.8 | EZ143: 0 | FA143: -2.4 | FE143: 4.3 | FG143: -1.7 | FI143: 2.4 | FJ143: 2.4 | FK143: 2 | FL143: 3 | FM143: 3 | FN143: 2.7 | FO143: 0.9 | FP143: 3.3 | FQ143: 4.1 | FR143: 4.1 | FS143: 0.9 | FX143: 0.2 | FY143: 0.5 | FZ143: 0.6 | GA143: -1 | GD143: 4 | GE143: 2.4 | GF143: 2.6 | GG143: 2.6 | GK143: 2.5 | GM143: 4 | GO143: 4.1 | GQ143: 2.4 | GR143: 0.8 | GS143: 0.8 | GT143: 0.9 | GU143: 2.2 | GV143: 2.2 | GX143: 1.7 | GY143: 1.7 | HA143: 1.9 | HC143: 3.9 | HD143: 1.5 | HH143: 2 | HL143: 1.8 | HN143: 0.5 | HO143: 0.1 | HP143: 2.2 | HQ143: 0 | HR143: -0.6 | HS143: 2.4 | HT143: -0.2 | HU143: -6 | HV143: 2.2 | HW143: 0.8 | HX143: 3.5 | HY143: 3.5 | HZ143: 2.2 | IA143: 2.2 | IB143: 8.7 | IC143: 0 | IF143: -0.4 | IQ143: 0.2
A144: 29921 | B144: 20.99 | C144: 20.42 | D144: 19 | E144: 16.81 | F144: 19.17 | G144: 24.54 | H144: 25.82 | I144: 25.63 | J144: 19.51 | K144: 31.17 | L144: 15.62 | M144: 57.24 | N144: 22.43 | O144: 22.21 | P144: 23.34 | Q144: 26.67 | R144: 19.7 | S144: 24.74 | X144: 23.89 | Y144: 20.07 | AC144: 27.51 | AE144: 26.11 | AG144: 17.17 | AH144: 18.23 | AI144: 15.87 | AJ144: 6.97 | AK144: 18.55 | AL144: 15.02 | AM144: 34.19 | AN144: 13.99 | AO144: 1.28 | AP144: 1.28 | AQ144: 52.09 | AV144: 65.2 | AW144: 76.28 | AX144: 59.36 | AY144: 61.64 | BB144: 15.52 | BC144: 17.78 | BD144: 17.43 | BE144: 17.43 | BI144: 20.61 | BK144: 12.05 | BM144: 12.31 | BO144: 35.52 | BP144: 31.93 | BQ144: 34.04 | BR144: 24.25 | BS144: 60.17 | BT144: 60.17 | BV144: 71.34 | BW144: 81.37 | BY144: 33.32 | CA144: 35.66 | CB144: 40.27 | CF144: 16.48 | CJ144: 24.14 | CL144: 11.34 | CM144: 11.27 | CN144: 12.11 | CO144: 23.13 | CP144: 23.85 | CQ144: 46.56 | CR144: 31.11 | CS144: 18.95 | CT144: 21.46 | CU144: 13.48 | CV144: 15.31 | CW144: 15.31 | CX144: 73.76 | CY144: 73.76 | CZ144: 19.15 | DA144: 81.2 | DD144: 2313.83 | DO144: 23.13 | ED144: 4.2 | EE144: 1.6 | EF144: 3 | EG144: 3.1 | EH144: 3.1 | EI144: 3.3 | EJ144: 4.2 | EK144: 0 | EL144: 0 | EM144: 4.1 | EN144: -5.8 | EO144: 2.8 | EP144: 1.3 | EQ144: 2.4 | ER144: 3.5 | ES144: 3.3 | ET144: 5 | EU144: 0.7 | EZ144: 0.1 | FA144: 1.7 | FE144: 6 | FG144: 1.6 | FI144: 2.8 | FJ144: 3 | FK144: 2.5 | FL144: 1.8 | FM144: 1.5 | FN144: 2.2 | FO144: 0.4 | FP144: 1.5 | FQ144: 1.6 | FR144: 1.6 | FS144: 2.7 | FX144: 2.1 | FY144: 0.9 | FZ144: 1.7 | GA144: 3.6 | GD144: 1 | GE144: 3.2 | GF144: 2.6 | GG144: 2.6 | GK144: 1.4 | GM144: 3.1 | GO144: 2.2 | GQ144: 3.5 | GR144: 3.6 | GS144: 4 | GT144: 2.5 | GU144: 1.8 | GV144: 1.8 | GX144: 2.1 | GY144: 2.1 | HA144: 1.7 | HC144: 4.3 | HD144: 2 | HH144: 3.2 | HL144: 3.3 | HN144: 43.2 | HO144: 51.9 | HP144: 1.5 | HQ144: 4.6 | HR144: 4.1 | HS144: 4.1 | HT144: 2.1 | HU144: 4.5 | HV144: 3.7 | HW144: 6.2 | HX144: 9.3 | HY144: 9.3 | HZ144: 4.8 | IA144: 4.8 | IB144: 0.3 | IC144: 6.8 | IF144: 3.5 | IQ144: 17.2
A145: 30011 | B145: 21.38 | C145: 20.61 | D145: 19.89 | E145: 17.63 | F145: 19.85 | G145: 25.69 | H145: 27.68 | I145: 25.51 | J145: 19.17 | K145: 31.76 | L145: 15.55 | M145: 58.26 | N145: 22.84 | O145: 22.12 | P145: 24.41 | Q145: 25.87 | R145: 20.41 | S145: 25.32 | X145: 24.17 | Y145: 20.59 | AC145: 28.63 | AE145: 26.29 | AG145: 17.66 | AH145: 18.7 | AI145: 16.43 | AJ145: 7.16 | AK145: 19.16 | AL145: 15.59 | AM145: 35.46 | AN145: 14.43 | AO145: 1.3 | AP145: 1.3 | AQ145: 52.28 | AV145: 65.65 | AW145: 76.88 | AX145: 59.58 | AY145: 62.45 | BB145: 16.03 | BC145: 18.19 | BD145: 17.83 | BE145: 17.83 | BI145: 21.33 | BK145: 12.86 | BM145: 13.42 | BO145: 36.45 | BP145: 32.28 | BQ145: 34.35 | BR145: 24.65 | BS145: 60.7 | BT145: 60.7 | BV145: 72.32 | BW145: 82.49 | BY145: 34.09 | CA145: 36.3 | CB145: 41.63 | CE145: 15.39 | CF145: 16.75 | CJ145: 25.17 | CL145: 11.54 | CM145: 11.45 | CN145: 12.45 | CO145: 23.4 | CP145: 24.12 | CQ145: 47.52 | CR145: 30.61 | CS145: 18.58 | CT145: 21.78 | CU145: 14.39 | CV145: 15.55 | CW145: 15.55 | CX145: 75.96 | CY145: 75.96 | CZ145: 19.15 | DA145: 84.36 | DD145: 2282.05 | DI145: 23.81 | DJ145: 19.88 | DK145: 25.41 | DO145: 23.2 | DS145: 7.63 | DT145: 7.63 | ED145: 1.9 | EE145: 0.9 | EF145: 4.7 | EG145: 4.9 | EH145: 3.5 | EI145: 4.7 | EJ145: 7.2 | EK145: -0.5 | EL145: -1.7 | EM145: 1.9 | EN145: -0.4 | EO145: 1.8 | EP145: 1.8 | EQ145: -0.4 | ER145: 4.6 | ES145: -3 | ET145: 3.6 | EU145: 2.3 | EZ145: 1.2 | FA145: 2.6 | FE145: 4.1 | FG145: 0.7 | FI145: 2.9 | FJ145: 2.6 | FK145: 3.5 | FL145: 2.7 | FM145: 3.3 | FN145: 3.8 | FO145: 3.7 | FP145: 3.1 | FQ145: 1.6 | FR145: 1.6 | FS145: 0.4 | FX145: 0.7 | FY145: 0.8 | FZ145: 0.4 | GA145: 1.3 | GD145: 3.3 | GE145: 2.3 | GF145: 2.3 | GG145: 2.3 | GK145: 3.5 | GM145: 6.7 | GO145: 9 | GQ145: 2.6 | GR145: 1.1 | GS145: 0.9 | GT145: 1.6 | GU145: 0.9 | GV145: 0.9 | GX145: 1.4 | GY145: 1.4 | HA145: 2.3 | HC145: 1.8 | HD145: 3.4 | HH145: 1.6 | HL145: 4.3 | HN145: 1.8 | HO145: 1.6 | HP145: 2.8 | HQ145: 1.2 | HR145: 1.1 | HS145: 2.1 | HT145: -1.6 | HU145: -2 | HV145: 1.5 | HW145: 6.8 | HX145: 1.6 | HY145: 1.6 | HZ145: 3 | IA145: 3 | IB145: 0 | IC145: 3.9 | IF145: -1.4 | IQ145: 0.3
A146: 30103 | B146: 21.88 | C146: 20.9 | D146: 20.51 | E146: 17.98 | F146: 20.77 | G146: 26.89 | H146: 28.21 | I146: 26 | J146: 19.55 | K146: 32.65 | L146: 16.41 | M146: 58.1 | N146: 23.18 | O146: 21.74 | P146: 25.09 | Q146: 26.36 | R146: 21.61 | S146: 26.52 | X146: 24.6 | Y146: 20.67 | AC146: 28.58 | AE146: 26.79 | AG146: 18.12 | AH146: 19.11 | AI146: 16.89 | AJ146: 7.32 | AK146: 19.58 | AL146: 15.77 | AM146: 36.63 | AN146: 14.76 | AO146: 1.33 | AP146: 1.33 | AQ146: 53.63 | AV146: 67.65 | AW146: 78.89 | AX146: 63.22 | AY146: 60.93 | BB146: 16.77 | BC146: 18.78 | BD146: 18.45 | BE146: 18.45 | BI146: 22.22 | BK146: 13.36 | BM146: 14.07 | BO146: 37.58 | BP146: 33.75 | BQ146: 36.35 | BR146: 24.83 | BS146: 61.86 | BT146: 61.86 | BV146: 73 | BW146: 83.27 | BY146: 34.57 | CA146: 37.84 | CB146: 42.05 | CE146: 15.84 | CF146: 17.29 | CJ146: 25.94 | CL146: 11.86 | CM146: 11.75 | CN146: 12.95 | CO146: 24.1 | CP146: 24.94 | CQ146: 48.01 | CR146: 31.16 | CS146: 19.11 | CT146: 23.18 | CU146: 15.18 | CV146: 15.55 | CW146: 15.55 | CX146: 77.17 | CY146: 77.17 | CZ146: 20.8 | DA146: 84.36 | DD146: 2214.77 | DI146: 23.46 | DJ146: 20.22 | DK146: 24.38 | DO146: 23.99 | DS146: 7.63 | DT146: 7.63 | ED146: 2.3 | EE146: 1.4 | EF146: 3.1 | EG146: 2 | EH146: 4.6 | EI146: 4.7 | EJ146: 1.9 | EK146: 1.9 | EL146: 2 | EM146: 2.8 | EN146: 5.5 | EO146: -0.3 | EP146: 1.5 | EQ146: -1.7 | ER146: 2.8 | ES146: 1.9 | ET146: 5.9 | EU146: 4.7 | EZ146: 1.8 | FA146: 0.4 | FE146: -0.2 | FG146: 1.9 | FI146: 2.6 | FJ146: 2.2 | FK146: 2.8 | FL146: 2.2 | FM146: 2.2 | FN146: 1.2 | FO146: 3.3 | FP146: 2.3 | FQ146: 2.3 | FR146: 2.3 | FS146: 2.6 | FX146: 3 | FY146: 2.6 | FZ146: 6.1 | GA146: -2.4 | GD146: 4.6 | GE146: 3.2 | GF146: 3.5 | GG146: 3.5 | GK146: 4.2 | GM146: 3.9 | GO146: 4.8 | GQ146: 3.1 | GR146: 4.6 | GS146: 5.8 | GT146: 0.7 | GU146: 1.9 | GV146: 1.9 | GX146: 0.9 | GY146: 0.9 | HA146: 1.4 | HC146: 4.2 | HD146: 1 | HG146: 2.9 | HH146: 3.2 | HL146: 3.1 | HN146: 2.8 | HO146: 2.6 | HP146: 4 | HQ146: 3 | HR146: 3.4 | HS146: 1 | HT146: 1.8 | HU146: 2.9 | HV146: 6.4 | HW146: 5.5 | HX146: 0 | HY146: 0 | HZ146: 1.6 | IA146: 1.6 | IB146: 8.6 | IC146: 0 | IF146: -2.9 | IK146: -1.5 | IL146: 1.7 | IM146: -4.1 | IQ146: 3.4
A147: 30195 | B147: 22.65 | C147: 21.55 | D147: 20.95 | E147: 18.23 | F147: 21.34 | G147: 27.73 | H147: 28.64 | I147: 26.21 | J147: 19.68 | K147: 34.05 | L147: 15.62 | M147: 59.51 | N147: 23.29 | O147: 22.59 | P147: 25.9 | Q147: 26.78 | R147: 22.91 | S147: 27.5 | X147: 25 | Y147: 21.76 | AC147: 29.84 | AE147: 27.65 | AG147: 18.57 | AH147: 19.54 | AI147: 17.36 | AJ147: 7.64 | AK147: 20.33 | AL147: 16.09 | AM147: 37.44 | AN147: 15.41 | AO147: 1.41 | AP147: 1.41 | AQ147: 54.17 | AV147: 68.99 | AW147: 79.13 | AX147: 64.1 | AY147: 64.58 | BB147: 17.33 | BC147: 19.26 | BD147: 19.18 | BE147: 19.18 | BI147: 23.16 | BK147: 14.42 | BM147: 15.45 | BO147: 38.77 | BP147: 34.8 | BQ147: 37.48 | BR147: 25.63 | BS147: 62.18 | BT147: 62.18 | BV147: 74.18 | BW147: 84.61 | BY147: 35.34 | CA147: 39.06 | CB147: 43.2 | CE147: 16.27 | CF147: 18.31 | CJ147: 26.76 | CL147: 12.78 | CM147: 12.76 | CN147: 13.29 | CO147: 25.46 | CP147: 26.34 | CQ147: 49.26 | CR147: 31.75 | CS147: 21.45 | CT147: 23.74 | CU147: 15.88 | CV147: 16.39 | CW147: 16.39 | CX147: 79.36 | CY147: 79.36 | CZ147: 21.2 | DA147: 86.82 | DD147: 2196.08 | DI147: 23.9 | DJ147: 21.33 | DK147: 24.2 | DO147: 24.07 | DS147: 7.63 | DT147: 7.63 | ED147: 3.5 | EE147: 3.1 | EF147: 2.1 | EG147: 1.4 | EH147: 2.7 | EI147: 3.1 | EJ147: 1.5 | EK147: 0.8 | EL147: 0.7 | EM147: 4.3 | EN147: -4.8 | EO147: 2.4 | EP147: 0.5 | EQ147: 3.9 | ER147: 3.2 | ES147: 1.6 | ET147: 6 | EU147: 3.7 | EZ147: 1.6 | FA147: 5.3 | FE147: 4.4 | FG147: 3.2 | FI147: 2.5 | FJ147: 2.3 | FK147: 2.8 | FL147: 4.4 | FM147: 3.8 | FN147: 2 | FO147: 2.2 | FP147: 4.4 | FQ147: 6 | FR147: 6 | FS147: 1 | FX147: 2 | FY147: 0.3 | FZ147: 1.4 | GA147: 6 | GD147: 3.3 | GE147: 2.6 | GF147: 4 | GG147: 4 | GK147: 4.2 | GM147: 7.9 | GO147: 9.8 | GQ147: 3.2 | GR147: 3.1 | GS147: 3.1 | GT147: 3.2 | GU147: 0.5 | GV147: 0.5 | GX147: 1.6 | GY147: 1.6 | HA147: 2.2 | HC147: 3.2 | HD147: 2.7 | HG147: 2.7 | HH147: 5.9 | HL147: 3.2 | HN147: 7.8 | HO147: 8.6 | HP147: 2.6 | HQ147: 5.6 | HR147: 5.6 | HS147: 2.6 | HT147: 1.9 | HU147: 12.2 | HV147: 2.4 | HW147: 4.6 | HX147: 5.4 | HY147: 5.4 | HZ147: 2.8 | IA147: 2.8 | IB147: 1.9 | IC147: 2.9 | IF147: -0.8 | IK147: 1.9 | IL147: 5.5 | IM147: -0.7 | IQ147: 0.3
A148: 30286 | B148: 23.31 | C148: 22.06 | D148: 21.4 | E148: 18.45 | F148: 22.13 | G148: 27.84 | H148: 28.73 | I148: 26.7 | J148: 20.12 | K148: 34.52 | L148: 15.79 | M148: 59.19 | N148: 23.67 | O148: 23.97 | P148: 26.54 | Q148: 27.31 | R148: 23.81 | S148: 28.33 | X148: 25.8 | Y148: 22.4 | AC148: 31.06 | AE148: 27.88 | AG148: 19 | AH148: 19.98 | AI148: 17.8 | AJ148: 8.04 | AK148: 21.22 | AL148: 16.51 | AM148: 37.96 | AN148: 16.25 | AO148: 1.51 | AP148: 1.51 | AQ148: 55.43 | AV148: 70.45 | AW148: 80.55 | AX148: 65.87 | AY148: 65.49 | BB148: 17.68 | BC148: 19.81 | BD148: 19.58 | BE148: 19.58 | BI148: 23.48 | BK148: 15.43 | BM148: 16.53 | BO148: 40.21 | BP148: 35.85 | BQ148: 38.79 | BR148: 26.07 | BS148: 63.34 | BT148: 63.34 | BV148: 74.37 | BW148: 84.84 | BY148: 37.08 | CA148: 40.21 | CB148: 45.55 | CE148: 16.66 | CF148: 18.53 | CJ148: 27.33 | CL148: 13.65 | CM148: 13.71 | CN148: 13.45 | CO148: 25.82 | CP148: 26.61 | CQ148: 49.55 | CR148: 31.65 | CS148: 21.48 | CT148: 24.22 | CU148: 16.02 | CV148: 17.16 | CW148: 17.16 | CX148: 82.44 | CY148: 82.44 | CZ148: 21.54 | DA148: 90.8 | DD148: 2141.88 | DI148: 25.12 | DJ148: 23.12 | DK148: 24.73 | DO148: 25.04 | DS148: 7.63 | DT148: 7.63 | ED148: 2.9 | EE148: 2.4 | EF148: 2.1 | EG148: 1.2 | EH148: 3.7 | EI148: 0.4 | EJ148: 0.3 | EK148: 1.9 | EL148: 2.2 | EM148: 1.4 | EN148: 1.1 | EO148: -0.5 | EP148: 1.6 | EQ148: 6.1 | ER148: 2.5 | ES148: 2 | ET148: 3.9 | EU148: 3 | EZ148: 3.2 | FA148: 2.9 | FE148: 4.1 | FG148: 0.8 | FI148: 2.3 | FJ148: 2.3 | FK148: 2.5 | FL148: 5.2 | FM148: 4.4 | FN148: 2.6 | FO148: 1.4 | FP148: 5.5 | FQ148: 7.1 | FR148: 7.1 | FS148: 2.3 | FX148: 2.1 | FY148: 1.8 | FZ148: 2.8 | GA148: 1.4 | GD148: 2 | GE148: 2.9 | GF148: 2.1 | GG148: 2.1 | GK148: 1.4 | GM148: 7 | GO148: 7 | GQ148: 3.7 | GR148: 3 | GS148: 3.5 | GT148: 1.7 | GU148: 1.9 | GV148: 1.9 | GX148: 0.3 | GY148: 0.3 | HA148: 4.9 | HC148: 2.9 | HD148: 5.4 | HG148: 2.4 | HH148: 1.2 | HL148: 2.1 | HN148: 6.8 | HO148: 7.4 | HP148: 1.2 | HQ148: 1.4 | HR148: 1 | HS148: 0.6 | HT148: -0.3 | HU148: 0.1 | HV148: 2 | HW148: 0.9 | HX148: 4.7 | HY148: 4.7 | HZ148: 3.9 | IA148: 3.9 | IB148: 1.6 | IC148: 4.6 | IF148: -2.5 | IK148: 5.1 | IL148: 8.4 | IM148: 2.2 | IQ148: 4
A149: 30376 | B149: 23.81 | C149: 22.46 | D149: 22.13 | E149: 19.2 | F149: 22.44 | G149: 29.88 | H149: 30.5 | I149: 27.16 | J149: 20.36 | K149: 35.19 | L149: 16.14 | M149: 60.83 | N149: 24.43 | O149: 24.11 | P149: 26.89 | Q149: 27.35 | R149: 24.6 | S149: 29.27 | X149: 26.35 | Y149: 23.07 | AC149: 31.83 | AE149: 29.33 | AG149: 19.45 | AH149: 20.48 | AI149: 18.17 | AJ149: 8.16 | AK149: 21.5 | AL149: 16.75 | AM149: 38.25 | AN149: 16.5 | AO149: 1.54 | AP149: 1.54 | AQ149: 55.52 | AV149: 69.66 | AW149: 81.27 | AX149: 65.87 | AY149: 61.33 | BB149: 17.83 | BC149: 20.11 | BD149: 19.91 | BE149: 19.91 | BI149: 24.09 | BK149: 15.57 | BM149: 16.63 | BO149: 40.83 | BP149: 36.38 | BQ149: 39.42 | BR149: 26.29 | BS149: 64.83 | BT149: 64.83 | BV149: 74.47 | BW149: 84.95 | BY149: 38.05 | CA149: 41.75 | CB149: 47.7 | CE149: 17.67 | CF149: 18.89 | CJ149: 29.96 | CL149: 14.11 | CM149: 14.19 | CN149: 13.84 | CO149: 26.56 | CP149: 27.47 | CQ149: 51.09 | CR149: 31.7 | CS149: 22.35 | CT149: 24.94 | CU149: 16.09 | CV149: 17.29 | CW149: 17.29 | CX149: 82.55 | CY149: 82.55 | CZ149: 21.54 | DA149: 90.8 | DD149: 2108.24 | DI149: 26.42 | DJ149: 22.78 | DK149: 27.46 | DO149: 25.94 | DS149: 8.65 | DT149: 8.65 | ED149: 2.1 | EE149: 1.8 | EF149: 3.4 | EG149: 4.1 | EH149: 1.4 | EI149: 7.3 | EJ149: 6.2 | EK149: 1.7 | EL149: 1.2 | EM149: 1.9 | EN149: 2.2 | EO149: 2.8 | EP149: 3.2 | EQ149: 0.6 | ER149: 1.3 | ES149: 0.1 | ET149: 3.3 | EU149: 3.3 | EZ149: 2.1 | FA149: 3 | FE149: 2.5 | FG149: 5.2 | FI149: 2.4 | FJ149: 2.5 | FK149: 2.1 | FL149: 1.5 | FM149: 1.3 | FN149: 1.5 | FO149: 0.8 | FP149: 1.5 | FQ149: 2 | FR149: 2 | FS149: 0.2 | FX149: -1.1 | FY149: 0.9 | FZ149: 0 | GA149: -6.4 | GD149: 0.8 | GE149: 1.5 | GF149: 1.7 | GG149: 1.7 | GK149: 2.6 | GM149: 0.9 | GO149: 0.6 | GQ149: 1.5 | GR149: 1.5 | GS149: 1.6 | GT149: 0.8 | GU149: 2.4 | GV149: 2.4 | GX149: 0.1 | GY149: 0.1 | HA149: 2.6 | HC149: 3.8 | HD149: 4.7 | HG149: 6.1 | HH149: 1.9 | HL149: 9.6 | HN149: 3.4 | HO149: 3.5 | HP149: 2.9 | HQ149: 2.9 | HR149: 3.2 | HS149: 3.1 | HT149: 0.2 | HU149: 4.1 | HV149: 3 | HW149: 0.4 | HX149: 0.8 | HY149: 0.8 | HZ149: 0.1 | IA149: 0.1 | IB149: 0 | IC149: 0 | IF149: -1.6 | IK149: 5.2 | IL149: -1.5 | IM149: 11 | IQ149: 3.6
A150: 30468 | B150: 24.32 | C150: 23.44 | D150: 22.46 | E150: 19.32 | F150: 23.01 | G150: 30.03 | H150: 30.83 | I150: 29.43 | J150: 23.11 | K150: 35.28 | L150: 19.13 | M150: 60.52 | N150: 24.36 | O150: 24.73 | P150: 27.31 | Q150: 27.65 | R150: 25.61 | S150: 29.69 | X150: 26.87 | Y150: 22.89 | AC150: 31.88 | AE150: 30.24 | AG150: 19.75 | AH150: 20.78 | AI150: 18.45 | AJ150: 8.33 | AK150: 21.82 | AL150: 16.9 | AM150: 38.95 | AN150: 16.74 | AO150: 1.59 | AP150: 1.59 | AQ150: 57.41 | AV150: 74.35 | AW150: 83.16 | AX150: 69.95 | AY150: 70.56 | BB150: 18.22 | BC150: 20.41 | BD150: 20.28 | BE150: 20.28 | BI150: 24.48 | BK150: 15.57 | BM150: 16.6 | BO150: 41.33 | BP150: 37.03 | BQ150: 40.04 | BR150: 26.96 | BS150: 69.07 | BT150: 69.07 | BV150: 75.35 | BW150: 85.95 | BY150: 39.02 | CA150: 42.13 | CB150: 48.77 | CE150: 18.02 | CF150: 19.07 | CJ150: 30.52 | CL150: 14.45 | CM150: 14.57 | CN150: 13.94 | CO150: 26.56 | CP150: 27.47 | CQ150: 52.83 | CR150: 33.32 | CS150: 21.29 | CT150: 25.22 | CU150: 16.07 | CV150: 17.29 | CW150: 17.29 | CX150: 82.44 | CY150: 82.44 | CZ150: 21.54 | DA150: 90.8 | DD150: 2166.18 | DI150: 27.47 | DJ150: 22.81 | DK150: 29.39 | DO150: 25.51 | DS150: 8.65 | DT150: 8.65 | ED150: 2.1 | EE150: 4.4 | EF150: 1.5 | EG150: 0.6 | EH150: 2.5 | EI150: 0.5 | EJ150: 1.1 | EK150: 8.4 | EL150: 13.5 | EM150: 0.3 | EN150: 18.5 | EO150: -0.5 | EP150: -0.3 | EQ150: 2.6 | ER150: 1.6 | ES150: 1.1 | ET150: 4.1 | EU150: 1.4 | EZ150: 2 | FA150: -0.8 | FE150: 0.2 | FG150: 3.1 | FI150: 1.5 | FJ150: 1.5 | FK150: 1.5 | FL150: 2.1 | FM150: 1.5 | FN150: 0.9 | FO150: 1.8 | FP150: 1.5 | FQ150: 3.2 | FR150: 3.2 | FS150: 3.4 | FX150: 6.7 | FY150: 2.3 | FZ150: 6.2 | GA150: 15 | GD150: 2.2 | GE150: 1.5 | GF150: 1.9 | GG150: 1.9 | GK150: 1.6 | GM150: 0 | GO150: -0.2 | GQ150: 1.2 | GR150: 1.8 | GS150: 1.6 | GT150: 2.5 | GU150: 6.5 | GV150: 6.5 | GX150: 1.2 | GY150: 1.2 | HA150: 2.5 | HC150: 0.9 | HD150: 2.2 | HG150: 2 | HH150: 1 | HL150: 1.9 | HN150: 2.4 | HO150: 2.7 | HP150: 0.7 | HQ150: 0 | HR150: 0 | HS150: 3.4 | HT150: 5.1 | HU150: -4.7 | HV150: 1.1 | HW150: -0.1 | HX150: 0 | HY150: 0 | HZ150: -0.1 | IA150: -0.1 | IB150: 0 | IC150: 0 | IF150: 2.7 | IK150: 4 | IL150: 0.1 | IM150: 7 | IQ150: -1.7
A151: 30560 | B151: 24.74 | C151: 23.74 | D151: 22.83 | E151: 19.58 | F151: 23.5 | G151: 30.92 | H151: 30.45 | I151: 28.81 | J151: 23.01 | K151: 34.3 | L151: 16.11 | M151: 64.5 | N151: 24.8 | O151: 24.78 | P151: 27.46 | Q151: 27.76 | R151: 25.83 | S151: 29.4 | X151: 27.27 | Y151: 23.56 | AC151: 31.74 | AE151: 31.01 | AG151: 20.24 | AH151: 21.12 | AI151: 19.01 | AJ151: 8.51 | AK151: 22 | AL151: 17.08 | AM151: 39.24 | AN151: 16.88 | AO151: 1.67 | AP151: 1.67 | AQ151: 57.41 | AV151: 74.46 | AW151: 82.93 | AX151: 70.17 | AY151: 70.86 | BB151: 18.37 | BC151: 20.63 | BD151: 20.6 | BE151: 20.6 | BI151: 24.7 | BK151: 16.02 | BM151: 17.11 | BO151: 42.02 | BP151: 37.73 | BQ151: 40.92 | BR151: 27.27 | BS151: 70.12 | BT151: 70.12 | BV151: 75.84 | BW151: 86.51 | BY151: 40.42 | CA151: 43.42 | CB151: 49.69 | CE151: 18.71 | CF151: 19.64 | CJ151: 31.09 | CL151: 14.76 | CM151: 14.87 | CN151: 14.21 | CO151: 27.53 | CP151: 28.46 | CQ151: 53.5 | CR151: 34.5 | CS151: 22.88 | CT151: 25.62 | CU151: 16.58 | CV151: 17.78 | CW151: 17.78 | CX151: 82.44 | CY151: 82.44 | CZ151: 21.54 | DA151: 90.8 | DD151: 2175.52 | DI151: 27.56 | DJ151: 23.2 | DK151: 29.21 | DO151: 25.4 | DS151: 8.65 | DT151: 8.65 | ED151: 1.7 | EE151: 1.3 | EF151: 1.6 | EG151: 1.3 | EH151: 2.1 | EI151: 3 | EJ151: -1.2 | EK151: -2.1 | EL151: -0.4 | EM151: -2.8 | EN151: -15.8 | EO151: 6.6 | EP151: 1.8 | EQ151: 0.2 | ER151: 0.5 | ES151: 0.4 | ET151: 0.9 | EU151: -1 | EZ151: 1.5 | FA151: 2.9 | FE151: -0.4 | FG151: 2.5 | FI151: 2.5 | FJ151: 1.6 | FK151: 3 | FL151: 2.2 | FM151: 0.8 | FN151: 1.1 | FO151: 0.7 | FP151: 0.8 | FQ151: 5 | FR151: 5 | FS151: 0 | FX151: 0.1 | FY151: -0.3 | FZ151: 0.3 | GA151: 0.4 | GD151: 0.8 | GE151: 1.1 | GF151: 1.6 | GG151: 1.6 | GK151: 0.9 | GM151: 2.9 | GO151: 3.1 | GQ151: 1.7 | GR151: 1.9 | GS151: 2.2 | GT151: 1.1 | GU151: 1.5 | GV151: 1.5 | GX151: 0.7 | GY151: 0.7 | HA151: 3.6 | HC151: 3.1 | HD151: 1.9 | HG151: 3.8 | HH151: 3 | HL151: 1.9 | HN151: 2.1 | HO151: 2.1 | HP151: 1.9 | HQ151: 3.7 | HR151: 3.6 | HS151: 1.3 | HT151: 3.5 | HU151: 7.5 | HV151: 1.6 | HW151: 3.2 | HX151: 2.8 | HY151: 2.8 | HZ151: 0 | IA151: 0 | IB151: 0 | IC151: 0 | IF151: 0.4 | IK151: 0.3 | IL151: 1.7 | IM151: -0.6 | IQ151: -0.4
A152: 30651 | B152: 25.32 | C152: 24.03 | D152: 23.39 | E152: 20.14 | F152: 23.96 | G152: 31.86 | H152: 31.16 | I152: 28.23 | J152: 22.67 | K152: 34.22 | L152: 15.1 | M152: 61.3 | N152: 24.87 | O152: 25.11 | P152: 28.03 | Q152: 28.64 | R152: 25.68 | S152: 29.85 | X152: 26.47 | Y152: 24.24 | AC152: 32.56 | AE152: 32.24 | AG152: 20.6 | AH152: 21.52 | AI152: 19.39 | AJ152: 9.04 | AK152: 22.92 | AL152: 17.7 | AM152: 41.21 | AN152: 17.59 | AO152: 1.86 | AP152: 1.86 | AQ152: 58.67 | AV152: 74.24 | AW152: 83.52 | AX152: 69.07 | AY152: 71.17 | BB152: 18.72 | BC152: 21.15 | BD152: 20.93 | BE152: 20.93 | BI152: 25.16 | BK152: 16.74 | BM152: 17.88 | BO152: 43.21 | BP152: 38.37 | BQ152: 41.61 | BR152: 27.8 | BS152: 71.29 | BT152: 71.29 | BV152: 76.43 | BW152: 87.18 | BY152: 42.02 | CA152: 43.67 | CB152: 49.62 | CE152: 19.07 | CF152: 20.42 | CJ152: 31.29 | CL152: 15.15 | CM152: 15.27 | CN152: 14.6 | CO152: 28.28 | CP152: 29.09 | CQ152: 53.98 | CR152: 34.79 | CS152: 23.97 | CT152: 25.9 | CU152: 16.77 | CV152: 19.36 | CW152: 19.36 | CX152: 90.47 | CY152: 90.47 | CZ152: 23.89 | DA152: 99.24 | DD152: 2130.67 | DI152: 27.38 | DJ152: 24.49 | DK152: 27.64 | DO152: 25.4 | DS152: 8.65 | DT152: 8.65 | ED152: 2.3 | EE152: 1.2 | EF152: 2.5 | EG152: 2.9 | EH152: 2 | EI152: 3 | EJ152: 2.3 | EK152: -2 | EL152: -1.5 | EM152: -0.2 | EN152: -6.3 | EO152: -5 | EP152: 0.3 | EQ152: 1.3 | ER152: 2.1 | ES152: 3.2 | ET152: -0.6 | EU152: 1.5 | EZ152: -2.9 | FA152: 2.9 | FE152: 2.6 | FG152: 4 | FI152: 1.8 | FJ152: 1.9 | FK152: 2 | FL152: 6.2 | FM152: 4.2 | FN152: 3.6 | FO152: 5 | FP152: 4.2 | FQ152: 11.4 | FR152: 11.4 | FS152: 2.2 | FX152: -0.3 | FY152: 0.7 | FZ152: -1.6 | GA152: 0.4 | GD152: 1.9 | GE152: 2.5 | GF152: 1.6 | GG152: 1.6 | GK152: 1.9 | GM152: 4.5 | GO152: 4.5 | GQ152: 2.8 | GR152: 1.7 | GS152: 1.7 | GT152: 1.9 | GU152: 1.7 | GV152: 1.7 | GX152: 0.8 | GY152: 0.8 | HA152: 4 | HC152: 0.6 | HD152: -0.1 | HG152: 1.9 | HH152: 4 | HL152: 0.6 | HN152: 2.6 | HO152: 2.7 | HP152: 2.7 | HQ152: 2.7 | HR152: 2.2 | HS152: 0.9 | HT152: 0.8 | HU152: 4.8 | HV152: 1.1 | HW152: 1.1 | HX152: 8.9 | HY152: 8.9 | HZ152: 9.7 | IA152: 9.7 | IB152: 10.9 | IC152: 9.3 | IF152: -2.1 | IK152: -0.7 | IL152: 5.6 | IM152: -5.4 | IQ152: 0
A153: 30742 | B153: 25.21 | C153: 24.39 | D153: 24.01 | E153: 20.92 | F153: 24.19 | G153: 32.96 | H153: 32.84 | I153: 28.85 | J153: 23.04 | K153: 33.84 | L153: 16.88 | M153: 61.69 | N153: 24.94 | O153: 25.4 | P153: 28.18 | Q153: 28.98 | R153: 25.49 | S153: 30.14 | X153: 26.35 | Y153: 24.16 | AC153: 32.46 | AE153: 33.15 | AG153: 21.02 | AH153: 22.03 | AI153: 19.7 | AJ153: 9.2 | AK153: 23.42 | AL153: 18 | AM153: 41.56 | AN153: 18.05 | AO153: 1.87 | AP153: 1.87 | AQ153: 58.85 | AV153: 75.02 | AW153: 83.16 | AX153: 69.18 | AY153: 74.92 | BB153: 18.87 | BC153: 21.48 | BD153: 21.26 | BE153: 21.26 | BI153: 25.84 | BK153: 16.67 | BM153: 17.66 | BO153: 43.52 | BP153: 38.84 | BQ153: 42.11 | BR153: 28.02 | BS153: 72.03 | BT153: 72.03 | BV153: 76.92 | BW153: 87.74 | BY153: 42.15 | CA153: 44.31 | CB153: 50.41 | CE153: 19.91 | CF153: 20.63 | CJ153: 32.01 | CL153: 10.68 | CM153: 10.14 | CN153: 15.1 | CO153: 28.5 | CP153: 29.27 | CQ153: 54.46 | CR153: 35.33 | CS153: 23.85 | CT153: 26.42 | CU153: 16.91 | CV153: 19.57 | CW153: 19.58 | CX153: 90.58 | CY153: 90.58 | CZ153: 23.92 | DA153: 99.47 | DD153: 2091.42 | DI153: 27.82 | DJ153: 24.23 | DK153: 28.72 | DO153: 25.36 | DS153: 9.59 | DT153: 9.59 | ED153: -0.4 | EE153: 1.5 | EF153: 2.7 | EG153: 3.9 | EH153: 1 | EI153: 3.5 | EJ153: 5.4 | EK153: 2.2 | EL153: 1.6 | EM153: -1.1 | EN153: 11.8 | EO153: 0.6 | EP153: 0.3 | EQ153: 1.2 | ER153: 0.5 | ES153: 1.2 | ET153: -0.7 | EU153: 1 | EZ153: -0.5 | FA153: -0.3 | FE153: -0.3 | FG153: 2.8 | FI153: 2 | FJ153: 2.4 | FK153: 1.6 | FL153: 1.8 | FM153: 2.2 | FN153: 1.7 | FO153: 0.8 | FP153: 2.6 | FQ153: 0.5 | FR153: 0.5 | FS153: 0.3 | FX153: 1.1 | FY153: -0.4 | FZ153: 0.2 | GA153: 5.3 | GD153: 0.8 | GE153: 1.6 | GF153: 1.6 | GG153: 1.6 | GK153: 2.7 | GM153: -0.4 | GO153: -1.2 | GQ153: 0.7 | GR153: 1.2 | GS153: 1.2 | GT153: 0.8 | GU153: 1 | GV153: 1 | GX153: 0.6 | GY153: 0.6 | HA153: 0.3 | HC153: 1.5 | HD153: 1.6 | HG153: 4.4 | HH153: 1 | HL153: 2.3 | HN153: -29.5 | HO153: -33.6 | HP153: 3.4 | HQ153: 0.8 | HR153: 0.6 | HS153: 0.9 | HT153: 1.6 | HU153: -0.5 | HV153: 2 | HW153: 0.8 | HX153: 1.1 | HY153: 1.1 | HZ153: 0.1 | IA153: 0.1 | IB153: 0.1 | IC153: 0.2 | IF153: -1.8 | IK153: 1.6 | IL153: -1.1 | IM153: 3.9 | IQ153: -0.2
A154: 30834 | B154: 25.28 | C154: 24.32 | D154: 24.56 | E154: 21.39 | F154: 24.83 | G154: 34.01 | H154: 32.55 | I154: 28.93 | J154: 23.25 | K154: 34.13 | L154: 16.98 | M154: 59.58 | N154: 24.74 | O154: 25.45 | P154: 28.15 | Q154: 29.05 | R154: 25.31 | S154: 29.85 | X154: 26.35 | Y154: 24.73 | AC154: 32.71 | AE154: 34.28 | AG154: 21.48 | AH154: 22.53 | AI154: 20.17 | AJ154: 9.43 | AK154: 24.06 | AL154: 18.42 | AM154: 42.08 | AN154: 18.57 | AO154: 1.91 | AP154: 1.91 | AQ154: 60.57 | AV154: 77.37 | AW154: 85.66 | AX154: 71.61 | AY154: 76.84 | BB154: 19.28 | BC154: 21.96 | BD154: 21.74 | BE154: 21.74 | BI154: 26.35 | BK154: 16.45 | BM154: 17.33 | BO154: 43.83 | BP154: 39.14 | BQ154: 42.36 | BR154: 28.42 | BS154: 73.73 | BT154: 73.73 | BV154: 77.41 | BW154: 88.3 | BY154: 42.71 | CA154: 45.79 | CB154: 50.62 | CE154: 20.27 | CF154: 20.6 | CJ154: 32.58 | CL154: 8.3 | CM154: 7.41 | CN154: 15.36 | CO154: 29.03 | CP154: 29.91 | CQ154: 55.24 | CR154: 36.36 | CS154: 24.72 | CT154: 26.78 | CU154: 17.33 | CV154: 19.57 | CW154: 19.58 | CX154: 90.58 | CY154: 90.58 | CZ154: 23.92 | DA154: 99.47 | DD154: 2037.22 | DI154: 27.6 | DJ154: 24.23 | DK154: 28.36 | DO154: 26.16 | DS154: 9.59 | DT154: 9.59 | ED154: 0.3 | EE154: -0.3 | EF154: 2.3 | EG154: 2.2 | EH154: 2.6 | EI154: 3.2 | EJ154: -0.9 | EK154: 0.3 | EL154: 0.9 | EM154: 0.9 | EN154: 0.6 | EO154: -3.4 | EP154: -0.8 | EQ154: 0.2 | ER154: -0.1 | ES154: 0.2 | ET154: -0.7 | EU154: -1 | EZ154: 0 | FA154: 2.4 | FE154: 0.8 | FG154: 3.4 | FI154: 2.2 | FJ154: 2.3 | FK154: 2.4 | FL154: 2.5 | FM154: 2.7 | FN154: 2.3 | FO154: 1.3 | FP154: 2.9 | FQ154: 2.1 | FR154: 2.1 | FS154: 2.9 | FX154: 3.1 | FY154: 3 | FZ154: 3.5 | GA154: 2.6 | GD154: 2.2 | GE154: 2.2 | GF154: 2.3 | GG154: 2.3 | GK154: 2 | GM154: -1.3 | GO154: -1.9 | GQ154: 0.7 | GR154: 0.8 | GS154: 0.6 | GT154: 1.4 | GU154: 2.4 | GV154: 2.4 | GX154: 0.6 | GY154: 0.6 | HA154: 1.3 | HC154: 3.3 | HD154: 0.4 | HG154: 1.8 | HH154: -0.1 | HL154: 1.8 | HN154: -22.3 | HO154: -26.9 | HP154: 1.7 | HQ154: 1.9 | HR154: 2.2 | HS154: 1.4 | HT154: 2.9 | HU154: 3.6 | HV154: 1.4 | HW154: 2.5 | HX154: 0 | HY154: 0 | HZ154: 0 | IA154: 0 | IB154: 0 | IC154: 0 | IF154: -2.6 | IK154: -0.8 | IL154: 0 | IM154: -1.3 | IQ154: 3.2
A155: 30926 | B155: 25.59 | C155: 24.86 | D155: 24.97 | E155: 21.65 | F155: 25.29 | G155: 34.74 | H155: 33.31 | I155: 29.47 | J155: 23.76 | K155: 34.39 | L155: 17.85 | M155: 60.36 | N155: 24.94 | O155: 25.35 | P155: 28.11 | Q155: 29.05 | R155: 25.38 | S155: 30.06 | X155: 26.17 | Y155: 24.88 | AC155: 32.71 | AE155: 36.05 | AG155: 21.67 | AH155: 22.73 | AI155: 20.35 | AJ155: 9.57 | AK155: 24.31 | AL155: 18.72 | AM155: 42.55 | AN155: 18.78 | AO155: 1.95 | AP155: 1.95 | AQ155: 60.84 | AV155: 78.04 | AW155: 87.67 | AX155: 71.83 | AY155: 77.05 | BB155: 20.05 | BC155: 22.33 | BD155: 22.14 | BE155: 22.14 | BI155: 26.63 | BK155: 16.9 | BM155: 17.9 | BO155: 44.33 | BP155: 39.66 | BQ155: 42.98 | BR155: 28.68 | BS155: 73.3 | BT155: 73.3 | BV155: 77.01 | BW155: 87.85 | BY155: 42.85 | CA155: 45.66 | CB155: 51.62 | CE155: 20.33 | CF155: 21 | CJ155: 32.79 | CL155: 8.18 | CM155: 7.25 | CN155: 15.51 | CO155: 29.38 | CP155: 30.22 | CQ155: 55.81 | CR155: 37 | CS155: 24.94 | CT155: 27.02 | CU155: 17.82 | CV155: 20.04 | CW155: 20.04 | CX155: 90.58 | CY155: 90.58 | CZ155: 23.92 | DA155: 99.47 | DD155: 1997.97 | DI155: 28.08 | DJ155: 24.53 | DK155: 28.89 | DO155: 26.01 | DS155: 9.64 | DT155: 9.64 | ED155: 1.2 | EE155: 2.2 | EF155: 1.7 | EG155: 1.2 | EH155: 1.9 | EI155: 2.1 | EJ155: 2.3 | EK155: 1.9 | EL155: 2.2 | EM155: 0.8 | EN155: 5.1 | EO155: 1.3 | EP155: 0.8 | EQ155: -0.4 | ER155: -0.1 | ES155: 0 | ET155: 0.3 | EU155: 0.7 | EZ155: -0.7 | FA155: 0.6 | FE155: 0 | FG155: 5.2 | FI155: 0.9 | FJ155: 0.9 | FK155: 0.9 | FL155: 1.5 | FM155: 1 | FN155: 1.6 | FO155: 1.1 | FP155: 1.1 | FQ155: 2.1 | FR155: 2.1 | FS155: 0.4 | FX155: 0.9 | FY155: 2.3 | FZ155: 0.3 | GA155: 0.3 | GD155: 4 | GE155: 1.7 | GF155: 1.8 | GG155: 1.8 | GK155: 1.1 | GM155: 2.7 | GO155: 3.3 | GQ155: 1.1 | GR155: 1.3 | GS155: 1.5 | GT155: 0.9 | GU155: -0.6 | GV155: -0.6 | GX155: -0.5 | GY155: -0.5 | HA155: 0.3 | HC155: -0.3 | HD155: 2 | HG155: 0.3 | HH155: 1.9 | HL155: 0.6 | HN155: -1.4 | HO155: -2.2 | HP155: 1 | HQ155: 1.2 | HR155: 1 | HS155: 1 | HT155: 1.8 | HU155: 0.9 | HV155: 0.9 | HW155: 2.8 | HX155: 2.4 | HY155: 2.3 | HZ155: 0 | IA155: 0 | IB155: 0 | IC155: 0 | IF155: -1.9 | IK155: 1.7 | IL155: 1.2 | IM155: 1.9 | IQ155: -0.6
A156: 31017 | B156: 25.98 | C156: 25.23 | D156: 25.01 | E156: 21.46 | F156: 25.6 | G156: 35.06 | H156: 33.03 | I156: 29.76 | J156: 24.06 | K156: 34.9 | L156: 17.15 | M156: 62.08 | N156: 25.01 | O156: 26.73 | P156: 27.99 | Q156: 29.01 | R156: 24.93 | S156: 29.6 | X156: 26.23 | Y156: 25.18 | AC156: 33.68 | AE156: 36.83 | AG156: 22.07 | AH156: 23.1 | AI156: 20.73 | AJ156: 9.76 | AK156: 24.81 | AL156: 18.78 | AM156: 44.29 | AN156: 19.11 | AO156: 2 | AP156: 2 | AQ156: 62.37 | AV156: 80.49 | AW156: 90.4 | AX156: 74.59 | AY156: 78.36 | BB156: 20.14 | BC156: 22.7 | BD156: 22.54 | BE156: 22.54 | BI156: 26.56 | BK156: 17.33 | BM156: 18.39 | BO156: 44.77 | BP156: 40.48 | BQ156: 44.05 | BR156: 28.99 | BS156: 73.51 | BT156: 73.51 | BV156: 76.72 | BW156: 87.51 | BY156: 43.27 | CA156: 46.17 | CB156: 53.98 | CE156: 19.75 | CF156: 21.48 | CJ156: 33.35 | CL156: 8.29 | CM156: 7.32 | CN156: 15.96 | CO156: 29.64 | CP156: 30.45 | CQ156: 56.68 | CR156: 37.1 | CS156: 24.72 | CT156: 27.38 | CU156: 18.49 | CV156: 20.5 | CW156: 20.5 | CX156: 90.58 | CY156: 90.58 | CZ156: 23.92 | DA156: 99.47 | DD156: 1923.21 | DI156: 28.34 | DJ156: 25.79 | DK156: 28.18 | DO156: 26.66 | DS156: 9.64 | DT156: 9.64 | ED156: 1.5 | EE156: 1.5 | EF156: 0.2 | EG156: -0.9 | EH156: 1.2 | EI156: 0.9 | EJ156: -0.8 | EK156: 1 | EL156: 1.3 | EM156: 1.5 | EN156: -3.9 | EO156: 2.8 | EP156: 0.3 | EQ156: 5.4 | ER156: -0.4 | ES156: -0.1 | ET156: -1.8 | EU156: -1.5 | EZ156: 0.2 | FA156: 1.2 | FE156: 3 | FG156: 2.2 | FI156: 1.8 | FJ156: 1.6 | FK156: 1.9 | FL156: 2 | FM156: 2.1 | FN156: 0.3 | FO156: 4.1 | FP156: 1.8 | FQ156: 2.6 | FR156: 2.6 | FS156: 2.5 | FX156: 3.1 | FY156: 3.1 | FZ156: 3.8 | GA156: 1.7 | GD156: 0.4 | GE156: 1.7 | GF156: 1.8 | GG156: 1.8 | GK156: -0.3 | GM156: 2.5 | GO156: 2.7 | GQ156: 1 | GR156: 2.1 | GS156: 2.5 | GT156: 1.1 | GU156: 0.3 | GV156: 0.3 | GX156: -0.4 | GY156: -0.4 | HA156: 1 | HC156: 1.1 | HD156: 4.6 | HG156: -2.9 | HH156: 2.3 | HL156: 1.7 | HN156: 1.3 | HO156: 1 | HP156: 2.9 | HQ156: 0.9 | HR156: 0.8 | HS156: 1.6 | HT156: 0.3 | HU156: -0.9 | HV156: 1.3 | HW156: 3.8 | HX156: 2.3 | HY156: 2.3 | HZ156: 0 | IA156: 0 | IB156: 0 | IC156: 0 | IF156: -3.7 | IK156: 0.9 | IL156: 5.1 | IM156: -2.5 | IQ156: 2.5
A157: 31107 | B157: 26.33 | C157: 25.48 | D157: 25.34 | E157: 21.68 | F157: 25.94 | G157: 35.47 | H157: 33.65 | I157: 29.88 | J157: 23.93 | K157: 35.7 | L157: 16.93 | M157: 64.18 | N157: 25.49 | O157: 26.59 | P157: 28.53 | Q157: 29.85 | R157: 25.23 | S157: 29.73 | X157: 26.69 | Y157: 25.82 | AC157: 34.11 | AE157: 38.46 | AG157: 22.52 | AH157: 23.54 | AI157: 21.2 | AJ157: 9.87 | AK157: 25.09 | AL157: 19.01 | AM157: 44.35 | AN157: 19.38 | AO157: 2.02 | AP157: 2.02 | AQ157: 62.55 | AV157: 80.83 | AW157: 90.4 | AX157: 74.92 | AY157: 78.77 | BB157: 19.64 | BC157: 23.03 | BD157: 22.94 | BE157: 22.94 | BI157: 26.7 | BK157: 17.76 | BM157: 18.96 | BO157: 45.46 | BP157: 40.95 | BQ157: 44.55 | BR157: 29.39 | BS157: 73.41 | BT157: 73.41 | BV157: 76.33 | BW157: 87.07 | BY157: 43.61 | CA157: 47.65 | CB157: 54.84 | CE157: 20.24 | CF157: 21.78 | CJ157: 33.87 | CL157: 8.48 | CM157: 7.48 | CN157: 16.38 | CO157: 30.13 | CP157: 31.03 | CQ157: 58.32 | CR157: 37.4 | CS157: 25.22 | CT157: 27.66 | CU157: 18.56 | CV157: 20.59 | CW157: 20.6 | CX157: 93.32 | CY157: 93.32 | CZ157: 24.7 | DA157: 102.4 | DD157: 1876.48 | DI157: 29.04 | DJ157: 25.6 | DK157: 29.65 | DO157: 26.66 | DS157: 10.42 | DT157: 10.42 | ED157: 1.3 | EE157: 1 | EF157: 1.3 | EG157: 1 | EH157: 1.3 | EI157: 1.2 | EJ157: 1.9 | EK157: 0.4 | EL157: -0.5 | EM157: 2.3 | EN157: -1.3 | EO157: 3.4 | EP157: 1.9 | EQ157: -0.5 | ER157: 1.9 | ES157: 2.9 | ET157: 1.2 | EU157: 0.4 | EZ157: 1.8 | FA157: 2.5 | FE157: 1.3 | FG157: 4.4 | FI157: 2 | FJ157: 1.9 | FK157: 2.3 | FL157: 1.1 | FM157: 1.1 | FN157: 1.2 | FO157: 0.1 | FP157: 1.4 | FQ157: 1 | FR157: 1 | FS157: 0.3 | FX157: 0.4 | FY157: 0 | FZ157: 0.4 | GA157: 0.5 | GD157: -2.5 | GE157: 1.5 | GF157: 1.8 | GG157: 1.8 | GK157: 0.5 | GM157: 2.5 | GO157: 3.1 | GQ157: 1.5 | GR157: 1.2 | GS157: 1.1 | GT157: 1.4 | GU157: -0.1 | GV157: -0.1 | GX157: -0.5 | GY157: -0.5 | HA157: 0.8 | HC157: 3.2 | HD157: 1.6 | HG157: 2.5 | HH157: 1.4 | HL157: 1.6 | HN157: 2.3 | HO157: 2.2 | HP157: 2.6 | HQ157: 1.7 | HR157: 1.9 | HS157: 2.9 | HT157: 0.8 | HU157: 2 | HV157: 1 | HW157: 0.4 | HX157: 0.4 | HY157: 0.5 | HZ157: 3 | IA157: 3 | IB157: 3.3 | IC157: 2.9 | IF157: -2.4 | IK157: 2.5 | IL157: -0.7 | IM157: 5.2 | IQ157: 0
... A163: 31656 | B163: 30 | C163: 29.01 | D163: 29.54 | E163: 24.81 | F163: 31.22 | G163: 40.03 | H163: 37.99 | I163: 32.56 | J163: 25.62 | K163: 35.96 | L163: 20.45 | M163: 64.65 | N163: 27.49 | O163: 32.44 | P163: 31.46 | Q163: 32.76 | R163: 28.52 | S163: 31.09 | X163: 27.52 | Y163: 29.12 | AC163: 38.58 | AE163: 47.13 | AG163: 25.66 | AH163: 26.93 | AI163: 24.03 | AJ163: 11.34 | AK163: 28.32 | AL163: 22.08 | AM163: 46.2 | AN163: 22.16 | AO163: 2.4 | AP163: 2.4 | AQ163: 71.2 | AV163: 93.33 | AW163: 100.25 | AX163: 90.03 | AY163: 88.6 | BB163: 21.86 | BC163: 25.99 | BD163: 26.62 | BE163: 26.62 | BI163: 29.39 | BK163: 19.13 | BM163: 20.46 | BO163: 51.02 | BP163: 46.87 | BQ163: 50.68 | BR163: 34.23 | BS163: 86.54 | BT163: 86.54 | BV163: 84.94 | BW163: 96.89 | BY163: 52.73 | CA163: 53.93 | CB163: 61.05 | CE163: 23.65 | CF163: 24.04 | CJ163: 39.94 | CL163: 10.14 | CM163: 9.01 | CN163: 19.05 | CO163: 34.57 | CP163: 35.55 | CQ163: 71.62 | CR163: 40.59 | CS163: 26.41 | CT163: 32.15 | CU163: 20.4 | CV163: 23.53 | CW163: 23.53 | CX163: 98.71 | CY163: 98.71 | CZ163: 27.42 | DA163: 107.09 | DD163: 1999.84 | DI163: 34.39 | DJ163: 28.8 | DK163: 36.54 | DO163: 29.87 | DS163: 11.48 | DT163: 11.48 | ED163: 2.6 | EE163: 2.8 | EF163: 1.7 | EG163: 1.8 | EH163: 0.7 | EI163: 2 | EJ163: 4.2 | EK163: 2.6 | EL163: 1.5 | EM163: -1.5 | EN163: 11.8 | EO163: -1 | EP163: 1 | EQ163: 3.3 | ER163: 2.2 | ES163: 1.4 | ET163: 5.2 | EU163: 0.9 | EZ163: -0.8 | FA163: 0.1 | FE163: 1.2 | FG163: -5 | FI163: 1.8 | FJ163: 2 | FK163: 1.6 | FL163: 2.3 | FM163: 2.3 | FN163: 2.2 | FO163: 1.9 | FP163: 2.4 | FQ163: 2.6 | FR163: 2.6 | FS163: 0.5 | FX163: 1 | FY163: 1.6 | FZ163: 0.7 | GA163: 0.8 | GD163: 1 | GE163: 1.8 | GF163: 2.7 | GG163: 2.7 | GK163: 0.3 | GM163: 2 | GO163: 1.7 | GQ163: 1.6 | GR163: 1.8 | GS163: 2.3 | GT163: 0.7 | GU163: 1.7 | GV163: 1.7 | GX163: 2 | GY163: 2 | HA163: 3 | HC163: -0.2 | HD163: 1.5 | HG163: 1.9 | HH163: 2.2 | HL163: 1.6 | HN163: 3.4 | HO163: 3.4 | HP163: 3.4 | HQ163: 5.1 | HR163: 4.9 | HS163: 5.1 | HT163: 1.9 | HU163: 6.3 | HV163: 2.8 | HW163: 4.4 | HX163: 6.3 | HY163: 6.3 | HZ163: 0.8 | IA163: 0.8 | IB163: 3.9 | IC163: 0 | IF163: 1.8 | IK163: 5.2 | IL163: 5.1 | IM163: 5 | IQ163: 2.2
A164: 31747 | B164: 30.85 | C164: 29.45 | D164: 29.65 | E164: 24.94 | F164: 31.22 | G164: 40.86 | H164: 38.23 | I164: 33.27 | J164: 26.13 | K164: 37.61 | L164: 19.31 | M164: 65.43 | N164: 28.15 | O164: 37 | P164: 31.31 | Q164: 32.92 | R164: 27.36 | S164: 31.29 | X164: 27.37 | Y164: 30.67 | AC164: 39.79 | AE164: 46.18 | AG164: 26.24 | AH164: 27.74 | AI164: 24.44 | AJ164: 11.68 | AK164: 29.18 | AL164: 22.71 | AM164: 48.76 | AN164: 22.73 | AO164: 2.47 | AP164: 2.47 | AQ164: 74.18 | AV164: 95.34 | AW164: 102.62 | AX164: 92.02 | AY164: 89.62 | BB164: 22.04 | BC164: 26.43 | BD164: 27.21 | BE164: 27.21 | BI164: 29.75 | BK164: 19.49 | BM164: 20.75 | BO164: 52.15 | BP164: 47.86 | BQ164: 51.8 | BR164: 34.85 | BS164: 87.71 | BT164: 87.71 | BV164: 86.21 | BW164: 98.34 | BY164: 57.39 | CA164: 53.81 | CB164: 61.55 | CE164: 23.78 | CF164: 24.46 | CI164: 45.28 | CJ164: 44.16 | CK164: 51.94 | CL164: 11.13 | CM164: 10.08 | CN164: 19.46 | CO164: 36.15 | CP164: 37.27 | CQ164: 76.44 | CR164: 41.43 | CS164: 28.18 | CT164: 32.83 | CU164: 20.61 | CV164: 24 | CW164: 24 | CX164: 100.91 | CY164: 100.91 | CZ164: 28.96 | DA164: 108.49 | DD164: 2052.17 | DI164: 34.13 | DJ164: 29.99 | DK164: 34.93 | DO164: 30.6 | DP164: 16.05 | DS164: 11.48 | DT164: 11.48 | ED164: 2.8 | EE164: 1.5 | EF164: 0.4 | EG164: 0.5 | EH164: 0 | EI164: 2.1 | EJ164: 0.6 | EK164: 2.2 | EL164: 2 | EM164: 4.6 | EN164: -5.6 | EO164: 1.2 | EP164: 2.4 | EQ164: 14.1 | ER164: -0.5 | ES164: 0.5 | ET164: -4.1 | EU164: 0.6 | EZ164: -0.5 | FA164: 5.3 | FE164: 3.1 | FG164: -2 | FI164: 2.3 | FJ164: 3 | FK164: 1.7 | FL164: 3 | FM164: 3 | FN164: 2.9 | FO164: 5.5 | FP164: 2.6 | FQ164: 2.9 | FR164: 2.9 | FS164: 4.2 | FX164: 2.2 | FY164: 2.4 | FZ164: 2.2 | GA164: 1.2 | GD164: 0.8 | GE164: 1.7 | GF164: 2.2 | GG164: 2.2 | GK164: 1.2 | GM164: 1.9 | GO164: 1.4 | GQ164: 2.2 | GR164: 2.1 | GS164: 2.2 | GT164: 1.8 | GU164: 1.4 | GV164: 1.4 | GX164: 1.5 | GY164: 1.5 | HA164: 8.8 | HC164: -0.2 | HD164: 0.8 | HG164: 0.5 | HH164: 1.7 | HL164: 10.6 | HN164: 9.8 | HO164: 11.9 | HP164: 2.2 | HQ164: 4.6 | HR164: 4.8 | HS164: 6.7 | HT164: 2.1 | HU164: 6.7 | HV164: 2.1 | HW164: 1 | HX164: 2 | HY164: 2 | HZ164: 2.2 | IA164: 2.2 | IB164: 5.6 | IC164: 1.3 | IF164: 2.6 | IK164: -0.8 | IL164: 4.1 | IM164: -4.4 | IQ164: 2.4
A165: 31837 | B165: 31.47 | C165: 29.78 | D165: 30.05 | E165: 25.54 | F165: 31.38 | G165: 41.33 | H165: 38.66 | I165: 33.76 | J165: 26.4 | K165: 37.06 | L165: 20.52 | M165: 67.69 | N165: 28.18 | O165: 37.57 | P165: 31.88 | Q165: 33.14 | R165: 28.78 | S165: 31.66 | X165: 27.76 | Y165: 31.42 | AC165: 40.71 | AE165: 46.54 | AG165: 26.73 | AH165: 28.17 | AI165: 24.97 | AJ165: 12 | AK165: 29.96 | AL165: 23.22 | AM165: 49.57 | AN165: 23.41 | AO165: 2.55 | AP165: 2.55 | AQ165: 74.63 | AV165: 95.57 | AW165: 103.21 | AX165: 92.13 | AY165: 89.92 | BB165: 22.45 | BC165: 26.91 | BD165: 27.83 | BE165: 27.83 | BI165: 30.11 | BK165: 19.63 | BM165: 20.87 | BO165: 52.71 | BP165: 47.45 | BQ165: 50.99 | BR165: 35.29 | BS165: 87.92 | BT165: 87.92 | BV165: 87.19 | BW165: 99.46 | BY165: 59.06 | CA165: 55.54 | CB165: 63.26 | CE165: 24.89 | CF165: 24.67 | CI165: 47.28 | CJ165: 46.37 | CK165: 53.08 | CL165: 11.54 | CM165: 10.48 | CN165: 20.07 | CO165: 37.16 | CP165: 38.4 | CQ165: 78.85 | CR165: 41.72 | CS165: 28.77 | CT165: 33.79 | CU165: 20.71 | CV165: 24.24 | CW165: 24.24 | CX165: 101.57 | CY165: 101.57 | CZ165: 28.96 | DA165: 109.31 | DD165: 2115.71 | DI165: 34.91 | DJ165: 30.37 | DK165: 36.1 | DO165: 30.7 | DP165: 16.97 | DS165: 12.65 | DT165: 12.65 | ED165: 2 | EE165: 1.1 | EF165: 1.3 | EG165: 2.4 | EH165: 0.5 | EI165: 1.2 | EJ165: 1.1 | EK165: 1.5 | EL165: 1 | EM165: -1.5 | EN165: 6.3 | EO165: 3.5 | EP165: 0.1 | EQ165: 1.5 | ER165: 1.8 | ES165: 0.7 | ET165: 5.2 | EU165: 1.2 | EZ165: 1.4 | FA165: 2.4 | FE165: 2.3 | FG165: 0.8 | FI165: 1.9 | FJ165: 1.6 | FK165: 2.2 | FL165: 2.7 | FM165: 2.7 | FN165: 2.2 | FO165: 1.7 | FP165: 3 | FQ165: 3.2 | FR165: 3.2 | FS165: 0.6 | FX165: 0.2 | FY165: 0.6 | FZ165: 0.1 | GA165: 0.3 | GD165: 1.9 | GE165: 1.8 | GF165: 2.3 | GG165: 2.3 | GK165: 1.2 | GM165: 0.7 | GO165: 0.6 | GQ165: 1.1 | GR165: -0.9 | GS165: -1.6 | GT165: 1.3 | GU165: 0.2 | GV165: 0.2 | GX165: 1.1 | GY165: 1.1 | HA165: 2.9 | HC165: 3.2 | HD165: 2.8 | HG165: 4.7 | HH165: 0.9 | HK165: 4.4 | HL165: 5 | HM165: 2.2 | HN165: 3.7 | HO165: 4 | HP165: 3.1 | HQ165: 2.8 | HR165: 3 | HS165: 3.2 | HT165: 0.7 | HU165: 2.1 | HV165: 2.9 | HW165: 0.5 | HX165: 1 | HY165: 1 | HZ165: 0.7 | IA165: 0.7 | IB165: 0 | IC165: 0.8 | IF165: 3.1 | IK165: 2.3 | IL165: 1.3 | IM165: 3.3 | IQ165: 0.3
A166: 31929 | B166: 31.93 | C166: 29.82 | D166: 30.53 | E166: 25.97 | F166: 31.68 | G166: 42.54 | H166: 39.76 | I166: 34.21 | J166: 26.67 | K166: 36.89 | L166: 20.99 | M166: 70.27 | N166: 28.7 | O166: 37.72 | P166: 32.11 | Q166: 33.56 | R166: 28.48 | S166: 32.2 | X166: 27.83 | Y166: 32.09 | AC166: 40.62 | AE166: 44.73 | AG166: 27.16 | AH166: 28.54 | AI166: 25.43 | AJ166: 12.29 | AK166: 30.67 | AL166: 23.93 | AM166: 50.15 | AN166: 24.04 | AO166: 2.62 | AP166: 2.62 | AQ166: 76.88 | AV166: 97.24 | AW166: 105.59 | AX166: 93.67 | AY166: 90.94 | BB166: 23.05 | BC166: 27.43 | BD166: 28.48 | BE166: 28.48 | BI166: 30.5 | BK166: 19.67 | BM166: 20.92 | BO166: 53.9 | BP166: 49.45 | BQ166: 53.31 | BR166: 36.31 | BS166: 90.89 | BT166: 90.89 | BV166: 88.86 | BW166: 101.36 | BY166: 61.77 | CA166: 55.92 | CB166: 64.47 | CE166: 25.21 | CF166: 25.3 | CI166: 46.23 | CJ166: 44.98 | CK166: 53.74 | CL166: 11.97 | CM166: 10.89 | CN166: 20.62 | CO166: 37.52 | CP166: 38.71 | CQ166: 80.4 | CR166: 42.46 | CS166: 27.93 | CT166: 34.63 | CU166: 21.55 | CV166: 24.3 | CW166: 24.31 | CX166: 101.9 | CY166: 101.9 | CZ166: 28.96 | DA166: 109.67 | DD166: 2153.09 | DI166: 34.61 | DJ166: 29.57 | DK166: 36.41 | DO166: 31.14 | DP166: 17.19 | DS166: 12.65 | DT166: 12.65 | ED166: 1.5 | EE166: 0.1 | EF166: 1.6 | EG166: 1.7 | EH166: 1 | EI166: 2.9 | EJ166: 2.8 | EK166: 1.3 | EL166: 1 | EM166: -0.5 | EN166: 2.3 | EO166: 3.8 | EP166: 1.8 | EQ166: 0.4 | ER166: 0.7 | ES166: 1.3 | ET166: -1 | EU166: 1.7 | EZ166: 0.3 | FA166: 2.1 | FE166: -0.2 | FG166: -3.9 | FI166: 1.6 | FJ166: 1.3 | FK166: 1.8 | FL166: 2.4 | FM166: 2.4 | FN166: 3.1 | FO166: 1.2 | FP166: 2.7 | FQ166: 2.7 | FR166: 2.7 | FS166: 3 | FX166: 1.7 | FY166: 2.3 | FZ166: 1.7 | GA166: 1.1 | GD166: 2.7 | GE166: 1.9 | GF166: 2.3 | GG166: 2.3 | GK166: 1.3 | GM166: 0.2 | GO166: 0.2 | GQ166: 2.3 | GR166: 4.2 | GS166: 4.5 | GT166: 2.9 | GU166: 3.4 | GV166: 3.4 | GX166: 1.9 | GY166: 1.9 | HA166: 4.6 | HC166: 0.7 | HD166: 1.9 | HG166: 1.3 | HH166: 2.6 | HK166: -2.2 | HL166: -3 | HM166: 1.2 | HN166: 3.7 | HO166: 3.9 | HP166: 2.7 | HQ166: 1 | HR166: 0.8 | HS166: 2 | HT166: 1.8 | HU166: -2.9 | HV166: 2.5 | HW166: 4.1 | HX166: 0.2 | HY166: 0.3 | HZ166: 0.3 | IA166: 0.3 | IB166: 0 | IC166: 0.3 | IF166: 1.8 | IK166: -0.9 | IL166: -2.6 | IM166: 0.9 | IQ166: 1.4
A167: 32021 | B167: 32.47 | C167: 30.25 | D167: 30.9 | E167: 25.85 | F167: 32.44 | G167: 43.48 | H167: 40.52 | I167: 34.67 | J167: 27.25 | K167: 37.1 | L167: 21.41 | M167: 68.16 | N167: 29.39 | O167: 38.62 | P167: 32.76 | Q167: 34.13 | R167: 29.19 | S167: 33.35 | X167: 27.92 | Y167: 32.69 | AC167: 41.88 | AE167: 44 | AG167: 27.55 | AH167: 29.04 | AI167: 25.75 | AJ167: 12.48 | AK167: 31.2 | AL167: 24.29 | AM167: 50.85 | AN167: 24.47 | AO167: 2.64 | AP167: 2.64 | AQ167: 77.51 | AV167: 97.91 | AW167: 105.11 | AX167: 94.01 | AY167: 93.37 | BB167: 23.43 | BC167: 27.91 | BD167: 29.43 | BE167: 29.43 | BI167: 30.97 | BK167: 20.49 | BM167: 21.9 | BO167: 54.9 | BP167: 49.8 | BQ167: 53.43 | BR167: 37.15 | BS167: 92.37 | BT167: 92.37 | BV167: 89.25 | BW167: 101.8 | BY167: 61.63 | CA167: 56.05 | CB167: 65.26 | CE167: 25.93 | CF167: 25.82 | CI167: 44.33 | CJ167: 42.67 | CK167: 53.86 | CL167: 12.26 | CM167: 11.13 | CN167: 21.24 | CO167: 38.22 | CP167: 39.44 | CQ167: 82.32 | CR167: 43.24 | CS167: 27.78 | CT167: 35.11 | CU167: 22.74 | CV167: 25.36 | CW167: 25.36 | CX167: 107.61 | CY167: 107.61 | CZ167: 29.74 | DA167: 116.11 | DD167: 2134.4 | DI167: 36.04 | DJ167: 30.86 | DK167: 37.79 | DO167: 31.32 | DP167: 17.61 | DS167: 12.65 | DT167: 12.65 | ED167: 1.7 | EE167: 1.4 | EF167: 1.2 | EG167: -0.5 | EH167: 2.4 | EI167: 2.2 | EJ167: 1.9 | EK167: 1.3 | EL167: 2.2 | EM167: 0.6 | EN167: 2 | EO167: -3 | EP167: 2.4 | EQ167: 2.4 | ER167: 2 | ES167: 1.7 | ET167: 2.5 | EU167: 3.6 | EZ167: 0.3 | FA167: 1.9 | FE167: 3.1 | FG167: -1.6 | FI167: 1.4 | FJ167: 1.8 | FK167: 1.3 | FL167: 1.5 | FM167: 1.7 | FN167: 1.5 | FO167: 1.4 | FP167: 1.8 | FQ167: 0.8 | FR167: 0.8 | FS167: 0.8 | FX167: 0.7 | FY167: -0.5 | FZ167: 0.4 | GA167: 2.7 | GD167: 1.6 | GE167: 1.7 | GF167: 3.3 | GG167: 3.3 | GK167: 1.5 | GM167: 4.2 | GO167: 4.7 | GQ167: 1.9 | GR167: 0.7 | GS167: 0.2 | GT167: 2.3 | GU167: 1.6 | GV167: 1.6 | GX167: 0.4 | GY167: 0.4 | HA167: -0.2 | HC167: 0.2 | HD167: 1.2 | HG167: 2.9 | HH167: 2.1 | HK167: -4.1 | HL167: -5.1 | HM167: 0.2 | HN167: 2.4 | HO167: 2.2 | HP167: 3 | HQ167: 1.9 | HR167: 1.9 | HS167: 2.4 | HT167: 1.8 | HU167: -0.5 | HV167: 1.4 | HW167: 5.5 | HX167: 4.4 | HY167: 4.3 | HZ167: 5.6 | IA167: 5.6 | IB167: 2.7 | IC167: 5.9 | IF167: -0.9 | IK167: 4.1 | IL167: 4.4 | IM167: 3.8 | IQ167: 0.6
A168: 32112 | B168: 33.05 | C168: 30.65 | D168: 31.05 | E168: 26.04 | F168: 32.78 | G168: 42.17 | H168: 41 | I168: 34.87 | J168: 27.22 | K168: 37.74 | L168: 20.32 | M168: 68.47 | N168: 29.7 | O168: 41 | P168: 33.37 | Q168: 34.47 | R168: 30.28 | S168: 34.13 | X168: 27.92 | Y168: 33.3 | AC168: 42.07 | AE168: 44.18 | AG168: 28.01 | AH168: 29.45 | AI168: 26.18 | AJ168: 12.69 | AK168: 31.66 | AL168: 24.77 | AM168: 50.79 | AN168: 24.99 | AO168: 2.7 | AP168: 2.7 | AQ168: 79.76 | AV168: 99.58 | AW168: 106.54 | AX168: 96.21 | AY168: 94.48 | BB168: 23.85 | BC168: 28.24 | BD168: 30.12 | BE168: 30.12 | BI168: 31.19 | BK168: 20.71 | BM168: 22.07 | BO168: 55.78 | BP168: 50.68 | BQ168: 54.18 | BR168: 38.26 | BS168: 93.32 | BT168: 93.32 | BV168: 90.13 | BW168: 102.81 | BY168: 63.79 | CA168: 58.1 | CB168: 65.55 | CE168: 26.09 | CF168: 26.09 | CI168: 42.17 | CJ168: 39.99 | CK168: 54.1 | CL168: 13.14 | CM168: 12.08 | CN168: 21.53 | CO168: 39.23 | CP168: 40.52 | CQ168: 84.54 | CR168: 43.88 | CS168: 28.93 | CT168: 35.55 | CU168: 23.09 | CV168: 25.7 | CW168: 25.7 | CX168: 109.59 | CY168: 109.59 | CZ168: 29.74 | DA168: 118.69 | DD168: 2119.45 | DI168: 36.39 | DJ168: 32.43 | DK168: 36.72 | DO168: 32.08 | DP168: 17.74 | DS168: 12.65 | DT168: 12.65 | ED168: 1.8 | EE168: 1.3 | EF168: 0.5 | EG168: 0.7 | EH168: 1 | EI168: -3 | EJ168: 1.2 | EK168: 0.6 | EL168: -0.1 | EM168: 1.7 | EN168: -5.1 | EO168: 0.5 | EP168: 1.1 | EQ168: 6.2 | ER168: 1.9 | ES168: 1 | ET168: 3.7 | EU168: 2.3 | EZ168: 0 | FA168: 1.9 | FE168: 0.5 | FG168: 0.4 | FI168: 1.7 | FJ168: 1.4 | FK168: 1.7 | FL168: 1.7 | FM168: 1.5 | FN168: 2 | FO168: -0.1 | FP168: 2.1 | FQ168: 2.3 | FR168: 2.3 | FS168: 2.9 | FX168: 1.7 | FY168: 1.4 | FZ168: 2.3 | GA168: 1.2 | GD168: 1.8 | GE168: 1.2 | GF168: 2.3 | GG168: 2.3 | GK168: 0.7 | GM168: 1.1 | GO168: 0.8 | GQ168: 1.6 | GR168: 1.8 | GS168: 1.4 | GT168: 3 | GU168: 1 | GV168: 1 | GX168: 1 | GY168: 1 | HA168: 3.5 | HC168: 3.7 | HD168: 0.4 | HG168: 0.6 | HH168: 1 | HK168: -4.9 | HL168: -6.3 | HM168: 0.4 | HN168: 7.2 | HO168: 8.5 | HP168: 1.4 | HQ168: 2.6 | HR168: 2.7 | HS168: 2.7 | HT168: 1.5 | HU168: 4.1 | HV168: 1.3 | HW168: 1.5 | HX168: 1.3 | HY168: 1.3 | HZ168: 1.8 | IA168: 1.8 | IB168: 0 | IC168: 2.2 | IF168: -0.7 | IK168: 1 | IL168: 5.1 | IM168: -2.8 | IQ168: 2.4
A169: 32203 | B169: 33.63 | C169: 31.16 | D169: 31.71 | E169: 26.51 | F169: 33.58 | G169: 42.9 | H169: 42 | I169: 35.41 | J169: 27.69 | K169: 37.87 | L169: 21.09 | M169: 68.08 | N169: 29.87 | O169: 42.38 | P169: 33.83 | Q169: 34.85 | R169: 30.91 | S169: 34.5 | X169: 28.47 | Y169: 33.6 | AC169: 41.68 | AE169: 44.82 | AG169: 28.5 | AH169: 29.72 | AI169: 26.87 | AJ169: 12.95 | AK169: 32.3 | AL169: 25.27 | AM169: 51.66 | AN169: 25.45 | AO169: 2.76 | AP169: 2.76 | AQ169: 79.85 | AV169: 99.92 | AW169: 107.25 | AX169: 96.54 | AY169: 94.59 | BB169: 24.38 | BC169: 28.69 | BD169: 31 | BE169: 31 | BI169: 31.65 | BK169: 20.78 | BM169: 22.14 | BO169: 56.4 | BP169: 51.61 | BQ169: 55.12 | BR169: 39.15 | BS169: 94.38 | BT169: 94.38 | BV169: 91.2 | BW169: 104.03 | BY169: 63.93 | CA169: 58.23 | CB169: 66.9 | CE169: 27.52 | CF169: 26.54 | CI169: 50.28 | CJ169: 49.62 | CK169: 55.06 | CL169: 13.43 | CM169: 12.38 | CN169: 21.87 | CO169: 39.67 | CP169: 40.93 | CQ169: 86.28 | CR169: 44.91 | CS169: 29.09 | CT169: 35.83 | CU169: 22.11 | CV169: 26.13 | CW169: 26.13 | CX169: 108.93 | CY169: 108.93 | CZ169: 29.74 | DA169: 117.75 | DD169: 2076.46 | DI169: 38.48 | DJ169: 32.73 | DK169: 40.7 | DO169: 32.33 | DP169: 18.72 | DS169: 14.15 | DT169: 14.15 | ED169: 1.8 | EE169: 1.7 | EF169: 2.1 | EG169: 1.8 | EH169: 2.4 | EI169: 1.7 | EJ169: 2.4 | EK169: 1.5 | EL169: 1.7 | EM169: 0.3 | EN169: 3.8 | EO169: -0.6 | EP169: 0.6 | EQ169: 3.4 | ER169: 1.4 | ES169: 1.1 | ET169: 2.1 | EU169: 1.1 | EZ169: 2 | FA169: 0.9 | FE169: -0.9 | FG169: 1.4 | FI169: 1.7 | FJ169: 0.9 | FK169: 2.6 | FL169: 2 | FM169: 2 | FN169: 2 | FO169: 1.7 | FP169: 1.8 | FQ169: 2.2 | FR169: 2.2 | FS169: 0.1 | FX169: 0.3 | FY169: 0.7 | FZ169: 0.3 | GA169: 0.1 | GD169: 2.2 | GE169: 1.6 | GF169: 2.9 | GG169: 2.9 | GK169: 1.5 | GM169: 0.3 | GO169: 0.3 | GQ169: 1.1 | GR169: 1.8 | GS169: 1.7 | GT169: 2.3 | GU169: 1.1 | GV169: 1.1 | GX169: 1.2 | GY169: 1.2 | HA169: 0.2 | HC169: 0.2 | HD169: 2.1 | HG169: 5.5 | HH169: 1.7 | HK169: 19.2 | HL169: 24.1 | HM169: 1.8 | HN169: 2.2 | HO169: 2.5 | HP169: 1.6 | HQ169: 1.1 | HR169: 1 | HS169: 2.1 | HT169: 2.3 | HU169: 0.6 | HV169: 0.8 | HW169: -4.2 | HX169: 1.7 | HY169: 1.7 | HZ169: -0.6 | IA169: -0.6 | IB169: 0 | IC169: -0.8 | IF169: -2 | IK169: 5.7 | IL169: 0.9 | IM169: 10.8 | IQ169: 0.8
A170: 32295 | B170: 34.21 | C170: 32.18 | D170: 32.63 | E170: 27.2 | F170: 34.04 | G170: 47.3 | H170: 43.14 | I170: 36.65 | J170: 29.05 | K170: 37.99 | L170: 22.82 | M170: 71.52 | N170: 30.38 | O170: 42.62 | P170: 34.29 | Q170: 35.26 | R170: 31.47 | S170: 35.66 | X170: 29.58 | Y170: 34.42 | AC170: 42.12 | AE170: 44.86 | AG170: 28.95 | AH170: 30.29 | AI170: 27.21 | AJ170: 13.16 | AK170: 32.91 | AL170: 25.9 | AM170: 53.23 | AN170: 25.84 | AO170: 2.77 | AP170: 2.77 | AQ170: 82.83 | AV170: 103.49 | AW170: 112.82 | AX170: 99.52 | AY170: 96.41 | BB170: 25.03 | BC170: 29.28 | BD170: 31.76 | BE170: 31.76 | BI170: 32.19 | BK170: 20.8 | BM170: 22.17 | BO170: 57.28 | BP170: 53.08 | BQ170: 56.56 | BR170: 40.48 | BS170: 94.28 | BT170: 94.28 | BV170: 92.48 | BW170: 105.49 | BY170: 64.9 | CA170: 58.74 | CB170: 68.54 | CE170: 28.08 | CF170: 26.96 | CI170: 50.28 | CJ170: 49.21 | CK170: 56.97 | CL170: 13.68 | CM170: 12.57 | CN170: 22.6 | CO170: 39.58 | CP170: 40.79 | CQ170: 88.4 | CR170: 46.34 | CS170: 27.31 | CT170: 36.71 | CU170: 22.22 | CV170: 26.28 | CW170: 26.29 | CX170: 108.93 | CY170: 108.93 | CZ170: 29.74 | DA170: 117.75 | DD170: 2063.38 | DI170: 38.79 | DJ170: 32.85 | DK170: 41.1 | DO170: 33.63 | DP170: 18.98 | DS170: 14.15 | DT170: 14.15 | ED170: 1.7 | EE170: 3.3 | EF170: 2.9 | EG170: 2.6 | EH170: 1.4 | EI170: 10.3 | EJ170: 2.7 | EK170: 3.5 | EL170: 4.9 | EM170: 0.3 | EN170: 8.2 | EO170: 5.1 | EP170: 1.7 | EQ170: 0.6 | ER170: 1.4 | ES170: 1.2 | ET170: 1.8 | EU170: 3.4 | EZ170: 3.9 | FA170: 2.4 | FE170: 1.1 | FG170: 0.1 | FI170: 1.6 | FJ170: 1.9 | FK170: 1.3 | FL170: 1.6 | FM170: 1.9 | FN170: 2.5 | FO170: 3 | FP170: 1.5 | FQ170: 0.4 | FR170: 0.4 | FS170: 3.7 | FX170: 3.6 | FY170: 5.2 | FZ170: 3.1 | GA170: 1.9 | GD170: 2.7 | GE170: 2.1 | GF170: 2.5 | GG170: 2.5 | GK170: 1.7 | GM170: 0.1 | GO170: 0.1 | GQ170: 1.6 | GR170: 2.8 | GS170: 2.6 | GT170: 3.4 | GU170: -0.1 | GV170: -0.1 | GX170: 1.4 | GY170: 1.4 | HA170: 1.5 | HC170: 0.9 | HD170: 2.5 | HG170: 2 | HH170: 1.6 | HK170: 0 | HL170: -0.8 | HM170: 3.5 | HN170: 1.9 | HO170: 1.5 | HP170: 3.3 | HQ170: -0.2 | HR170: -0.3 | HS170: 2.5 | HT170: 3.2 | HU170: -6.1 | HV170: 2.5 | HW170: 0.5 | HX170: 0.6 | HY170: 0.6 | HZ170: 0 | IA170: 0 | IB170: 0 | IC170: 0 | IF170: -0.6 | IK170: 0.8 | IL170: 0.4 | IM170: 1 | IQ170: 4
A171: 32387 | B171: 34.87 | C171: 33.09 | D171: 33.18 | E171: 27.64 | F171: 34.53 | G171: 49.08 | H171: 43.29 | I171: 37.43 | J171: 30.2 | K171: 37.95 | L171: 23.71 | M171: 70.35 | N171: 31.25 | O171: 42.9 | P171: 34.63 | Q171: 35.6 | R171: 31.7 | S171: 35.82 | X171: 31.39 | Y171: 34.84 | AC171: 43.48 | AE171: 45 | AG171: 29.44 | AH171: 30.72 | AI171: 27.74 | AJ171: 13.32 | AK171: 33.19 | AL171: 26.34 | AM171: 54.68 | AN171: 25.84 | AO171: 2.84 | AP171: 2.84 | AQ171: 83.19 | AV171: 104.5 | AW171: 113.06 | AX171: 100.96 | AY171: 97.83 | BB171: 25.77 | BC171: 30.46 | BD171: 32.75 | BE171: 32.75 | BI171: 33.01 | BK171: 21.59 | BM171: 23.16 | BO171: 58.21 | BP171: 53.2 | BQ171: 56.56 | BR171: 40.79 | BS171: 96.71 | BT171: 96.71 | BV171: 93.65 | BW171: 106.83 | BY171: 66.01 | CA171: 59.26 | CB171: 69.69 | CE171: 28.44 | CF171: 27.29 | CI171: 48.49 | CJ171: 46.99 | CK171: 57.33 | CL171: 13.9 | CM171: 12.76 | CN171: 23.07 | CO171: 40.15 | CP171: 41.29 | CQ171: 90.61 | CR171: 46.44 | CS171: 27.15 | CT171: 37.39 | CU171: 22.13 | CV171: 28.17 | CW171: 28.17 | CX171: 110.03 | CY171: 110.03 | CZ171: 29.74 | DA171: 119.16 | DD171: 2059.64 | DI171: 38.74 | DJ171: 34.03 | DK171: 39.72 | DO171: 33.95 | DP171: 19.2 | DS171: 14.15 | DT171: 14.15 | ED171: 1.9 | EE171: 2.8 | EF171: 1.7 | EG171: 1.6 | EH171: 1.4 | EI171: 3.8 | EJ171: 0.3 | EK171: 2.1 | EL171: 4 | EM171: -0.1 | EN171: 3.9 | EO171: -1.6 | EP171: 2.9 | EQ171: 0.7 | ER171: 1 | ES171: 1 | ET171: 0.7 | EU171: 0.4 | EZ171: 6.1 | FA171: 1.2 | FE171: 3.2 | FG171: 0.3 | FI171: 1.7 | FJ171: 1.4 | FK171: 1.9 | FL171: 1.2 | FM171: 0.9 | FN171: 1.7 | FO171: 2.7 | FP171: 0 | FQ171: 2.5 | FR171: 2.5 | FS171: 0.4 | FX171: 1 | FY171: 0.2 | FZ171: 1.4 | GA171: 1.5 | GD171: 3 | GE171: 4 | GF171: 3.1 | GG171: 3.1 | GK171: 2.5 | GM171: 3.8 | GO171: 4.5 | GQ171: 1.6 | GR171: 0.2 | GS171: 0 | GT171: 0.8 | GU171: 2.6 | GV171: 2.6 | GX171: 1.3 | GY171: 1.3 | HA171: 1.7 | HC171: 0.9 | HD171: 1.7 | HG171: 1.3 | HH171: 1.2 | HK171: -3.6 | HL171: -4.5 | HM171: 0.6 | HN171: 1.6 | HO171: 1.5 | HP171: 2.1 | HQ171: 1.4 | HR171: 1.2 | HS171: 2.5 | HT171: 0.2 | HU171: -0.6 | HV171: 1.9 | HW171: -0.4 | HX171: 7.2 | HY171: 7.2 | HZ171: 1 | IA171: 1 | IB171: 0 | IC171: 1.2 | IF171: -0.2 | IK171: -0.1 | IL171: 3.6 | IM171: -3.4 | IQ171: 1
A172: 32478 | B172: 35.57 | C172: 33.6 | D172: 34.32 | E172: 28.67 | F172: 35.64 | G172: 50.8 | H172: 44.81 | I172: 38.14 | J172: 30.31 | K172: 39.48 | L172: 22.18 | M172: 73.39 | N172: 31.73 | O172: 47.37 | P172: 35.58 | Q172: 36.1 | R172: 33.75 | S172: 36.85 | X172: 31.66 | Y172: 35.33 | AC172: 44.79 | AE172: 45.04 | AG172: 30.03 | AH172: 31.26 | AI172: 28.36 | AJ172: 13.35 | AK172: 32.91 | AL172: 26.88 | AM172: 55.26 | AN172: 25.18 | AO172: 2.93 | AP172: 2.93 | AQ172: 85.71 | AV172: 107.85 | AW172: 116.26 | AX172: 105.15 | AY172: 99.45 | BB172: 26.57 | BC172: 32.35 | BD172: 33.51 | BE172: 33.51 | BI172: 33.8 | BK172: 21.68 | BM172: 23.23 | BO172: 59.15 | BP172: 54.02 | BQ172: 57.25 | BR172: 41.72 | BS172: 97.45 | BT172: 97.45 | BV172: 95.31 | BW172: 108.72 | BY172: 67.82 | CA172: 59.58 | CB172: 67.62 | CE172: 28.83 | CF172: 27.8 | CI172: 45.01 | CJ172: 42.77 | CK172: 57.39 | CL172: 14.45 | CM172: 13.3 | CN172: 23.65 | CO172: 40.29 | CP172: 41.38 | CQ172: 91.77 | CR172: 47.42 | CS172: 26.5 | CT172: 37.95 | CU172: 22.53 | CV172: 28.57 | CW172: 28.57 | CX172: 112.78 | CY172: 112.78 | CZ172: 31.05 | DA172: 121.85 | DD172: 2042.82 | DI172: 41.27 | DJ172: 36.01 | DK172: 42.58 | DO172: 35 | DP172: 19.58 | DS172: 14.15 | DT172: 14.15 | ED172: 2 | EE172: 1.5 | EF172: 3.4 | EG172: 3.7 | EH172: 3.2 | EI172: 3.5 | EJ172: 3.5 | EK172: 1.9 | EL172: 0.4 | EM172: 4 | EN172: -6.5 | EO172: 4.3 | EP172: 1.5 | EQ172: 10.4 | ER172: 2.7 | ES172: 1.4 | ET172: 6.5 | EU172: 2.9 | EZ172: 0.9 | FA172: 1.4 | FE172: 3 | FG172: 0.1 | FI172: 2 | FJ172: 1.8 | FK172: 2.2 | FL172: 0.2 | FM172: -0.8 | FN172: 2.1 | FO172: 1.1 | FP172: -2.6 | FQ172: 3.2 | FR172: 3.2 | FS172: 3 | FX172: 3.2 | FY172: 2.8 | FZ172: 4.2 | GA172: 1.7 | GD172: 3.1 | GE172: 6.2 | GF172: 2.3 | GG172: 2.3 | GK172: 2.4 | GM172: 0.4 | GO172: 0.3 | GQ172: 1.6 | GR172: 1.5 | GS172: 1.2 | GT172: 2.3 | GU172: 0.8 | GV172: 0.8 | GX172: 1.8 | GY172: 1.8 | HA172: 2.7 | HC172: 0.5 | HD172: -3 | HG172: 1.4 | HH172: 1.9 | HK172: -7.2 | HL172: -9 | HM172: 0.1 | HN172: 4 | HO172: 4.2 | HP172: 2.5 | HQ172: 0.3 | HR172: 0.2 | HS172: 1.3 | HT172: 2.1 | HU172: -2.4 | HV172: 1.5 | HW172: 1.8 | HX172: 1.4 | HY172: 1.4 | HZ172: 2.5 | IA172: 2.5 | IB172: 4.4 | IC172: 2.3 | IF172: -0.8 | IK172: 6.5 | IL172: 5.8 | IM172: 7.2 | IQ172: 3.1
A173: 32568 | B173: 35.91 | C173: 34.11 | D173: 34.73 | E173: 29.33 | F173: 35.98 | G173: 49.44 | H173: 45.86 | I173: 39.21 | J173: 31.05 | K173: 40.66 | L173: 23.12 | M173: 75.02 | N173: 32.11 | O173: 49.42 | P173: 36.19 | Q173: 37.12 | R173: 33.72 | S173: 37.01 | X173: 31.97 | Y173: 35.51 | AC173: 46 | AE173: 45.77 | AG173: 30.59 | AH173: 31.46 | AI173: 29.21 | AJ173: 13.61 | AK173: 33.34 | AL173: 27.39 | AM173: 55.61 | AN173: 25.51 | AO173: 3.04 | AP173: 3.04 | AQ173: 85.71 | AV173: 107.06 | AW173: 114.72 | AX173: 105.26 | AY173: 97.42 | BB173: 27.28 | BC173: 32.01 | BD173: 34.32 | BE173: 34.32 | BI173: 33.69 | BK173: 21.7 | BM173: 23.28 | BO173: 59.59 | BP173: 54.78 | BQ173: 58.06 | BR173: 42.21 | BS173: 99.36 | BT173: 99.36 | BV173: 95.8 | BW173: 109.28 | BY173: 67.2 | CA173: 60.54 | CB173: 68.12 | CE173: 29.96 | CF173: 28.23 | CI173: 53.33 | CJ173: 52.6 | CK173: 58.41 | CL173: 15.07 | CM173: 13.91 | CN173: 24.3 | CO173: 40.68 | CP173: 41.83 | CQ173: 93.12 | CR173: 47.57 | CS173: 26.5 | CT173: 38.55 | CU173: 22.76 | CV173: 28.63 | CW173: 28.64 | CX173: 111.46 | CY173: 111.46 | CZ173: 31.65 | DA173: 119.98 | DD173: 2014.79 | DI173: 39.83 | DJ173: 35.37 | DK173: 40.3 | DO173: 34.93 | DP173: 20.25 | DS173: 15.91 | DT173: 15.91 | ED173: 1 | EE173: 1.5 | EF173: 1.2 | EG173: 2.3 | EH173: 1 | EI173: -2.7 | EJ173: 2.3 | EK173: 2.8 | EL173: 2.4 | EM173: 3 | EN173: 4.2 | EO173: 2.2 | EP173: 1.2 | EQ173: 4.3 | ER173: 1.7 | ES173: 2.8 | ET173: -0.1 | EU173: 0.4 | EZ173: 1 | FA173: 0.5 | FE173: 2.7 | FG173: 1.6 | FI173: 1.9 | FJ173: 0.6 | FK173: 3 | FL173: 1.9 | FM173: 1.3 | FN173: 1.9 | FO173: 0.6 | FP173: 1.3 | FQ173: 3.8 | FR173: 3.8 | FS173: 0 | FX173: -0.7 | FY173: -1.3 | FZ173: 0.1 | GA173: -2 | GD173: 2.7 | GE173: -1.1 | GF173: 2.4 | GG173: 2.4 | GK173: -0.3 | GM173: 0.1 | GO173: 0.2 | GQ173: 0.7 | GR173: 1.4 | GS173: 1.4 | GT173: 1.2 | GU173: 2 | GV173: 2 | GX173: 0.5 | GY173: 0.5 | HA173: -0.9 | HC173: 1.6 | HD173: 0.7 | HG173: 3.9 | HH173: 1.5 | HK173: 18.5 | HL173: 23 | HM173: 1.8 | HN173: 4.3 | HO173: 4.6 | HP173: 2.7 | HQ173: 1 | HR173: 1.1 | HS173: 1.5 | HT173: 0.3 | HU173: 0 | HV173: 1.6 | HW173: 1 | HX173: 0.2 | HY173: 0.2 | HZ173: -1.2 | IA173: -1.2 | IB173: 1.9 | IC173: -1.5 | IF173: -1.4 | IK173: -3.5 | IL173: -1.8 | IM173: -5.4 | IQ173: -0.2
A174: 32660 | B174: 36.8 | C174: 35.17 | D174: 34.95 | E174: 29.58 | F174: 36.21 | G174: 49.86 | H174: 45.39 | I174: 40.32 | J174: 32.85 | K174: 40.88 | L174: 24.43 | M174: 77.91 | N174: 32.62 | O174: 48.61 | P174: 36.57 | Q174: 36.97 | R174: 34.54 | S174: 38.83 | X174: 32.52 | Y174: 36.11 | AC174: 45.66 | AE174: 44.95 | AG174: 31.3 | AH174: 32.03 | AI174: 30.05 | AJ174: 13.91 | AK174: 34.08 | AL174: 28.34 | AM174: 57.29 | AN174: 25.92 | AO174: 3.1 | AP174: 3.1 | AQ174: 88.06 | AV174: 111.19 | AW174: 117.45 | AX174: 110.45 | AY174: 100.26 | BB174: 27.96 | BC174: 33.71 | BD174: 34.97 | BE174: 34.97 | BI174: 34.7 | BK174: 21.73 | BM174: 23.28 | BO174: 60.22 | BP174: 55.95 | BQ174: 59.5 | BR174: 42.69 | BS174: 101.69 | BT174: 101.69 | BV174: 95.41 | BW174: 108.83 | BY174: 68.52 | CA174: 61.44 | CB174: 68.19 | CE174: 30.29 | CF174: 28.53 | CI174: 52.75 | CJ174: 51.88 | CK174: 58.65 | CL174: 15.21 | CM174: 14.03 | CN174: 24.75 | CO174: 41.65 | CP174: 42.87 | CQ174: 93.7 | CR174: 48.31 | CS174: 28.71 | CT174: 38.43 | CU174: 22.99 | CV174: 28.73 | CW174: 28.73 | CX174: 109.04 | CY174: 109.04 | CZ174: 32.12 | DA174: 116.81 | DD174: 1975.54 | DI174: 40.83 | DJ174: 35.48 | DK174: 42.31 | DO174: 34.6 | DP174: 20.73 | DS174: 15.91 | DT174: 15.91 | ED174: 2.5 | EE174: 3.1 | EF174: 0.6 | EG174: 0.9 | EH174: 0.6 | EI174: 0.8 | EJ174: -1 | EK174: 2.8 | EL174: 5.8 | EM174: 0.5 | EN174: 5.7 | EO174: 3.9 | EP174: 1.6 | EQ174: -1.6 | ER174: 1.1 | ES174: -0.4 | ET174: 2.4 | EU174: 4.9 | EZ174: 1.7 | FA174: 1.7 | FE174: -0.7 | FG174: -1.8 | FI174: 2.3 | FJ174: 1.8 | FK174: 2.9 | FL174: 2.2 | FM174: 2.2 | FN174: 3.5 | FO174: 3 | FP174: 1.6 | FQ174: 2 | FR174: 2 | FS174: 2.7 | FX174: 3.9 | FY174: 2.4 | FZ174: 4.9 | GA174: 2.9 | GD174: 2.5 | GE174: 5.3 | GF174: 1.9 | GG174: 1.9 | GK174: 3 | GM174: 0.1 | GO174: 0 | GQ174: 1.1 | GR174: 2.1 | GS174: 2.5 | GT174: 1.1 | GU174: 2.3 | GV174: 2.3 | GX174: -0.4 | GY174: -0.4 | HA174: 2 | HC174: 1.5 | HD174: 0.1 | HG174: 1.1 | HH174: 1.1 | HK174: -1.1 | HL174: -1.4 | HM174: 0.4 | HN174: 0.9 | HO174: 0.9 | HP174: 1.9 | HQ174: 2.4 | HR174: 2.5 | HS174: 0.6 | HT174: 1.6 | HU174: 8.3 | HV174: -0.3 | HW174: 1 | HX174: 0.3 | HY174: 0.3 | HZ174: -2.2 | IA174: -2.2 | IB174: 1.5 | IC174: -2.6 | IF174: -1.9 | IK174: 2.5 | IL174: 0.3 | IM174: 5 | IQ174: -0.9
A175: 32752 | B175: 37.65 | C175: 36.04 | D175: 35.69 | E175: 30.4 | F175: 36.85 | G175: 50.49 | H175: 47.15 | I175: 40.86 | J175: 33.6 | K175: 41.39 | L175: 24.46 | M175: 76.66 | N175: 33.45 | O175: 49.32 | P175: 36.76 | Q175: 36.97 | R175: 35.14 | S175: 39.16 | T175: 41.55 | U175: 34.77 | V175: 46.34 | W175: 33.44 | X175: 31.14 | Y175: 36.3 | Z175: 49.83 | AA175: 29.27 | AB175: 31.37 | AC175: 46.88 | AD175: 38.81 | AE175: 45.18 | AF175: 37.58 | AG175: 31.76 | AH175: 32.87 | AI175: 30.14 | AJ175: 14.23 | AK175: 34.72 | AL175: 28.88 | AM175: 58.39 | AN175: 26.41 | AO175: 3.2 | AP175: 3.2 | AQ175: 88.24 | AR175: 102.29 | AS175: 99.25 | AT175: 108.64 | AU175: 86.9 | AV175: 110.41 | AW175: 115.08 | AX175: 110.34 | AY175: 100.36 | BB175: 28.38 | BC175: 35.53 | BD175: 35.7 | BE175: 35.7 | BI175: 34.98 | BK175: 22.36 | BM175: 23.98 | BN175: 16.89 | BO175: 61.09 | BP175: 56.53 | BQ175: 60.25 | BR175: 43.05 | BS175: 103.81 | BT175: 103.81 | BU175: 96.21 | BV175: 97.08 | BW175: 110.73 | BX175: 116.91 | BY175: 68.24 | BZ175: 60.68 | CA175: 61.76 | CB175: 69.83 | CC175: 51.48 | CD175: 24.19 | CE175: 31.4 | CF175: 29.16 | CG175: 21.49 | CH175: 20.08 | CI175: 50.96 | CJ175: 49.57 | CK175: 59.19 | CL175: 15.47 | CM175: 14.22 | CN175: 25.38 | CO175: 42.57 | CP175: 43.73 | CQ175: 94.76 | CR175: 48.45 | CS175: 29.15 | CT175: 38.83 | CU175: 22.83 | CV175: 30.33 | CW175: 30.34 | CX175: 109.04 | CY175: 109.04 | CZ175: 32.59 | DA175: 116.58 | DB175: 56.34 | DC175: 305.22 | DD175: 1923.21 | DE175: 80.52 | DF175: 36.37 | DI175: 41.44 | DJ175: 36.4 | DK175: 42.49 | DL175: 36.56 | DO175: 34.82 | DP175: 21.02 | DS175: 15.91 | DT175: 15.91 | DY175: 14.14 | DZ175: 14.14 | ED175: 2.3 | EE175: 2.5 | EF175: 2.1 | EG175: 2.8 | EH175: 1.8 | EI175: 1.3 | EJ175: 3.9 | EK175: 1.3 | EL175: 2.3 | EM175: 1.2 | EN175: 0.1 | EO175: -1.6 | EP175: 2.5 | EQ175: 1.5 | ER175: 0.5 | ES175: 0 | ET175: 1.7 | EU175: 0.8 | EZ175: -4.2 | FA175: 0.5 | FE175: 2.7 | FG175: 0.5 | FI175: 1.5 | FJ175: 2.6 | FK175: 0.3 | FL175: 2.3 | FM175: 1.9 | FN175: 1.9 | FO175: 1.9 | FP175: 1.9 | FQ175: 3.2 | FR175: 3.2 | FS175: 0.2 | FX175: -0.7 | FY175: -2 | FZ175: -0.1 | GA175: 0.1 | GD175: 1.5 | GE175: 5.4 | GF175: 2.1 | GG175: 2.1 | GK175: 0.8 | GM175: 2.9 | GO175: 3 | GQ175: 1.4 | GR175: 1 | GS175: 1.3 | GT175: 0.8 | GU175: 2.1 | GV175: 2.1 | GX175: 1.8 | GY175: 1.7 | HA175: -0.4 | HC175: 0.5 | HD175: 2.4 | HG175: 3.7 | HH175: 2.2 | HK175: -3.4 | HL175: -4.5 | HM175: 0.9 | HN175: 1.7 | HO175: 1.4 | HP175: 2.5 | HQ175: 2.2 | HR175: 2 | HS175: 1.1 | HT175: 0.3 | HU175: 1.5 | HV175: 1 | HW175: -0.7 | HX175: 5.6 | HY175: 5.6 | HZ175: 0 | IA175: 0 | IB175: 1.5 | IC175: -0.2 | IF175: -2.6 | IK175: 1.5 | IL175: 2.6 | IM175: 0.4 | IQ175: 0.6
A176: 32843 | B176: 38.35 | C176: 36.15 | D176: 36.35 | E176: 31.15 | F176: 37.31 | G176: 51.96 | H176: 47.3 | I176: 40.9 | J176: 33.36 | K176: 42.7 | L176: 23.81 | M176: 78.92 | N176: 34.35 | O176: 47.47 | P176: 37.79 | Q176: 37.61 | R176: 36.82 | S176: 41.3 | T176: 38.44 | U176: 33.55 | V176: 41.84 | W176: 34.2 | X176: 30.93 | Y176: 37.35 | Z176: 51.48 | AA176: 30.33 | AB176: 32.12 | AC176: 48.96 | AD176: 39.73 | AE176: 44.59 | AF176: 38.47 | AG176: 32.22 | AH176: 33.04 | AI176: 30.83 | AJ176: 14.51 | AK176: 35.22 | AL176: 29.41 | AM176: 58.16 | AN176: 26.92 | AO176: 3.31 | AP176: 3.31 | AQ176: 90.04 | AR176: 104.59 | AS176: 100.77 | AT176: 111.42 | AU176: 88.93 | AV176: 111.64 | AW176: 118.87 | AX176: 109.89 | AY176: 101.78 | BB176: 29.21 | BC176: 36.75 | BD176: 36.32 | BE176: 36.32 | BI176: 35.59 | BK176: 22.58 | BM176: 24.12 | BN176: 17.24 | BO176: 62.03 | BP176: 57.88 | BQ176: 61.69 | BR176: 43.98 | BS176: 105.29 | BT176: 105.29 | BU176: 97.28 | BV176: 98.35 | BW176: 112.18 | BX176: 116.55 | BY176: 69.7 | BZ176: 61.23 | CA176: 64 | CB176: 70.12 | CC176: 51.53 | CD176: 24.47 | CE176: 31.56 | CF176: 29.7 | CG176: 21.74 | CH176: 20.21 | CI176: 48.44 | CJ176: 46.48 | CK176: 59.49 | CL176: 15.8 | CM176: 14.54 | CN176: 25.87 | CO176: 43.58 | CP176: 44.77 | CQ176: 96.4 | CR176: 48.55 | CS176: 30.52 | CT176: 39.59 | CU176: 23.34 | CV176: 30.86 | CW176: 30.86 | CX176: 110.03 | CY176: 110.03 | CZ176: 33.73 | DA176: 117.16 | DB176: 58.02 | DC176: 308.01 | DD176: 1895.17 | DE176: 81.25 | DF176: 36.52 | DI176: 44.18 | DJ176: 38.76 | DK176: 45.35 | DL176: 36.6 | DO176: 34.71 | DP176: 21.37 | DS176: 15.91 | DT176: 15.91 | DY176: 14.28 | DZ176: 14.28 | ED176: 1.9 | EE176: 0.3 | EF176: 1.8 | EG176: 2.5 | EH176: 1.2 | EI176: 2.9 | EJ176: 0.3 | EK176: 0.1 | EL176: -0.7 | EM176: 3.2 | EN176: -2.7 | EO176: 2.9 | EP176: 2.7 | EQ176: -3.8 | ER176: 2.8 | ES176: 1.7 | ET176: 4.8 | EU176: 5.5 | EV176: -7.5 | EW176: -3.5 | EX176: -9.7 | EY176: 2.3 | EZ176: -0.7 | FA176: 2.9 | FB176: 3.3 | FC176: 3.6 | FD176: 2.4 | FE176: 4.4 | FF176: 2.4 | FG176: -1.3 | FH176: 2.4 | FI176: 1.4 | FJ176: 0.5 | FK176: 2.3 | FL176: 2 | FM176: 1.4 | FN176: 1.8 | FO176: -0.4 | FP176: 1.9 | FQ176: 3.4 | FR176: 3.4 | FS176: 2 | FT176: 2.2 | FU176: 1.5 | FV176: 2.6 | FW176: 2.3 | FX176: 1.1 | FY176: 3.3 | FZ176: -0.4 | GA176: 1.4 | GD176: 2.9 | GE176: 3.4 | GF176: 1.7 | GG176: 1.7 | GK176: 1.7 | GM176: 1 | GO176: 0.6 | GP176: 2.1 | GQ176: 1.5 | GR176: 2.4 | GS176: 2.4 | GT176: 2.2 | GU176: 1.4 | GV176: 1.4 | GW176: 1.1 | GX176: 1.3 | GY176: 1.3 | GZ176: -0.3 | HA176: 2.1 | HB176: 0.9 | HC176: 3.6 | HD176: 0.4 | HE176: 0.1 | HF176: 1.2 | HG176: 0.5 | HH176: 1.9 | HI176: 1.2 | HJ176: 0.6 | HK176: -4.9 | HL176: -6.2 | HM176: 0.5 | HN176: 2.1 | HO176: 2.3 | HP176: 1.9 | HQ176: 2.4 | HR176: 2.4 | HS176: 1.7 | HT176: 0.2 | HU176: 4.7 | HV176: 2 | HW176: 2.2 | HX176: 1.7 | HY176: 1.7 | HZ176: 0.9 | IA176: 0.9 | IB176: 3.5 | IC176: 0.5 | ID176: 3 | IE176: 0.9 | IF176: -1.5 | IG176: 0.9 | IH176: 0.4 | IK176: 6.6 | IL176: 6.5 | IM176: 6.7 | IN176: 0.1 | IQ176: -0.3
A177: 32933 | B177: 39.01 | C177: 36.22 | D177: 37.2 | E177: 31.75 | F177: 38.26 | G177: 53.37 | H177: 48.16 | I177: 41.44 | J177: 33.97 | K177: 42.66 | L177: 24.83 | M177: 78.22 | N177: 34.9 | O177: 47.13 | P177: 38.63 | Q177: 38.26 | R177: 38.17 | S177: 41.34 | T177: 34.26 | U177: 34.87 | V177: 33.73 | W177: 35.17 | X177: 30.34 | Y177: 38.11 | Z177: 51.85 | AA177: 30.2 | AB177: 33.06 | AC177: 49.01 | AD177: 40.25 | AE177: 45.77 | AF177: 38.97 | AG177: 32.94 | AH177: 33.78 | AI177: 31.54 | AJ177: 14.83 | AK177: 35.82 | AL177: 29.98 | AM177: 57.99 | AN177: 27.55 | AO177: 3.42 | AP177: 3.42 | AQ177: 90.13 | AR177: 104.49 | AS177: 100.56 | AT177: 111.75 | AU177: 87.52 | AV177: 111.75 | AW177: 118.64 | AX177: 110.11 | AY177: 102.09 | BB177: 29.92 | BC177: 37.49 | BD177: 36.72 | BE177: 36.72 | BI177: 35.99 | BK177: 22.65 | BM177: 24.14 | BN177: 17.41 | BO177: 62.97 | BP177: 59.11 | BQ177: 63 | BR177: 44.96 | BS177: 106.25 | BT177: 106.25 | BU177: 97.97 | BV177: 97.86 | BW177: 111.63 | BX177: 120.49 | BY177: 69.84 | BZ177: 62.35 | CA177: 64.64 | CB177: 71.9 | CC177: 51.84 | CD177: 24.86 | CE177: 33.35 | CF177: 30.42 | CG177: 22.09 | CH177: 21.09 | CI177: 55.7 | CJ177: 55.12 | CK177: 60.21 | CL177: 16.05 | CM177: 14.76 | CN177: 26.37 | CO177: 44.73 | CP177: 45.99 | CQ177: 97.36 | CR177: 49.44 | CS177: 32.48 | CT177: 40.27 | CU177: 23.53 | CV177: 31.17 | CW177: 31.17 | CX177: 110.25 | CY177: 110.25 | CZ177: 33.97 | DA177: 117.4 | DB177: 58.48 | DC177: 309.86 | DD177: 1850.31 | DE177: 81.74 | DF177: 37.41 | DI177: 44.14 | DJ177: 38.72 | DK177: 45.35 | DL177: 38.52 | DO177: 36.87 | DP177: 22.4 | DS177: 18.16 | DT177: 18.16 | DY177: 14.44 | DZ177: 14.44 | ED177: 1.7 | EE177: 0.2 | EF177: 2.3 | EG177: 1.9 | EH177: 2.5 | EI177: 2.7 | EJ177: 1.8 | EK177: 1.3 | EL177: 1.8 | EM177: -0.1 | EN177: 4.3 | EO177: -0.9 | EP177: 1.6 | EQ177: -0.7 | ER177: 2.2 | ES177: 1.7 | ET177: 3.7 | EU177: 0.1 | EV177: -10.9 | EW177: 3.9 | EX177: -19.4 | EY177: 2.8 | EZ177: -1.9 | FA177: 2 | FB177: 0.7 | FC177: -0.4 | FD177: 2.9 | FE177: 0.1 | FF177: 1.3 | FG177: 2.6 | FH177: 1.3 | FI177: 2.2 | FJ177: 2.2 | FK177: 2.3 | FL177: 2.2 | FM177: 1.7 | FN177: 1.9 | FO177: -0.3 | FP177: 2.3 | FQ177: 3.3 | FR177: 3.3 | FS177: 0.1 | FT177: -0.1 | FU177: -0.2 | FV177: 0.3 | FW177: -1.6 | FX177: 0.1 | FY177: -0.2 | FZ177: 0.2 | GA177: 0.3 | GD177: 2.4 | GE177: 2 | GF177: 1.1 | GG177: 1.1 | GK177: 1.1 | GM177: 0.3 | GO177: 0.1 | GP177: 1 | GQ177: 1.5 | GR177: 2.1 | GS177: 2.1 | GT177: 2.2 | GU177: 0.9 | GV177: 0.9 | GW177: 0.7 | GX177: -0.5 | GY177: -0.5 | GZ177: 3.4 | HA177: 0.2 | HB177: 1.8 | HC177: 1 | HD177: 2.5 | HE177: 0.6 | HF177: 1.6 | HG177: 5.7 | HH177: 2.4 | HI177: 1.6 | HJ177: 4.4 | HK177: 15 | HL177: 18.6 | HM177: 1.2 | HN177: 1.6 | HO177: 1.5 | HP177: 1.9 | HQ177: 2.6 | HR177: 2.7 | HS177: 1 | HT177: 1.8 | HU177: 6.4 | HV177: 1.7 | HW177: 0.8 | HX177: 1 | HY177: 1 | HZ177: 0.2 | IA177: 0.2 | IB177: 0.7 | IC177: 0.2 | ID177: 0.8 | IE177: 0.6 | IF177: -2.4 | IG177: 0.6 | IH177: 2.4 | IK177: -0.1 | IL177: -0.1 | IM177: 0 | IN177: 5.2 | IQ177: 6.2
