Workbook
Name A2325806K: Data1!$EC$1:$EC$10,Data1!$EC$11:$EC$294
Name A2325806K_Data: Data1!$EC$11:$EC$294
Name A2325806K_Latest: Data1!$EC$294
Name A2325811C: Data2!$AI$1:$AI$10,Data2!$AI$11:$AI$294
Name A2325811C_Data: Data2!$AI$11:$AI$294
Name A2325811C_Latest: Data2!$AI$294
Name A2325816R: Data2!$GE$1:$GE$10,Data2!$GE$11:$GE$294
Name A2325816R_Data: Data2!$GE$11:$GE$294
Name A2325816R_Latest: Data2!$GE$294
Name A2325821J: Data3!$CK$1:$CK$10,Data3!$CK$11:$CK$294
Name A2325821J_Data: Data3!$CK$11:$CK$294
Name A2325821J_Latest: Data3!$CK$294
Name A2325826V: Data3!$IG$1:$IG$10,Data3!$IG$11:$IG$294
Name A2325826V_Data: Data3!$IG$11:$IG$294
Name A2325826V_Latest: Data3!$IG$294
Name A2325831L: Data4!$EM$1:$EM$10,Data4!$EM$11:$EM$294
Name A2325831L_Data: Data4!$EM$11:$EM$294
Name A2325831L_Latest: Data4!$EM$294
Name A2325836X: Data5!$AS$1:$AS$10,Data5!$AS$139:$AS$294
Name A2325836X_Data: Data5!$AS$139:$AS$294
Name A2325836X_Latest: Data5!$AS$294
Name A2325841T: Data5!$GO$1:$GO$10,Data5!$GO$11:$GO$294
Name A2325841T_Data: Data5!$GO$11:$GO$294
Name A2325841T_Latest: Data5!$GO$294
Name A2325846C: Data6!$CU$1:$CU$10,Data6!$CU$11:$CU$294
Name A2325846C_Data: Data6!$CU$11:$CU$294
Name A2325846C_Latest: Data6!$CU$294
Name A2325851W: Data1!$B$1:$B$10,Data1!$B$107:$B$294
Name A2325851W_Data: Data1!$B$107:$B$294
Name A2325851W_Latest: Data1!$B$294
Name A2325856J: Data1!$EX$1:$EX$10,Data1!$EX$107:$EX$294
Name A2325856J_Data: Data1!$EX$107:$EX$294
Name A2325856J_Latest: Data1!$EX$294
Name A2325861A: Data2!$BD$1:$BD$10,Data2!$BD$107:$BD$294
Name A2325861A_Data: Data2!$BD$107:$BD$294
Name A2325861A_Latest: Data2!$BD$294
Name A2325866L: Data2!$GZ$1:$GZ$10,Data2!$GZ$107:$GZ$294
Name A2325866L_Data: Data2!$GZ$107:$GZ$294
Name A2325866L_Latest: Data2!$GZ$294
Name A2325871F: Data3!$DF$1:$DF$10,Data3!$DF$107:$DF$294
Name A2325871F_Data: Data3!$DF$107:$DF$294
Name A2325871F_Latest: Data3!$DF$294
Name A2325876T: Data4!$L$1:$L$10,Data4!$L$107:$L$294
Name A2325876T_Data: Data4!$L$107:$L$294
Name A2325876T_Latest: Data4!$L$294
Name A2325881K: Data4!$FH$1:$FH$10,Data4!$FH$139:$FH$294
Name A2325881K_Data: Data4!$FH$139:$FH$294
Name A2325881K_Latest: Data4!$FH$294
Name A2325886W: Data5!$BN$1:$BN$10,Data5!$BN$107:$BN$294
Name A2325886W_Data: Data5!$BN$107:$BN$294
Name A2325886W_Latest: Data5!$BN$294
Name A2325891R: Data5!$HJ$1:$HJ$10,Data5!$HJ$107:$HJ$294
Name A2325891R_Data: Data5!$HJ$107:$HJ$294
Name A2325891R_Latest: Data5!$HJ$294
Name A2325896A: Data1!$AP$1:$AP$10,Data1!$AP$107:$AP$294
Name A2325896A_Data: Data1!$AP$107:$AP$294
Name A2325896A_Latest: Data1!$AP$294
Name A2325901J: Data1!$GL$1:$GL$10,Data1!$GL$107:$GL$294
Name A2325901J_Data: Data1!$GL$107:$GL$294
Name A2325901J_Latest: Data1!$GL$294

Sheet Index
B2: Time Series Workbook
B5: 6401.0 Consumer Price Index, Australia
B6: TABLE 9. CPI: Group, Sub-group and Expenditure Class, Index Numbers by Capital City
A8: Related Information: | B8: Summary Publication | C8: Explanatory Notes | D8: Inquiries
A10: Data Item Description | D10: Series Type | E10: Series ID | F10: Series Start | G10: Series End | H10: No. Obs. | I10: Unit | J10: Data Type | K10: Freq. | L10: Collection Month
A12: Index Numbers ; Food and non-alcoholic beverages ; Sydney ; | D12: Original | E12: A2325851W | F12: 26543 | G12: 43617 | H12: 188 | I12: Index Numbers | J12: INDEX | K12: Quarter | L12: 3
A13: Index Numbers ; Bread and cereal products ; Sydney ; | D13: Original | E13: A2326166T | F13: 26543 | G13: 43617 | H13: 188 | I13: Index Numbers | J13: INDEX | K13: Quarter | L13: 3
A14: Index Numbers ; Bread ; Sydney ; | D14: Original | E14: A2327021W | F14: 29465 | G14: 43617 | H14: 156 | I14: Index Numbers | J14: INDEX | K14: Quarter | L14: 3
A15: Index Numbers ; Cakes and biscuits ; Sydney ; | D15: Original | E15: A2327066A | F15: 29465 | G15: 43617 | H15: 156 | I15: Index Numbers | J15: INDEX | K15: Quarter | L15: 3
A16: Index Numbers ; Breakfast cereals ; Sydney ; | D16: Original | E16: A2327111A | F16: 29465 | G16: 43617 | H16: 156 | I16: Index Numbers | J16: INDEX | K16: Quarter | L16: 3
A17: Index Numbers ; Other cereal products ; Sydney ; | D17: Original | E17: A2327156F | F17: 29465 | G17: 43617 | H17: 156 | I17: Index Numbers | J17: INDEX | K17: Quarter | L17: 3
A18: Index Numbers ; Meat and seafoods ; Sydney ; | D18: Original | E18: A2326211T | F18: 26543 | G18: 43617 | H18: 188 | I18: Index Numbers | J18: INDEX | K18: Quarter | L18: 3
A19: Index Numbers ; Beef and veal ; Sydney ; | D19: Original | E19: A2327201F | F19: 26543 | G19: 43617 | H19: 188 | I19: Index Numbers | J19: INDEX | K19: Quarter | L19: 3
A20: Index Numbers ; Pork ; Sydney ; | D20: Original | E20: A3603903T | F20: 29465 | G20: 43617 | H20: 156 | I20: Index Numbers | J20: INDEX | K20: Quarter | L20: 3
A21: Index Numbers ; Lamb and goat ; Sydney ; | D21: Original | E21: A2327246K | F21: 26543 | G21: 43617 | H21: 188 | I21: Index Numbers | J21: INDEX | K21: Quarter | L21: 3
A22: Index Numbers ; Poultry ; Sydney ; | D22: Original | E22: A2327336R | F22: 26543 | G22: 43617 | H22: 188 | I22: Index Numbers | J22: INDEX | K22: Quarter | L22: 3
A23: Index Numbers ; Other meats ; Sydney ; | D23: Original | E23: A2327426V | F23: 29465 | G23: 43617 | H23: 156 | I23: Index Numbers | J23: INDEX | K23: Quarter | L23: 3
... A1379: Index Numbers ; All groups CPI excluding 'volatile items' ; Australia ; | D1379: Original | E1379: A2330841L | F1379: 31747 | G1379: 43617 | H1379: 131 | I1379: Index Numbers | J1379: INDEX | K1379: Quarter | L1379: 3
A1381: © Commonwealth of Australia 2019

Sheet Energy Summary
A1: Energy Price Index — Summary
A2: Source: ABS 6401.0 Consumer Price Index, Table 9. Original series, quarterly, index 2011–12 = 100.
A3: Window: Sep-1989 to Jun-2019 (common window where all three fuel series are available nationally)
A5: 1. Time Series Data | AD5: Chart source helper tables (collapsed group)
B6: Sydney | E6: Melbourne | H6: Brisbane | K6: Adelaide | N6: Perth | Q6: Hobart | T6: Darwin | W6: Canberra | Z6: Australia
A7: Quarter | B7: Electricity | C7: Gas | D7: Auto fuel | E7: Electricity | F7: Gas | G7: Auto fuel | H7: Electricity | I7: Gas | J7: Auto fuel | K7: Electricity | L7: Gas | M7: Auto fuel | N7: Electricity | O7: Gas | P7: Auto fuel | Q7: Electricity | R7: Gas | S7: Auto fuel | T7: Electricity | U7: Gas | V7: Auto fuel | W7: Electricity | X7: Gas | Y7: Auto fuel | Z7: Electricity | AA7: Gas | AB7: Auto fuel | AD7: Quarter | AE7: Sydney | AF7: Melbourne | AG7: Brisbane | AH7: Adelaide | AI7: Perth | AJ7: Hobart | AK7: Darwin | AL7: Canberra | AM7: Australia | AP7: Quarter | AQ7: Sydney | AR7: Melbourne | AS7: Brisbane | AT7: Adelaide | AU7: Perth | AV7: Hobart | AW7: Darwin | AX7: Canberra | AY7: Australia | BA7: Quarter | BB7: Sydney | BC7: Melbourne | BD7: Brisbane | BE7: Adelaide | BF7: Perth | BG7: Hobart | BH7: Darwin | BI7: Canberra | BJ7: Australia
A8: =Data1!A175 -> 32752 | B8: =Data1!BL175 -> 34 | C8: =Data1!BM175 -> 34.9 | D8: =Data1!CR175 -> 36.6 | E8: =Data1!HH175 -> 35.3 | F8: =Data1!HI175 -> 38.9 | G8: =Data1!IN175 -> 38.3 | H8: =Data2!DN175 -> 40.3 | I8: =Data2!DO175 -> 35.4 | J8: =Data2!ET175 -> 35.6 | K8: =Data3!T175 -> 33 | L8: =Data3!U175 -> 34.5 | M8: =Data3!AZ175 -> 39 | N8: =Data3!FP175 -> 51.1 | O8: =Data3!FQ175 -> 34.6 | P8: =Data3!GV175 -> 41.4 | Q8: =Data4!BV175 -> 31.3 | R8: =Data4!BW175 -> 43.9 | S8: =Data4!DB175 -> 45 | T8: =Data4!HR175 -> 54.7 | U8: =Data4!HS175 -> 37.4 | V8: =Data5!H175 -> 40.5 | W8: =Data5!DX175 -> 38 | X8: =Data5!DY175 -> 30 | Y8: =Data5!FD175 -> 37.9 | Z8: =Data6!AD175 -> 36.5 | AA8: =Data6!AE175 -> 36.3 | AB8: =Data6!BJ175 -> 37.9 | AD8: =A8 -> 32752 | AE8: =B8 -> 34 | AF8: =E8 -> 35.3 | AG8: =H8 -> 40.3 | AH8: =K8 -> 33 | AI8: =N8 -> 51.1 | AJ8: =Q8 -> 31.3 | AK8: =T8 -> 54.7 | AL8: =W8 -> 38 | AM8: =Z8 -> 36.5 | AP8: =A8 -> 32752 | AQ8: =C8 -> 34.9 | AR8: =F8 -> 38.9 | AS8: =I8 -> 35.4 | AT8: =L8 -> 34.5 | AU8: =O8 -> 34.6 | AV8: =R8 -> 43.9 | AW8: =U8 -> 37.4 | AX8: =X8 -> 30 | AY8: =AA8 -> 36.3 | BA8: =A8 -> 32752 | BB8: =D8 -> 36.6 | BC8: =G8 -> 38.3 | BD8: =J8 -> 35.6 | BE8: =M8 -> 39 | BF8: =P8 -> 41.4 | BG8: =S8 -> 45 | BH8: =V8 -> 40.5 | BI8: =Y8 -> 37.9 | BJ8: =AB8 -> 37.9
A9: =Data1!A176 -> 32843 | B9: =Data1!BL176 -> 34 | C9: =Data1!BM176 -> 36.2 | D9: =Data1!CR176 -> 39.1 | E9: =Data1!HH176 -> 36.1 | F9: =Data1!HI176 -> 39.9 | G9: =Data1!IN176 -> 40 | H9: =Data2!DN176 -> 40.3 | I9: =Data2!DO176 -> 36.7 | J9: =Data2!ET176 -> 37.6 | K9: =Data3!T176 -> 33 | L9: =Data3!U176 -> 34.5 | M9: =Data3!AZ176 -> 40.4 | N9: =Data3!FP176 -> 51.1 | O9: =Data3!FQ176 -> 34.7 | P9: =Data3!GV176 -> 41.7 | Q9: =Data4!BV176 -> 31.3 | R9: =Data4!BW176 -> 44.3 | S9: =Data4!DB176 -> 44.1 | T9: =Data4!HR176 -> 54.7 | U9: =Data4!HS176 -> 37.7 | V9: =Data5!H176 -> 40 | W9: =Data5!DX176 -> 38.4 | X9: =Data5!DY176 -> 30.2 | Y9: =Data5!FD176 -> 40 | Z9: =Data6!AD176 -> 36.8 | AA9: =Data6!AE176 -> 37 | AB9: =Data6!BJ176 -> 39.6 | AD9: =A9 -> 32843 | AE9: =B9 -> 34 | AF9: =E9 -> 36.1 | AG9: =H9 -> 40.3 | AH9: =K9 -> 33 | AI9: =N9 -> 51.1 | AJ9: =Q9 -> 31.3 | AK9: =T9 -> 54.7 | AL9: =W9 -> 38.4 | AM9: =Z9 -> 36.8 | AP9: =A9 -> 32843 | AQ9: =C9 -> 36.2 | AR9: =F9 -> 39.9 | AS9: =I9 -> 36.7 | AT9: =L9 -> 34.5 | AU9: =O9 -> 34.7 | AV9: =R9 -> 44.3 | AW9: =U9 -> 37.7 | AX9: =X9 -> 30.2 | AY9: =AA9 -> 37 | BA9: =A9 -> 32843 | BB9: =D9 -> 39.1 | BC9: =G9 -> 40 | BD9: =J9 -> 37.6 | BE9: =M9 -> 40.4 | BF9: =P9 -> 41.7 | BG9: =S9 -> 44.1 | BH9: =V9 -> 40 | BI9: =Y9 -> 40 | BJ9: =AB9 -> 39.6
A10: =Data1!A177 -> 32933 | B10: =Data1!BL177 -> 34 | C10: =Data1!BM177 -> 36.4 | D10: =Data1!CR177 -> 42.1 | E10: =Data1!HH177 -> 36.1 | F10: =Data1!HI177 -> 39.9 | G10: =Data1!IN177 -> 42.6 | H10: =Data2!DN177 -> 40.3 | I10: =Data2!DO177 -> 37.1 | J10: =Data2!ET177 -> 39.9 | K10: =Data3!T177 -> 33 | L10: =Data3!U177 -> 36.1 | M10: =Data3!AZ177 -> 42.6 | N10: =Data3!FP177 -> 51.1 | O10: =Data3!FQ177 -> 34.8 | P10: =Data3!GV177 -> 43.6 | Q10: =Data4!BV177 -> 33 | R10: =Data4!BW177 -> 45.6 | S10: =Data4!DB177 -> 45.9 | T10: =Data4!HR177 -> 54.7 | U10: =Data4!HS177 -> 39.8 | V10: =Data5!H177 -> 41.3 | W10: =Data5!DX177 -> 38.4 | X10: =Data5!DY177 -> 30.9 | Y10: =Data5!FD177 -> 43.6 | Z10: =Data6!AD177 -> 36.8 | AA10: =Data6!AE177 -> 37.4 | AB10: =Data6!BJ177 -> 42.2 | AD10: =A10 -> 32933 | AE10: =B10 -> 34 | AF10: =E10 -> 36.1 | AG10: =H10 -> 40.3 | AH10: =K10 -> 33 | AI10: =N10 -> 51.1 | AJ10: =Q10 -> 33 | AK10: =T10 -> 54.7 | AL10: =W10 -> 38.4 | AM10: =Z10 -> 36.8 | AP10: =A10 -> 32933 | AQ10: =C10 -> 36.4 | AR10: =F10 -> 39.9 | AS10: =I10 -> 37.1 | AT10: =L10 -> 36.1 | AU10: =O10 -> 34.8 | AV10: =R10 -> 45.6 | AW10: =U10 -> 39.8 | AX10: =X10 -> 30.9 | AY10: =AA10 -> 37.4 | BA10: =A10 -> 32933 | BB10: =D10 -> 42.1 | BC10: =G10 -> 42.6 | BD10: =J10 -> 39.9 | BE10: =M10 -> 42.6 | BF10: =P10 -> 43.6 | BG10: =S10 -> 45.9 | BH10: =V10 -> 41.3 | BI10: =Y10 -> 43.6 | BJ10: =AB10 -> 42.2
A11: =Data1!A178 -> 33025 | B11: =Data1!BL178 -> 34 | C11: =Data1!BM178 -> 36.6 | D11: =Data1!CR178 -> 42.1 | E11: =Data1!HH178 -> 36.1 | F11: =Data1!HI178 -> 40 | G11: =Data1!IN178 -> 42.6 | H11: =Data2!DN178 -> 40.3 | I11: =Data2!DO178 -> 37.1 | J11: =Data2!ET178 -> 39.8 | K11: =Data3!T178 -> 33 | L11: =Data3!U178 -> 36.3 | M11: =Data3!AZ178 -> 42.9 | N11: =Data3!FP178 -> 51.1 | O11: =Data3!FQ178 -> 34.9 | P11: =Data3!GV178 -> 44 | Q11: =Data4!BV178 -> 33 | R11: =Data4!BW178 -> 46.9 | S11: =Data4!DB178 -> 43.9 | T11: =Data4!HR178 -> 54.7 | U11: =Data4!HS178 -> 40.2 | V11: =Data5!H178 -> 42.1 | W11: =Data5!DX178 -> 38.4 | X11: =Data5!DY178 -> 33.5 | Y11: =Data5!FD178 -> 44.1 | Z11: =Data6!AD178 -> 36.8 | AA11: =Data6!AE178 -> 37.5 | AB11: =Data6!BJ178 -> 42.2 | AD11: =A11 -> 33025 | AE11: =B11 -> 34 | AF11: =E11 -> 36.1 | AG11: =H11 -> 40.3 | AH11: =K11 -> 33 | AI11: =N11 -> 51.1 | AJ11: =Q11 -> 33 | AK11: =T11 -> 54.7 | AL11: =W11 -> 38.4 | AM11: =Z11 -> 36.8 | AP11: =A11 -> 33025 | AQ11: =C11 -> 36.6 | AR11: =F11 -> 40 | AS11: =I11 -> 37.1 | AT11: =L11 -> 36.3 | AU11: =O11 -> 34.9 | AV11: =R11 -> 46.9 | AW11: =U11 -> 40.2 | AX11: =X11 -> 33.5 | AY11: =AA11 -> 37.5 | BA11: =A11 -> 33025 | BB11: =D11 -> 42.1 | BC11: =G11 -> 42.6 | BD11: =J11 -> 39.8 | BE11: =M11 -> 42.9 | BF11: =P11 -> 44 | BG11: =S11 -> 43.9 | BH11: =V11 -> 42.1 | BI11: =Y11 -> 44.1 | BJ11: =AB11 -> 42.2
A12: =Data1!A179 -> 33117 | B12: =Data1!BL179 -> 27.8 | C12: =Data1!BM179 -> 38.2 | D12: =Data1!CR179 -> 45.1 | E12: =Data1!HH179 -> 38.5 | F12: =Data1!HI179 -> 41.7 | G12: =Data1!IN179 -> 44.9 | H12: =Data2!DN179 -> 40.3 | I12: =Data2!DO179 -> 37.1 | J12: =Data2!ET179 -> 41.1 | K12: =Data3!T179 -> 34.1 | L12: =Data3!U179 -> 36.3 | M12: =Data3!AZ179 -> 44.7 | N12: =Data3!FP179 -> 55.1 | O12: =Data3!FQ179 -> 37.1 | P12: =Data3!GV179 -> 45.3 | Q12: =Data4!BV179 -> 35.3 | R12: =Data4!BW179 -> 46.3 | S12: =Data4!DB179 -> 45.6 | T12: =Data4!HR179 -> 54.7 | U12: =Data4!HS179 -> 40.4 | V12: =Data5!H179 -> 43.2 | W12: =Data5!DX179 -> 39.5 | X12: =Data5!DY179 -> 33.6 | Y12: =Data5!FD179 -> 45.8 | Z12: =Data6!AD179 -> 35.5 | AA12: =Data6!AE179 -> 38.9 | AB12: =Data6!BJ179 -> 44.5 | AD12: =A12 -> 33117 | AE12: =B12 -> 27.8 | AF12: =E12 -> 38.5 | AG12: =H12 -> 40.3 | AH12: =K12 -> 34.1 | AI12: =N12 -> 55.1 | AJ12: =Q12 -> 35.3 | AK12: =T12 -> 54.7 | AL12: =W12 -> 39.5 | AM12: =Z12 -> 35.5 | AP12: =A12 -> 33117 | AQ12: =C12 -> 38.2 | AR12: =F12 -> 41.7 | AS12: =I12 -> 37.1 | AT12: =L12 -> 36.3 | AU12: =O12 -> 37.1 | AV12: =R12 -> 46.3 | AW12: =U12 -> 40.4 | AX12: =X12 -> 33.6 | AY12: =AA12 -> 38.9 | BA12: =A12 -> 33117 | BB12: =D12 -> 45.1 | BC12: =G12 -> 44.9 | BD12: =J12 -> 41.1 | BE12: =M12 -> 44.7 | BF12: =P12 -> 45.3 | BG12: =S12 -> 45.6 | BH12: =V12 -> 43.2 | BI12: =Y12 -> 45.8 | BJ12: =AB12 -> 44.5
A13: =Data1!A180 -> 33208 | B13: =Data1!BL180 -> 35.5 | C13: =Data1!BM180 -> 39.1 | D13: =Data1!CR180 -> 53.1 | E13: =Data1!HH180 -> 38.5 | F13: =Data1!HI180 -> 42.3 | G13: =Data1!IN180 -> 55.8 | H13: =Data2!DN180 -> 40.3 | I13: =Data2!DO180 -> 38.8 | J13: =Data2!ET180 -> 49.6 | K13: =Data3!T180 -> 34.1 | L13: =Data3!U180 -> 36.7 | M13: =Data3!AZ180 -> 53.6 | N13: =Data3!FP180 -> 55.1 | O13: =Data3!FQ180 -> 38.3 | P13: =Data3!GV180 -> 54.6 | Q13: =Data4!BV180 -> 36.3 | R13: =Data4!BW180 -> 51.4 | S13: =Data4!DB180 -> 54.3 | T13: =Data4!HR180 -> 54.7 | U13: =Data4!HS180 -> 41.3 | V13: =Data5!H180 -> 52.7 | W13: =Data5!DX180 -> 40 | X13: =Data5!DY180 -> 34.8 | Y13: =Data5!FD180 -> 55.9 | Z13: =Data6!AD180 -> 38.6 | AA13: =Data6!AE180 -> 39.7 | AB13: =Data6!BJ180 -> 53.7 | AD13: =A13 -> 33208 | AE13: =B13 -> 35.5 | AF13: =E13 -> 38.5 | AG13: =H13 -> 40.3 | AH13: =K13 -> 34.1 | AI13: =N13 -> 55.1 | AJ13: =Q13 -> 36.3 | AK13: =T13 -> 54.7 | AL13: =W13 -> 40 | AM13: =Z13 -> 38.6 | AP13: =A13 -> 33208 | AQ13: =C13 -> 39.1 | AR13: =F13 -> 42.3 | AS13: =I13 -> 38.8 | AT13: =L13 -> 36.7 | AU13: =O13 -> 38.3 | AV13: =R13 -> 51.4 | AW13: =U13 -> 41.3 | AX13: =X13 -> 34.8 | AY13: =AA13 -> 39.7 | BA13: =A13 -> 33208 | BB13: =D13 -> 53.1 | BC13: =G13 -> 55.8 | BD13: =J13 -> 49.6 | BE13: =M13 -> 53.6 | BF13: =P13 -> 54.6 | BG13: =S13 -> 54.3 | BH13: =V13 -> 52.7 | BI13: =Y13 -> 55.9 | BJ13: =AB13 -> 53.7
A14: =Data1!A181 -> 33298 | B14: =Data1!BL181 -> 35.5 | C14: =Data1!BM181 -> 40.1 | D14: =Data1!CR181 -> 44.7 | E14: =Data1!HH181 -> 38.5 | F14: =Data1!HI181 -> 42.1 | G14: =Data1!IN181 -> 47.7 | H14: =Data2!DN181 -> 41.5 | I14: =Data2!DO181 -> 40.5 | J14: =Data2!ET181 -> 41.6 | K14: =Data3!T181 -> 34.1 | L14: =Data3!U181 -> 38.5 | M14: =Data3!AZ181 -> 45.1 | N14: =Data3!FP181 -> 55.1 | O14: =Data3!FQ181 -> 38.2 | P14: =Data3!GV181 -> 45.7 | Q14: =Data4!BV181 -> 36.3 | R14: =Data4!BW181 -> 54.9 | S14: =Data4!DB181 -> 46.4 | T14: =Data4!HR181 -> 54.7 | U14: =Data4!HS181 -> 43.2 | V14: =Data5!H181 -> 45.8 | W14: =Data5!DX181 -> 40 | X14: =Data5!DY181 -> 36.1 | Y14: =Data5!FD181 -> 47.9 | Z14: =Data6!AD181 -> 38.7 | AA14: =Data6!AE181 -> 40 | AB14: =Data6!BJ181 -> 45.4 | AD14: =A14 -> 33298 | AE14: =B14 -> 35.5 | AF14: =E14 -> 38.5 | AG14: =H14 -> 41.5 | AH14: =K14 -> 34.1 | AI14: =N14 -> 55.1 | AJ14: =Q14 -> 36.3 | AK14: =T14 -> 54.7 | AL14: =W14 -> 40 | AM14: =Z14 -> 38.7 | AP14: =A14 -> 33298 | AQ14: =C14 -> 40.1 | AR14: =F14 -> 42.1 | AS14: =I14 -> 40.5 | AT14: =L14 -> 38.5 | AU14: =O14 -> 38.2 | AV14: =R14 -> 54.9 | AW14: =U14 -> 43.2 | AX14: =X14 -> 36.1 | AY14: =AA14 -> 40 | BA14: =A14 -> 33298 | BB14: =D14 -> 44.7 | BC14: =G14 -> 47.7 | BD14: =J14 -> 41.6 | BE14: =M14 -> 45.1 | BF14: =P14 -> 45.7 | BG14: =S14 -> 46.4 | BH14: =V14 -> 45.8 | BI14: =Y14 -> 47.9 | BJ14: =AB14 -> 45.4
A15: =Data1!A182 -> 33390 | B15: =Data1!BL182 -> 35.5 | C15: =Data1!BM182 -> 39.1 | D15: =Data1!CR182 -> 41.6 | E15: =Data1!HH182 -> 38.5 | F15: =Data1!HI182 -> 41.8 | G15: =Data1!IN182 -> 45 | H15: =Data2!DN182 -> 41.5 | I15: =Data2!DO182 -> 40.5 | J15: =Data2!ET182 -> 39.2 | K15: =Data3!T182 -> 34.1 | L15: =Data3!U182 -> 38.7 | M15: =Data3!AZ182 -> 42.8 | N15: =Data3!FP182 -> 55.1 | O15: =Data3!FQ182 -> 38.2 | P15: =Data3!GV182 -> 44.7 | Q15: =Data4!BV182 -> 36.3 | R15: =Data4!BW182 -> 52.3 | S15: =Data4!DB182 -> 45.2 | T15: =Data4!HR182 -> 56.5 | U15: =Data4!HS182 -> 42.3 | V15: =Data5!H182 -> 44.2 | W15: =Data5!DX182 -> 40 | X15: =Data5!DY182 -> 36.2 | Y15: =Data5!FD182 -> 45.4 | Z15: =Data6!AD182 -> 38.7 | AA15: =Data6!AE182 -> 39.8 | AB15: =Data6!BJ182 -> 42.9 | AD15: =A15 -> 33390 | AE15: =B15 -> 35.5 | AF15: =E15 -> 38.5 | AG15: =H15 -> 41.5 | AH15: =K15 -> 34.1 | AI15: =N15 -> 55.1 | AJ15: =Q15 -> 36.3 | AK15: =T15 -> 56.5 | AL15: =W15 -> 40 | AM15: =Z15 -> 38.7 | AP15: =A15 -> 33390 | AQ15: =C15 -> 39.1 | AR15: =F15 -> 41.8 | AS15: =I15 -> 40.5 | AT15: =L15 -> 38.7 | AU15: =O15 -> 38.2 | AV15: =R15 -> 52.3 | AW15: =U15 -> 42.3 | AX15: =X15 -> 36.2 | AY15: =AA15 -> 39.8 | BA15: =A15 -> 33390 | BB15: =D15 -> 41.6 | BC15: =G15 -> 45 | BD15: =J15 -> 39.2 | BE15: =M15 -> 42.8 | BF15: =P15 -> 44.7 | BG15: =S15 -> 45.2 | BH15: =V15 -> 44.2 | BI15: =Y15 -> 45.4 | BJ15: =AB15 -> 42.9
A16: =Data1!A183 -> 33482 | B16: =Data1!BL183 -> 36.8 | C16: =Data1!BM183 -> 40 | D16: =Data1!CR183 -> 44.9 | E16: =Data1!HH183 -> 41 | F16: =Data1!HI183 -> 44.1 | G16: =Data1!IN183 -> 47.1 | H16: =Data2!DN183 -> 41.5 | I16: =Data2!DO183 -> 40.5 | J16: =Data2!ET183 -> 41.2 | K16: =Data3!T183 -> 36.1 | L16: =Data3!U183 -> 38.7 | M16: =Data3!AZ183 -> 45.4 | N16: =Data3!FP183 -> 56.2 | O16: =Data3!FQ183 -> 38.6 | P16: =Data3!GV183 -> 45.9 | Q16: =Data4!BV183 -> 37.6 | R16: =Data4!BW183 -> 50.2 | S16: =Data4!DB183 -> 46.9 | T16: =Data4!HR183 -> 58.3 | U16: =Data4!HS183 -> 42.2 | V16: =Data5!H183 -> 45 | W16: =Data5!DX183 -> 41.3 | X16: =Data5!DY183 -> 36 | Y16: =Data5!FD183 -> 47.7 | Z16: =Data6!AD183 -> 40.3 | AA16: =Data6!AE183 -> 41.1 | AB16: =Data6!BJ183 -> 45.3 | AD16: =A16 -> 33482 | AE16: =B16 -> 36.8 | AF16: =E16 -> 41 | AG16: =H16 -> 41.5 | AH16: =K16 -> 36.1 | AI16: =N16 -> 56.2 | AJ16: =Q16 -> 37.6 | AK16: =T16 -> 58.3 | AL16: =W16 -> 41.3 | AM16: =Z16 -> 40.3 | AP16: =A16 -> 33482 | AQ16: =C16 -> 40 | AR16: =F16 -> 44.1 | AS16: =I16 -> 40.5 | AT16: =L16 -> 38.7 | AU16: =O16 -> 38.6 | AV16: =R16 -> 50.2 | AW16: =U16 -> 42.2 | AX16: =X16 -> 36 | AY16: =AA16 -> 41.1 | BA16: =A16 -> 33482 | BB16: =D16 -> 44.9 | BC16: =G16 -> 47.1 | BD16: =J16 -> 41.2 | BE16: =M16 -> 45.4 | BF16: =P16 -> 45.9 | BG16: =S16 -> 46.9 | BH16: =V16 -> 45 | BI16: =Y16 -> 47.7 | BJ16: =AB16 -> 45.3
A17: =Data1!A184 -> 33573 | B17: =Data1!BL184 -> 37.3 | C17: =Data1!BM184 -> 40 | D17: =Data1!CR184 -> 44.6 | E17: =Data1!HH184 -> 41 | F17: =Data1!HI184 -> 44.1 | G17: =Data1!IN184 -> 46.7 | H17: =Data2!DN184 -> 41.5 | I17: =Data2!DO184 -> 40.5 | J17: =Data2!ET184 -> 41.1 | K17: =Data3!T184 -> 36.1 | L17: =Data3!U184 -> 38.6 | M17: =Data3!AZ184 -> 46 | N17: =Data3!FP184 -> 56.2 | O17: =Data3!FQ184 -> 38.6 | P17: =Data3!GV184 -> 45.5 | Q17: =Data4!BV184 -> 38.3 | R17: =Data4!BW184 -> 48.9 | S17: =Data4!DB184 -> 46.4 | T17: =Data4!HR184 -> 58.3 | U17: =Data4!HS184 -> 42.2 | V17: =Data5!H184 -> 44.9 | W17: =Data5!DX184 -> 41.3 | X17: =Data5!DY184 -> 36.2 | Y17: =Data5!FD184 -> 47.9 | Z17: =Data6!AD184 -> 40.4 | AA17: =Data6!AE184 -> 41.1 | AB17: =Data6!BJ184 -> 45.1 | AD17: =A17 -> 33573 | AE17: =B17 -> 37.3 | AF17: =E17 -> 41 | AG17: =H17 -> 41.5 | AH17: =K17 -> 36.1 | AI17: =N17 -> 56.2 | AJ17: =Q17 -> 38.3 | AK17: =T17 -> 58.3 | AL17: =W17 -> 41.3 | AM17: =Z17 -> 40.4 | AP17: =A17 -> 33573 | AQ17: =C17 -> 40 | AR17: =F17 -> 44.1 | AS17: =I17 -> 40.5 | AT17: =L17 -> 38.6 | AU17: =O17 -> 38.6 | AV17: =R17 -> 48.9 | AW17: =U17 -> 42.2 | AX17: =X17 -> 36.2 | AY17: =AA17 -> 41.1 | BA17: =A17 -> 33573 | BB17: =D17 -> 44.6 | BC17: =G17 -> 46.7 | BD17: =J17 -> 41.1 | BE17: =M17 -> 46 | BF17: =P17 -> 45.5 | BG17: =S17 -> 46.4 | BH17: =V17 -> 44.9 | BI17: =Y17 -> 47.9 | BJ17: =AB17 -> 45.1
A18: =Data1!A185 -> 33664 | B18: =Data1!BL185 -> 37.3 | C18: =Data1!BM185 -> 40 | D18: =Data1!CR185 -> 44.3 | E18: =Data1!HH185 -> 41 | F18: =Data1!HI185 -> 44.1 | G18: =Data1!IN185 -> 46.2 | H18: =Data2!DN185 -> 41.9 | I18: =Data2!DO185 -> 40.5 | J18: =Data2!ET185 -> 40.4 | K18: =Data3!T185 -> 36.1 | L18: =Data3!U185 -> 39.8 | M18: =Data3!AZ185 -> 44.7 | N18: =Data3!FP185 -> 56.2 | O18: =Data3!FQ185 -> 38.6 | P18: =Data3!GV185 -> 45.2 | Q18: =Data4!BV185 -> 38.3 | R18: =Data4!BW185 -> 50.1 | S18: =Data4!DB185 -> 45.8 | T18: =Data4!HR185 -> 58.3 | U18: =Data4!HS185 -> 43 | V18: =Data5!H185 -> 44.8 | W18: =Data5!DX185 -> 41.3 | X18: =Data5!DY185 -> 36.2 | Y18: =Data5!FD185 -> 47.4 | Z18: =Data6!AD185 -> 40.5 | AA18: =Data6!AE185 -> 41.3 | AB18: =Data6!BJ185 -> 44.6 | AD18: =A18 -> 33664 | AE18: =B18 -> 37.3 | AF18: =E18 -> 41 | AG18: =H18 -> 41.9 | AH18: =K18 -> 36.1 | AI18: =N18 -> 56.2 | AJ18: =Q18 -> 38.3 | AK18: =T18 -> 58.3 | AL18: =W18 -> 41.3 | AM18: =Z18 -> 40.5 | AP18: =A18 -> 33664 | AQ18: =C18 -> 40 | AR18: =F18 -> 44.1 | AS18: =I18 -> 40.5 | AT18: =L18 -> 39.8 | AU18: =O18 -> 38.6 | AV18: =R18 -> 50.1 | AW18: =U18 -> 43 | AX18: =X18 -> 36.2 | AY18: =AA18 -> 41.3 | BA18: =A18 -> 33664 | BB18: =D18 -> 44.3 | BC18: =G18 -> 46.2 | BD18: =J18 -> 40.4 | BE18: =M18 -> 44.7 | BF18: =P18 -> 45.2 | BG18: =S18 -> 45.8 | BH18: =V18 -> 44.8 | BI18: =Y18 -> 47.4 | BJ18: =AB18 -> 44.6
A19: =Data1!A186 -> 33756 | B19: =Data1!BL186 -> 37.3 | C19: =Data1!BM186 -> 39.9 | D19: =Data1!CR186 -> 44 | E19: =Data1!HH186 -> 41 | F19: =Data1!HI186 -> 44 | G19: =Data1!IN186 -> 46.4 | H19: =Data2!DN186 -> 42.4 | I19: =Data2!DO186 -> 40.5 | J19: =Data2!ET186 -> 40.7 | K19: =Data3!T186 -> 36.1 | L19: =Data3!U186 -> 39.6 | M19: =Data3!AZ186 -> 45.5 | N19: =Data3!FP186 -> 56.2 | O19: =Data3!FQ186 -> 38.3 | P19: =Data3!GV186 -> 45.7 | Q19: =Data4!BV186 -> 38.3 | R19: =Data4!BW186 -> 49.2 | S19: =Data4!DB186 -> 45.5 | T19: =Data4!HR186 -> 58.3 | U19: =Data4!HS186 -> 43.4 | V19: =Data5!H186 -> 45.2 | W19: =Data5!DX186 -> 41.3 | X19: =Data5!DY186 -> 36.2 | Y19: =Data5!FD186 -> 48 | Z19: =Data6!AD186 -> 40.5 | AA19: =Data6!AE186 -> 41.2 | AB19: =Data6!BJ186 -> 44.8 | AD19: =A19 -> 33756 | AE19: =B19 -> 37.3 | AF19: =E19 -> 41 | AG19: =H19 -> 42.4 | AH19: =K19 -> 36.1 | AI19: =N19 -> 56.2 | AJ19: =Q19 -> 38.3 | AK19: =T19 -> 58.3 | AL19: =W19 -> 41.3 | AM19: =Z19 -> 40.5 | AP19: =A19 -> 33756 | AQ19: =C19 -> 39.9 | AR19: =F19 -> 44 | AS19: =I19 -> 40.5 | AT19: =L19 -> 39.6 | AU19: =O19 -> 38.3 | AV19: =R19 -> 49.2 | AW19: =U19 -> 43.4 | AX19: =X19 -> 36.2 | AY19: =AA19 -> 41.2 | BA19: =A19 -> 33756 | BB19: =D19 -> 44 | BC19: =G19 -> 46.4 | BD19: =J19 -> 40.7 | BE19: =M19 -> 45.5 | BF19: =P19 -> 45.7 | BG19: =S19 -> 45.5 | BH19: =V19 -> 45.2 | BI19: =Y19 -> 48 | BJ19: =AB19 -> 44.8
... A127: =Data1!A294 -> 43617 | B127: =Data1!BL294 -> 135.2 | C127: =Data1!BM294 -> 130.3 | D127: =Data1!CR294 -> 104.3 | E127: =Data1!HH294 -> 144.5 | F127: =Data1!HI294 -> 158.7 | G127: =Data1!IN294 -> 104.9 | H127: =Data2!DN294 -> 133.8 | I127: =Data2!DO294 -> 133.7 | J127: =Data2!ET294 -> 102.1 | K127: =Data3!T294 -> 141.9 | L127: =Data3!U294 -> 142.5 | M127: =Data3!AZ294 -> 105 | N127: =Data3!FP294 -> 143.2 | O127: =Data3!FQ294 -> 119.3 | P127: =Data3!GV294 -> 102.4 | Q127: =Data4!BV294 -> 106.8 | R127: =Data4!BW294 -> 124.4 | S127: =Data4!DB294 -> 102.7 | T127: =Data4!HR294 -> 130.3 | U127: =Data4!HS294 -> 109.3 | V127: =Data5!H294 -> 95.1 | W127: =Data5!DX294 -> 138.3 | X127: =Data5!DY294 -> 157.5 | Y127: =Data5!FD294 -> 102.1 | Z127: =Data6!AD294 -> 138.4 | AA127: =Data6!AE294 -> 144 | AB127: =Data6!BJ294 -> 103.8 | AD127: =A127 -> 43617 | AE127: =B127 -> 135.2 | AF127: =E127 -> 144.5 | AG127: =H127 -> 133.8 | AH127: =K127 -> 141.9 | AI127: =N127 -> 143.2 | AJ127: =Q127 -> 106.8 | AK127: =T127 -> 130.3 | AL127: =W127 -> 138.3 | AM127: =Z127 -> 138.4 | AP127: =A127 -> 43617 | AQ127: =C127 -> 130.3 | AR127: =F127 -> 158.7 | AS127: =I127 -> 133.7 | AT127: =L127 -> 142.5 | AU127: =O127 -> 119.3 | AV127: =R127 -> 124.4 | AW127: =U127 -> 109.3 | AX127: =X127 -> 157.5 | AY127: =AA127 -> 144 | BA127: =A127 -> 43617 | BB127: =D127 -> 104.3 | BC127: =G127 -> 104.9 | BD127: =J127 -> 102.1 | BE127: =M127 -> 105 | BF127: =P127 -> 102.4 | BG127: =S127 -> 102.7 | BH127: =V127 -> 95.1 | BI127: =Y127 -> 102.1 | BJ127: =AB127 -> 103.8
A130: 2. Summary Statistics (Sep-1989 to Jun-2019, index 2011–12 = 100)
A132: Electricity
A133: City | B133: Mean | C133: Median | D133: Std Dev | E133: Min | F133: Max | G133: Start (Sep-89) | H133: Latest (Jun-19) | I133: Total % change | J133: Avg annual %
A134: Sydney | B134: =AVERAGE(B$8:B$127) -> 66.723333 | C134: =MEDIAN(B$8:B$127) -> 47.45 | D134: =_xlfn.STDEV.S(B$8:B$127) -> 35.189818 | E134: =MIN(B$8:B$127) -> 27.8 | F134: =MAX(B$8:B$127) -> 140.5 | G134: =B$8 -> 34 | H134: =B$127 -> 135.2 | I134: =(B$127/B$8)-1 -> 2.9764706 | J134: =(B$127/B$8)^(1/(($A$127-$A$8)/365.25))-1 -> 0.047498448
A135: Melbourne | B135: =AVERAGE(E$8:E$127) -> 72.353333 | C135: =MEDIAN(E$8:E$127) -> 55.05 | D135: =_xlfn.STDEV.S(E$8:E$127) -> 35.020136 | E135: =MIN(E$8:E$127) -> 35.3 | F135: =MAX(E$8:E$127) -> 152.7 | G135: =E$8 -> 35.3 | H135: =E$127 -> 144.5 | I135: =(E$127/E$8)-1 -> 3.0934844 | J135: =(E$127/E$8)^(1/(($A$127-$A$8)/365.25))-1 -> 0.048520216
A136: Brisbane | B136: =AVERAGE(H$8:H$127) -> 74.1 | C136: =MEDIAN(H$8:H$127) -> 54.8 | D136: =_xlfn.STDEV.S(H$8:H$127) -> 38.403094 | E136: =MIN(H$8:H$127) -> 40.3 | F136: =MAX(H$8:H$127) -> 151.1 | G136: =H$8 -> 40.3 | H136: =H$127 -> 133.8 | I136: =(H$127/H$8)-1 -> 2.3200993 | J136: =(H$127/H$8)^(1/(($A$127-$A$8)/365.25))-1 -> 0.041165089
A137: Adelaide | B137: =AVERAGE(K$8:K$127) -> 69.184167 | C137: =MEDIAN(K$8:K$127) -> 61.3 | D137: =_xlfn.STDEV.S(K$8:K$127) -> 34.956686 | E137: =MIN(K$8:K$127) -> 33 | F137: =MAX(K$8:K$127) -> 147.4 | G137: =K$8 -> 33 | H137: =K$127 -> 141.9 | I137: =(K$127/K$8)-1 -> 3.3 | J137: =(K$127/K$8)^(1/(($A$127-$A$8)/365.25))-1 -> 0.050256516
A138: Perth | B138: =AVERAGE(N$8:N$127) -> 77.544167 | C138: =MEDIAN(N$8:N$127) -> 63.7 | D138: =_xlfn.STDEV.S(N$8:N$127) -> 27.457282 | E138: =MIN(N$8:N$127) -> 51.1 | F138: =MAX(N$8:N$127) -> 143.2 | G138: =N$8 -> 51.1 | H138: =N$127 -> 143.2 | I138: =(N$127/N$8)-1 -> 1.8023483 | J138: =(N$127/N$8)^(1/(($A$127-$A$8)/365.25))-1 -> 0.03524801
A139: Hobart | B139: =AVERAGE(Q$8:Q$127) -> 66.298333 | C139: =MEDIAN(Q$8:Q$127) -> 57.8 | D139: =_xlfn.STDEV.S(Q$8:Q$127) -> 26.052271 | E139: =MIN(Q$8:Q$127) -> 31.3 | F139: =MAX(Q$8:Q$127) -> 112.7 | G139: =Q$8 -> 31.3 | H139: =Q$127 -> 106.8 | I139: =(Q$127/Q$8)-1 -> 2.4121406 | J139: =(Q$127/Q$8)^(1/(($A$127-$A$8)/365.25))-1 -> 0.042122636
A140: Darwin | B140: =AVERAGE(T$8:T$127) -> 82.725833 | C140: =MEDIAN(T$8:T$127) -> 68.6 | D140: =_xlfn.STDEV.S(T$8:T$127) -> 28.239354 | E140: =MIN(T$8:T$127) -> 54.7 | F140: =MAX(T$8:T$127) -> 137.9 | G140: =T$8 -> 54.7 | H140: =T$127 -> 130.3 | I140: =(T$127/T$8)-1 -> 1.3820841 | J140: =(T$127/T$8)^(1/(($A$127-$A$8)/365.25))-1 -> 0.029608718
A141: Canberra | B141: =AVERAGE(W$8:W$127) -> 73.500833 | C141: =MEDIAN(W$8:W$127) -> 63.5 | D141: =_xlfn.STDEV.S(W$8:W$127) -> 31.168422 | E141: =MIN(W$8:W$127) -> 38 | F141: =MAX(W$8:W$127) -> 140.4 | G141: =W$8 -> 38 | H141: =W$127 -> 138.3 | I141: =(W$127/W$8)-1 -> 2.6394737 | J141: =(W$127/W$8)^(1/(($A$127-$A$8)/365.25))-1 -> 0.0443847
A142: Australia | B142: =AVERAGE(Z$8:Z$127) -> 70.6375 | C142: =MEDIAN(Z$8:Z$127) -> 54.4 | D142: =_xlfn.STDEV.S(Z$8:Z$127) -> 34.330348 | E142: =MIN(Z$8:Z$127) -> 35.5 | F142: =MAX(Z$8:Z$127) -> 141.6 | G142: =Z$8 -> 36.5 | H142: =Z$127 -> 138.4 | I142: =(Z$127/Z$8)-1 -> 2.7917808 | J142: =(Z$127/Z$8)^(1/(($A$127-$A$8)/365.25))-1 -> 0.045825054
A144: Gas and other household fuels
A145: City | B145: Mean | C145: Median | D145: Std Dev | E145: Min | F145: Max | G145: Start (Sep-89) | H145: Latest (Jun-19) | I145: Total % change | J145: Avg annual %
A146: Sydney | B146: =AVERAGE(C$8:C$127) -> 75.134167 | C146: =MEDIAN(C$8:C$127) -> 68.7 | D146: =_xlfn.STDEV.S(C$8:C$127) -> 33.868615 | E146: =MIN(C$8:C$127) -> 34.9 | F146: =MAX(C$8:C$127) -> 140.9 | G146: =C$8 -> 34.9 | H146: =C$127 -> 130.3 | I146: =(C$127/C$8)-1 -> 2.7335244 | J146: =(C$127/C$8)^(1/(($A$127-$A$8)/365.25))-1 -> 0.045280846
A147: Melbourne | B147: =AVERAGE(F$8:F$127) -> 78.556667 | C147: =MEDIAN(F$8:F$127) -> 63.85 | D147: =_xlfn.STDEV.S(F$8:F$127) -> 35.634328 | E147: =MIN(F$8:F$127) -> 38.9 | F147: =MAX(F$8:F$127) -> 163.8 | G147: =F$8 -> 38.9 | H147: =F$127 -> 158.7 | I147: =(F$127/F$8)-1 -> 3.0796915 | J147: =(F$127/F$8)^(1/(($A$127-$A$8)/365.25))-1 -> 0.048401254
A148: Brisbane | B148: =AVERAGE(I$8:I$127) -> 72.4675 | C148: =MEDIAN(I$8:I$127) -> 52.8 | D148: =_xlfn.STDEV.S(I$8:I$127) -> 34.861197 | E148: =MIN(I$8:I$127) -> 35.4 | F148: =MAX(I$8:I$127) -> 135.1 | G148: =I$8 -> 35.4 | H148: =I$127 -> 133.7 | I148: =(I$127/I$8)-1 -> 2.7768362 | J148: =(I$127/I$8)^(1/(($A$127-$A$8)/365.25))-1 -> 0.045686222
A149: Adelaide | B149: =AVERAGE(L$8:L$127) -> 77.159167 | C149: =MEDIAN(L$8:L$127) -> 64.55 | D149: =_xlfn.STDEV.S(L$8:L$127) -> 38.334693 | E149: =MIN(L$8:L$127) -> 34.5 | F149: =MAX(L$8:L$127) -> 150 | G149: =L$8 -> 34.5 | H149: =L$127 -> 142.5 | I149: =(L$127/L$8)-1 -> 3.1304348 | J149: =(L$127/L$8)^(1/(($A$127-$A$8)/365.25))-1 -> 0.048837009
A150: Perth | B150: =AVERAGE(O$8:O$127) -> 66.766667 | C150: =MEDIAN(O$8:O$127) -> 50.35 | D150: =_xlfn.STDEV.S(O$8:O$127) -> 32.84808 | E150: =MIN(O$8:O$127) -> 34.6 | F150: =MAX(O$8:O$127) -> 123.9 | G150: =O$8 -> 34.6 | H150: =O$127 -> 119.3 | I150: =(O$127/O$8)-1 -> 2.4479769 | J150: =(O$127/O$8)^(1/(($A$127-$A$8)/365.25))-1 -> 0.04248872
A151: Hobart | B151: =AVERAGE(R$8:R$127) -> 77.354167 | C151: =MEDIAN(R$8:R$127) -> 73.25 | D151: =_xlfn.STDEV.S(R$8:R$127) -> 25.040813 | E151: =MIN(R$8:R$127) -> 43.9 | F151: =MAX(R$8:R$127) -> 124.8 | G151: =R$8 -> 43.9 | H151: =R$127 -> 124.4 | I151: =(R$127/R$8)-1 -> 1.833713 | J151: =(R$127/R$8)^(1/(($A$127-$A$8)/365.25))-1 -> 0.035635433
A152: Darwin | B152: =AVERAGE(U$8:U$127) -> 75.468333 | C152: =MEDIAN(U$8:U$127) -> 71.7 | D152: =_xlfn.STDEV.S(U$8:U$127) -> 25.236328 | E152: =MIN(U$8:U$127) -> 37.4 | F152: =MAX(U$8:U$127) -> 116.5 | G152: =U$8 -> 37.4 | H152: =U$127 -> 109.3 | I152: =(U$127/U$8)-1 -> 1.9224599 | J152: =(U$127/U$8)^(1/(($A$127-$A$8)/365.25))-1 -> 0.036709611
A153: Canberra | B153: =AVERAGE(X$8:X$127) -> 73.423333 | C153: =MEDIAN(X$8:X$127) -> 59.85 | D153: =_xlfn.STDEV.S(X$8:X$127) -> 37.164433 | E153: =MIN(X$8:X$127) -> 30 | F153: =MAX(X$8:X$127) -> 157.5 | G153: =X$8 -> 30 | H153: =X$127 -> 157.5 | I153: =(X$127/X$8)-1 -> 4.25 | J153: =(X$127/X$8)^(1/(($A$127-$A$8)/365.25))-1 -> 0.057327873
A154: Australia | B154: =AVERAGE(AA$8:AA$127) -> 75.545833 | C154: =MEDIAN(AA$8:AA$127) -> 62.65 | D154: =_xlfn.STDEV.S(AA$8:AA$127) -> 34.777767 | E154: =MIN(AA$8:AA$127) -> 36.3 | F154: =MAX(AA$8:AA$127) -> 147.3 | G154: =AA$8 -> 36.3 | H154: =AA$127 -> 144 | I154: =(AA$127/AA$8)-1 -> 2.9669421 | J154: =(AA$127/AA$8)^(1/(($A$127-$A$8)/365.25))-1 -> 0.04741397
A156: Automotive fuel
A157: City | B157: Mean | C157: Median | D157: Std Dev | E157: Min | F157: Max | G157: Start (Sep-89) | H157: Latest (Jun-19) | I157: Total % change | J157: Avg annual %
A158: Sydney | B158: =AVERAGE(D$8:D$127) -> 71.229167 | C158: =MEDIAN(D$8:D$127) -> 69.1 | D158: =_xlfn.STDEV.S(D$8:D$127) -> 22.55533 | E158: =MIN(D$8:D$127) -> 36.6 | F158: =MAX(D$8:D$127) -> 108.3 | G158: =D$8 -> 36.6 | H158: =D$127 -> 104.3 | I158: =(D$127/D$8)-1 -> 1.8497268 | J158: =(D$127/D$8)^(1/(($A$127-$A$8)/365.25))-1 -> 0.035831644
A159: Melbourne | B159: =AVERAGE(G$8:G$127) -> 72.358333 | C159: =MEDIAN(G$8:G$127) -> 68.75 | D159: =_xlfn.STDEV.S(G$8:G$127) -> 22.196118 | E159: =MIN(G$8:G$127) -> 38.3 | F159: =MAX(G$8:G$127) -> 110.2 | G159: =G$8 -> 38.3 | H159: =G$127 -> 104.9 | I159: =(G$127/G$8)-1 -> 1.7389034 | J159: =(G$127/G$8)^(1/(($A$127-$A$8)/365.25))-1 -> 0.034451345
A160: Brisbane | B160: =AVERAGE(J$8:J$127) -> 67.579167 | C160: =MEDIAN(J$8:J$127) -> 62.25 | D160: =_xlfn.STDEV.S(J$8:J$127) -> 23.808038 | E160: =MIN(J$8:J$127) -> 35.6 | F160: =MAX(J$8:J$127) -> 108.4 | G160: =J$8 -> 35.6 | H160: =J$127 -> 102.1 | I160: =(J$127/J$8)-1 -> 1.8679775 | J160: =(J$127/J$8)^(1/(($A$127-$A$8)/365.25))-1 -> 0.036053968
A161: Adelaide | B161: =AVERAGE(M$8:M$127) -> 71.993333 | C161: =MEDIAN(M$8:M$127) -> 69.75 | D161: =_xlfn.STDEV.S(M$8:M$127) -> 21.60793 | E161: =MIN(M$8:M$127) -> 39 | F161: =MAX(M$8:M$127) -> 109.5 | G161: =M$8 -> 39 | H161: =M$127 -> 105 | I161: =(M$127/M$8)-1 -> 1.6923077 | J161: =(M$127/M$8)^(1/(($A$127-$A$8)/365.25))-1 -> 0.033854811
A162: Perth | B162: =AVERAGE(P$8:P$127) -> 71.675833 | C162: =MEDIAN(P$8:P$127) -> 68.2 | D162: =_xlfn.STDEV.S(P$8:P$127) -> 21.6915 | E162: =MIN(P$8:P$127) -> 41.4 | F162: =MAX(P$8:P$127) -> 108.6 | G162: =P$8 -> 41.4 | H162: =P$127 -> 102.4 | I162: =(P$127/P$8)-1 -> 1.47343 | J162: =(P$127/P$8)^(1/(($A$127-$A$8)/365.25))-1 -> 0.030912012
A163: Hobart | B163: =AVERAGE(S$8:S$127) -> 72.950833 | C163: =MEDIAN(S$8:S$127) -> 70.05 | D163: =_xlfn.STDEV.S(S$8:S$127) -> 21.802166 | E163: =MIN(S$8:S$127) -> 43.9 | F163: =MAX(S$8:S$127) -> 108.9 | G163: =S$8 -> 45 | H163: =S$127 -> 102.7 | I163: =(S$127/S$8)-1 -> 1.2822222 | J163: =(S$127/S$8)^(1/(($A$127-$A$8)/365.25))-1 -> 0.028127466
A164: Darwin | B164: =AVERAGE(V$8:V$127) -> 71.910833 | C164: =MEDIAN(V$8:V$127) -> 67.85 | D164: =_xlfn.STDEV.S(V$8:V$127) -> 22.036508 | E164: =MIN(V$8:V$127) -> 40 | F164: =MAX(V$8:V$127) -> 112.8 | G164: =V$8 -> 40.5 | H164: =V$127 -> 95.1 | I164: =(V$127/V$8)-1 -> 1.3481481 | J164: =(V$127/V$8)^(1/(($A$127-$A$8)/365.25))-1 -> 0.029112191
A165: Canberra | B165: =AVERAGE(Y$8:Y$127) -> 72.865833 | C165: =MEDIAN(Y$8:Y$127) -> 68.5 | D165: =_xlfn.STDEV.S(Y$8:Y$127) -> 21.810665 | E165: =MIN(Y$8:Y$127) -> 37.9 | F165: =MAX(Y$8:Y$127) -> 110.8 | G165: =Y$8 -> 37.9 | H165: =Y$127 -> 102.1 | I165: =(Y$127/Y$8)-1 -> 1.6939314 | J165: =(Y$127/Y$8)^(1/(($A$127-$A$8)/365.25))-1 -> 0.033875765
A166: Australia | B166: =AVERAGE(AB$8:AB$127) -> 71.269167 | C166: =MEDIAN(AB$8:AB$127) -> 67.95 | D166: =_xlfn.STDEV.S(AB$8:AB$127) -> 22.35986 | E166: =MIN(AB$8:AB$127) -> 37.9 | F166: =MAX(AB$8:AB$127) -> 109.1 | G166: =AB$8 -> 37.9 | H166: =AB$127 -> 103.8 | I166: =(AB$127/AB$8)-1 -> 1.7387863 | J166: =(AB$127/AB$8)^(1/(($A$127-$A$8)/365.25))-1 -> 0.034449858

Sheet Data1
B1: Index Numbers ; Food and non-alcoholic beverages ; Sydney ; | C1: Index Numbers ; Bread and cereal products ; Sydney ; | D1: Index Numbers ; Bread ; Sydney ; | E1: Index Numbers ; Cakes and biscuits ; Sydney ; | F1: Index Numbers ; Breakfast cereals ; Sydney ; | G1: Index Numbers ; Other cereal products ; Sydney ; | H1: Index Numbers ; Meat and seafoods ; Sydney ; | I1: Index Numbers ; Beef and veal ; Sydney ; | J1: Index Numbers ; Pork ; Sydney ; | K1: Index Numbers ; Lamb and goat ; Sydney ; | L1: Index Numbers ; Poultry ; Sydney ; | M1: Index Numbers ; Other meats ; Sydney ; | N1: Index Numbers ; Fish and other seafood ; Sydney ; | O1: Index Numbers ; Dairy and related products ; Sydney ; | P1: Index Numbers ; Milk ; Sydney ; | Q1: Index Numbers ; Cheese ; Sydney ; | R1: Index Numbers ; Ice cream and other dairy products ; Sydney ; | S1: Index Numbers ; Fruit and vegetables ; Sydney ; | T1: Index Numbers ; Fruit ; Sydney ; | U1: Index Numbers ; Vegetables ; Sydney ; | V1: Index Numbers ; Food products n.e.c. ; Sydney ; | W1: Index Numbers ; Eggs ; Sydney ; | X1: Index Numbers ; Jams, honey and spreads ; Sydney ; | Y1: Index Numbers ; Food additives and condiments ; Sydney ; | Z1: Index Numbers ; Oils and fats ; Sydney ; | AA1: Index Numbers ; Snacks and confectionery ; Sydney ; | AB1: Index Numbers ; Other food products n.e.c. ; Sydney ; | AC1: Index Numbers ; Non-alcoholic beverages ; Sydney ; | AD1: Index Numbers ; Coffee, tea and cocoa ; Sydney ; | AE1: Index Numbers ; Waters, soft drinks and juices ; Sydney ; | AF1: Index Numbers ; Meals out and take away foods ; Sydney ; | AG1: Index Numbers ; Restaurant meals ; Sydney ; | AH1: Index Numbers ; Take away and fast foods ; Sydney ; | AI1: Index Numbers ; Alcohol and tobacco ; Sydney ; | AJ1: Index Numbers ; Alcoholic beverages ; Sydney ; | AK1: Index Numbers ; Spirits ; Sydney ; | AL1: Index Numbers ; Wine ; Sydney ; | AM1: Index Numbers ; Beer ; Sydney ; | AN1: Index Numbers ; Tobacco ; Sydney ; | AO1: Index Numbers ; Tobacco ; Sydney ; | AP1: Index Numbers ; Clothing and footwear ; Sydney ; | AQ1: Index Numbers ; Garments ; Sydney ; | AR1: Index Numbers ; Garments for men ; Sydney ; | AS1: Index Numbers ; Garments for women ; Sydney ; | AT1: Index Numbers ; Garments for infants and children ; Sydney ; | AU1: Index Numbers ; Footwear ; Sydney ; | AV1: Index Numbers ; Footwear for men ; Sydney ; | AW1: Index Numbers ; Footwear for women ; Sydney ; | AX1: Index Numbers ; Footwear for infants and children ; Sydney ; | AY1: Index Numbers ; Accessories and clothing services ; Sydney ; | AZ1: Index Numbers ; Accessories ; Sydney ; | BA1: Index Numbers ; Cleaning, repair and hire of clothing and footwear ; Sydney ; | BB1: Index Numbers ; Housing ; Sydney ; | BC1: Index Numbers ; Rents ; Sydney ; | BD1: Index Numbers ; Rents ; Sydney ; | BE1: Index Numbers ; New dwelling purchase by owner-occupiers ; Sydney ; | BF1: Index Numbers ; New dwelling purchase by owner-occupiers ; Sydney ; | BG1: Index Numbers ; Other housing ; Sydney ; | BH1: Index Numbers ; Maintenance and repair of the dwelling ; Sydney ; | BI1: Index Numbers ; Property rates and charges ; Sydney ; | BJ1: Index Numbers ; Utilities ; Sydney ; | BK1: Index Numbers ; Water and sewerage ; Sydney ; | BL1: Index Numbers ; Electricity ; Sydney ; | BM1: Index Numbers ; Gas and other household fuels ; Sydney ; | BN1: Index Numbers ; Furnishings, household equipment and services ; Sydney ; | BO1: Index Numbers ; Furniture and furnishings ; Sydney ; | BP1: Index Numbers ; Furniture ; Sydney ; | BQ1: Index Numbers ; Carpets and other floor coverings ; Sydney ; | BR1: Index Numbers ; Household textiles ; Sydney ; | BS1: Index Numbers ; Household textiles ; Sydney ; | BT1: Index Numbers ; Household appliances, utensils and tools ; Sydney ; | BU1: Index Numbers ; Major household appliances ; Sydney ; | BV1: Index Numbers ; Small electric household appliances ; Sydney ; | BW1: Index Numbers ; Glassware, tableware and household utensils ; Sydney ; | BX1: Index Numbers ; Tools and equipment for house and garden ; Sydney ; | BY1: Index Numbers ; Non-durable household products ; Sydney ; | BZ1: Index Numbers ; Cleaning and maintenance products ; Sydney ; | CA1: Index Numbers ; Personal care products ; Sydney ; | CB1: Index Numbers ; Other non-durable household products ; Sydney ; | CC1: Index Numbers ; Domestic and household services ; Sydney ; | CD1: Index Numbers ; Child care ; Sydney ; | CE1: Index Numbers ; Hairdressing and personal grooming services ; Sydney ; | CF1: Index Numbers ; Other household services ; Sydney ; | CG1: Index Numbers ; Health ; Sydney ; | CH1: Index Numbers ; Medical products, appliances and equipment ; Sydney ; | CI1: Index Numbers ; Pharmaceutical products ; Sydney ; | CJ1: Index Numbers ; Therapeutic appliances and equipment ; Sydney ; | CK1: Index Numbers ; Medical, dental and hospital services ; Sydney ; | CL1: Index Numbers ; Medical and hospital services ; Sydney ; | CM1: Index Numbers ; Dental services ; Sydney ; | CN1: Index Numbers ; Transport ; Sydney ; | CO1: Index Numbers ; Private motoring ; Sydney ; | CP1: Index Numbers ; Motor vehicles ; Sydney ; | CQ1: Index Numbers ; Spare parts and accessories for motor vehicles ; Sydney ; | CR1: Index Numbers ; Automotive fuel ; Sydney ; | CS1: Index Numbers ; Maintenance and repair of motor vehicles ; Sydney ; | CT1: Index Numbers ; Other services in respect of motor vehicles ; Sydney ; | CU1: Index Numbers ; Urban transport fares ; Sydney ; | CV1: Index Numbers ; Urban transport fares ; Sydney ; | CW1: Index Numbers ; Communication ; Sydney ; | CX1: Index Numbers ; Communication ; Sydney ; | CY1: Index Numbers ; Postal services ; Sydney ; | CZ1: Index Numbers ; Telecommunication equipment and services ; Sydney ; | DA1: Index Numbers ; Recreation and culture ; Sydney ; | DB1: Index Numbers ; Audio, visual and computing equipment and services ; Sydney ; | DC1: Index Numbers ; Audio, visual and computing equipment ; Sydney ; | DD1: Index Numbers ; Audio, visual and computing media and services ; Sydney ; | DE1: Index Numbers ; Newspapers, books and stationery ; Sydney ; | DF1: Index Numbers ; Books ; Sydney ; | DG1: Index Numbers ; Newspapers, magazines and stationery ; Sydney ; | DH1: Index Numbers ; Holiday travel and accommodation ; Sydney ; | DI1: Index Numbers ; Domestic holiday travel and accommodation ; Sydney ; | DJ1: Index Numbers ; International holiday travel and accommodation ; Sydney ; | DK1: Index Numbers ; Other recreation, sport and culture ; Sydney ; | DL1: Index Numbers ; Equipment for sports, camping and open-air recreation ; Sydney ; | DM1: Index Numbers ; Games, toys and hobbies ; Sydney ; | DN1: Index Numbers ; Pets and related products ; Sydney ; | DO1: Index Numbers ; Veterinary and other services for pets ; Sydney ; | DP1: Index Numbers ; Sports participation ; Sydney ; | DQ1: Index Numbers ; Other recreational, sporting and cultural services ; Sydney ; | DR1: Index Numbers ; Education ; Sydney ; | DS1: Index Numbers ; Education ; Sydney ; | DT1: Index Numbers ; Preschool and primary education ; Sydney ; | DU1: Index Numbers ; Secondary education ; Sydney ; | DV1: Index Numbers ; Tertiary education ; Sydney ; | DW1: Index Numbers ; Insurance and financial services ; Sydney ; | DX1: Index Numbers ; Insurance ; Sydney ; | DY1: Index Numbers ; Insurance ; Sydney ; | DZ1: Index Numbers ; Financial services ; Sydney ; | EA1: Index Numbers ; Deposit and loan facilities (direct charges) ; Sydney ; | EB1: Index Numbers ; Other financial services ; Sydney ; | EC1: Index Numbers ; All groups CPI ; Sydney ; | ED1: Index Numbers ; Tradables ; Sydney ; | EE1: Index Numbers ; Non-tradables ; Sydney ; | EF1: Index Numbers ; All groups, goods component ; Sydney ; | EG1: Index Numbers ; All groups, services component ; Sydney ; | EH1: Index Numbers ; All groups CPI including deposit and loan facilities (indirect charges) ; Sydney ; | EI1: Index Numbers ; All groups CPI excluding Food and non-alcoholic beverages ; Sydney ; | EJ1: Index Numbers ; All groups CPI excluding Alcohol and tobacco ; Sydney ; | EK1: Index Numbers ; All groups CPI excluding Clothing and footwear ; Sydney ; | EL1: Index Numbers ; All groups CPI excluding Housing ; Sydney ; | EM1: Index Numbers ; All groups CPI excluding Furnishings, household equipment and services ; Sydney ; | EN1: Index Numbers ; All groups CPI excluding Health ; Sydney ; | EO1: Index Numbers ; All groups CPI excluding Transport ; Sydney ; | EP1: Index Numbers ; All groups CPI excluding Communication ; Sydney ; | EQ1: Index Numbers ; All groups CPI excluding Recreation and culture ; Sydney ; | ER1: Index Numbers ; All groups CPI excluding Education ; Sydney ; | ES1: Index Numbers ; All groups CPI excluding Insurance and financial services ; Sydney ; | ET1: Index Numbers ; All groups CPI excluding Housing and Insurance and financial services ; Sydney ; | EU1: Index Numbers ; All groups CPI excluding Medical and hospital services ; Sydney ; | EV1: Index Numbers ; All groups CPI excluding food and energy ; Sydney ; | EW1: Index Numbers ; All groups CPI excluding 'volatile items' ; Sydney ; | EX1: Index Numbers ; Food and non-alcoholic beverages ; Melbourne ; | EY1: Index Numbers ; Bread and cereal products ; Melbourne ; | EZ1: Index Numbers ; Bread ; Melbourne ; | FA1: Index Numbers ; Cakes and biscuits ; Melbourne ; | FB1: Index Numbers ; Breakfast cereals ; Melbourne ; | FC1: Index Numbers ; Other cereal products ; Melbourne ; | FD1: Index Numbers ; Meat and seafoods ; Melbourne ; | FE1: Index Numbers ; Beef and veal ; Melbourne ; | FF1: Index Numbers ; Pork ; Melbourne ; | FG1: Index Numbers ; Lamb and goat ; Melbourne ; | FH1: Index Numbers ; Poultry ; Melbourne ; | FI1: Index Numbers ; Other meats ; Melbourne ; | FJ1: Index Numbers ; Fish and other seafood ; Melbourne ; | FK1: Index Numbers ; Dairy and related products ; Melbourne ; | FL1: Index Numbers ; Milk ; Melbourne ; | FM1: Index Numbers ; Cheese ; Melbourne ; | FN1: Index Numbers ; Ice cream and other dairy products ; Melbourne ; | FO1: Index Numbers ; Fruit and vegetables ; Melbourne ; | FP1: Index Numbers ; Fruit ; Melbourne ; | FQ1: Index Numbers ; Vegetables ; Melbourne ; | FR1: Index Numbers ; Food products n.e.c. ; Melbourne ; | FS1: Index Numbers ; Eggs ; Melbourne ; | FT1: Index Numbers ; Jams, honey and spreads ; Melbourne ; | FU1: Index Numbers ; Food additives and condiments ; Melbourne ; | FV1: Index Numbers ; Oils and fats ; Melbourne ; | FW1: Index Numbers ; Snacks and confectionery ; Melbourne ; | FX1: Index Numbers ; Other food products n.e.c. ; Melbourne ; | FY1: Index Numbers ; Non-alcoholic beverages ; Melbourne ; | FZ1: Index Numbers ; Coffee, tea and cocoa ; Melbourne ; | GA1: Index Numbers ; Waters, soft drinks and juices ; Melbourne ; | GB1: Index Numbers ; Meals out and take away foods ; Melbourne ; | GC1: Index Numbers ; Restaurant meals ; Melbourne ; | GD1: Index Numbers ; Take away and fast foods ; Melbourne ; | GE1: Index Numbers ; Alcohol and tobacco ; Melbourne ; | GF1: Index Numbers ; Alcoholic beverages ; Melbourne ; | GG1: Index Numbers ; Spirits ; Melbourne ; | GH1: Index Numbers ; Wine ; Melbourne ; | GI1: Index Numbers ; Beer ; Melbourne ; | GJ1: Index Numbers ; Tobacco ; Melbourne ; | GK1: Index Numbers ; Tobacco ; Melbourne ; | GL1: Index Numbers ; Clothing and footwear ; Melbourne ; | GM1: Index Numbers ; Garments ; Melbourne ; | GN1: Index Numbers ; Garments for men ; Melbourne ; | GO1: Index Numbers ; Garments for women ; Melbourne ; | GP1: Index Numbers ; Garments for infants and children ; Melbourne ; | GQ1: Index Numbers ; Footwear ; Melbourne ; | GR1: Index Numbers ; Footwear for men ; Melbourne ; | GS1: Index Numbers ; Footwear for women ; Melbourne ; | GT1: Index Numbers ; Footwear for infants and children ; Melbourne ; | GU1: Index Numbers ; Accessories and clothing services ; Melbourne ; | GV1: Index Numbers ; Accessories ; Melbourne ; | GW1: Index Numbers ; Cleaning, repair and hire of clothing and footwear ; Melbourne ; | GX1: Index Numbers ; Housing ; Melbourne ; | GY1: Index Numbers ; Rents ; Melbourne ; | GZ1: Index Numbers ; Rents ; Melbourne ; | HA1: Index Numbers ; New dwelling purchase by owner-occupiers ; Melbourne ; | HB1: Index Numbers ; New dwelling purchase by owner-occupiers ; Melbourne ; | HC1: Index Numbers ; Other housing ; Melbourne ; | HD1: Index Numbers ; Maintenance and repair of the dwelling ; Melbourne ; | HE1: Index Numbers ; Property rates and charges ; Melbourne ; | HF1: Index Numbers ; Utilities ; Melbourne ; | HG1: Index Numbers ; Water and sewerage ; Melbourne ; | HH1: Index Numbers ; Electricity ; Melbourne ; | HI1: Index Numbers ; Gas and other household fuels ; Melbourne ; | HJ1: Index Numbers ; Furnishings, household equipment and services ; Melbourne ; | HK1: Index Numbers ; Furniture and furnishings ; Melbourne ; | HL1: Index Numbers ; Furniture ; Melbourne ; | HM1: Index Numbers ; Carpets and other floor coverings ; Melbourne ; | HN1: Index Numbers ; Household textiles ; Melbourne ; | HO1: Index Numbers ; Household textiles ; Melbourne ; | HP1: Index Numbers ; Household appliances, utensils and tools ; Melbourne ; | HQ1: Index Numbers ; Major household appliances ; Melbourne ; | HR1: Index Numbers ; Small electric household appliances ; Melbourne ; | HS1: Index Numbers ; Glassware, tableware and household utensils ; Melbourne ; | HT1: Index Numbers ; Tools and equipment for house and garden ; Melbourne ; | HU1: Index Numbers ; Non-durable household products ; Melbourne ; | HV1: Index Numbers ; Cleaning and maintenance products ; Melbourne ; | HW1: Index Numbers ; Personal care products ; Melbourne ; | HX1: Index Numbers ; Other non-durable household products ; Melbourne ; | HY1: Index Numbers ; Domestic and household services ; Melbourne ; | HZ1: Index Numbers ; Child care ; Melbourne ; | IA1: Index Numbers ; Hairdressing and personal grooming services ; Melbourne ; | IB1: Index Numbers ; Other household services ; Melbourne ; | IC1: Index Numbers ; Health ; Melbourne ; | ID1: Index Numbers ; Medical products, appliances and equipment ; Melbourne ; | IE1: Index Numbers ; Pharmaceutical products ; Melbourne ; | IF1: Index Numbers ; Therapeutic appliances and equipment ; Melbourne ; | IG1: Index Numbers ; Medical, dental and hospital services ; Melbourne ; | IH1: Index Numbers ; Medical and hospital services ; Melbourne ; | II1: Index Numbers ; Dental services ; Melbourne ; | IJ1: Index Numbers ; Transport ; Melbourne ; | IK1: Index Numbers ; Private motoring ; Melbourne ; | IL1: Index Numbers ; Motor vehicles ; Melbourne ; | IM1: Index Numbers ; Spare parts and accessories for motor vehicles ; Melbourne ; | IN1: Index Numbers ; Automotive fuel ; Melbourne ; | IO1: Index Numbers ; Maintenance and repair of motor vehicles ; Melbourne ; | IP1: Index Numbers ; Other services in respect of motor vehicles ; Melbourne ; | IQ1: Index Numbers ; Urban transport fares ; Melbourne ;
A2: Unit | B2: Index Numbers | C2: Index Numbers | D2: Index Numbers | E2: Index Numbers | F2: Index Numbers | G2: Index Numbers | H2: Index Numbers | I2: Index Numbers | J2: Index Numbers | K2: Index Numbers | L2: Index Numbers | M2: Index Numbers | N2: Index Numbers | O2: Index Numbers | P2: Index Numbers | Q2: Index Numbers | R2: Index Numbers | S2: Index Numbers | T2: Index Numbers | U2: Index Numbers | V2: Index Numbers | W2: Index Numbers | X2: Index Numbers | Y2: Index Numbers | Z2: Index Numbers | AA2: Index Numbers | AB2: Index Numbers | AC2: Index Numbers | AD2: Index Numbers | AE2: Index Numbers | AF2: Index Numbers | AG2: Index Numbers | AH2: Index Numbers | AI2: Index Numbers | AJ2: Index Numbers | AK2: Index Numbers | AL2: Index Numbers | AM2: Index Numbers | AN2: Index Numbers | AO2: Index Numbers | AP2: Index Numbers | AQ2: Index Numbers | AR2: Index Numbers | AS2: Index Numbers | AT2: Index Numbers | AU2: Index Numbers | AV2: Index Numbers | AW2: Index Numbers | AX2: Index Numbers | AY2: Index Numbers | AZ2: Index Numbers | BA2: Index Numbers | BB2: Index Numbers | BC2: Index Numbers | BD2: Index Numbers | BE2: Index Numbers | BF2: Index Numbers | BG2: Index Numbers | BH2: Index Numbers | BI2: Index Numbers | BJ2: Index Numbers | BK2: Index Numbers | BL2: Index Numbers | BM2: Index Numbers | BN2: Index Numbers | BO2: Index Numbers | BP2: Index Numbers | BQ2: Index Numbers | BR2: Index Numbers | BS2: Index Numbers | BT2: Index Numbers | BU2: Index Numbers | BV2: Index Numbers | BW2: Index Numbers | BX2: Index Numbers | BY2: Index Numbers | BZ2: Index Numbers | CA2: Index Numbers | CB2: Index Numbers | CC2: Index Numbers | CD2: Index Numbers | CE2: Index Numbers | CF2: Index Numbers | CG2: Index Numbers | CH2: Index Numbers | CI2: Index Numbers | CJ2: Index Numbers | CK2: Index Numbers | CL2: Index Numbers | CM2: Index Numbers | CN2: Index Numbers | CO2: Index Numbers | CP2: Index Numbers | CQ2: Index Numbers | CR2: Index Numbers | CS2: Index Numbers | CT2: Index Numbers | CU2: Index Numbers | CV2: Index Numbers | CW2: Index Numbers | CX2: Index Numbers | CY2: Index Numbers | CZ2: Index Numbers | DA2: Index Numbers | DB2: Index Numbers | DC2: Index Numbers | DD2: Index Numbers | DE2: Index Numbers | DF2: Index Numbers | DG2: Index Numbers | DH2: Index Numbers | DI2: Index Numbers | DJ2: Index Numbers | DK2: Index Numbers | DL2: Index Numbers | DM2: Index Numbers | DN2: Index Numbers | DO2: Index Numbers | DP2: Index Numbers | DQ2: Index Numbers | DR2: Index Numbers | DS2: Index Numbers | DT2: Index Numbers | DU2: Index Numbers | DV2: Index Numbers | DW2: Index Numbers | DX2: Index Numbers | DY2: Index Numbers | DZ2: Index Numbers | EA2: Index Numbers | EB2: Index Numbers | EC2: Index Numbers | ED2: Index Numbers | EE2: Index Numbers | EF2: Index Numbers | EG2: Index Numbers | EH2: Index Numbers | EI2: Index Numbers | EJ2: Index Numbers | EK2: Index Numbers | EL2: Index Numbers | EM2: Index Numbers | EN2: Index Numbers | EO2: Index Numbers | EP2: Index Numbers | EQ2: Index Numbers | ER2: Index Numbers | ES2: Index Numbers | ET2: Index Numbers | EU2: Index Numbers | EV2: Index Numbers | EW2: Index Numbers | EX2: Index Numbers | EY2: Index Numbers | EZ2: Index Numbers | FA2: Index Numbers | FB2: Index Numbers | FC2: Index Numbers | FD2: Index Numbers | FE2: Index Numbers | FF2: Index Numbers | FG2: Index Numbers | FH2: Index Numbers | FI2: Index Numbers | FJ2: Index Numbers | FK2: Index Numbers | FL2: Index Numbers | FM2: Index Numbers | FN2: Index Numbers | FO2: Index Numbers | FP2: Index Numbers | FQ2: Index Numbers | FR2: Index Numbers | FS2: Index Numbers | FT2: Index Numbers | FU2: Index Numbers | FV2: Index Numbers | FW2: Index Numbers | FX2: Index Numbers | FY2: Index Numbers | FZ2: Index Numbers | GA2: Index Numbers | GB2: Index Numbers | GC2: Index Numbers | GD2: Index Numbers | GE2: Index Numbers | GF2: Index Numbers | GG2: Index Numbers | GH2: Index Numbers | GI2: Index Numbers | GJ2: Index Numbers | GK2: Index Numbers | GL2: Index Numbers | GM2: Index Numbers | GN2: Index Numbers | GO2: Index Numbers | GP2: Index Numbers | GQ2: Index Numbers | GR2: Index Numbers | GS2: Index Numbers | GT2: Index Numbers | GU2: Index Numbers | GV2: Index Numbers | GW2: Index Numbers | GX2: Index Numbers | GY2: Index Numbers | GZ2: Index Numbers | HA2: Index Numbers | HB2: Index Numbers | HC2: Index Numbers | HD2: Index Numbers | HE2: Index Numbers | HF2: Index Numbers | HG2: Index Numbers | HH2: Index Numbers | HI2: Index Numbers | HJ2: Index Numbers | HK2: Index Numbers | HL2: Index Numbers | HM2: Index Numbers | HN2: Index Numbers | HO2: Index Numbers | HP2: Index Numbers | HQ2: Index Numbers | HR2: Index Numbers | HS2: Index Numbers | HT2: Index Numbers | HU2: Index Numbers | HV2: Index Numbers | HW2: Index Numbers | HX2: Index Numbers | HY2: Index Numbers | HZ2: Index Numbers | IA2: Index Numbers | IB2: Index Numbers | IC2: Index Numbers | ID2: Index Numbers | IE2: Index Numbers | IF2: Index Numbers | IG2: Index Numbers | IH2: Index Numbers | II2: Index Numbers | IJ2: Index Numbers | IK2: Index Numbers | IL2: Index Numbers | IM2: Index Numbers | IN2: Index Numbers | IO2: Index Numbers | IP2: Index Numbers | IQ2: Index Numbers
A3: Series Type | B3: Original | C3: Original | D3: Original | E3: Original | F3: Original | G3: Original | H3: Original | I3: Original | J3: Original | K3: Original | L3: Original | M3: Original | N3: Original | O3: Original | P3: Original | Q3: Original | R3: Original | S3: Original | T3: Original | U3: Original | V3: Original | W3: Original | X3: Original | Y3: Original | Z3: Original | AA3: Original | AB3: Original | AC3: Original | AD3: Original | AE3: Original | AF3: Original | AG3: Original | AH3: Original | AI3: Original | AJ3: Original | AK3: Original | AL3: Original | AM3: Original | AN3: Original | AO3: Original | AP3: Original | AQ3: Original | AR3: Original | AS3: Original | AT3: Original | AU3: Original | AV3: Original | AW3: Original | AX3: Original | AY3: Original | AZ3: Original | BA3: Original | BB3: Original | BC3: Original | BD3: Original | BE3: Original | BF3: Original | BG3: Original | BH3: Original | BI3: Original | BJ3: Original | BK3: Original | BL3: Original | BM3: Original | BN3: Original | BO3: Original | BP3: Original | BQ3: Original | BR3: Original | BS3: Original | BT3: Original | BU3: Original | BV3: Original | BW3: Original | BX3: Original | BY3: Original | BZ3: Original | CA3: Original | CB3: Original | CC3: Original | CD3: Original | CE3: Original | CF3: Original | CG3: Original | CH3: Original | CI3: Original | CJ3: Original | CK3: Original | CL3: Original | CM3: Original | CN3: Original | CO3: Original | CP3: Original | CQ3: Original | CR3: Original | CS3: Original | CT3: Original | CU3: Original | CV3: Original | CW3: Original | CX3: Original | CY3: Original | CZ3: Original | DA3: Original | DB3: Original | DC3: Original | DD3: Original | DE3: Original | DF3: Original | DG3: Original | DH3: Original | DI3: Original | DJ3: Original | DK3: Original | DL3: Original | DM3: Original | DN3: Original | DO3: Original | DP3: Original | DQ3: Original | DR3: Original | DS3: Original | DT3: Original | DU3: Original | DV3: Original | DW3: Original | DX3: Original | DY3: Original | DZ3: Original | EA3: Original | EB3: Original | EC3: Original | ED3: Original | EE3: Original | EF3: Original | EG3: Original | EH3: Original | EI3: Original | EJ3: Original | EK3: Original | EL3: Original | EM3: Original | EN3: Original | EO3: Original | EP3: Original | EQ3: Original | ER3: Original | ES3: Original | ET3: Original | EU3: Original | EV3: Original | EW3: Original | EX3: Original | EY3: Original | EZ3: Original | FA3: Original | FB3: Original | FC3: Original | FD3: Original | FE3: Original | FF3: Original | FG3: Original | FH3: Original | FI3: Original | FJ3: Original | FK3: Original | FL3: Original | FM3: Original | FN3: Original | FO3: Original | FP3: Original | FQ3: Original | FR3: Original | FS3: Original | FT3: Original | FU3: Original | FV3: Original | FW3: Original | FX3: Original | FY3: Original | FZ3: Original | GA3: Original | GB3: Original | GC3: Original | GD3: Original | GE3: Original | GF3: Original | GG3: Original | GH3: Original | GI3: Original | GJ3: Original | GK3: Original | GL3: Original | GM3: Original | GN3: Original | GO3: Original | GP3: Original | GQ3: Original | GR3: Original | GS3: Original | GT3: Original | GU3: Original | GV3: Original | GW3: Original | GX3: Original | GY3: Original | GZ3: Original | HA3: Original | HB3: Original | HC3: Original | HD3: Original | HE3: Original | HF3: Original | HG3: Original | HH3: Original | HI3: Original | HJ3: Original | HK3: Original | HL3: Original | HM3: Original | HN3: Original | HO3: Original | HP3: Original | HQ3: Original | HR3: Original | HS3: Original | HT3: Original | HU3: Original | HV3: Original | HW3: Original | HX3: Original | HY3: Original | HZ3: Original | IA3: Original | IB3: Original | IC3: Original | ID3: Original | IE3: Original | IF3: Original | IG3: Original | IH3: Original | II3: Original | IJ3: Original | IK3: Original | IL3: Original | IM3: Original | IN3: Original | IO3: Original | IP3: Original | IQ3: Original
A4: Data Type | B4: INDEX | C4: INDEX | D4: INDEX | E4: INDEX | F4: INDEX | G4: INDEX | H4: INDEX | I4: INDEX | J4: INDEX | K4: INDEX | L4: INDEX | M4: INDEX | N4: INDEX | O4: INDEX | P4: INDEX | Q4: INDEX | R4: INDEX | S4: INDEX | T4: INDEX | U4: INDEX | V4: INDEX | W4: INDEX | X4: INDEX | Y4: INDEX | Z4: INDEX | AA4: INDEX | AB4: INDEX | AC4: INDEX | AD4: INDEX | AE4: INDEX | AF4: INDEX | AG4: INDEX | AH4: INDEX | AI4: INDEX | AJ4: INDEX | AK4: INDEX | AL4: INDEX | AM4: INDEX | AN4: INDEX | AO4: INDEX | AP4: INDEX | AQ4: INDEX | AR4: INDEX | AS4: INDEX | AT4: INDEX | AU4: INDEX | AV4: INDEX | AW4: INDEX | AX4: INDEX | AY4: INDEX | AZ4: INDEX | BA4: INDEX | BB4: INDEX | BC4: INDEX | BD4: INDEX | BE4: INDEX | BF4: INDEX | BG4: INDEX | BH4: INDEX | BI4: INDEX | BJ4: INDEX | BK4: INDEX | BL4: INDEX | BM4: INDEX | BN4: INDEX | BO4: INDEX | BP4: INDEX | BQ4: INDEX | BR4: INDEX | BS4: INDEX | BT4: INDEX | BU4: INDEX | BV4: INDEX | BW4: INDEX | BX4: INDEX | BY4: INDEX | BZ4: INDEX | CA4: INDEX | CB4: INDEX | CC4: INDEX | CD4: INDEX | CE4: INDEX | CF4: INDEX | CG4: INDEX | CH4: INDEX | CI4: INDEX | CJ4: INDEX | CK4: INDEX | CL4: INDEX | CM4: INDEX | CN4: INDEX | CO4: INDEX | CP4: INDEX | CQ4: INDEX | CR4: INDEX | CS4: INDEX | CT4: INDEX | CU4: INDEX | CV4: INDEX | CW4: INDEX | CX4: INDEX | CY4: INDEX | CZ4: INDEX | DA4: INDEX | DB4: INDEX | DC4: INDEX | DD4: INDEX | DE4: INDEX | DF4: INDEX | DG4: INDEX | DH4: INDEX | DI4: INDEX | DJ4: INDEX | DK4: INDEX | DL4: INDEX | DM4: INDEX | DN4: INDEX | DO4: INDEX | DP4: INDEX | DQ4: INDEX | DR4: INDEX | DS4: INDEX | DT4: INDEX | DU4: INDEX | DV4: INDEX | DW4: INDEX | DX4: INDEX | DY4: INDEX | DZ4: INDEX | EA4: INDEX | EB4: INDEX | EC4: INDEX | ED4: INDEX | EE4: INDEX | EF4: INDEX | EG4: INDEX | EH4: INDEX | EI4: INDEX | EJ4: INDEX | EK4: INDEX | EL4: INDEX | EM4: INDEX | EN4: INDEX | EO4: INDEX | EP4: INDEX | EQ4: INDEX | ER4: INDEX | ES4: INDEX | ET4: INDEX | EU4: INDEX | EV4: INDEX | EW4: INDEX | EX4: INDEX | EY4: INDEX | EZ4: INDEX | FA4: INDEX | FB4: INDEX | FC4: INDEX | FD4: INDEX | FE4: INDEX | FF4: INDEX | FG4: INDEX | FH4: INDEX | FI4: INDEX | FJ4: INDEX | FK4: INDEX | FL4: INDEX | FM4: INDEX | FN4: INDEX | FO4: INDEX | FP4: INDEX | FQ4: INDEX | FR4: INDEX | FS4: INDEX | FT4: INDEX | FU4: INDEX | FV4: INDEX | FW4: INDEX | FX4: INDEX | FY4: INDEX | FZ4: INDEX | GA4: INDEX | GB4: INDEX | GC4: INDEX | GD4: INDEX | GE4: INDEX | GF4: INDEX | GG4: INDEX | GH4: INDEX | GI4: INDEX | GJ4: INDEX | GK4: INDEX | GL4: INDEX | GM4: INDEX | GN4: INDEX | GO4: INDEX | GP4: INDEX | GQ4: INDEX | GR4: INDEX | GS4: INDEX | GT4: INDEX | GU4: INDEX | GV4: INDEX | GW4: INDEX | GX4: INDEX | GY4: INDEX | GZ4: INDEX | HA4: INDEX | HB4: INDEX | HC4: INDEX | HD4: INDEX | HE4: INDEX | HF4: INDEX | HG4: INDEX | HH4: INDEX | HI4: INDEX | HJ4: INDEX | HK4: INDEX | HL4: INDEX | HM4: INDEX | HN4: INDEX | HO4: INDEX | HP4: INDEX | HQ4: INDEX | HR4: INDEX | HS4: INDEX | HT4: INDEX | HU4: INDEX | HV4: INDEX | HW4: INDEX | HX4: INDEX | HY4: INDEX | HZ4: INDEX | IA4: INDEX | IB4: INDEX | IC4: INDEX | ID4: INDEX | IE4: INDEX | IF4: INDEX | IG4: INDEX | IH4: INDEX | II4: INDEX | IJ4: INDEX | IK4: INDEX | IL4: INDEX | IM4: INDEX | IN4: INDEX | IO4: INDEX | IP4: INDEX | IQ4: INDEX
A5: Frequency | B5: Quarter | C5: Quarter | D5: Quarter | E5: Quarter | F5: Quarter | G5: Quarter | H5: Quarter | I5: Quarter | J5: Quarter | K5: Quarter | L5: Quarter | M5: Quarter | N5: Quarter | O5: Quarter | P5: Quarter | Q5: Quarter | R5: Quarter | S5: Quarter | T5: Quarter | U5: Quarter | V5: Quarter | W5: Quarter | X5: Quarter | Y5: Quarter | Z5: Quarter | AA5: Quarter | AB5: Quarter | AC5: Quarter | AD5: Quarter | AE5: Quarter | AF5: Quarter | AG5: Quarter | AH5: Quarter | AI5: Quarter | AJ5: Quarter | AK5: Quarter | AL5: Quarter | AM5: Quarter | AN5: Quarter | AO5: Quarter | AP5: Quarter | AQ5: Quarter | AR5: Quarter | AS5: Quarter | AT5: Quarter | AU5: Quarter | AV5: Quarter | AW5: Quarter | AX5: Quarter | AY5: Quarter | AZ5: Quarter | BA5: Quarter | BB5: Quarter | BC5: Quarter | BD5: Quarter | BE5: Quarter | BF5: Quarter | BG5: Quarter | BH5: Quarter | BI5: Quarter | BJ5: Quarter | BK5: Quarter | BL5: Quarter | BM5: Quarter | BN5: Quarter | BO5: Quarter | BP5: Quarter | BQ5: Quarter | BR5: Quarter | BS5: Quarter | BT5: Quarter | BU5: Quarter | BV5: Quarter | BW5: Quarter | BX5: Quarter | BY5: Quarter | BZ5: Quarter | CA5: Quarter | CB5: Quarter | CC5: Quarter | CD5: Quarter | CE5: Quarter | CF5: Quarter | CG5: Quarter | CH5: Quarter | CI5: Quarter | CJ5: Quarter | CK5: Quarter | CL5: Quarter | CM5: Quarter | CN5: Quarter | CO5: Quarter | CP5: Quarter | CQ5: Quarter | CR5: Quarter | CS5: Quarter | CT5: Quarter | CU5: Quarter | CV5: Quarter | CW5: Quarter | CX5: Quarter | CY5: Quarter | CZ5: Quarter | DA5: Quarter | DB5: Quarter | DC5: Quarter | DD5: Quarter | DE5: Quarter | DF5: Quarter | DG5: Quarter | DH5: Quarter | DI5: Quarter | DJ5: Quarter | DK5: Quarter | DL5: Quarter | DM5: Quarter | DN5: Quarter | DO5: Quarter | DP5: Quarter | DQ5: Quarter | DR5: Quarter | DS5: Quarter | DT5: Quarter | DU5: Quarter | DV5: Quarter | DW5: Quarter | DX5: Quarter | DY5: Quarter | DZ5: Quarter | EA5: Quarter | EB5: Quarter | EC5: Quarter | ED5: Quarter | EE5: Quarter | EF5: Quarter | EG5: Quarter | EH5: Quarter | EI5: Quarter | EJ5: Quarter | EK5: Quarter | EL5: Quarter | EM5: Quarter | EN5: Quarter | EO5: Quarter | EP5: Quarter | EQ5: Quarter | ER5: Quarter | ES5: Quarter | ET5: Quarter | EU5: Quarter | EV5: Quarter | EW5: Quarter | EX5: Quarter | EY5: Quarter | EZ5: Quarter | FA5: Quarter | FB5: Quarter | FC5: Quarter | FD5: Quarter | FE5: Quarter | FF5: Quarter | FG5: Quarter | FH5: Quarter | FI5: Quarter | FJ5: Quarter | FK5: Quarter | FL5: Quarter | FM5: Quarter | FN5: Quarter | FO5: Quarter | FP5: Quarter | FQ5: Quarter | FR5: Quarter | FS5: Quarter | FT5: Quarter | FU5: Quarter | FV5: Quarter | FW5: Quarter | FX5: Quarter | FY5: Quarter | FZ5: Quarter | GA5: Quarter | GB5: Quarter | GC5: Quarter | GD5: Quarter | GE5: Quarter | GF5: Quarter | GG5: Quarter | GH5: Quarter | GI5: Quarter | GJ5: Quarter | GK5: Quarter | GL5: Quarter | GM5: Quarter | GN5: Quarter | GO5: Quarter | GP5: Quarter | GQ5: Quarter | GR5: Quarter | GS5: Quarter | GT5: Quarter | GU5: Quarter | GV5: Quarter | GW5: Quarter | GX5: Quarter | GY5: Quarter | GZ5: Quarter | HA5: Quarter | HB5: Quarter | HC5: Quarter | HD5: Quarter | HE5: Quarter | HF5: Quarter | HG5: Quarter | HH5: Quarter | HI5: Quarter | HJ5: Quarter | HK5: Quarter | HL5: Quarter | HM5: Quarter | HN5: Quarter | HO5: Quarter | HP5: Quarter | HQ5: Quarter | HR5: Quarter | HS5: Quarter | HT5: Quarter | HU5: Quarter | HV5: Quarter | HW5: Quarter | HX5: Quarter | HY5: Quarter | HZ5: Quarter | IA5: Quarter | IB5: Quarter | IC5: Quarter | ID5: Quarter | IE5: Quarter | IF5: Quarter | IG5: Quarter | IH5: Quarter | II5: Quarter | IJ5: Quarter | IK5: Quarter | IL5: Quarter | IM5: Quarter | IN5: Quarter | IO5: Quarter | IP5: Quarter | IQ5: Quarter
A6: Collection Month | B6: 3 | C6: 3 | D6: 3 | E6: 3 | F6: 3 | G6: 3 | H6: 3 | I6: 3 | J6: 3 | K6: 3 | L6: 3 | M6: 3 | N6: 3 | O6: 3 | P6: 3 | Q6: 3 | R6: 3 | S6: 3 | T6: 3 | U6: 3 | V6: 3 | W6: 3 | X6: 3 | Y6: 3 | Z6: 3 | AA6: 3 | AB6: 3 | AC6: 3 | AD6: 3 | AE6: 3 | AF6: 3 | AG6: 3 | AH6: 3 | AI6: 3 | AJ6: 3 | AK6: 3 | AL6: 3 | AM6: 3 | AN6: 3 | AO6: 3 | AP6: 3 | AQ6: 3 | AR6: 3 | AS6: 3 | AT6: 3 | AU6: 3 | AV6: 3 | AW6: 3 | AX6: 3 | AY6: 3 | AZ6: 3 | BA6: 3 | BB6: 3 | BC6: 3 | BD6: 3 | BE6: 3 | BF6: 3 | BG6: 3 | BH6: 3 | BI6: 3 | BJ6: 3 | BK6: 3 | BL6: 3 | BM6: 3 | BN6: 3 | BO6: 3 | BP6: 3 | BQ6: 3 | BR6: 3 | BS6: 3 | BT6: 3 | BU6: 3 | BV6: 3 | BW6: 3 | BX6: 3 | BY6: 3 | BZ6: 3 | CA6: 3 | CB6: 3 | CC6: 3 | CD6: 3 | CE6: 3 | CF6: 3 | CG6: 3 | CH6: 3 | CI6: 3 | CJ6: 3 | CK6: 3 | CL6: 3 | CM6: 3 | CN6: 3 | CO6: 3 | CP6: 3 | CQ6: 3 | CR6: 3 | CS6: 3 | CT6: 3 | CU6: 3 | CV6: 3 | CW6: 3 | CX6: 3 | CY6: 3 | CZ6: 3 | DA6: 3 | DB6: 3 | DC6: 3 | DD6: 3 | DE6: 3 | DF6: 3 | DG6: 3 | DH6: 3 | DI6: 3 | DJ6: 3 | DK6: 3 | DL6: 3 | DM6: 3 | DN6: 3 | DO6: 3 | DP6: 3 | DQ6: 3 | DR6: 3 | DS6: 3 | DT6: 3 | DU6: 3 | DV6: 3 | DW6: 3 | DX6: 3 | DY6: 3 | DZ6: 3 | EA6: 3 | EB6: 3 | EC6: 3 | ED6: 3 | EE6: 3 | EF6: 3 | EG6: 3 | EH6: 3 | EI6: 3 | EJ6: 3 | EK6: 3 | EL6: 3 | EM6: 3 | EN6: 3 | EO6: 3 | EP6: 3 | EQ6: 3 | ER6: 3 | ES6: 3 | ET6: 3 | EU6: 3 | EV6: 3 | EW6: 3 | EX6: 3 | EY6: 3 | EZ6: 3 | FA6: 3 | FB6: 3 | FC6: 3 | FD6: 3 | FE6: 3 | FF6: 3 | FG6: 3 | FH6: 3 | FI6: 3 | FJ6: 3 | FK6: 3 | FL6: 3 | FM6: 3 | FN6: 3 | FO6: 3 | FP6: 3 | FQ6: 3 | FR6: 3 | FS6: 3 | FT6: 3 | FU6: 3 | FV6: 3 | FW6: 3 | FX6: 3 | FY6: 3 | FZ6: 3 | GA6: 3 | GB6: 3 | GC6: 3 | GD6: 3 | GE6: 3 | GF6: 3 | GG6: 3 | GH6: 3 | GI6: 3 | GJ6: 3 | GK6: 3 | GL6: 3 | GM6: 3 | GN6: 3 | GO6: 3 | GP6: 3 | GQ6: 3 | GR6: 3 | GS6: 3 | GT6: 3 | GU6: 3 | GV6: 3 | GW6: 3 | GX6: 3 | GY6: 3 | GZ6: 3 | HA6: 3 | HB6: 3 | HC6: 3 | HD6: 3 | HE6: 3 | HF6: 3 | HG6: 3 | HH6: 3 | HI6: 3 | HJ6: 3 | HK6: 3 | HL6: 3 | HM6: 3 | HN6: 3 | HO6: 3 | HP6: 3 | HQ6: 3 | HR6: 3 | HS6: 3 | HT6: 3 | HU6: 3 | HV6: 3 | HW6: 3 | HX6: 3 | HY6: 3 | HZ6: 3 | IA6: 3 | IB6: 3 | IC6: 3 | ID6: 3 | IE6: 3 | IF6: 3 | IG6: 3 | IH6: 3 | II6: 3 | IJ6: 3 | IK6: 3 | IL6: 3 | IM6: 3 | IN6: 3 | IO6: 3 | IP6: 3 | IQ6: 3
A7: Series Start | B7: 26543 | C7: 26543 | D7: 29465 | E7: 29465 | F7: 29465 | G7: 29465 | H7: 26543 | I7: 26543 | J7: 29465 | K7: 26543 | L7: 26543 | M7: 29465 | N7: 28004 | O7: 26543 | P7: 29465 | Q7: 29465 | R7: 29465 | S7: 32752 | T7: 32752 | U7: 32752 | V7: 32752 | W7: 29465 | X7: 29465 | Y7: 32752 | Z7: 32752 | AA7: 32752 | AB7: 29465 | AC7: 32752 | AD7: 29465 | AE7: 32752 | AF7: 28004 | AG7: 29465 | AH7: 29465 | AI7: 26543 | AJ7: 26543 | AK7: 29465 | AL7: 29465 | AM7: 26543 | AN7: 26543 | AO7: 26543 | AP7: 26543 | AQ7: 32752 | AR7: 32752 | AS7: 32752 | AT7: 32752 | AU7: 26543 | AV7: 29465 | AW7: 29465 | AX7: 29465 | AY7: 35947 | AZ7: 35947 | BA7: 26543 | BB7: 26543 | BC7: 26543 | BD7: 26543 | BE7: 35947 | BF7: 35947 | BG7: 35947 | BH7: 29465 | BI7: 35947 | BJ7: 26543 | BK7: 35947 | BL7: 29465 | BM7: 32752 | BN7: 26543 | BO7: 26543 | BP7: 29465 | BQ7: 29465 | BR7: 26543 | BS7: 26543 | BT7: 32752 | BU7: 26543 | BV7: 26543 | BW7: 32752 | BX7: 29465 | BY7: 32752 | BZ7: 29465 | CA7: 29465 | CB7: 32752 | CC7: 32752 | CD7: 30011 | CE7: 26543 | CF7: 32752 | CG7: 32752 | CH7: 31747 | CI7: 29465 | CJ7: 31747 | CK7: 29465 | CL7: 29465 | CM7: 29465 | CN7: 26543 | CO7: 26543 | CP7: 26543 | CQ7: 29465 | CR7: 26543 | CS7: 29465 | CT7: 29465 | CU7: 26543 | CV7: 26543 | CW7: 26543 | CX7: 26543 | CY7: 29465 | CZ7: 29465 | DA7: 32752 | DB7: 32752 | DC7: 29465 | DD7: 32752 | DE7: 32752 | DF7: 35947 | DG7: 35947 | DH7: 30011 | DI7: 30011 | DJ7: 30011 | DK7: 32752 | DL7: 35947 | DM7: 35947 | DN7: 29465 | DO7: 31747 | DP7: 35947 | DQ7: 35947 | DR7: 30011 | DS7: 30011 | DT7: 36678 | DU7: 36678 | DV7: 36678 | DW7: 38504 | DX7: 32752 | DY7: 32752 | DZ7: 40695 | EA7: 40695 | EB7: 38504 | EC7: 17777 | ED7: 35947 | EE7: 35947 | EF7: 27273 | EG7: 27273 | EH7: 17777 | EI7: 26543 | EJ7: 29465 | EK7: 29465 | EL7: 26543 | EM7: 29465 | EN7: 32752 | EO7: 29465 | EP7: 32752 | EQ7: 32752 | ER7: 32752 | ES7: 32752 | ET7: 32752 | EU7: 26451 | EV7: 32752 | EW7: 36039 | EX7: 26543 | EY7: 26543 | EZ7: 29465 | FA7: 29465 | FB7: 29465 | FC7: 29465 | FD7: 26543 | FE7: 26543 | FF7: 29465 | FG7: 26543 | FH7: 26543 | FI7: 29465 | FJ7: 28004 | FK7: 26543 | FL7: 29465 | FM7: 29465 | FN7: 29465 | FO7: 32752 | FP7: 32752 | FQ7: 32752 | FR7: 32752 | FS7: 29465 | FT7: 29465 | FU7: 32752 | FV7: 32752 | FW7: 32752 | FX7: 29465 | FY7: 32752 | FZ7: 29465 | GA7: 32752 | GB7: 28004 | GC7: 29465 | GD7: 29465 | GE7: 26543 | GF7: 26543 | GG7: 29465 | GH7: 29465 | GI7: 26543 | GJ7: 26543 | GK7: 26543 | GL7: 26543 | GM7: 32752 | GN7: 32752 | GO7: 32752 | GP7: 32752 | GQ7: 26543 | GR7: 29465 | GS7: 29465 | GT7: 29465 | GU7: 35947 | GV7: 35947 | GW7: 26543 | GX7: 26543 | GY7: 26543 | GZ7: 26543 | HA7: 35947 | HB7: 35947 | HC7: 35947 | HD7: 29465 | HE7: 35947 | HF7: 26543 | HG7: 35947 | HH7: 29465 | HI7: 32752 | HJ7: 26543 | HK7: 26543 | HL7: 29465 | HM7: 29465 | HN7: 26543 | HO7: 26543 | HP7: 32752 | HQ7: 26543 | HR7: 26543 | HS7: 32752 | HT7: 29465 | HU7: 32752 | HV7: 29465 | HW7: 29465 | HX7: 32752 | HY7: 32752 | HZ7: 30011 | IA7: 26543 | IB7: 32752 | IC7: 32752 | ID7: 31747 | IE7: 29465 | IF7: 31747 | IG7: 29465 | IH7: 29465 | II7: 29465 | IJ7: 26543 | IK7: 26543 | IL7: 26543 | IM7: 29465 | IN7: 26543 | IO7: 29465 | IP7: 29465 | IQ7: 26543
A8: Series End | B8: 43617 | C8: 43617 | D8: 43617 | E8: 43617 | F8: 43617 | G8: 43617 | H8: 43617 | I8: 43617 | J8: 43617 | K8: 43617 | L8: 43617 | M8: 43617 | N8: 43617 | O8: 43617 | P8: 43617 | Q8: 43617 | R8: 43617 | S8: 43617 | T8: 43617 | U8: 43617 | V8: 43617 | W8: 43617 | X8: 43617 | Y8: 43617 | Z8: 43617 | AA8: 43617 | AB8: 43617 | AC8: 43617 | AD8: 43617 | AE8: 43617 | AF8: 43617 | AG8: 43617 | AH8: 43617 | AI8: 43617 | AJ8: 43617 | AK8: 43617 | AL8: 43617 | AM8: 43617 | AN8: 43617 | AO8: 43617 | AP8: 43617 | AQ8: 43617 | AR8: 43617 | AS8: 43617 | AT8: 43617 | AU8: 43617 | AV8: 43617 | AW8: 43617 | AX8: 43617 | AY8: 43617 | AZ8: 43617 | BA8: 43617 | BB8: 43617 | BC8: 43617 | BD8: 43617 | BE8: 43617 | BF8: 43617 | BG8: 43617 | BH8: 43617 | BI8: 43617 | BJ8: 43617 | BK8: 43617 | BL8: 43617 | BM8: 43617 | BN8: 43617 | BO8: 43617 | BP8: 43617 | BQ8: 43617 | BR8: 43617 | BS8: 43617 | BT8: 43617 | BU8: 43617 | BV8: 43617 | BW8: 43617 | BX8: 43617 | BY8: 43617 | BZ8: 43617 | CA8: 43617 | CB8: 43617 | CC8: 43617 | CD8: 43617 | CE8: 43617 | CF8: 43617 | CG8: 43617 | CH8: 43617 | CI8: 43617 | CJ8: 43617 | CK8: 43617 | CL8: 43617 | CM8: 43617 | CN8: 43617 | CO8: 43617 | CP8: 43617 | CQ8: 43617 | CR8: 43617 | CS8: 43617 | CT8: 43617 | CU8: 43617 | CV8: 43617 | CW8: 43617 | CX8: 43617 | CY8: 43617 | CZ8: 43617 | DA8: 43617 | DB8: 43617 | DC8: 43617 | DD8: 43617 | DE8: 43617 | DF8: 43617 | DG8: 43617 | DH8: 43617 | DI8: 43617 | DJ8: 43617 | DK8: 43617 | DL8: 43617 | DM8: 43617 | DN8: 43617 | DO8: 43617 | DP8: 43617 | DQ8: 43617 | DR8: 43617 | DS8: 43617 | DT8: 43617 | DU8: 43617 | DV8: 43617 | DW8: 43617 | DX8: 43617 | DY8: 43617 | DZ8: 43617 | EA8: 43617 | EB8: 43617 | EC8: 43617 | ED8: 43617 | EE8: 43617 | EF8: 43617 | EG8: 43617 | EH8: 43617 | EI8: 43617 | EJ8: 43617 | EK8: 43617 | EL8: 43617 | EM8: 43617 | EN8: 43617 | EO8: 43617 | EP8: 43617 | EQ8: 43617 | ER8: 43617 | ES8: 43617 | ET8: 43617 | EU8: 43617 | EV8: 43617 | EW8: 43617 | EX8: 43617 | EY8: 43617 | EZ8: 43617 | FA8: 43617 | FB8: 43617 | FC8: 43617 | FD8: 43617 | FE8: 43617 | FF8: 43617 | FG8: 43617 | FH8: 43617 | FI8: 43617 | FJ8: 43617 | FK8: 43617 | FL8: 43617 | FM8: 43617 | FN8: 43617 | FO8: 43617 | FP8: 43617 | FQ8: 43617 | FR8: 43617 | FS8: 43617 | FT8: 43617 | FU8: 43617 | FV8: 43617 | FW8: 43617 | FX8: 43617 | FY8: 43617 | FZ8: 43617 | GA8: 43617 | GB8: 43617 | GC8: 43617 | GD8: 43617 | GE8: 43617 | GF8: 43617 | GG8: 43617 | GH8: 43617 | GI8: 43617 | GJ8: 43617 | GK8: 43617 | GL8: 43617 | GM8: 43617 | GN8: 43617 | GO8: 43617 | GP8: 43617 | GQ8: 43617 | GR8: 43617 | GS8: 43617 | GT8: 43617 | GU8: 43617 | GV8: 43617 | GW8: 43617 | GX8: 43617 | GY8: 43617 | GZ8: 43617 | HA8: 43617 | HB8: 43617 | HC8: 43617 | HD8: 43617 | HE8: 43617 | HF8: 43617 | HG8: 43617 | HH8: 43617 | HI8: 43617 | HJ8: 43617 | HK8: 43617 | HL8: 43617 | HM8: 43617 | HN8: 43617 | HO8: 43617 | HP8: 43617 | HQ8: 43617 | HR8: 43617 | HS8: 43617 | HT8: 43617 | HU8: 43617 | HV8: 43617 | HW8: 43617 | HX8: 43617 | HY8: 43617 | HZ8: 43617 | IA8: 43617 | IB8: 43617 | IC8: 43617 | ID8: 43617 | IE8: 43617 | IF8: 43617 | IG8: 43617 | IH8: 43617 | II8: 43617 | IJ8: 43617 | IK8: 43617 | IL8: 43617 | IM8: 43617 | IN8: 43617 | IO8: 43617 | IP8: 43617 | IQ8: 43617
A9: No. Obs | B9: 188 | C9: 188 | D9: 156 | E9: 156 | F9: 156 | G9: 156 | H9: 188 | I9: 188 | J9: 156 | K9: 188 | L9: 188 | M9: 156 | N9: 172 | O9: 188 | P9: 156 | Q9: 156 | R9: 156 | S9: 120 | T9: 120 | U9: 120 | V9: 120 | W9: 156 | X9: 156 | Y9: 120 | Z9: 120 | AA9: 120 | AB9: 156 | AC9: 120 | AD9: 156 | AE9: 120 | AF9: 172 | AG9: 156 | AH9: 156 | AI9: 188 | AJ9: 188 | AK9: 156 | AL9: 156 | AM9: 188 | AN9: 188 | AO9: 188 | AP9: 188 | AQ9: 120 | AR9: 120 | AS9: 120 | AT9: 120 | AU9: 188 | AV9: 156 | AW9: 156 | AX9: 156 | AY9: 85 | AZ9: 85 | BA9: 188 | BB9: 188 | BC9: 188 | BD9: 188 | BE9: 85 | BF9: 85 | BG9: 85 | BH9: 156 | BI9: 85 | BJ9: 188 | BK9: 85 | BL9: 156 | BM9: 120 | BN9: 188 | BO9: 188 | BP9: 156 | BQ9: 156 | BR9: 188 | BS9: 188 | BT9: 120 | BU9: 188 | BV9: 188 | BW9: 120 | BX9: 156 | BY9: 120 | BZ9: 156 | CA9: 156 | CB9: 120 | CC9: 120 | CD9: 150 | CE9: 188 | CF9: 120 | CG9: 120 | CH9: 131 | CI9: 156 | CJ9: 131 | CK9: 156 | CL9: 156 | CM9: 156 | CN9: 188 | CO9: 188 | CP9: 188 | CQ9: 156 | CR9: 188 | CS9: 156 | CT9: 156 | CU9: 188 | CV9: 188 | CW9: 188 | CX9: 188 | CY9: 156 | CZ9: 156 | DA9: 120 | DB9: 120 | DC9: 156 | DD9: 120 | DE9: 120 | DF9: 85 | DG9: 85 | DH9: 150 | DI9: 150 | DJ9: 150 | DK9: 120 | DL9: 85 | DM9: 85 | DN9: 156 | DO9: 131 | DP9: 85 | DQ9: 85 | DR9: 150 | DS9: 150 | DT9: 77 | DU9: 77 | DV9: 77 | DW9: 57 | DX9: 120 | DY9: 120 | DZ9: 33 | EA9: 33 | EB9: 57 | EC9: 284 | ED9: 85 | EE9: 85 | EF9: 180 | EG9: 180 | EH9: 284 | EI9: 188 | EJ9: 156 | EK9: 156 | EL9: 188 | EM9: 156 | EN9: 120 | EO9: 156 | EP9: 120 | EQ9: 120 | ER9: 120 | ES9: 120 | ET9: 120 | EU9: 189 | EV9: 120 | EW9: 84 | EX9: 188 | EY9: 188 | EZ9: 156 | FA9: 156 | FB9: 156 | FC9: 156 | FD9: 188 | FE9: 188 | FF9: 156 | FG9: 188 | FH9: 188 | FI9: 156 | FJ9: 172 | FK9: 188 | FL9: 156 | FM9: 156 | FN9: 156 | FO9: 120 | FP9: 120 | FQ9: 120 | FR9: 120 | FS9: 156 | FT9: 156 | FU9: 120 | FV9: 120 | FW9: 120 | FX9: 156 | FY9: 120 | FZ9: 156 | GA9: 120 | GB9: 172 | GC9: 156 | GD9: 156 | GE9: 188 | GF9: 188 | GG9: 156 | GH9: 156 | GI9: 188 | GJ9: 188 | GK9: 188 | GL9: 188 | GM9: 120 | GN9: 120 | GO9: 120 | GP9: 120 | GQ9: 188 | GR9: 156 | GS9: 156 | GT9: 156 | GU9: 85 | GV9: 85 | GW9: 188 | GX9: 188 | GY9: 188 | GZ9: 188 | HA9: 85 | HB9: 85 | HC9: 85 | HD9: 156 | HE9: 85 | HF9: 188 | HG9: 85 | HH9: 156 | HI9: 120 | HJ9: 188 | HK9: 188 | HL9: 156 | HM9: 156 | HN9: 188 | HO9: 188 | HP9: 120 | HQ9: 188 | HR9: 188 | HS9: 120 | HT9: 156 | HU9: 120 | HV9: 156 | HW9: 156 | HX9: 120 | HY9: 120 | HZ9: 150 | IA9: 188 | IB9: 120 | IC9: 120 | ID9: 131 | IE9: 156 | IF9: 131 | IG9: 156 | IH9: 156 | II9: 156 | IJ9: 188 | IK9: 188 | IL9: 188 | IM9: 156 | IN9: 188 | IO9: 156 | IP9: 156 | IQ9: 188
A10: Series ID | B10: A2325851W | C10: A2326166T | D10: A2327021W | E10: A2327066A | F10: A2327111A | G10: A2327156F | H10: A2326211T | I10: A2327201F | J10: A3603903T | K10: A2327246K | L10: A2327336R | M10: A2327426V | N10: A2327471F | O10: A2326121L | P10: A2326886R | Q10: A2326931R | R10: A2326976V | S10: A2330846X | T10: A2330891K | U10: A2330936C | V10: A3603943K | W10: A2327606C | X10: A2327651R | Y10: A2329451J | Z10: A2329496L | AA10: A2331701C | AB10: A2327741V | AC10: A3603983C | AD10: A2327696V | AE10: A2331746J | AF10: A2326256W | AG10: A2327516X | AH10: A2327561K | AI10: A2326076L | AJ10: A2326706V | AK10: A2328911T | AL10: A2328866T | AM10: A2328821L | AN10: A2326751F | AO10: A2328956W | AP10: A2325896A | AQ10: A3604023L | AR10: A2329541L | AS10: A2329676W | AT10: A2329721W | AU10: A2326346A | AV10: A2327876C | AW10: A2327921C | AX10: A2327966J | AY10: A2329766A | AZ10: A2329811A | BA10: A2328011K | BB10: A2325941A | BC10: A2331836L | BD10: A2326391L | BE10: A3604223F | BF10: A2329901F | BG10: A3603573L | BH10: A2328056R | BI10: A2329946K | BJ10: A2326481T | BK10: A2329856F | BL10: A2328101R | BM10: A2331881X | BN10: A2325986F | BO10: A3604143F | BP10: A2328146V | BQ10: A3604183X | BR10: A3604063F | BS10: A3604103L | BT10: A2329991W | BU10: A2328236X | BV10: A2330981R | BW10: A2331026K | BX10: A2328281K | BY10: A2330036W | BZ10: A2328326C | CA10: A2329181V | CB10: A2330081J | CC10: A2330126A | CD10: A2331566X | CE10: A2329226L | CF10: A2331656C | CG10: A2331071W | CH10: A3603613V | CI10: A2329136J | CJ10: A2329046C | CK10: A3603653L | CL10: A2329001X | CM10: A2329091R | CN10: A2326031J | CO10: A2326616R | CP10: A2328551X | CQ10: A2328686J | CR10: A2328596C | CS10: A2328731J | CT10: A2328641C | CU10: A2326661A | CV10: A2328776L | CW10: A2331161A | CX10: A2326571W | CY10: A2328461V | CZ10: A2328506L | DA10: A2331206V | DB10: A3603813L | DC10: A2329271X | DD10: A3603693F | DE10: A3603733L | DF10: A2330171L | DG10: A3603773F | DH10: A2326841K | DI10: A2329316T | DJ10: A2329361C | DK10: A2331341K | DL10: A2330306K | DM10: A2330351W | DN10: A2328416J | DO10: A2328371R | DP10: A2330396A | DQ10: A2330441A | DR10: A2331386R | DS10: A2329406W | DT10: A2331431R | DU10: A2331476V | DV10: A2331521V | DW10: A2332556L | DX10: A3602793W | DY10: A3602838R | DZ10: A3603893X | EA10: A3603853F | EB10: A2332736W | EC10: A2325806K | ED10: A2330486F | EE10: A2330531F | EF10: A2330576K | EG10: A2330666R | EH10: A3604318W | EI10: A2332061K | EJ10: A2332106C | EK10: A2332151R | EL10: A2332196V | EM10: A2332241V | EN10: A2332286X | EO10: A2332331X | EP10: A2332376C | EQ10: A2332421C | ER10: A2332466J | ES10: A2332601L | ET10: A2332646T | EU10: A2332511J | EV10: A3604278R | EW10: A2330801V | EX10: A2325856J | EY10: A2326171K | EZ10: A2327026J | FA10: A2327071V | FB10: A2327116L | FC10: A2327161X | FD10: A2326216C | FE10: A2327206T | FF10: A3603908C | FG10: A2327251C | FH10: A2327341J | FI10: A2327431L | FJ10: A2327476T | FK10: A2326126X | FL10: A2326891J | FM10: A2326936A | FN10: A2326981L | FO10: A2330851T | FP10: A2330896W | FQ10: A2330941W | FR10: A3603948W | FS10: A2327611W | FT10: A2327656A | FU10: A2329456V | FV10: A2329501V | FW10: A2331706R | FX10: A2327746F | FY10: A3603988R | FZ10: A2327701A | GA10: A2331751A | GB10: A2326261R | GC10: A2327521T | GD10: A2327566W | GE10: A2326081F | GF10: A2326711L | GG10: A2328916C | GH10: A2328871K | GI10: A2328826X | GJ10: A2326756T | GK10: A2328961R | GL10: A2325901J | GM10: A3604028X | GN10: A2329546X | GO10: A2329681R | GP10: A2329726J | GQ10: A2326351V | GR10: A2327881W | GS10: A2327926R | GT10: A2327971A | GU10: A2329771V | GV10: A2329816L | GW10: A2328016W | GX10: A2325946L | GY10: A2331841F | GZ10: A2326396X | HA10: A3604228T | HB10: A2329906T | HC10: A3603578X | HD10: A2328061J | HE10: A2329951C | HF10: A2326486C | HG10: A2329861X | HH10: A2328106A | HI10: A2331886K | HJ10: A2325991X | HK10: A3604148T | HL10: A2328151L | HM10: A3604188K | HN10: A3604068T | HO10: A3604108X | HP10: A2329996J | HQ10: A2328241T | HR10: A2330986A | HS10: A2331031C | HT10: A2328286W | HU10: A2330041R | HV10: A2328331W | HW10: A2329186F | HX10: A2330086V | HY10: A2330131V | HZ10: A2331571T | IA10: A2329231F | IB10: A2331661W | IC10: A2331076J | ID10: A3603618F | IE10: A2329141A | IF10: A2329051W | IG10: A3603658X | IH10: A2329006K | II10: A2329096A | IJ10: A2326036V | IK10: A2326621J | IL10: A2328556K | IM10: A2328691A | IN10: A2328601K | IO10: A2328736V | IP10: A2328646R | IQ10: A2326666L
A11: 17777 | EC11: 3.7 | EH11: 3.7
A12: 17868 | EC12: 3.7 | EH12: 3.7
A13: 17958 | EC13: 3.9 | EH13: 3.9
A14: 18050 | EC14: 3.9 | EH14: 3.9
A15: 18142 | EC15: 4 | EH15: 4
A16: 18233 | EC16: 4.1 | EH16: 4.1
A17: 18323 | EC17: 4.1 | EH17: 4.1
A18: 18415 | EC18: 4.3 | EH18: 4.3
A19: 18507 | EC19: 4.4 | EH19: 4.4
A20: 18598 | EC20: 4.6 | EH20: 4.6
A21: 18688 | EC21: 4.7 | EH21: 4.7
A22: 18780 | EC22: 5.1 | EH22: 5.1
... A105: 26359 | EC105: 10.9 | EH105: 11
A106: 26451 | EC106: 11.1 | EH106: 11.1 | EU106: 11
A107: 26543 | B107: 10.2 | C107: 9.2 | H107: 11.8 | I107: 12.7 | K107: 6.8 | L107: 34.1 | O107: 13.4 | AI107: 5.3 | AJ107: 8.6 | AM107: 7.1 | AN107: 2.3 | AO107: 2.3 | AP107: 18.2 | AU107: 21.6 | BA107: 7 | BB107: 9.4 | BC107: 8.5 | BD107: 8.5 | BJ107: 7.5 | BN107: 18.7 | BO107: 16.4 | BR107: 15.6 | BS107: 15.6 | BU107: 49.4 | BV107: 49.4 | CE107: 7.4 | CN107: 11.4 | CO107: 11.4 | CP107: 22.3 | CR107: 7 | CU107: 8.7 | CV107: 8.7 | CW107: 29.9 | CX107: 29.9 | EC107: 11.2 | EH107: 11.2 | EI107: 11.5 | EL107: 11.7 | EU107: 11.2 | EX107: 10 | EY107: 8.8 | FD107: 13.2 | FE107: 14 | FG107: 7.5 | FH107: 35 | FK107: 10.7 | GE107: 5.9 | GF107: 10.7 | GI107: 8.7 | GJ107: 2.2 | GK107: 2.2 | GL107: 19.2 | GQ107: 19.6 | GW107: 7.7 | GX107: 11.2 | GY107: 10.6 | GZ107: 10.6 | HF107: 6.9 | HJ107: 17.1 | HK107: 13.8 | HN107: 17.7 | HO107: 17.7 | HQ107: 43.1 | HR107: 46.4 | IA107: 5.9 | IJ107: 11.7 | IK107: 11.7 | IL107: 21.9 | IN107: 6.5 | IQ107: 8.6
A108: 26634 | B108: 10.3 | C108: 9.2 | H108: 12.1 | I108: 13 | K108: 7.2 | L108: 34 | O108: 13.4 | AI108: 5.4 | AJ108: 8.9 | AM108: 7.4 | AN108: 2.3 | AO108: 2.3 | AP108: 18.5 | AU108: 21.8 | BA108: 7 | BB108: 9.7 | BC108: 8.6 | BD108: 8.6 | BJ108: 7.5 | BN108: 18.8 | BO108: 16.6 | BR108: 15.7 | BS108: 15.7 | BU108: 49.5 | BV108: 49.6 | CE108: 7.4 | CN108: 11.4 | CO108: 11.4 | CP108: 22.3 | CR108: 7 | CU108: 8.7 | CV108: 8.7 | CW108: 29.9 | CX108: 29.9 | EC108: 11.3 | EH108: 11.3 | EI108: 11.6 | EL108: 11.8 | EU108: 11.4 | EX108: 10.1 | EY108: 8.8 | FD108: 13.2 | FE108: 14.1 | FG108: 7.4 | FH108: 36.8 | FK108: 10.8 | GE108: 5.9 | GF108: 10.7 | GI108: 8.7 | GJ108: 2.2 | GK108: 2.2 | GL108: 19.5 | GQ108: 19.8 | GW108: 8.1 | GX108: 11.3 | GY108: 10.8 | GZ108: 10.8 | HF108: 6.9 | HJ108: 17.2 | HK108: 14.1 | HN108: 17.8 | HO108: 17.8 | HQ108: 43.1 | HR108: 46.4 | IA108: 6.3 | IJ108: 11.8 | IK108: 11.8 | IL108: 21.9 | IN108: 6.5 | IQ108: 8.6
A109: 26724 | B109: 10.7 | C109: 9.3 | H109: 13.2 | I109: 13.9 | K109: 8.4 | L109: 34.1 | O109: 13.5 | AI109: 5.5 | AJ109: 8.9 | AM109: 7.4 | AN109: 2.4 | AO109: 2.4 | AP109: 18.7 | AU109: 22.6 | BA109: 7.1 | BB109: 9.8 | BC109: 8.7 | BD109: 8.7 | BJ109: 7.5 | BN109: 19 | BO109: 17.1 | BR109: 16 | BS109: 16 | BU109: 49.6 | BV109: 49.7 | CE109: 7.5 | CN109: 11.5 | CO109: 11.4 | CP109: 22.3 | CR109: 7 | CU109: 8.9 | CV109: 8.9 | CW109: 29.9 | CX109: 29.9 | EC109: 11.6 | EH109: 11.6 | EI109: 11.7 | EL109: 12.1 | EU109: 11.6 | EX109: 10.7 | EY109: 8.9 | FD109: 14.4 | FE109: 15 | FG109: 9 | FH109: 35.6 | FK109: 11.1 | GE109: 6 | GF109: 10.7 | GI109: 8.7 | GJ109: 2.3 | GK109: 2.3 | GL109: 19.8 | GQ109: 20.5 | GW109: 8.3 | GX109: 11.5 | GY109: 10.9 | GZ109: 10.9 | HF109: 6.9 | HJ109: 17.2 | HK109: 14.5 | HN109: 18 | HO109: 18 | HQ109: 43 | HR109: 46.3 | IA109: 6.6 | IJ109: 11.8 | IK109: 11.9 | IL109: 21.9 | IN109: 6.4 | IQ109: 8.6
A110: 26816 | B110: 11.2 | C110: 9.4 | H110: 14.4 | I110: 14.9 | K110: 9.5 | L110: 36.7 | O110: 13.7 | AI110: 5.7 | AJ110: 9.6 | AM110: 7.9 | AN110: 2.4 | AO110: 2.4 | AP110: 19.5 | AU110: 23.4 | BA110: 7.5 | BB110: 10.1 | BC110: 8.9 | BD110: 8.9 | BJ110: 7.5 | BN110: 19.4 | BO110: 17.5 | BR110: 18.3 | BS110: 18.3 | BU110: 49.9 | BV110: 50 | CE110: 7.5 | CN110: 11.5 | CO110: 11.6 | CP110: 22.4 | CR110: 7 | CU110: 8.9 | CV110: 8.9 | CW110: 29.9 | CX110: 29.9 | EC110: 11.9 | EH110: 11.9 | EI110: 12 | EL110: 12.4 | EU110: 11.9 | EX110: 11.3 | EY110: 9.2 | FD110: 16.2 | FE110: 16.5 | FG110: 10.6 | FH110: 39 | FK110: 11.7 | GE110: 6.2 | GF110: 11.4 | GI110: 9.2 | GJ110: 2.3 | GK110: 2.3 | GL110: 20.6 | GQ110: 21.1 | GW110: 8.6 | GX110: 11.7 | GY110: 11.1 | GZ110: 11.1 | HF110: 6.9 | HJ110: 17.6 | HK110: 15.2 | HN110: 19.7 | HO110: 19.7 | HQ110: 43.2 | HR110: 46.5 | IA110: 6.6 | IJ110: 11.8 | IK110: 11.8 | IL110: 22 | IN110: 6.2 | IQ110: 8.6
A111: 26908 | B111: 12 | C111: 9.9 | H111: 15.7 | I111: 15.9 | K111: 11.2 | L111: 40.2 | O111: 14.1 | AI111: 5.7 | AJ111: 9.6 | AM111: 7.9 | AN111: 2.4 | AO111: 2.4 | AP111: 20.1 | AU111: 24.8 | BA111: 8 | BB111: 10.3 | BC111: 9.1 | BD111: 9.1 | BJ111: 7.8 | BN111: 20 | BO111: 18.2 | BR111: 19.4 | BS111: 19.4 | BU111: 50.9 | BV111: 50.9 | CE111: 8.7 | CN111: 11.7 | CO111: 11.8 | CP111: 23 | CR111: 7 | CU111: 8.9 | CV111: 8.9 | CW111: 29.9 | CX111: 29.9 | EC111: 12.3 | EH111: 12.3 | EI111: 12.3 | EL111: 12.9 | EU111: 12.4 | EX111: 11.8 | EY111: 9.3 | FD111: 16.9 | FE111: 17.2 | FG111: 11.4 | FH111: 40.6 | FK111: 11.7 | GE111: 6.2 | GF111: 11.4 | GI111: 9.2 | GJ111: 2.3 | GK111: 2.3 | GL111: 21.2 | GQ111: 22.5 | GW111: 9.2 | GX111: 12 | GY111: 11.3 | GZ111: 11.3 | HF111: 7.3 | HJ111: 18.3 | HK111: 15.4 | HN111: 20.5 | HO111: 20.5 | HQ111: 44.2 | HR111: 47.5 | IA111: 6.9 | IJ111: 12.2 | IK111: 12.4 | IL111: 22.4 | IN111: 7 | IQ111: 8.8
A112: 26999 | B112: 12.6 | C112: 10.2 | H112: 16.6 | I112: 16.7 | K112: 11.7 | L112: 40.6 | O112: 14.7 | AI112: 6 | AJ112: 9.6 | AM112: 7.9 | AN112: 2.6 | AO112: 2.6 | AP112: 20.9 | AU112: 25.3 | BA112: 8.1 | BB112: 10.6 | BC112: 9.3 | BD112: 9.3 | BJ112: 7.8 | BN112: 20.4 | BO112: 19 | BR112: 20.3 | BS112: 20.3 | BU112: 51.3 | BV112: 51.3 | CE112: 9.1 | CN112: 12 | CO112: 12.2 | CP112: 23.5 | CR112: 7.8 | CU112: 8.9 | CV112: 8.9 | CW112: 29.9 | CX112: 29.9 | EC112: 12.8 | EH112: 12.9 | EI112: 12.6 | EL112: 13.5 | EU112: 12.8 | EX112: 12.2 | EY112: 9.4 | FD112: 17.4 | FE112: 17.7 | FG112: 11.5 | FH112: 40.2 | FK112: 11.8 | GE112: 6.6 | GF112: 11.4 | GI112: 9.2 | GJ112: 2.6 | GK112: 2.6 | GL112: 22 | GQ112: 22.9 | GW112: 9.3 | GX112: 12.5 | GY112: 11.9 | GZ112: 11.9 | HF112: 7.3 | HJ112: 18.5 | HK112: 15.9 | HN112: 21.3 | HO112: 21.3 | HQ112: 44.6 | HR112: 47.9 | IA112: 7.3 | IJ112: 12.6 | IK112: 12.8 | IL112: 23 | IN112: 7.8 | IQ112: 8.7
A113: 27089 | B113: 13 | C113: 10.5 | H113: 17.8 | I113: 17.5 | K113: 13.3 | L113: 41.7 | O113: 14.9 | AI113: 6.1 | AJ113: 9.6 | AM113: 7.9 | AN113: 2.6 | AO113: 2.6 | AP113: 21.5 | AU113: 26.5 | BA113: 8.3 | BB113: 10.8 | BC113: 9.4 | BD113: 9.4 | BJ113: 8.2 | BN113: 21.1 | BO113: 19.5 | BR113: 21.8 | BS113: 21.8 | BU113: 51.9 | BV113: 52 | CE113: 9.2 | CN113: 12.3 | CO113: 12.5 | CP113: 24.2 | CR113: 8 | CU113: 8.9 | CV113: 8.9 | CW113: 29.9 | CX113: 29.9 | EC113: 13.1 | EH113: 13.1 | EI113: 12.9 | EL113: 13.8 | EU113: 13.1 | EX113: 12.6 | EY113: 9.6 | FD113: 18.9 | FE113: 18.6 | FG113: 13 | FH113: 44.1 | FK113: 12.1 | GE113: 6.6 | GF113: 11.4 | GI113: 9.2 | GJ113: 2.6 | GK113: 2.6 | GL113: 22.4 | GQ113: 23.6 | GW113: 10 | GX113: 12.9 | GY113: 12.2 | GZ113: 12.2 | HF113: 7.5 | HJ113: 19 | HK113: 16.8 | HN113: 22.1 | HO113: 22.1 | HQ113: 45 | HR113: 48.3 | IA113: 7.9 | IJ113: 12.8 | IK113: 13.1 | IL113: 23.7 | IN113: 7.8 | IQ113: 8.7
A114: 27181 | B114: 13.4 | C114: 11 | H114: 18 | I114: 17.3 | K114: 13.3 | L114: 43 | O114: 15.2 | AI114: 6.5 | AJ114: 10.6 | AM114: 8.8 | AN114: 2.7 | AO114: 2.7 | AP114: 22.9 | AU114: 27.3 | BA114: 8.9 | BB114: 11.4 | BC114: 9.7 | BD114: 9.7 | BJ114: 8.6 | BN114: 21.8 | BO114: 20.5 | BR114: 23.3 | BS114: 23.3 | BU114: 52.3 | BV114: 52.4 | CE114: 9.2 | CN114: 12.5 | CO114: 12.7 | CP114: 24.4 | CR114: 8 | CU114: 9.1 | CV114: 9.1 | CW114: 29.9 | CX114: 29.9 | EC114: 13.6 | EH114: 13.6 | EI114: 13.4 | EL114: 14.2 | EU114: 13.7 | EX114: 13.2 | EY114: 10 | FD114: 19.3 | FE114: 18.4 | FG114: 13.2 | FH114: 45.2 | FK114: 12.6 | GE114: 6.9 | GF114: 12.2 | GI114: 10 | GJ114: 2.6 | GK114: 2.6 | GL114: 24.1 | GQ114: 24.7 | GW114: 11.3 | GX114: 13.6 | GY114: 12.6 | GZ114: 12.6 | HF114: 8 | HJ114: 19.9 | HK114: 18 | HN114: 24.7 | HO114: 24.7 | HQ114: 45.8 | HR114: 49.2 | IA114: 7.9 | IJ114: 13.2 | IK114: 13.6 | IL114: 24.1 | IN114: 7.9 | IQ114: 8.7
A115: 27273 | B115: 13.8 | C115: 11.9 | H115: 17.3 | I115: 16 | K115: 12.3 | L115: 44.5 | O115: 16 | AI115: 6.8 | AJ115: 10.8 | AM115: 8.8 | AN115: 2.9 | AO115: 2.9 | AP115: 24.1 | AU115: 30.7 | BA115: 9.7 | BB115: 11.8 | BC115: 10.1 | BD115: 10.1 | BJ115: 8.9 | BN115: 23.1 | BO115: 21.9 | BR115: 24.4 | BS115: 24.4 | BU115: 55.9 | BV115: 56 | CE115: 11.7 | CN115: 13.4 | CO115: 13.9 | CP115: 26.3 | CR115: 8.4 | CU115: 9.1 | CV115: 9.1 | CW115: 29.9 | CX115: 29.9 | EC115: 14.4 | EF115: 15.8 | EG115: 12 | EH115: 14.4 | EI115: 14.2 | EL115: 15 | EU115: 14.4 | EX115: 13.5 | EY115: 10.7 | FD115: 17.9 | FE115: 16.5 | FG115: 11.5 | FH115: 45.2 | FK115: 13.5 | GE115: 7.4 | GF115: 12.9 | GI115: 10.4 | GJ115: 2.8 | GK115: 2.8 | GL115: 25.3 | GQ115: 27.2 | GW115: 12.1 | GX115: 14.3 | GY115: 13.2 | GZ115: 13.2 | HF115: 8.2 | HJ115: 20.8 | HK115: 19 | HN115: 25.5 | HO115: 25.5 | HQ115: 47.8 | HR115: 51.4 | IA115: 9 | IJ115: 14.3 | IK115: 14.7 | IL115: 25.8 | IN115: 8.3 | IQ115: 9.2
A116: 27364 | B116: 13.8 | C116: 12.8 | H116: 16.4 | I116: 14.8 | K116: 10.7 | L116: 43.6 | O116: 17.3 | AI116: 6.9 | AJ116: 11.1 | AM116: 9 | AN116: 3 | AO116: 3 | AP116: 25.9 | AU116: 31.9 | BA116: 10.7 | BB116: 12.3 | BC116: 10.4 | BD116: 10.4 | BJ116: 8.9 | BN116: 24.4 | BO116: 23.5 | BR116: 25.2 | BS116: 25.2 | BU116: 57.1 | BV116: 57.1 | CE116: 12 | CN116: 14.3 | CO116: 14.6 | CP116: 28.2 | CR116: 8.4 | CU116: 10.5 | CV116: 10.5 | CW116: 36.3 | CX116: 36.3 | EC116: 14.9 | EF116: 16.3 | EG116: 12.7 | EH116: 14.9 | EI116: 15 | EL116: 15.5 | EU116: 14.9 | EX116: 13.4 | EY116: 11.4 | FD116: 16.5 | FE116: 15 | FG116: 9.3 | FH116: 44.3 | FK116: 14 | GE116: 7.6 | GF116: 13.4 | GI116: 10.7 | GJ116: 2.8 | GK116: 2.8 | GL116: 27 | GQ116: 28.8 | GW116: 12.6 | GX116: 15.2 | GY116: 13.8 | GZ116: 13.8 | HF116: 8.3 | HJ116: 21.9 | HK116: 20.1 | HN116: 26.7 | HO116: 26.7 | HQ116: 49.3 | HR116: 53 | IA116: 10 | IJ116: 14.7 | IK116: 15.2 | IL116: 27.8 | IN116: 8.2 | IQ116: 9.2
A117: 27454 | B117: 14 | C117: 13.5 | H117: 15.9 | I117: 13.7 | K117: 10.7 | L117: 42.5 | O117: 18.4 | AI117: 7.2 | AJ117: 11.5 | AM117: 9.3 | AN117: 3.1 | AO117: 3.1 | AP117: 26.2 | AU117: 32.8 | BA117: 10.8 | BB117: 12.6 | BC117: 10.7 | BD117: 10.7 | BJ117: 9.9 | BN117: 25.3 | BO117: 23.9 | BR117: 25.5 | BS117: 25.5 | BU117: 57.7 | BV117: 57.8 | CE117: 12.5 | CN117: 15 | CO117: 15.4 | CP117: 27.1 | CR117: 9.9 | CU117: 10.8 | CV117: 10.8 | CW117: 36.3 | CX117: 36.3 | EC117: 15.3 | EF117: 16.7 | EG117: 13.4 | EH117: 15.3 | EI117: 15.6 | EL117: 16.1 | EU117: 15.3 | EX117: 13.4 | EY117: 11.9 | FD117: 16.4 | FE117: 14.4 | FG117: 9.4 | FH117: 43.4 | FK117: 14.4 | GE117: 8 | GF117: 13.9 | GI117: 11.1 | GJ117: 3.1 | GK117: 3.1 | GL117: 27.4 | GQ117: 29.7 | GW117: 13.4 | GX117: 15.8 | GY117: 14.4 | GZ117: 14.4 | HF117: 9 | HJ117: 22.9 | HK117: 20.5 | HN117: 27.7 | HO117: 27.7 | HQ117: 50.3 | HR117: 54.1 | IA117: 10.9 | IJ117: 15.3 | IK117: 15.9 | IL117: 26.8 | IN117: 8.7 | IQ117: 9.2
A118: 27546 | B118: 14.3 | C118: 13.8 | H118: 16.3 | I118: 13.8 | K118: 11.2 | L118: 45.3 | O118: 18.7 | AI118: 7.3 | AJ118: 11.6 | AM118: 9.3 | AN118: 3.2 | AO118: 3.2 | AP118: 27.3 | AU118: 33.9 | BA118: 11.5 | BB118: 13.4 | BC118: 11.1 | BD118: 11.1 | BJ118: 10.9 | BN118: 26.5 | BO118: 24.5 | BR118: 26.6 | BS118: 26.6 | BU118: 58.5 | BV118: 58.6 | CE118: 12.8 | CN118: 15.4 | CO118: 15.8 | CP118: 28.6 | CR118: 10 | CU118: 10.8 | CV118: 10.8 | CW118: 36.4 | CX118: 36.4 | EC118: 15.9 | EF118: 17.3 | EG118: 14.1 | EH118: 15.9 | EI118: 16.2 | EL118: 16.7 | EU118: 15.8 | EX118: 13.9 | EY118: 12.4 | FD118: 17.3 | FE118: 14 | FG118: 11.1 | FH118: 47 | FK118: 14.8 | GE118: 8.1 | GF118: 14.1 | GI118: 11.3 | GJ118: 3.1 | GK118: 3.1 | GL118: 28.7 | GQ118: 30.9 | GW118: 14.7 | GX118: 16.7 | GY118: 15 | GZ118: 15 | HF118: 9.2 | HJ118: 23.4 | HK118: 20.9 | HN118: 29.4 | HO118: 29.4 | HQ118: 51.5 | HR118: 55.3 | IA118: 10.9 | IJ118: 15.9 | IK118: 16.6 | IL118: 28.2 | IN118: 8.9 | IQ118: 9.2
A119: 27638 | B119: 14.6 | C119: 14.3 | H119: 16.6 | I119: 13.8 | K119: 11.4 | L119: 47 | O119: 18.8 | AI119: 7.4 | AJ119: 11.8 | AM119: 9.4 | AN119: 3.2 | AO119: 3.2 | AP119: 27.9 | AU119: 35.3 | BA119: 12.3 | BB119: 13.9 | BC119: 11.6 | BD119: 11.6 | BJ119: 10.9 | BN119: 26.9 | BO119: 25.2 | BR119: 27.7 | BS119: 27.7 | BU119: 58.4 | BV119: 58.5 | CE119: 13.8 | CN119: 16.3 | CO119: 16.8 | CP119: 30.9 | CR119: 10 | CU119: 11.2 | CV119: 11.2 | CW119: 36.4 | CX119: 36.4 | EC119: 16.1 | EF119: 17.6 | EG119: 14 | EH119: 16.1 | EI119: 16.5 | EL119: 16.8 | EU119: 16.3 | EX119: 14.2 | EY119: 12.9 | FD119: 17.6 | FE119: 13.9 | FG119: 11.6 | FH119: 48.4 | FK119: 15.5 | GE119: 8.3 | GF119: 14.5 | GI119: 11.6 | GJ119: 3.2 | GK119: 3.2 | GL119: 29.4 | GQ119: 32.5 | GW119: 16.8 | GX119: 17.3 | GY119: 15.8 | GZ119: 15.8 | HF119: 9.3 | HJ119: 23.9 | HK119: 21.9 | HN119: 30.2 | HO119: 30.2 | HQ119: 51.3 | HR119: 55.1 | IA119: 12.3 | IJ119: 16.9 | IK119: 17.4 | IL119: 30.4 | IN119: 8.7 | IQ119: 11
A120: 27729 | B120: 15 | C120: 14.6 | H120: 17.3 | I120: 14.9 | K120: 11.8 | L120: 47 | O120: 19.1 | AI120: 9.2 | AJ120: 14.5 | AM120: 12.2 | AN120: 4.1 | AO120: 4.1 | AP120: 29.8 | AU120: 36.4 | BA120: 12.6 | BB120: 14.5 | BC120: 12 | BD120: 12 | BJ120: 11 | BN120: 28.7 | BO120: 26.2 | BR120: 28.4 | BS120: 28.4 | BU120: 59.9 | BV120: 60 | CE120: 14.3 | CN120: 17.2 | CO120: 17.8 | CP120: 33.2 | CR120: 11.2 | CU120: 11.2 | CV120: 11.2 | CW120: 51.3 | CX120: 51.3 | EC120: 16.9 | EF120: 18.8 | EG120: 13.8 | EH120: 16.9 | EI120: 17.3 | EL120: 17.6 | EU120: 17.4 | EX120: 14.6 | EY120: 13.3 | FD120: 17.8 | FE120: 14.4 | FG120: 11.3 | FH120: 48.4 | FK120: 15.6 | GE120: 9.7 | GF120: 17.1 | GI120: 14.1 | GJ120: 3.6 | GK120: 3.6 | GL120: 31.3 | GQ120: 33.3 | GW120: 18.4 | GX120: 18.1 | GY120: 16.4 | GZ120: 16.4 | HF120: 9.5 | HJ120: 25.7 | HK120: 23 | HN120: 30.7 | HO120: 30.7 | HQ120: 52.5 | HR120: 56.4 | IA120: 12.4 | IJ120: 17.8 | IK120: 18.4 | IL120: 32.7 | IN120: 9.5 | IQ120: 11.2
A121: 27820 | B121: 15.8 | C121: 15.1 | H121: 17.8 | I121: 15.1 | K121: 12.2 | L121: 49.3 | O121: 20.1 | AI121: 9.3 | AJ121: 14.7 | AM121: 12.2 | AN121: 4.1 | AO121: 4.1 | AP121: 30.1 | AU121: 36.9 | BA121: 12.7 | BB121: 14.9 | BC121: 12.2 | BD121: 12.2 | BJ121: 11.3 | BN121: 29.3 | BO121: 27 | BR121: 29 | BS121: 29 | BU121: 60.5 | BV121: 60.6 | CE121: 14.6 | CN121: 18 | CO121: 18.4 | CP121: 34.3 | CR121: 11.9 | CU121: 12.7 | CV121: 12.7 | CW121: 51.3 | CX121: 51.3 | EC121: 17.4 | EF121: 19.4 | EG121: 14.2 | EH121: 17.4 | EI121: 17.8 | EL121: 18.2 | EU121: 17.9 | EX121: 15.3 | EY121: 13.9 | FD121: 18.1 | FE121: 14.7 | FG121: 11.1 | FH121: 50.1 | FK121: 15.9 | GE121: 10 | GF121: 17.2 | GI121: 14.1 | GJ121: 3.9 | GK121: 3.9 | GL121: 31.8 | GQ121: 34.5 | GW121: 18.2 | GX121: 18.7 | GY121: 17.1 | GZ121: 17.1 | HF121: 9.8 | HJ121: 26.2 | HK121: 23.4 | HN121: 31.5 | HO121: 31.5 | HQ121: 52.6 | HR121: 56.5 | IA121: 12.5 | IJ121: 18 | IK121: 18.7 | IL121: 33.5 | IN121: 9.4 | IQ121: 11.2
A122: 27912 | B122: 15.7 | C122: 15.4 | H122: 17.8 | I122: 15.1 | K122: 12 | L122: 49.5 | O122: 20.1 | AI122: 9.7 | AJ122: 15.4 | AM122: 12.9 | AN122: 4.2 | AO122: 4.2 | AP122: 31.8 | AU122: 38.4 | BA122: 13.3 | BB122: 15.6 | BC122: 12.6 | BD122: 12.6 | BJ122: 11.8 | BN122: 30.2 | BO122: 28.7 | BR122: 30 | BS122: 30 | BU122: 61.1 | BV122: 61.1 | CE122: 15.9 | CN122: 17.8 | CO122: 18.3 | CP122: 35.3 | CR122: 10.7 | CU122: 12.7 | CV122: 12.7 | CW122: 51.5 | CX122: 51.5 | EC122: 17.8 | EF122: 19.7 | EG122: 14.8 | EH122: 17.8 | EI122: 18.3 | EL122: 18.5 | EU122: 18.3 | EX122: 15.3 | EY122: 14.3 | FD122: 18.1 | FE122: 14.7 | FG122: 11 | FH122: 51.2 | FK122: 16 | GE122: 10.2 | GF122: 17.6 | GI122: 14.4 | GJ122: 4 | GK122: 4 | GL122: 33.7 | GQ122: 35.9 | GW122: 18 | GX122: 19.5 | GY122: 17.6 | GZ122: 17.6 | HF122: 9.9 | HJ122: 26.8 | HK122: 24.6 | HN122: 33.1 | HO122: 33.1 | HQ122: 53 | HR122: 57 | IA122: 13.7 | IJ122: 18.4 | IK122: 19.1 | IL122: 34.3 | IN122: 9.5 | IQ122: 11.2
A123: 28004 | B123: 16.1 | C123: 15.5 | H123: 18.3 | I123: 15.6 | K123: 13 | L123: 47.6 | N123: 17.1 | O123: 20.2 | AF123: 15.8 | AI123: 9.7 | AJ123: 15.4 | AM123: 12.9 | AN123: 4.2 | AO123: 4.2 | AP123: 32.4 | AU123: 40.2 | BA123: 13.5 | BB123: 16 | BC123: 13.1 | BD123: 13.1 | BJ123: 11.8 | BN123: 30.7 | BO123: 29.4 | BR123: 31.2 | BS123: 31.2 | BU123: 61.1 | BV123: 61.1 | CE123: 16.4 | CN123: 17.8 | CO123: 18.7 | CP123: 36.2 | CR123: 10.9 | CU123: 10.6 | CV123: 10.6 | CW123: 51.4 | CX123: 51.4 | EC123: 18.1 | EF123: 20.1 | EG123: 15 | EH123: 18.1 | EI123: 18.6 | EL123: 18.8 | EU123: 18.6 | EX123: 15.9 | EY123: 14.5 | FD123: 19.1 | FE123: 15.6 | FG123: 12.5 | FH123: 50.6 | FJ123: 16.8 | FK123: 16.2 | GB123: 14.3 | GE123: 10.1 | GF123: 17.2 | GI123: 14 | GJ123: 4 | GK123: 4 | GL123: 34.3 | GQ123: 37 | GW123: 18.5 | GX123: 20 | GY123: 18.2 | GZ123: 18.2 | HF123: 10.1 | HJ123: 27.4 | HK123: 25.6 | HN123: 34 | HO123: 34 | HQ123: 53.6 | HR123: 57.6 | IA123: 14.6 | IJ123: 19 | IK123: 19.6 | IL123: 35.3 | IN123: 9.7 | IQ123: 12.5
A124: 28095 | B124: 16.8 | C124: 15.8 | H124: 19 | I124: 16.1 | K124: 14.4 | L124: 47.6 | N124: 17.3 | O124: 20.4 | AF124: 15.9 | AI124: 9.8 | AJ124: 15.7 | AM124: 13.2 | AN124: 4.2 | AO124: 4.2 | AP124: 34.4 | AU124: 40.7 | BA124: 13.9 | BB124: 16.5 | BC124: 13.6 | BD124: 13.6 | BJ124: 11.8 | BN124: 31.4 | BO124: 30.6 | BR124: 31.3 | BS124: 31.3 | BU124: 61.4 | BV124: 61.4 | CE124: 17.1 | CN124: 18 | CO124: 18.9 | CP124: 37 | CR124: 11 | CU124: 10.6 | CV124: 10.6 | CW124: 51.9 | CX124: 51.9 | EC124: 19.1 | EF124: 20.7 | EG124: 16.9 | EH124: 19.1 | EI124: 19.7 | EL124: 19.9 | EU124: 19.1 | EX124: 16.5 | EY124: 14.8 | FD124: 19.8 | FE124: 16.1 | FG124: 13.3 | FH124: 51.3 | FJ124: 18 | FK124: 16.3 | GB124: 14.7 | GE124: 10.2 | GF124: 17.3 | GI124: 14.1 | GJ124: 4.1 | GK124: 4.1 | GL124: 36.6 | GQ124: 37.5 | GW124: 19 | GX124: 20.5 | GY124: 18.6 | GZ124: 18.6 | HF124: 10.3 | HJ124: 27.8 | HK124: 26.6 | HN124: 34.1 | HO124: 34.1 | HQ124: 54.5 | HR124: 58.6 | IA124: 14.8 | IJ124: 19.4 | IK124: 20 | IL124: 36 | IN124: 9.7 | IQ124: 12.5
A125: 28185 | B125: 17 | C125: 16 | H125: 19.4 | I125: 16.1 | K125: 14.1 | L125: 53.2 | N125: 19.3 | O125: 20.6 | AF125: 16.4 | AI125: 9.8 | AJ125: 15.7 | AM125: 13.3 | AN125: 4.3 | AO125: 4.3 | AP125: 34.9 | AU125: 42.2 | BA125: 14 | BB125: 16.8 | BC125: 13.9 | BD125: 13.9 | BJ125: 12.1 | BN125: 32.1 | BO125: 31.5 | BR125: 33.2 | BS125: 33.2 | BU125: 61.9 | BV125: 62 | CE125: 18.2 | CN125: 18.5 | CO125: 19.6 | CP125: 38 | CR125: 11.4 | CU125: 10.6 | CV125: 10.6 | CW125: 51.9 | CX125: 51.9 | EC125: 19.5 | EF125: 21 | EG125: 17.3 | EH125: 19.5 | EI125: 20.1 | EL125: 20.3 | EU125: 19.5 | EX125: 16.8 | EY125: 15.2 | FD125: 20.1 | FE125: 15.9 | FG125: 13.1 | FH125: 54.3 | FJ125: 20 | FK125: 17.7 | GB125: 15.4 | GE125: 10.3 | GF125: 17.6 | GI125: 14.4 | GJ125: 4.1 | GK125: 4.1 | GL125: 37.2 | GQ125: 39 | GW125: 19.4 | GX125: 21.1 | GY125: 19.2 | GZ125: 19.2 | HF125: 11.2 | HJ125: 28.9 | HK125: 27.2 | HN125: 36.5 | HO125: 36.5 | HQ125: 55.2 | HR125: 59.4 | IA125: 15.3 | IJ125: 20.2 | IK125: 20.9 | IL125: 37.1 | IN125: 10.2 | IQ125: 12.5
A126: 28277 | B126: 17.4 | C126: 16.3 | H126: 20.1 | I126: 16.7 | K126: 14.9 | L126: 53.4 | N126: 20.3 | O126: 20.7 | AF126: 17 | AI126: 10 | AJ126: 16 | AM126: 13.5 | AN126: 4.3 | AO126: 4.3 | AP126: 36.3 | AU126: 43.4 | BA126: 14.7 | BB126: 17.3 | BC126: 14.3 | BD126: 14.3 | BJ126: 12.2 | BN126: 32.9 | BO126: 32.6 | BR126: 36 | BS126: 36 | BU126: 63.6 | BV126: 63.7 | CE126: 18.4 | CN126: 18.7 | CO126: 19.8 | CP126: 39.1 | CR126: 11.1 | CU126: 10.6 | CV126: 10.6 | CW126: 51.9 | CX126: 51.9 | EC126: 19.9 | EF126: 21.5 | EG126: 17.7 | EH126: 19.9 | EI126: 20.5 | EL126: 20.7 | EU126: 19.9 | EX126: 17.4 | EY126: 15.3 | FD126: 21.3 | FE126: 17 | FG126: 14.4 | FH126: 55.5 | FJ126: 21.7 | FK126: 18.4 | GB126: 16 | GE126: 10.4 | GF126: 17.6 | GI126: 14.4 | GJ126: 4.2 | GK126: 4.2 | GL126: 38.4 | GQ126: 40.1 | GW126: 20 | GX126: 21.8 | GY126: 19.5 | GZ126: 19.5 | HF126: 11.3 | HJ126: 29.6 | HK126: 28.5 | HN126: 39.1 | HO126: 39.1 | HQ126: 56.1 | HR126: 60.3 | IA126: 16.1 | IJ126: 20.7 | IK126: 21.5 | IL126: 38.2 | IN126: 10.2 | IQ126: 12.5
A127: 28369 | B127: 17.9 | C127: 16.7 | H127: 20.1 | I127: 16.6 | K127: 14.8 | L127: 53.4 | N127: 19.9 | O127: 20.8 | AF127: 17.4 | AI127: 10 | AJ127: 16 | AM127: 13.6 | AN127: 4.3 | AO127: 4.3 | AP127: 36.8 | AU127: 44.7 | BA127: 14.8 | BB127: 17.6 | BC127: 14.7 | BD127: 14.7 | BJ127: 12.2 | BN127: 33.3 | BO127: 32.9 | BR127: 37 | BS127: 37 | BU127: 63.8 | BV127: 63.9 | CE127: 19.4 | CN127: 18.9 | CO127: 20.1 | CP127: 40 | CR127: 10.9 | CU127: 10.6 | CV127: 10.6 | CW127: 51.9 | CX127: 51.9 | EC127: 20.3 | EF127: 21.9 | EG127: 18 | EH127: 20.3 | EI127: 20.7 | EL127: 21 | EU127: 20.3 | EX127: 18.1 | EY127: 15.7 | FD127: 21.4 | FE127: 16.8 | FG127: 14.4 | FH127: 56.4 | FJ127: 23.2 | FK127: 18.9 | GB127: 16.4 | GE127: 10.6 | GF127: 18.2 | GI127: 14.8 | GJ127: 4.2 | GK127: 4.2 | GL127: 39 | GQ127: 41.2 | GW127: 20.6 | GX127: 22.1 | GY127: 19.8 | GZ127: 19.8 | HF127: 11.4 | HJ127: 30 | HK127: 28.4 | HN127: 40.2 | HO127: 40.2 | HQ127: 55.7 | HR127: 59.9 | IA127: 16.7 | IJ127: 21 | IK127: 21.8 | IL127: 39.1 | IN127: 10.6 | IQ127: 12.8
A128: 28460 | B128: 18.4 | C128: 17.2 | H128: 20.4 | I128: 16.8 | K128: 14.6 | L128: 54.6 | N128: 20.8 | O128: 22.1 | AF128: 17.6 | AI128: 10.2 | AJ128: 16.5 | AM128: 14 | AN128: 4.3 | AO128: 4.3 | AP128: 38 | AU128: 45.2 | BA128: 15.2 | BB128: 18 | BC128: 15 | BD128: 15 | BJ128: 12.3 | BN128: 33.9 | BO128: 33.4 | BR128: 38.1 | BS128: 38.1 | BU128: 64.9 | BV128: 64.9 | CE128: 19.6 | CN128: 19.5 | CO128: 20.7 | CP128: 40.5 | CR128: 12.2 | CU128: 10.9 | CV128: 10.9 | CW128: 52.6 | CX128: 52.6 | EC128: 20.7 | EF128: 22.4 | EG128: 18.4 | EH128: 20.7 | EI128: 21.2 | EL128: 21.6 | EU128: 20.8 | EX128: 18.5 | EY128: 15.9 | FD128: 21.4 | FE128: 16.7 | FG128: 13.6 | FH128: 57 | FJ128: 24.2 | FK128: 20.1 | GB128: 16.7 | GE128: 10.7 | GF128: 18.4 | GI128: 15 | GJ128: 4.2 | GK128: 4.2 | GL128: 40.3 | GQ128: 42.1 | GW128: 21.7 | GX128: 22.5 | GY128: 20.1 | GZ128: 20.1 | HF128: 11.8 | HJ128: 30.7 | HK128: 29 | HN128: 41.8 | HO128: 41.8 | HQ128: 56.9 | HR128: 61.2 | IA128: 17.4 | IJ128: 21.5 | IK128: 22.4 | IL128: 39.5 | IN128: 11.5 | IQ128: 12.8
A129: 28550 | B129: 18.6 | C129: 17.6 | H129: 21.4 | I129: 17.9 | K129: 16.4 | L129: 53.1 | N129: 21 | O129: 22.4 | AF129: 17.9 | AI129: 10.3 | AJ129: 16.5 | AM129: 14 | AN129: 4.4 | AO129: 4.4 | AP129: 38.3 | AU129: 45.8 | BA129: 15.5 | BB129: 18.3 | BC129: 15.3 | BD129: 15.3 | BJ129: 12.5 | BN129: 34.3 | BO129: 33.8 | BR129: 38.3 | BS129: 38.3 | BU129: 65.3 | BV129: 65.3 | CE129: 20 | CN129: 19.8 | CO129: 21 | CP129: 41.5 | CR129: 11.9 | CU129: 11.2 | CV129: 11.2 | CW129: 52.5 | CX129: 52.5 | EC129: 21 | EF129: 22.7 | EG129: 18.7 | EH129: 21 | EI129: 21.5 | EL129: 21.9 | EU129: 21.1 | EX129: 18.4 | EY129: 16.4 | FD129: 21.8 | FE129: 16.6 | FG129: 14.7 | FH129: 57.8 | FJ129: 25.1 | FK129: 20.2 | GB129: 17 | GE129: 10.9 | GF129: 18.6 | GI129: 15.1 | GJ129: 4.3 | GK129: 4.3 | GL129: 41 | GQ129: 43 | GW129: 21.6 | GX129: 22.8 | GY129: 20.2 | GZ129: 20.2 | HF129: 11.9 | HJ129: 31.1 | HK129: 29.5 | HN129: 42.3 | HO129: 42.3 | HQ129: 57.9 | HR129: 62.2 | IA129: 18 | IJ129: 21.9 | IK129: 22.6 | IL129: 40.7 | IN129: 11.5 | IQ129: 14.3
A130: 28642 | B130: 19.1 | C130: 17.9 | H130: 22.1 | I130: 18.8 | K130: 17.1 | L130: 53.8 | N130: 20.8 | O130: 22.5 | AF130: 17.9 | AI130: 10.3 | AJ130: 16.5 | AM130: 14 | AN130: 4.3 | AO130: 4.3 | AP130: 39.3 | AU130: 46.6 | BA130: 15.7 | BB130: 18.8 | BC130: 15.6 | BD130: 15.6 | BJ130: 12.8 | BN130: 34.8 | BO130: 34.1 | BR130: 39.4 | BS130: 39.4 | BU130: 65.6 | BV130: 65.6 | CE130: 20.7 | CN130: 20 | CO130: 21.3 | CP130: 42.5 | CR130: 11.9 | CU130: 11.2 | CV130: 11.2 | CW130: 52.5 | CX130: 52.5 | EC130: 21.4 | EF130: 23.1 | EG130: 19.2 | EH130: 21.5 | EI130: 21.9 | EL130: 22.3 | EU130: 21.4 | EX130: 18.9 | EY130: 16.6 | FD130: 22.6 | FE130: 17.4 | FG130: 15.8 | FH130: 57.8 | FJ130: 25.8 | FK130: 20.3 | GB130: 17.3 | GE130: 10.9 | GF130: 18.8 | GI130: 15.2 | GJ130: 4.3 | GK130: 4.3 | GL130: 42 | GQ130: 43.5 | GW130: 21.9 | GX130: 23.1 | GY130: 20.4 | GZ130: 20.4 | HF130: 12.5 | HJ130: 31.8 | HK130: 29.8 | HN130: 44.1 | HO130: 44.1 | HQ130: 58.5 | HR130: 62.9 | IA130: 18.4 | IJ130: 22.1 | IK130: 22.8 | IL130: 41.5 | IN130: 11.7 | IQ130: 14.3
A131: 28734 | B131: 19.7 | C131: 18.3 | H131: 23.6 | I131: 21 | K131: 18.1 | L131: 52.3 | N131: 21.4 | O131: 22.8 | AF131: 18.3 | AI131: 10.4 | AJ131: 16.8 | AM131: 14.2 | AN131: 4.4 | AO131: 4.4 | AP131: 39.8 | AU131: 47.4 | BA131: 16.1 | BB131: 19.1 | BC131: 16.1 | BD131: 16.1 | BJ131: 12.9 | BN131: 35.2 | BO131: 34.1 | BR131: 39.7 | BS131: 39.7 | BU131: 66.5 | BV131: 66.6 | CE131: 21.1 | CN131: 20.5 | CO131: 21.8 | CP131: 43.9 | CR131: 12.2 | CU131: 11.2 | CV131: 11.2 | CW131: 53.6 | CX131: 53.6 | EC131: 21.9 | EF131: 23.5 | EG131: 19.7 | EH131: 21.9 | EI131: 22.3 | EL131: 22.7 | EU131: 21.8 | EX131: 19.5 | EY131: 16.9 | FD131: 23.8 | FE131: 19.2 | FG131: 16 | FH131: 56.9 | FJ131: 26 | FK131: 20.4 | GB131: 17.7 | GE131: 11 | GF131: 19 | GI131: 15.5 | GJ131: 4.3 | GK131: 4.3 | GL131: 42.5 | GQ131: 44.5 | GW131: 22.2 | GX131: 23.4 | GY131: 21 | GZ131: 21 | HF131: 12.5 | HJ131: 32.3 | HK131: 30.3 | HN131: 44.8 | HO131: 44.8 | HQ131: 59.1 | HR131: 63.5 | IA131: 19.3 | IJ131: 22.5 | IK131: 23.3 | IL131: 42.8 | IN131: 11.4 | IQ131: 14.3
A132: 28825 | B132: 20.4 | C132: 18.5 | H132: 24.4 | I132: 21.9 | K132: 17.8 | L132: 54 | N132: 22.8 | O132: 23.4 | AF132: 18.9 | AI132: 12.1 | AJ132: 19.5 | AM132: 16.3 | AN132: 5.1 | AO132: 5.1 | AP132: 40.8 | AU132: 48.3 | BA132: 16.3 | BB132: 19.5 | BC132: 16.5 | BD132: 16.5 | BJ132: 13.1 | BN132: 35.6 | BO132: 34.7 | BR132: 40.4 | BS132: 40.4 | BU132: 67 | BV132: 67 | CE132: 22.3 | CN132: 21.1 | CO132: 22.6 | CP132: 42.4 | CR132: 14.5 | CU132: 11.2 | CV132: 11.2 | CW132: 54.2 | CX132: 54.2 | EC132: 22.4 | EF132: 24.6 | EG132: 19.2 | EH132: 22.4 | EI132: 22.8 | EL132: 23.3 | EU132: 22.7 | EX132: 20.2 | EY132: 16.9 | FD132: 24.2 | FE132: 19.5 | FG132: 15.7 | FH132: 58.1 | FJ132: 26.7 | FK132: 21.6 | GB132: 18.1 | GE132: 12.7 | GF132: 21.9 | GI132: 17.6 | GJ132: 5 | GK132: 5 | GL132: 43.2 | GQ132: 44.7 | GW132: 22.6 | GX132: 23.6 | GY132: 21.2 | GZ132: 21.2 | HF132: 13 | HJ132: 32.8 | HK132: 30.3 | HN132: 45.3 | HO132: 45.3 | HQ132: 59.1 | HR132: 63.5 | IA132: 19.3 | IJ132: 23.3 | IK132: 24.2 | IL132: 41.4 | IN132: 14.1 | IQ132: 14.3
A133: 28915 | B133: 21.1 | C133: 18.8 | H133: 27 | I133: 25.4 | K133: 19.9 | L133: 54.2 | N133: 22.3 | O133: 23.6 | AF133: 19.3 | AI133: 12.1 | AJ133: 19.6 | AM133: 16.4 | AN133: 5.1 | AO133: 5.1 | AP133: 40.9 | AU133: 48.7 | BA133: 16.7 | BB133: 19.9 | BC133: 16.9 | BD133: 16.9 | BJ133: 13.4 | BN133: 36.1 | BO133: 34.8 | BR133: 41.3 | BS133: 41.3 | BU133: 67.6 | BV133: 67.6 | CE133: 22.8 | CN133: 21.9 | CO133: 23.4 | CP133: 43.5 | CR133: 15.4 | CU133: 11.8 | CV133: 11.8 | CW133: 53.8 | CX133: 53.8 | EC133: 22.8 | EF133: 25.1 | EG133: 19.6 | EH133: 22.9 | EI133: 23.2 | EL133: 23.8 | EU133: 23.1 | EX133: 20.8 | EY133: 17.3 | FD133: 27.3 | FE133: 23.3 | FG133: 18.3 | FH133: 59.5 | FJ133: 26.9 | FK133: 21.7 | GB133: 18.7 | GE133: 12.9 | GF133: 22.3 | GI133: 17.9 | GJ133: 5 | GK133: 5 | GL133: 43.6 | GQ133: 45 | GW133: 23 | GX133: 23.7 | GY133: 21.4 | GZ133: 21.4 | HF133: 14 | HJ133: 33.5 | HK133: 30.5 | HN133: 46.1 | HO133: 46.1 | HQ133: 59.8 | HR133: 64.3 | IA133: 19.9 | IJ133: 23.7 | IK133: 24.6 | IL133: 42.4 | IN133: 14.3 | IQ133: 14.5
A134: 29007 | B134: 22.1 | C134: 19 | H134: 32.4 | I134: 33 | K134: 24.2 | L134: 55 | N134: 23.4 | O134: 24.2 | AF134: 19.9 | AI134: 12.4 | AJ134: 20.1 | AM134: 16.9 | AN134: 5.1 | AO134: 5.1 | AP134: 42.1 | AU134: 50 | BA134: 17.4 | BB134: 20.4 | BC134: 17.4 | BD134: 17.4 | BJ134: 13.8 | BN134: 36.5 | BO134: 34.7 | BR134: 41.6 | BS134: 41.6 | BU134: 68 | BV134: 68.1 | CE134: 23 | CN134: 22.4 | CO134: 24 | CP134: 44.1 | CR134: 16.1 | CU134: 11.8 | CV134: 11.8 | CW134: 53.8 | CX134: 53.8 | EC134: 23.5 | EF134: 25.8 | EG134: 19.9 | EH134: 23.5 | EI134: 23.8 | EL134: 24.5 | EU134: 23.8 | EX134: 21.8 | EY134: 17.4 | FD134: 32.6 | FE134: 31 | FG134: 20.9 | FH134: 60.7 | FJ134: 28.3 | FK134: 21.9 | GB134: 19.2 | GE134: 13 | GF134: 22.4 | GI134: 18.1 | GJ134: 5.1 | GK134: 5.1 | GL134: 44.9 | GQ134: 46.3 | GW134: 23.1 | GX134: 24.2 | GY134: 21.6 | GZ134: 21.6 | HF134: 14.2 | HJ134: 33.9 | HK134: 30.5 | HN134: 45.9 | HO134: 45.9 | HQ134: 60.5 | HR134: 65 | IA134: 21 | IJ134: 24.5 | IK134: 25.6 | IL134: 42.7 | IN134: 16.1 | IQ134: 14.5
... A138: 29373 | B138: 25.1 | C138: 20.8 | H138: 36.5 | I138: 37.4 | K138: 26.6 | L138: 61.4 | N138: 27.1 | O138: 25.7 | AF138: 22.6 | AI138: 13.1 | AJ138: 21.4 | AM138: 18.2 | AN138: 5.4 | AO138: 5.4 | AP138: 44.9 | AU138: 55.5 | BA138: 20.2 | BB138: 22.5 | BC138: 19 | BD138: 19 | BJ138: 15.5 | BN138: 39.8 | BO138: 37.3 | BR138: 45.9 | BS138: 45.9 | BU138: 72.3 | BV138: 72.4 | CE138: 24.6 | CN138: 25.4 | CO138: 27.1 | CP138: 46.5 | CR138: 21.8 | CU138: 14 | CV138: 14 | CW138: 55.6 | CX138: 55.6 | EC138: 26.1 | EF138: 28.6 | EG138: 22.3 | EH138: 26.1 | EI138: 26.2 | EL138: 27.2 | EU138: 26.3 | EX138: 24.3 | EY138: 19.1 | FD138: 36.3 | FE138: 34.3 | FG138: 22.9 | FH138: 66.1 | FJ138: 32.5 | FK138: 24.5 | GB138: 21.2 | GE138: 13.8 | GF138: 23.6 | GI138: 19.1 | GJ138: 5.5 | GK138: 5.5 | GL138: 47.8 | GQ138: 50.3 | GW138: 25.1 | GX138: 25.8 | GY138: 22.7 | GZ138: 22.7 | HF138: 16.6 | HJ138: 37.5 | HK138: 33.5 | HN138: 49.6 | HO138: 49.6 | HQ138: 64.5 | HR138: 69.3 | IA138: 22.7 | IJ138: 27.9 | IK138: 29 | IL138: 46 | IN138: 21.7 | IQ138: 17
A139: 29465 | B139: 25.5 | C139: 21.7 | D139: 20.3 | E139: 21.8 | F139: 25.5 | G139: 27.7 | H139: 36.4 | I139: 37.7 | J139: 34 | K139: 26.3 | L139: 57.8 | M139: 30 | N139: 27.4 | O139: 26 | P139: 27.9 | Q139: 22.1 | R139: 27.3 | W139: 31.8 | X139: 22.9 | AB139: 26 | AD139: 36.2 | AF139: 23 | AG139: 24.6 | AH139: 21.3 | AI139: 13.5 | AJ139: 22 | AK139: 18.3 | AL139: 33.9 | AM139: 18.7 | AN139: 5.5 | AO139: 5.5 | AP139: 45.6 | AU139: 57.3 | AV139: 76.3 | AW139: 50.2 | AX139: 49.1 | BA139: 20.3 | BB139: 23.2 | BC139: 19.6 | BD139: 19.6 | BH139: 29.4 | BJ139: 15.4 | BL139: 13.6 | BN139: 41 | BO139: 39.4 | BP139: 43.2 | BQ139: 28.2 | BR139: 47.3 | BS139: 47.3 | BU139: 74.6 | BV139: 74.7 | BX139: 35.4 | BZ139: 33.2 | CA139: 36.1 | CE139: 24.8 | CI139: 24.4 | CK139: 16.9 | CL139: 17.1 | CM139: 15.4 | CN139: 25.4 | CO139: 26.9 | CP139: 46.5 | CQ139: 44.7 | CR139: 20.8 | CS139: 28.2 | CT139: 17 | CU139: 14 | CV139: 14 | CW139: 55.6 | CX139: 55.6 | CY139: 30.1 | CZ139: 59.3 | DC139: 1136.5 | DN139: 26.6 | EC139: 26.6 | EF139: 29.2 | EG139: 22.6 | EH139: 26.6 | EI139: 26.7 | EJ139: 28.2 | EK139: 25.7 | EL139: 27.6 | EM139: 25 | EO139: 26.8 | EU139: 26.8 | EX139: 25 | EY139: 20 | EZ139: 16.5 | FA139: 22 | FB139: 24.7 | FC139: 25.6 | FD139: 36.3 | FE139: 34.3 | FF139: 38.2 | FG139: 22.8 | FH139: 65.8 | FI139: 29.8 | FJ139: 33.7 | FK139: 25.3 | FL139: 27.5 | FM139: 22.3 | FN139: 28.9 | FS139: 37.3 | FT139: 25.3 | FX139: 28 | FZ139: 36.2 | GB139: 21.8 | GC139: 22.9 | GD139: 20.5 | GE139: 14 | GF139: 23.9 | GG139: 22.3 | GH139: 38.2 | GI139: 19.4 | GJ139: 5.6 | GK139: 5.6 | GL139: 48.3 | GQ139: 51 | GR139: 58.7 | GS139: 44.1 | GT139: 58.6 | GW139: 25.4 | GX139: 26.4 | GY139: 23 | GZ139: 23 | HD139: 26.9 | HF139: 17.2 | HH139: 17 | HJ139: 38.9 | HK139: 34.2 | HL139: 35.2 | HM139: 30.3 | HN139: 50.5 | HO139: 50.5 | HQ139: 67 | HR139: 72 | HT139: 37.3 | HV139: 34.1 | HW139: 33.2 | IA139: 22.8 | IE139: 24.6 | IG139: 13.7 | IH139: 13.5 | II139: 15.1 | IJ139: 28.3 | IK139: 28.9 | IL139: 45.8 | IM139: 38.6 | IN139: 20.8 | IO139: 29.5 | IP139: 31.7 | IQ139: 19.7
A140: 29556 | B140: 26.3 | C140: 22.6 | D140: 21.1 | E140: 22.8 | F140: 26.3 | G140: 28.7 | H140: 36.1 | I140: 37.2 | J140: 36.1 | K140: 23.9 | L140: 63.5 | M140: 30.8 | N140: 28.3 | O140: 28.1 | P140: 30.7 | Q140: 23.2 | R140: 28.4 | W140: 33.4 | X140: 23.7 | AB140: 26.9 | AD140: 36.8 | AF140: 23.5 | AG140: 25.1 | AH140: 22 | AI140: 13.6 | AJ140: 22.3 | AK140: 18.1 | AL140: 35.3 | AM140: 19 | AN140: 5.5 | AO140: 5.5 | AP140: 46.6 | AU140: 58.8 | AV140: 77.6 | AW140: 52 | AX140: 49.6 | BA140: 20.6 | BB140: 23.8 | BC140: 19.9 | BD140: 19.9 | BH140: 29.4 | BJ140: 15.5 | BL140: 13.6 | BN140: 41.9 | BO140: 40.9 | BP140: 45.1 | BQ140: 28.7 | BR140: 48.8 | BS140: 48.8 | BU140: 74.5 | BV140: 74.6 | BX140: 36.3 | BZ140: 36.5 | CA140: 36.3 | CE140: 25.9 | CI140: 24.8 | CK140: 17 | CL140: 17.2 | CM140: 15.4 | CN140: 26 | CO140: 27.3 | CP140: 47.3 | CQ140: 45.4 | CR140: 21.5 | CS140: 28.6 | CT140: 17 | CU140: 15.8 | CV140: 15.8 | CW140: 55.6 | CX140: 55.6 | CY140: 30.1 | CZ140: 59.2 | DC140: 1111.7 | DN140: 26.5 | EC140: 27.1 | EF140: 29.8 | EG140: 23.2 | EH140: 27.2 | EI140: 27.2 | EJ140: 28.9 | EK140: 26.3 | EL140: 28.2 | EM140: 25.6 | EO140: 27.4 | EU140: 27.4 | EX140: 25.6 | EY140: 20.9 | EZ140: 17.4 | FA140: 22.8 | FB140: 25.7 | FC140: 26.2 | FD140: 36.1 | FE140: 33.7 | FF140: 41.4 | FG140: 20.9 | FH140: 70.2 | FI140: 30.6 | FJ140: 33.4 | FK140: 26.1 | FL140: 28.3 | FM140: 23.4 | FN140: 29.8 | FS140: 37.1 | FT140: 26.2 | FX140: 29.6 | FZ140: 37.5 | GB140: 22.3 | GC140: 23.4 | GD140: 20.9 | GE140: 14.2 | GF140: 24.2 | GG140: 22.7 | GH140: 38.9 | GI140: 19.6 | GJ140: 5.6 | GK140: 5.6 | GL140: 49.4 | GQ140: 52.4 | GR140: 59.6 | GS140: 46.3 | GT140: 59.1 | GW140: 26 | GX140: 27 | GY140: 23.3 | GZ140: 23.3 | HD140: 27.3 | HF140: 17.3 | HH140: 17 | HJ140: 39.7 | HK140: 35.5 | HL140: 36.5 | HM140: 31.2 | HN140: 53.4 | HO140: 53.4 | HQ140: 66.9 | HR140: 71.9 | HT140: 38.8 | HV140: 36.2 | HW140: 35.3 | IA140: 23.4 | IE140: 25.1 | IG140: 13.9 | IH140: 13.6 | II140: 15.6 | IJ140: 28.6 | IK140: 29.2 | IL140: 46.4 | IM140: 39.7 | IN140: 21.4 | IO140: 29.9 | IP140: 31.7 | IQ140: 19.7
A141: 29646 | B141: 26.8 | C141: 22.9 | D141: 21.5 | E141: 23.1 | F141: 26.1 | G141: 29.9 | H141: 36.7 | I141: 37 | J141: 37.9 | K141: 24.8 | L141: 68.2 | M141: 31.3 | N141: 28.8 | O141: 28.3 | P141: 30.7 | Q141: 23.8 | R141: 28.9 | W141: 33.4 | X141: 24.4 | AB141: 27.9 | AD141: 36.5 | AF141: 24.1 | AG141: 25.7 | AH141: 22.4 | AI141: 14.1 | AJ141: 23.3 | AK141: 18.3 | AL141: 35.8 | AM141: 20.3 | AN141: 5.5 | AO141: 5.5 | AP141: 47.1 | AU141: 59.7 | AV141: 79.9 | AW141: 52.6 | AX141: 50 | BA141: 21.9 | BB141: 24.4 | BC141: 20.3 | BD141: 20.3 | BH141: 30.3 | BJ141: 16.9 | BL141: 15.2 | BN141: 43.3 | BO141: 41.6 | BP141: 45.9 | BQ141: 29.1 | BR141: 49.4 | BS141: 49.4 | BU141: 76 | BV141: 76.1 | BX141: 37.7 | BZ141: 37.7 | CA141: 38.2 | CE141: 26.7 | CI141: 25.8 | CK141: 17.1 | CL141: 17.2 | CM141: 16 | CN141: 26.8 | CO141: 28.1 | CP141: 48.3 | CQ141: 46.2 | CR141: 22 | CS141: 29 | CT141: 19.6 | CU141: 16.2 | CV141: 16.2 | CW141: 55.6 | CX141: 55.6 | CY141: 30.1 | CZ141: 59.2 | DC141: 1119.3 | DN141: 27 | EC141: 27.9 | EF141: 30.5 | EG141: 23.9 | EH141: 27.9 | EI141: 28 | EJ141: 29.5 | EK141: 27 | EL141: 28.9 | EM141: 26.2 | EO141: 28.1 | EU141: 28.1 | EX141: 26 | EY141: 21.6 | EZ141: 18.2 | FA141: 23.4 | FB141: 25.7 | FC141: 27.5 | FD141: 36.3 | FE141: 33.5 | FF141: 41.3 | FG141: 21.2 | FH141: 73.1 | FI141: 31.6 | FJ141: 33.7 | FK141: 27.1 | FL141: 29.8 | FM141: 24 | FN141: 29.9 | FS141: 40 | FT141: 26.2 | FX141: 28.9 | FZ141: 35.7 | GB141: 22.7 | GC141: 23.5 | GD141: 21.7 | GE141: 14.3 | GF141: 24.4 | GG141: 22.8 | GH141: 38.1 | GI141: 19.9 | GJ141: 5.6 | GK141: 5.6 | GL141: 49.9 | GQ141: 53.1 | GR141: 61.5 | GS141: 46.2 | GT141: 59.9 | GW141: 26.9 | GX141: 27.6 | GY141: 23.6 | GZ141: 23.6 | HD141: 27.9 | HF141: 18.8 | HH141: 19.5 | HJ141: 41 | HK141: 35.8 | HL141: 36.7 | HM141: 31.5 | HN141: 53.6 | HO141: 53.6 | HQ141: 67.2 | HR141: 72.2 | HT141: 40.5 | HV141: 36.6 | HW141: 35.1 | IA141: 23.7 | IE141: 25.8 | IG141: 14.1 | IH141: 13.7 | II141: 16.1 | IJ141: 29.8 | IK141: 30.7 | IL141: 47.6 | IM141: 39.7 | IN141: 24.1 | IO141: 30.6 | IP141: 31.7 | IQ141: 19.7
A142: 29738 | B142: 27.2 | C142: 23.5 | D142: 21.7 | E142: 23.9 | F142: 27 | G142: 32 | H142: 36.5 | I142: 36.6 | J142: 38.3 | K142: 24.9 | L142: 69.4 | M142: 31.6 | N142: 27.5 | O142: 29.5 | P142: 32 | Q142: 24.8 | R142: 29.6 | W142: 35.5 | X142: 24.5 | AB142: 28.3 | AD142: 35.9 | AF142: 24.6 | AG142: 26 | AH142: 23.1 | AI142: 14.2 | AJ142: 23.5 | AK142: 18.3 | AL142: 36.5 | AM142: 20.4 | AN142: 5.6 | AO142: 5.6 | AP142: 48.3 | AU142: 61.2 | AV142: 80.6 | AW142: 54.7 | AX142: 51.2 | BA142: 22.4 | BB142: 25.1 | BC142: 20.8 | BD142: 20.8 | BH142: 30.8 | BJ142: 17.2 | BL142: 15.6 | BN142: 44.1 | BO142: 42.3 | BP142: 46.8 | BQ142: 29.7 | BR142: 50.2 | BS142: 50.2 | BU142: 76.7 | BV142: 76.8 | BX142: 38.6 | BZ142: 37.4 | CA142: 39.1 | CE142: 26.8 | CI142: 26.2 | CK142: 17.3 | CL142: 17.3 | CM142: 16.7 | CN142: 27.6 | CO142: 29 | CP142: 49.3 | CQ142: 47.6 | CR142: 23.4 | CS142: 29.7 | CT142: 19.6 | CU142: 16.2 | CV142: 16.2 | CW142: 55 | CX142: 55 | CY142: 30.1 | CZ142: 58.5 | DC142: 1110.7 | DN142: 26.9 | EC142: 28.4 | EF142: 31.2 | EG142: 24.3 | EH142: 28.4 | EI142: 28.5 | EJ142: 30.2 | EK142: 27.5 | EL142: 29.4 | EM142: 26.7 | EO142: 28.6 | EU142: 28.7 | EX142: 26.3 | EY142: 22.1 | EZ142: 18.7 | FA142: 23.9 | FB142: 26.4 | FC142: 27.2 | FD142: 36.4 | FE142: 33.7 | FF142: 41.9 | FG142: 21.2 | FH142: 73.5 | FI142: 31.5 | FJ142: 32.9 | FK142: 27.4 | FL142: 29.8 | FM142: 24.6 | FN142: 30.8 | FS142: 42.2 | FT142: 26.4 | FX142: 29.2 | FZ142: 35.3 | GB142: 22.9 | GC142: 23.6 | GD142: 22 | GE142: 14.5 | GF142: 25 | GG142: 23.3 | GH142: 39.4 | GI142: 20.4 | GJ142: 5.7 | GK142: 5.7 | GL142: 51.4 | GQ142: 54.3 | GR142: 62.2 | GS142: 47.9 | GT142: 60.8 | GW142: 28 | GX142: 28.5 | GY142: 24.1 | GZ142: 24.1 | HD142: 28 | HF142: 18.9 | HH142: 19.5 | HJ142: 41.5 | HK142: 36.1 | HL142: 37 | HM142: 32.5 | HN142: 55.3 | HO142: 55.3 | HQ142: 68.8 | HR142: 74 | HT142: 41.2 | HV142: 36.8 | HW142: 35.1 | IA142: 24.5 | IE142: 26.2 | IG142: 14.1 | IH142: 13.8 | II142: 16.3 | IJ142: 31 | IK142: 32 | IL142: 48.5 | IM142: 40.6 | IN142: 26.3 | IO142: 31.1 | IP142: 31.7 | IQ142: 19.7
A143: 29830 | B143: 27.8 | C143: 23.9 | D143: 21.9 | E143: 24.5 | F143: 28.2 | G143: 32.1 | H143: 36.7 | I143: 35.9 | J143: 40.5 | K143: 25.5 | L143: 72 | M143: 31.7 | N143: 27.1 | O143: 29.9 | P143: 32 | Q143: 25.6 | R143: 30.3 | W143: 35.4 | X143: 23.6 | AB143: 29.1 | AD143: 35.1 | AF143: 25 | AG143: 26.4 | AH143: 23.5 | AI143: 14.7 | AJ143: 24.2 | AK143: 19 | AL143: 36.3 | AM143: 21.2 | AN143: 5.8 | AO143: 5.8 | AP143: 48.8 | AU143: 61.1 | AV143: 80.4 | AW143: 54.6 | AX143: 51.2 | BA143: 23.4 | BB143: 25.7 | BC143: 21.4 | BD143: 21.4 | BH143: 31.1 | BJ143: 17.4 | BL143: 15.8 | BN143: 44.9 | BO143: 42.6 | BP143: 46.9 | BQ143: 30.2 | BR143: 51.6 | BS143: 51.6 | BU143: 78.6 | BV143: 78.7 | BX143: 39.5 | BZ143: 39 | CA143: 39.2 | CE143: 27.1 | CI143: 26.6 | CK143: 17.4 | CL143: 17.3 | CM143: 16.9 | CN143: 27.6 | CO143: 29 | CP143: 50.6 | CQ143: 47 | CR143: 22.1 | CS143: 30.7 | CT143: 19.6 | CU143: 16.2 | CV143: 16.2 | CW143: 56.2 | CX143: 56.2 | CY143: 32.7 | CZ143: 58.5 | DC143: 1106 | DN143: 26.7 | EC143: 28.9 | EF143: 31.7 | EG143: 24.8 | EH143: 28.9 | EI143: 29 | EJ143: 30.6 | EK143: 28 | EL143: 30 | EM143: 27.2 | EO143: 29.2 | EU143: 29.2 | EX143: 27.5 | EY143: 22.8 | EZ143: 19.4 | FA143: 24.4 | FB143: 28.3 | FC143: 27.5 | FD143: 37.3 | FE143: 34.1 | FF143: 42.1 | FG143: 23 | FH143: 75 | FI143: 31.7 | FJ143: 33.6 | FK143: 28.5 | FL143: 31.1 | FM143: 25.1 | FN143: 31.5 | FS143: 42.1 | FT143: 25.9 | FX143: 31.2 | FZ143: 34.7 | GB143: 23.6 | GC143: 24.7 | GD143: 22.3 | GE143: 15 | GF143: 25.8 | GG143: 23.9 | GH143: 40.1 | GI143: 21 | GJ143: 5.9 | GK143: 5.9 | GL143: 51.8 | GQ143: 54.6 | GR143: 62.5 | GS143: 48.4 | GT143: 60.5 | GW143: 29.2 | GX143: 29.2 | GY143: 24.5 | GZ143: 24.5 | HD143: 29.3 | HF143: 19.4 | HH143: 19.5 | HJ143: 42.4 | HK143: 36.3 | HL143: 37.1 | HM143: 32.8 | HN143: 56.1 | HO143: 56.1 | HQ143: 69.7 | HR143: 75 | HT143: 42.3 | HV143: 38.1 | HW143: 36.1 | IA143: 24.8 | IE143: 26.5 | IG143: 14.2 | IH143: 13.8 | II143: 16.7 | IJ143: 30.7 | IK143: 31.4 | IL143: 49.7 | IM143: 39.8 | IN143: 24 | IO143: 31.6 | IP143: 31.7 | IQ143: 20.8
A144: 29921 | B144: 28.4 | C144: 24.7 | D144: 22.5 | E144: 25.2 | F144: 29.4 | G144: 33 | H144: 36.8 | I144: 36.4 | J144: 41.7 | K144: 24.5 | L144: 72.3 | M144: 31.8 | N144: 27.9 | O144: 31.3 | P144: 33.4 | Q144: 27.4 | R144: 31.1 | W144: 35.3 | X144: 23.9 | AB144: 31.3 | AD144: 35.6 | AF144: 25.3 | AG144: 26.9 | AH144: 23.7 | AI144: 14.9 | AJ144: 24.6 | AK144: 19.4 | AL144: 36.7 | AM144: 21.4 | AN144: 6 | AO144: 6 | AP144: 50 | AU144: 62.1 | AV144: 81 | AW144: 55.4 | AX144: 52.4 | BA144: 23.7 | BB144: 26.4 | BC144: 21.9 | BD144: 21.9 | BH144: 31.7 | BJ144: 17.7 | BL144: 16 | BN144: 46.4 | BO144: 44.4 | BP144: 49.1 | BQ144: 30.9 | BR144: 53.1 | BS144: 53.1 | BU144: 79.4 | BV144: 79.4 | BX144: 40.2 | BZ144: 41.4 | CA144: 39.8 | CE144: 28.5 | CI144: 27.1 | CK144: 23.1 | CL144: 24.3 | CM144: 17.3 | CN144: 29 | CO144: 30.3 | CP144: 52.5 | CQ144: 48 | CR144: 24 | CS144: 31.9 | CT144: 19.6 | CU144: 17.7 | CV144: 17.7 | CW144: 59.1 | CX144: 59.1 | CY144: 32.8 | CZ144: 62.4 | DC144: 1144.2 | DN144: 31.4 | EC144: 30.1 | EF144: 32.7 | EG144: 26.5 | EH144: 30.1 | EI144: 30.4 | EJ144: 32 | EK144: 29.2 | EL144: 31.3 | EM144: 28.3 | EO144: 30.3 | EU144: 30.1 | EX144: 27.7 | EY144: 23.4 | EZ144: 19.7 | FA144: 25 | FB144: 29.1 | FC144: 29 | FD144: 37 | FE144: 33.8 | FF144: 44.1 | FG144: 21.2 | FH144: 76.4 | FI144: 32.1 | FJ144: 34.2 | FK144: 29.2 | FL144: 31.8 | FM144: 26.2 | FN144: 31.1 | FS144: 42.1 | FT144: 26.8 | FX144: 32.6 | FZ144: 35.5 | GB144: 24.4 | GC144: 25.7 | GD144: 23 | GE144: 15.3 | GF144: 26.2 | GG144: 24.3 | GH144: 39.6 | GI144: 21.5 | GJ144: 6 | GK144: 6 | GL144: 53 | GQ144: 55.7 | GR144: 63.4 | GS144: 49.4 | GT144: 62.2 | GW144: 29.2 | GX144: 30 | GY144: 25.2 | GZ144: 25.2 | HD144: 29.5 | HF144: 20.1 | HH144: 19.5 | HJ144: 44.1 | HK144: 37.7 | HL144: 38.7 | HM144: 33.6 | HN144: 56.3 | HO144: 56.3 | HQ144: 71.8 | HR144: 77.1 | HT144: 43.1 | HV144: 39.3 | HW144: 37 | IA144: 25.3 | IE144: 27.7 | IG144: 22.1 | IH144: 23.1 | II144: 16.8 | IJ144: 32 | IK144: 32.6 | IL144: 51.8 | IM144: 40.6 | IN144: 24.9 | IO144: 32.3 | IP144: 31.7 | IQ144: 22.9
A145: 30011 | B145: 28.7 | C145: 25.5 | D145: 22.9 | E145: 26.2 | F145: 31.5 | G145: 35.1 | H145: 36.8 | I145: 35.9 | J145: 43 | K145: 24.5 | L145: 74.3 | M145: 32.3 | N145: 28.3 | O145: 32.9 | P145: 35.3 | Q145: 28.2 | R145: 31.7 | W145: 35.3 | X145: 24.8 | AB145: 32.7 | AD145: 36.1 | AF145: 26.3 | AG145: 27.5 | AH145: 25 | AI145: 15.4 | AJ145: 25.6 | AK145: 20.2 | AL145: 38.1 | AM145: 22.3 | AN145: 6 | AO145: 6 | AP145: 50.1 | AU145: 61.3 | AV145: 82.9 | AW145: 53.8 | AX145: 51.6 | BA145: 24.1 | BB145: 27.1 | BC145: 22.4 | BD145: 22.4 | BH145: 33.5 | BJ145: 19.2 | BL145: 17.7 | BN145: 47.5 | BO145: 44.1 | BP145: 48.3 | BQ145: 31.8 | BR145: 53.3 | BS145: 53.3 | BU145: 81.1 | BV145: 81.2 | BX145: 41.7 | BZ145: 42.7 | CA145: 41.2 | CD145: 30.9 | CE145: 28.8 | CI145: 28.1 | CK145: 24 | CL145: 25.4 | CM145: 17.5 | CN145: 29.5 | CO145: 30.9 | CP145: 53.4 | CQ145: 46.5 | CR145: 23.7 | CS145: 32.6 | CT145: 21.2 | CU145: 17.9 | CV145: 17.9 | CW145: 60.7 | CX145: 60.7 | CY145: 32.8 | CZ145: 64.9 | DC145: 1139.4 | DH145: 35.4 | DI145: 31.6 | DJ145: 38.7 | DN145: 31.8 | DR145: 13.1 | DS145: 13.1 | EC145: 30.7 | EF145: 33.2 | EG145: 27.3 | EH145: 30.7 | EI145: 31 | EJ145: 32.6 | EK145: 29.8 | EL145: 31.8 | EM145: 28.9 | EO145: 31 | EU145: 30.7 | EX145: 27.9 | EY145: 24.7 | EZ145: 21.3 | FA145: 26 | FB145: 30.1 | FC145: 31.1 | FD145: 36.8 | FE145: 33.3 | FF145: 44.1 | FG145: 20.9 | FH145: 77.4 | FI145: 33.1 | FJ145: 34.2 | FK145: 30.9 | FL145: 33.7 | FM145: 26.9 | FN145: 32.1 | FS145: 43 | FT145: 26.8 | FX145: 33.8 | FZ145: 35.3 | GB145: 25.1 | GC145: 26.5 | GD145: 23.6 | GE145: 15.6 | GF145: 27 | GG145: 25.3 | GH145: 41.6 | GI145: 22 | GJ145: 6.1 | GK145: 6.1 | GL145: 53.3 | GQ145: 56.3 | GR145: 62.8 | GS145: 50.3 | GT145: 63.9 | GW145: 30.7 | GX145: 30.7 | GY145: 25.8 | GZ145: 25.8 | HD145: 29.8 | HF145: 22.1 | HH145: 22.9 | HJ145: 45.6 | HK145: 38.7 | HL145: 39.7 | HM145: 34 | HN145: 56.8 | HO145: 56.8 | HQ145: 72.4 | HR145: 77.8 | HT145: 43.9 | HV145: 39.7 | HW145: 38.4 | HZ145: 19.7 | IA145: 25.6 | IE145: 28.8 | IG145: 22.3 | IH145: 23.2 | II145: 17.5 | IJ145: 31.9 | IK145: 32.4 | IL145: 53.1 | IM145: 40.8 | IN145: 23.1 | IO145: 32.8 | IP145: 36.1 | IQ145: 23.1
A146: 30103 | B146: 29.1 | C146: 26.5 | D146: 23.3 | E146: 27.8 | F146: 33.2 | G146: 36.3 | H146: 37.5 | I146: 36.7 | J146: 44.9 | K146: 25.6 | L146: 73.4 | M146: 33.1 | N146: 27.4 | O146: 33.5 | P146: 35.3 | Q146: 30 | R146: 32.7 | W146: 34.9 | X146: 25.5 | AB146: 32.7 | AD146: 36.3 | AF146: 26.8 | AG146: 27.8 | AH146: 25.6 | AI146: 15.9 | AJ146: 26.4 | AK146: 20.7 | AL146: 39.9 | AM146: 22.9 | AN146: 6.2 | AO146: 6.2 | AP146: 51.5 | AU146: 64.4 | AV146: 85 | AW146: 58.4 | AX146: 52 | BA146: 25.4 | BB146: 28 | BC146: 23 | BD146: 23 | BH146: 34.9 | BJ146: 21 | BL146: 19.6 | BN146: 49.7 | BO146: 47 | BP146: 52.5 | BQ146: 31.4 | BR146: 54.4 | BS146: 54.4 | BU146: 81 | BV146: 81.1 | BX146: 41.8 | BZ146: 44.2 | CA146: 41.5 | CD146: 32 | CE146: 29.4 | CI146: 28.8 | CK146: 25.4 | CL146: 26.8 | CM146: 18.8 | CN146: 30.5 | CO146: 32.1 | CP146: 53.9 | CQ146: 47.7 | CR146: 24.3 | CS146: 35 | CT146: 24 | CU146: 17.9 | CV146: 17.9 | CW146: 61.7 | CX146: 61.7 | CY146: 35.6 | CZ146: 64.9 | DC146: 1102.1 | DH146: 34.8 | DI146: 32.4 | DJ146: 37.2 | DN146: 32.9 | DR146: 13.1 | DS146: 13.1 | EC146: 31.6 | EF146: 34 | EG146: 28.3 | EH146: 31.6 | EI146: 32.1 | EJ146: 33.5 | EK146: 30.7 | EL146: 32.7 | EM146: 29.6 | EO146: 31.8 | EU146: 31.5 | EX146: 28.5 | EY146: 25.5 | EZ146: 21.7 | FA146: 27.2 | FB146: 31.3 | FC146: 31.6 | FD146: 37.5 | FE146: 33.9 | FF146: 44.4 | FG146: 22.3 | FH146: 77.6 | FI146: 33.7 | FJ146: 33.8 | FK146: 32 | FL146: 34.6 | FM146: 28.4 | FN146: 33.9 | FS146: 45.1 | FT146: 26.4 | FX146: 33.6 | FZ146: 36 | GB146: 25.9 | GC146: 27.4 | GD146: 24.2 | GE146: 15.9 | GF146: 27.2 | GG146: 25.3 | GH146: 42.6 | GI146: 22.2 | GJ146: 6.2 | GK146: 6.2 | GL146: 54.4 | GQ146: 57.4 | GR146: 64.7 | GS146: 52.2 | GT146: 61.9 | GW146: 31.8 | GX146: 31.8 | GY146: 26.6 | GZ146: 26.6 | HD146: 31.3 | HF146: 22.1 | HH146: 22.9 | HJ146: 46.5 | HK146: 39.5 | HL146: 40.7 | HM146: 34.7 | HN146: 58.6 | HO146: 58.6 | HQ146: 72.8 | HR146: 78.2 | HT146: 44.6 | HV146: 41.4 | HW146: 38.8 | HZ146: 19.8 | IA146: 26.1 | IE146: 29.8 | IG146: 22.4 | IH146: 23.3 | II146: 17.8 | IJ146: 33.2 | IK146: 33.9 | IL146: 53.6 | IM146: 41.7 | IN146: 25.2 | IO146: 34.3 | IP146: 36.8 | IQ146: 23.1
A147: 30195 | B147: 29.9 | C147: 26.9 | D147: 23.5 | E147: 28.5 | F147: 33.9 | G147: 36.6 | H147: 37.7 | I147: 36.5 | J147: 46.6 | K147: 24 | L147: 79.8 | M147: 32.7 | N147: 28.3 | O147: 34.6 | P147: 35.9 | Q147: 31.7 | R147: 34.3 | W147: 36 | X147: 26.8 | AB147: 33.9 | AD147: 38.7 | AF147: 27.4 | AG147: 28.5 | AH147: 26.3 | AI147: 16.6 | AJ147: 27.5 | AK147: 21.4 | AL147: 41 | AM147: 24.1 | AN147: 6.5 | AO147: 6.5 | AP147: 52.2 | AU147: 66.2 | AV147: 86 | AW147: 59.9 | AX147: 55.3 | BA147: 26.2 | BB147: 28.7 | BC147: 24 | BD147: 24 | BH147: 36.2 | BJ147: 23.5 | BL147: 22.1 | BN147: 51.6 | BO147: 48.7 | BP147: 54.4 | BQ147: 33 | BR147: 54.6 | BS147: 54.6 | BU147: 82.8 | BV147: 82.9 | BX147: 43.2 | BZ147: 45.6 | CA147: 42.7 | CD147: 32.6 | CE147: 31.9 | CI147: 30 | CK147: 26.1 | CL147: 27.7 | CM147: 18.9 | CN147: 32.6 | CO147: 34.2 | CP147: 55.6 | CQ147: 48.6 | CR147: 28.1 | CS147: 35.6 | CT147: 25.7 | CU147: 19.5 | CV147: 19.5 | CW147: 63.4 | CX147: 63.4 | CY147: 36.3 | CZ147: 66.8 | DC147: 1107.9 | DH147: 35.1 | DI147: 34.1 | DJ147: 36.9 | DN147: 32.7 | DR147: 13.2 | DS147: 13.2 | EC147: 32.7 | EF147: 35.3 | EG147: 29.2 | EH147: 32.7 | EI147: 33.2 | EJ147: 34.6 | EK147: 31.9 | EL147: 33.9 | EM147: 30.6 | EO147: 32.7 | EU147: 32.6 | EX147: 29.5 | EY147: 26 | EZ147: 22.1 | FA147: 27.8 | FB147: 32.2 | FC147: 32.2 | FD147: 37.9 | FE147: 34.2 | FF147: 47.4 | FG147: 21.4 | FH147: 77.6 | FI147: 34.1 | FJ147: 34.6 | FK147: 32.7 | FL147: 34.6 | FM147: 30.4 | FN147: 35.4 | FS147: 45.1 | FT147: 28.7 | FX147: 35.6 | FZ147: 36.7 | GB147: 26.4 | GC147: 27.8 | GD147: 24.9 | GE147: 16.5 | GF147: 28 | GG147: 25.5 | GH147: 42.9 | GI147: 23 | GJ147: 6.6 | GK147: 6.6 | GL147: 55.1 | GQ147: 58 | GR147: 64.4 | GS147: 52.6 | GT147: 64.7 | GW147: 33 | GX147: 32.5 | GY147: 27.5 | GZ147: 27.5 | HD147: 32.5 | HF147: 22.6 | HH147: 23.4 | HJ147: 47.4 | HK147: 40.7 | HL147: 41.9 | HM147: 35.7 | HN147: 59.2 | HO147: 59.2 | HQ147: 74.4 | HR147: 80 | HT147: 45.4 | HV147: 42.9 | HW147: 40.1 | HZ147: 20.4 | IA147: 28.2 | IE147: 30.9 | IG147: 25.2 | IH147: 26.4 | II147: 18.8 | IJ147: 35 | IK147: 35.9 | IL147: 54.8 | IM147: 42.4 | IN147: 28.7 | IO147: 35.4 | IP147: 38 | IQ147: 23.3
A148: 30286 | B148: 30.4 | C148: 27.4 | D148: 23.5 | E148: 29.8 | F148: 33.5 | G148: 36.9 | H148: 38.3 | I148: 37.2 | J148: 46.8 | K148: 24.8 | L148: 73.6 | M148: 33.2 | N148: 30.3 | O148: 35.6 | P148: 37.1 | Q148: 32.7 | R148: 34.8 | W148: 38 | X148: 26.4 | AB148: 34.5 | AD148: 38.5 | AF148: 28.1 | AG148: 29.5 | AH148: 26.7 | AI148: 17.5 | AJ148: 28.9 | AK148: 22 | AL148: 42 | AM148: 25.5 | AN148: 7 | AO148: 7 | AP148: 53.3 | AU148: 67.5 | AV148: 86.8 | AW148: 61.3 | AX148: 56.3 | BA148: 26.8 | BB148: 29.3 | BC148: 24.3 | BD148: 24.3 | BH148: 36.4 | BJ148: 25.5 | BL148: 24.3 | BN148: 53.7 | BO148: 49.8 | BP148: 55.8 | BQ148: 33.3 | BR148: 55.7 | BS148: 55.7 | BU148: 82.2 | BV148: 82.3 | BX148: 45.8 | BZ148: 47 | CA148: 45.5 | CD148: 33 | CE148: 32.1 | CI148: 30.5 | CK148: 28.9 | CL148: 31.1 | CM148: 19.1 | CN148: 33.3 | CO148: 34.8 | CP148: 55.7 | CQ148: 48.3 | CR148: 28.6 | CS148: 36.2 | CT148: 25.9 | CU148: 21 | CV148: 21 | CW148: 65.9 | CX148: 65.9 | CY148: 36.9 | CZ148: 69.9 | DC148: 1092.6 | DH148: 36.7 | DI148: 37.3 | DJ148: 37.6 | DN148: 34.1 | DR148: 13.2 | DS148: 13.2 | EC148: 33.7 | EF148: 36.1 | EG148: 30.5 | EH148: 33.7 | EI148: 34.4 | EJ148: 35.7 | EK148: 32.8 | EL148: 35 | EM148: 31.5 | EO148: 33.8 | EU148: 33.5 | EX148: 30.2 | EY148: 26.7 | EZ148: 22.5 | FA148: 28.9 | FB148: 32.1 | FC148: 32.6 | FD148: 38.8 | FE148: 35 | FF148: 48.2 | FG148: 21.4 | FH148: 81.4 | FI148: 34.4 | FJ148: 36.3 | FK148: 33.1 | FL148: 34.6 | FM148: 32 | FN148: 36.2 | FS148: 46.6 | FT148: 29.7 | FX148: 37.3 | FZ148: 37.6 | GB148: 27 | GC148: 28.1 | GD148: 25.7 | GE148: 17.3 | GF148: 29.2 | GG148: 26.3 | GH148: 42.8 | GI148: 24.5 | GJ148: 7 | GK148: 7 | GL148: 56.3 | GQ148: 59.6 | GR148: 66.8 | GS148: 54.1 | GT148: 65.4 | GW148: 33.4 | GX148: 33.5 | GY148: 28.6 | GZ148: 28.6 | HD148: 33.1 | HF148: 24.4 | HH148: 25.1 | HJ148: 49.5 | HK148: 42.9 | HL148: 44.6 | HM148: 36.5 | HN148: 59.8 | HO148: 59.8 | HQ148: 75.2 | HR148: 80.9 | HT148: 46.5 | HV148: 43.7 | HW148: 42 | HZ148: 21 | IA148: 28.4 | IE148: 31.5 | IG148: 25.7 | IH148: 27 | II148: 19 | IJ148: 34.8 | IK148: 35.7 | IL148: 55.3 | IM148: 41.6 | IN148: 27.6 | IO148: 36.1 | IP148: 38 | IQ148: 23.4
A149: 30376 | B149: 31.1 | C149: 28.4 | D149: 24.7 | E149: 29.8 | F149: 36.2 | G149: 39.6 | H149: 39 | I149: 37.9 | J149: 47.2 | K149: 25.1 | L149: 78.9 | M149: 34.2 | N149: 30.8 | O149: 36.1 | P149: 37.1 | Q149: 33.6 | R149: 36.6 | W149: 39.2 | X149: 27.2 | AB149: 36 | AD149: 40.1 | AF149: 28.8 | AG149: 30.2 | AH149: 27.3 | AI149: 17.8 | AJ149: 29.3 | AK149: 22.4 | AL149: 42.5 | AM149: 26 | AN149: 7.1 | AO149: 7.1 | AP149: 53.3 | AU149: 65.8 | AV149: 86.8 | AW149: 61.2 | AX149: 50.1 | BA149: 27 | BB149: 29.5 | BC149: 24.6 | BD149: 24.6 | BH149: 37.6 | BJ149: 25.4 | BL149: 24.1 | BN149: 54.3 | BO149: 50.8 | BP149: 57 | BQ149: 33.7 | BR149: 57.8 | BS149: 57.8 | BU149: 82.6 | BV149: 82.7 | BX149: 46.6 | BZ149: 47.9 | CA149: 47.4 | CD149: 33.8 | CE149: 32.8 | CI149: 33.3 | CK149: 29.7 | CL149: 31.8 | CM149: 20.2 | CN149: 34.3 | CO149: 35.9 | CP149: 57.5 | CQ149: 46.8 | CR149: 29.2 | CS149: 37.6 | CT149: 26.1 | CU149: 21.1 | CV149: 21.1 | CW149: 66 | CX149: 66 | CY149: 36.9 | CZ149: 69.9 | DC149: 1061 | DH149: 39 | DI149: 36.3 | DJ149: 41.9 | DN149: 35.1 | DR149: 15.3 | DS149: 15.3 | EC149: 34.4 | EF149: 36.8 | EG149: 31.5 | EH149: 34.4 | EI149: 35.1 | EJ149: 36.4 | EK149: 33.7 | EL149: 35.8 | EM149: 32.3 | EO149: 34.5 | EU149: 34.2 | EX149: 30.6 | EY149: 27.6 | EZ149: 23.2 | FA149: 29.6 | FB149: 34.2 | FC149: 34.4 | FD149: 39.5 | FE149: 35.3 | FF149: 50.5 | FG149: 22.1 | FH149: 82.3 | FI149: 35.7 | FJ149: 36 | FK149: 33.6 | FL149: 34.6 | FM149: 33.1 | FN149: 37 | FS149: 46.5 | FT149: 30.3 | FX149: 37.7 | FZ149: 39.7 | GB149: 27.9 | GC149: 29.3 | GD149: 26.3 | GE149: 17.5 | GF149: 29.5 | GG149: 26.9 | GH149: 42.9 | GI149: 24.7 | GJ149: 7.2 | GK149: 7.2 | GL149: 56.1 | GQ149: 58.7 | GR149: 67.1 | GS149: 54.3 | GT149: 59.3 | GW149: 33.9 | GX149: 34.2 | GY149: 29.4 | GZ149: 29.4 | HD149: 33.9 | HF149: 24.7 | HH149: 25.2 | HJ149: 50.3 | HK149: 43.2 | HL149: 44.9 | HM149: 36.5 | HN149: 60.7 | HO149: 60.7 | HQ149: 75.3 | HR149: 81 | HT149: 48.1 | HV149: 46.2 | HW149: 44.2 | HZ149: 24.2 | IA149: 28.5 | IE149: 34.6 | IG149: 26.6 | IH149: 28 | II149: 19.3 | IJ149: 36 | IK149: 37 | IL149: 57.1 | IM149: 42.9 | IN149: 29.1 | IO149: 37.2 | IP149: 38 | IQ149: 23.4
A150: 30468 | B150: 32.3 | C150: 28.8 | D150: 24.7 | E150: 30.9 | F150: 35.8 | G150: 39.2 | H150: 41.7 | I150: 41.8 | J150: 46.9 | K150: 29.4 | L150: 76.5 | M150: 34.6 | N150: 31.8 | O150: 36.4 | P150: 37.1 | Q150: 34.9 | R150: 36.3 | W150: 39 | X150: 27.4 | AB150: 36.8 | AD150: 41.5 | AF150: 28.9 | AG150: 30.4 | AH150: 27.3 | AI150: 18.3 | AJ150: 29.9 | AK150: 22.7 | AL150: 43.3 | AM150: 26.5 | AN150: 7.4 | AO150: 7.4 | AP150: 55.4 | AU150: 70.9 | AV150: 88.5 | AW150: 65.1 | AX150: 60.2 | BA150: 28.1 | BB150: 29.9 | BC150: 25 | BD150: 25 | BH150: 38.1 | BJ150: 25.4 | BL150: 24.1 | BN150: 55 | BO150: 51.7 | BP150: 57.8 | BQ150: 34.7 | BR150: 62.6 | BS150: 62.6 | BU150: 82.8 | BV150: 82.9 | BX150: 48.7 | BZ150: 49 | CA150: 48.1 | CD150: 34.3 | CE150: 32.4 | CI150: 34 | CK150: 29.9 | CL150: 32 | CM150: 20.3 | CN150: 34 | CO150: 35.6 | CP150: 59.4 | CQ150: 50 | CR150: 26.9 | CS150: 38 | CT150: 26.1 | CU150: 21.1 | CV150: 21.1 | CW150: 66 | CX150: 66 | CY150: 36.9 | CZ150: 69.9 | DC150: 1091.6 | DH150: 41.2 | DI150: 36.8 | DJ150: 45.1 | DN150: 34.3 | DR150: 15.3 | DS150: 15.3 | EC150: 35.1 | EF150: 37.5 | EG150: 31.9 | EH150: 35.1 | EI150: 35.6 | EJ150: 37.1 | EK150: 34.2 | EL150: 36.6 | EM150: 32.9 | EO150: 35.3 | EU150: 34.9 | EX150: 32.4 | EY150: 28.3 | EZ150: 23.8 | FA150: 30.5 | FB150: 35.1 | FC150: 35 | FD150: 44.1 | FE150: 42.5 | FF150: 51.3 | FG150: 27.6 | FH150: 83.6 | FI150: 34.5 | FJ150: 37.2 | FK150: 33.9 | FL150: 34.6 | FM150: 34.3 | FN150: 37.8 | FS150: 49.6 | FT150: 30.5 | FX150: 37.3 | FZ150: 41 | GB150: 28.4 | GC150: 29.9 | GD150: 26.8 | GE150: 17.9 | GF150: 29.9 | GG150: 26.8 | GH150: 43.9 | GI150: 25 | GJ150: 7.4 | GK150: 7.4 | GL150: 58.2 | GQ150: 63.4 | GR150: 68.3 | GS150: 58.7 | GT150: 71 | GW150: 34.1 | GX150: 35.1 | GY150: 30.2 | GZ150: 30.2 | HD150: 34.6 | HF150: 24.7 | HH150: 25.2 | HJ150: 50.9 | HK150: 43.8 | HL150: 45.4 | HM150: 37.6 | HN150: 65.6 | HO150: 65.6 | HQ150: 76.6 | HR150: 82.4 | HT150: 48.4 | HV150: 46 | HW150: 45.8 | HZ150: 24.7 | IA150: 28.9 | IE150: 35.2 | IG150: 28.2 | IH150: 29.9 | II150: 19.4 | IJ150: 36 | IK150: 37 | IL150: 59.1 | IM150: 44.8 | IN150: 27.6 | IO150: 37.4 | IP150: 37.8 | IQ150: 23.4
A151: 30560 | B151: 32.7 | C151: 29.4 | D151: 25.3 | E151: 31.6 | F151: 37.5 | G151: 39.1 | H151: 41 | I151: 42.4 | J151: 45.4 | K151: 24.3 | L151: 83.2 | M151: 34.5 | N151: 32.1 | O151: 36.6 | P151: 37.1 | Q151: 35.7 | R151: 36.2 | W151: 39 | X151: 29.6 | AB151: 36.9 | AD151: 43.3 | AF151: 29.9 | AG151: 31 | AH151: 28.6 | AI151: 18.5 | AJ151: 30 | AK151: 22.7 | AL151: 43.2 | AM151: 26.7 | AN151: 7.6 | AO151: 7.6 | AP151: 55.2 | AU151: 71.6 | AV151: 89 | AW151: 65.8 | AX151: 60.5 | BA151: 28.1 | BB151: 30.2 | BC151: 25.3 | BD151: 25.3 | BH151: 38.1 | BJ151: 25.5 | BL151: 24.1 | BN151: 55.7 | BO151: 52.9 | BP151: 59.2 | BQ151: 35.2 | BR151: 63.2 | BS151: 63.2 | BU151: 82.8 | BV151: 82.9 | BX151: 51.9 | BZ151: 49.4 | CA151: 49 | CD151: 36.9 | CE151: 34.2 | CI151: 34.4 | CK151: 30.2 | CL151: 32.4 | CM151: 20.5 | CN151: 35.1 | CO151: 36.8 | CP151: 60.2 | CQ151: 51.9 | CR151: 29 | CS151: 38.6 | CT151: 28.1 | CU151: 21.4 | CV151: 21.4 | CW151: 66 | CX151: 66 | CY151: 36.9 | CZ151: 69.9 | DC151: 1105 | DH151: 41 | DI151: 37.3 | DJ151: 44.5 | DN151: 34.2 | DR151: 15.3 | DS151: 15.3 | EC151: 35.5 | EF151: 38 | EG151: 32.4 | EH151: 35.5 | EI151: 36.1 | EJ151: 37.6 | EK151: 34.7 | EL151: 37.1 | EM151: 33.4 | EO151: 35.7 | EU151: 35.4 | EX151: 32.6 | EY151: 28.5 | EZ151: 23.9 | FA151: 30.9 | FB151: 36.3 | FC151: 34.3 | FD151: 42.5 | FE151: 41.5 | FF151: 50.3 | FG151: 22.3 | FH151: 87.7 | FI151: 36.2 | FJ151: 36.4 | FK151: 34 | FL151: 34.6 | FM151: 34.5 | FN151: 37.5 | FS151: 50.1 | FT151: 30.4 | FX151: 37.3 | FZ151: 41.4 | GB151: 28.9 | GC151: 30.3 | GD151: 27.3 | GE151: 18.3 | GF151: 30.3 | GG151: 27.1 | GH151: 44.9 | GI151: 25.2 | GJ151: 7.7 | GK151: 7.7 | GL151: 58.3 | GQ151: 63.3 | GR151: 67.4 | GS151: 59.1 | GT151: 71.1 | GW151: 34.3 | GX151: 35.7 | GY151: 30.9 | GZ151: 30.9 | HD151: 34.9 | HF151: 25.2 | HH151: 25.7 | HJ151: 51.6 | HK151: 44.3 | HL151: 46.1 | HM151: 37.9 | HN151: 65.8 | HO151: 65.8 | HQ151: 77.9 | HR151: 83.7 | HT151: 49.7 | HV151: 48.3 | HW151: 46.8 | HZ151: 24.9 | IA151: 29.3 | IE151: 36.2 | IG151: 28.8 | IH151: 30.5 | II151: 20 | IJ151: 37.5 | IK151: 38.7 | IL151: 59.8 | IM151: 45.7 | IN151: 30.8 | IO151: 38.3 | IP151: 37.5 | IQ151: 23.4
A152: 30651 | B152: 33.2 | C152: 29.8 | D152: 26.1 | E152: 31.6 | F152: 37.8 | G152: 39.9 | H152: 40.2 | I152: 42 | J152: 45.8 | K152: 23.2 | L152: 76.3 | M152: 34.9 | N152: 31.9 | O152: 36.8 | P152: 37.7 | Q152: 35.1 | R152: 36.9 | W152: 37.1 | X152: 29.2 | AB152: 37.8 | AD152: 44.7 | AF152: 30.5 | AG152: 31.6 | AH152: 29.3 | AI152: 19.5 | AJ152: 31.2 | AK152: 23.8 | AL152: 44.3 | AM152: 27.7 | AN152: 8.3 | AO152: 8.3 | AP152: 56.7 | AU152: 72 | AV152: 89 | AW152: 66.7 | AX152: 60.6 | BA152: 28.9 | BB152: 30.7 | BC152: 25.4 | BD152: 25.4 | BH152: 39 | BJ152: 27.1 | BL152: 25.8 | BN152: 57.5 | BO152: 53.8 | BP152: 60.3 | BQ152: 35.8 | BR152: 64.6 | BS152: 64.6 | BU152: 83.6 | BV152: 83.6 | BX152: 53 | BZ152: 49.4 | CA152: 49.3 | CD152: 37.6 | CE152: 35.3 | CI152: 34.8 | CK152: 30.4 | CL152: 32.5 | CM152: 21.2 | CN152: 36 | CO152: 37.5 | CP152: 60.8 | CQ152: 51.9 | CR152: 30 | CS152: 39 | CT152: 28.1 | CU152: 23.1 | CV152: 23.1 | CW152: 72.3 | CX152: 72.3 | CY152: 40.9 | CZ152: 76.4 | DC152: 1071.5 | DH152: 40.5 | DI152: 39.8 | DJ152: 42.1 | DN152: 34.4 | DR152: 15.3 | DS152: 15.3 | EC152: 36.2 | EF152: 38.8 | EG152: 32.9 | EH152: 36.3 | EI152: 36.9 | EJ152: 38.3 | EK152: 35.4 | EL152: 37.9 | EM152: 34.1 | EO152: 36.4 | EU152: 36.1 | EX152: 33.1 | EY152: 29.7 | EZ152: 25.1 | FA152: 31.7 | FB152: 37.9 | FC152: 35.7 | FD152: 41.7 | FE152: 40.6 | FF152: 50.1 | FG152: 20.8 | FH152: 85.1 | FI152: 36.3 | FJ152: 38.1 | FK152: 35.7 | FL152: 37.3 | FM152: 34.6 | FN152: 38.3 | FS152: 49.4 | FT152: 32.4 | FX152: 38.4 | FZ152: 43.4 | GB152: 29.4 | GC152: 30.7 | GD152: 27.8 | GE152: 20.1 | GF152: 32 | GG152: 28 | GH152: 50 | GI152: 26.4 | GJ152: 9 | GK152: 9 | GL152: 59.5 | GQ152: 62.4 | GR152: 68.4 | GS152: 56.5 | GT152: 71.3 | GW152: 34.8 | GX152: 36.7 | GY152: 31.7 | GZ152: 31.7 | HD152: 35.6 | HF152: 26.7 | HH152: 27.1 | HJ152: 53.4 | HK152: 45.3 | HL152: 46.8 | HM152: 39.6 | HN152: 66.2 | HO152: 66.2 | HQ152: 78.6 | HR152: 84.5 | HT152: 52.7 | HV152: 48.8 | HW152: 46.4 | HZ152: 25.5 | IA152: 31.2 | IE152: 36.4 | IG152: 30.5 | IH152: 32.4 | II152: 20.6 | IJ152: 38.5 | IK152: 39.3 | IL152: 59.7 | IM152: 46.9 | IN152: 32.1 | IO152: 38.1 | IP152: 37.7 | IQ152: 26.9
A153: 30742 | B153: 33.8 | C153: 30.7 | D153: 27.3 | E153: 31.9 | F153: 39.3 | G153: 41.7 | H153: 41.1 | I153: 42.6 | J153: 45 | K153: 26 | L153: 77.4 | M153: 34.8 | N153: 32.1 | O153: 37.5 | P153: 38.9 | Q153: 34.9 | R153: 37.1 | W153: 37.5 | X153: 29.5 | AB153: 36.9 | AD153: 45.4 | AF153: 31.2 | AG153: 32.5 | AH153: 29.9 | AI153: 19.8 | AJ153: 31.9 | AK153: 24.3 | AL153: 44.5 | AM153: 28.5 | AN153: 8.4 | AO153: 8.4 | AP153: 56.9 | AU153: 73 | AV153: 89.7 | AW153: 66.6 | AX153: 63.8 | BA153: 29.4 | BB153: 30.8 | BC153: 25.7 | BD153: 25.7 | BH153: 40.1 | BJ153: 25.9 | BL153: 24.4 | BN153: 57.4 | BO153: 54.8 | BP153: 61.5 | BQ153: 36.3 | BR153: 65 | BS153: 65 | BU153: 84.4 | BV153: 84.5 | BX153: 52.4 | BZ153: 50.4 | CA153: 49.7 | CD153: 39.2 | CE153: 35.6 | CI153: 35.4 | CK153: 22.4 | CL153: 22.3 | CM153: 22.2 | CN153: 36.3 | CO153: 37.8 | CP153: 61.2 | CQ153: 52.5 | CR153: 30.1 | CS153: 39.4 | CT153: 28.1 | CU153: 23.4 | CV153: 23.4 | CW153: 72.4 | CX153: 72.4 | CY153: 41 | CZ153: 76.6 | DC153: 1052.4 | DH153: 41.4 | DI153: 39.4 | DJ153: 43.9 | DN153: 34.1 | DR153: 16.9 | DS153: 16.9 | EC153: 36.1 | EF153: 39.2 | EG153: 31.7 | EH153: 36.1 | EI153: 36.5 | EJ153: 38 | EK153: 35.2 | EL153: 37.6 | EM153: 33.8 | EO153: 36.1 | EU153: 36.6 | EX153: 33.5 | EY153: 30.6 | EZ153: 26.1 | FA153: 32.2 | FB153: 38.8 | FC153: 36.9 | FD153: 42.7 | FE153: 41.3 | FF153: 49.5 | FG153: 23.4 | FH153: 85.3 | FI153: 36 | FJ153: 38.6 | FK153: 35.6 | FL153: 37.3 | FM153: 33.9 | FN153: 39.1 | FS153: 47.9 | FT153: 31.7 | FX153: 37.9 | FZ153: 45.2 | GB153: 29.8 | GC153: 31.2 | GD153: 28.1 | GE153: 20.3 | GF153: 32.6 | GG153: 28.2 | GH153: 50.4 | GI153: 27.1 | GJ153: 9 | GK153: 9 | GL153: 59.5 | GQ153: 62.6 | GR153: 67.1 | GS153: 56.3 | GT153: 75.1 | GW153: 34.7 | GX153: 37.7 | GY153: 32.4 | GZ153: 32.4 | HD153: 36.8 | HF153: 26.8 | HH153: 27.3 | HJ153: 53.7 | HK153: 45.3 | HL153: 46.5 | HM153: 39.7 | HN153: 67.1 | HO153: 67.1 | HQ153: 78.6 | HR153: 84.5 | HT153: 53.6 | HV153: 49.3 | HW153: 47.2 | HZ153: 26.8 | IA153: 31.5 | IE153: 37.4 | IG153: 20.4 | IH153: 20.3 | II153: 21.1 | IJ153: 38.8 | IK153: 39.5 | IL153: 60.3 | IM153: 47.8 | IN153: 31.6 | IO153: 39.3 | IP153: 38.5 | IQ153: 27.2
A154: 30834 | B154: 33.6 | C154: 31.8 | D154: 28 | E154: 33.2 | F154: 41.5 | G154: 41.6 | H154: 41.1 | I154: 42.8 | J154: 46.6 | K154: 25.8 | L154: 73.1 | M154: 35 | N154: 32.4 | O154: 37.2 | P154: 38.7 | Q154: 34.7 | R154: 35.8 | W154: 37.5 | X154: 30.4 | AB154: 37.3 | AD154: 45.7 | AF154: 31.8 | AG154: 33.1 | AH154: 30.4 | AI154: 20.3 | AJ154: 32.6 | AK154: 24.8 | AL154: 45 | AM154: 29.2 | AN154: 8.6 | AO154: 8.6 | AP154: 58.5 | AU154: 73.9 | AV154: 91.8 | AW154: 66.9 | AX154: 64.8 | BA154: 30.2 | BB154: 31.4 | BC154: 26.2 | BD154: 26.2 | BH154: 40.8 | BJ154: 24.6 | BL154: 23 | BN154: 57.5 | BO154: 54.8 | BP154: 61.2 | BQ154: 37 | BR154: 67 | BS154: 67 | BU154: 84.8 | BV154: 84.9 | BX154: 53.4 | BZ154: 53.1 | CA154: 50.3 | CD154: 39.8 | CE154: 35.3 | CI154: 36.2 | CK154: 18.1 | CL154: 16.8 | CM154: 22.5 | CN154: 37.1 | CO154: 38.7 | CP154: 61.9 | CQ154: 53.6 | CR154: 32.2 | CS154: 40 | CT154: 28.1 | CU154: 23.4 | CV154: 23.4 | CW154: 72.5 | CX154: 72.5 | CY154: 41 | CZ154: 76.6 | DC154: 1019 | DH154: 41 | DI154: 39.1 | DJ154: 43.5 | DN154: 35.9 | DR154: 16.9 | DS154: 16.9 | EC154: 36.1 | EF154: 39.6 | EG154: 31.1 | EH154: 36.1 | EI154: 36.6 | EJ154: 37.9 | EK154: 35.1 | EL154: 37.5 | EM154: 33.8 | EO154: 35.9 | EU154: 36.9 | EX154: 33.4 | EY154: 31.2 | EZ154: 26.9 | FA154: 32.7 | FB154: 39.4 | FC154: 36.7 | FD154: 42.6 | FE154: 41.6 | FF154: 49.7 | FG154: 24 | FH154: 81.9 | FI154: 35.3 | FJ154: 38.3 | FK154: 35.7 | FL154: 37.4 | FM154: 34.1 | FN154: 39.2 | FS154: 47 | FT154: 32.5 | FX154: 38.2 | FZ154: 48.2 | GB154: 30.8 | GC154: 32.2 | GD154: 29.1 | GE154: 20.8 | GF154: 33.5 | GG154: 29 | GH154: 50.7 | GI154: 27.9 | GJ154: 9.2 | GK154: 9.2 | GL154: 61.3 | GQ154: 65.7 | GR154: 70 | GS154: 60.3 | GT154: 76.5 | GW154: 35.3 | GX154: 38.8 | GY154: 33.4 | GZ154: 33.4 | HD154: 37.5 | HF154: 26.8 | HH154: 27.3 | HJ154: 54.3 | HK154: 46.2 | HL154: 47.7 | HM154: 40.3 | HN154: 68.1 | HO154: 68.1 | HQ154: 79.3 | HR154: 85.2 | HT154: 54 | HV154: 50.8 | HW154: 47.1 | HZ154: 27.3 | IA154: 31.6 | IE154: 37.9 | IG154: 15.2 | IH154: 14.1 | II154: 21.4 | IJ154: 39.6 | IK154: 40.4 | IL154: 61.1 | IM154: 49.6 | IN154: 32.9 | IO154: 39.8 | IP154: 38.9 | IQ154: 27.2
A155: 30926 | B155: 34.2 | C155: 32.4 | D155: 28.8 | E155: 33.5 | F155: 42.4 | G155: 42.4 | H155: 41.8 | I155: 43.5 | J155: 46.1 | K155: 27.1 | L155: 75.5 | M155: 34.8 | N155: 32.1 | O155: 37.3 | P155: 38.9 | Q155: 35 | R155: 36.6 | W155: 36.6 | X155: 30.8 | AB155: 37.3 | AD155: 48.2 | AF155: 32.1 | AG155: 33.6 | AH155: 30.5 | AI155: 20.6 | AJ155: 33 | AK155: 25.4 | AL155: 45.3 | AM155: 29.6 | AN155: 8.8 | AO155: 8.8 | AP155: 58.8 | AU155: 74.5 | AV155: 93.3 | AW155: 67 | AX155: 65.5 | BA155: 31.9 | BB155: 31.8 | BC155: 26.8 | BD155: 26.8 | BH155: 41.3 | BJ155: 25.4 | BL155: 23.8 | BN155: 58.2 | BO155: 55.4 | BP155: 61.9 | BQ155: 36.9 | BR155: 66.4 | BS155: 66.4 | BU155: 84.1 | BV155: 84.2 | BX155: 54.2 | BZ155: 52.5 | CA155: 50.8 | CD155: 40.2 | CE155: 35.9 | CI155: 36.2 | CK155: 17.7 | CL155: 16.4 | CM155: 22.5 | CN155: 37.7 | CO155: 39.2 | CP155: 62.7 | CQ155: 54 | CR155: 32.6 | CS155: 40.5 | CT155: 29.5 | CU155: 24.4 | CV155: 24.4 | CW155: 72.5 | CX155: 72.5 | CY155: 41 | CZ155: 76.6 | DC155: 997 | DH155: 41.3 | DI155: 38.9 | DJ155: 44 | DN155: 35.3 | DR155: 17.1 | DS155: 17.1 | EC155: 36.5 | EF155: 40.1 | EG155: 31.4 | EH155: 36.5 | EI155: 37 | EJ155: 38.4 | EK155: 35.6 | EL155: 38 | EM155: 34.3 | EO155: 36.4 | EU155: 37.4 | EX155: 34.2 | EY155: 31.3 | EZ155: 26.5 | FA155: 33.3 | FB155: 39.7 | FC155: 38.4 | FD155: 43.9 | FE155: 43.2 | FF155: 50 | FG155: 25.6 | FH155: 82.9 | FI155: 36.1 | FJ155: 37.7 | FK155: 35.4 | FL155: 37.1 | FM155: 33.9 | FN155: 39 | FS155: 46.9 | FT155: 32.1 | FX155: 39 | FZ155: 48.9 | GB155: 31 | GC155: 32.3 | GD155: 29.4 | GE155: 21 | GF155: 33.9 | GG155: 29.3 | GH155: 51.1 | GI155: 28.3 | GJ155: 9.4 | GK155: 9.4 | GL155: 61.7 | GQ155: 66.8 | GR155: 72.6 | GS155: 60.4 | GT155: 77.4 | GW155: 36.8 | GX155: 39.7 | GY155: 34 | GZ155: 34 | HD155: 38.1 | HF155: 27.1 | HH155: 27.6 | HJ155: 54.8 | HK155: 47.1 | HL155: 48.6 | HM155: 41.1 | HN155: 67.3 | HO155: 67.3 | HQ155: 79.1 | HR155: 85 | HT155: 53.7 | HV155: 51.4 | HW155: 48.7 | HZ155: 27.4 | IA155: 32.1 | IE155: 38.2 | IG155: 15.1 | IH155: 13.9 | II155: 21.8 | IJ155: 39.8 | IK155: 40.7 | IL155: 61.8 | IM155: 50.9 | IN155: 33 | IO155: 39.9 | IP155: 38.9 | IQ155: 27
A156: 31017 | B156: 34.9 | C156: 32.6 | D156: 28.8 | E156: 33.9 | F156: 42.8 | G156: 42.6 | H156: 42.4 | I156: 43.6 | J156: 47.5 | K156: 26.6 | L156: 81.2 | M156: 35.1 | N156: 34.4 | O156: 37.1 | P156: 38.8 | Q156: 34.3 | R156: 36.4 | W156: 37 | X156: 30.8 | AB156: 38.1 | AD156: 49.9 | AF156: 32.8 | AG156: 34.4 | AH156: 31.1 | AI156: 21 | AJ156: 33.7 | AK156: 25.5 | AL156: 47.7 | AM156: 30 | AN156: 9 | AO156: 9 | AP156: 60.1 | AU156: 76.6 | AV156: 97.1 | AW156: 68.4 | AX156: 67.1 | BA156: 32 | BB156: 32 | BC156: 27.2 | BD156: 27.2 | BH156: 41.1 | BJ156: 26.2 | BL156: 24.6 | BN156: 58.8 | BO156: 56.4 | BP156: 63.3 | BQ156: 37.4 | BR156: 66.6 | BS156: 66.6 | BU156: 84.1 | BV156: 84.2 | BX156: 54.9 | BZ156: 52.7 | CA156: 52.9 | CD156: 39.3 | CE156: 36.4 | CI156: 36.8 | CK156: 18.1 | CL156: 16.6 | CM156: 23.4 | CN156: 38.1 | CO156: 39.5 | CP156: 63.4 | CQ156: 54 | CR156: 32 | CS156: 41.5 | CT156: 31.9 | CU156: 25.2 | CV156: 25.2 | CW156: 72.5 | CX156: 72.5 | CY156: 41 | CZ156: 76.6 | DC156: 944.4 | DH156: 41.8 | DI156: 42 | DJ156: 43 | DN156: 36 | DR156: 17.1 | DS156: 17.1 | EC156: 37.1 | EF156: 40.6 | EG156: 31.9 | EH156: 37.1 | EI156: 37.4 | EJ156: 38.9 | EK156: 36.1 | EL156: 38.5 | EM156: 34.8 | EO156: 36.9 | EU156: 37.9 | EX156: 34.6 | EY156: 31.2 | EZ156: 26 | FA156: 34 | FB156: 39.9 | FC156: 37.3 | FD156: 44.2 | FE156: 44.2 | FF156: 51.3 | FG156: 23.9 | FH156: 82.5 | FI156: 36.2 | FJ156: 39.4 | FK156: 35.1 | FL156: 36.9 | FM156: 33.4 | FN156: 37.7 | FS156: 46.9 | FT156: 33.3 | FX156: 40.4 | FZ156: 50.1 | GB156: 31.3 | GC156: 32.4 | GD156: 29.9 | GE156: 21.5 | GF156: 34.6 | GG156: 29.4 | GH156: 52.4 | GI156: 28.9 | GJ156: 9.5 | GK156: 9.5 | GL156: 63.3 | GQ156: 69.4 | GR156: 74.2 | GS156: 64.3 | GT156: 78.5 | GW156: 36.9 | GX156: 40.5 | GY156: 34.8 | GZ156: 34.8 | HD156: 38 | HF156: 27.9 | HH156: 28.3 | HJ156: 55.5 | HK156: 48.6 | HL156: 50.4 | HM156: 41.6 | HN156: 67.9 | HO156: 67.9 | HQ156: 78.5 | HR156: 84.3 | HT156: 54.4 | HV156: 51.7 | HW156: 51.2 | HZ156: 26.1 | IA156: 33.4 | IE156: 38.9 | IG156: 15.3 | IH156: 14 | II156: 22.2 | IJ156: 39.9 | IK156: 40.9 | IL156: 63.3 | IM156: 50.7 | IN156: 32.5 | IO156: 40.3 | IP156: 38.9 | IQ156: 27
... A163: 31656 | B163: 39.8 | C163: 38.3 | D163: 33.8 | E163: 41.1 | F163: 46.8 | G163: 47.1 | H163: 45 | I163: 45.3 | J163: 47.8 | K163: 30.3 | L163: 79 | M163: 37.4 | N163: 41.6 | O163: 41.1 | P163: 43.4 | Q163: 38.5 | R163: 38.5 | W163: 36.6 | X163: 35.3 | AB163: 43.6 | AD163: 63.6 | AF163: 38.2 | AG163: 39.9 | AH163: 36.4 | AI163: 24.7 | AJ163: 38.2 | AK163: 30.4 | AL163: 50.7 | AM163: 34.2 | AN163: 11.5 | AO163: 11.5 | AP163: 68 | AU163: 87.5 | AV163: 103.8 | AW163: 81.5 | AX163: 76.6 | BA163: 35.5 | BB163: 37.2 | BC163: 32.8 | BD163: 32.8 | BH163: 45.1 | BJ163: 29.3 | BL163: 27.8 | BN163: 66.8 | BO163: 64.5 | BP163: 72.4 | BQ163: 43 | BR163: 75.3 | BS163: 75.3 | BU163: 91.3 | BV163: 91.4 | BX163: 70.5 | BZ163: 61.5 | CA163: 60 | CD163: 46.1 | CE163: 41.5 | CI163: 44.5 | CK163: 21.5 | CL163: 19.6 | CM163: 28.1 | CN163: 44.9 | CO163: 46.7 | CP163: 80.5 | CQ163: 57.7 | CR163: 34.1 | CS163: 49.5 | CT163: 36.4 | CU163: 28.9 | CV163: 28.9 | CW163: 79.3 | CX163: 79.3 | CY163: 46.9 | CZ163: 82.8 | DC163: 987.4 | DH163: 50.7 | DI163: 45.4 | DJ163: 55.3 | DN163: 39.2 | DR163: 19.9 | DS163: 19.9 | EC163: 42.8 | EF163: 46.7 | EG163: 37.6 | EH163: 42.9 | EI163: 43.5 | EJ163: 44.9 | EK163: 41.8 | EL163: 44.6 | EM163: 40.3 | EO163: 42.5 | EU163: 43.8 | EX163: 40.2 | EY163: 37.5 | EZ163: 30.8 | FA163: 41.7 | FB163: 47.1 | FC163: 43.9 | FD163: 48.6 | FE163: 46.9 | FF163: 49.8 | FG163: 30.2 | FH163: 89.9 | FI163: 39.4 | FJ163: 48.5 | FK163: 40.6 | FL163: 42.7 | FM163: 39.9 | FN163: 39.7 | FS163: 49.2 | FT163: 39.3 | FX163: 45.7 | FZ163: 63.7 | GB163: 37.1 | GC163: 39 | GD163: 35 | GE163: 24.5 | GF163: 39.5 | GG163: 34.1 | GH163: 53.6 | GI163: 34.1 | GJ163: 10.8 | GK163: 10.8 | GL163: 72.6 | GQ163: 81 | GR163: 83.2 | GS163: 78.2 | GT163: 88.8 | GW163: 38.4 | GX163: 46.9 | GY163: 40.9 | GZ163: 40.9 | HD163: 42.6 | HF163: 30.3 | HH163: 30.6 | HJ163: 63.2 | HK163: 56.6 | HL163: 58.1 | HM163: 50.2 | HN163: 80.5 | HO163: 80.5 | HQ163: 88.3 | HR163: 94.9 | HT163: 65.4 | HV163: 60.8 | HW163: 57.8 | HZ163: 31.4 | IA163: 37.1 | IE163: 46.7 | IG163: 19.1 | IH163: 17.7 | II163: 27 | IJ163: 46.1 | IK163: 47.3 | IL163: 79.7 | IM163: 57.2 | IN163: 35.5 | IO163: 46.4 | IP163: 40.6 | IQ163: 30.8
A164: 31747 | B164: 40.6 | C164: 38.7 | D164: 34.4 | E164: 41.1 | F164: 48.1 | G164: 46.6 | H164: 46 | I164: 46.3 | J164: 50 | K164: 28.4 | L164: 79.4 | M164: 38.1 | N164: 47.5 | O164: 41.1 | P164: 43.5 | Q164: 38.1 | R164: 37.6 | W164: 38 | X164: 37 | AB164: 44.1 | AD164: 61 | AF164: 38.9 | AG164: 41.1 | AH164: 36.7 | AI164: 25.6 | AJ164: 39.5 | AK164: 31.3 | AL164: 53.8 | AM164: 35.2 | AN164: 12 | AO164: 12 | AP164: 71.2 | AU164: 89.8 | AV164: 107.1 | AW164: 84.2 | AX164: 76.7 | BA164: 36.1 | BB164: 37.9 | BC164: 33.6 | BD164: 33.6 | BH164: 46 | BJ164: 29.4 | BL164: 27.8 | BN164: 68 | BO164: 66.2 | BP164: 74.5 | BQ164: 43.5 | BR164: 77.3 | BS164: 77.3 | BU164: 92.5 | BV164: 92.6 | BX164: 75 | BZ164: 61.7 | CA164: 60 | CD164: 45.6 | CE164: 42.7 | CH164: 49.7 | CI164: 48.8 | CJ164: 53.1 | CK164: 23.4 | CL164: 21.8 | CM164: 28.7 | CN164: 46.5 | CO164: 48.6 | CP164: 85.8 | CQ164: 58.5 | CR164: 35.9 | CS164: 50.2 | CT164: 36.4 | CU164: 29.5 | CV164: 29.5 | CW164: 81.1 | CX164: 81.1 | CY164: 49.6 | CZ164: 83.9 | DC164: 1009.4 | DH164: 49.9 | DI164: 47.2 | DJ164: 53.1 | DN164: 40 | DO164: 27.9 | DR164: 19.9 | DS164: 19.9 | EC164: 44.1 | EF164: 48 | EG164: 38.4 | EH164: 44.1 | EI164: 44.7 | EJ164: 46.1 | EK164: 42.9 | EL164: 45.9 | EM164: 41.5 | EO164: 43.7 | EU164: 44.9 | EX164: 40.9 | EY164: 37.5 | EZ164: 30.8 | FA164: 41.6 | FB164: 48 | FC164: 44.2 | FD164: 50.1 | FE164: 48.3 | FF164: 52.8 | FG164: 28.6 | FH164: 92.4 | FI164: 40.9 | FJ164: 55.5 | FK164: 40 | FL164: 42.9 | FM164: 36 | FN164: 41.1 | FS164: 46.4 | FT164: 40.4 | FX164: 48 | FZ164: 64.1 | GB164: 38.2 | GC164: 40.3 | GD164: 35.9 | GE164: 25.2 | GF164: 40.8 | GG164: 35 | GH164: 56.4 | GI164: 35.1 | GJ164: 11 | GK164: 11 | GL164: 75.2 | GQ164: 82 | GR164: 84.3 | GS164: 79.6 | GT164: 89.5 | GW164: 38.4 | GX164: 47.6 | GY164: 41.8 | GZ164: 41.8 | HD164: 42.9 | HF164: 31.3 | HH164: 31.8 | HJ164: 65 | HK164: 57.6 | HL164: 58.9 | HM164: 51.4 | HN164: 80.9 | HO164: 80.9 | HQ164: 90 | HR164: 96.8 | HT164: 72.9 | HV164: 59.8 | HW164: 58.5 | HZ164: 32.1 | IA164: 37.3 | ID164: 52.1 | IE164: 52.1 | IF164: 50.5 | IG164: 21.5 | IH164: 20.4 | II164: 27.5 | IJ164: 48.4 | IK164: 49.7 | IL164: 84.9 | IM164: 58.3 | IN164: 37.9 | IO164: 48 | IP164: 40.6 | IQ164: 31.3
A165: 31837 | B165: 41 | C165: 39 | D165: 34.7 | E165: 41.2 | F165: 48.4 | G165: 47.9 | H165: 46.6 | I165: 47 | J165: 47.5 | K165: 30.5 | L165: 85.7 | M165: 38.4 | N165: 46.8 | O165: 41.8 | P165: 44.4 | Q165: 38.5 | R165: 38.3 | W165: 39 | X165: 37.5 | AB165: 46.1 | AD165: 62.1 | AF165: 39.7 | AG165: 41.3 | AH165: 37.9 | AI165: 26.4 | AJ165: 40.5 | AK165: 32.1 | AL165: 54.2 | AM165: 36.3 | AN165: 12.5 | AO165: 12.5 | AP165: 71.7 | AU165: 90.1 | AV165: 107.6 | AW165: 84.5 | AX165: 77.4 | BA165: 36.5 | BB165: 38.9 | BC165: 34.6 | BD165: 34.6 | BH165: 46.2 | BJ165: 29.4 | BL165: 27.8 | BN165: 68.5 | BO165: 65.1 | BP165: 72.3 | BQ165: 44.4 | BR165: 76.8 | BS165: 76.8 | BU165: 94 | BV165: 94.1 | BX165: 74.3 | BZ165: 63.8 | CA165: 61.9 | CD165: 48.9 | CE165: 43.2 | CH165: 52.4 | CI165: 51.8 | CJ165: 54.4 | CK165: 24.5 | CL165: 22.9 | CM165: 29.6 | CN165: 48 | CO165: 50.2 | CP165: 88.6 | CQ165: 59.5 | CR165: 36.6 | CS165: 51.5 | CT165: 36.5 | CU165: 29.7 | CV165: 29.7 | CW165: 81.6 | CX165: 81.6 | CY165: 49.6 | CZ165: 84.5 | DC165: 1048.6 | DH165: 51 | DI165: 48 | DJ165: 54.6 | DN165: 41.2 | DO165: 31.3 | DR165: 21.8 | DS165: 21.8 | EC165: 45 | EF165: 48.8 | EG165: 39.5 | EH165: 45 | EI165: 45.8 | EJ165: 47.1 | EK165: 43.9 | EL165: 46.9 | EM165: 42.5 | EO165: 44.5 | EU165: 45.9 | EX165: 41.2 | EY165: 38 | EZ165: 31.5 | FA165: 41.9 | FB165: 48.9 | FC165: 44.4 | FD165: 50.5 | FE165: 48.6 | FF165: 52 | FG165: 29.8 | FH165: 91.8 | FI165: 40.5 | FJ165: 57.5 | FK165: 41.1 | FL165: 42.9 | FM165: 39.9 | FN165: 41.2 | FS165: 47.6 | FT165: 42.3 | FX165: 48.4 | FZ165: 63.4 | GB165: 38.9 | GC165: 41.2 | GD165: 36.4 | GE165: 25.8 | GF165: 41.8 | GG165: 35.3 | GH165: 57.6 | GI165: 36.1 | GJ165: 11.3 | GK165: 11.3 | GL165: 75.5 | GQ165: 82.4 | GR165: 85.5 | GS165: 79.4 | GT165: 89.9 | GW165: 39.4 | GX165: 48.4 | GY165: 42.6 | GZ165: 42.6 | HD165: 43.4 | HF165: 31.3 | HH165: 31.8 | HJ165: 65.7 | HK165: 57.3 | HL165: 58.3 | HM165: 51.8 | HN165: 81.5 | HO165: 81.5 | HQ165: 90.3 | HR165: 97.1 | HT165: 74.7 | HV165: 62.1 | HW165: 60.7 | HZ165: 33.4 | IA165: 37.6 | ID165: 54 | IE165: 54.2 | IF165: 51.4 | IG165: 21.9 | IH165: 20.8 | II165: 28.6 | IJ165: 50 | IK165: 51.5 | IL165: 87.4 | IM165: 58.5 | IN165: 39.2 | IO165: 49.6 | IP165: 40.7 | IQ165: 31.7
A166: 31929 | B166: 41.1 | C166: 39.9 | D166: 35.5 | E166: 41.7 | F166: 50.7 | G166: 50.6 | H166: 47.4 | I166: 47.2 | J166: 48 | K166: 31 | L166: 89.4 | M166: 39.1 | N166: 48.1 | O166: 42.6 | P166: 44.9 | Q166: 39.6 | R166: 38.9 | W166: 39.8 | X166: 38.7 | AB166: 45.8 | AD166: 60.2 | AF166: 40.3 | AG166: 41.9 | AH166: 38.6 | AI166: 27.1 | AJ166: 41.7 | AK166: 33.1 | AL166: 55.2 | AM166: 37.4 | AN166: 12.8 | AO166: 12.8 | AP166: 73.6 | AU166: 90.9 | AV166: 108.7 | AW166: 85.2 | AX166: 77.7 | BA166: 37 | BB166: 39.9 | BC166: 35.7 | BD166: 35.7 | BH166: 47.5 | BJ166: 29.4 | BL166: 27.8 | BN166: 69.9 | BO166: 67.6 | BP166: 75.5 | BQ166: 45.5 | BR166: 79.7 | BS166: 79.7 | BU166: 96.2 | BV166: 96.3 | BX166: 78 | BZ166: 64.1 | CA166: 63.7 | CD166: 49.4 | CE166: 43.2 | CH166: 51.3 | CI166: 50.3 | CJ166: 55.1 | CK166: 25.2 | CL166: 23.6 | CM166: 30.4 | CN166: 48.2 | CO166: 50.4 | CP166: 90.1 | CQ166: 60.2 | CR166: 35.3 | CS166: 52.8 | CT166: 37.9 | CU166: 29.8 | CV166: 29.8 | CW166: 81.8 | CX166: 81.8 | CY166: 49.6 | CZ166: 84.8 | DC166: 1060.1 | DH166: 50.2 | DI166: 45.8 | DJ166: 55.2 | DN166: 41.1 | DO166: 31.3 | DR166: 21.8 | DS166: 21.8 | EC166: 45.7 | EF166: 49.5 | EG166: 40.3 | EH166: 45.7 | EI166: 46.7 | EJ166: 47.7 | EK166: 44.5 | EL166: 47.4 | EM166: 43.1 | EO166: 45.3 | EU166: 46.6 | EX166: 41.3 | EY166: 38.6 | EZ166: 32.2 | FA166: 42.2 | FB166: 48.9 | FC166: 45.4 | FD166: 51.2 | FE166: 49.1 | FF166: 51.5 | FG166: 30.7 | FH166: 95.5 | FI166: 41.7 | FJ166: 56.8 | FK166: 41.2 | FL166: 43.4 | FM166: 39.3 | FN166: 41.7 | FS166: 47.3 | FT166: 43.3 | FX166: 48.7 | FZ166: 60.7 | GB166: 39.4 | GC166: 41.3 | GD166: 37.2 | GE166: 26.3 | GF166: 42.5 | GG166: 36.5 | GH166: 56.9 | GI166: 36.9 | GJ166: 11.6 | GK166: 11.6 | GL166: 78.2 | GQ166: 84.6 | GR166: 88.4 | GS166: 81.5 | GT166: 91.2 | GW166: 40.6 | GX166: 49.3 | GY166: 43.3 | GZ166: 43.3 | HD166: 43.7 | HF166: 31.3 | HH166: 31.8 | HJ166: 67.2 | HK166: 60 | HL166: 61.3 | HM166: 53.8 | HN166: 84.3 | HO166: 84.3 | HQ166: 91.4 | HR166: 98.2 | HT166: 80.1 | HV166: 62.1 | HW166: 60.8 | HZ166: 33.5 | IA166: 40.1 | ID166: 52.6 | IE166: 52.4 | IF166: 51.9 | IG166: 22.8 | IH166: 21.6 | II166: 29.5 | IJ166: 50.4 | IK166: 51.8 | IL166: 89.2 | IM166: 59.6 | IN166: 37.3 | IO166: 50.9 | IP166: 41.2 | IQ166: 31.7
A167: 32021 | B167: 41.5 | C167: 40.6 | D167: 35.7 | E167: 43 | F167: 51.9 | G167: 51.3 | H167: 47.7 | I167: 48.3 | J167: 47.5 | K167: 31.5 | L167: 84.3 | M167: 39.7 | N167: 49.5 | O167: 43.1 | P167: 45.8 | Q167: 38.9 | R167: 40.3 | W167: 40.7 | X167: 39.4 | AB167: 48.2 | AD167: 58.9 | AF167: 40.7 | AG167: 42.3 | AH167: 39 | AI167: 27.5 | AJ167: 42.3 | AK167: 33.7 | AL167: 56.1 | AM167: 38 | AN167: 12.9 | AO167: 12.9 | AP167: 74.2 | AU167: 90.9 | AV167: 107.5 | AW167: 85.6 | AX167: 78.9 | BA167: 37.9 | BB167: 40.8 | BC167: 37.2 | BD167: 37.2 | BH167: 47.9 | BJ167: 31.4 | BL167: 30 | BN167: 71.5 | BO167: 68 | BP167: 75.4 | BQ167: 46.8 | BR167: 80.2 | BS167: 80.2 | BU167: 96.1 | BV167: 96.2 | BX167: 79.4 | BZ167: 64.3 | CA167: 64.5 | CD167: 49.2 | CE167: 44.5 | CH167: 49 | CI167: 47.6 | CJ167: 54.6 | CK167: 26 | CL167: 24.4 | CM167: 31.4 | CN167: 49.5 | CO167: 51.8 | CP167: 92.2 | CQ167: 61.7 | CR167: 35 | CS167: 53.2 | CT167: 41.2 | CU167: 31.1 | CV167: 31.1 | CW167: 86.3 | CX167: 86.3 | CY167: 50.9 | CZ167: 89.7 | DC167: 1056.3 | DH167: 52 | DI167: 47.9 | DJ167: 56.7 | DN167: 41.6 | DO167: 32 | DR167: 21.8 | DS167: 21.8 | EC167: 46.5 | EF167: 50.1 | EG167: 41.4 | EH167: 46.5 | EI167: 47.6 | EJ167: 48.6 | EK167: 45.3 | EL167: 48.3 | EM167: 43.8 | EO167: 46 | EU167: 47.4 | EX167: 42.2 | EY167: 38.8 | EZ167: 31.4 | FA167: 43.4 | FB167: 50.1 | FC167: 46.2 | FD167: 52.6 | FE167: 50.9 | FF167: 53.5 | FG167: 31.9 | FH167: 95.5 | FI167: 42.8 | FJ167: 57.8 | FK167: 42 | FL167: 43.5 | FM167: 41.1 | FN167: 43.4 | FS167: 47.9 | FT167: 44.3 | FX167: 49.3 | FZ167: 59.6 | GB167: 40.4 | GC167: 42.8 | GD167: 37.9 | GE167: 26.6 | GF167: 43 | GG167: 36.7 | GH167: 57.6 | GI167: 37.4 | GJ167: 11.7 | GK167: 11.7 | GL167: 79.1 | GQ167: 85.5 | GR167: 88.7 | GS167: 81.8 | GT167: 94.4 | GW167: 41.4 | GX167: 50.2 | GY167: 44.5 | GZ167: 44.5 | HD167: 44.8 | HF167: 32.1 | HH167: 32.7 | HJ167: 68.4 | HK167: 61.4 | HL167: 62.9 | HM167: 54.6 | HN167: 86.7 | HO167: 86.7 | HQ167: 92 | HR167: 98.9 | HT167: 77.8 | HV167: 61.5 | HW167: 61.4 | HZ167: 35.4 | IA167: 40.3 | ID167: 50.5 | IE167: 49.6 | IF167: 52 | IG167: 23.2 | IH167: 21.9 | II167: 30.3 | IJ167: 51.4 | IK167: 52.9 | IL167: 91.7 | IM167: 60.4 | IN167: 37.1 | IO167: 52.2 | IP167: 42.8 | IQ167: 33.5
A168: 32112 | B168: 42.3 | C168: 41 | D168: 35.9 | E168: 43.9 | F168: 50.7 | G168: 50.9 | H168: 48.2 | I168: 48.8 | J168: 49 | K168: 29.3 | L168: 80.6 | M168: 40.3 | N168: 54.2 | O168: 44.1 | P168: 46.1 | Q168: 41.8 | R168: 41.2 | W168: 40.2 | X168: 40.8 | AB168: 48.2 | AD168: 59 | AF168: 41.4 | AG168: 42.9 | AH168: 39.7 | AI168: 28 | AJ168: 43 | AK168: 34.3 | AL168: 55.8 | AM168: 38.7 | AN168: 13.2 | AO168: 13.2 | AP168: 76.3 | AU168: 91.9 | AV168: 107 | AW168: 87.4 | AX168: 78.8 | BA168: 38.1 | BB168: 41.5 | BC168: 38.5 | BD168: 38.5 | BH168: 48.2 | BJ168: 31.6 | BL168: 30 | BN168: 72.3 | BO168: 68.4 | BP168: 75.1 | BQ168: 48.2 | BR168: 81.2 | BS168: 81.2 | BU168: 97.2 | BV168: 97.3 | BX168: 80.2 | BZ168: 67.2 | CA168: 64.9 | CD168: 49.8 | CE168: 44.5 | CH168: 46.4 | CI168: 44.4 | CJ168: 54.8 | CK168: 28.1 | CL168: 26.9 | CM168: 31.6 | CN168: 50.5 | CO168: 52.7 | CP168: 94.4 | CQ168: 63.6 | CR168: 36.3 | CS168: 54.1 | CT168: 41.2 | CU168: 31.2 | CV168: 31.2 | CW168: 88.1 | CX168: 88.1 | CY168: 50.9 | CZ168: 91.7 | DC168: 1055.3 | DH168: 52.3 | DI168: 49.8 | DJ168: 55.3 | DN168: 42.2 | DO168: 31.4 | DR168: 21.8 | DS168: 21.8 | EC168: 47.2 | EF168: 50.9 | EG168: 42.2 | EH168: 47.3 | EI168: 48.4 | EJ168: 49.3 | EK168: 46.1 | EL168: 49.1 | EM168: 44.6 | EO168: 46.8 | EU168: 48.1 | EX168: 42.4 | EY168: 38.7 | EZ168: 31.3 | FA168: 43.4 | FB168: 48.5 | FC168: 46.9 | FD168: 52.6 | FE168: 50.4 | FF168: 53.9 | FG168: 30.3 | FH168: 98 | FI168: 43.4 | FJ168: 59.1 | FK168: 42.8 | FL168: 44.2 | FM168: 41.9 | FN168: 44.3 | FS168: 48.5 | FT168: 43.9 | FX168: 49.2 | FZ168: 60.1 | GB168: 41.1 | GC168: 43.4 | GD168: 38.6 | GE168: 27.1 | GF168: 43.5 | GG168: 37.6 | GH168: 57.4 | GI168: 38.1 | GJ168: 12.1 | GK168: 12.1 | GL168: 81.4 | GQ168: 87 | GR168: 91 | GS168: 82.7 | GT168: 95.9 | GW168: 42.8 | GX168: 50.3 | GY168: 45.2 | GZ168: 45.2 | HD168: 45.1 | HF168: 32.9 | HH168: 33.4 | HJ168: 69.7 | HK168: 62.5 | HL168: 63.8 | HM168: 56.2 | HN168: 87.5 | HO168: 87.5 | HQ168: 92.9 | HR168: 99.8 | HT168: 82.4 | HV168: 64.5 | HW168: 61.3 | HZ168: 35.1 | IA168: 41.3 | ID168: 48.3 | IE168: 46.8 | IF168: 52.4 | IG168: 24.4 | IH168: 23.3 | II168: 30.9 | IJ168: 53.4 | IK168: 55 | IL168: 94.1 | IM168: 60.7 | IN168: 39.4 | IO168: 52.9 | IP168: 44.2 | IQ168: 33.5
A169: 32203 | B169: 43 | C169: 41.8 | D169: 36.8 | E169: 44.5 | F169: 50.2 | G169: 53.3 | H169: 48.8 | I169: 49.7 | J169: 48.3 | K169: 31 | L169: 83.5 | M169: 40 | N169: 54 | O169: 44.8 | P169: 47.1 | Q169: 41.8 | R169: 42 | W169: 42 | X169: 41.1 | AB169: 47 | AD169: 59.3 | AF169: 42.4 | AG169: 43.4 | AH169: 41.2 | AI169: 28.4 | AJ169: 43.7 | AK169: 34.9 | AL169: 56.5 | AM169: 39.5 | AN169: 13.4 | AO169: 13.4 | AP169: 76.6 | AU169: 93.5 | AV169: 110.4 | AW169: 88.2 | AX169: 80.6 | BA169: 39.4 | BB169: 42.7 | BC169: 40.1 | BD169: 40.1 | BH169: 48.9 | BJ169: 31.6 | BL169: 30 | BN169: 73.1 | BO169: 70.1 | BP169: 77.2 | BQ169: 49.2 | BR169: 81.8 | BS169: 81.8 | BU169: 98 | BV169: 98.1 | BX169: 80.1 | BZ169: 66.8 | CA169: 66.4 | CD169: 53.2 | CE169: 45.3 | CH169: 55.5 | CI169: 55.4 | CJ169: 55.4 | CK169: 28.7 | CL169: 27.7 | CM169: 31.7 | CN169: 51.6 | CO169: 53.9 | CP169: 96.6 | CQ169: 64.6 | CR169: 37.6 | CS169: 54.6 | CT169: 41.3 | CU169: 32 | CV169: 32 | CW169: 87.4 | CX169: 87.4 | CY169: 50.9 | CZ169: 91 | DC169: 1034.3 | DH169: 55.5 | DI169: 50.5 | DJ169: 61.4 | DN169: 42.8 | DO169: 34.6 | DR169: 24.4 | DS169: 24.4 | EC169: 48.3 | EF169: 51.8 | EG169: 43.4 | EH169: 48.3 | EI169: 49.4 | EJ169: 50.5 | EK169: 47.1 | EL169: 50.1 | EM169: 45.7 | EO169: 47.8 | EU169: 49.1 | EX169: 43.1 | EY169: 39.6 | EZ169: 31.9 | FA169: 44.6 | FB169: 50.1 | FC169: 47.1 | FD169: 53.6 | FE169: 51.2 | FF169: 55 | FG169: 31.3 | FH169: 95.1 | FI169: 44 | FJ169: 63.3 | FK169: 43.4 | FL169: 44.6 | FM169: 43.1 | FN169: 44.4 | FS169: 48.5 | FT169: 44.7 | FX169: 48.4 | FZ169: 61.6 | GB169: 41.7 | GC169: 43.6 | GD169: 39.6 | GE169: 27.9 | GF169: 44.6 | GG169: 38.5 | GH169: 59.1 | GI169: 38.8 | GJ169: 12.6 | GK169: 12.6 | GL169: 81.3 | GQ169: 86.5 | GR169: 90.5 | GS169: 82.7 | GT169: 94.6 | GW169: 42.9 | GX169: 51.1 | GY169: 46 | GZ169: 46 | HD169: 45.6 | HF169: 32.9 | HH169: 33.4 | HJ169: 70.4 | HK169: 62.9 | HL169: 63.8 | HM169: 57.7 | HN169: 88.4 | HO169: 88.4 | HQ169: 94 | HR169: 101 | HT169: 81.9 | HV169: 64.5 | HW169: 62.7 | HZ169: 36.2 | IA169: 41.9 | ID169: 57.5 | IE169: 58 | IF169: 53.5 | IG169: 25 | IH169: 23.8 | II169: 31.5 | IJ169: 53 | IK169: 54.6 | IL169: 96.3 | IM169: 63.1 | IN169: 38 | IO169: 53.4 | IP169: 34.2 | IQ169: 33.7
A170: 32295 | B170: 44.4 | C170: 43.4 | D170: 37.9 | E170: 46 | F170: 57.1 | G170: 54.5 | H170: 50.8 | I170: 52.4 | J170: 48.3 | K170: 33.6 | L170: 88.8 | M170: 40.9 | N170: 55.4 | O170: 45.7 | P170: 47.3 | Q170: 43.9 | R170: 44 | W170: 44.9 | X170: 42.2 | AB170: 46.9 | AD170: 59.9 | AF170: 43.3 | AG170: 44.6 | AH170: 41.8 | AI170: 28.7 | AJ170: 44.4 | AK170: 35.7 | AL170: 57.8 | AM170: 39.9 | AN170: 13.4 | AO170: 13.4 | AP170: 79.4 | AU170: 96.5 | AV170: 114.3 | AW170: 90.8 | AX170: 83 | BA170: 40.6 | BB170: 44.1 | BC170: 41.6 | BD170: 41.6 | BH170: 49.7 | BJ170: 31.6 | BL170: 30 | BN170: 74.2 | BO170: 72.3 | BP170: 79.5 | BQ170: 50.8 | BR170: 81.8 | BS170: 81.8 | BU170: 99.6 | BV170: 99.7 | BX170: 80.2 | BZ170: 66.5 | CA170: 67.6 | CD170: 54.3 | CE170: 45.7 | CH170: 55.5 | CI170: 55.1 | CJ170: 56.6 | CK170: 28.9 | CL170: 27.6 | CM170: 33 | CN170: 50.7 | CO170: 53 | CP170: 98.8 | CQ170: 67.1 | CR170: 33.8 | CS170: 55.1 | CT170: 41.5 | CU170: 32 | CV170: 32 | CW170: 87.4 | CX170: 87.4 | CY170: 50.9 | CZ170: 91 | DC170: 1025.7 | DH170: 55.6 | DI170: 50.4 | DJ170: 61.8 | DN170: 43.8 | DO170: 34.6 | DR170: 24.4 | DS170: 24.4 | EC170: 49 | EF170: 52.5 | EG170: 44.2 | EH170: 49.1 | EI170: 50 | EJ170: 51.3 | EK170: 47.8 | EL170: 50.7 | EM170: 46.4 | EO170: 48.8 | EU170: 49.9 | EX170: 44.8 | EY170: 40.7 | EZ170: 32.9 | FA170: 45.4 | FB170: 53.4 | FC170: 49 | FD170: 55.7 | FE170: 54.4 | FF170: 55.6 | FG170: 33.7 | FH170: 100.8 | FI170: 44.1 | FJ170: 62.9 | FK170: 44 | FL170: 45.4 | FM170: 43.6 | FN170: 45.3 | FS170: 50.5 | FT170: 45.4 | FX170: 50.1 | FZ170: 61.6 | GB170: 42.3 | GC170: 44.2 | GD170: 40 | GE170: 28.4 | GF170: 45.5 | GG170: 39.1 | GH170: 61.9 | GI170: 39.3 | GJ170: 12.7 | GK170: 12.7 | GL170: 84.7 | GQ170: 89.2 | GR170: 95.9 | GS170: 83.9 | GT170: 96.8 | GW170: 44.2 | GX170: 51.8 | GY170: 46.6 | GZ170: 46.6 | HD170: 46.4 | HF170: 32.9 | HH170: 33.4 | HJ170: 71.2 | HK170: 63.9 | HL170: 64 | HM170: 60.8 | HN170: 88.1 | HO170: 88.1 | HQ170: 95.4 | HR170: 102.6 | HT170: 84.4 | HV170: 65.6 | HW170: 64.4 | HZ170: 37 | IA170: 43.1 | ID170: 57.8 | IE170: 57.7 | IF170: 56.2 | IG170: 25.8 | IH170: 24.6 | II170: 32.5 | IJ170: 53.2 | IK170: 54.7 | IL170: 98.9 | IM170: 64.4 | IN170: 36.1 | IO170: 55.1 | IP170: 34.7 | IQ170: 33.9
A171: 32387 | B171: 45.5 | C171: 44 | D171: 38.9 | E171: 46.1 | F171: 58 | G171: 53.6 | H171: 52 | I171: 54.4 | J171: 48.7 | K171: 34.8 | L171: 90.3 | M171: 42.3 | N171: 54.6 | O171: 45.1 | P171: 47.8 | Q171: 40.2 | R171: 44.5 | W171: 48.7 | X171: 42.4 | AB171: 49.2 | AD171: 59.9 | AF171: 44 | AG171: 45.3 | AH171: 42.4 | AI171: 29 | AJ171: 44.6 | AK171: 36.5 | AL171: 59.2 | AM171: 39.6 | AN171: 13.6 | AO171: 13.6 | AP171: 79.5 | AU171: 96.8 | AV171: 113.8 | AW171: 91.9 | AX171: 82.3 | BA171: 41.9 | BB171: 46.6 | BC171: 43.4 | BD171: 43.4 | BH171: 50.8 | BJ171: 34.7 | BL171: 32.9 | BN171: 76.1 | BO171: 72.3 | BP171: 79.6 | BQ171: 50.8 | BR171: 84.6 | BS171: 84.6 | BU171: 101.3 | BV171: 101.4 | BX171: 81.1 | BZ171: 67.8 | CA171: 68.2 | CD171: 55.2 | CE171: 46.4 | CH171: 53.4 | CI171: 52.4 | CJ171: 57.2 | CK171: 29.3 | CL171: 28 | CM171: 33.3 | CN171: 52.4 | CO171: 54.2 | CP171: 101.2 | CQ171: 67 | CR171: 34.3 | CS171: 56.6 | CT171: 43.9 | CU171: 36.4 | CV171: 36.4 | CW171: 88.5 | CX171: 88.5 | CY171: 50.9 | CZ171: 92.2 | DC171: 1036.2 | DH171: 55.7 | DI171: 52 | DJ171: 59.9 | DN171: 44.4 | DO171: 34.8 | DR171: 24.4 | DS171: 24.4 | EC171: 50.3 | EF171: 53.5 | EG171: 45.8 | EH171: 50.3 | EI171: 51.3 | EJ171: 52.7 | EK171: 49.1 | EL171: 51.7 | EM171: 47.7 | EO171: 50 | EU171: 51.2 | EX171: 46.2 | EY171: 41.7 | EZ171: 33.3 | FA171: 46.1 | FB171: 57.5 | FC171: 49.6 | FD171: 56.8 | FE171: 56.6 | FF171: 55.4 | FG171: 35.2 | FH171: 95.7 | FI171: 45.6 | FJ171: 64.9 | FK171: 45 | FL171: 45.5 | FM171: 46.7 | FN171: 45.1 | FS171: 53.1 | FT171: 46.4 | FX171: 51.6 | FZ171: 61.8 | GB171: 42.9 | GC171: 44.6 | GD171: 40.9 | GE171: 28.8 | GF171: 46 | GG171: 39.6 | GH171: 63.5 | GI171: 39.5 | GJ171: 13 | GK171: 13 | GL171: 85.2 | GQ171: 90.2 | GR171: 97 | GS171: 84.9 | GT171: 98 | GW171: 45.7 | GX171: 53 | GY171: 47.8 | GZ171: 47.8 | HD171: 47.5 | HF171: 33.2 | HH171: 33.9 | HJ171: 71.9 | HK171: 63.6 | HL171: 63.5 | HM171: 61.4 | HN171: 90.4 | HO171: 90.4 | HQ171: 95.5 | HR171: 102.7 | HT171: 85.2 | HV171: 66.1 | HW171: 65.9 | HZ171: 37.2 | IA171: 43.7 | ID171: 56 | IE171: 55.2 | IF171: 57.2 | IG171: 26.2 | IH171: 24.9 | II171: 33.5 | IJ171: 53.3 | IK171: 54.8 | IL171: 101.3 | IM171: 64.9 | IN171: 35.5 | IO171: 55.8 | IP171: 27.5 | IQ171: 33.9
A172: 32478 | B172: 46.5 | C172: 45.7 | D172: 40.1 | E172: 47.9 | F172: 61.6 | G172: 56.7 | H172: 53 | I172: 55.2 | J172: 50.1 | K172: 32.7 | L172: 91.4 | M172: 42 | N172: 61.8 | O172: 46.7 | P172: 48.7 | Q172: 43.9 | R172: 45.8 | W172: 48.8 | X172: 43 | AB172: 50.4 | AD172: 60.4 | AF172: 45.2 | AG172: 45.8 | AH172: 44.3 | AI172: 28.9 | AJ172: 44 | AK172: 37.3 | AL172: 60.1 | AM172: 38.2 | AN172: 14 | AO172: 14 | AP172: 81.6 | AU172: 98.4 | AV172: 117 | AW172: 92 | AX172: 85.1 | BA172: 42.9 | BB172: 50.3 | BC172: 44.5 | BD172: 44.5 | BH172: 52.2 | BJ172: 34.7 | BL172: 32.9 | BN172: 77.1 | BO172: 73.1 | BP172: 80 | BQ172: 52.1 | BR172: 85.2 | BS172: 85.2 | BU172: 102.6 | BV172: 102.7 | BX172: 84.1 | BZ172: 68.4 | CA172: 66.2 | CD172: 55.9 | CE172: 47 | CH172: 49.4 | CI172: 47.4 | CJ172: 57.2 | CK172: 30.9 | CL172: 29.7 | CM172: 34.5 | CN172: 52.5 | CO172: 54.2 | CP172: 102.2 | CQ172: 68.7 | CR172: 33.2 | CS172: 57.4 | CT172: 43.9 | CU172: 37.1 | CV172: 37.1 | CW172: 90.7 | CX172: 90.7 | CY172: 53.2 | CZ172: 94.3 | DC172: 1041 | DH172: 59.5 | DI172: 56.1 | DJ172: 63.4 | DN172: 46 | DO172: 35 | DR172: 24.4 | DS172: 24.4 | EC172: 51.6 | EF172: 54.1 | EG172: 48.1 | EH172: 51.6 | EI172: 52.7 | EJ172: 54.1 | EK172: 50.3 | EL172: 52.5 | EM172: 48.9 | EO172: 51.5 | EU172: 52.4 | EX172: 46.9 | EY172: 43.3 | EZ172: 35.3 | FA172: 47.5 | FB172: 58.8 | FC172: 51 | FD172: 57.7 | FE172: 56.2 | FF172: 58.3 | FG172: 32.5 | FH172: 99.8 | FI172: 46.9 | FJ172: 70.9 | FK172: 46.2 | FL172: 46.3 | FM172: 48.8 | FN172: 47.6 | FS172: 53.2 | FT172: 46.8 | FX172: 54.3 | FZ172: 61.4 | GB172: 43.4 | GC172: 45.6 | GD172: 41 | GE172: 28.8 | GF172: 45.5 | GG172: 40.2 | GH172: 63.8 | GI172: 38.4 | GJ172: 13.4 | GK172: 13.4 | GL172: 88.3 | GQ172: 95.2 | GR172: 98.8 | GS172: 93.8 | GT172: 98.7 | GW172: 47 | GX172: 56 | GY172: 48.8 | GZ172: 48.8 | HD172: 48.7 | HF172: 33.6 | HH172: 34.4 | HJ172: 72.9 | HK172: 63.6 | HL172: 62.9 | HM172: 62.3 | HN172: 91.8 | HO172: 91.8 | HQ172: 97.9 | HR172: 105.2 | HT172: 87.9 | HV172: 67.4 | HW172: 63.7 | HZ172: 37.5 | IA172: 44.7 | ID172: 52.1 | IE172: 50.4 | IF172: 57.1 | IG172: 26.9 | IH172: 25.6 | II172: 34 | IJ172: 53.4 | IK172: 54.9 | IL172: 102.5 | IM172: 66.4 | IN172: 34.5 | IO172: 56.7 | IP172: 27.5 | IQ172: 34.1
A173: 32568 | B173: 47.1 | C173: 46.1 | D173: 41.1 | E173: 48.1 | F173: 58.8 | G173: 58.3 | H173: 54.2 | I173: 57 | J173: 51.2 | K173: 33.8 | L173: 91.5 | M173: 42.1 | N173: 64.1 | O173: 48.1 | P173: 51.3 | Q173: 43.5 | R173: 46.2 | W173: 49.5 | X173: 42.8 | AB173: 52 | AD173: 61 | AF173: 45.7 | AG173: 46 | AH173: 45.1 | AI173: 29.2 | AJ173: 44.5 | AK173: 38 | AL173: 60.2 | AM173: 38.6 | AN173: 14.2 | AO173: 14.2 | AP173: 81.5 | AU173: 97.2 | AV173: 114.4 | AW173: 92.3 | AX173: 82.3 | BA173: 45.1 | BB173: 48.2 | BC173: 45.7 | BD173: 45.7 | BH173: 51.4 | BJ173: 34.7 | BL173: 32.9 | BN173: 77.5 | BO173: 73.7 | BP173: 80.4 | BQ173: 53.1 | BR173: 87.7 | BS173: 87.7 | BU173: 103.3 | BV173: 103.4 | BX173: 83.5 | BZ173: 69.3 | CA173: 67 | CD173: 59.5 | CE173: 47.8 | CH173: 58.5 | CI173: 58.4 | CJ173: 58.4 | CK173: 32.1 | CL173: 30.9 | CM173: 35.7 | CN173: 52.6 | CO173: 54.4 | CP173: 103.6 | CQ173: 68.7 | CR173: 32.2 | CS173: 58.6 | CT173: 44.1 | CU173: 36.9 | CV173: 36.9 | CW173: 89.6 | CX173: 89.6 | CY173: 54.2 | CZ173: 92.9 | DC173: 1027.6 | DH173: 57 | DI173: 54.7 | DJ173: 59.7 | DN173: 45.7 | DO173: 36.9 | DR173: 27.2 | DS173: 27.2 | EC173: 51.7 | EF173: 54.5 | EG173: 47.6 | EH173: 51.7 | EI173: 52.6 | EJ173: 54.2 | EK173: 50.4 | EL173: 53 | EM173: 49 | EO173: 51.5 | EU173: 52.5 | EX173: 47.3 | EY173: 43.8 | EZ173: 36.1 | FA173: 48 | FB173: 56.9 | FC173: 52.2 | FD173: 59.3 | FE173: 57.6 | FF173: 59.4 | FG173: 34.3 | FH173: 102.6 | FI173: 47.9 | FJ173: 73.4 | FK173: 46.5 | FL173: 46.8 | FM173: 48.4 | FN173: 47.3 | FS173: 52.7 | FT173: 46.9 | FX173: 55.4 | FZ173: 62.8 | GB173: 44.7 | GC173: 45.8 | GD173: 43 | GE173: 29.2 | GF173: 46.1 | GG173: 41.1 | GH173: 64 | GI173: 38.9 | GJ173: 13.5 | GK173: 13.5 | GL173: 88.3 | GQ173: 95.4 | GR173: 99.2 | GS173: 93.7 | GT173: 99.1 | GW173: 47.4 | GX173: 56.7 | GY173: 49.8 | GZ173: 49.8 | HD173: 48.7 | HF173: 33.6 | HH173: 34.4 | HJ173: 73.4 | HK173: 64.8 | HL173: 64.3 | HM173: 63.1 | HN173: 93.3 | HO173: 93.3 | HQ173: 98.5 | HR173: 105.8 | HT173: 84 | HV173: 68.3 | HW173: 64.4 | HZ173: 38.3 | IA173: 45.3 | ID173: 61.7 | IE173: 62.1 | IF173: 57.8 | IG173: 28.2 | IH173: 27 | II173: 35.1 | IJ173: 54.3 | IK173: 55.9 | IL173: 104.2 | IM173: 66.6 | IN173: 35.5 | IO173: 57.7 | IP173: 27.7 | IQ173: 34.3
A174: 32660 | B174: 48.7 | C174: 46.3 | D174: 40.8 | E174: 48.7 | F174: 60.1 | G174: 58.3 | H174: 55.7 | I174: 60 | J174: 51.3 | K174: 35.6 | L174: 95.2 | M174: 42.9 | N174: 63 | O174: 47.8 | P174: 49.5 | Q174: 45.4 | R174: 47.2 | W174: 50 | X174: 44.2 | AB174: 51.5 | AD174: 60.4 | AF174: 46.7 | AG174: 46.7 | AH174: 46.2 | AI174: 29.8 | AJ174: 45.4 | AK174: 39.2 | AL174: 61.7 | AM174: 39.2 | AN174: 14.4 | AO174: 14.4 | AP174: 84 | AU174: 102 | AV174: 116.1 | AW174: 99.2 | AX174: 85.7 | BA174: 47.1 | BB174: 50.9 | BC174: 46.6 | BD174: 46.6 | BH174: 52.7 | BJ174: 34.7 | BL174: 32.9 | BN174: 78.2 | BO174: 74.2 | BP174: 80.6 | BQ174: 53.8 | BR174: 89.9 | BS174: 89.9 | BU174: 101.2 | BV174: 101.3 | BX174: 85.3 | BZ174: 70.1 | CA174: 67 | CD174: 60 | CE174: 47.5 | CH174: 58.1 | CI174: 57.8 | CJ174: 59 | CK174: 32.3 | CL174: 31.1 | CM174: 36.1 | CN174: 53.8 | CO174: 55.7 | CP174: 103.7 | CQ174: 69.5 | CR174: 35.5 | CS174: 58.4 | CT174: 44.4 | CU174: 36.9 | CV174: 36.9 | CW174: 87.7 | CX174: 87.7 | CY174: 55 | CZ174: 90.6 | DC174: 1003.7 | DH174: 59 | DI174: 55.2 | DJ174: 63.4 | DN174: 45.8 | DO174: 37.6 | DR174: 27.2 | DS174: 27.2 | EC174: 52.9 | EF174: 55.7 | EG174: 49 | EH174: 53 | EI174: 53.8 | EJ174: 55.6 | EK174: 51.7 | EL174: 54 | EM174: 50.4 | EO174: 52.9 | EU174: 53.8 | EX174: 49.1 | EY174: 44 | EZ174: 36.9 | FA174: 47.9 | FB174: 57 | FC174: 50.6 | FD174: 62 | FE174: 62.2 | FF174: 59.8 | FG174: 36.8 | FH174: 109.3 | FI174: 48.9 | FJ174: 72.6 | FK174: 47.3 | FL174: 47.7 | FM174: 48.3 | FN174: 50.5 | FS174: 53.8 | FT174: 47.2 | FX174: 54.9 | FZ174: 61.2 | GB174: 45.8 | GC174: 46.7 | GD174: 44.5 | GE174: 29.9 | GF174: 47.3 | GG174: 42.6 | GH174: 66.4 | GI174: 39.7 | GJ174: 13.8 | GK174: 13.8 | GL174: 90.1 | GQ174: 97.9 | GR174: 101.1 | GS174: 97.1 | GT174: 100.4 | GW174: 47.8 | GX174: 59.9 | GY174: 50.6 | GZ174: 50.6 | HD174: 50.6 | HF174: 33.6 | HH174: 34.4 | HJ174: 74.5 | HK174: 67.3 | HL174: 67.7 | HM174: 63.4 | HN174: 94.3 | HO174: 94.3 | HQ174: 99.1 | HR174: 106.5 | HT174: 87.6 | HV174: 69.1 | HW174: 63.8 | HZ174: 40.1 | IA174: 46 | ID174: 60.7 | IE174: 60.9 | IF174: 57.6 | IG174: 28.6 | IH174: 27.4 | II174: 35.7 | IJ174: 55.6 | IK174: 57.4 | IL174: 105.1 | IM174: 68.1 | IN174: 38.1 | IO174: 57.4 | IP174: 28.5 | IQ174: 34.4
A175: 32752 | B175: 50 | C175: 48 | D175: 42.7 | E175: 50.4 | F175: 60.9 | G175: 61 | H175: 56.7 | I175: 61.7 | J175: 52.2 | K175: 35.7 | L175: 92.8 | M175: 44.2 | N175: 64.7 | O175: 47.7 | P175: 48.7 | Q175: 46.1 | R175: 47.8 | S175: 57 | T175: 44.5 | U175: 68.8 | V175: 44 | W175: 43.4 | X175: 44.5 | Y175: 58.8 | Z175: 48.8 | AA175: 42.5 | AB175: 53.5 | AC175: 50.4 | AD175: 62.1 | AE175: 49 | AF175: 47.5 | AG175: 48.3 | AH175: 46.4 | AI175: 30.6 | AJ175: 46.1 | AK175: 40 | AL175: 62.8 | AM175: 39.7 | AN175: 15.1 | AO175: 15.1 | AP175: 84.2 | AQ175: 87.9 | AR175: 92.5 | AS175: 84.8 | AT175: 91.6 | AU175: 101.6 | AV175: 115.7 | AW175: 99 | AX175: 84.9 | BA175: 47.5 | BB175: 53.7 | BC175: 47.6 | BD175: 47.6 | BH175: 52.9 | BJ175: 35.9 | BL175: 34 | BM175: 34.9 | BN175: 79.2 | BO175: 74.3 | BP175: 81.1 | BQ175: 53.4 | BR175: 90.5 | BS175: 90.5 | BT175: 97.7 | BU175: 104.4 | BV175: 104.5 | BW175: 101.3 | BX175: 85.7 | BY175: 70.8 | BZ175: 71.3 | CA175: 69.2 | CB175: 67.1 | CC175: 40.6 | CD175: 60.9 | CE175: 48.3 | CF175: 35.8 | CG175: 37.2 | CH175: 56.2 | CI175: 55.3 | CJ175: 59.8 | CK175: 32.7 | CL175: 31.3 | CM175: 36.7 | CN175: 56.2 | CO175: 58 | CP175: 105.1 | CQ175: 69.1 | CR175: 36.6 | CS175: 58.5 | CT175: 45.2 | CU175: 40.2 | CV175: 40.2 | CW175: 87.8 | CX175: 87.8 | CY175: 55.8 | CZ175: 90.4 | DA175: 71.1 | DB175: 248.5 | DC175: 976.9 | DD175: 110.7 | DE175: 49.1 | DH175: 60 | DI175: 56.7 | DJ175: 63.9 | DK175: 49.1 | DN175: 46.4 | DO175: 37.7 | DR175: 27.2 | DS175: 27.2 | DX175: 28 | DY175: 28 | EC175: 54.4 | EF175: 56.6 | EG175: 51.2 | EH175: 54.4 | EI175: 55.3 | EJ175: 57.1 | EK175: 53.2 | EL175: 55.2 | EM175: 51.9 | EN175: 55.6 | EO175: 54.1 | EP175: 53.9 | EQ175: 52.7 | ER175: 55 | ES175: 52.4 | ET175: 55.2 | EU175: 55.3 | EV175: 57.3 | EX175: 50.6 | EY175: 44.5 | EZ175: 37.5 | FA175: 48.1 | FB175: 56.6 | FC175: 53.1 | FD175: 62.8 | FE175: 63.6 | FF175: 60.3 | FG175: 37.1 | FH175: 107.7 | FI175: 49.9 | FJ175: 73.1 | FK175: 47.2 | FL175: 47.7 | FM175: 48 | FN175: 51 | FO175: 56.8 | FP175: 43 | FQ175: 68.2 | FR175: 44.6 | FS175: 54.3 | FT175: 47.2 | FU175: 60.3 | FV175: 53.6 | FW175: 43.1 | FX175: 56.1 | FY175: 54.6 | FZ175: 60.3 | GA175: 52.8 | GB175: 46.5 | GC175: 48.3 | GD175: 44.3 | GE175: 30.6 | GF175: 48.2 | GG175: 43.3 | GH175: 67.5 | GI175: 40.4 | GJ175: 14.3 | GK175: 14.3 | GL175: 90.7 | GM175: 96.9 | GN175: 96.4 | GO175: 98.5 | GP175: 91.3 | GQ175: 97.1 | GR175: 98.2 | GS175: 97 | GT175: 101 | GW175: 48.6 | GX175: 63.2 | GY175: 51.8 | GZ175: 51.8 | HD175: 51.1 | HF175: 34.5 | HH175: 35.3 | HI175: 38.9 | HJ175: 75.7 | HK175: 68.6 | HL175: 68.9 | HM175: 64.9 | HN175: 98.6 | HO175: 98.6 | HP175: 101.9 | HQ175: 100.2 | HR175: 107.7 | HS175: 115 | HT175: 86.3 | HU175: 67.9 | HV175: 68.7 | HW175: 65.4 | HX175: 64.9 | HY175: 45.7 | HZ175: 42.8 | IA175: 47.3 | IB175: 41.5 | IC175: 33.6 | ID175: 58.4 | IE175: 58 | IF175: 57.9 | IG175: 29.1 | IH175: 27.7 | II175: 37 | IJ175: 56.1 | IK175: 57.8 | IL175: 106.4 | IM175: 68.8 | IN175: 38.3 | IO175: 58.6 | IP175: 21.8 | IQ175: 35.2
A176: 32843 | B176: 50 | C176: 48.3 | D176: 43.6 | E176: 50 | F176: 63 | G176: 58.3 | H176: 56.9 | I176: 61.3 | J176: 53.5 | K176: 35.3 | L176: 98.3 | M176: 45.2 | N176: 62.3 | O176: 50 | P176: 50.6 | Q176: 49.1 | R176: 51.4 | S176: 52.3 | T176: 43.9 | U176: 60.5 | V176: 44.9 | W176: 42.8 | X176: 45.8 | Y176: 60.6 | Z176: 49.4 | AA176: 43.4 | AB176: 55.1 | AC176: 52 | AD176: 60.6 | AE176: 50.6 | AF176: 48 | AG176: 48.2 | AH176: 47.4 | AI176: 31.2 | AJ176: 46.9 | AK176: 40.8 | AL176: 63 | AM176: 40.6 | AN176: 15.5 | AO176: 15.5 | AP176: 85.7 | AQ176: 89.7 | AR176: 94 | AS176: 87 | AT176: 92.7 | AU176: 101.8 | AV176: 120 | AW176: 96.6 | AX176: 86.3 | BA176: 47.6 | BB176: 55.7 | BC176: 48.1 | BD176: 48.1 | BH176: 53.6 | BJ176: 36 | BL176: 34 | BM176: 36.2 | BN176: 80.2 | BO176: 75 | BP176: 81.6 | BQ176: 54.5 | BR176: 92.1 | BS176: 92.1 | BT176: 98.7 | BU176: 105.2 | BV176: 105.3 | BW176: 101.7 | BX176: 87.5 | BY176: 71.2 | BZ176: 74.2 | CA176: 69.2 | CB176: 66.6 | CC176: 40.4 | CD176: 61.4 | CE176: 48.9 | CF176: 35.5 | CG176: 37.3 | CH176: 53.8 | CI176: 52.2 | CJ176: 60.2 | CK176: 33.1 | CL176: 31.7 | CM176: 37.7 | CN176: 57.8 | CO176: 59.7 | CP176: 106.6 | CQ176: 71 | CR176: 39.1 | CS176: 60.1 | CT176: 46.9 | CU176: 41 | CV176: 41 | CW176: 88.5 | CX176: 88.5 | CY176: 57.8 | CZ176: 90.8 | DA176: 73.1 | DB176: 250 | DC176: 975 | DD176: 111.4 | DE176: 49.2 | DH176: 63.4 | DI176: 60 | DJ176: 67.4 | DK176: 48.6 | DN176: 45.5 | DO176: 38.1 | DR176: 27.2 | DS176: 27.2 | DX176: 27.8 | DY176: 27.8 | EC176: 55.4 | EF176: 57.3 | EG176: 52.7 | EH176: 55.4 | EI176: 56.6 | EJ176: 58.1 | EK176: 54.1 | EL176: 56 | EM176: 53 | EN176: 56.7 | EO176: 55 | EP176: 54.9 | EQ176: 53.6 | ER176: 56.1 | ES176: 53.3 | ET176: 56 | EU176: 56.3 | EV176: 58.5 | EX176: 50.9 | EY176: 46.1 | EZ176: 38.5 | FA176: 49.8 | FB176: 59.9 | FC176: 55.2 | FD176: 62.8 | FE176: 63.4 | FF176: 63.1 | FG176: 35.2 | FH176: 107.6 | FI176: 51.5 | FJ176: 71.6 | FK176: 48.2 | FL176: 48.2 | FM176: 49.5 | FN176: 53 | FO176: 53.8 | FP176: 40.9 | FQ176: 64.3 | FR176: 45.7 | FS176: 53.7 | FT176: 48.9 | FU176: 62.3 | FV176: 56.8 | FW176: 44.3 | FX176: 59 | FY176: 55.4 | FZ176: 59.2 | GA176: 53.6 | GB176: 47.4 | GC176: 48.5 | GD176: 45.8 | GE176: 31.3 | GF176: 48.9 | GG176: 44 | GH176: 67 | GI176: 41.3 | GJ176: 14.9 | GK176: 14.9 | GL176: 92.7 | GM176: 99.5 | GN176: 98 | GO176: 101.3 | GP176: 94.4 | GQ176: 98.2 | GR176: 101.5 | GS176: 97 | GT176: 101.6 | GW176: 51.7 | GX176: 64.9 | GY176: 52.7 | GZ176: 52.7 | HD176: 52.2 | HF176: 35.3 | HH176: 36.1 | HI176: 39.9 | HJ176: 77.4 | HK176: 71 | HL176: 71.6 | HM176: 66.4 | HN176: 98.9 | HO176: 98.9 | HP176: 103.2 | HQ176: 101.6 | HR176: 109.2 | HS176: 114.5 | HT176: 88.7 | HU176: 69.4 | HV176: 71.1 | HW176: 65.9 | HX176: 66.1 | HY176: 47 | HZ176: 43.3 | IA176: 48.7 | IB176: 42.6 | IC176: 33.3 | ID176: 55.1 | IE176: 53.9 | IF176: 58.2 | IG176: 29.1 | IH176: 27.6 | II176: 37.5 | IJ176: 57.5 | IK176: 59.2 | IL176: 108.6 | IM176: 67.2 | IN176: 40 | IO176: 59.3 | IP176: 21.8 | IQ176: 36.1
A177: 32933 | B177: 50.6 | C177: 50 | D177: 45 | E177: 51.9 | F177: 65.3 | G177: 59.1 | H177: 57.8 | I177: 63.3 | J177: 53.2 | K177: 36.4 | L177: 97.4 | M177: 46 | N177: 62.8 | O177: 50.8 | P177: 51.3 | Q177: 50.8 | R177: 50.9 | S177: 49.6 | T177: 48.1 | U177: 51.8 | V177: 46.2 | W177: 41.6 | X177: 46.3 | Y177: 61.2 | Z177: 49.4 | AA177: 44.5 | AB177: 54.6 | AC177: 52.5 | AD177: 61.5 | AE177: 51.1 | AF177: 49.3 | AG177: 49.8 | AH177: 48.4 | AI177: 31.7 | AJ177: 47.4 | AK177: 41.3 | AL177: 62.6 | AM177: 41.3 | AN177: 16 | AO177: 16 | AP177: 85.7 | AQ177: 89.5 | AR177: 93 | AS177: 87.2 | AT177: 91.9 | AU177: 101.9 | AV177: 118.4 | AW177: 97.2 | AX177: 87.2 | BA177: 48.8 | BB177: 56.6 | BC177: 48.5 | BD177: 48.5 | BH177: 54.6 | BJ177: 36 | BL177: 34 | BM177: 36.4 | BN177: 81.5 | BO177: 76.2 | BP177: 82.6 | BQ177: 55.6 | BR177: 94.6 | BS177: 94.6 | BT177: 100.1 | BU177: 105.4 | BV177: 105.5 | BW177: 106.9 | BX177: 87.1 | BY177: 72.7 | BZ177: 74.3 | CA177: 70.8 | CB177: 67.6 | CC177: 41 | CD177: 65.6 | CE177: 50.7 | CF177: 36.1 | CG177: 39 | CH177: 61.7 | CI177: 61.8 | CJ177: 60.7 | CK177: 33.7 | CL177: 32.2 | CM177: 38.3 | CN177: 59.4 | CO177: 61.5 | CP177: 107.9 | CQ177: 71.6 | CR177: 42.1 | CS177: 60.6 | CT177: 48.1 | CU177: 41.2 | CV177: 41.2 | CW177: 88.7 | CX177: 88.7 | CY177: 58.1 | CZ177: 91.1 | DA177: 73.5 | DB177: 252.8 | DC177: 954.9 | DD177: 112.6 | DE177: 50.7 | DH177: 63.4 | DI177: 59.8 | DJ177: 67.6 | DK177: 51.9 | DN177: 49.2 | DO177: 40.9 | DR177: 30.8 | DS177: 30.8 | DX177: 27.9 | DY177: 27.9 | EC177: 56.3 | EF177: 58.2 | EG177: 53.7 | EH177: 56.4 | EI177: 57.7 | EJ177: 59.1 | EK177: 55.2 | EL177: 57 | EM177: 53.9 | EN177: 57.5 | EO177: 55.9 | EP177: 55.8 | EQ177: 54.5 | ER177: 57 | ES177: 54.1 | ET177: 57 | EU177: 57.3 | EV177: 59.5 | EX177: 50.3 | EY177: 46.8 | EZ177: 39.2 | FA177: 50.5 | FB177: 60.3 | FC177: 56 | FD177: 63.4 | FE177: 63.8 | FF177: 62 | FG177: 37.5 | FH177: 108 | FI177: 52.2 | FJ177: 70.6 | FK177: 49.8 | FL177: 49.8 | FM177: 51.9 | FN177: 52.9 | FO177: 41.9 | FP177: 40.1 | FQ177: 43.5 | FR177: 47.1 | FS177: 51.9 | FT177: 50.2 | FU177: 62.6 | FV177: 56.1 | FW177: 45.7 | FX177: 60.1 | FY177: 56.8 | FZ177: 61.9 | GA177: 54.9 | GB177: 48.4 | GC177: 49.3 | GD177: 47 | GE177: 32 | GF177: 49.9 | GG177: 45.1 | GH177: 67.2 | GI177: 42.5 | GJ177: 15.3 | GK177: 15.3 | GL177: 93 | GM177: 99.5 | GN177: 98.6 | GO177: 101.5 | GP177: 92.1 | GQ177: 98.6 | GR177: 102 | GS177: 97.2 | GT177: 102.5 | GW177: 53.2 | GX177: 66.4 | GY177: 53.8 | GZ177: 53.8 | HD177: 52.2 | HF177: 35.4 | HH177: 36.1 | HI177: 39.9 | HJ177: 78.7 | HK177: 73.9 | HL177: 74.6 | HM177: 68.7 | HN177: 100.1 | HO177: 100.1 | HP177: 104.1 | HQ177: 101.6 | HR177: 109.2 | HS177: 116.5 | HT177: 90 | HU177: 70.1 | HV177: 72.5 | HW177: 68.8 | HX177: 65.3 | HY177: 47.5 | HZ177: 46.1 | IA177: 48.9 | IB177: 43.1 | IC177: 34.5 | ID177: 63.3 | IE177: 63.9 | IF177: 58.6 | IG177: 29.4 | IH177: 27.9 | II177: 38.1 | IJ177: 59 | IK177: 60.7 | IL177: 108.6 | IM177: 69.9 | IN177: 42.6 | IO177: 60.8 | IP177: 22.4 | IQ177: 37.2
A178: 33025 | B178: 51.8 | C178: 51.3 | D178: 46 | E178: 54.1 | F178: 64.6 | G178: 59.6 | H178: 58 | I178: 65 | J178: 52.7 | K178: 37.3 | L178: 97.2 | M178: 45.5 | N178: 60.3 | O178: 52.1 | P178: 52 | Q178: 52.9 | R178: 53.9 | S178: 53.8 | T178: 47.6 | U178: 60.1 | V178: 46.4 | W178: 41.7 | X178: 45.2 | Y178: 63.4 | Z178: 49.9 | AA178: 44.8 | AB178: 55.4 | AC178: 54.7 | AD178: 63.3 | AE178: 53.2 | AF178: 50.1 | AG178: 50.7 | AH178: 49.2 | AI178: 32.3 | AJ178: 48.1 | AK178: 42.4 | AL178: 61.7 | AM178: 42.1 | AN178: 16.4 | AO178: 16.4 | AP178: 87.6 | AQ178: 91.5 | AR178: 96.3 | AS178: 88.4 | AT178: 95.3 | AU178: 103.2 | AV178: 123.5 | AW178: 98.4 | AX178: 83.7 | BA178: 51.5 | BB178: 57.4 | BC178: 49 | BD178: 49 | BH178: 55.9 | BJ178: 36.1 | BL178: 34 | BM178: 36.6 | BN178: 82.5 | BO178: 77.8 | BP178: 84.7 | BQ178: 56.5 | BR178: 97.9 | BS178: 97.9 | BT178: 101.3 | BU178: 105.2 | BV178: 105.3 | BW178: 109.9 | BX178: 88.4 | BY178: 73.8 | BZ178: 74.3 | CA178: 72 | CB178: 69.1 | CC178: 42.8 | CD178: 66.3 | CE178: 52 | CF178: 37.7 | CG178: 39.2 | CH178: 60.9 | CI178: 60.8 | CJ178: 61.2 | CK178: 34.1 | CL178: 32.3 | CM178: 39.8 | CN178: 59.7 | CO178: 61.8 | CP178: 107.8 | CQ178: 72.7 | CR178: 42.1 | CS178: 62.3 | CT178: 48.3 | CU178: 41.3 | CV178: 41.3 | CW178: 88.8 | CX178: 88.8 | CY178: 58.3 | CZ178: 91.1 | DA178: 74.2 | DB178: 252.5 | DC178: 917.7 | DD178: 112.5 | DE178: 50 | DH178: 63.6 | DI178: 59.8 | DJ178: 68.2 | DK178: 52.5 | DN178: 50 | DO178: 41.1 | DR178: 30.8 | DS178: 30.8 | DX178: 28.2 | DY178: 28.2 | EC178: 57.2 | EF178: 59.1 | EG178: 54.5 | EH178: 57.3 | EI178: 58.3 | EJ178: 60 | EK178: 55.9 | EL178: 57.8 | EM178: 54.7 | EN178: 58.5 | EO178: 56.9 | EP178: 56.7 | EQ178: 55.5 | ER178: 57.9 | ES178: 55 | ET178: 57.9 | EU178: 58.2 | EV178: 60.3 | EX178: 52.2 | EY178: 48.1 | EZ178: 40 | FA178: 52.6 | FB178: 61.3 | FC178: 56.5 | FD178: 64.5 | FE178: 65.1 | FF178: 63.2 | FG178: 40.1 | FH178: 106.2 | FI178: 52.9 | FJ178: 70.6 | FK178: 50.5 | FL178: 50.1 | FM178: 53.7 | FN178: 53.2 | FO178: 48 | FP178: 43.4 | FQ178: 52 | FR178: 47.6 | FS178: 52.2 | FT178: 51.4 | FU178: 65.3 | FV178: 57.4 | FW178: 46.1 | FX178: 59.9 | FY178: 59.2 | FZ178: 62.3 | GA178: 57.2 | GB178: 50.1 | GC178: 51.4 | GD178: 48.2 | GE178: 32.5 | GF178: 50.5 | GG178: 46.2 | GH178: 66 | GI178: 43.3 | GJ178: 15.7 | GK178: 15.7 | GL178: 95 | GM178: 102 | GN178: 101.9 | GO178: 103 | GP178: 97.8 | GQ178: 99.5 | GR178: 103.1 | GS178: 97.9 | GT178: 103.8 | GW178: 54.3 | GX178: 67.9 | GY178: 54.6 | GZ178: 54.6 | HD178: 53.6 | HF178: 35.4 | HH178: 36.1 | HI178: 40 | HJ178: 80 | HK178: 76.1 | HL178: 77.7 | HM178: 68.6 | HN178: 101.1 | HO178: 101.1 | HP178: 104.7 | HQ178: 102.6 | HR178: 110.3 | HS178: 116 | HT178: 90.8 | HU178: 71.3 | HV178: 75 | HW178: 70.6 | HX178: 66 | HY178: 50.1 | HZ178: 47.4 | IA178: 50.2 | IB178: 45.5 | IC178: 34.8 | ID178: 63.5 | IE178: 63.9 | IF178: 59.7 | IG178: 29.7 | IH178: 28.2 | II178: 38.7 | IJ178: 59.2 | IK178: 60.9 | IL178: 108 | IM178: 70.4 | IN178: 42.6 | IO178: 62.3 | IP178: 22.4 | IQ178: 37.3
A179: 33117 | B179: 51.2 | C179: 51.8 | D179: 46.7 | E179: 54.2 | F179: 67 | G179: 60.4 | H179: 57.5 | I179: 65.2 | J179: 52.8 | K179: 36.6 | L179: 86.5 | M179: 45.5 | N179: 62.5 | O179: 52.6 | P179: 53.1 | Q179: 52.9 | R179: 53.4 | S179: 46 | T179: 44.4 | U179: 48.4 | V179: 47.6 | W179: 42.2 | X179: 48.4 | Y179: 63.9 | Z179: 50 | AA179: 46 | AB179: 56.7 | AC179: 53.9 | AD179: 63.1 | AE179: 52.4 | AF179: 50.8 | AG179: 51.6 | AH179: 49.8 | AI179: 32.8 | AJ179: 49 | AK179: 43.3 | AL179: 62.3 | AM179: 43 | AN179: 16.6 | AO179: 16.6 | AP179: 88.2 | AQ179: 92 | AR179: 97.5 | AS179: 88.5 | AT179: 95.7 | AU179: 104.1 | AV179: 126.7 | AW179: 98 | AX179: 84.4 | BA179: 51.9 | BB179: 57.8 | BC179: 49.7 | BD179: 49.7 | BH179: 56.7 | BJ179: 30.5 | BL179: 27.8 | BM179: 38.2 | BN179: 82 | BO179: 78.4 | BP179: 85 | BQ179: 57.4 | BR179: 99.9 | BS179: 99.9 | BT179: 102 | BU179: 106.8 | BV179: 106.9 | BW179: 108.5 | BX179: 89.5 | BY179: 75.7 | BZ179: 76.6 | CA179: 73 | CB179: 70.8 | CC179: 44.3 | CD179: 67.3 | CE179: 52.5 | CF179: 39 | CG179: 39.5 | CH179: 59.6 | CI179: 58.8 | CJ179: 62.7 | CK179: 34.7 | CL179: 32.7 | CM179: 41 | CN179: 61.4 | CO179: 63.3 | CP179: 106 | CQ179: 72.7 | CR179: 45.1 | CS179: 63 | CT179: 49.3 | CU179: 44.8 | CV179: 44.8 | CW179: 90.8 | CX179: 90.8 | CY179: 59.2 | CZ179: 93.3 | DA179: 74.7 | DB179: 257.5 | DC179: 918.6 | DD179: 114.9 | DE179: 50.3 | DH179: 63.8 | DI179: 59.8 | DJ179: 68.4 | DK179: 53.4 | DN179: 51.1 | DO179: 41.6 | DR179: 30.8 | DS179: 30.8 | DX179: 29.8 | DY179: 29.8 | EC179: 57.6 | EF179: 59.1 | EG179: 55.3 | EH179: 57.6 | EI179: 58.9 | EJ179: 60.3 | EK179: 56.3 | EL179: 58.2 | EM179: 55.1 | EN179: 58.8 | EO179: 56.9 | EP179: 57 | EQ179: 55.8 | ER179: 58.2 | ES179: 55.3 | ET179: 58.1 | EU179: 58.5 | EV179: 61 | EX179: 51.8 | EY179: 48.5 | EZ179: 40.7 | FA179: 52.3 | FB179: 63 | FC179: 57.7 | FD179: 64.1 | FE179: 65 | FF179: 62.6 | FG179: 40.4 | FH179: 107.8 | FI179: 51.7 | FJ179: 68.6 | FK179: 49.9 | FL179: 50.3 | FM179: 52.1 | FN179: 50.6 | FO179: 45.4 | FP179: 45.6 | FQ179: 45.4 | FR179: 48.4 | FS179: 54.1 | FT179: 51.9 | FU179: 67.2 | FV179: 57.9 | FW179: 46.9 | FX179: 59.9 | FY179: 58.8 | FZ179: 60.9 | GA179: 56.9 | GB179: 49.9 | GC179: 50.5 | GD179: 48.6 | GE179: 33.2 | GF179: 51.6 | GG179: 47.3 | GH179: 66.6 | GI179: 44.4 | GJ179: 16 | GK179: 16 | GL179: 95.7 | GM179: 102.5 | GN179: 102.9 | GO179: 103.3 | GP179: 98.3 | GQ179: 99.6 | GR179: 104.1 | GS179: 97.4 | GT179: 104 | GW179: 55.3 | GX179: 68.2 | GY179: 55.6 | GZ179: 55.6 | HD179: 54.3 | HF179: 37.3 | HH179: 38.5 | HI179: 41.7 | HJ179: 81.7 | HK179: 77.4 | HL179: 79 | HM179: 69.6 | HN179: 100.3 | HO179: 100.3 | HP179: 106.6 | HQ179: 102.7 | HR179: 110.4 | HS179: 120.9 | HT179: 92.9 | HU179: 72 | HV179: 73.7 | HW179: 71.4 | HX179: 67.4 | HY179: 50.8 | HZ179: 50 | IA179: 50.4 | IB179: 46.1 | IC179: 35.5 | ID179: 61.5 | IE179: 61.5 | IF179: 59.6 | IG179: 30.7 | IH179: 29.1 | II179: 39.5 | IJ179: 60.2 | IK179: 61.9 | IL179: 106.3 | IM179: 78.2 | IN179: 44.9 | IO179: 64 | IP179: 22.4 | IQ179: 38
A180: 33208 | B180: 51.9 | C180: 53.4 | D180: 47.3 | E180: 56.6 | F180: 69.2 | G180: 62 | H180: 57.8 | I180: 65.1 | J180: 54.8 | K180: 34.2 | L180: 89 | M180: 45.9 | N180: 64.2 | O180: 52.7 | P180: 53.2 | Q180: 52.8 | R180: 54.4 | S180: 44.2 | T180: 46.2 | U180: 43.4 | V180: 48.1 | W180: 41.9 | X180: 49.9 | Y180: 64.7 | Z180: 49.9 | AA180: 46.4 | AB180: 59 | AC180: 55 | AD180: 63.9 | AE180: 53.5 | AF180: 51.7 | AG180: 52.2 | AH180: 50.9 | AI180: 33.5 | AJ180: 50 | AK180: 44.8 | AL180: 62.3 | AM180: 43.9 | AN180: 17 | AO180: 17 | AP180: 89.6 | AQ180: 93.5 | AR180: 97.4 | AS180: 90.7 | AT180: 98.3 | AU180: 105.9 | AV180: 125.9 | AW180: 102.2 | AX180: 83.9 | BA180: 52.5 | BB180: 57.9 | BC180: 50.2 | BD180: 50.2 | BH180: 56.4 | BJ180: 37.7 | BL180: 35.5 | BM180: 39.1 | BN180: 84.5 | BO180: 80.3 | BP180: 87.6 | BQ180: 57.8 | BR180: 95.6 | BS180: 95.6 | BT180: 100.8 | BU180: 106.4 | BV180: 106.5 | BW180: 110.1 | BX180: 85.2 | BY180: 77.8 | BZ180: 80.5 | CA180: 75.1 | CB180: 72.1 | CC180: 44.7 | CD180: 65.4 | CE180: 52.8 | CF180: 39.3 | CG180: 41.3 | CH180: 58 | CI180: 56.7 | CJ180: 63.2 | CK180: 36.9 | CL180: 35.5 | CM180: 41.1 | CN180: 64.9 | CO180: 67.1 | CP180: 108.1 | CQ180: 72.9 | CR180: 53.1 | CS180: 64.3 | CT180: 49.4 | CU180: 46.2 | CV180: 46.2 | CW180: 90.9 | CX180: 90.9 | CY180: 59.7 | CZ180: 93.3 | DA180: 77 | DB180: 259.8 | DC180: 905.2 | DD180: 115.9 | DE180: 51 | DH180: 68.6 | DI180: 64 | DJ180: 74 | DK180: 53.9 | DN180: 51.9 | DO180: 41.4 | DR180: 30.8 | DS180: 30.8 | DX180: 29.8 | DY180: 29.8 | EC180: 58.9 | EF180: 60.9 | EG180: 56.1 | EH180: 58.9 | EI180: 60.5 | EJ180: 61.8 | EK180: 57.7 | EL180: 59.9 | EM180: 56.4 | EN180: 60.1 | EO180: 57.9 | EP180: 58.3 | EQ180: 57 | ER180: 59.6 | ES180: 56.8 | ET180: 59.8 | EU180: 59.9 | EV180: 61.7 | EX180: 51.8 | EY180: 48.8 | EZ180: 41 | FA180: 52.6 | FB180: 65.1 | FC180: 56.3 | FD180: 63.8 | FE180: 65.1 | FF180: 62.8 | FG180: 38.8 | FH180: 101.9 | FI180: 53.1 | FJ180: 69.1 | FK180: 51.1 | FL180: 52.2 | FM180: 52.3 | FN180: 52 | FO180: 41.2 | FP180: 43.9 | FQ180: 39.2 | FR180: 48.7 | FS180: 53.4 | FT180: 53.5 | FU180: 65.4 | FV180: 57.9 | FW180: 47.2 | FX180: 61 | FY180: 58.3 | FZ180: 61.8 | GA180: 56.4 | GB180: 51.1 | GC180: 51.8 | GD180: 49.7 | GE180: 35.2 | GF180: 53.2 | GG180: 49.3 | GH180: 66.8 | GI180: 46 | GJ180: 18 | GK180: 18 | GL180: 96.8 | GM180: 103.9 | GN180: 102.9 | GO180: 105.1 | GP180: 100.5 | GQ180: 101 | GR180: 104.8 | GS180: 99.7 | GT180: 104.5 | GW180: 55.8 | GX180: 68.9 | GY180: 56.4 | GZ180: 56.4 | HD180: 54.9 | HF180: 37.6 | HH180: 38.5 | HI180: 42.3 | HJ180: 82.4 | HK180: 78.1 | HL180: 80.4 | HM180: 68.7 | HN180: 100.5 | HO180: 100.5 | HP180: 107.7 | HQ180: 103.2 | HR180: 111 | HS180: 124.2 | HT180: 93.1 | HU180: 72.8 | HV180: 76.8 | HW180: 71.3 | HX180: 68 | HY180: 51.8 | HZ180: 51.1 | IA180: 51.6 | IB180: 47 | IC180: 37.8 | ID180: 59.4 | IE180: 58.8 | IF180: 59.8 | IG180: 33.5 | IH180: 32.5 | II180: 39.9 | IJ180: 65 | IK180: 66.8 | IL180: 107.4 | IM180: 72.7 | IN180: 55.8 | IO180: 64.5 | IP180: 23.5 | IQ180: 42.3
A181: 33298 | B181: 53.4 | C181: 54.1 | D181: 48 | E181: 56.9 | F181: 71 | G181: 63.3 | H181: 58.7 | I181: 65.4 | J181: 54.6 | K181: 36.6 | L181: 92.6 | M181: 46.3 | N181: 64.9 | O181: 53.8 | P181: 55.1 | Q181: 53 | R181: 54.4 | S181: 53 | T181: 52.1 | U181: 54.9 | V181: 48.6 | W181: 41.6 | X181: 51.3 | Y181: 64.5 | Z181: 49.3 | AA181: 46.9 | AB181: 60.2 | AC181: 56.8 | AD181: 63.6 | AE181: 55.2 | AF181: 52.4 | AG181: 52.7 | AH181: 51.7 | AI181: 34.1 | AJ181: 51.1 | AK181: 45.5 | AL181: 64.3 | AM181: 44.7 | AN181: 17.2 | AO181: 17.2 | AP181: 90 | AQ181: 94 | AR181: 98.8 | AS181: 90.9 | AT181: 97.5 | AU181: 106.1 | AV181: 126 | AW181: 102.2 | AX181: 84.3 | BA181: 52.5 | BB181: 57.1 | BC181: 50.4 | BD181: 50.4 | BH181: 57.2 | BJ181: 37.9 | BL181: 35.5 | BM181: 40.1 | BN181: 85.3 | BO181: 79.6 | BP181: 86.5 | BQ181: 57.9 | BR181: 98.8 | BS181: 98.8 | BT181: 103.2 | BU181: 106.9 | BV181: 107 | BW181: 110.9 | BX181: 91.3 | BY181: 77.5 | BZ181: 80.5 | CA181: 75.6 | CB181: 71.7 | CC181: 47 | CD181: 57.8 | CE181: 53.8 | CF181: 41.4 | CG181: 42.3 | CH181: 64.4 | CI181: 64.5 | CJ181: 63 | CK181: 37.1 | CL181: 35.6 | CM181: 41.6 | CN181: 62.4 | CO181: 64.2 | CP181: 107.9 | CQ181: 74.1 | CR181: 44.7 | CS181: 65.3 | CT181: 51.3 | CU181: 46.3 | CV181: 46.3 | CW181: 90.9 | CX181: 90.9 | CY181: 59.7 | CZ181: 93.3 | DA181: 76.8 | DB181: 257.8 | DC181: 898.5 | DD181: 115 | DE181: 50.9 | DH181: 66.3 | DI181: 63.2 | DJ181: 70 | DK181: 54.7 | DN181: 52 | DO181: 44 | DR181: 34.5 | DS181: 34.5 | DX181: 30.2 | DY181: 30.2 | EC181: 59 | EF181: 61 | EG181: 56.1 | EH181: 59.1 | EI181: 60.2 | EJ181: 61.8 | EK181: 57.7 | EL181: 60.1 | EM181: 56.4 | EN181: 60.1 | EO181: 58.5 | EP181: 58.5 | EQ181: 57.1 | ER181: 59.6 | ES181: 57 | ET181: 60.1 | EU181: 59.9 | EV181: 62.1 | EX181: 52.5 | EY181: 49.3 | EZ181: 41.5 | FA181: 52.8 | FB181: 66.8 | FC181: 57.1 | FD181: 64.9 | FE181: 65.2 | FF181: 64.6 | FG181: 39 | FH181: 102.4 | FI181: 55.2 | FJ181: 71.6 | FK181: 51.4 | FL181: 53 | FM181: 52 | FN181: 53.2 | FO181: 44.8 | FP181: 44.9 | FQ181: 44.9 | FR181: 48.6 | FS181: 52.5 | FT181: 53.2 | FU181: 65.6 | FV181: 58.2 | FW181: 47.2 | FX181: 61.2 | FY181: 58.7 | FZ181: 61.7 | GA181: 56.8 | GB181: 51.4 | GC181: 52 | GD181: 50.1 | GE181: 35.6 | GF181: 53.7 | GG181: 50 | GH181: 67.6 | GI181: 46.4 | GJ181: 18.3 | GK181: 18.3 | GL181: 97.3 | GM181: 104.1 | GN181: 104.2 | GO181: 105.4 | GP181: 98.3 | GQ181: 102.1 | GR181: 106.8 | GS181: 99.8 | GT181: 106.6 | GW181: 56.3 | GX181: 68.1 | GY181: 56.9 | GZ181: 56.9 | HD181: 56 | HF181: 37.5 | HH181: 38.5 | HI181: 42.1 | HJ181: 82.7 | HK181: 77.4 | HL181: 79.6 | HM181: 68.4 | HN181: 102.9 | HO181: 102.9 | HP181: 108.8 | HQ181: 103 | HR181: 110.8 | HS181: 126.9 | HT181: 94.4 | HU181: 72.2 | HV181: 76.6 | HW181: 73.1 | HX181: 67.4 | HY181: 52.9 | HZ181: 42.8 | IA181: 52.2 | IB181: 48 | IC181: 40.1 | ID181: 66.6 | IE181: 67.5 | IF181: 60.8 | IG181: 35.1 | IH181: 34 | II181: 41.5 | IJ181: 61.7 | IK181: 63 | IL181: 105.9 | IM181: 72.8 | IN181: 47.7 | IO181: 64.8 | IP181: 23.5 | IQ181: 43.5
