Workbook
Name A130389940C: Data1!$EW$1:$EW$10,Data1!$EW$11:$EW$111
Name A130389940C_Data: Data1!$EW$11:$EW$111
Name A130389940C_Latest: Data1!$EW$111
Name A130389947V: Data3!$AW$1:$AW$10,Data3!$AW$11:$AW$111
Name A130389947V_Data: Data3!$AW$11:$AW$111
Name A130389947V_Latest: Data3!$AW$111
Name A130389954T: Data4!$BK$1:$BK$10,Data4!$BK$11:$BK$111
Name A130389954T_Data: Data4!$BK$11:$BK$111
Name A130389954T_Latest: Data4!$BK$111
Name A130389961R: Data1!$V$1:$V$10,Data1!$V$11:$V$111
Name A130389961R_Data: Data1!$V$11:$V$111
Name A130389961R_Latest: Data1!$V$111
Name A130389968F: Data2!$FL$1:$FL$10,Data2!$FL$11:$FL$111
Name A130389968F_Data: Data2!$FL$11:$FL$111
Name A130389968F_Latest: Data2!$FL$111
Name A130389975C: Data3!$IA$1:$IA$10,Data3!$IA$90:$IA$111
Name A130389975C_Data: Data3!$IA$90:$IA$111
Name A130389975C_Latest: Data3!$IA$111
Name A130389982A: Data3!$DJ$1:$DJ$10,Data3!$DJ$90:$DJ$111
Name A130389982A_Data: Data3!$DJ$90:$DJ$111
Name A130389982A_Latest: Data3!$DJ$111
Name A130389996R: Data4!$DX$1:$DX$10,Data4!$DX$90:$DX$111
Name A130389996R_Data: Data4!$DX$90:$DX$111
Name A130389996R_Latest: Data4!$DX$111
Name A130390003J: Data4!$L$1:$L$10,Data4!$L$90:$L$111
Name A130390003J_Data: Data4!$L$90:$L$111
Name A130390003J_Latest: Data4!$L$111
Name A130390010F: Data4!$EN$1:$EN$10,Data4!$EN$90:$EN$111
Name A130390010F_Data: Data4!$EN$90:$EN$111
Name A130390010F_Latest: Data4!$EN$111
Name A130390017W: Data1!$IN$1:$IN$10,Data1!$IN$90:$IN$111
Name A130390017W_Data: Data1!$IN$90:$IN$111
Name A130390017W_Latest: Data1!$IN$111
Name A130390031T: Data3!$EW$1:$EW$10,Data3!$EW$90:$EW$111
Name A130390031T_Data: Data3!$EW$90:$EW$111
Name A130390031T_Latest: Data3!$EW$111
Name A130390038J: Data2!$EJ$1:$EJ$10,Data2!$EJ$11:$EJ$111
Name A130390038J_Data: Data2!$EJ$11:$EJ$111
Name A130390038J_Latest: Data2!$EJ$111
Name A130390045F: Data3!$V$1:$V$10,Data3!$V$11:$V$111
Name A130390045F_Data: Data3!$V$11:$V$111
Name A130390045F_Latest: Data3!$V$111
Name A130390066T: Data1!$HI$1:$HI$10,Data1!$HI$90:$HI$111
Name A130390066T_Data: Data1!$HI$90:$HI$111
Name A130390066T_Latest: Data1!$HI$111
Name A130390073R: Data2!$CU$1:$CU$10,Data2!$CU$90:$CU$111
Name A130390073R_Data: Data2!$CU$90:$CU$111
Name A130390073R_Latest: Data2!$CU$111
Name A130390080L: Data3!$BH$1:$BH$10,Data3!$BH$11:$BH$111
Name A130390080L_Data: Data3!$BH$11:$BH$111
Name A130390080L_Latest: Data3!$BH$111
Name A130390087C: Data4!$GX$1:$GX$10,Data4!$GX$11:$GX$111
Name A130390087C_Data: Data4!$GX$11:$GX$111
Name A130390087C_Latest: Data4!$GX$111
Name A130390101L: Data5!$BA$1:$BA$10,Data5!$BA$90:$BA$111
Name A130390101L_Data: Data5!$BA$90:$BA$111
Name A130390101L_Latest: Data5!$BA$111
Name A130390171V: Data2!$EL$1:$EL$10,Data2!$EL$90:$EL$111
Name A130390171V_Data: Data2!$EL$90:$EL$111
Name A130390171V_Latest: Data2!$EL$111

Sheet Index
B2: Time Series Workbook
B5: 6401.0 Consumer Price Index, Australia
B6: TABLE 10. CPI: Group, Sub-group and Expenditure Class, Index Numbers by Capital City
D8: Enquiries
A10: Data Item Description | D10: Series Type | E10: Series ID | F10: Series Start | G10: Series End | H10: No. Obs. | I10: Unit | J10: Data Type | K10: Freq. | L10: Collection Month
A12: Index Numbers ; All groups CPI ; Sydney ; | D12: Original | E12: A130397375X | F12: 45383 | G12: 46023 | H12: 22 | I12: Index Numbers | J12: INDEX | K12: Month | L12: 1
A13: Index Numbers ; Food and non-alcoholic beverages ; Sydney ; | D13: Original | E13: A130392957J | F13: 45383 | G13: 46023 | H13: 22 | I13: Index Numbers | J13: INDEX | K13: Month | L13: 1
A14: Index Numbers ; Bread and cereal products ; Sydney ; | D14: Original | E14: A130394343A | F14: 42979 | G14: 46023 | H14: 101 | I14: Index Numbers | J14: INDEX | K14: Month | L14: 1
A15: Index Numbers ; Bread ; Sydney ; | D15: Original | E15: A130398033T | F15: 42979 | G15: 46023 | H15: 101 | I15: Index Numbers | J15: INDEX | K15: Month | L15: 1
A16: Index Numbers ; Cakes and biscuits ; Sydney ; | D16: Original | E16: A130394448W | F16: 42979 | G16: 46023 | H16: 101 | I16: Index Numbers | J16: INDEX | K16: Month | L16: 1
A17: Index Numbers ; Breakfast cereals ; Sydney ; | D17: Original | E17: A130399331J | F17: 42979 | G17: 46023 | H17: 101 | I17: Index Numbers | J17: INDEX | K17: Month | L17: 1
A18: Index Numbers ; Other cereal products ; Sydney ; | D18: Original | E18: A130399352V | F18: 42979 | G18: 46023 | H18: 101 | I18: Index Numbers | J18: INDEX | K18: Month | L18: 1
A19: Index Numbers ; Meat and seafoods ; Sydney ; | D19: Original | E19: A130393055R | F19: 42979 | G19: 46023 | H19: 101 | I19: Index Numbers | J19: INDEX | K19: Month | L19: 1
A20: Index Numbers ; Beef and veal ; Sydney ; | D20: Original | E20: A130394462T | F20: 42979 | G20: 46023 | H20: 101 | I20: Index Numbers | J20: INDEX | K20: Month | L20: 1
A21: Index Numbers ; Pork ; Sydney ; | D21: Original | E21: A130391473V | F21: 42979 | G21: 46023 | H21: 101 | I21: Index Numbers | J21: INDEX | K21: Month | L21: 1
A22: Index Numbers ; Lamb and goat ; Sydney ; | D22: Original | E22: A130396863T | F22: 42979 | G22: 46023 | H22: 101 | I22: Index Numbers | J22: INDEX | K22: Month | L22: 1
A23: Index Numbers ; Poultry ; Sydney ; | D23: Original | E23: A130398096A | F23: 42979 | G23: 46023 | H23: 101 | I23: Index Numbers | J23: INDEX | K23: Month | L23: 1
... A1067: Index Numbers ; Other financial services ; Canberra ; | D1067: Original | E1067: A130392488C | F1067: 42979 | G1067: 46023 | H1067: 101 | I1067: Index Numbers | J1067: INDEX | K1067: Month | L1067: 1
A1069: © Commonwealth of Australia 2026

Sheet Energy Summary
A1: Energy Prices by Capital City — CPI Index
A2: Source: ABS 6401.0 Consumer Price Index, Table 10. Reference period: September 2025 = 100.00. Series Type: Original.
A4: Summary Table — Index Levels & % Change
A6: City | B6: Electricity — Latest | C6: Elec — 1Y ago | D6: Elec — 3Y ago | E6: Elec — 1Y %Δ | F6: Elec — 3Y %Δ | G6: Gas — Latest | H6: Gas — 1Y ago | I6: Gas — 3Y ago | J6: Gas — 1Y %Δ | K6: Gas — 3Y %Δ
A7: Sydney | B7: =Data1!BM111 -> 115.58 | C7: =Data1!BM99 -> 88.39 | D7: =Data1!BM75 -> 93.54 | E7: =B7/C7-1 -> 0.30761398 | F7: =B7/D7-1 -> 0.23562112 | G7: =Data1!BN111 -> 102.71 | H7: =Data1!BN99 -> 94.47 | I7: =Data1!BN75 -> 85.4 | J7: =G7/H7-1 -> 0.087223457 | K7: =G7/I7-1 -> 0.20269321
A8: Melbourne | B8: =Data1!GO111 -> 121.55 | C8: =Data1!GO99 -> 108.1 | D8: =Data1!GO75 -> 107.55 | E8: =B8/C8-1 -> 0.12442183 | F8: =B8/D8-1 -> 0.13017201 | G8: =Data1!GP111 -> 98.39 | H8: =Data1!GP99 -> 92.84 | I8: =Data1!GP75 -> 93.55 | J8: =G8/H8-1 -> 0.059780267 | K8: =G8/I8-1 -> 0.051737039
A9: Brisbane | B9: =Data2!CA111 -> 113.46 | C9: =Data2!CA99 -> 79.29 | D9: =Data2!CA75 -> 88.18 | E9: =B9/C9-1 -> 0.43094968 | F9: =B9/D9-1 -> 0.28668632 | G9: =Data2!CB111 -> 98.35 | H9: =Data2!CB99 -> 97.31 | I9: =Data2!CB75 -> 96.35 | J9: =G9/H9-1 -> 0.010687494 | K9: =G9/I9-1 -> 0.020757654
A10: Adelaide | B10: =Data2!HC111 -> 115.65 | C10: =Data2!HC99 -> 99.14 | D10: =Data2!HC75 -> 96.87 | E10: =B10/C10-1 -> 0.16653218 | F10: =B10/D10-1 -> 0.19386807 | G10: =Data2!HD111 -> 98.56 | H10: =Data2!HD99 -> 95.82 | I10: =Data2!HD75 -> 85.96 | J10: =G10/H10-1 -> 0.028595283 | K10: =G10/I10-1 -> 0.1465798
A11: Perth | B11: =Data3!CO111 -> 90.07 | C11: =Data3!CO99 -> 25.71 | D11: =Data3!CO75 -> 92.86 | E11: =B11/C11-1 -> 2.5033061 | F11: =B11/D11-1 -> -0.030045229 | G11: =Data3!CP111 -> 101.81 | H11: =Data3!CP99 -> 96.91 | I11: =Data3!CP75 -> 85.48 | J11: =G11/H11-1 -> 0.050562377 | K11: =G11/I11-1 -> 0.19103884
A12: Hobart | B12: =Data3!HQ111 -> 112.33 | C12: =Data3!HQ99 -> 98.38 | D12: =Data3!HQ75 -> 101.1 | E12: =B12/C12-1 -> 0.14179711 | F12: =B12/D12-1 -> 0.11107814 | G12: =Data3!HR111 -> 100.79 | H12: =Data3!HR99 -> 97.83 | I12: =Data3!HR75 -> 89.99 | J12: =G12/H12-1 -> 0.030256568 | K12: =G12/I12-1 -> 0.12001333
A13: Darwin | B13: =Data4!DC111 -> 115.92 | C13: =Data4!DC99 -> 96.31 | D13: =Data4!DC75 -> 104.48 | E13: =B13/C13-1 -> 0.20361333 | F13: =B13/D13-1 -> 0.10949464 | G13: =Data4!DD111 -> 114.68 | H13: =Data4!DD99 -> 109.1 | I13: =Data4!DD75 -> 91.4 | J13: =G13/H13-1 -> 0.051145738 | K13: =G13/I13-1 -> 0.2547046
A14: Canberra | B14: =Data4!IE111 -> 114.61 | C14: =Data4!IE99 -> 87.66 | D14: =Data4!IE75 -> 89.44 | E14: =B14/C14-1 -> 0.30743783 | F14: =B14/D14-1 -> 0.28141771 | G14: =Data4!IF111 -> 99.81 | H14: =Data4!IF99 -> 98.44 | I14: =Data4!IF75 -> 80.27 | J14: =G14/H14-1 -> 0.013917107 | K14: =G14/I14-1 -> 0.24342843
A16: Time Series — Electricity & Gas Index by City (Sep 2021 – Sep 2025)
A18: Date | B18: Sydney — Elec | C18: Melbourne — Elec | D18: Brisbane — Elec | E18: Adelaide — Elec | F18: Perth — Elec | G18: Hobart — Elec | H18: Darwin — Elec | I18: Canberra — Elec | J18: Sydney — Gas | K18: Melbourne — Gas | L18: Brisbane — Gas | M18: Adelaide — Gas | N18: Perth — Gas | O18: Hobart — Gas | P18: Darwin — Gas | Q18: Canberra — Gas | S18: Date | T18: Sydney | U18: Melbourne | V18: Brisbane | W18: Adelaide | X18: Perth | Y18: Hobart | Z18: Darwin | AA18: Canberra
A19: =Data1!A60 -> 44470 | B19: =Data1!BM60 -> 72.41 | C19: =Data1!GO60 -> 100.83 | D19: =Data2!CA60 -> 71.14 | E19: =Data2!HC60 -> 84.11 | F19: =Data3!CO60 -> 90.6 | G19: =Data3!HQ60 -> 90.34 | H19: =Data4!DC60 -> 101.44 | I19: =Data4!IE60 -> 82.83 | J19: =Data1!BN60 -> 71.13 | K19: =Data1!GP60 -> 60.92 | L19: =Data2!CB60 -> 84.69 | M19: =Data2!HD60 -> 72.2 | N19: =Data3!CP60 -> 82.13 | O19: =Data3!HR60 -> 82.27 | P19: =Data4!DD60 -> 85.34 | Q19: =Data4!IF60 -> 75.26 | S19: =A19 -> 44470 | T19: =J19 -> 71.13 | U19: =K19 -> 60.92 | V19: =L19 -> 84.69 | W19: =M19 -> 72.2 | X19: =N19 -> 82.13 | Y19: =O19 -> 82.27 | Z19: =P19 -> 85.34 | AA19: =Q19 -> 75.26
A20: =Data1!A61 -> 44501 | B20: =Data1!BM61 -> 73.85 | C20: =Data1!GO61 -> 102.25 | D20: =Data2!CA61 -> 71.14 | E20: =Data2!HC61 -> 84.11 | F20: =Data3!CO61 -> 90.6 | G20: =Data3!HQ61 -> 90.34 | H20: =Data4!DC61 -> 101.44 | I20: =Data4!IE61 -> 82.83 | J20: =Data1!BN61 -> 71.13 | K20: =Data1!GP61 -> 63.74 | L20: =Data2!CB61 -> 84.69 | M20: =Data2!HD61 -> 72.2 | N20: =Data3!CP61 -> 82.13 | O20: =Data3!HR61 -> 82.27 | P20: =Data4!DD61 -> 85.34 | Q20: =Data4!IF61 -> 75.26 | S20: =A20 -> 44501 | T20: =J20 -> 71.13 | U20: =K20 -> 63.74 | V20: =L20 -> 84.69 | W20: =M20 -> 72.2 | X20: =N20 -> 82.13 | Y20: =O20 -> 82.27 | Z20: =P20 -> 85.34 | AA20: =Q20 -> 75.26
A21: =Data1!A62 -> 44531 | B21: =Data1!BM62 -> 74.6 | C21: =Data1!GO62 -> 101.84 | D21: =Data2!CA62 -> 71 | E21: =Data2!HC62 -> 84.27 | F21: =Data3!CO62 -> 90.6 | G21: =Data3!HQ62 -> 90.34 | H21: =Data4!DC62 -> 101.44 | I21: =Data4!IE62 -> 83.25 | J21: =Data1!BN62 -> 72.83 | K21: =Data1!GP62 -> 65.82 | L21: =Data2!CB62 -> 86.1 | M21: =Data2!HD62 -> 72.2 | N21: =Data3!CP62 -> 82.13 | O21: =Data3!HR62 -> 83.17 | P21: =Data4!DD62 -> 87.2 | Q21: =Data4!IF62 -> 75.26 | S21: =A21 -> 44531 | T21: =J21 -> 72.83 | U21: =K21 -> 65.82 | V21: =L21 -> 86.1 | W21: =M21 -> 72.2 | X21: =N21 -> 82.13 | Y21: =O21 -> 83.17 | Z21: =P21 -> 87.2 | AA21: =Q21 -> 75.26
A22: =Data1!A63 -> 44562 | B22: =Data1!BM63 -> 74.45 | C22: =Data1!GO63 -> 101.12 | D22: =Data2!CA63 -> 71 | E22: =Data2!HC63 -> 84.27 | F22: =Data3!CO63 -> 90.6 | G22: =Data3!HQ63 -> 90.34 | H22: =Data4!DC63 -> 101.44 | I22: =Data4!IE63 -> 88.02 | J22: =Data1!BN63 -> 72.83 | K22: =Data1!GP63 -> 66.93 | L22: =Data2!CB63 -> 86.1 | M22: =Data2!HD63 -> 72.2 | N22: =Data3!CP63 -> 82.13 | O22: =Data3!HR63 -> 83.86 | P22: =Data4!DD63 -> 87.2 | Q22: =Data4!IF63 -> 75.26 | S22: =A22 -> 44562 | T22: =J22 -> 72.83 | U22: =K22 -> 66.93 | V22: =L22 -> 86.1 | W22: =M22 -> 72.2 | X22: =N22 -> 82.13 | Y22: =O22 -> 83.86 | Z22: =P22 -> 87.2 | AA22: =Q22 -> 75.26
A23: =Data1!A64 -> 44593 | B23: =Data1!BM64 -> 74.45 | C23: =Data1!GO64 -> 100.26 | D23: =Data2!CA64 -> 70.15 | E23: =Data2!HC64 -> 84.27 | F23: =Data3!CO64 -> 90.6 | G23: =Data3!HQ64 -> 90.34 | H23: =Data4!DC64 -> 101.44 | I23: =Data4!IE64 -> 88.02 | J23: =Data1!BN64 -> 72.83 | K23: =Data1!GP64 -> 69.27 | L23: =Data2!CB64 -> 86.1 | M23: =Data2!HD64 -> 72.2 | N23: =Data3!CP64 -> 82.13 | O23: =Data3!HR64 -> 83.86 | P23: =Data4!DD64 -> 87.2 | Q23: =Data4!IF64 -> 75.26 | S23: =A23 -> 44593 | T23: =J23 -> 72.83 | U23: =K23 -> 69.27 | V23: =L23 -> 86.1 | W23: =M23 -> 72.2 | X23: =N23 -> 82.13 | Y23: =O23 -> 83.86 | Z23: =P23 -> 87.2 | AA23: =Q23 -> 75.26
A24: =Data1!A65 -> 44621 | B24: =Data1!BM65 -> 74.31 | C24: =Data1!GO65 -> 100.26 | D24: =Data2!CA65 -> 70.15 | E24: =Data2!HC65 -> 84.27 | F24: =Data3!CO65 -> 90.6 | G24: =Data3!HQ65 -> 90.34 | H24: =Data4!DC65 -> 101.44 | I24: =Data4!IE65 -> 88.02 | J24: =Data1!BN65 -> 72.83 | K24: =Data1!GP65 -> 69.25 | L24: =Data2!CB65 -> 86.87 | M24: =Data2!HD65 -> 72.2 | N24: =Data3!CP65 -> 82.13 | O24: =Data3!HR65 -> 86.47 | P24: =Data4!DD65 -> 89.11 | Q24: =Data4!IF65 -> 75.26 | S24: =A24 -> 44621 | T24: =J24 -> 72.83 | U24: =K24 -> 69.25 | V24: =L24 -> 86.87 | W24: =M24 -> 72.2 | X24: =N24 -> 82.13 | Y24: =O24 -> 86.47 | Z24: =P24 -> 89.11 | AA24: =Q24 -> 75.26
A25: =Data1!A66 -> 44652 | B25: =Data1!BM66 -> 73.01 | C25: =Data1!GO66 -> 100.39 | D25: =Data2!CA66 -> 70.45 | E25: =Data2!HC66 -> 84.4 | F25: =Data3!CO66 -> 90.6 | G25: =Data3!HQ66 -> 90.34 | H25: =Data4!DC66 -> 101.44 | I25: =Data4!IE66 -> 88.02 | J25: =Data1!BN66 -> 72.31 | K25: =Data1!GP66 -> 69.25 | L25: =Data2!CB66 -> 86.87 | M25: =Data2!HD66 -> 72.2 | N25: =Data3!CP66 -> 82.13 | O25: =Data3!HR66 -> 86.47 | P25: =Data4!DD66 -> 89.11 | Q25: =Data4!IF66 -> 75.26 | S25: =A25 -> 44652 | T25: =J25 -> 72.31 | U25: =K25 -> 69.25 | V25: =L25 -> 86.87 | W25: =M25 -> 72.2 | X25: =N25 -> 82.13 | Y25: =O25 -> 86.47 | Z25: =P25 -> 89.11 | AA25: =Q25 -> 75.26
A26: =Data1!A67 -> 44682 | B26: =Data1!BM67 -> 73.44 | C26: =Data1!GO67 -> 100.01 | D26: =Data2!CA67 -> 70.08 | E26: =Data2!HC67 -> 85.54 | F26: =Data3!CO67 -> 90.6 | G26: =Data3!HQ67 -> 90.34 | H26: =Data4!DC67 -> 101.44 | I26: =Data4!IE67 -> 88.02 | J26: =Data1!BN67 -> 70.99 | K26: =Data1!GP67 -> 66.21 | L26: =Data2!CB67 -> 86.87 | M26: =Data2!HD67 -> 71.37 | N26: =Data3!CP67 -> 82.13 | O26: =Data3!HR67 -> 86.47 | P26: =Data4!DD67 -> 89.11 | Q26: =Data4!IF67 -> 75.26 | S26: =A26 -> 44682 | T26: =J26 -> 70.99 | U26: =K26 -> 66.21 | V26: =L26 -> 86.87 | W26: =M26 -> 71.37 | X26: =N26 -> 82.13 | Y26: =O26 -> 86.47 | Z26: =P26 -> 89.11 | AA26: =Q26 -> 75.26
A27: =Data1!A68 -> 44713 | B27: =Data1!BM68 -> 77.73 | C27: =Data1!GO68 -> 99.57 | D27: =Data2!CA68 -> 72.7 | E27: =Data2!HC68 -> 87.11 | F27: =Data3!CO68 -> 90.6 | G27: =Data3!HQ68 -> 90.34 | H27: =Data4!DC68 -> 101.44 | I27: =Data4!IE68 -> 89.66 | J27: =Data1!BN68 -> 72.95 | K27: =Data1!GP68 -> 69.38 | L27: =Data2!CB68 -> 88.31 | M27: =Data2!HD68 -> 73.62 | N27: =Data3!CP68 -> 82.13 | O27: =Data3!HR68 -> 87.3 | P27: =Data4!DD68 -> 87.02 | Q27: =Data4!IF68 -> 75.26 | S27: =A27 -> 44713 | T27: =J27 -> 72.95 | U27: =K27 -> 69.38 | V27: =L27 -> 88.31 | W27: =M27 -> 73.62 | X27: =N27 -> 82.13 | Y27: =O27 -> 87.3 | Z27: =P27 -> 87.02 | AA27: =Q27 -> 75.26
A28: =Data1!A69 -> 44743 | B28: =Data1!BM69 -> 92.38 | C28: =Data1!GO69 -> 107.05 | D28: =Data2!CA69 -> 84.34 | E28: =Data2!HC69 -> 94.89 | F28: =Data3!CO69 -> 14.2 | G28: =Data3!HQ69 -> 101.1 | H28: =Data4!DC69 -> 104.48 | I28: =Data4!IE69 -> 88.56 | J28: =Data1!BN69 -> 81.87 | K28: =Data1!GP69 -> 76.67 | L28: =Data2!CB69 -> 93.91 | M28: =Data2!HD69 -> 84.46 | N28: =Data3!CP69 -> 84.62 | O28: =Data3!HR69 -> 87.57 | P28: =Data4!DD69 -> 87.02 | Q28: =Data4!IF69 -> 78.12 | S28: =A28 -> 44743 | T28: =J28 -> 81.87 | U28: =K28 -> 76.67 | V28: =L28 -> 93.91 | W28: =M28 -> 84.46 | X28: =N28 -> 84.62 | Y28: =O28 -> 87.57 | Z28: =P28 -> 87.02 | AA28: =Q28 -> 78.12
A29: =Data1!A70 -> 44774 | B29: =Data1!BM70 -> 93.08 | C29: =Data1!GO70 -> 108.12 | D29: =Data2!CA70 -> 88.1 | E29: =Data2!HC70 -> 96.81 | F29: =Data3!CO70 -> 14.2 | G29: =Data3!HQ70 -> 101.1 | H29: =Data4!DC70 -> 104.48 | I29: =Data4!IE70 -> 89.2 | J29: =Data1!BN70 -> 81.87 | K29: =Data1!GP70 -> 78.28 | L29: =Data2!CB70 -> 93.91 | M29: =Data2!HD70 -> 83.85 | N29: =Data3!CP70 -> 84.62 | O29: =Data3!HR70 -> 87.57 | P29: =Data4!DD70 -> 87.02 | Q29: =Data4!IF70 -> 80.27 | S29: =A29 -> 44774 | T29: =J29 -> 81.87 | U29: =K29 -> 78.28 | V29: =L29 -> 93.91 | W29: =M29 -> 83.85 | X29: =N29 -> 84.62 | Y29: =O29 -> 87.57 | Z29: =P29 -> 87.02 | AA29: =Q29 -> 80.27
A30: =Data1!A71 -> 44805 | B30: =Data1!BM71 -> 92.4 | C30: =Data1!GO71 -> 108.12 | D30: =Data2!CA71 -> 55.51 | E30: =Data2!HC71 -> 97.12 | F30: =Data3!CO71 -> 14.2 | G30: =Data3!HQ71 -> 101.1 | H30: =Data4!DC71 -> 104.48 | I30: =Data4!IE71 -> 89.61 | J30: =Data1!BN71 -> 82.63 | K30: =Data1!GP71 -> 78.28 | L30: =Data2!CB71 -> 94.14 | M30: =Data2!HD71 -> 85.59 | N30: =Data3!CP71 -> 84.62 | O30: =Data3!HR71 -> 88.57 | P30: =Data4!DD71 -> 88.18 | Q30: =Data4!IF71 -> 80.27 | S30: =A30 -> 44805 | T30: =J30 -> 82.63 | U30: =K30 -> 78.28 | V30: =L30 -> 94.14 | W30: =M30 -> 85.59 | X30: =N30 -> 84.62 | Y30: =O30 -> 88.57 | Z30: =P30 -> 88.18 | AA30: =Q30 -> 80.27
... A70: =Data1!A111 -> 46023 | B70: =Data1!BM111 -> 115.58 | C70: =Data1!GO111 -> 121.55 | D70: =Data2!CA111 -> 113.46 | E70: =Data2!HC111 -> 115.65 | F70: =Data3!CO111 -> 90.07 | G70: =Data3!HQ111 -> 112.33 | H70: =Data4!DC111 -> 115.92 | I70: =Data4!IE111 -> 114.61 | J70: =Data1!BN111 -> 102.71 | K70: =Data1!GP111 -> 98.39 | L70: =Data2!CB111 -> 98.35 | M70: =Data2!HD111 -> 98.56 | N70: =Data3!CP111 -> 101.81 | O70: =Data3!HR111 -> 100.79 | P70: =Data4!DD111 -> 114.68 | Q70: =Data4!IF111 -> 99.81 | S70: =A70 -> 46023 | T70: =J70 -> 102.71 | U70: =K70 -> 98.39 | V70: =L70 -> 98.35 | W70: =M70 -> 98.56 | X70: =N70 -> 101.81 | Y70: =O70 -> 100.79 | Z70: =P70 -> 114.68 | AA70: =Q70 -> 99.81
A72: Notes:
A73: • Index reference: Sep 2025 = 100.00. Index Numbers are CPI sub-group indices, not nominal $ prices.
A74: • "Electricity" and "Gas and other household fuels" series for each capital city, ABS 6401.0 Table 10 (Original).
A75: • Large 1Y movements in Electricity (esp. Perth, Brisbane, Sydney) reflect timing of Commonwealth/State energy bill rebates, which reduced the index sharply in 2024 then unwound as rebates expired.
A76: • Time series starts Sep 2021 (earliest period with data for all 8 capitals on this reference base).
A78: Rebased Time Series — Sep 2021 = 1.00
A79: Each series divided by its Sep 2021 value. Values >1 mean prices rose vs baseline; <1 mean prices fell.
A80: Date | B80: Sydney — Elec | C80: Melbourne — Elec | D80: Brisbane — Elec | E80: Adelaide — Elec | F80: Perth — Elec | G80: Hobart — Elec | H80: Darwin — Elec | I80: Canberra — Elec | J80: Sydney — Gas | K80: Melbourne — Gas | L80: Brisbane — Gas | M80: Adelaide — Gas | N80: Perth — Gas | O80: Hobart — Gas | P80: Darwin — Gas | Q80: Canberra — Gas | AE80: Date | AF80: Sydney | AG80: Melbourne | AH80: Brisbane | AI80: Adelaide | AJ80: Perth | AK80: Hobart | AL80: Darwin | AM80: Canberra
A81: =A19 -> 44470 | B81: =B19/B$19 -> 1 | C81: =C19/C$19 -> 1 | D81: =D19/D$19 -> 1 | E81: =E19/E$19 -> 1 | F81: =F19/F$19 -> 1 | G81: =G19/G$19 -> 1 | H81: =H19/H$19 -> 1 | I81: =I19/I$19 -> 1 | ... Q81: =Q19/Q$19 -> 1 | AE81: =A81 -> 44470 | AF81: =J81 -> 1 | AG81: =K81 -> 1 | AH81: =L81 -> 1 | AI81: =M81 -> 1 | AJ81: =N81 -> 1 | AK81: =O81 -> 1 | AL81: =P81 -> 1 | AM81: =Q81 -> 1
A82: =A20 -> 44501 | B82: =B20/B$19 -> 1.0198868 | C82: =C20/C$19 -> 1.0140831 | D82: =D20/D$19 -> 1 | E82: =E20/E$19 -> 1 | F82: =F20/F$19 -> 1 | G82: =G20/G$19 -> 1 | H82: =H20/H$19 -> 1 | I82: =I20/I$19 -> 1 | ... Q82: =Q20/Q$19 -> 1 | AE82: =A82 -> 44501 | AF82: =J82 -> 1 | AG82: =K82 -> 1.0462902 | AH82: =L82 -> 1 | AI82: =M82 -> 1 | AJ82: =N82 -> 1 | AK82: =O82 -> 1 | AL82: =P82 -> 1 | AM82: =Q82 -> 1
A83: =A21 -> 44531 | B83: =B21/B$19 -> 1.0302444 | C83: =C21/C$19 -> 1.0100169 | D83: =D21/D$19 -> 0.99803205 | E83: =E21/E$19 -> 1.0019023 | F83: =F21/F$19 -> 1 | G83: =G21/G$19 -> 1 | H83: =H21/H$19 -> 1 | I83: =I21/I$19 -> 1.0050706 | ... Q83: =Q21/Q$19 -> 1 | AE83: =A83 -> 44531 | AF83: =J83 -> 1.0238999 | AG83: =K83 -> 1.0804334 | AH83: =L83 -> 1.016649 | AI83: =M83 -> 1 | AJ83: =N83 -> 1 | AK83: =O83 -> 1.0109396 | AL83: =P83 -> 1.0217952 | AM83: =Q83 -> 1
A84: =A22 -> 44562 | B84: =B22/B$19 -> 1.0281729 | C84: =C22/C$19 -> 1.0028761 | D84: =D22/D$19 -> 0.99803205 | E84: =E22/E$19 -> 1.0019023 | F84: =F22/F$19 -> 1 | G84: =G22/G$19 -> 1 | H84: =H22/H$19 -> 1 | I84: =I22/I$19 -> 1.0626585 | ... Q84: =Q22/Q$19 -> 1 | AE84: =A84 -> 44562 | AF84: =J84 -> 1.0238999 | AG84: =K84 -> 1.098654 | AH84: =L84 -> 1.016649 | AI84: =M84 -> 1 | AJ84: =N84 -> 1 | AK84: =O84 -> 1.0193266 | AL84: =P84 -> 1.0217952 | AM84: =Q84 -> 1
A85: =A23 -> 44593 | B85: =B23/B$19 -> 1.0281729 | C85: =C23/C$19 -> 0.99434692 | D85: =D23/D$19 -> 0.98608378 | E85: =E23/E$19 -> 1.0019023 | F85: =F23/F$19 -> 1 | G85: =G23/G$19 -> 1 | H85: =H23/H$19 -> 1 | I85: =I23/I$19 -> 1.0626585 | ... Q85: =Q23/Q$19 -> 1 | AE85: =A85 -> 44593 | AF85: =J85 -> 1.0238999 | AG85: =K85 -> 1.137065 | AH85: =L85 -> 1.016649 | AI85: =M85 -> 1 | AJ85: =N85 -> 1 | AK85: =O85 -> 1.0193266 | AL85: =P85 -> 1.0217952 | AM85: =Q85 -> 1
A86: =A24 -> 44621 | B86: =B24/B$19 -> 1.0262395 | C86: =C24/C$19 -> 0.99434692 | D86: =D24/D$19 -> 0.98608378 | E86: =E24/E$19 -> 1.0019023 | F86: =F24/F$19 -> 1 | G86: =G24/G$19 -> 1 | H86: =H24/H$19 -> 1 | I86: =I24/I$19 -> 1.0626585 | ... Q86: =Q24/Q$19 -> 1 | AE86: =A86 -> 44621 | AF86: =J86 -> 1.0238999 | AG86: =K86 -> 1.1367367 | AH86: =L86 -> 1.0257409 | AI86: =M86 -> 1 | AJ86: =N86 -> 1 | AK86: =O86 -> 1.0510514 | AL86: =P86 -> 1.0441762 | AM86: =Q86 -> 1
A87: =A25 -> 44652 | B87: =B25/B$19 -> 1.0082861 | C87: =C25/C$19 -> 0.99563622 | D87: =D25/D$19 -> 0.99030082 | E87: =E25/E$19 -> 1.0034479 | F87: =F25/F$19 -> 1 | G87: =G25/G$19 -> 1 | H87: =H25/H$19 -> 1 | I87: =I25/I$19 -> 1.0626585 | ... Q87: =Q25/Q$19 -> 1 | AE87: =A87 -> 44652 | AF87: =J87 -> 1.0165893 | AG87: =K87 -> 1.1367367 | AH87: =L87 -> 1.0257409 | AI87: =M87 -> 1 | AJ87: =N87 -> 1 | AK87: =O87 -> 1.0510514 | AL87: =P87 -> 1.0441762 | AM87: =Q87 -> 1
A88: =A26 -> 44682 | B88: =B26/B$19 -> 1.0142246 | C88: =C26/C$19 -> 0.9918675 | D88: =D26/D$19 -> 0.9850998 | E88: =E26/E$19 -> 1.0170015 | F88: =F26/F$19 -> 1 | G88: =G26/G$19 -> 1 | H88: =H26/H$19 -> 1 | I88: =I26/I$19 -> 1.0626585 | ... Q88: =Q26/Q$19 -> 1 | AE88: =A88 -> 44682 | AF88: =J88 -> 0.99803177 | AG88: =K88 -> 1.0868352 | AH88: =L88 -> 1.0257409 | AI88: =M88 -> 0.98850416 | AJ88: =N88 -> 1 | AK88: =O88 -> 1.0510514 | AL88: =P88 -> 1.0441762 | AM88: =Q88 -> 1
A89: =A27 -> 44713 | B89: =B27/B$19 -> 1.0734705 | C89: =C27/C$19 -> 0.98750372 | D89: =D27/D$19 -> 1.0219286 | E89: =E27/E$19 -> 1.0356676 | F89: =F27/F$19 -> 1 | G89: =G27/G$19 -> 1 | H89: =H27/H$19 -> 1 | I89: =I27/I$19 -> 1.082458 | ... Q89: =Q27/Q$19 -> 1 | AE89: =A89 -> 44713 | AF89: =J89 -> 1.025587 | AG89: =K89 -> 1.1388707 | AH89: =L89 -> 1.0427441 | AI89: =M89 -> 1.0196676 | AJ89: =N89 -> 1 | AK89: =O89 -> 1.0611401 | AL89: =P89 -> 1.019686 | AM89: =Q89 -> 1
A90: =A28 -> 44743 | B90: =B28/B$19 -> 1.2757906 | C90: =C28/C$19 -> 1.061688 | D90: =D28/D$19 -> 1.1855496 | E90: =E28/E$19 -> 1.1281655 | F90: =F28/F$19 -> 0.15673289 | G90: =G28/G$19 -> 1.1191056 | H90: =H28/H$19 -> 1.0299685 | I90: =I28/I$19 -> 1.0691778 | ... Q90: =Q28/Q$19 -> 1.0380016 | AE90: =A90 -> 44743 | AF90: =J90 -> 1.1509911 | AG90: =K90 -> 1.2585358 | AH90: =L90 -> 1.1088676 | AI90: =M90 -> 1.1698061 | AJ90: =N90 -> 1.0303178 | AK90: =O90 -> 1.064422 | AL90: =P90 -> 1.019686 | AM90: =Q90 -> 1.0380016
A91: =A29 -> 44774 | B91: =B29/B$19 -> 1.2854578 | C91: =C29/C$19 -> 1.0722999 | D91: =D29/D$19 -> 1.2384031 | E91: =E29/E$19 -> 1.1509927 | F91: =F29/F$19 -> 0.15673289 | G91: =G29/G$19 -> 1.1191056 | H91: =H29/H$19 -> 1.0299685 | I91: =I29/I$19 -> 1.0769045 | ... Q91: =Q29/Q$19 -> 1.0665692 | AE91: =A91 -> 44774 | AF91: =J91 -> 1.1509911 | AG91: =K91 -> 1.2849639 | AH91: =L91 -> 1.1088676 | AI91: =M91 -> 1.1613573 | AJ91: =N91 -> 1.0303178 | AK91: =O91 -> 1.064422 | AL91: =P91 -> 1.019686 | AM91: =Q91 -> 1.0665692
A92: =A30 -> 44805 | B92: =B30/B$19 -> 1.2760668 | C92: =C30/C$19 -> 1.0722999 | D92: =D30/D$19 -> 0.78029238 | E92: =E30/E$19 -> 1.1546784 | F92: =F30/F$19 -> 0.15673289 | G92: =G30/G$19 -> 1.1191056 | H92: =H30/H$19 -> 1.0299685 | I92: =I30/I$19 -> 1.0818544 | ... Q92: =Q30/Q$19 -> 1.0665692 | AE92: =A92 -> 44805 | AF92: =J92 -> 1.1616758 | AG92: =K92 -> 1.2849639 | AH92: =L92 -> 1.1115834 | AI92: =M92 -> 1.1854571 | AJ92: =N92 -> 1.0303178 | AK92: =O92 -> 1.0765771 | AL92: =P92 -> 1.0332787 | AM92: =Q92 -> 1.0665692
... A132: =A70 -> 46023 | B132: =B70/B$19 -> 1.5961884 | C132: =C70/C$19 -> 1.2054944 | D132: =D70/D$19 -> 1.5948833 | E132: =E70/E$19 -> 1.3749851 | F132: =F70/F$19 -> 0.99415011 | G132: =G70/G$19 -> 1.2434138 | H132: =H70/H$19 -> 1.1427445 | I132: =I70/I$19 -> 1.3836774 | ... Q132: =Q70/Q$19 -> 1.3262025 | AE132: =A132 -> 46023 | AF132: =J132 -> 1.4439758 | AG132: =K132 -> 1.6150689 | AH132: =L132 -> 1.1612941 | AI132: =M132 -> 1.365097 | AJ132: =N132 -> 1.2396201 | AK132: =O132 -> 1.2251124 | AL132: =P132 -> 1.3438013 | AM132: =Q132 -> 1.3262025
A134: Ranking by Cumulative Price Growth (Sep 2021 → Sep 2025)
A136: Rank | B136: City — Fuel | C136: Rebased Index (Sep 2025) | D136: Cumulative %Δ | AC136: City — Fuel | AD136: Cumulative %Δ
A137: 1 | B137: =INDEX($B$80:$Q$80,MATCH(C137,$B$132:$Q$132,0)) -> Melbourne — Gas | C137: =LARGE($B$132:$Q$132,A137) -> 1.6150689 | D137: =C137-1 -> 0.61506894 | AC137: =B137 -> Melbourne — Gas | AD137: =D137 -> 0.61506894
A138: 2 | B138: =INDEX($B$80:$Q$80,MATCH(C138,$B$132:$Q$132,0)) -> Sydney — Elec | C138: =LARGE($B$132:$Q$132,A138) -> 1.5961884 | D138: =C138-1 -> 0.59618837 | AC138: =B138 -> Sydney — Elec | AD138: =D138 -> 0.59618837
A139: 3 | B139: =INDEX($B$80:$Q$80,MATCH(C139,$B$132:$Q$132,0)) -> Brisbane — Elec | C139: =LARGE($B$132:$Q$132,A139) -> 1.5948833 | D139: =C139-1 -> 0.59488333 | AC139: =B139 -> Brisbane — Elec | AD139: =D139 -> 0.59488333
A140: 4 | B140: =INDEX($B$80:$Q$80,MATCH(C140,$B$132:$Q$132,0)) -> Sydney — Gas | C140: =LARGE($B$132:$Q$132,A140) -> 1.4439758 | D140: =C140-1 -> 0.44397582 | AC140: =B140 -> Sydney — Gas | AD140: =D140 -> 0.44397582
A141: 5 | B141: =INDEX($B$80:$Q$80,MATCH(C141,$B$132:$Q$132,0)) -> Canberra — Elec | C141: =LARGE($B$132:$Q$132,A141) -> 1.3836774 | D141: =C141-1 -> 0.38367741 | AC141: =B141 -> Canberra — Elec | AD141: =D141 -> 0.38367741
A142: 6 | B142: =INDEX($B$80:$Q$80,MATCH(C142,$B$132:$Q$132,0)) -> Adelaide — Elec | C142: =LARGE($B$132:$Q$132,A142) -> 1.3749851 | D142: =C142-1 -> 0.37498514 | AC142: =B142 -> Adelaide — Elec | AD142: =D142 -> 0.37498514
A143: 7 | B143: =INDEX($B$80:$Q$80,MATCH(C143,$B$132:$Q$132,0)) -> Adelaide — Gas | C143: =LARGE($B$132:$Q$132,A143) -> 1.365097 | D143: =C143-1 -> 0.36509695 | AC143: =B143 -> Adelaide — Gas | AD143: =D143 -> 0.36509695
A144: 8 | B144: =INDEX($B$80:$Q$80,MATCH(C144,$B$132:$Q$132,0)) -> Darwin — Gas | C144: =LARGE($B$132:$Q$132,A144) -> 1.3438013 | D144: =C144-1 -> 0.34380127 | AC144: =B144 -> Darwin — Gas | AD144: =D144 -> 0.34380127
A145: 9 | B145: =INDEX($B$80:$Q$80,MATCH(C145,$B$132:$Q$132,0)) -> Canberra — Gas | C145: =LARGE($B$132:$Q$132,A145) -> 1.3262025 | D145: =C145-1 -> 0.3262025 | AC145: =B145 -> Canberra — Gas | AD145: =D145 -> 0.3262025
A146: 10 | B146: =INDEX($B$80:$Q$80,MATCH(C146,$B$132:$Q$132,0)) -> Hobart — Elec | C146: =LARGE($B$132:$Q$132,A146) -> 1.2434138 | D146: =C146-1 -> 0.24341377 | AC146: =B146 -> Hobart — Elec | AD146: =D146 -> 0.24341377
A147: 11 | B147: =INDEX($B$80:$Q$80,MATCH(C147,$B$132:$Q$132,0)) -> Perth — Gas | C147: =LARGE($B$132:$Q$132,A147) -> 1.2396201 | D147: =C147-1 -> 0.23962011 | AC147: =B147 -> Perth — Gas | AD147: =D147 -> 0.23962011
A148: 12 | B148: =INDEX($B$80:$Q$80,MATCH(C148,$B$132:$Q$132,0)) -> Hobart — Gas | C148: =LARGE($B$132:$Q$132,A148) -> 1.2251124 | D148: =C148-1 -> 0.22511243 | AC148: =B148 -> Hobart — Gas | AD148: =D148 -> 0.22511243
... A152: 16 | B152: =INDEX($B$80:$Q$80,MATCH(C152,$B$132:$Q$132,0)) -> Perth — Elec | C152: =LARGE($B$132:$Q$132,A152) -> 0.99415011 | D152: =C152-1 -> -0.0058498896 | AC152: =B152 -> Perth — Elec | AD152: =D152 -> -0.0058498896

Sheet Telecom Prices
A1: Telecommunications & Communication Prices — ABS CPI (Sydney + 7 capitals)
A2: Source: ABS 6401.0 Consumer Price Index, Table 10. Index reference period: September 2025 = 100.00. All series Original (not seasonally adjusted).
A4: Note: ABS rebased these series with September 2025 = 100; only 22 months of data are available (Dec 2023 – Sep 2025). Two related series are shown: 'Telecommunication equipment and services' and the broader 'Communication' group.
A6: A. Telecommunication Equipment and Services — Monthly Index, Dec 2023 – Sep 2025 (Sep 2025 = 100) | L6: Summary Statistics
A7: Month | B7: Sydney | C7: Melbourne | D7: Brisbane | E7: Adelaide | F7: Perth | G7: Hobart | H7: Darwin | I7: Canberra | J7: 8-Capital Avg | L7: City | M7: First (Dec-23) | N7: Latest (Sep-25) | O7: Min | P7: Max | Q7: Mean | R7: Std Dev | S7: % Change (Dec-23 → Sep-25) | T7: YoY % (Sep-25 vs Sep-24) | U7: MoM % (latest)
A8: =Data1!A90 -> 45383 | B8: =Data1!DA90 -> 98.61 | C8: =Data1!IC90 -> 98.61 | D8: =Data2!DO90 -> 98.63 | E8: =Data2!IQ90 -> 98.66 | F8: =Data3!EC90 -> 98.57 | G8: =Data4!O90 -> 98.48 | H8: =Data4!EQ90 -> 98.73 | I8: =Data5!AC90 -> 98.64 | J8: =AVERAGE(B8:I8) -> 98.61625 | L8: Telecommunication Equipment & Services
A9: =Data1!A91 -> 45413 | B9: =Data1!DA91 -> 98.06 | C9: =Data1!IC91 -> 98.06 | D9: =Data2!DO91 -> 98.07 | E9: =Data2!IQ91 -> 98.11 | F9: =Data3!EC91 -> 98.03 | G9: =Data4!O91 -> 97.94 | H9: =Data4!EQ91 -> 98.16 | I9: =Data5!AC91 -> 98.09 | J9: =AVERAGE(B9:I9) -> 98.065 | L9: Sydney | M9: =B8 -> 98.61 | N9: =B29 -> 99.65 | O9: =MIN(B8:B29) -> 97.51 | P9: =MAX(B8:B29) -> 100.24 | Q9: =AVERAGE(B8:B29) -> 99.071364 | R9: =STDEV(B8:B29) -> 0.72044494 | S9: =B29/B8-1 -> 0.010546598 | T9: =B29/B17-1 -> 0.011264461 | U9: =B29/B28-1 -> -0.0009023461
A10: =Data1!A92 -> 45444 | B10: =Data1!DA92 -> 97.51 | C10: =Data1!IC92 -> 97.52 | D10: =Data2!DO92 -> 97.53 | E10: =Data2!IQ92 -> 97.56 | F10: =Data3!EC92 -> 97.48 | G10: =Data4!O92 -> 97.4 | H10: =Data4!EQ92 -> 97.61 | I10: =Data5!AC92 -> 97.54 | J10: =AVERAGE(B10:I10) -> 97.51875 | L10: Melbourne | M10: =C8 -> 98.61 | N10: =C29 -> 99.66 | O10: =MIN(C8:C29) -> 97.52 | P10: =MAX(C8:C29) -> 100.23 | Q10: =AVERAGE(C8:C29) -> 99.075455 | R10: =STDEV(C8:C29) -> 0.71972036 | S10: =C29/C8-1 -> 0.010648007 | T10: =C29/C17-1 -> 0.011365943 | U10: =C29/C28-1 -> -0.00090225564 | V10: =C30/C29-1 -> -1
A11: =Data1!A93 -> 45474 | B11: =Data1!DA93 -> 99.02 | C11: =Data1!IC93 -> 99.02 | D11: =Data2!DO93 -> 99.03 | E11: =Data2!IQ93 -> 99.06 | F11: =Data3!EC93 -> 98.99 | G11: =Data4!O93 -> 98.91 | H11: =Data4!EQ93 -> 99.11 | I11: =Data5!AC93 -> 99.04 | J11: =AVERAGE(B11:I11) -> 99.0225 | L11: Brisbane | M11: =D8 -> 98.63 | N11: =D29 -> 99.66 | O11: =MIN(D8:D29) -> 97.53 | P11: =MAX(D8:D29) -> 100.23 | Q11: =AVERAGE(D8:D29) -> 99.081818 | R11: =STDEV(D8:D29) -> 0.71722107 | S11: =D29/D8-1 -> 0.01044307 | T11: =D29/D17-1 -> 0.011263318 | U11: =D29/D28-1 -> -0.00090225564
A12: =Data1!A94 -> 45505 | B12: =Data1!DA94 -> 98.48 | C12: =Data1!IC94 -> 98.48 | D12: =Data2!DO94 -> 98.49 | E12: =Data2!IQ94 -> 98.51 | F12: =Data3!EC94 -> 98.45 | G12: =Data4!O94 -> 98.39 | H12: =Data4!EQ94 -> 98.56 | I12: =Data5!AC94 -> 98.5 | J12: =AVERAGE(B12:I12) -> 98.4825 | L12: Adelaide | M12: =E8 -> 98.66 | N12: =E29 -> 99.68 | O12: =MIN(E8:E29) -> 97.56 | P12: =MAX(E8:E29) -> 100.25 | Q12: =AVERAGE(E8:E29) -> 99.101818 | R12: =STDEV(E8:E29) -> 0.71136111 | S12: =E29/E8-1 -> 0.010338536 | T12: =E29/E17-1 -> 0.01115845 | U12: =E29/E28-1 -> -0.00090207477
A13: =Data1!A95 -> 45536 | B13: =Data1!DA95 -> 98.53 | C13: =Data1!IC95 -> 98.54 | D13: =Data2!DO95 -> 98.55 | E13: =Data2!IQ95 -> 98.57 | F13: =Data3!EC95 -> 98.51 | G13: =Data4!O95 -> 98.44 | H13: =Data4!EQ95 -> 98.62 | I13: =Data5!AC95 -> 98.56 | J13: =AVERAGE(B13:I13) -> 98.54 | L13: Perth | M13: =F8 -> 98.57 | N13: =F29 -> 99.63 | O13: =MIN(F8:F29) -> 97.48 | P13: =MAX(F8:F29) -> 100.25 | Q13: =AVERAGE(F8:F29) -> 99.052273 | R13: =STDEV(F8:F29) -> 0.72611774 | S13: =F29/F8-1 -> 0.010753779 | T13: =F29/F17-1 -> 0.011369404 | U13: =F29/F28-1 -> -0.00090252708
A14: =Data1!A96 -> 45566 | B14: =Data1!DA96 -> 99.24 | C14: =Data1!IC96 -> 99.25 | D14: =Data2!DO96 -> 99.26 | E14: =Data2!IQ96 -> 99.29 | F14: =Data3!EC96 -> 99.22 | G14: =Data4!O96 -> 99.13 | H14: =Data4!EQ96 -> 99.35 | I14: =Data5!AC96 -> 99.27 | J14: =AVERAGE(B14:I14) -> 99.25125 | L14: Hobart | M14: =G8 -> 98.48 | N14: =G29 -> 99.57 | O14: =MIN(G8:G29) -> 97.4 | P14: =MAX(G8:G29) -> 100.28 | Q14: =AVERAGE(G8:G29) -> 98.997273 | R14: =STDEV(G8:G29) -> 0.74181362 | S14: =G29/G8-1 -> 0.011068237 | T14: =G29/G17-1 -> 0.011684617 | U14: =G29/G28-1 -> -0.0010033109
A15: =Data1!A97 -> 45597 | B15: =Data1!DA97 -> 99.13 | C15: =Data1!IC97 -> 99.14 | D15: =Data2!DO97 -> 99.15 | E15: =Data2!IQ97 -> 99.18 | F15: =Data3!EC97 -> 99.1 | G15: =Data4!O97 -> 99.01 | H15: =Data4!EQ97 -> 99.24 | I15: =Data5!AC97 -> 99.16 | J15: =AVERAGE(B15:I15) -> 99.13875 | L15: Darwin | M15: =H8 -> 98.73 | N15: =H29 -> 99.72 | O15: =MIN(H8:H29) -> 97.61 | P15: =MAX(H8:H29) -> 100.29 | Q15: =AVERAGE(H8:H29) -> 99.138182 | R15: =STDEV(H8:H29) -> 0.70353283 | S15: =H29/H8-1 -> 0.010027347 | T15: =H29/H17-1 -> 0.010948905 | U15: =H29/H28-1 -> -0.00090171326
A16: =Data1!A98 -> 45627 | B16: =Data1!DA98 -> 98.91 | C16: =Data1!IC98 -> 98.92 | D16: =Data2!DO98 -> 98.93 | E16: =Data2!IQ98 -> 98.96 | F16: =Data3!EC98 -> 98.88 | G16: =Data4!O98 -> 98.8 | H16: =Data4!EQ98 -> 99.01 | I16: =Data5!AC98 -> 98.94 | J16: =AVERAGE(B16:I16) -> 98.91875 | L16: Canberra | M16: =I8 -> 98.64 | N16: =I29 -> 99.67 | O16: =MIN(I8:I29) -> 97.54 | P16: =MAX(I8:I29) -> 100.24 | Q16: =AVERAGE(I8:I29) -> 99.09 | R16: =STDEV(I8:I29) -> 0.71504246 | S16: =I29/I8-1 -> 0.010442011 | T16: =I29/I17-1 -> 0.011262175 | U16: =I29/I28-1 -> -0.0009021652
A17: =Data1!A99 -> 45658 | B17: =Data1!DA99 -> 98.54 | C17: =Data1!IC99 -> 98.54 | D17: =Data2!DO99 -> 98.55 | E17: =Data2!IQ99 -> 98.58 | F17: =Data3!EC99 -> 98.51 | G17: =Data4!O99 -> 98.42 | H17: =Data4!EQ99 -> 98.64 | I17: =Data5!AC99 -> 98.56 | J17: =AVERAGE(B17:I17) -> 98.5425 | L17: 8-Capital Avg | M17: =J8 -> 98.61625 | N17: =J29 -> 99.655 | O17: =MIN(J8:J29) -> 97.51875 | P17: =MAX(J8:J29) -> 100.235 | Q17: =AVERAGE(J8:J29) -> 99.076023 | R17: =STDEV(J8:J29) -> 0.7190574 | S17: =J29/J8-1 -> 0.010533254 | T17: =J29/J17-1 -> 0.011289545 | U17: =J29/J28-1 -> -0.00091482136
A18: =Data1!A100 -> 45689 | B18: =Data1!DA100 -> 99.23 | C18: =Data1!IC100 -> 99.24 | D18: =Data2!DO100 -> 99.24 | E18: =Data2!IQ100 -> 99.26 | F18: =Data3!EC100 -> 99.22 | G18: =Data4!O100 -> 99.18 | H18: =Data4!EQ100 -> 99.28 | I18: =Data5!AC100 -> 99.25 | J18: =AVERAGE(B18:I18) -> 99.2375 | L18: Communication (broader group)
A19: =Data1!A101 -> 45717 | B19: =Data1!DA101 -> 99.06 | C19: =Data1!IC101 -> 99.07 | D19: =Data2!DO101 -> 99.08 | E19: =Data2!IQ101 -> 99.1 | F19: =Data3!EC101 -> 99.04 | G19: =Data4!O101 -> 98.98 | H19: =Data4!EQ101 -> 99.14 | I19: =Data5!AC101 -> 99.08 | J19: =AVERAGE(B19:I19) -> 99.06875 | L19: Sydney | M19: =B33 -> 98.52 | N19: =B54 -> 99.72 | O19: =MIN(B33:B54) -> 97.2 | P19: =MAX(B33:B54) -> 100.24 | Q19: =AVERAGE(B33:B54) -> 98.975909 | R19: =STDEV(B33:B54) -> 0.79237232 | S19: =B54/B33-1 -> 0.012180268 | T19: =B54/B42-1 -> 0.014136072 | U19: =B54/B53-1 -> -0.00090171326
A20: =Data1!A102 -> 45748 | B20: =Data1!DA102 -> 99.27 | C20: =Data1!IC102 -> 99.27 | D20: =Data2!DO102 -> 99.28 | E20: =Data2!IQ102 -> 99.31 | F20: =Data3!EC102 -> 99.24 | G20: =Data4!O102 -> 99.17 | H20: =Data4!EQ102 -> 99.35 | I20: =Data5!AC102 -> 99.29 | J20: =AVERAGE(B20:I20) -> 99.2725 | L20: Melbourne | M20: =C33 -> 98.54 | N20: =C54 -> 99.71 | O20: =MIN(C33:C54) -> 97.25 | P20: =MAX(C33:C54) -> 100.24 | Q20: =AVERAGE(C33:C54) -> 98.991364 | R20: =STDEV(C33:C54) -> 0.78008116 | S20: =C54/C33-1 -> 0.011873351 | T20: =C54/C42-1 -> 0.013622039 | U20: =C54/C53-1 -> -0.00090180361
A21: =Data1!A103 -> 45778 | B21: =Data1!DA103 -> 98.89 | C21: =Data1!IC103 -> 98.89 | D21: =Data2!DO103 -> 98.89 | E21: =Data2!IQ103 -> 98.89 | F21: =Data3!EC103 -> 98.89 | G21: =Data4!O103 -> 98.89 | H21: =Data4!EQ103 -> 98.89 | I21: =Data5!AC103 -> 98.89 | J21: =AVERAGE(B21:I21) -> 98.89 | L21: Brisbane | M21: =D33 -> 98.56 | N21: =D54 -> 99.71 | O21: =MIN(D33:D54) -> 97.31 | P21: =MAX(D33:D54) -> 100.25 | Q21: =AVERAGE(D33:D54) -> 99.013182 | R21: =STDEV(D33:D54) -> 0.76773251 | S21: =D54/D33-1 -> 0.011668019 | T21: =D54/D42-1 -> 0.01321004 | U21: =D54/D53-1 -> -0.00090180361
A22: =Data1!A104 -> 45809 | B22: =Data1!DA104 -> 97.99 | C22: =Data1!IC104 -> 97.99 | D22: =Data2!DO104 -> 97.99 | E22: =Data2!IQ104 -> 98 | F22: =Data3!EC104 -> 97.99 | G22: =Data4!O104 -> 97.98 | H22: =Data4!EQ104 -> 98 | I22: =Data5!AC104 -> 98 | J22: =AVERAGE(B22:I22) -> 97.9925 | L22: Adelaide | M22: =E33 -> 98.59 | N22: =E54 -> 99.73 | O22: =MIN(E33:E54) -> 97.33 | P22: =MAX(E33:E54) -> 100.27 | Q22: =AVERAGE(E33:E54) -> 99.03 | R22: =STDEV(E33:E54) -> 0.764336 | S22: =E54/E33-1 -> 0.011563039 | T22: =E54/E42-1 -> 0.013207355 | U22: =E54/E53-1 -> -0.00090162292
A23: =Data1!A105 -> 45839 | B23: =Data1!DA105 -> 99.5 | C23: =Data1!IC105 -> 99.5 | D23: =Data2!DO105 -> 99.5 | E23: =Data2!IQ105 -> 99.5 | F23: =Data3!EC105 -> 99.5 | G23: =Data4!O105 -> 99.49 | H23: =Data4!EQ105 -> 99.51 | I23: =Data5!AC105 -> 99.5 | J23: =AVERAGE(B23:I23) -> 99.5 | L23: Perth | M23: =F33 -> 98.51 | N23: =F54 -> 99.68 | O23: =MIN(F33:F54) -> 97.27 | P23: =MAX(F33:F54) -> 100.22 | Q23: =AVERAGE(F33:F54) -> 98.985909 | R23: =STDEV(F33:F54) -> 0.77565124 | S23: =F54/F33-1 -> 0.011876967 | T23: =F54/F42-1 -> 0.013317068 | U23: =F54/F53-1 -> -0.00090207477
A24: =Data1!A106 -> 45870 | B24: =Data1!DA106 -> 100.24 | C24: =Data1!IC106 -> 100.23 | D24: =Data2!DO106 -> 100.23 | E24: =Data2!IQ106 -> 100.22 | F24: =Data3!EC106 -> 100.25 | G24: =Data4!O106 -> 100.28 | H24: =Data4!EQ106 -> 100.2 | I24: =Data5!AC106 -> 100.23 | J24: =AVERAGE(B24:I24) -> 100.235 | L24: Hobart | M24: =G33 -> 98.4 | N24: =G54 -> 99.64 | O24: =MIN(G33:G54) -> 97.12 | P24: =MAX(G33:G54) -> 100.24 | Q24: =AVERAGE(G33:G54) -> 98.910455 | R24: =STDEV(G33:G54) -> 0.80897629 | S24: =G54/G33-1 -> 0.012601626 | T24: =G54/G42-1 -> 0.014250814 | U24: =G54/G53-1 -> -0.00090243658
A25: =Data1!A107 -> 45901 | B25: =Data1!DA107 -> 100 | C25: =Data1!IC107 -> 100 | D25: =Data2!DO107 -> 100 | E25: =Data2!IQ107 -> 100 | F25: =Data3!EC107 -> 100 | G25: =Data4!O107 -> 100 | H25: =Data4!EQ107 -> 100 | I25: =Data5!AC107 -> 100 | J25: =AVERAGE(B25:I25) -> 100 | L25: Darwin | M25: =H33 -> 98.65 | N25: =H54 -> 99.77 | O25: =MIN(H33:H54) -> 97.36 | P25: =MAX(H33:H54) -> 100.31 | Q25: =AVERAGE(H33:H54) -> 99.058182 | R25: =STDEV(H33:H54) -> 0.75953392 | S25: =H54/H33-1 -> 0.011353269 | T25: =H54/H42-1 -> 0.01320199 | U25: =H54/H53-1 -> -0.00090126177
A26: =Data1!A108 -> 45931 | B26: =Data1!DA108 -> 99.75 | C26: =Data1!IC108 -> 99.76 | D26: =Data2!DO108 -> 99.76 | E26: =Data2!IQ108 -> 99.78 | F26: =Data3!EC108 -> 99.73 | G26: =Data4!O108 -> 99.67 | H26: =Data4!EQ108 -> 99.82 | I26: =Data5!AC108 -> 99.77 | J26: =AVERAGE(B26:I26) -> 99.755 | L26: Canberra | M26: =I33 -> 98.51 | N26: =I54 -> 99.76 | O26: =MIN(I33:I54) -> 97.1 | P26: =MAX(I33:I54) -> 100.27 | Q26: =AVERAGE(I33:I54) -> 98.950909 | R26: =STDEV(I33:I54) -> 0.81936624 | S26: =I54/I33-1 -> 0.012689067 | T26: =I54/I42-1 -> 0.015162308 | U26: =I54/I53-1 -> -0.00090135203
A27: =Data1!A109 -> 45962 | B27: =Data1!DA109 -> 100.22 | C27: =Data1!IC109 -> 100.22 | D27: =Data2!DO109 -> 100.23 | E27: =Data2!IQ109 -> 100.25 | F27: =Data3!EC109 -> 100.2 | G27: =Data4!O109 -> 100.14 | H27: =Data4!EQ109 -> 100.29 | I27: =Data5!AC109 -> 100.24 | J27: =AVERAGE(B27:I27) -> 100.22375 | L27: 8-Capital Avg | M27: =J33 -> 98.535 | N27: =J54 -> 99.715 | O27: =MIN(J33:J54) -> 97.2425 | P27: =MAX(J33:J54) -> 100.24625 | Q27: =AVERAGE(J33:J54) -> 98.989489 | R27: =STDEV(J33:J54) -> 0.78302818 | S27: =J54/J33-1 -> 0.01197544 | T27: =J54/J42-1 -> 0.013763042 | U27: =J54/J53-1 -> -0.00090175843
A28: =Data1!A110 -> 45992 | B28: =Data1!DA110 -> 99.74 | C28: =Data1!IC110 -> 99.75 | D28: =Data2!DO110 -> 99.75 | E28: =Data2!IQ110 -> 99.77 | F28: =Data3!EC110 -> 99.72 | G28: =Data4!O110 -> 99.67 | H28: =Data4!EQ110 -> 99.81 | I28: =Data5!AC110 -> 99.76 | J28: =AVERAGE(B28:I28) -> 99.74625
A29: =Data1!A111 -> 46023 | B29: =Data1!DA111 -> 99.65 | C29: =Data1!IC111 -> 99.66 | D29: =Data2!DO111 -> 99.66 | E29: =Data2!IQ111 -> 99.68 | F29: =Data3!EC111 -> 99.63 | G29: =Data4!O111 -> 99.57 | H29: =Data4!EQ111 -> 99.72 | I29: =Data5!AC111 -> 99.67 | J29: =AVERAGE(B29:I29) -> 99.655
A31: B. Communication (CPI sub-group, broader) — Monthly Index, Dec 2023 – Sep 2025 (Sep 2025 = 100)
A32: Month | B32: Sydney | C32: Melbourne | D32: Brisbane | E32: Adelaide | F32: Perth | G32: Hobart | H32: Darwin | I32: Canberra | J32: 8-Capital Avg
A33: =Data1!A90 -> 45383 | B33: =Data1!CY90 -> 98.52 | C33: =Data1!IA90 -> 98.54 | D33: =Data2!DM90 -> 98.56 | E33: =Data2!IO90 -> 98.59 | F33: =Data3!EA90 -> 98.51 | G33: =Data4!M90 -> 98.4 | H33: =Data4!EO90 -> 98.65 | I33: =Data5!AA90 -> 98.51 | J33: =AVERAGE(B33:I33) -> 98.535
A34: =Data1!A91 -> 45413 | B34: =Data1!CY91 -> 97.86 | C34: =Data1!IA91 -> 97.89 | D34: =Data2!DM91 -> 97.93 | E34: =Data2!IO91 -> 97.96 | F34: =Data3!EA91 -> 97.89 | G34: =Data4!M91 -> 97.76 | H34: =Data4!EO91 -> 98 | I34: =Data5!AA91 -> 97.8 | J34: =AVERAGE(B34:I34) -> 97.88625
A35: =Data1!A92 -> 45444 | B35: =Data1!CY92 -> 97.2 | C35: =Data1!IA92 -> 97.25 | D35: =Data2!DM92 -> 97.31 | E35: =Data2!IO92 -> 97.33 | F35: =Data3!EA92 -> 97.27 | G35: =Data4!M92 -> 97.12 | H35: =Data4!EO92 -> 97.36 | I35: =Data5!AA92 -> 97.1 | J35: =AVERAGE(B35:I35) -> 97.2425
A36: =Data1!A93 -> 45474 | B36: =Data1!CY93 -> 98.87 | C36: =Data1!IA93 -> 98.89 | D36: =Data2!DM93 -> 98.92 | E36: =Data2!IO93 -> 98.95 | F36: =Data3!EA93 -> 98.88 | G36: =Data4!M93 -> 98.77 | H36: =Data4!EO93 -> 98.99 | I36: =Data5!AA93 -> 98.83 | J36: =AVERAGE(B36:I36) -> 98.8875
A37: =Data1!A94 -> 45505 | B37: =Data1!CY94 -> 98.36 | C37: =Data1!IA94 -> 98.38 | D37: =Data2!DM94 -> 98.4 | E37: =Data2!IO94 -> 98.42 | F37: =Data3!EA94 -> 98.37 | G37: =Data4!M94 -> 98.28 | H37: =Data4!EO94 -> 98.46 | I37: =Data5!AA94 -> 98.33 | J37: =AVERAGE(B37:I37) -> 98.375
A38: =Data1!A95 -> 45536 | B38: =Data1!CY95 -> 98.4 | C38: =Data1!IA95 -> 98.42 | D38: =Data2!DM95 -> 98.45 | E38: =Data2!IO95 -> 98.47 | F38: =Data3!EA95 -> 98.41 | G38: =Data4!M95 -> 98.31 | H38: =Data4!EO95 -> 98.5 | I38: =Data5!AA95 -> 98.36 | J38: =AVERAGE(B38:I38) -> 98.415
A39: =Data1!A96 -> 45566 | B39: =Data1!CY96 -> 99.02 | C39: =Data1!IA96 -> 99.06 | D39: =Data2!DM96 -> 99.1 | E39: =Data2!IO96 -> 99.13 | F39: =Data3!EA96 -> 99.06 | G39: =Data4!M96 -> 98.93 | H39: =Data4!EO96 -> 99.16 | I39: =Data5!AA96 -> 98.95 | J39: =AVERAGE(B39:I39) -> 99.05125
A40: =Data1!A97 -> 45597 | B40: =Data1!CY97 -> 98.91 | C40: =Data1!IA97 -> 98.94 | D40: =Data2!DM97 -> 98.99 | E40: =Data2!IO97 -> 99.01 | F40: =Data3!EA97 -> 98.94 | G40: =Data4!M97 -> 98.8 | H40: =Data4!EO97 -> 99.05 | I40: =Data5!AA97 -> 98.84 | J40: =AVERAGE(B40:I40) -> 98.935
A41: =Data1!A98 -> 45627 | B41: =Data1!CY98 -> 98.69 | C41: =Data1!IA98 -> 98.72 | D41: =Data2!DM98 -> 98.77 | E41: =Data2!IO98 -> 98.79 | F41: =Data3!EA98 -> 98.73 | G41: =Data4!M98 -> 98.6 | H41: =Data4!EO98 -> 98.83 | I41: =Data5!AA98 -> 98.62 | J41: =AVERAGE(B41:I41) -> 98.71875
A42: =Data1!A99 -> 45658 | B42: =Data1!CY99 -> 98.33 | C42: =Data1!IA99 -> 98.37 | D42: =Data2!DM99 -> 98.41 | E42: =Data2!IO99 -> 98.43 | F42: =Data3!EA99 -> 98.37 | G42: =Data4!M99 -> 98.24 | H42: =Data4!EO99 -> 98.47 | I42: =Data5!AA99 -> 98.27 | J42: =AVERAGE(B42:I42) -> 98.36125
A43: =Data1!A100 -> 45689 | B43: =Data1!CY100 -> 99.07 | C43: =Data1!IA100 -> 99.09 | D43: =Data2!DM100 -> 99.12 | E43: =Data2!IO100 -> 99.13 | F43: =Data3!EA100 -> 99.1 | G43: =Data4!M100 -> 99.02 | H43: =Data4!EO100 -> 99.15 | I43: =Data5!AA100 -> 99.01 | J43: =AVERAGE(B43:I43) -> 99.08625
A44: =Data1!A101 -> 45717 | B44: =Data1!CY101 -> 98.93 | C44: =Data1!IA101 -> 98.95 | D44: =Data2!DM101 -> 98.98 | E44: =Data2!IO101 -> 99 | F44: =Data3!EA101 -> 98.95 | G44: =Data4!M101 -> 98.86 | H44: =Data4!EO101 -> 99.03 | I44: =Data5!AA101 -> 98.89 | J44: =AVERAGE(B44:I44) -> 98.94875
... A54: =Data1!A111 -> 46023 | B54: =Data1!CY111 -> 99.72 | C54: =Data1!IA111 -> 99.71 | D54: =Data2!DM111 -> 99.71 | E54: =Data2!IO111 -> 99.73 | F54: =Data3!EA111 -> 99.68 | G54: =Data4!M111 -> 99.64 | H54: =Data4!EO111 -> 99.77 | I54: =Data5!AA111 -> 99.76 | J54: =AVERAGE(B54:I54) -> 99.715

Sheet Data1
B1: Index Numbers ; All groups CPI ; Sydney ; | C1: Index Numbers ; Food and non-alcoholic beverages ; Sydney ; | D1: Index Numbers ; Bread and cereal products ; Sydney ; | E1: Index Numbers ; Bread ; Sydney ; | F1: Index Numbers ; Cakes and biscuits ; Sydney ; | G1: Index Numbers ; Breakfast cereals ; Sydney ; | H1: Index Numbers ; Other cereal products ; Sydney ; | I1: Index Numbers ; Meat and seafoods ; Sydney ; | J1: Index Numbers ; Beef and veal ; Sydney ; | K1: Index Numbers ; Pork ; Sydney ; | L1: Index Numbers ; Lamb and goat ; Sydney ; | M1: Index Numbers ; Poultry ; Sydney ; | N1: Index Numbers ; Other meats ; Sydney ; | O1: Index Numbers ; Fish and other seafood ; Sydney ; | P1: Index Numbers ; Dairy and related products ; Sydney ; | Q1: Index Numbers ; Milk ; Sydney ; | R1: Index Numbers ; Cheese ; Sydney ; | S1: Index Numbers ; Ice cream and other dairy products ; Sydney ; | T1: Index Numbers ; Fruit and vegetables ; Sydney ; | U1: Index Numbers ; Fruit ; Sydney ; | V1: Index Numbers ; Vegetables ; Sydney ; | W1: Index Numbers ; Food products n.e.c. ; Sydney ; | X1: Index Numbers ; Eggs ; Sydney ; | Y1: Index Numbers ; Jams, honey and spreads ; Sydney ; | Z1: Index Numbers ; Food additives and condiments ; Sydney ; | AA1: Index Numbers ; Oils and fats ; Sydney ; | AB1: Index Numbers ; Snacks and confectionery ; Sydney ; | AC1: Index Numbers ; Other food products n.e.c. ; Sydney ; | AD1: Index Numbers ; Non-alcoholic beverages ; Sydney ; | AE1: Index Numbers ; Coffee, tea and cocoa ; Sydney ; | AF1: Index Numbers ; Waters, soft drinks and juices ; Sydney ; | AG1: Index Numbers ; Meals out and take away foods ; Sydney ; | AH1: Index Numbers ; Restaurant meals ; Sydney ; | AI1: Index Numbers ; Take away and fast foods ; Sydney ; | AJ1: Index Numbers ; Alcohol and tobacco ; Sydney ; | AK1: Index Numbers ; Alcoholic beverages ; Sydney ; | AL1: Index Numbers ; Spirits ; Sydney ; | AM1: Index Numbers ; Wine ; Sydney ; | AN1: Index Numbers ; Beer ; Sydney ; | AO1: Index Numbers ; Tobacco ; Sydney ; | AP1: Index Numbers ; Tobacco ; Sydney ; | AQ1: Index Numbers ; Clothing and footwear ; Sydney ; | AR1: Index Numbers ; Garments ; Sydney ; | AS1: Index Numbers ; Garments for men ; Sydney ; | AT1: Index Numbers ; Garments for women ; Sydney ; | AU1: Index Numbers ; Garments for infants and children ; Sydney ; | AV1: Index Numbers ; Footwear ; Sydney ; | AW1: Index Numbers ; Footwear for men ; Sydney ; | AX1: Index Numbers ; Footwear for women ; Sydney ; | AY1: Index Numbers ; Footwear for infants and children ; Sydney ; | AZ1: Index Numbers ; Accessories and clothing services ; Sydney ; | BA1: Index Numbers ; Accessories ; Sydney ; | BB1: Index Numbers ; Cleaning, repair and hire of clothing and footwear ; Sydney ; | BC1: Index Numbers ; Housing ; Sydney ; | BD1: Index Numbers ; Rents ; Sydney ; | BE1: Index Numbers ; Rents ; Sydney ; | BF1: Index Numbers ; New dwelling purchase by owner-occupiers ; Sydney ; | BG1: Index Numbers ; New dwelling purchase by owner-occupiers ; Sydney ; | BH1: Index Numbers ; Other housing ; Sydney ; | BI1: Index Numbers ; Maintenance and repair of the dwelling ; Sydney ; | BJ1: Index Numbers ; Property rates and charges ; Sydney ; | BK1: Index Numbers ; Utilities ; Sydney ; | BL1: Index Numbers ; Water and sewerage ; Sydney ; | BM1: Index Numbers ; Electricity ; Sydney ; | BN1: Index Numbers ; Gas and other household fuels ; Sydney ; | BO1: Index Numbers ; Furnishings, household equipment and services ; Sydney ; | BP1: Index Numbers ; Furniture and furnishings ; Sydney ; | BQ1: Index Numbers ; Furniture ; Sydney ; | BR1: Index Numbers ; Carpets and other floor coverings ; Sydney ; | BS1: Index Numbers ; Household textiles ; Sydney ; | BT1: Index Numbers ; Household textiles ; Sydney ; | BU1: Index Numbers ; Household appliances, utensils and tools ; Sydney ; | BV1: Index Numbers ; Major household appliances ; Sydney ; | BW1: Index Numbers ; Small electric household appliances ; Sydney ; | BX1: Index Numbers ; Glassware, tableware and household utensils ; Sydney ; | BY1: Index Numbers ; Tools and equipment for house and garden ; Sydney ; | BZ1: Index Numbers ; Non-durable household products ; Sydney ; | CA1: Index Numbers ; Cleaning and maintenance products ; Sydney ; | CB1: Index Numbers ; Personal care products ; Sydney ; | CC1: Index Numbers ; Other non-durable household products ; Sydney ; | CD1: Index Numbers ; Domestic and household services ; Sydney ; | CE1: Index Numbers ; Child care ; Sydney ; | CF1: Index Numbers ; Hairdressing and personal grooming services ; Sydney ; | CG1: Index Numbers ; Other household services ; Sydney ; | CH1: Index Numbers ; Health ; Sydney ; | CI1: Index Numbers ; Medical products, appliances and equipment ; Sydney ; | CJ1: Index Numbers ; Pharmaceutical products ; Sydney ; | CK1: Index Numbers ; Therapeutic appliances and equipment ; Sydney ; | CL1: Index Numbers ; Medical, dental and hospital services ; Sydney ; | CM1: Index Numbers ; Medical and hospital services ; Sydney ; | CN1: Index Numbers ; Dental services ; Sydney ; | CO1: Index Numbers ; Transport ; Sydney ; | CP1: Index Numbers ; Private motoring ; Sydney ; | CQ1: Index Numbers ; Motor vehicles ; Sydney ; | CR1: Index Numbers ; Spare parts and accessories for motor vehicles ; Sydney ; | CS1: Index Numbers ; Automotive fuel ; Sydney ; | CT1: Index Numbers ; Maintenance and repair of motor vehicles ; Sydney ; | CU1: Index Numbers ; Other services in respect of motor vehicles ; Sydney ; | CV1: Index Numbers ; Urban transport fares ; Sydney ; | CW1: Index Numbers ; Urban transport fares ; Sydney ; | CX1: Index Numbers ; Communication ; Sydney ; | CY1: Index Numbers ; Communication ; Sydney ; | CZ1: Index Numbers ; Postal services ; Sydney ; | DA1: Index Numbers ; Telecommunication equipment and services ; Sydney ; | DB1: Index Numbers ; Recreation and culture ; Sydney ; | DC1: Index Numbers ; Audio, visual and computing equipment and services ; Sydney ; | DD1: Index Numbers ; Audio, visual and computing equipment ; Sydney ; | DE1: Index Numbers ; Audio, visual and computing media and services ; Sydney ; | DF1: Index Numbers ; Newspapers, books and stationery ; Sydney ; | DG1: Index Numbers ; Books ; Sydney ; | DH1: Index Numbers ; Newspapers, magazines and stationery ; Sydney ; | DI1: Index Numbers ; Holiday travel and accommodation ; Sydney ; | DJ1: Index Numbers ; Domestic holiday travel and accommodation ; Sydney ; | DK1: Index Numbers ; International holiday travel and accommodation ; Sydney ; | DL1: Index Numbers ; Other recreation, sport and culture ; Sydney ; | DM1: Index Numbers ; Equipment for sports, camping and open-air recreation ; Sydney ; | DN1: Index Numbers ; Games, toys and hobbies ; Sydney ; | DO1: Index Numbers ; Pets and related products ; Sydney ; | DP1: Index Numbers ; Veterinary and other services for pets ; Sydney ; | DQ1: Index Numbers ; Sports participation ; Sydney ; | DR1: Index Numbers ; Other recreational, sporting and cultural services ; Sydney ; | DS1: Index Numbers ; Education ; Sydney ; | DT1: Index Numbers ; Education ; Sydney ; | DU1: Index Numbers ; Preschool and primary education ; Sydney ; | DV1: Index Numbers ; Secondary education ; Sydney ; | DW1: Index Numbers ; Tertiary education ; Sydney ; | DX1: Index Numbers ; Insurance and financial services ; Sydney ; | DY1: Index Numbers ; Insurance ; Sydney ; | DZ1: Index Numbers ; Insurance ; Sydney ; | EA1: Index Numbers ; Financial services ; Sydney ; | EB1: Index Numbers ; Deposit and loan facilities (direct charges) ; Sydney ; | EC1: Index Numbers ; Other financial services ; Sydney ; | ED1: Index Numbers ; All groups CPI ; Melbourne ; | EE1: Index Numbers ; Food and non-alcoholic beverages ; Melbourne ; | EF1: Index Numbers ; Bread and cereal products ; Melbourne ; | EG1: Index Numbers ; Bread ; Melbourne ; | EH1: Index Numbers ; Cakes and biscuits ; Melbourne ; | EI1: Index Numbers ; Breakfast cereals ; Melbourne ; | EJ1: Index Numbers ; Other cereal products ; Melbourne ; | EK1: Index Numbers ; Meat and seafoods ; Melbourne ; | EL1: Index Numbers ; Beef and veal ; Melbourne ; | EM1: Index Numbers ; Pork ; Melbourne ; | EN1: Index Numbers ; Lamb and goat ; Melbourne ; | EO1: Index Numbers ; Poultry ; Melbourne ; | EP1: Index Numbers ; Other meats ; Melbourne ; | EQ1: Index Numbers ; Fish and other seafood ; Melbourne ; | ER1: Index Numbers ; Dairy and related products ; Melbourne ; | ES1: Index Numbers ; Milk ; Melbourne ; | ET1: Index Numbers ; Cheese ; Melbourne ; | EU1: Index Numbers ; Ice cream and other dairy products ; Melbourne ; | EV1: Index Numbers ; Fruit and vegetables ; Melbourne ; | EW1: Index Numbers ; Fruit ; Melbourne ; | EX1: Index Numbers ; Vegetables ; Melbourne ; | EY1: Index Numbers ; Food products n.e.c. ; Melbourne ; | EZ1: Index Numbers ; Eggs ; Melbourne ; | FA1: Index Numbers ; Jams, honey and spreads ; Melbourne ; | FB1: Index Numbers ; Food additives and condiments ; Melbourne ; | FC1: Index Numbers ; Oils and fats ; Melbourne ; | FD1: Index Numbers ; Snacks and confectionery ; Melbourne ; | FE1: Index Numbers ; Other food products n.e.c. ; Melbourne ; | FF1: Index Numbers ; Non-alcoholic beverages ; Melbourne ; | FG1: Index Numbers ; Coffee, tea and cocoa ; Melbourne ; | FH1: Index Numbers ; Waters, soft drinks and juices ; Melbourne ; | FI1: Index Numbers ; Meals out and take away foods ; Melbourne ; | FJ1: Index Numbers ; Restaurant meals ; Melbourne ; | FK1: Index Numbers ; Take away and fast foods ; Melbourne ; | FL1: Index Numbers ; Alcohol and tobacco ; Melbourne ; | FM1: Index Numbers ; Alcoholic beverages ; Melbourne ; | FN1: Index Numbers ; Spirits ; Melbourne ; | FO1: Index Numbers ; Wine ; Melbourne ; | FP1: Index Numbers ; Beer ; Melbourne ; | FQ1: Index Numbers ; Tobacco ; Melbourne ; | FR1: Index Numbers ; Tobacco ; Melbourne ; | FS1: Index Numbers ; Clothing and footwear ; Melbourne ; | FT1: Index Numbers ; Garments ; Melbourne ; | FU1: Index Numbers ; Garments for men ; Melbourne ; | FV1: Index Numbers ; Garments for women ; Melbourne ; | FW1: Index Numbers ; Garments for infants and children ; Melbourne ; | FX1: Index Numbers ; Footwear ; Melbourne ; | FY1: Index Numbers ; Footwear for men ; Melbourne ; | FZ1: Index Numbers ; Footwear for women ; Melbourne ; | GA1: Index Numbers ; Footwear for infants and children ; Melbourne ; | GB1: Index Numbers ; Accessories and clothing services ; Melbourne ; | GC1: Index Numbers ; Accessories ; Melbourne ; | GD1: Index Numbers ; Cleaning, repair and hire of clothing and footwear ; Melbourne ; | GE1: Index Numbers ; Housing ; Melbourne ; | GF1: Index Numbers ; Rents ; Melbourne ; | GG1: Index Numbers ; Rents ; Melbourne ; | GH1: Index Numbers ; New dwelling purchase by owner-occupiers ; Melbourne ; | GI1: Index Numbers ; New dwelling purchase by owner-occupiers ; Melbourne ; | GJ1: Index Numbers ; Other housing ; Melbourne ; | GK1: Index Numbers ; Maintenance and repair of the dwelling ; Melbourne ; | GL1: Index Numbers ; Property rates and charges ; Melbourne ; | GM1: Index Numbers ; Utilities ; Melbourne ; | GN1: Index Numbers ; Water and sewerage ; Melbourne ; | GO1: Index Numbers ; Electricity ; Melbourne ; | GP1: Index Numbers ; Gas and other household fuels ; Melbourne ; | GQ1: Index Numbers ; Furnishings, household equipment and services ; Melbourne ; | GR1: Index Numbers ; Furniture and furnishings ; Melbourne ; | GS1: Index Numbers ; Furniture ; Melbourne ; | GT1: Index Numbers ; Carpets and other floor coverings ; Melbourne ; | GU1: Index Numbers ; Household textiles ; Melbourne ; | GV1: Index Numbers ; Household textiles ; Melbourne ; | GW1: Index Numbers ; Household appliances, utensils and tools ; Melbourne ; | GX1: Index Numbers ; Major household appliances ; Melbourne ; | GY1: Index Numbers ; Small electric household appliances ; Melbourne ; | GZ1: Index Numbers ; Glassware, tableware and household utensils ; Melbourne ; | HA1: Index Numbers ; Tools and equipment for house and garden ; Melbourne ; | HB1: Index Numbers ; Non-durable household products ; Melbourne ; | HC1: Index Numbers ; Cleaning and maintenance products ; Melbourne ; | HD1: Index Numbers ; Personal care products ; Melbourne ; | HE1: Index Numbers ; Other non-durable household products ; Melbourne ; | HF1: Index Numbers ; Domestic and household services ; Melbourne ; | HG1: Index Numbers ; Child care ; Melbourne ; | HH1: Index Numbers ; Hairdressing and personal grooming services ; Melbourne ; | HI1: Index Numbers ; Other household services ; Melbourne ; | HJ1: Index Numbers ; Health ; Melbourne ; | HK1: Index Numbers ; Medical products, appliances and equipment ; Melbourne ; | HL1: Index Numbers ; Pharmaceutical products ; Melbourne ; | HM1: Index Numbers ; Therapeutic appliances and equipment ; Melbourne ; | HN1: Index Numbers ; Medical, dental and hospital services ; Melbourne ; | HO1: Index Numbers ; Medical and hospital services ; Melbourne ; | HP1: Index Numbers ; Dental services ; Melbourne ; | HQ1: Index Numbers ; Transport ; Melbourne ; | HR1: Index Numbers ; Private motoring ; Melbourne ; | HS1: Index Numbers ; Motor vehicles ; Melbourne ; | HT1: Index Numbers ; Spare parts and accessories for motor vehicles ; Melbourne ; | HU1: Index Numbers ; Automotive fuel ; Melbourne ; | HV1: Index Numbers ; Maintenance and repair of motor vehicles ; Melbourne ; | HW1: Index Numbers ; Other services in respect of motor vehicles ; Melbourne ; | HX1: Index Numbers ; Urban transport fares ; Melbourne ; | HY1: Index Numbers ; Urban transport fares ; Melbourne ; | HZ1: Index Numbers ; Communication ; Melbourne ; | IA1: Index Numbers ; Communication ; Melbourne ; | IB1: Index Numbers ; Postal services ; Melbourne ; | IC1: Index Numbers ; Telecommunication equipment and services ; Melbourne ; | ID1: Index Numbers ; Recreation and culture ; Melbourne ; | IE1: Index Numbers ; Audio, visual and computing equipment and services ; Melbourne ; | IF1: Index Numbers ; Audio, visual and computing equipment ; Melbourne ; | IG1: Index Numbers ; Audio, visual and computing media and services ; Melbourne ; | IH1: Index Numbers ; Newspapers, books and stationery ; Melbourne ; | II1: Index Numbers ; Books ; Melbourne ; | IJ1: Index Numbers ; Newspapers, magazines and stationery ; Melbourne ; | IK1: Index Numbers ; Holiday travel and accommodation ; Melbourne ; | IL1: Index Numbers ; Domestic holiday travel and accommodation ; Melbourne ; | IM1: Index Numbers ; International holiday travel and accommodation ; Melbourne ; | IN1: Index Numbers ; Other recreation, sport and culture ; Melbourne ; | IO1: Index Numbers ; Equipment for sports, camping and open-air recreation ; Melbourne ; | IP1: Index Numbers ; Games, toys and hobbies ; Melbourne ; | IQ1: Index Numbers ; Pets and related products ; Melbourne ;
A2: Unit | B2: Index Numbers | C2: Index Numbers | D2: Index Numbers | E2: Index Numbers | F2: Index Numbers | G2: Index Numbers | H2: Index Numbers | I2: Index Numbers | J2: Index Numbers | K2: Index Numbers | L2: Index Numbers | M2: Index Numbers | N2: Index Numbers | O2: Index Numbers | P2: Index Numbers | Q2: Index Numbers | R2: Index Numbers | S2: Index Numbers | T2: Index Numbers | U2: Index Numbers | V2: Index Numbers | W2: Index Numbers | X2: Index Numbers | Y2: Index Numbers | Z2: Index Numbers | AA2: Index Numbers | AB2: Index Numbers | AC2: Index Numbers | AD2: Index Numbers | AE2: Index Numbers | AF2: Index Numbers | AG2: Index Numbers | AH2: Index Numbers | AI2: Index Numbers | AJ2: Index Numbers | AK2: Index Numbers | AL2: Index Numbers | AM2: Index Numbers | AN2: Index Numbers | AO2: Index Numbers | AP2: Index Numbers | AQ2: Index Numbers | AR2: Index Numbers | AS2: Index Numbers | AT2: Index Numbers | AU2: Index Numbers | AV2: Index Numbers | AW2: Index Numbers | AX2: Index Numbers | AY2: Index Numbers | AZ2: Index Numbers | BA2: Index Numbers | BB2: Index Numbers | BC2: Index Numbers | BD2: Index Numbers | BE2: Index Numbers | BF2: Index Numbers | BG2: Index Numbers | BH2: Index Numbers | BI2: Index Numbers | BJ2: Index Numbers | BK2: Index Numbers | BL2: Index Numbers | BM2: Index Numbers | BN2: Index Numbers | BO2: Index Numbers | BP2: Index Numbers | BQ2: Index Numbers | BR2: Index Numbers | BS2: Index Numbers | BT2: Index Numbers | BU2: Index Numbers | BV2: Index Numbers | BW2: Index Numbers | BX2: Index Numbers | BY2: Index Numbers | BZ2: Index Numbers | CA2: Index Numbers | CB2: Index Numbers | CC2: Index Numbers | CD2: Index Numbers | CE2: Index Numbers | CF2: Index Numbers | CG2: Index Numbers | CH2: Index Numbers | CI2: Index Numbers | CJ2: Index Numbers | CK2: Index Numbers | CL2: Index Numbers | CM2: Index Numbers | CN2: Index Numbers | CO2: Index Numbers | CP2: Index Numbers | CQ2: Index Numbers | CR2: Index Numbers | CS2: Index Numbers | CT2: Index Numbers | CU2: Index Numbers | CV2: Index Numbers | CW2: Index Numbers | CX2: Index Numbers | CY2: Index Numbers | CZ2: Index Numbers | DA2: Index Numbers | DB2: Index Numbers | DC2: Index Numbers | DD2: Index Numbers | DE2: Index Numbers | DF2: Index Numbers | DG2: Index Numbers | DH2: Index Numbers | DI2: Index Numbers | DJ2: Index Numbers | DK2: Index Numbers | DL2: Index Numbers | DM2: Index Numbers | DN2: Index Numbers | DO2: Index Numbers | DP2: Index Numbers | DQ2: Index Numbers | DR2: Index Numbers | DS2: Index Numbers | DT2: Index Numbers | DU2: Index Numbers | DV2: Index Numbers | DW2: Index Numbers | DX2: Index Numbers | DY2: Index Numbers | DZ2: Index Numbers | EA2: Index Numbers | EB2: Index Numbers | EC2: Index Numbers | ED2: Index Numbers | EE2: Index Numbers | EF2: Index Numbers | EG2: Index Numbers | EH2: Index Numbers | EI2: Index Numbers | EJ2: Index Numbers | EK2: Index Numbers | EL2: Index Numbers | EM2: Index Numbers | EN2: Index Numbers | EO2: Index Numbers | EP2: Index Numbers | EQ2: Index Numbers | ER2: Index Numbers | ES2: Index Numbers | ET2: Index Numbers | EU2: Index Numbers | EV2: Index Numbers | EW2: Index Numbers | EX2: Index Numbers | EY2: Index Numbers | EZ2: Index Numbers | FA2: Index Numbers | FB2: Index Numbers | FC2: Index Numbers | FD2: Index Numbers | FE2: Index Numbers | FF2: Index Numbers | FG2: Index Numbers | FH2: Index Numbers | FI2: Index Numbers | FJ2: Index Numbers | FK2: Index Numbers | FL2: Index Numbers | FM2: Index Numbers | FN2: Index Numbers | FO2: Index Numbers | FP2: Index Numbers | FQ2: Index Numbers | FR2: Index Numbers | FS2: Index Numbers | FT2: Index Numbers | FU2: Index Numbers | FV2: Index Numbers | FW2: Index Numbers | FX2: Index Numbers | FY2: Index Numbers | FZ2: Index Numbers | GA2: Index Numbers | GB2: Index Numbers | GC2: Index Numbers | GD2: Index Numbers | GE2: Index Numbers | GF2: Index Numbers | GG2: Index Numbers | GH2: Index Numbers | GI2: Index Numbers | GJ2: Index Numbers | GK2: Index Numbers | GL2: Index Numbers | GM2: Index Numbers | GN2: Index Numbers | GO2: Index Numbers | GP2: Index Numbers | GQ2: Index Numbers | GR2: Index Numbers | GS2: Index Numbers | GT2: Index Numbers | GU2: Index Numbers | GV2: Index Numbers | GW2: Index Numbers | GX2: Index Numbers | GY2: Index Numbers | GZ2: Index Numbers | HA2: Index Numbers | HB2: Index Numbers | HC2: Index Numbers | HD2: Index Numbers | HE2: Index Numbers | HF2: Index Numbers | HG2: Index Numbers | HH2: Index Numbers | HI2: Index Numbers | HJ2: Index Numbers | HK2: Index Numbers | HL2: Index Numbers | HM2: Index Numbers | HN2: Index Numbers | HO2: Index Numbers | HP2: Index Numbers | HQ2: Index Numbers | HR2: Index Numbers | HS2: Index Numbers | HT2: Index Numbers | HU2: Index Numbers | HV2: Index Numbers | HW2: Index Numbers | HX2: Index Numbers | HY2: Index Numbers | HZ2: Index Numbers | IA2: Index Numbers | IB2: Index Numbers | IC2: Index Numbers | ID2: Index Numbers | IE2: Index Numbers | IF2: Index Numbers | IG2: Index Numbers | IH2: Index Numbers | II2: Index Numbers | IJ2: Index Numbers | IK2: Index Numbers | IL2: Index Numbers | IM2: Index Numbers | IN2: Index Numbers | IO2: Index Numbers | IP2: Index Numbers | IQ2: Index Numbers
A3: Series Type | B3: Original | C3: Original | D3: Original | E3: Original | F3: Original | G3: Original | H3: Original | I3: Original | J3: Original | K3: Original | L3: Original | M3: Original | N3: Original | O3: Original | P3: Original | Q3: Original | R3: Original | S3: Original | T3: Original | U3: Original | V3: Original | W3: Original | X3: Original | Y3: Original | Z3: Original | AA3: Original | AB3: Original | AC3: Original | AD3: Original | AE3: Original | AF3: Original | AG3: Original | AH3: Original | AI3: Original | AJ3: Original | AK3: Original | AL3: Original | AM3: Original | AN3: Original | AO3: Original | AP3: Original | AQ3: Original | AR3: Original | AS3: Original | AT3: Original | AU3: Original | AV3: Original | AW3: Original | AX3: Original | AY3: Original | AZ3: Original | BA3: Original | BB3: Original | BC3: Original | BD3: Original | BE3: Original | BF3: Original | BG3: Original | BH3: Original | BI3: Original | BJ3: Original | BK3: Original | BL3: Original | BM3: Original | BN3: Original | BO3: Original | BP3: Original | BQ3: Original | BR3: Original | BS3: Original | BT3: Original | BU3: Original | BV3: Original | BW3: Original | BX3: Original | BY3: Original | BZ3: Original | CA3: Original | CB3: Original | CC3: Original | CD3: Original | CE3: Original | CF3: Original | CG3: Original | CH3: Original | CI3: Original | CJ3: Original | CK3: Original | CL3: Original | CM3: Original | CN3: Original | CO3: Original | CP3: Original | CQ3: Original | CR3: Original | CS3: Original | CT3: Original | CU3: Original | CV3: Original | CW3: Original | CX3: Original | CY3: Original | CZ3: Original | DA3: Original | DB3: Original | DC3: Original | DD3: Original | DE3: Original | DF3: Original | DG3: Original | DH3: Original | DI3: Original | DJ3: Original | DK3: Original | DL3: Original | DM3: Original | DN3: Original | DO3: Original | DP3: Original | DQ3: Original | DR3: Original | DS3: Original | DT3: Original | DU3: Original | DV3: Original | DW3: Original | DX3: Original | DY3: Original | DZ3: Original | EA3: Original | EB3: Original | EC3: Original | ED3: Original | EE3: Original | EF3: Original | EG3: Original | EH3: Original | EI3: Original | EJ3: Original | EK3: Original | EL3: Original | EM3: Original | EN3: Original | EO3: Original | EP3: Original | EQ3: Original | ER3: Original | ES3: Original | ET3: Original | EU3: Original | EV3: Original | EW3: Original | EX3: Original | EY3: Original | EZ3: Original | FA3: Original | FB3: Original | FC3: Original | FD3: Original | FE3: Original | FF3: Original | FG3: Original | FH3: Original | FI3: Original | FJ3: Original | FK3: Original | FL3: Original | FM3: Original | FN3: Original | FO3: Original | FP3: Original | FQ3: Original | FR3: Original | FS3: Original | FT3: Original | FU3: Original | FV3: Original | FW3: Original | FX3: Original | FY3: Original | FZ3: Original | GA3: Original | GB3: Original | GC3: Original | GD3: Original | GE3: Original | GF3: Original | GG3: Original | GH3: Original | GI3: Original | GJ3: Original | GK3: Original | GL3: Original | GM3: Original | GN3: Original | GO3: Original | GP3: Original | GQ3: Original | GR3: Original | GS3: Original | GT3: Original | GU3: Original | GV3: Original | GW3: Original | GX3: Original | GY3: Original | GZ3: Original | HA3: Original | HB3: Original | HC3: Original | HD3: Original | HE3: Original | HF3: Original | HG3: Original | HH3: Original | HI3: Original | HJ3: Original | HK3: Original | HL3: Original | HM3: Original | HN3: Original | HO3: Original | HP3: Original | HQ3: Original | HR3: Original | HS3: Original | HT3: Original | HU3: Original | HV3: Original | HW3: Original | HX3: Original | HY3: Original | HZ3: Original | IA3: Original | IB3: Original | IC3: Original | ID3: Original | IE3: Original | IF3: Original | IG3: Original | IH3: Original | II3: Original | IJ3: Original | IK3: Original | IL3: Original | IM3: Original | IN3: Original | IO3: Original | IP3: Original | IQ3: Original
A4: Data Type | B4: INDEX | C4: INDEX | D4: INDEX | E4: INDEX | F4: INDEX | G4: INDEX | H4: INDEX | I4: INDEX | J4: INDEX | K4: INDEX | L4: INDEX | M4: INDEX | N4: INDEX | O4: INDEX | P4: INDEX | Q4: INDEX | R4: INDEX | S4: INDEX | T4: INDEX | U4: INDEX | V4: INDEX | W4: INDEX | X4: INDEX | Y4: INDEX | Z4: INDEX | AA4: INDEX | AB4: INDEX | AC4: INDEX | AD4: INDEX | AE4: INDEX | AF4: INDEX | AG4: INDEX | AH4: INDEX | AI4: INDEX | AJ4: INDEX | AK4: INDEX | AL4: INDEX | AM4: INDEX | AN4: INDEX | AO4: INDEX | AP4: INDEX | AQ4: INDEX | AR4: INDEX | AS4: INDEX | AT4: INDEX | AU4: INDEX | AV4: INDEX | AW4: INDEX | AX4: INDEX | AY4: INDEX | AZ4: INDEX | BA4: INDEX | BB4: INDEX | BC4: INDEX | BD4: INDEX | BE4: INDEX | BF4: INDEX | BG4: INDEX | BH4: INDEX | BI4: INDEX | BJ4: INDEX | BK4: INDEX | BL4: INDEX | BM4: INDEX | BN4: INDEX | BO4: INDEX | BP4: INDEX | BQ4: INDEX | BR4: INDEX | BS4: INDEX | BT4: INDEX | BU4: INDEX | BV4: INDEX | BW4: INDEX | BX4: INDEX | BY4: INDEX | BZ4: INDEX | CA4: INDEX | CB4: INDEX | CC4: INDEX | CD4: INDEX | CE4: INDEX | CF4: INDEX | CG4: INDEX | CH4: INDEX | CI4: INDEX | CJ4: INDEX | CK4: INDEX | CL4: INDEX | CM4: INDEX | CN4: INDEX | CO4: INDEX | CP4: INDEX | CQ4: INDEX | CR4: INDEX | CS4: INDEX | CT4: INDEX | CU4: INDEX | CV4: INDEX | CW4: INDEX | CX4: INDEX | CY4: INDEX | CZ4: INDEX | DA4: INDEX | DB4: INDEX | DC4: INDEX | DD4: INDEX | DE4: INDEX | DF4: INDEX | DG4: INDEX | DH4: INDEX | DI4: INDEX | DJ4: INDEX | DK4: INDEX | DL4: INDEX | DM4: INDEX | DN4: INDEX | DO4: INDEX | DP4: INDEX | DQ4: INDEX | DR4: INDEX | DS4: INDEX | DT4: INDEX | DU4: INDEX | DV4: INDEX | DW4: INDEX | DX4: INDEX | DY4: INDEX | DZ4: INDEX | EA4: INDEX | EB4: INDEX | EC4: INDEX | ED4: INDEX | EE4: INDEX | EF4: INDEX | EG4: INDEX | EH4: INDEX | EI4: INDEX | EJ4: INDEX | EK4: INDEX | EL4: INDEX | EM4: INDEX | EN4: INDEX | EO4: INDEX | EP4: INDEX | EQ4: INDEX | ER4: INDEX | ES4: INDEX | ET4: INDEX | EU4: INDEX | EV4: INDEX | EW4: INDEX | EX4: INDEX | EY4: INDEX | EZ4: INDEX | FA4: INDEX | FB4: INDEX | FC4: INDEX | FD4: INDEX | FE4: INDEX | FF4: INDEX | FG4: INDEX | FH4: INDEX | FI4: INDEX | FJ4: INDEX | FK4: INDEX | FL4: INDEX | FM4: INDEX | FN4: INDEX | FO4: INDEX | FP4: INDEX | FQ4: INDEX | FR4: INDEX | FS4: INDEX | FT4: INDEX | FU4: INDEX | FV4: INDEX | FW4: INDEX | FX4: INDEX | FY4: INDEX | FZ4: INDEX | GA4: INDEX | GB4: INDEX | GC4: INDEX | GD4: INDEX | GE4: INDEX | GF4: INDEX | GG4: INDEX | GH4: INDEX | GI4: INDEX | GJ4: INDEX | GK4: INDEX | GL4: INDEX | GM4: INDEX | GN4: INDEX | GO4: INDEX | GP4: INDEX | GQ4: INDEX | GR4: INDEX | GS4: INDEX | GT4: INDEX | GU4: INDEX | GV4: INDEX | GW4: INDEX | GX4: INDEX | GY4: INDEX | GZ4: INDEX | HA4: INDEX | HB4: INDEX | HC4: INDEX | HD4: INDEX | HE4: INDEX | HF4: INDEX | HG4: INDEX | HH4: INDEX | HI4: INDEX | HJ4: INDEX | HK4: INDEX | HL4: INDEX | HM4: INDEX | HN4: INDEX | HO4: INDEX | HP4: INDEX | HQ4: INDEX | HR4: INDEX | HS4: INDEX | HT4: INDEX | HU4: INDEX | HV4: INDEX | HW4: INDEX | HX4: INDEX | HY4: INDEX | HZ4: INDEX | IA4: INDEX | IB4: INDEX | IC4: INDEX | ID4: INDEX | IE4: INDEX | IF4: INDEX | IG4: INDEX | IH4: INDEX | II4: INDEX | IJ4: INDEX | IK4: INDEX | IL4: INDEX | IM4: INDEX | IN4: INDEX | IO4: INDEX | IP4: INDEX | IQ4: INDEX
A5: Frequency | B5: Month | C5: Month | D5: Month | E5: Month | F5: Month | G5: Month | H5: Month | I5: Month | J5: Month | K5: Month | L5: Month | M5: Month | N5: Month | O5: Month | P5: Month | Q5: Month | R5: Month | S5: Month | T5: Month | U5: Month | V5: Month | W5: Month | X5: Month | Y5: Month | Z5: Month | AA5: Month | AB5: Month | AC5: Month | AD5: Month | AE5: Month | AF5: Month | AG5: Month | AH5: Month | AI5: Month | AJ5: Month | AK5: Month | AL5: Month | AM5: Month | AN5: Month | AO5: Month | AP5: Month | AQ5: Month | AR5: Month | AS5: Month | AT5: Month | AU5: Month | AV5: Month | AW5: Month | AX5: Month | AY5: Month | AZ5: Month | BA5: Month | BB5: Month | BC5: Month | BD5: Month | BE5: Month | BF5: Month | BG5: Month | BH5: Month | BI5: Month | BJ5: Month | BK5: Month | BL5: Month | BM5: Month | BN5: Month | BO5: Month | BP5: Month | BQ5: Month | BR5: Month | BS5: Month | BT5: Month | BU5: Month | BV5: Month | BW5: Month | BX5: Month | BY5: Month | BZ5: Month | CA5: Month | CB5: Month | CC5: Month | CD5: Month | CE5: Month | CF5: Month | CG5: Month | CH5: Month | CI5: Month | CJ5: Month | CK5: Month | CL5: Month | CM5: Month | CN5: Month | CO5: Month | CP5: Month | CQ5: Month | CR5: Month | CS5: Month | CT5: Month | CU5: Month | CV5: Month | CW5: Month | CX5: Month | CY5: Month | CZ5: Month | DA5: Month | DB5: Month | DC5: Month | DD5: Month | DE5: Month | DF5: Month | DG5: Month | DH5: Month | DI5: Month | DJ5: Month | DK5: Month | DL5: Month | DM5: Month | DN5: Month | DO5: Month | DP5: Month | DQ5: Month | DR5: Month | DS5: Month | DT5: Month | DU5: Month | DV5: Month | DW5: Month | DX5: Month | DY5: Month | DZ5: Month | EA5: Month | EB5: Month | EC5: Month | ED5: Month | EE5: Month | EF5: Month | EG5: Month | EH5: Month | EI5: Month | EJ5: Month | EK5: Month | EL5: Month | EM5: Month | EN5: Month | EO5: Month | EP5: Month | EQ5: Month | ER5: Month | ES5: Month | ET5: Month | EU5: Month | EV5: Month | EW5: Month | EX5: Month | EY5: Month | EZ5: Month | FA5: Month | FB5: Month | FC5: Month | FD5: Month | FE5: Month | FF5: Month | FG5: Month | FH5: Month | FI5: Month | FJ5: Month | FK5: Month | FL5: Month | FM5: Month | FN5: Month | FO5: Month | FP5: Month | FQ5: Month | FR5: Month | FS5: Month | FT5: Month | FU5: Month | FV5: Month | FW5: Month | FX5: Month | FY5: Month | FZ5: Month | GA5: Month | GB5: Month | GC5: Month | GD5: Month | GE5: Month | GF5: Month | GG5: Month | GH5: Month | GI5: Month | GJ5: Month | GK5: Month | GL5: Month | GM5: Month | GN5: Month | GO5: Month | GP5: Month | GQ5: Month | GR5: Month | GS5: Month | GT5: Month | GU5: Month | GV5: Month | GW5: Month | GX5: Month | GY5: Month | GZ5: Month | HA5: Month | HB5: Month | HC5: Month | HD5: Month | HE5: Month | HF5: Month | HG5: Month | HH5: Month | HI5: Month | HJ5: Month | HK5: Month | HL5: Month | HM5: Month | HN5: Month | HO5: Month | HP5: Month | HQ5: Month | HR5: Month | HS5: Month | HT5: Month | HU5: Month | HV5: Month | HW5: Month | HX5: Month | HY5: Month | HZ5: Month | IA5: Month | IB5: Month | IC5: Month | ID5: Month | IE5: Month | IF5: Month | IG5: Month | IH5: Month | II5: Month | IJ5: Month | IK5: Month | IL5: Month | IM5: Month | IN5: Month | IO5: Month | IP5: Month | IQ5: Month
A6: Collection Month | B6: 1 | C6: 1 | D6: 1 | E6: 1 | F6: 1 | G6: 1 | H6: 1 | I6: 1 | J6: 1 | K6: 1 | L6: 1 | M6: 1 | N6: 1 | O6: 1 | P6: 1 | Q6: 1 | R6: 1 | S6: 1 | T6: 1 | U6: 1 | V6: 1 | W6: 1 | X6: 1 | Y6: 1 | Z6: 1 | AA6: 1 | AB6: 1 | AC6: 1 | AD6: 1 | AE6: 1 | AF6: 1 | AG6: 1 | AH6: 1 | AI6: 1 | AJ6: 1 | AK6: 1 | AL6: 1 | AM6: 1 | AN6: 1 | AO6: 1 | AP6: 1 | AQ6: 1 | AR6: 1 | AS6: 1 | AT6: 1 | AU6: 1 | AV6: 1 | AW6: 1 | AX6: 1 | AY6: 1 | AZ6: 1 | BA6: 1 | BB6: 1 | BC6: 1 | BD6: 1 | BE6: 1 | BF6: 1 | BG6: 1 | BH6: 1 | BI6: 1 | BJ6: 1 | BK6: 1 | BL6: 1 | BM6: 1 | BN6: 1 | BO6: 1 | BP6: 1 | BQ6: 1 | BR6: 1 | BS6: 1 | BT6: 1 | BU6: 1 | BV6: 1 | BW6: 1 | BX6: 1 | BY6: 1 | BZ6: 1 | CA6: 1 | CB6: 1 | CC6: 1 | CD6: 1 | CE6: 1 | CF6: 1 | CG6: 1 | CH6: 1 | CI6: 1 | CJ6: 1 | CK6: 1 | CL6: 1 | CM6: 1 | CN6: 1 | CO6: 1 | CP6: 1 | CQ6: 1 | CR6: 1 | CS6: 1 | CT6: 1 | CU6: 1 | CV6: 1 | CW6: 1 | CX6: 1 | CY6: 1 | CZ6: 1 | DA6: 1 | DB6: 1 | DC6: 1 | DD6: 1 | DE6: 1 | DF6: 1 | DG6: 1 | DH6: 1 | DI6: 1 | DJ6: 1 | DK6: 1 | DL6: 1 | DM6: 1 | DN6: 1 | DO6: 1 | DP6: 1 | DQ6: 1 | DR6: 1 | DS6: 1 | DT6: 1 | DU6: 1 | DV6: 1 | DW6: 1 | DX6: 1 | DY6: 1 | DZ6: 1 | EA6: 1 | EB6: 1 | EC6: 1 | ED6: 1 | EE6: 1 | EF6: 1 | EG6: 1 | EH6: 1 | EI6: 1 | EJ6: 1 | EK6: 1 | EL6: 1 | EM6: 1 | EN6: 1 | EO6: 1 | EP6: 1 | EQ6: 1 | ER6: 1 | ES6: 1 | ET6: 1 | EU6: 1 | EV6: 1 | EW6: 1 | EX6: 1 | EY6: 1 | EZ6: 1 | FA6: 1 | FB6: 1 | FC6: 1 | FD6: 1 | FE6: 1 | FF6: 1 | FG6: 1 | FH6: 1 | FI6: 1 | FJ6: 1 | FK6: 1 | FL6: 1 | FM6: 1 | FN6: 1 | FO6: 1 | FP6: 1 | FQ6: 1 | FR6: 1 | FS6: 1 | FT6: 1 | FU6: 1 | FV6: 1 | FW6: 1 | FX6: 1 | FY6: 1 | FZ6: 1 | GA6: 1 | GB6: 1 | GC6: 1 | GD6: 1 | GE6: 1 | GF6: 1 | GG6: 1 | GH6: 1 | GI6: 1 | GJ6: 1 | GK6: 1 | GL6: 1 | GM6: 1 | GN6: 1 | GO6: 1 | GP6: 1 | GQ6: 1 | GR6: 1 | GS6: 1 | GT6: 1 | GU6: 1 | GV6: 1 | GW6: 1 | GX6: 1 | GY6: 1 | GZ6: 1 | HA6: 1 | HB6: 1 | HC6: 1 | HD6: 1 | HE6: 1 | HF6: 1 | HG6: 1 | HH6: 1 | HI6: 1 | HJ6: 1 | HK6: 1 | HL6: 1 | HM6: 1 | HN6: 1 | HO6: 1 | HP6: 1 | HQ6: 1 | HR6: 1 | HS6: 1 | HT6: 1 | HU6: 1 | HV6: 1 | HW6: 1 | HX6: 1 | HY6: 1 | HZ6: 1 | IA6: 1 | IB6: 1 | IC6: 1 | ID6: 1 | IE6: 1 | IF6: 1 | IG6: 1 | IH6: 1 | II6: 1 | IJ6: 1 | IK6: 1 | IL6: 1 | IM6: 1 | IN6: 1 | IO6: 1 | IP6: 1 | IQ6: 1
A7: Series Start | B7: 45383 | C7: 45383 | D7: 42979 | E7: 42979 | F7: 42979 | G7: 42979 | H7: 42979 | I7: 42979 | J7: 42979 | K7: 42979 | L7: 42979 | M7: 42979 | N7: 42979 | O7: 42979 | P7: 42979 | Q7: 42979 | R7: 42979 | S7: 42979 | T7: 42979 | U7: 42979 | V7: 42979 | W7: 42979 | X7: 42979 | Y7: 42979 | Z7: 42979 | AA7: 42979 | AB7: 42979 | AC7: 42979 | AD7: 42979 | AE7: 42979 | AF7: 42979 | AG7: 45383 | AH7: 45383 | AI7: 45383 | AJ7: 45383 | AK7: 45383 | AL7: 42979 | AM7: 45383 | AN7: 42979 | AO7: 42979 | AP7: 42979 | AQ7: 45383 | AR7: 45383 | AS7: 45383 | AT7: 45383 | AU7: 45383 | AV7: 45383 | AW7: 45383 | AX7: 45383 | AY7: 45383 | AZ7: 45383 | BA7: 45383 | BB7: 45383 | BC7: 45383 | BD7: 44743 | BE7: 44743 | BF7: 42979 | BG7: 42979 | BH7: 45383 | BI7: 45383 | BJ7: 42979 | BK7: 45383 | BL7: 45383 | BM7: 44470 | BN7: 44470 | BO7: 45383 | BP7: 45383 | BQ7: 45383 | BR7: 45383 | BS7: 45383 | BT7: 45383 | BU7: 45383 | BV7: 45383 | BW7: 45383 | BX7: 45383 | BY7: 45383 | BZ7: 42979 | CA7: 42979 | CB7: 42979 | CC7: 42979 | CD7: 45383 | CE7: 45383 | CF7: 45383 | CG7: 45383 | CH7: 45383 | CI7: 45383 | CJ7: 45383 | CK7: 45383 | CL7: 45383 | CM7: 45383 | CN7: 45383 | CO7: 45383 | CP7: 45383 | CQ7: 45383 | CR7: 45383 | CS7: 42979 | CT7: 45383 | CU7: 45383 | CV7: 45383 | CW7: 45383 | CX7: 45383 | CY7: 45383 | CZ7: 44743 | DA7: 45383 | DB7: 45383 | DC7: 45383 | DD7: 45383 | DE7: 45383 | DF7: 45383 | DG7: 45383 | DH7: 45383 | DI7: 42979 | DJ7: 42979 | DK7: 42979 | DL7: 45383 | DM7: 45383 | DN7: 45383 | DO7: 42979 | DP7: 45383 | DQ7: 45383 | DR7: 45383 | DS7: 45383 | DT7: 45383 | DU7: 45383 | DV7: 42979 | DW7: 42979 | DX7: 45383 | DY7: 45383 | DZ7: 45383 | EA7: 42979 | EB7: 42979 | EC7: 42979 | ED7: 45383 | EE7: 45383 | EF7: 42979 | EG7: 42979 | EH7: 42979 | EI7: 42979 | EJ7: 42979 | EK7: 42979 | EL7: 42979 | EM7: 42979 | EN7: 42979 | EO7: 42979 | EP7: 42979 | EQ7: 42979 | ER7: 42979 | ES7: 42979 | ET7: 42979 | EU7: 42979 | EV7: 42979 | EW7: 42979 | EX7: 42979 | EY7: 42979 | EZ7: 42979 | FA7: 42979 | FB7: 42979 | FC7: 42979 | FD7: 42979 | FE7: 42979 | FF7: 42979 | FG7: 42979 | FH7: 42979 | FI7: 45383 | FJ7: 45383 | FK7: 45383 | FL7: 45383 | FM7: 45383 | FN7: 42979 | FO7: 45383 | FP7: 42979 | FQ7: 42979 | FR7: 42979 | FS7: 45383 | FT7: 45383 | FU7: 45383 | FV7: 45383 | FW7: 45383 | FX7: 45383 | FY7: 45383 | FZ7: 45383 | GA7: 45383 | GB7: 45383 | GC7: 45383 | GD7: 45383 | GE7: 45383 | GF7: 44743 | GG7: 44743 | GH7: 42979 | GI7: 42979 | GJ7: 45383 | GK7: 45383 | GL7: 42979 | GM7: 45383 | GN7: 45383 | GO7: 44470 | GP7: 44470 | GQ7: 45383 | GR7: 45383 | GS7: 45383 | GT7: 45383 | GU7: 45383 | GV7: 45383 | GW7: 45383 | GX7: 45383 | GY7: 45383 | GZ7: 45383 | HA7: 45383 | HB7: 42979 | HC7: 42979 | HD7: 42979 | HE7: 42979 | HF7: 45383 | HG7: 45383 | HH7: 45383 | HI7: 45383 | HJ7: 45383 | HK7: 45383 | HL7: 45383 | HM7: 45383 | HN7: 45383 | HO7: 45383 | HP7: 45383 | HQ7: 45383 | HR7: 45383 | HS7: 45383 | HT7: 45383 | HU7: 42979 | HV7: 45383 | HW7: 45383 | HX7: 45383 | HY7: 45383 | HZ7: 45383 | IA7: 45383 | IB7: 44743 | IC7: 45383 | ID7: 45383 | IE7: 45383 | IF7: 45383 | IG7: 45383 | IH7: 45383 | II7: 45383 | IJ7: 45383 | IK7: 42979 | IL7: 42979 | IM7: 42979 | IN7: 45383 | IO7: 45383 | IP7: 45383 | IQ7: 42979
A8: Series End | B8: 46023 | C8: 46023 | D8: 46023 | E8: 46023 | F8: 46023 | G8: 46023 | H8: 46023 | I8: 46023 | J8: 46023 | K8: 46023 | L8: 46023 | M8: 46023 | N8: 46023 | O8: 46023 | P8: 46023 | Q8: 46023 | R8: 46023 | S8: 46023 | T8: 46023 | U8: 46023 | V8: 46023 | W8: 46023 | X8: 46023 | Y8: 46023 | Z8: 46023 | AA8: 46023 | AB8: 46023 | AC8: 46023 | AD8: 46023 | AE8: 46023 | AF8: 46023 | AG8: 46023 | AH8: 46023 | AI8: 46023 | AJ8: 46023 | AK8: 46023 | AL8: 46023 | AM8: 46023 | AN8: 46023 | AO8: 46023 | AP8: 46023 | AQ8: 46023 | AR8: 46023 | AS8: 46023 | AT8: 46023 | AU8: 46023 | AV8: 46023 | AW8: 46023 | AX8: 46023 | AY8: 46023 | AZ8: 46023 | BA8: 46023 | BB8: 46023 | BC8: 46023 | BD8: 46023 | BE8: 46023 | BF8: 46023 | BG8: 46023 | BH8: 46023 | BI8: 46023 | BJ8: 46023 | BK8: 46023 | BL8: 46023 | BM8: 46023 | BN8: 46023 | BO8: 46023 | BP8: 46023 | BQ8: 46023 | BR8: 46023 | BS8: 46023 | BT8: 46023 | BU8: 46023 | BV8: 46023 | BW8: 46023 | BX8: 46023 | BY8: 46023 | BZ8: 46023 | CA8: 46023 | CB8: 46023 | CC8: 46023 | CD8: 46023 | CE8: 46023 | CF8: 46023 | CG8: 46023 | CH8: 46023 | CI8: 46023 | CJ8: 46023 | CK8: 46023 | CL8: 46023 | CM8: 46023 | CN8: 46023 | CO8: 46023 | CP8: 46023 | CQ8: 46023 | CR8: 46023 | CS8: 46023 | CT8: 46023 | CU8: 46023 | CV8: 46023 | CW8: 46023 | CX8: 46023 | CY8: 46023 | CZ8: 46023 | DA8: 46023 | DB8: 46023 | DC8: 46023 | DD8: 46023 | DE8: 46023 | DF8: 46023 | DG8: 46023 | DH8: 46023 | DI8: 46023 | DJ8: 46023 | DK8: 46023 | DL8: 46023 | DM8: 46023 | DN8: 46023 | DO8: 46023 | DP8: 46023 | DQ8: 46023 | DR8: 46023 | DS8: 46023 | DT8: 46023 | DU8: 46023 | DV8: 46023 | DW8: 46023 | DX8: 46023 | DY8: 46023 | DZ8: 46023 | EA8: 46023 | EB8: 46023 | EC8: 46023 | ED8: 46023 | EE8: 46023 | EF8: 46023 | EG8: 46023 | EH8: 46023 | EI8: 46023 | EJ8: 46023 | EK8: 46023 | EL8: 46023 | EM8: 46023 | EN8: 46023 | EO8: 46023 | EP8: 46023 | EQ8: 46023 | ER8: 46023 | ES8: 46023 | ET8: 46023 | EU8: 46023 | EV8: 46023 | EW8: 46023 | EX8: 46023 | EY8: 46023 | EZ8: 46023 | FA8: 46023 | FB8: 46023 | FC8: 46023 | FD8: 46023 | FE8: 46023 | FF8: 46023 | FG8: 46023 | FH8: 46023 | FI8: 46023 | FJ8: 46023 | FK8: 46023 | FL8: 46023 | FM8: 46023 | FN8: 46023 | FO8: 46023 | FP8: 46023 | FQ8: 46023 | FR8: 46023 | FS8: 46023 | FT8: 46023 | FU8: 46023 | FV8: 46023 | FW8: 46023 | FX8: 46023 | FY8: 46023 | FZ8: 46023 | GA8: 46023 | GB8: 46023 | GC8: 46023 | GD8: 46023 | GE8: 46023 | GF8: 46023 | GG8: 46023 | GH8: 46023 | GI8: 46023 | GJ8: 46023 | GK8: 46023 | GL8: 46023 | GM8: 46023 | GN8: 46023 | GO8: 46023 | GP8: 46023 | GQ8: 46023 | GR8: 46023 | GS8: 46023 | GT8: 46023 | GU8: 46023 | GV8: 46023 | GW8: 46023 | GX8: 46023 | GY8: 46023 | GZ8: 46023 | HA8: 46023 | HB8: 46023 | HC8: 46023 | HD8: 46023 | HE8: 46023 | HF8: 46023 | HG8: 46023 | HH8: 46023 | HI8: 46023 | HJ8: 46023 | HK8: 46023 | HL8: 46023 | HM8: 46023 | HN8: 46023 | HO8: 46023 | HP8: 46023 | HQ8: 46023 | HR8: 46023 | HS8: 46023 | HT8: 46023 | HU8: 46023 | HV8: 46023 | HW8: 46023 | HX8: 46023 | HY8: 46023 | HZ8: 46023 | IA8: 46023 | IB8: 46023 | IC8: 46023 | ID8: 46023 | IE8: 46023 | IF8: 46023 | IG8: 46023 | IH8: 46023 | II8: 46023 | IJ8: 46023 | IK8: 46023 | IL8: 46023 | IM8: 46023 | IN8: 46023 | IO8: 46023 | IP8: 46023 | IQ8: 46023
A9: No. Obs | B9: 22 | C9: 22 | D9: 101 | E9: 101 | F9: 101 | G9: 101 | H9: 101 | I9: 101 | J9: 101 | K9: 101 | L9: 101 | M9: 101 | N9: 101 | O9: 101 | P9: 101 | Q9: 101 | R9: 101 | S9: 101 | T9: 101 | U9: 101 | V9: 101 | W9: 101 | X9: 101 | Y9: 101 | Z9: 101 | AA9: 101 | AB9: 101 | AC9: 101 | AD9: 101 | AE9: 101 | AF9: 101 | AG9: 22 | AH9: 22 | AI9: 22 | AJ9: 22 | AK9: 22 | AL9: 101 | AM9: 22 | AN9: 101 | AO9: 101 | AP9: 101 | AQ9: 22 | AR9: 22 | AS9: 22 | AT9: 22 | AU9: 22 | AV9: 22 | AW9: 22 | AX9: 22 | AY9: 22 | AZ9: 22 | BA9: 22 | BB9: 22 | BC9: 22 | BD9: 43 | BE9: 43 | BF9: 101 | BG9: 101 | BH9: 22 | BI9: 22 | BJ9: 101 | BK9: 22 | BL9: 22 | BM9: 52 | BN9: 52 | BO9: 22 | BP9: 22 | BQ9: 22 | BR9: 22 | BS9: 22 | BT9: 22 | BU9: 22 | BV9: 22 | BW9: 22 | BX9: 22 | BY9: 22 | BZ9: 101 | CA9: 101 | CB9: 101 | CC9: 101 | CD9: 22 | CE9: 22 | CF9: 22 | CG9: 22 | CH9: 22 | CI9: 22 | CJ9: 22 | CK9: 22 | CL9: 22 | CM9: 22 | CN9: 22 | CO9: 22 | CP9: 22 | CQ9: 22 | CR9: 22 | CS9: 101 | CT9: 22 | CU9: 22 | CV9: 22 | CW9: 22 | CX9: 22 | CY9: 22 | CZ9: 43 | DA9: 22 | DB9: 22 | DC9: 22 | DD9: 22 | DE9: 22 | DF9: 22 | DG9: 22 | DH9: 22 | DI9: 101 | DJ9: 101 | DK9: 101 | DL9: 22 | DM9: 22 | DN9: 22 | DO9: 101 | DP9: 22 | DQ9: 22 | DR9: 22 | DS9: 22 | DT9: 22 | DU9: 22 | DV9: 101 | DW9: 101 | DX9: 22 | DY9: 22 | DZ9: 22 | EA9: 101 | EB9: 101 | EC9: 101 | ED9: 22 | EE9: 22 | EF9: 101 | EG9: 101 | EH9: 101 | EI9: 101 | EJ9: 101 | EK9: 101 | EL9: 101 | EM9: 101 | EN9: 101 | EO9: 101 | EP9: 101 | EQ9: 101 | ER9: 101 | ES9: 101 | ET9: 101 | EU9: 101 | EV9: 101 | EW9: 101 | EX9: 101 | EY9: 101 | EZ9: 101 | FA9: 101 | FB9: 101 | FC9: 101 | FD9: 101 | FE9: 101 | FF9: 101 | FG9: 101 | FH9: 101 | FI9: 22 | FJ9: 22 | FK9: 22 | FL9: 22 | FM9: 22 | FN9: 101 | FO9: 22 | FP9: 101 | FQ9: 101 | FR9: 101 | FS9: 22 | FT9: 22 | FU9: 22 | FV9: 22 | FW9: 22 | FX9: 22 | FY9: 22 | FZ9: 22 | GA9: 22 | GB9: 22 | GC9: 22 | GD9: 22 | GE9: 22 | GF9: 43 | GG9: 43 | GH9: 101 | GI9: 101 | GJ9: 22 | GK9: 22 | GL9: 101 | GM9: 22 | GN9: 22 | GO9: 52 | GP9: 52 | GQ9: 22 | GR9: 22 | GS9: 22 | GT9: 22 | GU9: 22 | GV9: 22 | GW9: 22 | GX9: 22 | GY9: 22 | GZ9: 22 | HA9: 22 | HB9: 101 | HC9: 101 | HD9: 101 | HE9: 101 | HF9: 22 | HG9: 22 | HH9: 22 | HI9: 22 | HJ9: 22 | HK9: 22 | HL9: 22 | HM9: 22 | HN9: 22 | HO9: 22 | HP9: 22 | HQ9: 22 | HR9: 22 | HS9: 22 | HT9: 22 | HU9: 101 | HV9: 22 | HW9: 22 | HX9: 22 | HY9: 22 | HZ9: 22 | IA9: 22 | IB9: 43 | IC9: 22 | ID9: 22 | IE9: 22 | IF9: 22 | IG9: 22 | IH9: 22 | II9: 22 | IJ9: 22 | IK9: 101 | IL9: 101 | IM9: 101 | IN9: 22 | IO9: 22 | IP9: 22 | IQ9: 101
A10: Series ID | B10: A130397375X | C10: A130392957J | D10: A130394343A | E10: A130398033T | F10: A130394448W | G10: A130399331J | H10: A130399352V | I10: A130393055R | J10: A130394462T | K10: A130391473V | L10: A130396863T | M10: A130398096A | N10: A130390577V | O10: A130396898T | P10: A130399226F | Q10: A130396807X | R10: A130395603C | S10: A130398026V | T10: A130398687C | U10: A130398701L | V10: A130389961R | W10: A130396450V | X10: A130398152J | Y10: A130399422R | Z10: A130399688X | AA10: A130391004C | AB10: A130391347F | AC10: A130398180T | AD10: A130390220C | AE10: A130391970J | AF10: A130397620T | AG10: A130397956W | AH10: A130399401C | AI10: A130390605T | AJ10: A130396695T | AK10: A130391802W | AL10: A130397101R | AM10: A130399590A | AN10: A130395897W | AO10: A130394420V | AP10: A130394721X | AQ10: A130392964F | AR10: A130398967W | AS10: A130398460K | AT10: A130395995A | AU10: A130394847F | AV10: A130391746R | AW10: A130390661K | AX10: A130393293W | AY10: A130390682W | AZ10: A130394854C | BA10: A130392257V | BB10: A130390710V | BC10: A130394280C | BD10: A130392586J | BE10: A130390458C | BF10: A130394154R | BG10: A130392278F | BH10: A130392838T | BI10: A130394581J | BJ10: A130398488L | BK10: A130390472X | BL10: A130391053X | BM10: A130390724J | BN10: A130396282V | BO10: A130392999F | BP10: A130394133C | BQ10: A130398215F | BR10: A130397809W | BS10: A130391501T | BT10: A130394119J | BU10: A130393643K | BV10: A130399499L | BW10: A130393797A | BX10: A130396191L | BY10: A130398236T | BZ10: A130398530F | CA10: A130394623V | CB10: A130392173K | CC10: A130398544V | CD10: A130396037R | CE10: A130392558X | CF10: A130390955T | CG10: A130392565W | CH10: A130391270V | CI10: A130394161L | CJ10: A130393503J | CK10: A130399625R | CL10: A130399030C | CM10: A130398383T | CN10: A130390934F | CO10: A130391683T | CP10: A130399275A | CQ10: A130393370R | CR10: A130390857L | CS10: A130397059W | CT10: A130398355J | CU10: A130395862W | CV10: A130396772K | CW10: A130392124R | CX10: A130391277K | CY10: A130391781W | CZ10: A130390815R | DA10: A130398278R | DB10: A130393825X | DC10: A130399065C | DD10: A130394770V | DE10: A130390290K | DF10: A130391599A | DG10: A130399800L | DH10: A130392873X | DI10: A130398019W | DJ10: A130397199X | DK10: A130394791F | DL10: A130392523X | DM10: A130397353K | DN10: A130394966W | DO10: A130398257C | DP10: A130392040F | DQ10: A130391137J | DR10: A130394980T | DS10: A130396219C | DT10: A130393559V | DU10: A130393853J | DV10: A130393860F | DW10: A130395176W | DX10: A130398932W | DY10: A130392621C | DZ10: A130392628V | EA10: A130391620J | EB10: A130394231J | EC10: A130396170A | ED10: A130396086K | EE10: A130399170F | EF10: A130396709V | EG10: A130398040R | EH10: A130394455V | EI10: A130391886T | EJ10: A130391900A | EK10: A130390430A | EL10: A130396842F | EM10: A130397767K | EN10: A130391914R | EO10: A130399380C | EP10: A130399387V | EQ10: A130398124X | ER10: A130399233C | ES10: A130396814W | ET10: A130393174F | EU10: A130391858J | EV10: A130396156F | EW10: A130389940C | EX10: A130398708C | EY10: A130396457K | EZ10: A130391956L | FA10: A130394518T | FB10: A130397234V | FC10: A130397248J | FD10: A130391354C | FE10: A130396940K | FF10: A130396471F | FG10: A130399436C | FH10: A130396268X | FI10: A130394371K | FJ10: A130398131W | FK10: A130398138L | FL10: A130390409J | FM10: A130397991C | FN10: A130395911F | FO10: A130399597T | FP10: A130398369W | FQ10: A130391816K | FR10: A130395925V | FS10: A130396660T | FT10: A130396478W | FU10: A130393594A | FV10: A130396002R | FW10: A130391011A | FX10: A130395512W | FY10: A130391984W | FZ10: A130399457R | GA10: A130396975K | GB10: A130391025R | GC10: A130392264T | GD10: A130391998K | GE10: A130392985T | GF10: A130397627J | GG10: A130390465A | GH10: A130391529V | GI10: A130397297C | GJ10: A130398995F | GK10: A130396989X | GL10: A130398495K | GM10: A130391767A | GN10: A130394875R | GO10: A130395785C | GP10: A130396289K | GQ10: A130393006V | GR10: A130390276R | GS10: A130390752T | GT10: A130391522C | GU10: A130392810R | GV10: A130390269T | GW10: A130397311L | GX10: A130393307X | GY10: A130396184R | GZ10: A130395106R | HA10: A130394616W | HB10: A130397318C | HC10: A130397017X | HD10: A130398411R | HE10: A130392299T | HF10: A130394931W | HG10: A130395190T | HH10: A130392187X | HI10: A130390066T | HJ10: A130397522L | HK10: A130391557C | HL10: A130398404T | HM10: A130398390R | HN10: A130399037V | HO10: A130397122A | HP10: A130394742K | HQ10: A130390402T | HR10: A130395554V | HS10: A130390829C | HT10: A130390864K | HU10: A130399562T | HV10: A130392096T | HW10: A130390843X | HX10: A130396779A | HY10: A130394700L | HZ10: A130391284J | IA10: A130393104X | IB10: A130399541F | IC10: A130394651C | ID10: A130397543X | IE10: A130394217L | IF10: A130397178L | IG10: A130396555R | IH10: A130394182X | II10: A130398572C | IJ10: A130391606L | IK10: A130390514K | IL10: A130398432A | IM10: A130390976C | IN10: A130390017W | IO10: A130398593R | IP10: A130392327R | IQ10: A130398264A
A11: 42979 | D11: 73.27 | E11: 72.62 | F11: 73.55 | G11: 72.44 | H11: 75.33 | I11: 75.89 | J11: 68.25 | K11: 78.49 | L11: 68.35 | M11: 81.7 | N11: 78.07 | O11: 79.19 | P11: 72.02 | Q11: 70.23 | R11: 72.55 | S11: 73.22 | T11: 73.34 | U11: 70.78 | V11: 75.66 | W11: 73.52 | X11: 63.06 | Y11: 79.91 | Z11: 81.33 | AA11: 63.18 | AB11: 71.59 | AC11: 78.65 | AD11: 72.99 | AE11: 68.52 | AF11: 74.09 | AL11: 77.41 | AN11: 72.53 | AO11: 43.44 | AP11: 43.44 | BF11: 72.63 | BG11: 72.63 | BJ11: 76.5 | BZ11: 82.94 | CA11: 78.52 | CB11: 85.25 | CC11: 82.22 | CS11: 67.66 | DI11: 86.05 | DJ11: 69.38 | DK11: 67.68 | DO11: 74.03 | DV11: 70.1 | DW11: 74.09 | EA11: 80.55 | EB11: 96.97 | EC11: 78.89 | EF11: 73.5 | EG11: 71.63 | EH11: 74.52 | EI11: 73.08 | EJ11: 76.19 | EK11: 76.07 | EL11: 69.83 | EM11: 78.38 | EN11: 70.03 | EO11: 82.01 | EP11: 77.15 | EQ11: 78.1 | ER11: 72.41 | ES11: 71.14 | ET11: 72.23 | EU11: 73.94 | EV11: 72.09 | EW11: 68.32 | EX11: 74.95 | EY11: 73.3 | EZ11: 63.65 | FA11: 80.37 | FB11: 80.94 | FC11: 62.9 | FD11: 71.99 | FE11: 77.97 | FF11: 72.72 | FG11: 69.23 | FH11: 73.96 | FN11: 76.45 | FP11: 79.34 | FQ11: 42.38 | FR11: 42.38 | GH11: 74.19 | GI11: 74.19 | GL11: 76.09 | HB11: 83.72 | HC11: 79.47 | HD11: 86.96 | HE11: 81.97 | HU11: 68.05 | IK11: 81.53 | IL11: 67.48 | IM11: 68.01 | IQ11: 73.82
A12: 43009 | D12: 73.8 | E12: 73.48 | F12: 74.02 | G12: 71.49 | H12: 76.2 | I12: 76.13 | J12: 68.37 | K12: 78.36 | L12: 68.71 | M12: 82.1 | N12: 77.79 | O12: 80.06 | P12: 72.46 | Q12: 70.18 | R12: 73.3 | S12: 73.88 | T12: 78.5 | U12: 80.89 | V12: 75.91 | W12: 73.7 | X12: 62.04 | Y12: 80.63 | Z12: 81.81 | AA12: 64.16 | AB12: 71.65 | AC12: 78.81 | AD12: 73.26 | AE12: 69.03 | AF12: 74.29 | AL12: 77.59 | AN12: 71.6 | AO12: 45.16 | AP12: 45.16 | BF12: 71.69 | BG12: 71.69 | BJ12: 76.5 | BZ12: 82 | CA12: 79.2 | CB12: 83.45 | CC12: 81.61 | CS12: 71.53 | DI12: 86.19 | DJ12: 72.1 | DK12: 65.84 | DO12: 72.94 | DV12: 70.1 | DW12: 74.09 | EA12: 80.29 | EB12: 94.3 | EC12: 78.89 | EF12: 73.95 | EG12: 72.48 | EH12: 74.89 | EI12: 71.91 | EJ12: 76.99 | EK12: 76.46 | EL12: 70.04 | EM12: 78.58 | EN12: 70.55 | EO12: 82.39 | EP12: 77.08 | EQ12: 79.16 | ER12: 72.91 | ES12: 71.22 | ET12: 73.14 | EU12: 74.51 | EV12: 76.88 | EW12: 78.29 | EX12: 75.46 | EY12: 73.49 | EZ12: 63.05 | FA12: 80.87 | FB12: 81.5 | FC12: 63.53 | FD12: 72.09 | FE12: 78.14 | FF12: 72.94 | FG12: 69.66 | FH12: 74.1 | FN12: 75.76 | FP12: 79.66 | FQ12: 43.92 | FR12: 43.92 | GH12: 74.14 | GI12: 74.14 | GL12: 76.09 | HB12: 82.58 | HC12: 80.13 | HD12: 84.84 | HE12: 81.32 | HU12: 71.33 | IK12: 81.54 | IL12: 70.02 | IM12: 65.81 | IQ12: 72.73
A13: 43040 | D13: 74.24 | E13: 73.76 | F13: 74.55 | G13: 73.18 | H13: 75.92 | I13: 76.35 | J13: 68.53 | K13: 78.04 | L13: 69.58 | M13: 82.52 | N13: 78.56 | O13: 79.71 | P13: 72.29 | Q13: 70.5 | R13: 73.28 | S13: 73.1 | T13: 82.53 | U13: 84.86 | V13: 79.99 | W13: 73.92 | X13: 62.84 | Y13: 80.28 | Z13: 82.15 | AA13: 65.22 | AB13: 71.31 | AC13: 79.75 | AD13: 73.25 | AE13: 69.96 | AF13: 74.01 | AL13: 78.44 | AN13: 72.36 | AO13: 45.39 | AP13: 45.39 | BF13: 72.62 | BG13: 72.62 | BJ13: 76.5 | BZ13: 82.24 | CA13: 77.58 | CB13: 84.07 | CC13: 81.96 | CS13: 74.28 | DI13: 84.24 | DJ13: 70.11 | DK13: 64.61 | DO13: 73.59 | DV13: 70.1 | DW13: 74.09 | EA13: 80.3 | EB13: 94.32 | EC13: 78.89 | EF13: 74.38 | EG13: 72.77 | EH13: 75.3 | EI13: 73.85 | EJ13: 76.72 | EK13: 76.7 | EL13: 69.65 | EM13: 78.33 | EN13: 70.68 | EO13: 82.92 | EP13: 78.14 | EQ13: 79.62 | ER13: 72.85 | ES13: 71.66 | ET13: 73.21 | EU13: 73.79 | EV13: 81.14 | EW13: 82.79 | EX13: 79.51 | EY13: 73.68 | EZ13: 63.31 | FA13: 80.59 | FB13: 81.94 | FC13: 64.72 | FD13: 71.6 | FE13: 79.26 | FF13: 73.23 | FG13: 70.43 | FH13: 74.21 | FN13: 75.99 | FP13: 79.55 | FQ13: 44.15 | FR13: 44.15 | GH13: 74.32 | GI13: 74.32 | GL13: 76.09 | HB13: 82.97 | HC13: 78.41 | HD13: 85.34 | HE13: 81.99 | HU13: 74.56 | IK13: 81.19 | IL13: 70.29 | IM13: 65.02 | IQ13: 73.3
A14: 43070 | D14: 75.02 | E14: 74.59 | F14: 74.42 | G14: 76.18 | H14: 78.43 | I14: 75.93 | J14: 67.97 | K14: 77.92 | L14: 68.72 | M14: 81.81 | N14: 78.27 | O14: 79.63 | P14: 73.43 | Q14: 72.09 | R14: 73.55 | S14: 74.54 | T14: 82.34 | U14: 85.4 | V14: 79.08 | W14: 74.47 | X14: 63.19 | Y14: 80.45 | Z14: 81.07 | AA14: 66.42 | AB14: 72.25 | AC14: 80.27 | AD14: 78.71 | AE14: 69.61 | AF14: 81.18 | AL14: 77.75 | AN14: 73.7 | AO14: 45.32 | AP14: 45.32 | BF14: 73 | BG14: 73 | BJ14: 76.5 | BZ14: 82.83 | CA14: 78.5 | CB14: 85.74 | CC14: 81.62 | CS14: 75.06 | DI14: 93.8 | DJ14: 76.79 | DK14: 72.91 | DO14: 73.54 | DV14: 70.1 | DW14: 74.09 | EA14: 80.7 | EB14: 93.49 | EC14: 79.43 | EF14: 75.02 | EG14: 73.51 | EH14: 75.02 | EI14: 76.59 | EJ14: 79.02 | EK14: 76.25 | EL14: 69.29 | EM14: 79.39 | EN14: 69.88 | EO14: 82.42 | EP14: 77.42 | EQ14: 78.52 | ER14: 73.62 | ES14: 72.21 | ET14: 73.48 | EU14: 75.27 | EV14: 81.65 | EW14: 84.67 | EX14: 78.9 | EY14: 74.23 | EZ14: 63.98 | FA14: 80.62 | FB14: 80.73 | FC14: 65.82 | FD14: 72.65 | FE14: 79.69 | FF14: 72.28 | FG14: 70.52 | FH14: 72.88 | FN14: 73.82 | FP14: 79.13 | FQ14: 44.23 | FR14: 44.23 | GH14: 74.81 | GI14: 74.81 | GL14: 76.09 | HB14: 83.57 | HC14: 79.71 | HD14: 86.88 | HE14: 81.69 | HU14: 76.94 | IK14: 90.44 | IL14: 76 | IM14: 74.44 | IQ14: 73.25
A15: 43101 | D15: 74.63 | E15: 74.03 | F15: 75.18 | G15: 72.83 | H15: 76.28 | I15: 76.5 | J15: 68.89 | K15: 78.36 | L15: 69.05 | M15: 82.56 | N15: 77.64 | O15: 80.9 | P15: 73.12 | Q15: 71.12 | R15: 73.63 | S15: 74.56 | T15: 81.9 | U15: 81.39 | V15: 82.18 | W15: 74.69 | X15: 62.37 | Y15: 80.29 | Z15: 82.68 | AA15: 65.55 | AB15: 72.81 | AC15: 79.93 | AD15: 79.84 | AE15: 71.41 | AF15: 82.11 | AL15: 78.93 | AN15: 74.1 | AO15: 45.47 | AP15: 45.47 | BF15: 73.16 | BG15: 73.16 | BJ15: 76.5 | BZ15: 83.15 | CA15: 77.5 | CB15: 86.02 | CC15: 82.27 | CS15: 74.34 | DI15: 93.16 | DJ15: 79.11 | DK15: 70.26 | DO15: 73.99 | DV15: 70.1 | DW15: 74.09 | EA15: 80.7 | EB15: 93.51 | EC15: 79.43 | EF15: 74.88 | EG15: 73.07 | EH15: 76.13 | EI15: 73.77 | EJ15: 77 | EK15: 76.81 | EL15: 70.11 | EM15: 78.98 | EN15: 70.04 | EO15: 83.05 | EP15: 77.42 | EQ15: 80.09 | ER15: 73.36 | ES15: 71.4 | ET15: 73.61 | EU15: 75.24 | EV15: 81.07 | EW15: 79.97 | EX15: 81.71 | EY15: 74.59 | EZ15: 63.52 | FA15: 80.59 | FB15: 82.45 | FC15: 64.84 | FD15: 73.26 | FE15: 79.67 | FF15: 73.41 | FG15: 72.2 | FH15: 73.79 | FN15: 75.53 | FP15: 79.97 | FQ15: 44.34 | FR15: 44.34 | GH15: 74.54 | GI15: 74.54 | GL15: 76.09 | HB15: 83.87 | HC15: 78.31 | HD15: 87.15 | HE15: 82.31 | HU15: 75.83 | IK15: 90.13 | IL15: 78.71 | IM15: 71.59 | IQ15: 73.78
A16: 43132 | D16: 73.78 | E16: 73.84 | F16: 73.87 | G16: 73.02 | H16: 74.21 | I16: 76.11 | J16: 69.11 | K16: 78.69 | L16: 68.66 | M16: 82.68 | N16: 77.57 | O16: 78.59 | P16: 72.8 | Q16: 71 | R16: 73.59 | S16: 73.78 | T16: 82.56 | U16: 82.95 | V16: 81.95 | W16: 73.91 | X16: 62.36 | Y16: 78.57 | Z16: 82.26 | AA16: 65.11 | AB16: 72.13 | AC16: 78.7 | AD16: 79.41 | AE16: 69.6 | AF16: 82.09 | AL16: 79.15 | AN16: 74.16 | AO16: 45.26 | AP16: 45.26 | BF16: 73.83 | BG16: 73.83 | BJ16: 76.5 | BZ16: 81.99 | CA16: 77.45 | CB16: 83.91 | CC16: 81.61 | CS16: 72.99 | DI16: 85.58 | DJ16: 71.51 | DK16: 65.43 | DO16: 72.83 | DV16: 72.71 | DW16: 75.56 | EA16: 80.71 | EB16: 93.53 | EC16: 79.43 | EF16: 74.03 | EG16: 72.9 | EH16: 74.92 | EI16: 73.42 | EJ16: 75.07 | EK16: 76.26 | EL16: 70.27 | EM16: 78.76 | EN16: 69.97 | EO16: 82.62 | EP16: 77.21 | EQ16: 77.62 | ER16: 73 | ES16: 71.07 | ET16: 73.61 | EU16: 74.53 | EV16: 82.08 | EW16: 82.4 | EX16: 81.54 | EY16: 73.76 | EZ16: 63.5 | FA16: 79.16 | FB16: 82.22 | FC16: 64.74 | FD16: 72.37 | FE16: 78.16 | FF16: 73.24 | FG16: 70.57 | FH16: 74.17 | FN16: 76.8 | FP16: 81.39 | FQ16: 44 | FR16: 44 | GH16: 74.8 | GI16: 74.8 | GL16: 76.09 | HB16: 82.95 | HC16: 78.41 | HD16: 85.6 | HE16: 81.76 | HU16: 75.63 | IK16: 82.25 | IL16: 71.16 | IM16: 65.91 | IQ16: 72.83
A17: 43160 | D17: 74.05 | E17: 73.85 | F17: 74.2 | G17: 71.21 | H17: 76.8 | I17: 76.22 | J17: 69.15 | K17: 79.11 | L17: 68.68 | M17: 82.25 | N17: 78.53 | O17: 78.37 | P17: 73.05 | Q17: 71.36 | R17: 73.77 | S17: 74 | T17: 81.59 | U17: 81.8 | V17: 81.16 | W17: 73.91 | X17: 62.9 | Y17: 80.49 | Z17: 82.18 | AA17: 65.37 | AB17: 71.89 | AC17: 78.45 | AD17: 79.45 | AE17: 70.34 | AF17: 81.93 | AL17: 79.06 | AN17: 74.52 | AO17: 45.78 | AP17: 45.78 | BF17: 74 | BG17: 74 | BJ17: 76.5 | BZ17: 82.78 | CA17: 77.98 | CB17: 84.78 | CC17: 82.4 | CS17: 72.54 | DI17: 83.89 | DJ17: 71.75 | DK17: 62.89 | DO17: 72.8 | DV17: 72.71 | DW17: 75.56 | EA17: 80.49 | EB17: 93.55 | EC17: 79.19 | EF17: 74.3 | EG17: 72.92 | EH17: 75.2 | EI17: 72 | EJ17: 77.39 | EK17: 76.56 | EL17: 70.13 | EM17: 79.69 | EN17: 71.44 | EO17: 82.72 | EP17: 77.48 | EQ17: 77.57 | ER17: 73.29 | ES17: 71.56 | ET17: 73.81 | EU17: 74.67 | EV17: 80.49 | EW17: 80.96 | EX17: 79.84 | EY17: 73.76 | EZ17: 63.96 | FA17: 80.74 | FB17: 82.12 | FC17: 64.63 | FD17: 72.22 | FE17: 78.04 | FF17: 73.07 | FG17: 71.22 | FH17: 73.69 | FN17: 76.46 | FP17: 81.08 | FQ17: 44.51 | FR17: 44.51 | GH17: 75.01 | GI17: 75.01 | GL17: 76.09 | HB17: 83.51 | HC17: 78.92 | HD17: 86.22 | HE17: 82.27 | HU17: 73.78 | IK17: 80.96 | IL17: 71.63 | IM17: 63.51 | IQ17: 72.59
A18: 43191 | D18: 73.76 | E18: 73.26 | F18: 74.02 | G18: 71.42 | H18: 76.65 | I18: 76.4 | J18: 68.32 | K18: 78.03 | L18: 70.77 | M18: 82.12 | N18: 78.23 | O18: 80.16 | P18: 73.4 | Q18: 71.7 | R18: 74.13 | S18: 74.35 | T18: 79.75 | U18: 79.44 | V18: 79.83 | W18: 73.87 | X18: 63.43 | Y18: 77.67 | Z18: 81.21 | AA18: 66.01 | AB18: 72.65 | AC18: 77.7 | AD18: 79.44 | AE18: 68.89 | AF18: 82.35 | AL18: 79.31 | AN18: 76.4 | AO18: 46.43 | AP18: 46.43 | BF18: 73.8 | BG18: 73.8 | BJ18: 76.5 | BZ18: 82.27 | CA18: 76.86 | CB18: 83.81 | CC18: 82.4 | CS18: 77.12 | DI18: 88.91 | DJ18: 74.17 | DK18: 68.07 | DO18: 73.22 | DV18: 72.71 | DW18: 75.56 | EA18: 80.49 | EB18: 93.57 | EC18: 79.19 | EF18: 73.98 | EG18: 72.23 | EH18: 75.11 | EI18: 71.84 | EJ18: 77.21 | EK18: 76.81 | EL18: 69.88 | EM18: 78.71 | EN18: 71.7 | EO18: 82.85 | EP18: 77.72 | EQ18: 79.46 | ER18: 73.51 | ES18: 71.7 | ET18: 74 | EU18: 75.01 | EV18: 78.28 | EW18: 77.65 | EX18: 78.54 | EY18: 73.7 | EZ18: 64.09 | FA18: 78.46 | FB18: 80.78 | FC18: 65.38 | FD18: 72.96 | FE18: 77.16 | FF18: 73.19 | FG18: 69.68 | FH18: 74.44 | FN18: 77.16 | FP18: 80.72 | FQ18: 45.07 | FR18: 45.07 | GH18: 75.95 | GI18: 75.95 | GL18: 76.09 | HB18: 82.89 | HC18: 77.92 | HD18: 84.93 | HE18: 82.26 | HU18: 77.56 | IK18: 85.5 | IL18: 73.37 | IM18: 69.05 | IQ18: 73.02
A19: 43221 | D19: 73.72 | E19: 74.18 | F19: 73.13 | G19: 72.05 | H19: 76.33 | I19: 76.47 | J19: 67.79 | K19: 77.97 | L19: 70.45 | M19: 82.14 | N19: 78.96 | O19: 80.7 | P19: 73.29 | Q19: 71.28 | R19: 74.31 | S19: 74.28 | T19: 78.1 | U19: 78.93 | V19: 77.06 | W19: 73.28 | X19: 63.06 | Y19: 80.36 | Z19: 81.06 | AA19: 65.15 | AB19: 71.59 | AC19: 76.98 | AD19: 78.71 | AE19: 68.18 | AF19: 81.61 | AL19: 79.94 | AN19: 76.19 | AO19: 46.93 | AP19: 46.93 | BF19: 74.07 | BG19: 74.07 | BJ19: 76.5 | BZ19: 82.02 | CA19: 75.45 | CB19: 83.59 | CC19: 82.37 | CS19: 80.47 | DI19: 84.74 | DJ19: 69.98 | DK19: 65.41 | DO19: 73.4 | DV19: 72.71 | DW19: 75.56 | EA19: 80.5 | EB19: 93.59 | EC19: 79.19 | EF19: 73.93 | EG19: 72.93 | EH19: 74.35 | EI19: 72.72 | EJ19: 76.89 | EK19: 76.49 | EL19: 68.39 | EM19: 78.52 | EN19: 71.08 | EO19: 82.29 | EP19: 78.29 | EQ19: 80.24 | ER19: 73.41 | ES19: 71.35 | ET19: 74.16 | EU19: 74.94 | EV19: 77.73 | EW19: 77.73 | EX19: 77.47 | EY19: 73.04 | EZ19: 63.55 | FA19: 80.61 | FB19: 80.56 | FC19: 64.32 | FD19: 71.98 | FE19: 76.34 | FF19: 73.11 | FG19: 68.67 | FH19: 74.71 | FN19: 76.76 | FP19: 81.04 | FQ19: 45.56 | FR19: 45.56 | GH19: 76.02 | GI19: 76.02 | GL19: 76.09 | HB19: 82.67 | HC19: 76.57 | HD19: 85.03 | HE19: 81.98 | HU19: 80.48 | IK19: 80.83 | IL19: 68.32 | IM19: 66.19 | IQ19: 73.06
A20: 43252 | D20: 73.48 | E20: 74.02 | F20: 72.95 | G20: 72.3 | H20: 75.11 | I20: 76.36 | J20: 67.93 | K20: 76.96 | L20: 70.79 | M20: 82.44 | N20: 77.92 | O20: 81.12 | P20: 73.39 | Q20: 71.55 | R20: 74.01 | S20: 74.57 | T20: 80.35 | U20: 80.59 | V20: 79.89 | W20: 73.29 | X20: 63.3 | Y20: 79.19 | Z20: 81.32 | AA20: 64.97 | AB20: 71.47 | AC20: 77.38 | AD20: 77.89 | AE20: 68.22 | AF20: 80.53 | AL20: 79.35 | AN20: 76.02 | AO20: 46.83 | AP20: 46.83 | BF20: 74.39 | BG20: 74.39 | BJ20: 76.5 | BZ20: 81.81 | CA20: 75.75 | CB20: 84.08 | CC20: 81.49 | CS20: 80.4 | DI20: 86.56 | DJ20: 70.59 | DK20: 67.48 | DO20: 72.41 | DV20: 72.71 | DW20: 75.56 | EA20: 80.75 | EB20: 93.6 | EC20: 79.48 | EF20: 73.69 | EG20: 72.8 | EH20: 74.12 | EI20: 72.92 | EJ20: 75.89 | EK20: 76.64 | EL20: 68.5 | EM20: 77.56 | EN20: 71.42 | EO20: 82.91 | EP20: 77.44 | EQ20: 81.4 | ER20: 73.52 | ES20: 71.55 | ET20: 74.05 | EU20: 75.16 | EV20: 79.28 | EW20: 78.37 | EX20: 79.76 | EY20: 73.04 | EZ20: 63.69 | FA20: 79.63 | FB20: 80.78 | FC20: 64.13 | FD20: 71.88 | FE20: 76.68 | FF20: 72.46 | FG20: 68.42 | FH20: 73.91 | FN20: 77.69 | FP20: 80.79 | FQ20: 45.42 | FR20: 45.42 | GH20: 76.79 | GI20: 76.79 | GL20: 76.09 | HB20: 82.45 | HC20: 76.66 | HD20: 85.22 | HE20: 81.36 | HU20: 81.63 | IK20: 82.39 | IL20: 68.71 | IM20: 68.28 | IQ20: 72.28
A21: 43282 | D21: 74.04 | E21: 75.01 | F21: 73.83 | G21: 71.07 | H21: 74.4 | I21: 76.3 | J21: 67.33 | K21: 77.12 | L21: 70.42 | M21: 83.3 | N21: 77.27 | O21: 81.4 | P21: 73.4 | Q21: 71.46 | R21: 74.16 | S21: 74.54 | T21: 80.75 | U21: 82.45 | V21: 78.84 | W21: 73.72 | X21: 63.05 | Y21: 80.29 | Z21: 81.54 | AA21: 66.31 | AB21: 71.94 | AC21: 77.58 | AD21: 78.98 | AE21: 70.13 | AF21: 81.38 | AL21: 80.12 | AN21: 76.81 | AO21: 46.95 | AP21: 46.95 | BF21: 74.52 | BG21: 74.52 | BJ21: 76.5 | BZ21: 81.98 | CA21: 76.52 | CB21: 84.18 | CC21: 81.58 | CS21: 77.66 | DI21: 94.68 | DJ21: 74.74 | DK21: 75.66 | DO21: 72.78 | DV21: 72.71 | DW21: 75.56 | EA21: 80.76 | EB21: 93.63 | EC21: 79.48 | EF21: 74.07 | EG21: 73.7 | EH21: 74.65 | EI21: 71.59 | EJ21: 75.37 | EK21: 76.61 | EL21: 68.44 | EM21: 77.85 | EN21: 71.41 | EO21: 83.75 | EP21: 76.95 | EQ21: 80.66 | ER21: 73.45 | ES21: 71.4 | ET21: 74 | EU21: 75.17 | EV21: 79.25 | EW21: 80.8 | EX21: 77.72 | EY21: 73.4 | EZ21: 63.37 | FA21: 80.36 | FB21: 80.92 | FC21: 65.65 | FD21: 72.14 | FE21: 77 | FF21: 73.45 | FG21: 70.95 | FH21: 74.33 | FN21: 77.39 | FP21: 81.03 | FQ21: 45.6 | FR21: 45.6 | GH21: 76.26 | GI21: 76.26 | GL21: 76.09 | HB21: 82.76 | HC21: 77.78 | HD21: 85.42 | HE21: 81.62 | HU21: 80.11 | IK21: 88.45 | IL21: 71.29 | IM21: 75.46 | IQ21: 72.56
A22: 43313 | D22: 73.93 | E22: 75.12 | F22: 73 | G22: 72.21 | H22: 75.44 | I22: 77.01 | J22: 69.1 | K22: 77.63 | L22: 72.19 | M22: 83.08 | N22: 77.95 | O22: 81.24 | P22: 72.91 | Q22: 70.98 | R22: 73.94 | S22: 73.81 | T22: 80.4 | U22: 79.64 | V22: 80.93 | W22: 74.01 | X22: 62.94 | Y22: 79.77 | Z22: 81.4 | AA22: 66.44 | AB22: 72.61 | AC22: 77.74 | AD22: 78.88 | AE22: 69.01 | AF22: 81.59 | AL22: 79.83 | AN22: 77.69 | AO22: 47.05 | AP22: 47.05 | BF22: 74.58 | BG22: 74.58 | BJ22: 76.5 | BZ22: 81.83 | CA22: 76.41 | CB22: 83.64 | CC22: 81.74 | CS22: 80.14 | DI22: 86.27 | DJ22: 72.35 | DK22: 65.76 | DO22: 72.73 | DV22: 72.71 | DW22: 78.01 | EA22: 80.76 | EB22: 93.66 | EC22: 79.48 | EF22: 73.99 | EG22: 73.76 | EH22: 73.99 | EI22: 73 | EJ22: 76.02 | EK22: 77.11 | EL22: 69.91 | EM22: 78.22 | EN22: 72.96 | EO22: 82.84 | EP22: 77.72 | EQ22: 80.6 | ER22: 73.05 | ES22: 70.94 | ET22: 74.08 | EU22: 74.39 | EV22: 79.42 | EW22: 78.34 | EX22: 80.05 | EY22: 73.72 | EZ22: 63.2 | FA22: 79.95 | FB22: 80.85 | FC22: 66.21 | FD22: 72.7 | FE22: 77.27 | FF22: 73.08 | FG22: 69.96 | FH22: 74.18 | FN22: 77.36 | FP22: 82.06 | FQ22: 45.77 | FR22: 45.77 | GH22: 75.37 | GI22: 75.37 | GL22: 76.09 | HB22: 82.37 | HC22: 77.32 | HD22: 84.68 | HE22: 81.54 | HU22: 78.91 | IK22: 81.53 | IL22: 69.97 | IM22: 65.84 | IQ22: 72.64
... A59: 44440 | D59: 79.15 | E59: 78.83 | F59: 78.11 | G59: 81.7 | H59: 82.85 | I59: 87.33 | J59: 87.31 | K59: 86.97 | L59: 86.12 | M59: 87.3 | N59: 89.02 | O59: 85.92 | P59: 79.82 | Q59: 79.3 | R59: 80.93 | S59: 79.25 | T59: 82.9 | U59: 77.95 | V59: 86.99 | W59: 78.15 | X59: 68.01 | Y59: 86 | Z59: 84.05 | AA59: 70.19 | AB59: 76.17 | AC59: 83.02 | AD59: 80.97 | AE59: 73.2 | AF59: 83.07 | AL59: 83.03 | AN59: 82.34 | AO59: 70.22 | AP59: 70.22 | BF59: 78.03 | BG59: 78.03 | BJ59: 83.57 | BZ59: 86.23 | CA59: 82.3 | CB59: 87.75 | CC59: 85.99 | CS59: 87.16 | DI59: 86.2 | DJ59: 82.11 | DK59: 75.63 | DO59: 81.28 | DV59: 81.73 | DW59: 78.62 | EA59: 84.82 | EB59: 90.3 | EC59: 84.34 | EF59: 79.39 | EG59: 78.27 | EH59: 78.98 | EI59: 81.75 | EJ59: 83.16 | EK59: 87.94 | EL59: 89.3 | EM59: 87.12 | EN59: 86.53 | EO59: 87.45 | EP59: 89.55 | EQ59: 86.03 | ER59: 79.68 | ES59: 79.07 | ET59: 80.77 | EU59: 79.26 | EV59: 83.16 | EW59: 77.82 | EX59: 86.78 | EY59: 77.88 | EZ59: 67.88 | FA59: 85.57 | FB59: 83.9 | FC59: 70.16 | FD59: 76.28 | FE59: 82.86 | FF59: 74.7 | FG59: 73.12 | FH59: 75.28 | FN59: 81.71 | FP59: 85.01 | FQ59: 68.62 | FR59: 68.62 | GH59: 79.48 | GI59: 79.48 | GL59: 84.43 | HB59: 86.34 | HC59: 82.48 | HD59: 88.32 | HE59: 85.54 | HU59: 85.49 | IK59: 82.02 | IL59: 78.99 | IM59: 73.61 | IQ59: 81.17
A60: 44470 | D60: 79.29 | E60: 78.62 | F60: 78.91 | G60: 78.96 | H60: 83.7 | I60: 86.95 | J60: 87.25 | K60: 86.81 | L60: 85.78 | M60: 86.15 | N60: 88.67 | O60: 85.68 | P60: 79.79 | Q60: 78.68 | R60: 81.07 | S60: 79.78 | T60: 82.98 | U60: 79.16 | V60: 86.08 | W60: 78.5 | X60: 68.27 | Y60: 86.08 | Z60: 84.63 | AA60: 70.47 | AB60: 76.62 | AC60: 83.16 | AD60: 81.04 | AE60: 73.89 | AF60: 82.98 | AL60: 83.93 | AN60: 83.56 | AO60: 70.81 | AP60: 70.81 | BF60: 77.63 | BG60: 77.63 | BJ60: 83.57 | BM60: 72.41 | BN60: 71.13 | BZ60: 86.13 | CA60: 82.71 | CB60: 86.6 | CC60: 86.51 | CS60: 91.48 | DI60: 91.99 | DJ60: 87.45 | DK60: 84.5 | DO60: 80.12 | DV60: 81.73 | DW60: 78.62 | EA60: 84.82 | EB60: 90.35 | EC60: 84.34 | EF60: 79.77 | EG60: 78.43 | EH60: 79.98 | EI60: 79.1 | EJ60: 83.98 | EK60: 87.7 | EL60: 89.31 | EM60: 87.06 | EN60: 86.66 | EO60: 86.75 | EP60: 89.4 | EQ60: 85.55 | ER60: 79.78 | ES60: 78.77 | ET60: 81.01 | EU60: 79.77 | EV60: 84.36 | EW60: 80.97 | EX60: 86.54 | EY60: 78.28 | EZ60: 68.23 | FA60: 85.69 | FB60: 84.51 | FC60: 70.45 | FD60: 76.69 | FE60: 83.23 | FF60: 74.86 | FG60: 74.53 | FH60: 74.99 | FN60: 83.42 | FP60: 85.4 | FQ60: 69.27 | FR60: 69.27 | GH60: 79.65 | GI60: 79.65 | GL60: 84.43 | GO60: 100.83 | GP60: 60.92 | HB60: 86.48 | HC60: 83.35 | HD60: 87.41 | HE60: 86.34 | HU60: 89.73 | IK60: 81.47 | IL60: 78.1 | IM60: 82.32 | IQ60: 80.29
A61: 44501 | D61: 80.02 | E61: 79.09 | F61: 79.83 | G61: 80.83 | H61: 83.77 | I61: 87.48 | J61: 87.44 | K61: 88.47 | L61: 85.36 | M61: 85.97 | N61: 90.7 | O61: 85.87 | P61: 80.35 | Q61: 78.72 | R61: 82.46 | S61: 80.1 | T61: 85.86 | U61: 83.39 | V61: 87.74 | W61: 78.8 | X61: 67.16 | Y61: 85.76 | Z61: 85.02 | AA61: 71.24 | AB61: 76.55 | AC61: 84.47 | AD61: 80.58 | AE61: 72.74 | AF61: 82.71 | AL61: 83.67 | AN61: 83.66 | AO61: 71.55 | AP61: 71.55 | BF61: 78.79 | BG61: 78.79 | BJ61: 83.57 | BM61: 73.85 | BN61: 71.13 | BZ61: 86.65 | CA61: 83.35 | CB61: 86.94 | CC61: 87.13 | CS61: 88.65 | DI61: 86.35 | DJ61: 81.83 | DK61: 84.78 | DO61: 80.91 | DV61: 81.73 | DW61: 78.62 | EA61: 84.86 | EB61: 90.82 | EC61: 84.34 | EF61: 80.33 | EG61: 78.69 | EH61: 80.68 | EI61: 81.06 | EJ61: 84.03 | EK61: 87.86 | EL61: 89.21 | EM61: 87.69 | EN61: 86.51 | EO61: 86.38 | EP61: 90.28 | EQ61: 85.9 | ER61: 80.38 | ES61: 78.97 | ET61: 82.24 | EU61: 80.19 | EV61: 85.21 | EW61: 82.11 | EX61: 87.19 | EY61: 78.6 | EZ61: 67.28 | FA61: 85.29 | FB61: 84.81 | FC61: 71.23 | FD61: 76.7 | FE61: 84.6 | FF61: 74.56 | FG61: 72.89 | FH61: 75.18 | FN61: 83.12 | FP61: 85.35 | FQ61: 69.68 | FR61: 69.68 | GH61: 80.88 | GI61: 80.88 | GL61: 84.43 | GO61: 102.25 | GP61: 63.74 | HB61: 87.23 | HC61: 84.1 | HD61: 87.68 | HE61: 87.45 | HU61: 92.69 | IK61: 77.26 | IL61: 73.88 | IM61: 82.58 | IQ61: 81.02
A62: 44531 | D62: 80.66 | E62: 79.46 | F62: 80.35 | G62: 82.72 | H62: 84.86 | I62: 87.63 | J62: 88.68 | K62: 86.64 | L62: 86.28 | M62: 86.23 | N62: 89.64 | O62: 86.53 | P62: 82.62 | Q62: 82.65 | R62: 82.58 | S62: 82.59 | T62: 87.73 | U62: 84.35 | V62: 90.41 | W62: 79.31 | X62: 67.51 | Y62: 86.81 | Z62: 84.08 | AA62: 70.41 | AB62: 77.2 | AC62: 86.03 | AD62: 80.94 | AE62: 74.38 | AF62: 82.71 | AL62: 83.64 | AN62: 83.55 | AO62: 72.02 | AP62: 72.02 | BF62: 81.01 | BG62: 81.01 | BJ62: 83.57 | BM62: 74.6 | BN62: 72.83 | BZ62: 88.51 | CA62: 86.36 | CB62: 88.48 | CC62: 88.99 | CS62: 91.98 | DI62: 93.48 | DJ62: 88.91 | DK62: 84.97 | DO62: 83.13 | DV62: 81.73 | DW62: 78.62 | EA62: 85.57 | EB62: 90.96 | EC62: 85.1 | EF62: 80.87 | EG62: 79.09 | EH62: 80.97 | EI62: 82.45 | EJ62: 85.32 | EK62: 88.12 | EL62: 90.52 | EM62: 86.69 | EN62: 86.04 | EO62: 86.57 | EP62: 90.78 | EQ62: 86.2 | ER62: 82.55 | ES62: 82.57 | ET62: 82.4 | EU62: 82.65 | EV62: 87.31 | EW62: 83.67 | EX62: 89.68 | EY62: 78.99 | EZ62: 67.63 | FA62: 86.3 | FB62: 83.95 | FC62: 70.22 | FD62: 77.19 | FE62: 86.28 | FF62: 75.22 | FG62: 74.47 | FH62: 75.5 | FN62: 82.54 | FP62: 84.05 | FQ62: 70.11 | FR62: 70.11 | GH62: 81.88 | GI62: 81.88 | GL62: 84.43 | GO62: 101.84 | GP62: 65.82 | HB62: 88.71 | HC62: 86.42 | HD62: 89.05 | HE62: 88.88 | HU62: 84.7 | IK62: 87.35 | IL62: 83.96 | IM62: 82.8 | IQ62: 83.2
A63: 44562 | D63: 81.07 | E63: 79.46 | F63: 81.21 | G63: 82.58 | H63: 85.33 | I63: 90.54 | J63: 93.28 | K63: 89.1 | L63: 91.09 | M63: 88.43 | N63: 92.57 | O63: 87.32 | P63: 82.09 | Q63: 82.27 | R63: 81.92 | S63: 82.02 | T63: 89.34 | U63: 85.26 | V63: 92.65 | W63: 80.78 | X63: 67.95 | Y63: 86.35 | Z63: 86.37 | AA63: 72.74 | AB63: 79.28 | AC63: 86.4 | AD63: 83 | AE63: 77.27 | AF63: 84.52 | AL63: 83.58 | AN63: 83.8 | AO63: 72.23 | AP63: 72.23 | BF63: 81.36 | BG63: 81.36 | BJ63: 83.57 | BM63: 74.45 | BN63: 72.83 | BZ63: 89.77 | CA63: 85.91 | CB63: 89.74 | CC63: 90.6 | CS63: 92.59 | DI63: 96.25 | DJ63: 92.59 | DK63: 65.34 | DO63: 85.12 | DV63: 81.73 | DW63: 78.62 | EA63: 85.56 | EB63: 90.82 | EC63: 85.1 | EF63: 81.36 | EG63: 79.13 | EH63: 81.89 | EI63: 82.6 | EJ63: 85.76 | EK63: 91.13 | EL63: 95.26 | EM63: 89.14 | EN63: 91.41 | EO63: 88.86 | EP63: 93.01 | EQ63: 87.22 | ER63: 82.18 | ES63: 82.33 | ET63: 81.75 | EU63: 82.38 | EV63: 88.6 | EW63: 84.08 | EX63: 91.6 | EY63: 80.55 | EZ63: 68.2 | FA63: 85.98 | FB63: 86.31 | FC63: 72.46 | FD63: 79.23 | FE63: 86.76 | FF63: 76.87 | FG63: 77.09 | FH63: 76.79 | FN63: 83 | FP63: 85.05 | FQ63: 70.3 | FR63: 70.3 | GH63: 83.37 | GI63: 83.37 | GL63: 84.43 | GO63: 101.12 | GP63: 66.93 | HB63: 89.98 | HC63: 86.2 | HD63: 89.89 | HE63: 90.7 | HU63: 90.49 | IK63: 90.44 | IL63: 87.65 | IM63: 67.75 | IQ63: 85.09
A64: 44593 | D64: 80.58 | E64: 79.71 | F64: 80.47 | G64: 78.07 | H64: 86.14 | I64: 92.41 | J64: 94.6 | K64: 90.39 | L64: 93.82 | M64: 90.54 | N64: 94.45 | O64: 89.37 | P64: 81.82 | Q64: 81.95 | R64: 82.12 | S64: 81.31 | T64: 91.78 | U64: 89.45 | V64: 93.52 | W64: 80.56 | X64: 68.26 | Y64: 86.03 | Z64: 88.3 | AA64: 73.91 | AB64: 77.77 | AC64: 86.61 | AD64: 86.44 | AE64: 76.71 | AF64: 89.1 | AL64: 84.7 | AN64: 84.43 | AO64: 72.12 | AP64: 72.12 | BF64: 82.36 | BG64: 82.36 | BJ64: 83.57 | BM64: 74.45 | BN64: 72.83 | BZ64: 91.03 | CA64: 86.38 | CB64: 88.06 | CC64: 94.07 | CS64: 97.17 | DI64: 83.4 | DJ64: 80.03 | DK64: 60.66 | DO64: 84.48 | DV64: 84.28 | DW64: 82.83 | EA64: 85.56 | EB64: 90.87 | EC64: 85.1 | EF64: 81.05 | EG64: 79.48 | EH64: 81.36 | EI64: 78.7 | EJ64: 86.79 | EK64: 92.83 | EL64: 96.39 | EM64: 90.85 | EN64: 93.95 | EO64: 89.96 | EP64: 95.2 | EQ64: 89.19 | ER64: 81.92 | ES64: 82.03 | ET64: 82.02 | EU64: 81.61 | EV64: 91.58 | EW64: 88.16 | EX64: 93.76 | EY64: 80.3 | EZ64: 68.37 | FA64: 85.86 | FB64: 87.96 | FC64: 73.64 | FD64: 77.72 | FE64: 86.86 | FF64: 79.76 | FG64: 76.77 | FH64: 80.84 | FN64: 84.48 | FP64: 85.83 | FQ64: 70.28 | FR64: 70.28 | GH64: 84.23 | GI64: 84.23 | GL64: 84.43 | GO64: 100.26 | GP64: 69.27 | HB64: 91.14 | HC64: 86.63 | HD64: 88.54 | HE64: 93.83 | HU64: 97.05 | IK64: 78.59 | IL64: 76.01 | IM64: 62.74 | IQ64: 84.7
A65: 44621 | D65: 82.1 | E65: 81.61 | F65: 80.38 | G65: 86.66 | H65: 87.53 | I65: 91.19 | J65: 95.3 | K65: 89.09 | L65: 91.66 | M65: 90.84 | N65: 94.31 | O65: 84.75 | P65: 82.85 | Q65: 82.41 | R65: 83.94 | S65: 82.21 | T65: 93.11 | U65: 88.14 | V65: 97.18 | W65: 81.31 | X65: 68.66 | Y65: 87.44 | Z65: 88.63 | AA65: 75.39 | AB65: 79.27 | AC65: 85.83 | AD65: 86.28 | AE65: 79.99 | AF65: 87.96 | AL65: 85.18 | AN65: 84.37 | AO65: 72.85 | AP65: 72.85 | BF65: 84.39 | BG65: 84.39 | BJ65: 83.57 | BM65: 74.31 | BN65: 72.83 | BZ65: 92.28 | CA65: 88.03 | CB65: 89.53 | CC65: 95.1 | CS65: 108.54 | DI65: 84.57 | DJ65: 81.13 | DK65: 62.31 | DO65: 89.6 | DV65: 84.28 | DW65: 82.83 | EA65: 86.14 | EB65: 90.91 | EC65: 85.73 | EF65: 82.48 | EG65: 81.52 | EH65: 81.18 | EI65: 86.6 | EJ65: 87.83 | EK65: 91.83 | EL65: 97.46 | EM65: 89.15 | EN65: 92.42 | EO65: 90.63 | EP65: 94.48 | EQ65: 84.82 | ER65: 82.76 | ES65: 82.21 | ET65: 83.77 | EU65: 82.36 | EV65: 91.84 | EW65: 85.07 | EX65: 96.47 | EY65: 80.88 | EZ65: 68.74 | FA65: 87.15 | FB65: 87.93 | FC65: 74.85 | FD65: 79 | FE65: 85.9 | FF65: 80.04 | FG65: 80.09 | FH65: 80.02 | FN65: 84.11 | FP65: 85.08 | FQ65: 70.99 | FR65: 70.99 | GH65: 86.12 | GI65: 86.12 | GL65: 84.43 | GO65: 100.26 | GP65: 69.25 | HB65: 92.17 | HC65: 88.46 | HD65: 90.11 | HE65: 94.34 | HU65: 110.03 | IK65: 82.68 | IL65: 80.01 | IM65: 64.69 | IQ65: 89.5
A66: 44652 | D66: 83.26 | E66: 83.05 | F66: 81.43 | G66: 87.59 | H66: 88.37 | I66: 91.34 | J66: 95.18 | K66: 88.6 | L66: 91.58 | M66: 92.04 | N66: 93.99 | O66: 85.22 | P66: 83.62 | Q66: 83.01 | R66: 84.09 | S66: 83.82 | T66: 94.5 | U66: 88.48 | V66: 99.51 | W66: 82 | X66: 69.11 | Y66: 88.04 | Z66: 88.63 | AA66: 77.38 | AB66: 79.68 | AC66: 86.95 | AD66: 86.27 | AE66: 79.9 | AF66: 87.98 | AL66: 85.31 | AN66: 84.4 | AO66: 73.05 | AP66: 73.05 | BF66: 85.2 | BG66: 85.2 | BJ66: 83.57 | BM66: 73.01 | BN66: 72.31 | BZ66: 93.18 | CA66: 90.39 | CB66: 91.13 | CC66: 95.2 | CS66: 93.59 | DI66: 91.33 | DJ66: 87.48 | DK66: 70.08 | DO66: 91.5 | DV66: 84.28 | DW66: 82.83 | EA66: 86 | EB66: 89.23 | EC66: 85.73 | EF66: 83.5 | EG66: 82.88 | EH66: 82.04 | EI66: 87.54 | EJ66: 88.44 | EK66: 91.92 | EL66: 97.65 | EM66: 89.02 | EN66: 92.05 | EO66: 91.02 | EP66: 94.63 | EQ66: 84.9 | ER66: 83.55 | ES66: 82.88 | ET66: 83.8 | EU66: 84.13 | EV66: 92.79 | EW66: 84.97 | EX66: 98.18 | EY66: 81.61 | EZ66: 69.21 | FA66: 87.58 | FB66: 87.89 | FC66: 76.97 | FD66: 79.51 | FE66: 86.98 | FF66: 80.27 | FG66: 80.08 | FH66: 80.34 | FN66: 83.95 | FP66: 85.81 | FQ66: 71.2 | FR66: 71.2 | GH66: 89.29 | GI66: 89.29 | GL66: 84.43 | GO66: 100.39 | GP66: 69.25 | HB66: 93.2 | HC66: 89.95 | HD66: 91.66 | HE66: 94.92 | HU66: 94.59 | IK66: 85.5 | IL66: 82.47 | IM66: 73.68 | IQ66: 91.3
A67: 44682 | D67: 83.6 | E67: 83.78 | F67: 81.67 | G67: 85.41 | H67: 89.59 | I67: 92.24 | J67: 95.78 | K67: 89.44 | L67: 92.86 | M67: 92.12 | N67: 94.88 | O67: 86.91 | P67: 83.09 | Q67: 81.78 | R67: 84.38 | S67: 83.28 | T67: 95.98 | U67: 90.39 | V67: 100.6 | W67: 81.87 | X67: 69.41 | Y67: 87.35 | Z67: 89.52 | AA67: 77.65 | AB67: 78.85 | AC67: 87.37 | AD67: 86.74 | AE67: 78.91 | AF67: 88.86 | AL67: 85.52 | AN67: 84.75 | AO67: 73.08 | AP67: 73.08 | BF67: 86.09 | BG67: 86.09 | BJ67: 83.57 | BM67: 73.44 | BN67: 70.99 | BZ67: 93.66 | CA67: 91.43 | CB67: 91.85 | CC67: 95.4 | CS67: 105.02 | DI67: 85.23 | DJ67: 81.14 | DK67: 75.93 | DO67: 90.35 | DV67: 84.28 | DW67: 82.83 | EA67: 86.01 | EB67: 89.3 | EC67: 85.73 | EF67: 84 | EG67: 83.63 | EH67: 82.46 | EI67: 85.85 | EJ67: 89.99 | EK67: 92.87 | EL67: 97.85 | EM67: 90.24 | EN67: 93.44 | EO67: 92.02 | EP67: 95.21 | EQ67: 86.42 | ER67: 83.1 | ES67: 81.96 | ET67: 84.23 | EU67: 83.35 | EV67: 95.6 | EW67: 89.24 | EX67: 99.92 | EY67: 81.5 | EZ67: 69.64 | FA67: 86.89 | FB67: 88.65 | FC67: 77.52 | FD67: 78.46 | FE67: 87.86 | FF67: 80.37 | FG67: 78.96 | FH67: 80.89 | FN67: 84.26 | FP67: 86.29 | FQ67: 71.14 | FR67: 71.14 | GH67: 90.08 | GI67: 90.08 | GL67: 84.43 | GO67: 100.01 | GP67: 66.21 | HB67: 94.08 | HC67: 91.32 | HD67: 92.26 | HE67: 95.91 | HU67: 104.56 | IK67: 79.71 | IL67: 76.53 | IM67: 77.38 | IQ67: 90.23
A68: 44713 | D68: 84.76 | E68: 84.6 | F68: 82.99 | G68: 88.09 | H68: 90.2 | I68: 92.32 | J68: 94.91 | K68: 88.66 | L68: 92.73 | M68: 91.09 | N68: 96.47 | O68: 88.4 | P68: 83.75 | Q68: 83.64 | R68: 84.02 | S68: 83.56 | T68: 98.62 | U68: 91.2 | V68: 104.85 | W68: 83.04 | X68: 72.72 | Y68: 89.01 | Z68: 90.17 | AA68: 79.51 | AB68: 80.34 | AC68: 87.14 | AD68: 87.11 | AE68: 78.78 | AF68: 89.37 | AL68: 85.52 | AN68: 84.46 | AO68: 73.14 | AP68: 73.14 | BF68: 87.84 | BG68: 87.84 | BJ68: 83.57 | BM68: 77.73 | BN68: 72.95 | BZ68: 93.83 | CA68: 90.79 | CB68: 91.54 | CC68: 96.07 | CS68: 111.35 | DI68: 89.64 | DJ68: 85.22 | DK68: 82.4 | DO68: 92.08 | DV68: 84.28 | DW68: 82.83 | EA68: 87.36 | EB68: 89.81 | EC68: 87.15 | EF68: 84.94 | EG68: 84.27 | EH68: 83.76 | EI68: 87.63 | EJ68: 89.96 | EK68: 92.96 | EL68: 97.33 | EM68: 88.79 | EN68: 93.27 | EO68: 91.4 | EP68: 96.63 | EQ68: 88.01 | ER68: 83.66 | ES68: 83.38 | ET68: 83.94 | EU68: 83.69 | EV68: 98.93 | EW68: 90.65 | EX68: 104.64 | EY68: 82.64 | EZ68: 73.43 | FA68: 88.62 | FB68: 89.53 | FC68: 79.18 | FD68: 79.85 | FE68: 87.3 | FF68: 80.54 | FG68: 78.67 | FH68: 81.22 | FN68: 84.49 | FP68: 85.49 | FQ68: 71.19 | FR68: 71.19 | GH68: 91.85 | GI68: 91.85 | GL68: 84.43 | GO68: 99.57 | GP68: 69.38 | HB68: 94.1 | HC68: 90.86 | HD68: 92.17 | HE68: 96.1 | HU68: 112.53 | IK68: 86.36 | IL68: 82.91 | IM68: 84.22 | IQ68: 91.93
A69: 44743 | D69: 85.72 | E69: 84.98 | F69: 83.97 | G69: 88.95 | H69: 93.13 | I69: 93.22 | J69: 95.63 | K69: 88.88 | L69: 92.26 | M69: 92.81 | N69: 96.78 | O69: 90.56 | P69: 87.06 | Q69: 88.77 | R69: 86.23 | S69: 85.81 | T69: 102.91 | U69: 98.94 | V69: 106.08 | W69: 84.54 | X69: 74.01 | Y69: 90.83 | Z69: 91.59 | AA69: 82.84 | AB69: 81.15 | AC69: 89.17 | AD69: 88.03 | AE69: 79.54 | AF69: 90.34 | AL69: 85.91 | AN69: 84.51 | AO69: 73.25 | AP69: 73.25 | BD69: 82.63 | BE69: 82.63 | BF69: 88.69 | BG69: 88.69 | BJ69: 83.57 | BM69: 92.38 | BN69: 81.87 | BZ69: 94.85 | CA69: 91.3 | CB69: 92.3 | CC69: 97.38 | CS69: 104.64 | CZ69: 80.95 | DI69: 91.17 | DJ69: 86.62 | DK69: 84.91 | DO69: 92.43 | DV69: 84.28 | DW69: 82.83 | EA69: 87.37 | EB69: 89.9 | EC69: 87.15 | EF69: 85.74 | EG69: 84.66 | EH69: 84.29 | EI69: 88.55 | EJ69: 92.92 | EK69: 93.82 | EL69: 97.77 | EM69: 89.02 | EN69: 93.27 | EO69: 92.79 | EP69: 97.16 | EQ69: 90.06 | ER69: 87.03 | ES69: 88.5 | ET69: 86.18 | EU69: 85.91 | EV69: 102.19 | EW69: 96.53 | EX69: 105.98 | EY69: 84.1 | EZ69: 74.2 | FA69: 90.32 | FB69: 91.04 | FC69: 82.44 | FD69: 80.63 | FE69: 89.31 | FF69: 81.21 | FG69: 79.46 | FH69: 81.85 | FN69: 84.63 | FP69: 85.41 | FQ69: 71.37 | FR69: 71.37 | GF69: 85.02 | GG69: 85.02 | GH69: 93.4 | GI69: 93.4 | GL69: 84.43 | GO69: 107.05 | GP69: 76.67 | HB69: 95.39 | HC69: 91.8 | HD69: 92.79 | HE69: 97.94 | HU69: 114.13 | IB69: 80.95 | IK69: 88.31 | IL69: 84.73 | IM69: 87.29 | IQ69: 92.26
A70: 44774 | D70: 86.8 | E70: 85.35 | F70: 85.27 | G70: 92.07 | H70: 94.24 | I70: 93.65 | J70: 95.88 | K70: 89.07 | L70: 91.33 | M70: 94.85 | N70: 97.5 | O70: 90.6 | P70: 89.1 | Q70: 92.52 | R70: 87.73 | S70: 86.36 | T70: 104.51 | U70: 100.79 | V70: 107.43 | W70: 85.85 | X70: 74.75 | Y70: 92.55 | Z70: 91.76 | AA70: 84.46 | AB70: 82.38 | AC70: 91.16 | AD70: 89.01 | AE70: 80.26 | AF70: 91.39 | AL70: 88.82 | AN70: 86.49 | AO70: 73.5 | AP70: 73.5 | BD70: 83.02 | BE70: 83.02 | BF70: 89.72 | BG70: 89.72 | BJ70: 83.57 | BM70: 93.08 | BN70: 81.87 | BZ70: 95.44 | CA70: 91.98 | CB70: 94.15 | CC70: 97.08 | CS70: 95.89 | CZ70: 81.15 | DI70: 86.7 | DJ70: 82.11 | DK70: 86.13 | DO70: 92.64 | DV70: 84.28 | DW70: 82.87 | EA70: 87.27 | EB70: 88.73 | EC70: 87.15 | EF70: 87.08 | EG70: 85.07 | EH70: 86.04 | EI70: 91.71 | EJ70: 94.3 | EK70: 94.28 | EL70: 97.78 | EM70: 89.35 | EN70: 92.47 | EO70: 95.15 | EP70: 97.63 | EQ70: 90.08 | ER70: 89.19 | ES70: 92.56 | ET70: 87.59 | EU70: 86.28 | EV70: 104.17 | EW70: 99.43 | EX70: 107.28 | EY70: 85.35 | EZ70: 74.8 | FA70: 92.02 | FB70: 91.31 | FC70: 84.26 | FD70: 81.8 | FE70: 91.17 | FF70: 82.64 | FG70: 80.3 | FH70: 83.49 | FN70: 88.71 | FP70: 86.94 | FQ70: 71.5 | FR70: 71.5 | GF70: 85.4 | GG70: 85.4 | GH70: 94.32 | GI70: 94.32 | GL70: 84.43 | GO70: 108.12 | GP70: 78.28 | HB70: 96.13 | HC70: 92.38 | HD70: 94.56 | HE70: 97.94 | HU70: 95.65 | IB70: 81.15 | IK70: 83.51 | IL70: 79.82 | IM70: 90.11 | IQ70: 92.62
A71: 44805 | D71: 88.61 | E71: 89.22 | F71: 86.33 | G71: 92.42 | H71: 93.17 | I71: 93.84 | J71: 95.99 | K71: 89.07 | L71: 90.24 | M71: 95.95 | N71: 97.64 | O71: 91.11 | P71: 90.3 | Q71: 92.88 | R71: 89.53 | S71: 87.96 | T71: 97.57 | U71: 93.31 | V71: 101 | W71: 86.23 | X71: 74.96 | Y71: 92.22 | Z71: 92 | AA71: 84.05 | AB71: 83.33 | AC71: 91.15 | AD71: 89.05 | AE71: 82.35 | AF71: 90.84 | AL71: 89.16 | AN71: 86.67 | AO71: 74.32 | AP71: 74.32 | BD71: 83.43 | BE71: 83.43 | BF71: 90.71 | BG71: 90.71 | BJ71: 85.84 | BM71: 92.4 | BN71: 82.63 | BZ71: 96.31 | CA71: 93.07 | CB71: 94.53 | CC71: 98.23 | CS71: 93.35 | CZ71: 81.84 | DI71: 90.17 | DJ71: 85.14 | DK71: 95.31 | DO71: 94.38 | DV71: 84.28 | DW71: 82.87 | EA71: 87.68 | EB71: 88.82 | EC71: 87.59 | EF71: 88.53 | EG71: 88.78 | EH71: 86.57 | EI71: 92.25 | EJ71: 92.98 | EK71: 94.44 | EL71: 97.75 | EM71: 89.63 | EN71: 90.91 | EO71: 96.15 | EP71: 97.52 | EQ71: 90.94 | ER71: 90.36 | ES71: 92.99 | ET71: 89.38 | EU71: 87.78 | EV71: 96.95 | EW71: 91.9 | EX71: 100.31 | EY71: 85.84 | EZ71: 75.08 | FA71: 91.68 | FB71: 91.87 | FC71: 83.65 | FD71: 82.97 | FE71: 91.11 | FF71: 82.88 | FG71: 82.01 | FH71: 83.21 | FN71: 88.84 | FP71: 86.92 | FQ71: 72.3 | FR71: 72.3 | GF71: 85.67 | GG71: 85.67 | GH71: 94.91 | GI71: 94.91 | GL71: 87.49 | GO71: 108.12 | GP71: 78.28 | HB71: 96.63 | HC71: 93.09 | HD71: 94.91 | HE71: 98.53 | HU71: 94.33 | IB71: 81.84 | IK71: 93.88 | IL71: 89.9 | IM71: 97.27 | IQ71: 94.13
A72: 44835 | D72: 88.91 | E72: 88.88 | F72: 87.61 | G72: 89.52 | H72: 93.92 | I72: 93.94 | J72: 95.85 | K72: 89.96 | L72: 89.22 | M72: 95.24 | N72: 97.26 | O72: 92.76 | P72: 90.95 | Q72: 92.17 | R72: 91.01 | S72: 89.41 | T72: 90.82 | U72: 89.88 | V72: 91.55 | W72: 87.05 | X72: 75.06 | Y72: 92.23 | Z72: 92.96 | AA72: 83.96 | AB72: 83.64 | AC72: 93.73 | AD72: 89.84 | AE72: 82.18 | AF72: 91.91 | AL72: 89.29 | AN72: 87.16 | AO72: 74.8 | AP72: 74.8 | BD72: 83.87 | BE72: 83.87 | BF72: 90.92 | BG72: 90.92 | BJ72: 85.84 | BM72: 93.29 | BN72: 82.85 | BZ72: 96.13 | CA72: 93.16 | CB72: 93.73 | CC72: 98.45 | CS72: 98.86 | CZ72: 81.82 | DI72: 83.51 | DJ72: 82.23 | DK72: 83.59 | DO72: 95.18 | DV72: 84.28 | DW72: 82.87 | EA72: 87.7 | EB72: 89 | EC72: 87.59 | EF72: 89.2 | EG72: 88.6 | EH72: 88.48 | EI72: 89.53 | EJ72: 93.82 | EK72: 94.48 | EL72: 97.58 | EM72: 90.41 | EN72: 89.74 | EO72: 95.4 | EP72: 97.72 | EQ72: 92.38 | ER72: 91.23 | ES72: 92.81 | ET72: 90.78 | EU72: 89.51 | EV72: 91.42 | EW72: 90.64 | EX72: 91.97 | EY72: 86.67 | EZ72: 75.3 | FA72: 91.71 | FB72: 92.74 | FC72: 83.62 | FD72: 83.42 | FE72: 93.71 | FF72: 83.33 | FG72: 82.04 | FH72: 83.81 | FN72: 88.75 | FP72: 87.73 | FQ72: 72.77 | FR72: 72.77 | GF72: 85.98 | GG72: 85.98 | GH72: 95.33 | GI72: 95.33 | GL72: 87.49 | GO72: 107.7 | GP72: 74.36 | HB72: 96.36 | HC72: 93.17 | HD72: 94.23 | HE72: 98.53 | HU72: 101.18 | IB72: 81.82 | IK72: 89.42 | IL72: 90.27 | IM72: 86.04 | IQ72: 95.37
A73: 44866 | D73: 89.79 | E73: 89.25 | F73: 88.09 | G73: 93.94 | H73: 95.67 | I73: 94.55 | J73: 95.72 | K73: 91.03 | L73: 89.19 | M73: 95.54 | N73: 98.82 | O73: 93.79 | P73: 92.55 | Q73: 94.03 | R73: 93.84 | S73: 89.48 | T73: 93.86 | U73: 95.64 | V73: 92.38 | W73: 87.39 | X73: 75.14 | Y73: 92.29 | Z73: 93.21 | AA73: 85.73 | AB73: 83.61 | AC73: 94.33 | AD73: 89.27 | AE73: 82.78 | AF73: 91.01 | AL73: 89.53 | AN73: 87.17 | AO73: 74.83 | AP73: 74.83 | BD73: 84.23 | BE73: 84.23 | BF73: 90.98 | BG73: 90.98 | BJ73: 85.84 | BM73: 93.72 | BN73: 82.53 | BZ73: 98.37 | CA73: 98.79 | CB73: 94.65 | CC73: 100.92 | CS73: 105.97 | CZ73: 81.73 | DI73: 90.54 | DJ73: 93.11 | DK73: 85.17 | DO73: 97.77 | DV73: 84.28 | DW73: 82.87 | EA73: 87.8 | EB73: 90.24 | EC73: 87.59 | EF73: 89.82 | EG73: 88.81 | EH73: 88.47 | EI73: 93.83 | EJ73: 95.51 | EK73: 95.14 | EL73: 97.68 | EM73: 91.81 | EN73: 90.53 | EO73: 95.7 | EP73: 98.66 | EQ73: 93.28 | ER73: 92.7 | ES73: 94.33 | ET73: 93.5 | EU73: 89.61 | EV73: 93.41 | EW73: 94.33 | EX73: 92.84 | EY73: 87.1 | EZ73: 75.53 | FA73: 92.01 | FB73: 92.8 | FC73: 85.75 | FD73: 83.35 | FE73: 94.61 | FF73: 83.12 | FG73: 82.77 | FH73: 83.26 | FN73: 90.48 | FP73: 87.7 | FQ73: 72.79 | FR73: 72.79 | GF73: 85.95 | GG73: 85.95 | GH73: 94.81 | GI73: 94.81 | GL73: 87.49 | GO73: 107.7 | GP73: 77.79 | HB73: 98.29 | HC73: 98.98 | HD73: 94.83 | HE73: 100.84 | HU73: 107.7 | IB73: 81.73 | IK73: 91.84 | IL73: 92.17 | IM73: 89.14 | IQ73: 97.86
A74: 44896 | D74: 91.33 | E74: 90.21 | F74: 89.73 | G74: 97.76 | H74: 97.2 | I74: 94.98 | J74: 95.9 | K74: 92.26 | L74: 87.66 | M74: 95.99 | N74: 99.79 | O74: 94.83 | P74: 94.44 | Q74: 95.8 | R74: 95.63 | S74: 91.63 | T74: 96.83 | U74: 98.35 | V74: 95.57 | W74: 88.68 | X74: 75.25 | Y74: 93.47 | Z74: 92.12 | AA74: 86.83 | AB74: 85.47 | AC74: 96.41 | AD74: 88.49 | AE74: 83.46 | AF74: 89.82 | AL74: 89.61 | AN74: 87.26 | AO74: 74.82 | AP74: 74.82 | BD74: 84.67 | BE74: 84.67 | BF74: 91.8 | BG74: 91.8 | BJ74: 85.84 | BM74: 93.72 | BN74: 85.4 | BZ74: 99.2 | CA74: 99.63 | CB74: 97.05 | CC74: 100.64 | CS74: 97.39 | CZ74: 81.41 | DI74: 115.21 | DJ74: 111.54 | DK74: 117.94 | DO74: 99.33 | DV74: 84.28 | DW74: 82.87 | EA74: 89.81 | EB74: 89.12 | EC74: 89.87 | EF74: 91.22 | EG74: 89.87 | EH74: 89.78 | EI74: 97.52 | EJ74: 96.8 | EK74: 95.83 | EL74: 97.88 | EM74: 92.81 | EN74: 90.68 | EO74: 96.24 | EP74: 100.21 | EQ74: 94.19 | ER74: 94.53 | ES74: 95.82 | ET74: 95.18 | EU74: 92.07 | EV74: 96.01 | EW74: 97.66 | EX74: 94.97 | EY74: 88.42 | EZ74: 75.53 | FA74: 93.11 | FB74: 92.08 | FC74: 86.66 | FD74: 85.43 | FE74: 96.51 | FF74: 82.55 | FG74: 83.67 | FH74: 82.16 | FN74: 88.76 | FP74: 87.28 | FQ74: 72.76 | FR74: 72.76 | GF74: 86.29 | GG74: 86.29 | GH74: 95.86 | GI74: 95.86 | GL74: 87.49 | GO74: 107.55 | GP74: 81.72 | HB74: 99.4 | HC74: 99.59 | HD74: 97.59 | HE74: 100.74 | HU74: 97.81 | IB74: 81.41 | IK74: 117.08 | IL74: 110.43 | IM74: 123.69 | IQ74: 99.3
A75: 44927 | D75: 91.27 | E75: 91.21 | F75: 89.43 | G75: 95.32 | H75: 96.22 | I75: 95.31 | J75: 95.69 | K75: 92.2 | L75: 90.67 | M75: 96.1 | N75: 99.9 | O75: 94.53 | P75: 93.87 | Q75: 94.62 | R75: 95.98 | S75: 90.89 | T75: 93.3 | U75: 92.81 | V75: 93.67 | W75: 89.71 | X75: 75.41 | Y75: 93.02 | Z75: 94.16 | AA75: 87.32 | AB75: 87.15 | AC75: 96.53 | AD75: 91.06 | AE75: 84.63 | AF75: 92.78 | AL75: 89.56 | AN75: 87.35 | AO75: 74.9 | AP75: 74.9 | BD75: 85.19 | BE75: 85.19 | BF75: 93.87 | BG75: 93.87 | BJ75: 85.84 | BM75: 93.54 | BN75: 85.4 | BZ75: 98.51 | CA75: 97.76 | CB75: 95.87 | CC75: 100.54 | CS75: 97.13 | CZ75: 81.82 | DI75: 109.41 | DJ75: 115.92 | DK75: 98.21 | DO75: 99.84 | DV75: 84.28 | DW75: 82.87 | EA75: 89.82 | EB75: 89.24 | EC75: 89.87 | EF75: 91.37 | EG75: 90.99 | EH75: 89.9 | EI75: 94.93 | EJ75: 95.98 | EK75: 95.88 | EL75: 97.47 | EM75: 92.84 | EN75: 91.08 | EO75: 96.19 | EP75: 100.3 | EQ75: 94.6 | ER75: 94.03 | ES75: 94.83 | ET75: 95.59 | EU75: 91.28 | EV75: 93.53 | EW75: 93.5 | EX75: 93.6 | EY75: 89.3 | EZ75: 75.62 | FA75: 92.79 | FB75: 93.97 | FC75: 87.38 | FD75: 86.66 | FE75: 96.58 | FF75: 84.86 | FG75: 84.72 | FH75: 84.92 | FN75: 89.55 | FP75: 88.14 | FQ75: 72.88 | FR75: 72.88 | GF75: 86.73 | GG75: 86.73 | GH75: 94.69 | GI75: 94.69 | GL75: 87.49 | GO75: 107.55 | GP75: 93.55 | HB75: 98.62 | HC75: 98.2 | HD75: 96.26 | HE75: 100.49 | HU75: 100.03 | IB75: 81.82 | IK75: 109.56 | IL75: 113.47 | IM75: 101.33 | IQ75: 99.81
A76: 44958 | D76: 91.23 | E76: 91.08 | F76: 89.91 | G76: 90.43 | H76: 97.65 | I76: 95.36 | J76: 95.34 | K76: 93.09 | L76: 90.32 | M76: 96.12 | N76: 100.12 | O76: 94.65 | P76: 93.71 | Q76: 94.86 | R76: 96.3 | S76: 89.78 | T76: 96.76 | U76: 99.6 | V76: 94.42 | W76: 90.59 | X76: 77.82 | Y76: 92.41 | Z76: 96.39 | AA76: 88.32 | AB76: 87.63 | AC76: 97.24 | AD76: 92.28 | AE76: 85.46 | AF76: 94.11 | AL76: 92.23 | AN76: 89.02 | AO76: 75.03 | AP76: 75.03 | BD76: 85.78 | BE76: 85.78 | BF76: 93.97 | BG76: 93.97 | BJ76: 85.84 | BM76: 93.54 | BN76: 88.12 | BZ76: 99.91 | CA76: 98.4 | CB76: 97.57 | CC76: 101.88 | CS76: 104.25 | CZ76: 81.4 | DI76: 92.09 | DJ76: 98.53 | DK76: 81.33 | DO76: 99.25 | DV76: 87.96 | DW76: 89.61 | EA76: 89.82 | EB76: 89.35 | EC76: 89.87 | EF76: 91.28 | EG76: 90.91 | EH76: 90.24 | EI76: 90.51 | EJ76: 97.03 | EK76: 96.14 | EL76: 97.48 | EM76: 93.61 | EN76: 91.97 | EO76: 96.51 | EP76: 100.59 | EQ76: 94.29 | ER76: 93.81 | ES76: 94.92 | ET76: 96.02 | EU76: 89.94 | EV76: 96.49 | EW76: 97.59 | EX76: 95.81 | EY76: 90.34 | EZ76: 77.99 | FA76: 92.47 | FB76: 96.15 | FC76: 88.21 | FD76: 87.55 | FE76: 97.2 | FF76: 85.93 | FG76: 85.34 | FH76: 86.15 | FN76: 92.38 | FP76: 89.73 | FQ76: 73.01 | FR76: 73.01 | GF76: 87.3 | GG76: 87.3 | GH76: 94.77 | GI76: 94.77 | GL76: 87.49 | GO76: 107.55 | GP76: 93.58 | HB76: 100.01 | HC76: 98.46 | HD76: 97.98 | HE76: 101.81 | HU76: 103.94 | IB76: 81.4 | IK76: 92.03 | IL76: 95.21 | IM76: 85.26 | IQ76: 99.27
A77: 44986 | D77: 91.42 | E77: 90.91 | F77: 89.54 | G77: 94.56 | H77: 98.45 | I77: 95.25 | J77: 95.03 | K77: 93.31 | L77: 89.29 | M77: 97.06 | N77: 100.42 | O77: 93.9 | P77: 95.59 | Q77: 96.3 | R77: 97.23 | S77: 93.12 | T77: 97.55 | U77: 99.69 | V77: 95.78 | W77: 91.2 | X77: 78.21 | Y77: 93.94 | Z77: 95.87 | AA77: 88.69 | AB77: 88.69 | AC77: 97.58 | AD77: 92.95 | AE77: 84.25 | AF77: 95.3 | AL77: 93.04 | AN77: 89.7 | AO77: 75.57 | AP77: 75.57 | BD77: 86.21 | BE77: 86.21 | BF77: 93.87 | BG77: 93.87 | BJ77: 85.84 | BM77: 93.54 | BN77: 88.12 | BZ77: 100.28 | CA77: 98.92 | CB77: 97.92 | CC77: 102.23 | CS77: 100.77 | CZ77: 85.88 | DI77: 93.78 | DJ77: 98.96 | DK77: 84.74 | DO77: 100.18 | DV77: 87.96 | DW77: 89.61 | EA77: 91.11 | EB77: 90.73 | EC77: 91.15 | EF77: 91.63 | EG77: 90.83 | EH77: 89.99 | EI77: 94.67 | EJ77: 98.39 | EK77: 95.86 | EL77: 97.03 | EM77: 93.59 | EN77: 90.82 | EO77: 97.25 | EP77: 100.56 | EQ77: 93.37 | ER77: 95.52 | ES77: 96.06 | ET77: 97.03 | EU77: 93.16 | EV77: 97.16 | EW77: 97.56 | EX77: 96.95 | EY77: 90.81 | EZ77: 78.38 | FA77: 93.95 | FB77: 95.66 | FC77: 88.74 | FD77: 88.25 | FE77: 97.54 | FF77: 86.59 | FG77: 84.31 | FH77: 87.43 | FN77: 93.88 | FP77: 89.8 | FQ77: 73.64 | FR77: 73.64 | GF77: 87.46 | GG77: 87.46 | GH77: 95.12 | GI77: 95.12 | GL77: 87.49 | GO77: 106.9 | GP77: 94.11 | HB77: 100.31 | HC77: 98.98 | HD77: 98.21 | HE77: 102.14 | HU77: 100.15 | IB77: 85.88 | IK77: 93.79 | IL77: 97.85 | IM77: 85.73 | IQ77: 100.14
A78: 45017 | D78: 93.11 | E78: 93.68 | F78: 91.47 | G78: 91.92 | H78: 98.65 | I78: 95.64 | J78: 94.79 | K78: 92.48 | L78: 91.16 | M78: 98.37 | N78: 99.7 | O78: 94.82 | P78: 95.78 | Q78: 95.13 | R78: 97.06 | S78: 95.28 | T78: 96.97 | U78: 95.89 | V78: 97.81 | W78: 91.51 | X78: 78.13 | Y78: 92.68 | Z78: 96.49 | AA78: 89.08 | AB78: 88.66 | AC78: 98.87 | AD78: 95.03 | AE78: 84.98 | AF78: 97.76 | AL78: 93.77 | AN78: 90.04 | AO78: 76.11 | AP78: 76.11 | BD78: 86.97 | BE78: 86.97 | BF78: 94.23 | BG78: 94.23 | BJ78: 85.84 | BM78: 92.6 | BN78: 88.12 | BZ78: 100.31 | CA78: 98.9 | CB78: 97.92 | CC78: 102.3 | CS78: 103.29 | CZ78: 85.15 | DI78: 100.9 | DJ78: 107.24 | DK78: 90.12 | DO78: 99.09 | DV78: 87.96 | DW78: 89.61 | EA78: 91.12 | EB78: 90.84 | EC78: 91.15 | EF78: 93.2 | EG78: 93.54 | EH78: 91.75 | EI78: 92.03 | EJ78: 98.66 | EK78: 96.2 | EL78: 96.67 | EM78: 93.01 | EN78: 91.37 | EO78: 97.75 | EP78: 101.26 | EQ78: 94.51 | ER78: 95.77 | ES78: 95.26 | ET78: 96.7 | EU78: 95.44 | EV78: 96.79 | EW78: 94.2 | EX78: 98.54 | EY78: 91.17 | EZ78: 78.45 | FA78: 92.7 | FB78: 96.13 | FC78: 89 | FD78: 88.46 | FE78: 98.76 | FF78: 88.14 | FG78: 84.79 | FH78: 89.35 | FN78: 93.94 | FP78: 90.56 | FQ78: 74.14 | FR78: 74.14 | GF78: 88.02 | GG78: 88.02 | GH78: 95.65 | GI78: 95.65 | GL78: 87.49 | GO78: 104.41 | GP78: 94.11 | HB78: 100.1 | HC78: 98.79 | HD78: 98.12 | HE78: 101.82 | HU78: 103.99 | IB78: 85.15 | IK78: 99.46 | IL78: 101.46 | IM78: 94.2 | IQ78: 99.39
A79: 45047 | D79: 94.73 | E79: 97.37 | F79: 91.47 | G79: 95.64 | H79: 98.28 | I79: 96.04 | J79: 94.19 | K79: 92.54 | L79: 91.34 | M79: 99.31 | N79: 100.51 | O79: 95.89 | P79: 95.59 | Q79: 94.99 | R79: 97.2 | S79: 94.71 | T79: 97.96 | U79: 95.43 | V79: 99.99 | W79: 91.3 | X79: 78.65 | Y79: 92.61 | Z79: 96.6 | AA79: 89.06 | AB79: 88.41 | AC79: 98.18 | AD79: 94.51 | AE79: 84.14 | AF79: 97.33 | AL79: 93.34 | AN79: 90.29 | AO79: 75.89 | AP79: 75.89 | BD79: 87.87 | BE79: 87.87 | BF79: 94.92 | BG79: 94.92 | BJ79: 85.84 | BM79: 91.61 | BN79: 88.12 | BZ79: 100.69 | CA79: 99.54 | CB79: 98.08 | CC79: 102.78 | CS79: 93.85 | CZ79: 86.33 | DI79: 88.29 | DJ79: 88.11 | DK79: 86.77 | DO79: 98.76 | DV79: 87.96 | DW79: 89.61 | EA79: 91.13 | EB79: 90.94 | EC79: 91.15 | EF79: 94.74 | EG79: 96.81 | EH79: 92.05 | EI79: 95.47 | EJ79: 98.41 | EK79: 96.74 | EL79: 95.96 | EM79: 93.18 | EN79: 91.73 | EO79: 99.48 | EP79: 101.37 | EQ79: 95.93 | ER79: 95.58 | ES79: 94.87 | ET79: 96.99 | EU79: 95.03 | EV79: 98.44 | EW79: 95.33 | EX79: 100.53 | EY79: 90.87 | EZ79: 79.09 | FA79: 93 | FB79: 96.18 | FC79: 89.36 | FD79: 87.97 | FE79: 97.73 | FF79: 88.25 | FG79: 83.9 | FH79: 89.83 | FN79: 93.77 | FP79: 91.19 | FQ79: 74.05 | FR79: 74.05 | GF79: 88.65 | GG79: 88.65 | GH79: 96.2 | GI79: 96.2 | GL79: 87.49 | GO79: 102.83 | GP79: 90.58 | HB79: 100.64 | HC79: 99.4 | HD79: 98.52 | HE79: 102.47 | HU79: 96.97 | IB79: 86.33 | IK79: 88.13 | IL79: 86.25 | IM79: 88.66 | IQ79: 98.56
A80: 45078 | D80: 94.31 | E80: 97.42 | F80: 90.64 | G80: 95.14 | H80: 97.92 | I80: 94.99 | J80: 92.93 | K80: 91.84 | L80: 89.41 | M80: 98.31 | N80: 100.08 | O80: 94.86 | P80: 96.22 | Q80: 95.25 | R80: 98.35 | S80: 95.29 | T80: 99.32 | U80: 101.38 | V80: 97.63 | W80: 91.72 | X80: 79.76 | Y80: 93.77 | Z80: 96.53 | AA80: 89.15 | AB80: 89.06 | AC80: 98.19 | AD80: 92.74 | AE80: 83.99 | AF80: 95.1 | AL80: 93.81 | AN80: 90.53 | AO80: 75.72 | AP80: 75.72 | BD80: 88.78 | BE80: 88.78 | BF80: 95.19 | BG80: 95.19 | BJ80: 85.84 | BM80: 92.51 | BN80: 88.12 | BZ80: 100.37 | CA80: 99.04 | CB80: 98.02 | CC80: 102.31 | CS80: 99.61 | CZ80: 86.04 | DI80: 98.14 | DJ80: 94.73 | DK80: 100.88 | DO80: 102.04 | DV80: 87.96 | DW80: 89.61 | EA80: 93.58 | EB80: 91.31 | EC80: 93.79 | EF80: 94.16 | EG80: 96.9 | EH80: 90.92 | EI80: 95.06 | EJ80: 97.69 | EK80: 95.71 | EL80: 94.93 | EM80: 92.29 | EN80: 90.32 | EO80: 98.8 | EP80: 100.31 | EQ80: 94.78 | ER80: 96.29 | ES80: 95.27 | ET80: 98.31 | EU80: 95.51 | EV80: 98.87 | EW80: 100.14 | EX80: 98.09 | EY80: 91.17 | EZ80: 79.85 | FA80: 93.97 | FB80: 96.29 | FC80: 88.94 | FD80: 88.46 | FE80: 97.86 | FF80: 86.51 | FG80: 83.55 | FH80: 87.58 | FN80: 93.24 | FP80: 90.56 | FQ80: 73.9 | FR80: 73.9 | GF80: 89.33 | GG80: 89.33 | GH80: 96.34 | GI80: 96.34 | GL80: 87.49 | GO80: 98.31 | GP80: 89.47 | HB80: 100.31 | HC80: 98.97 | HD80: 98.48 | HE80: 101.94 | HU80: 101.88 | IB80: 86.04 | IK80: 98.71 | IL80: 92.4 | IM80: 105.28 | IQ80: 101.92
... A89: 45352 | D89: 98.3 | E89: 98.73 | F89: 97.13 | G89: 99.26 | H89: 100.58 | I89: 94.64 | J89: 89.26 | K89: 96.73 | L89: 79.48 | M89: 99.01 | N89: 101.42 | O89: 98.86 | P89: 98.36 | Q89: 98.08 | R89: 100.49 | S89: 96.55 | T89: 96.21 | U89: 92.1 | V89: 99.52 | W89: 94.6 | X89: 83.62 | Y89: 97.08 | Z89: 98.24 | AA89: 94.83 | AB89: 92.14 | AC89: 99.67 | AD89: 96.38 | AE89: 87.09 | AF89: 98.89 | AL89: 96.79 | AN89: 95.35 | AO89: 84.63 | AP89: 84.63 | BD89: 93.81 | BE89: 93.81 | BF89: 97.5 | BG89: 97.5 | BJ89: 89.65 | BM89: 99.16 | BN89: 87.59 | BZ89: 100.44 | CA89: 100.76 | CB89: 99.49 | CC89: 101.03 | CS89: 109.4 | CZ89: 96.21 | DI89: 89.72 | DJ89: 95.66 | DK89: 82.56 | DO89: 102.01 | DV89: 93.97 | DW89: 96.16 | EA89: 95.81 | EB89: 96.22 | EC89: 95.78 | EF89: 98.27 | EG89: 98.43 | EH89: 97.43 | EI89: 98.93 | EJ89: 100.44 | EK89: 95.14 | EL89: 92.14 | EM89: 97.35 | EN89: 78.78 | EO89: 99.04 | EP89: 102.01 | EQ89: 98.68 | ER89: 98.6 | ES89: 98.45 | ET89: 100.58 | EU89: 96.67 | EV89: 95.85 | EW89: 90.34 | EX89: 99.53 | EY89: 94.43 | EZ89: 83.88 | FA89: 97.04 | FB89: 98.25 | FC89: 94.53 | FD89: 92.03 | FE89: 99.7 | FF89: 95.45 | FG89: 86.94 | FH89: 98.56 | FN89: 97.32 | FP89: 95.67 | FQ89: 82.34 | FR89: 82.34 | GF89: 93.4 | GG89: 93.4 | GH89: 99.3 | GI89: 99.3 | GL89: 90.08 | GO89: 115.82 | GP89: 87.15 | HB89: 100.79 | HC89: 100.72 | HD89: 99.84 | HE89: 101.53 | HU89: 108.6 | IB89: 96.21 | IK89: 89.59 | IL89: 94.51 | IM89: 82.84 | IQ89: 101.77
A90: 45383 | B90: 96.69 | C90: 96.23 | D90: 97.73 | E90: 98.95 | F90: 95.96 | G90: 99.2 | H90: 99.41 | I90: 95.68 | J90: 91.98 | K90: 97.28 | L90: 79.91 | M90: 99.31 | N90: 100.65 | O90: 101.07 | P90: 98.36 | Q90: 97.56 | R90: 100.56 | S90: 97.11 | T90: 99.68 | U90: 98.03 | V90: 100.96 | W90: 95.24 | X90: 83.65 | Y90: 96.15 | Z90: 98.85 | AA90: 99.34 | AB90: 93.16 | AC90: 98.33 | AD90: 95.83 | AE90: 85.48 | AF90: 98.65 | AG90: 95.27 | AH90: 95.93 | AI90: 94.33 | AJ90: 93.63 | AK90: 97.08 | AL90: 95.45 | AM90: 99.59 | AN90: 95.43 | AO90: 85.61 | AP90: 85.61 | AQ90: 99.06 | AR90: 103.07 | AS90: 107.31 | AT90: 102.29 | AU90: 99.89 | AV90: 101.93 | AW90: 103.58 | AX90: 101.53 | AY90: 102.17 | AZ90: 89.24 | BA90: 88.85 | BB90: 93.39 | BC90: 95.86 | BD90: 94.38 | BE90: 94.38 | BF90: 97.94 | BG90: 97.94 | BH90: 93.94 | BI90: 96.25 | BJ90: 89.65 | BK90: 96.26 | BL90: 100.1 | BM90: 97.31 | BN90: 87.59 | BO90: 97.32 | BP90: 98.41 | BQ90: 98.8 | BR90: 96.89 | BS90: 101.97 | BT90: 101.97 | BU90: 102.07 | BV90: 101.48 | BW90: 103.66 | BX90: 101.3 | BY90: 102.45 | BZ90: 100.55 | CA90: 99.81 | CB90: 98.82 | CC90: 101.93 | CD90: 92.19 | CE90: 84.36 | CF90: 96.17 | CG90: 98.77 | CH90: 95.81 | CI90: 101.86 | CJ90: 102.66 | CK90: 96.27 | CL90: 94.79 | CM90: 94.62 | CN90: 96.31 | CO90: 102.63 | CP90: 103.01 | CQ90: 101.81 | CR90: 98.73 | CS90: 113.66 | CT90: 95.58 | CU90: 94.21 | CV90: 94.59 | CW90: 94.59 | CX90: 98.52 | CY90: 98.52 | CZ90: 96.77 | DA90: 98.61 | DB90: 95.87 | DC90: 94.28 | DD90: 101.56 | DE90: 86.39 | DF90: 95.41 | DG90: 99.89 | DH90: 93.88 | DI90: 96.36 | DJ90: 97.87 | DK90: 94.04 | DL90: 95.52 | DM90: 98.09 | DN90: 95.41 | DO90: 100.79 | DP90: 92.56 | DQ90: 92.41 | DR90: 97.15 | DS90: 94.3 | DT90: 94.3 | DU90: 92.07 | DV90: 93.97 | DW90: 96.16 | DX90: 95.52 | DY90: 94.27 | DZ90: 94.27 | EA90: 95.84 | EB90: 96.53 | EC90: 95.78 | ED90: 96.51 | EE90: 96.22 | EF90: 97.61 | EG90: 98.6 | EH90: 96.12 | EI90: 98.66 | EJ90: 99.38 | EK90: 95.78 | EL90: 92.24 | EM90: 97.37 | EN90: 80.33 | EO90: 99.49 | EP90: 101.11 | EQ90: 101.13 | ER90: 98.54 | ES90: 98 | ET90: 100.48 | EU90: 97.17 | EV90: 99.36 | EW90: 96.48 | EX90: 101.27 | EY90: 95.13 | EZ90: 83.83 | FA90: 95.97 | FB90: 98.58 | FC90: 99.19 | FD90: 92.97 | FE90: 98.4 | FF90: 94.86 | FG90: 85.43 | FH90: 98.32 | FI90: 95.4 | FJ90: 95.36 | FK90: 95.46 | FL90: 91.64 | FM90: 95.63 | FN90: 95.17 | FO90: 96.32 | FP90: 95.32 | FQ90: 83.69 | FR90: 83.69 | FS90: 97.29 | FT90: 101.35 | FU90: 105.48 | FV90: 99.99 | FW90: 98.14 | FX90: 98.26 | FY90: 103.91 | FZ90: 93.72 | GA90: 104.82 | GB90: 87.22 | GC90: 86.28 | GD90: 97.33 | GE90: 96.37 | GF90: 93.9 | GG90: 93.9 | GH90: 98.78 | GI90: 98.78 | GJ90: 93.56 | GK90: 96.5 | GL90: 90.08 | GM90: 97.66 | GN90: 94.03 | GO90: 112.06 | GP90: 86.16 | GQ90: 97.97 | GR90: 98.4 | GS90: 97.99 | GT90: 100.5 | GU90: 100.45 | GV90: 100.45 | GW90: 99.83 | GX90: 100.93 | GY90: 100.64 | GZ90: 99.4 | HA90: 98.44 | HB90: 100.55 | HC90: 99.61 | HD90: 98.56 | HE90: 102.23 | HF90: 94.05 | HG90: 85.78 | HH90: 95.61 | HI90: 99.31 | HJ90: 96.71 | HK90: 101.26 | HL90: 102.1 | HM90: 96.56 | HN90: 95.73 | HO90: 95.72 | HP90: 96.03 | HQ90: 102 | HR90: 102.19 | HS90: 100.96 | HT90: 101.79 | HU90: 110.61 | HV90: 95.88 | HW90: 95.37 | HX90: 96.33 | HY90: 96.33 | HZ90: 98.54 | IA90: 98.54 | IB90: 96.77 | IC90: 98.61 | ID90: 95.05 | IE90: 95.98 | IF90: 105.41 | IG90: 86.35 | IH90: 97.09 | II90: 102.87 | IJ90: 94.66 | IK90: 92.1 | IL90: 93.31 | IM90: 89.85 | IN90: 98.75 | IO90: 96.64 | IP90: 98.91 | IQ90: 100.65
A91: 45413 | B91: 96.09 | C91: 96.61 | D91: 97.84 | E91: 98.74 | F91: 96.24 | G91: 98.45 | H91: 100.4 | I91: 96.06 | J91: 92.61 | K91: 97.4 | L91: 81.25 | M91: 100 | N91: 100.29 | O91: 101.03 | P91: 97.88 | Q91: 97.05 | R91: 100.12 | S91: 96.63 | T91: 101.95 | U91: 101.01 | V91: 102.63 | W91: 94.98 | X91: 83.99 | Y91: 95.95 | Z91: 98.21 | AA91: 100.06 | AB91: 92.46 | AC91: 98.46 | AD91: 96.7 | AE91: 85.33 | AF91: 99.79 | AG91: 95.41 | AH91: 96.04 | AI91: 94.52 | AJ91: 93.4 | AK91: 96.61 | AL91: 97.6 | AM91: 97.68 | AN91: 95.25 | AO91: 85.87 | AP91: 85.87 | AQ91: 95.57 | AR91: 97.92 | AS91: 102.5 | AT91: 96.63 | AU91: 96.2 | AV91: 94.46 | AW91: 100.74 | AX91: 92.37 | AY91: 96.06 | AZ91: 91.18 | BA91: 90.92 | BB91: 93.86 | BC91: 96.11 | BD91: 95.12 | BE91: 95.12 | BF91: 97.99 | BG91: 97.99 | BH91: 94.26 | BI91: 96.75 | BJ91: 89.65 | BK91: 95.94 | BL91: 100.1 | BM91: 96.86 | BN91: 87.59 | BO91: 96.94 | BP91: 97.54 | BQ91: 98.09 | BR91: 95.43 | BS91: 100.51 | BT91: 100.51 | BU91: 101.57 | BV91: 100.29 | BW91: 104.56 | BX91: 100.25 | BY91: 102.35 | BZ91: 100.28 | CA91: 99.26 | CB91: 98.92 | CC91: 101.45 | CD91: 92.16 | CE91: 84.24 | CF91: 96.98 | CG91: 97.24 | CH91: 96.07 | CI91: 102.43 | CJ91: 103.2 | CK91: 97.02 | CL91: 95.01 | CM91: 94.86 | CN91: 96.31 | CO91: 99.46 | CP91: 99.69 | CQ91: 100.28 | CR91: 98.35 | CS91: 103.92 | CT91: 96.1 | CU91: 94.21 | CV91: 94.56 | CW91: 94.56 | CX91: 97.86 | CY91: 97.86 | CZ91: 94.61 | DA91: 98.06 | DB91: 93.85 | DC91: 95.35 | DD91: 101.42 | DE91: 88.81 | DF91: 95.32 | DG91: 99.89 | DH91: 93.76 | DI91: 91.98 | DJ91: 90 | DK91: 93.56 | DL91: 95.72 | DM91: 97.72 | DN91: 97.43 | DO91: 100.22 | DP91: 92.7 | DQ91: 92.43 | DR91: 96.87 | DS91: 94.34 | DT91: 94.34 | DU91: 92.24 | DV91: 93.97 | DW91: 96.16 | DX91: 95.71 | DY91: 95.17 | DZ91: 95.17 | EA91: 95.84 | EB91: 96.59 | EC91: 95.78 | ED91: 96.51 | EE91: 96.73 | EF91: 97.87 | EG91: 98.49 | EH91: 96.63 | EI91: 98.4 | EJ91: 100.15 | EK91: 95.85 | EL91: 92.23 | EM91: 97.3 | EN91: 80.98 | EO91: 100.03 | EP91: 100.92 | EQ91: 100.62 | ER91: 98.22 | ES91: 97.66 | ET91: 100.25 | EU91: 96.76 | EV91: 102.17 | EW91: 98.99 | EX91: 104.29 | EY91: 94.84 | EZ91: 84.22 | FA91: 95.87 | FB91: 97.97 | FC91: 99.97 | FD91: 92.35 | FE91: 98.15 | FF91: 95.74 | FG91: 85.28 | FH91: 99.59 | FI91: 95.77 | FJ91: 95.81 | FK91: 95.72 | FL91: 92.09 | FM91: 96.23 | FN91: 96.39 | FO91: 96.74 | FP91: 95.74 | FQ91: 83.88 | FR91: 83.88 | FS91: 95.34 | FT91: 97.97 | FU91: 101.11 | FV91: 96.35 | FW91: 97.29 | FX91: 95.3 | FY91: 98.77 | FZ91: 91.81 | GA91: 102.76 | GB91: 89.24 | GC91: 88.5 | GD91: 96.93 | GE91: 97.12 | GF91: 94.56 | GG91: 94.56 | GH91: 99.6 | GI91: 99.6 | GJ91: 93.89 | GK91: 97.1 | GL91: 90.08 | GM91: 98.74 | GN91: 94.03 | GO91: 119.37 | GP91: 82.14 | GQ91: 98.13 | GR91: 99.87 | GS91: 99.78 | GT91: 100.36 | GU91: 98.91 | GV91: 98.91 | GW91: 99.92 | GX91: 101.01 | GY91: 103.39 | GZ91: 97.54 | HA91: 97.95 | HB91: 100.35 | HC91: 98.69 | HD91: 99.05 | HE91: 101.61 | HF91: 94.09 | HG91: 85.62 | HH91: 95.8 | HI91: 99.31 | HJ91: 96.58 | HK91: 100.86 | HL91: 101.59 | HM91: 96.71 | HN91: 95.66 | HO91: 95.62 | HP91: 96.16 | HQ91: 100.88 | HR91: 101.03 | HS91: 101.85 | HT91: 100.47 | HU91: 106.08 | HV91: 96.08 | HW91: 95.37 | HX91: 96.33 | HY91: 96.33 | HZ91: 97.89 | IA91: 97.89 | IB91: 94.61 | IC91: 98.06 | ID91: 94.35 | IE91: 97.83 | IF91: 106.54 | IG91: 88.97 | IH91: 96.73 | II91: 102.87 | IJ91: 94.15 | IK91: 89.97 | IL91: 86.51 | IM91: 93.43 | IN91: 98.94 | IO91: 99.29 | IP91: 97.87 | IQ91: 99.92
A92: 45444 | B92: 96.73 | C92: 96.8 | D92: 97.32 | E92: 98.84 | F92: 95.45 | G92: 97.2 | H92: 99.33 | I92: 95.4 | J92: 91.82 | K92: 95.97 | L92: 82.08 | M92: 99.11 | N92: 99.94 | O92: 99.97 | P92: 97.98 | Q92: 97.51 | R92: 99.75 | S92: 96.77 | T92: 102.65 | U92: 104.89 | V92: 100.73 | W92: 95.02 | X92: 84.22 | Y92: 96.62 | Z92: 98.4 | AA92: 100.93 | AB92: 92.25 | AC92: 98.34 | AD92: 96.89 | AE92: 84.64 | AF92: 100.23 | AG92: 95.86 | AH92: 96.04 | AI92: 95.6 | AJ92: 94.13 | AK92: 97.62 | AL92: 97.04 | AM92: 100.11 | AN92: 95.57 | AO92: 86.03 | AP92: 86.03 | AQ92: 94.15 | AR92: 96.84 | AS92: 100.06 | AT92: 95.63 | AU92: 96.77 | AV92: 98.59 | AW92: 101.62 | AX92: 97.18 | AY92: 101.36 | AZ92: 86.39 | BA92: 85.73 | BB92: 93.86 | BC92: 96.46 | BD92: 95.68 | BE92: 95.68 | BF92: 98.39 | BG92: 98.39 | BH92: 94.32 | BI92: 96.84 | BJ92: 89.65 | BK92: 96.09 | BL92: 100.1 | BM92: 97.07 | BN92: 87.59 | BO92: 96 | BP92: 96.03 | BQ92: 95.68 | BR92: 97.32 | BS92: 94.5 | BT92: 94.5 | BU92: 99.5 | BV92: 99.4 | BW92: 101.01 | BX92: 95.35 | BY92: 102.48 | BZ92: 100.11 | CA92: 98.98 | CB92: 98.86 | CC92: 101.22 | CD92: 92.15 | CE92: 84.94 | CF92: 96.45 | CG92: 96.92 | CH92: 96.1 | CI92: 101.73 | CJ92: 102.41 | CK92: 97.02 | CL92: 95.16 | CM92: 95.03 | CN92: 96.31 | CO92: 100.73 | CP92: 101.03 | CQ92: 99.89 | CR92: 99 | CS92: 108.98 | CT92: 95.68 | CU92: 94.21 | CV92: 94.53 | CW92: 94.53 | CX92: 97.2 | CY92: 97.2 | CZ92: 92.38 | DA92: 97.51 | DB92: 97.27 | DC92: 95.14 | DD92: 100.27 | DE92: 89.63 | DF92: 96.16 | DG92: 101.15 | DH92: 94.46 | DI92: 98.64 | DJ92: 96.9 | DK92: 99.9 | DL92: 95.76 | DM92: 96.44 | DN92: 95.9 | DO92: 102.45 | DP92: 93.19 | DQ92: 92.66 | DR92: 97.42 | DS92: 94.37 | DT92: 94.37 | DU92: 92.38 | DV92: 93.97 | DW92: 96.16 | DX92: 96.88 | DY92: 95.9 | DZ92: 95.9 | EA92: 97.13 | EB92: 96.92 | EC92: 97.15 | ED92: 96.81 | EE92: 96.32 | EF92: 97.47 | EG92: 98.57 | EH92: 96.02 | EI92: 97.25 | EJ92: 99.48 | EK92: 95.34 | EL92: 91.56 | EM92: 96.25 | EN92: 82.3 | EO92: 98.97 | EP92: 100.46 | EQ92: 99.87 | ER92: 98.19 | ES92: 97.85 | ET92: 99.81 | EU92: 96.9 | EV92: 102.03 | EW92: 103.06 | EX92: 101.32 | EY92: 94.88 | EZ92: 84.56 | FA92: 96.4 | FB92: 98.23 | FC92: 100.82 | FD92: 91.91 | FE92: 98.33 | FF92: 95.74 | FG92: 84.53 | FH92: 99.88 | FI92: 95.06 | FJ92: 96.21 | FK92: 93.58 | FL92: 91.59 | FM92: 95.29 | FN92: 94.56 | FO92: 95.39 | FP92: 95.58 | FQ92: 84.14 | FR92: 84.14 | FS92: 93.68 | FT92: 96.27 | FU92: 99.15 | FV92: 94.22 | FW92: 97.33 | FX92: 95.01 | FY92: 96.07 | FZ92: 92.71 | GA92: 103.27 | GB92: 86.89 | GC92: 85.95 | GD92: 96.93 | GE92: 97.78 | GF92: 95.17 | GG92: 95.17 | GH92: 100.06 | GI92: 100.06 | GJ92: 93.77 | GK92: 96.9 | GL92: 90.08 | GM92: 100.42 | GN92: 94.03 | GO92: 119.02 | GP92: 86.29 | GQ92: 96.55 | GR92: 94.39 | GS92: 93.36 | GT92: 99.63 | GU92: 92.46 | GV92: 92.46 | GW92: 98.27 | GX92: 99.93 | GY92: 102.45 | GZ92: 93.24 | HA92: 97.91 | HB92: 100.19 | HC92: 98.42 | HD92: 98.98 | HE92: 101.41 | HF92: 94.52 | HG92: 85.95 | HH92: 96.56 | HI92: 99.31 | HJ92: 96.4 | HK92: 100.22 | HL92: 100.84 | HM92: 96.71 | HN92: 95.57 | HO92: 95.51 | HP92: 96.33 | HQ92: 101.27 | HR92: 101.44 | HS92: 101.52 | HT92: 101.03 | HU92: 107.63 | HV92: 96.04 | HW92: 95.37 | HX92: 96.33 | HY92: 96.33 | HZ92: 97.25 | IA92: 97.25 | IB92: 92.38 | IC92: 97.52 | ID92: 97.58 | IE92: 95.94 | IF92: 102.13 | IG92: 89.74 | IH92: 97.03 | II92: 103.03 | IJ92: 94.52 | IK92: 96.68 | IL92: 93.68 | IM92: 99.52 | IN92: 99.7 | IO92: 97.03 | IP92: 97.24 | IQ92: 102.32
A93: 45474 | B93: 97.25 | C93: 97.31 | D93: 98.33 | E93: 99.11 | F93: 97.24 | G93: 97.13 | H93: 100.49 | I93: 96.39 | J93: 92.13 | K93: 96.2 | L93: 85.65 | M93: 100.79 | N93: 100.15 | O93: 100.44 | P93: 97.83 | Q93: 96.79 | R93: 100.18 | S93: 96.72 | T93: 103.67 | U93: 109.39 | V93: 98.87 | W93: 95.52 | X93: 85.36 | Y93: 96.06 | Z93: 97.98 | AA93: 101.59 | AB93: 93.1 | AC93: 98.7 | AD93: 96.63 | AE93: 85.19 | AF93: 99.74 | AG93: 96.22 | AH93: 96.58 | AI93: 95.7 | AJ93: 94.24 | AK93: 97.74 | AL93: 96.79 | AM93: 99.4 | AN93: 96.59 | AO93: 86.11 | AP93: 86.11 | AQ93: 97.01 | AR93: 99.28 | AS93: 103.86 | AT93: 98.18 | AU93: 96.81 | AV93: 99.29 | AW93: 104.11 | AX93: 97.62 | AY93: 100.95 | AZ93: 91.18 | BA93: 90.92 | BB93: 93.86 | BC93: 97.82 | BD93: 96.23 | BE93: 96.23 | BF93: 98.96 | BG93: 98.96 | BH93: 94.51 | BI93: 97.12 | BJ93: 89.65 | BK93: 101.85 | BL93: 99.99 | BM93: 104.15 | BN93: 92.49 | BO93: 97.74 | BP93: 100.17 | BQ93: 100.88 | BR93: 97.44 | BS93: 102.15 | BT93: 102.15 | BU93: 102.67 | BV93: 100.31 | BW93: 107.08 | BX93: 101.51 | BY93: 103.6 | BZ93: 99.71 | CA93: 99.73 | CB93: 98.41 | CC93: 100.63 | CD93: 92.74 | CE93: 85.27 | CF93: 97.17 | CG93: 97.74 | CH93: 95.78 | CI93: 100.96 | CJ93: 101.53 | CK93: 97.02 | CL93: 94.92 | CM93: 94.76 | CN93: 96.31 | CO93: 99.95 | CP93: 100.08 | CQ93: 99.46 | CR93: 99.45 | CS93: 105.62 | CT93: 95.65 | CU93: 95.71 | CV93: 97.16 | CW93: 97.16 | CX93: 98.87 | CY93: 98.87 | CZ93: 96.26 | DA93: 99.02 | DB93: 96.62 | DC93: 95.8 | DD93: 100.81 | DE93: 90.42 | DF93: 96.39 | DG93: 101.66 | DH93: 94.6 | DI93: 96.86 | DJ93: 95.79 | DK93: 97.41 | DL93: 96.29 | DM93: 96.34 | DN93: 92.99 | DO93: 103.14 | DP93: 93.86 | DQ93: 95.25 | DR93: 98.24 | DS93: 94.39 | DT93: 94.39 | DU93: 92.48 | DV93: 93.97 | DW93: 96.16 | DX93: 97.03 | DY93: 96.62 | DZ93: 96.62 | EA93: 97.13 | EB93: 96.98 | EC93: 97.15 | ED93: 97.19 | EE93: 97.23 | EF93: 98.35 | EG93: 98.8 | EH93: 97.56 | EI93: 97.17 | EJ93: 100.52 | EK93: 96.35 | EL93: 92.09 | EM93: 96.92 | EN93: 84.9 | EO93: 100.91 | EP93: 100.59 | EQ93: 100.12 | ER93: 98.14 | ES93: 97.4 | ET93: 100.25 | EU93: 96.86 | EV93: 102.8 | EW93: 107.26 | EX93: 99.79 | EY93: 95.35 | EZ93: 85.67 | FA93: 95.84 | FB93: 97.73 | FC93: 101.18 | FD93: 92.78 | FE93: 98.72 | FF93: 95.67 | FG93: 85.17 | FH93: 99.53 | FI93: 96.42 | FJ93: 96.54 | FK93: 96.27 | FL93: 91.83 | FM93: 95.7 | FN93: 95.31 | FO93: 95.91 | FP93: 95.72 | FQ93: 84.09 | FR93: 84.09 | FS93: 96.3 | FT93: 99.22 | FU93: 101.6 | FV93: 98.4 | FW93: 97.46 | FX93: 98.38 | FY93: 101.95 | FZ93: 94.57 | GA93: 107.05 | GB93: 88.34 | GC93: 87.51 | GD93: 97.13 | GE93: 98.7 | GF93: 95.79 | GG93: 95.79 | GH93: 99.98 | GI93: 99.98 | GJ93: 94.02 | GK93: 97.35 | GL93: 90.08 | GM93: 104.03 | GN93: 96.98 | GO93: 121.22 | GP93: 91.42 | GQ93: 98.08 | GR93: 98.18 | GS93: 97.74 | GT93: 100.45 | GU93: 99.34 | GV93: 99.34 | GW93: 100.68 | GX93: 101.55 | GY93: 102.74 | GZ93: 100.2 | HA93: 98.31 | HB93: 99.83 | HC93: 99.78 | HD93: 98.75 | HE93: 100.66 | HF93: 94.94 | HG93: 86.22 | HH93: 96.57 | HI93: 100.53 | HJ93: 96.63 | HK93: 100.92 | HL93: 101.65 | HM93: 96.82 | HN93: 95.7 | HO93: 95.65 | HP93: 96.33 | HQ93: 99.97 | HR93: 100.09 | HS93: 101.62 | HT93: 101.05 | HU93: 102.85 | HV93: 95.35 | HW93: 96.97 | HX93: 96.37 | HY93: 96.37 | HZ93: 98.89 | IA93: 98.89 | IB93: 96.26 | IC93: 99.02 | ID93: 96.66 | IE93: 98.04 | IF93: 105.35 | IG93: 90.66 | IH93: 97.86 | II93: 103.58 | IJ93: 95.45 | IK93: 94.23 | IL93: 92.79 | IM93: 95.2 | IN93: 99.43 | IO93: 96.71 | IP93: 95.22 | IQ93: 103.05
A94: 45505 | B94: 97.04 | C94: 97.49 | D94: 98.23 | E94: 98.78 | F94: 96.98 | G94: 100.87 | H94: 99.57 | I94: 96.82 | J94: 92.98 | K94: 96.61 | L94: 86.52 | M94: 101.22 | N94: 99.45 | O94: 101.1 | P94: 97.98 | Q94: 97.92 | R94: 99.31 | S94: 96.7 | T94: 104.42 | U94: 107.02 | V94: 102.19 | W94: 95.49 | X94: 87.94 | Y94: 97.92 | Z94: 98.68 | AA94: 101.06 | AB94: 92.1 | AC94: 99.13 | AD94: 96.61 | AE94: 85.42 | AF94: 99.65 | AG94: 96.32 | AH94: 96.69 | AI94: 95.79 | AJ94: 95 | AK94: 98.94 | AL94: 97.29 | AM94: 101.08 | AN94: 97.63 | AO94: 85.93 | AP94: 85.93 | AQ94: 96.8 | AR94: 100.01 | AS94: 105.38 | AT94: 98.39 | AU94: 98.33 | AV94: 96.64 | AW94: 102.24 | AX94: 95.17 | AY94: 96.48 | AZ94: 90.14 | BA94: 89.83 | BB94: 93.39 | BC94: 96.91 | BD94: 96.72 | BE94: 96.72 | BF94: 99.21 | BG94: 99.21 | BH94: 94.25 | BI94: 96.74 | BJ94: 89.65 | BK94: 95.02 | BL94: 99.99 | BM94: 94.37 | BN94: 93.32 | BO94: 98.92 | BP94: 100.13 | BQ94: 100.67 | BR94: 98.03 | BS94: 107.62 | BT94: 107.62 | BU94: 103.61 | BV94: 98.4 | BW94: 107.22 | BX94: 107.69 | BY94: 103.13 | BZ94: 99.93 | CA94: 99.2 | CB94: 98.88 | CC94: 100.82 | CD94: 94.6 | CE94: 89.52 | CF94: 97.62 | CG94: 97.8 | CH94: 95.5 | CI94: 100.47 | CJ94: 100.97 | CK94: 97.02 | CL94: 94.67 | CM94: 94.48 | CN94: 96.31 | CO94: 98.77 | CP94: 98.87 | CQ94: 99.49 | CR94: 101.13 | CS94: 100.64 | CT94: 96.42 | CU94: 95.71 | CV94: 96.72 | CW94: 96.72 | CX94: 98.36 | CY94: 98.36 | CZ94: 96.17 | DA94: 98.48 | DB94: 96.34 | DC94: 96.11 | DD94: 101.16 | DE94: 90.68 | DF94: 97.31 | DG94: 102.72 | DH94: 95.47 | DI94: 95.42 | DJ94: 93.27 | DK94: 97.16 | DL94: 97.56 | DM94: 98.28 | DN94: 97.48 | DO94: 102.28 | DP94: 94.18 | DQ94: 95.67 | DR94: 99.12 | DS94: 94.67 | DT94: 94.67 | DU94: 93.1 | DV94: 93.97 | DW94: 96.6 | DX94: 97.12 | DY94: 97.68 | DZ94: 97.68 | EA94: 96.96 | EB94: 94.95 | EC94: 97.15 | ED94: 97.12 | EE94: 97.43 | EF94: 98.28 | EG94: 98.46 | EH94: 97.34 | EI94: 100.5 | EJ94: 99.86 | EK94: 97.07 | EL94: 92.74 | EM94: 97.11 | EN94: 88.97 | EO94: 101.23 | EP94: 99.72 | EQ94: 100.55 | ER94: 98.04 | ES94: 98.14 | ET94: 99.15 | EU94: 96.7 | EV94: 103.49 | EW94: 105.16 | EX94: 102.36 | EY94: 95.32 | EZ94: 87.79 | FA94: 97.56 | FB94: 98.69 | FC94: 100.79 | FD94: 91.89 | FE94: 98.98 | FF94: 95.71 | FG94: 85.64 | FH94: 99.41 | FI94: 96.52 | FJ94: 96.59 | FK94: 96.44 | FL94: 92.66 | FM94: 96.99 | FN94: 95.46 | FO94: 98.74 | FP94: 96.35 | FQ94: 84.1 | FR94: 84.1 | FS94: 95.3 | FT94: 98.42 | FU94: 102.2 | FV94: 97.14 | FW94: 95.6 | FX94: 95.67 | FY94: 99.41 | FZ94: 91.15 | GA94: 107.28 | GB94: 87.82 | GC94: 86.89 | GD94: 97.83 | GE94: 98.25 | GF94: 96.35 | GG94: 96.35 | GH94: 100.03 | GI94: 100.03 | GJ94: 94 | GK94: 97.3 | GL94: 90.08 | GM94: 101.07 | GN94: 96.98 | GO94: 112.55 | GP94: 92.33 | GQ94: 98.94 | GR94: 97.94 | GS94: 97.67 | GT94: 99.34 | GU94: 106.59 | GV94: 106.59 | GW94: 100.02 | GX94: 100.46 | GY94: 101.37 | GZ94: 99.47 | HA94: 98.86 | HB94: 100.04 | HC94: 99.17 | HD94: 99.1 | HE94: 100.89 | HF94: 96.7 | HG94: 91.14 | HH94: 97.34 | HI94: 100.62 | HJ94: 96.66 | HK94: 100.76 | HL94: 101.46 | HM94: 96.82 | HN94: 95.78 | HO94: 95.61 | HP94: 97.38 | HQ94: 99.12 | HR94: 99.21 | HS94: 101.4 | HT94: 101.16 | HU94: 100.07 | HV94: 95.76 | HW94: 96.49 | HX94: 96.37 | HY94: 96.37 | HZ94: 98.38 | IA94: 98.38 | IB94: 96.17 | IC94: 98.48 | ID94: 96.59 | IE94: 97.29 | IF94: 103.68 | IG94: 90.89 | IH94: 98.13 | II94: 105.22 | IJ94: 95.16 | IK94: 93 | IL94: 91.04 | IM94: 94.61 | IN94: 101.42 | IO94: 96.88 | IP94: 98.48 | IQ94: 102.44
A95: 45536 | B95: 96.75 | C95: 96.93 | D95: 98.2 | E95: 98.47 | F95: 96.93 | G95: 101.17 | H95: 100.33 | I95: 97.02 | J95: 93.55 | K95: 96.85 | L95: 88.31 | M95: 100.79 | N95: 98.95 | O95: 100.97 | P95: 97.49 | Q95: 97.68 | R95: 98.9 | S95: 95.81 | T95: 99.85 | U95: 99.42 | V95: 100.13 | W95: 95.83 | X95: 92.12 | Y95: 96.86 | Z95: 98.07 | AA95: 100.09 | AB95: 92.86 | AC95: 99.06 | AD95: 95.23 | AE95: 86.19 | AF95: 97.67 | AG95: 96.39 | AH95: 96.69 | AI95: 95.98 | AJ95: 96.41 | AK95: 99.24 | AL95: 97.64 | AM95: 100.93 | AN95: 98.33 | AO95: 89.67 | AP95: 89.67 | AQ95: 95.75 | AR95: 98.46 | AS95: 103.28 | AT95: 97.25 | AU95: 96.06 | AV95: 94.27 | AW95: 106.83 | AX95: 90.39 | AY95: 95.66 | AZ95: 90.78 | BA95: 90.52 | BB95: 93.39 | BC95: 96.21 | BD95: 96.88 | BE95: 96.88 | BF95: 98.85 | BG95: 98.85 | BH95: 96.18 | BI95: 97 | BJ95: 94.65 | BK95: 89.49 | BL95: 99.99 | BM95: 86.59 | BN95: 93.32 | BO95: 98.3 | BP95: 100.33 | BQ95: 100.87 | BR95: 98.26 | BS95: 100.04 | BT95: 100.04 | BU95: 101.01 | BV95: 98.89 | BW95: 103.25 | BX95: 100.55 | BY95: 102.3 | BZ95: 99.23 | CA95: 98.44 | CB95: 97.73 | CC95: 100.44 | CD95: 95.42 | CE95: 90.69 | CF95: 98.19 | CG95: 98.46 | CH95: 95.44 | CI95: 100.04 | CJ95: 100.47 | CK95: 97.02 | CL95: 94.68 | CM95: 94.49 | CN95: 96.31 | CO95: 96.89 | CP95: 96.89 | CQ95: 99.02 | CR95: 100.82 | CS95: 94.42 | CT95: 96.48 | CU95: 96.04 | CV95: 96.75 | CW95: 96.75 | CX95: 98.4 | CY95: 98.4 | CZ95: 95.96 | DA95: 98.53 | DB95: 97.45 | DC95: 95.7 | DD95: 100.23 | DE95: 90.86 | DF95: 96.56 | DG95: 99.7 | DH95: 95.49 | DI95: 97.49 | DJ95: 95.84 | DK95: 98.68 | DL95: 98.01 | DM95: 99.15 | DN95: 99.95 | DO95: 101.56 | DP95: 94.18 | DQ95: 96.15 | DR95: 98.53 | DS95: 94.72 | DT95: 94.72 | DU95: 93.3 | DV95: 93.97 | DW95: 96.6 | DX95: 97.68 | DY95: 97.87 | DZ95: 97.87 | EA95: 97.63 | EB95: 95.16 | EC95: 97.86 | ED95: 97.4 | EE95: 96.97 | EF95: 98.13 | EG95: 98.26 | EH95: 97.05 | EI95: 100.81 | EJ95: 100.07 | EK95: 96.96 | EL95: 93.19 | EM95: 96.73 | EN95: 89.89 | EO95: 100.55 | EP95: 99 | EQ95: 100.38 | ER95: 97.52 | ES95: 97.72 | ET95: 98.81 | EU95: 95.81 | EV95: 99.96 | EW95: 99.39 | EX95: 100.32 | EY95: 95.75 | EZ95: 92.49 | FA95: 96.47 | FB95: 98.08 | FC95: 99.91 | FD95: 92.7 | FE95: 99.16 | FF95: 94.52 | FG95: 86.16 | FH95: 97.58 | FI95: 96.61 | FJ95: 96.7 | FK95: 96.48 | FL95: 94.27 | FM95: 97.6 | FN95: 96.34 | FO95: 99.27 | FP95: 96.88 | FQ95: 87.45 | FR95: 87.45 | FS95: 96.39 | FT95: 98.19 | FU95: 101.33 | FV95: 96.76 | FW95: 96.95 | FX95: 97.08 | FY95: 103.02 | FZ95: 92.03 | GA95: 105.29 | GB95: 91.87 | GC95: 91.29 | GD95: 97.83 | GE95: 97.54 | GF95: 96.51 | GG95: 96.51 | GH95: 100.03 | GI95: 100.03 | GJ95: 95.77 | GK95: 97.49 | GL95: 93.74 | GM95: 95.98 | GN95: 96.98 | GO95: 99.42 | GP95: 92.33 | GQ95: 98.58 | GR95: 98.8 | GS95: 98.7 | GT95: 99.35 | GU95: 100.25 | GV95: 100.25 | GW95: 99.6 | GX95: 98.59 | GY95: 99.77 | GZ95: 101.51 | HA95: 98.35 | HB95: 99.23 | HC95: 98.47 | HD95: 97.82 | HE95: 100.43 | HF95: 97.06 | HG95: 92.24 | HH95: 97.34 | HI95: 100.79 | HJ95: 96.35 | HK95: 99.7 | HL95: 100.23 | HM95: 96.72 | HN95: 95.63 | HO95: 95.33 | HP95: 98.27 | HQ95: 99.43 | HR95: 99.53 | HS95: 101.05 | HT95: 101.46 | HU95: 100.03 | HV95: 95.89 | HW95: 99.4 | HX95: 96.55 | HY95: 96.55 | HZ95: 98.42 | IA95: 98.42 | IB95: 95.96 | IC95: 98.54 | ID95: 99.02 | IE95: 97.53 | IF95: 103.94 | IG95: 91.12 | IH95: 96.94 | II95: 100.25 | IJ95: 95.53 | IK95: 97.71 | IL95: 95.09 | IM95: 100.09 | IN95: 101.86 | IO95: 98.53 | IP95: 99.66 | IQ95: 101.71
A96: 45566 | B96: 96.46 | C96: 97.04 | D96: 99.4 | E96: 99.59 | F96: 99.31 | G96: 97.66 | H96: 100.07 | I96: 97.34 | J96: 93.12 | K96: 98.12 | L96: 88.49 | M96: 101.52 | N96: 100.23 | O96: 100.38 | P96: 96.52 | Q96: 96.09 | R96: 98.49 | S96: 95.05 | T96: 99.39 | U96: 102.51 | V96: 96.74 | W96: 95.86 | X96: 93.39 | Y96: 98.04 | Z96: 98.57 | AA96: 100.32 | AB96: 92.08 | AC96: 99.65 | AD96: 95.28 | AE96: 85.16 | AF96: 98.02 | AG96: 96.56 | AH96: 97.03 | AI96: 95.88 | AJ96: 97.28 | AK96: 99.34 | AL96: 98.16 | AM96: 100.37 | AN96: 98.87 | AO96: 92.15 | AP96: 92.15 | AQ96: 96.23 | AR96: 98.38 | AS96: 101.97 | AT96: 97.47 | AU96: 96.67 | AV96: 99.09 | AW96: 107.04 | AX96: 96.44 | AY96: 101.03 | AZ96: 90.39 | BA96: 90.03 | BB96: 94.21 | BC96: 94.49 | BD96: 96.79 | BE96: 96.79 | BF96: 98.92 | BG96: 98.92 | BH96: 96.66 | BI96: 97.73 | BJ96: 94.65 | BK96: 78.55 | BL96: 99.99 | BM96: 70.05 | BN96: 98.75 | BO96: 98.95 | BP96: 102.68 | BQ96: 104.29 | BR96: 96.62 | BS96: 99.31 | BT96: 99.31 | BU96: 102.74 | BV96: 99.65 | BW96: 103.84 | BX96: 107.09 | BY96: 101.24 | BZ96: 98.53 | CA96: 99.26 | CB96: 96.95 | CC96: 99.49 | CD96: 95.89 | CE96: 91.28 | CF96: 98.4 | CG96: 99.2 | CH96: 95.7 | CI96: 101.02 | CJ96: 101.6 | CK96: 97.02 | CL96: 94.81 | CM96: 94.57 | CN96: 96.81 | CO96: 97.45 | CP96: 97.48 | CQ96: 99.15 | CR96: 98.93 | CS96: 96.47 | CT96: 96.87 | CU96: 95.86 | CV96: 96.72 | CW96: 96.72 | CX96: 99.02 | CY96: 99.02 | CZ96: 95.36 | DA96: 99.24 | DB96: 96.37 | DC96: 94.92 | DD96: 98.66 | DE96: 90.95 | DF96: 97.37 | DG96: 99.81 | DH96: 96.53 | DI96: 96.73 | DJ96: 99.7 | DK96: 92.81 | DL96: 95.99 | DM96: 97.72 | DN96: 97.14 | DO96: 97.53 | DP96: 94.84 | DQ96: 96.16 | DR96: 94.09 | DS96: 94.74 | DT96: 94.74 | DU96: 93.38 | DV96: 93.97 | DW96: 96.6 | DX96: 97.87 | DY96: 98.06 | DZ96: 98.06 | EA96: 97.81 | EB96: 97.32 | EC96: 97.86 | ED96: 96.83 | EE96: 97.1 | EF96: 99.51 | EG96: 99.41 | EH96: 99.78 | EI96: 97.65 | EJ96: 99.93 | EK96: 97.35 | EL96: 92.9 | EM96: 98.59 | EN96: 89.84 | EO96: 101.21 | EP96: 100.16 | EQ96: 99.97 | ER96: 96.55 | ES96: 96.12 | ET96: 98.37 | EU96: 95.13 | EV96: 98.99 | EW96: 101.17 | EX96: 97.51 | EY96: 95.77 | EZ96: 93.4 | FA96: 97.58 | FB96: 98.65 | FC96: 100.2 | FD96: 91.89 | FE96: 99.91 | FF96: 94.61 | FG96: 85.4 | FH96: 97.99 | FI96: 96.89 | FJ96: 97.12 | FK96: 96.59 | FL96: 95.33 | FM96: 97.79 | FN96: 97.07 | FO96: 99.05 | FP96: 97.13 | FQ96: 90 | FR96: 90 | FS96: 96.5 | FT96: 98.03 | FU96: 100.73 | FV96: 97.21 | FW96: 95.73 | FX96: 99.21 | FY96: 103.96 | FZ96: 94.45 | GA96: 109.22 | GB96: 91.48 | GC96: 90.84 | GD96: 98.05 | GE96: 95.53 | GF96: 96.33 | GG96: 96.33 | GH96: 100.28 | GI96: 100.28 | GJ96: 96.15 | GK96: 98.18 | GL96: 93.74 | GM96: 85.78 | GN96: 96.98 | GO96: 77.1 | GP96: 88.78 | GQ96: 99.16 | GR96: 102.13 | GS96: 102.72 | GT96: 99.19 | GU96: 99.16 | GV96: 99.16 | GW96: 99.82 | GX96: 100.91 | GY96: 99.52 | GZ96: 100.66 | HA96: 98.19 | HB96: 98.67 | HC96: 99.08 | HD96: 97.2 | HE96: 99.72 | HF96: 97.42 | HG96: 92.51 | HH96: 97.42 | HI96: 101.65 | HJ96: 96.73 | HK96: 99.5 | HL96: 99.87 | HM96: 97.42 | HN96: 96.14 | HO96: 95.89 | HP96: 98.34 | HQ96: 98.03 | HR96: 98.06 | HS96: 101.45 | HT96: 101.63 | HU96: 96.03 | HV96: 95.88 | HW96: 96.49 | HX96: 97.04 | HY96: 97.04 | HZ96: 99.06 | IA96: 99.06 | IB96: 95.36 | IC96: 99.25 | ID96: 97.52 | IE96: 96.89 | IF96: 102.6 | IG96: 91.2 | IH96: 97.59 | II96: 100.19 | IJ96: 96.47 | IK96: 95.99 | IL96: 98.73 | IM96: 91.84 | IN96: 100.05 | IO96: 98.28 | IP96: 98.28 | IQ96: 97.64
A97: 45597 | B97: 96.73 | C97: 97.35 | D97: 99.84 | E97: 100.35 | F97: 99.38 | G97: 99.91 | H97: 99.85 | I97: 97.58 | J97: 93.62 | K97: 99.1 | L97: 89.18 | M97: 101.21 | N97: 100.68 | O97: 99.94 | P97: 97.3 | Q97: 97.26 | R97: 99.34 | S97: 95.28 | T97: 99.45 | U97: 102.72 | V97: 96.67 | W97: 96.26 | X97: 93.66 | Y97: 98.07 | Z97: 98.37 | AA97: 100.64 | AB97: 92.65 | AC97: 100.24 | AD97: 95.77 | AE97: 86.93 | AF97: 98.16 | AG97: 96.81 | AH97: 97.3 | AI97: 96.11 | AJ97: 96.82 | AK97: 98.63 | AL97: 98.65 | AM97: 99.32 | AN97: 97.98 | AO97: 92.25 | AP97: 92.25 | AQ97: 93.94 | AR97: 97.65 | AS97: 101.62 | AT97: 96.52 | AU97: 96.17 | AV97: 95.47 | AW97: 102.02 | AX97: 92.94 | AY97: 98.58 | AZ97: 85.4 | BA97: 84.54 | BB97: 95.35 | BC97: 95.79 | BD97: 97.27 | BE97: 97.27 | BF97: 98.36 | BG97: 98.36 | BH97: 96.85 | BI97: 98.03 | BJ97: 94.65 | BK97: 86.69 | BL97: 99.99 | BM97: 81.49 | BN97: 98.75 | BO97: 98.4 | BP97: 98.47 | BQ97: 98.59 | BR97: 97.99 | BS97: 102.68 | BT97: 102.68 | BU97: 102.28 | BV97: 99.82 | BW97: 106.39 | BX97: 103.56 | BY97: 101.28 | BZ97: 98.49 | CA97: 97.78 | CB97: 96.52 | CC97: 100.03 | CD97: 96.13 | CE97: 91.68 | CF97: 98.64 | CG97: 99.15 | CH97: 95.42 | CI97: 99.92 | CJ97: 100.34 | CK97: 97.02 | CL97: 94.67 | CM97: 94.43 | CN97: 96.69 | CO97: 98.11 | CP97: 98.19 | CQ97: 99.1 | CR97: 100.54 | CS97: 98.4 | CT97: 97.11 | CU97: 95.92 | CV97: 96.41 | CW97: 96.41 | CX97: 98.91 | CY97: 98.91 | CZ97: 95.19 | DA97: 99.13 | DB97: 96.54 | DC97: 96.3 | DD97: 100.59 | DE97: 91.71 | DF97: 97.43 | DG97: 101.22 | DH97: 96.14 | DI97: 95.22 | DJ97: 99.01 | DK97: 90.4 | DL97: 98.43 | DM97: 100.6 | DN97: 101.35 | DO97: 99.53 | DP97: 95.21 | DQ97: 96.23 | DR97: 98.84 | DS97: 94.76 | DT97: 94.76 | DU97: 93.48 | DV97: 93.97 | DW97: 96.6 | DX97: 97.81 | DY97: 98.31 | DZ97: 98.31 | EA97: 97.68 | EB97: 95.75 | EC97: 97.86 | ED97: 97.2 | EE97: 97.36 | EF97: 99.77 | EG97: 100.32 | EH97: 99.31 | EI97: 99.66 | EJ97: 99.92 | EK97: 97.51 | EL97: 93.27 | EM97: 99.35 | EN97: 90.32 | EO97: 101.04 | EP97: 100.55 | EQ97: 99.48 | ER97: 97.47 | ES97: 97.34 | ET97: 99.42 | EU97: 95.52 | EV97: 98.48 | EW97: 100.78 | EX97: 96.91 | EY97: 96.33 | EZ97: 94.04 | FA97: 97.6 | FB97: 98.49 | FC97: 100.74 | FD97: 92.76 | FE97: 100.4 | FF97: 95 | FG97: 86.74 | FH97: 98.02 | FI97: 97.19 | FJ97: 97.56 | FK97: 96.71 | FL97: 96.12 | FM97: 99.05 | FN97: 97.98 | FO97: 100.3 | FP97: 98.58 | FQ97: 89.96 | FR97: 89.96 | FS97: 93.63 | FT97: 97.52 | FU97: 99.53 | FV97: 96.9 | FW97: 95.84 | FX97: 93.1 | FY97: 98.02 | FZ97: 87.55 | GA97: 106.4 | GB97: 84.82 | GC97: 83.52 | GD97: 99.09 | GE97: 96.51 | GF97: 96.85 | GG97: 96.85 | GH97: 99.08 | GI97: 99.08 | GJ97: 96.27 | GK97: 98.41 | GL97: 93.74 | GM97: 91.84 | GN97: 96.98 | GO97: 86.45 | GP97: 94.36 | GQ97: 99.42 | GR97: 99.36 | GS97: 99.56 | GT97: 98.37 | GU97: 109.67 | GV97: 109.67 | GW97: 100.24 | GX97: 100.18 | GY97: 101.36 | GZ97: 102.45 | HA97: 96.79 | HB97: 98.81 | HC97: 97.96 | HD97: 96.91 | HE97: 100.39 | HF97: 97.76 | HG97: 92.56 | HH97: 98.18 | HI97: 101.65 | HJ97: 96.67 | HK97: 98.54 | HL97: 98.87 | HM97: 96.72 | HN97: 96.27 | HO97: 96.05 | HP97: 98.34 | HQ97: 98.92 | HR97: 98.98 | HS97: 100.84 | HT97: 101.76 | HU97: 98.32 | HV97: 97.31 | HW97: 97.27 | HX97: 96.98 | HY97: 96.98 | HZ97: 98.94 | IA97: 98.94 | IB97: 95.19 | IC97: 99.14 | ID97: 97.79 | IE97: 98.11 | IF97: 104.28 | IG97: 91.94 | IH97: 97.52 | II97: 99.51 | IJ97: 96.66 | IK97: 95.16 | IL97: 98.51 | IM97: 90.28 | IN97: 101.57 | IO97: 98.51 | IP97: 100.85 | IQ97: 99.69
A98: 45627 | B98: 97.57 | C98: 97.52 | D98: 100.37 | E98: 101.07 | F98: 98.75 | G98: 103.98 | H98: 101.99 | I98: 97.76 | J98: 94.19 | K98: 99.01 | L98: 88.94 | M98: 100.74 | N98: 101.27 | O98: 100.44 | P98: 98.32 | Q98: 97.93 | R98: 99.88 | S98: 97.23 | T98: 97.94 | U98: 99.55 | V98: 96.53 | W98: 97.44 | X98: 93.95 | Y98: 97.72 | Z98: 98.75 | AA98: 100.11 | AB98: 94.71 | AC98: 101.63 | AD98: 96.06 | AE98: 89.47 | AF98: 97.83 | AG98: 96.99 | AH98: 97.44 | AI98: 96.34 | AJ98: 96.53 | AK98: 98.12 | AL98: 97.92 | AM98: 97.96 | AN98: 98.35 | AO98: 92.41 | AP98: 92.41 | AQ98: 94.46 | AR98: 97.37 | AS98: 100.06 | AT98: 97.22 | AU98: 94.08 | AV98: 92.97 | AW98: 101.7 | AX98: 89.77 | AY98: 96.22 | AZ98: 89.05 | BA98: 88.48 | BB98: 95.46 | BC98: 96.59 | BD98: 97.53 | BE98: 97.53 | BF98: 98.46 | BG98: 98.46 | BH98: 96.76 | BI98: 97.9 | BJ98: 94.65 | BK98: 90.94 | BL98: 99.99 | BM98: 88.39 | BN98: 94.47 | BO98: 97.87 | BP98: 100.08 | BQ98: 100.28 | BR98: 99.28 | BS98: 91.29 | BT98: 91.29 | BU98: 98.97 | BV98: 95.35 | BW98: 98.37 | BX98: 100.64 | BY98: 101.43 | BZ98: 99.22 | CA98: 100.29 | CB98: 97.76 | CC98: 100.04 | CD98: 96.42 | CE98: 92.23 | CF98: 98.64 | CG98: 99.5 | CH98: 95.19 | CI98: 98.89 | CJ98: 99.42 | CK98: 95.21 | CL98: 94.58 | CM98: 94.33 | CN98: 96.69 | CO98: 99.23 | CP98: 99.36 | CQ98: 99.4 | CR98: 94.04 | CS98: 103.31 | CT98: 97.23 | CU98: 95.92 | CV98: 96.48 | CW98: 96.48 | CX98: 98.69 | CY98: 98.69 | CZ98: 95.05 | DA98: 98.91 | DB98: 101.09 | DC98: 93.7 | DD98: 95.85 | DE98: 91.48 | DF98: 97.1 | DG98: 100.71 | DH98: 95.87 | DI98: 105.43 | DJ98: 100.64 | DK98: 110.03 | DL98: 97.57 | DM98: 100.17 | DN98: 92.84 | DO98: 101.54 | DP98: 96.49 | DQ98: 96.44 | DR98: 99.91 | DS98: 94.78 | DT98: 94.78 | DU98: 93.6 | DV98: 93.97 | DW98: 96.6 | DX98: 98.25 | DY98: 98.65 | DZ98: 98.65 | EA98: 98.14 | EB98: 95.94 | EC98: 98.34 | ED98: 97.95 | EE98: 97.52 | EF98: 100.59 | EG98: 101.03 | EH98: 99.29 | EI98: 104.08 | EJ98: 102.03 | EK98: 97.25 | EL98: 92.98 | EM98: 99.24 | EN98: 88.85 | EO98: 99.9 | EP98: 101.52 | EQ98: 100.05 | ER98: 98.41 | ES98: 97.63 | ET98: 100.05 | EU98: 97.69 | EV98: 96.5 | EW98: 96.93 | EX98: 96.2 | EY98: 97.68 | EZ98: 93.97 | FA98: 97.64 | FB98: 98.92 | FC98: 99.77 | FD98: 95.2 | FE98: 102.23 | FF98: 95.5 | FG98: 89.25 | FH98: 97.77 | FI98: 97.36 | FJ98: 97.83 | FK98: 96.76 | FL98: 95.56 | FM98: 98.06 | FN98: 97.27 | FO98: 98.26 | FP98: 98.28 | FQ98: 90.16 | FR98: 90.16 | FS98: 94.85 | FT98: 98.33 | FU98: 99.29 | FV98: 98.86 | FW98: 95.07 | FX98: 93.71 | FY98: 99.58 | FZ98: 88.65 | GA98: 102.15 | GB98: 87.37 | GC98: 86.28 | GD98: 99.09 | GE98: 97.28 | GF98: 97.24 | GG98: 97.24 | GH98: 98.53 | GI98: 98.53 | GJ98: 96.1 | GK98: 98.09 | GL98: 93.74 | GM98: 96.17 | GN98: 96.98 | GO98: 99.35 | GP98: 92.84 | GQ98: 98.02 | GR98: 98 | GS98: 97.87 | GT98: 98.68 | GU98: 92.47 | GV98: 92.47 | GW98: 97.49 | GX98: 98.72 | GY98: 96.74 | GZ98: 95.77 | HA98: 99.01 | HB98: 99.64 | HC98: 100.32 | HD98: 97.93 | HE98: 100.83 | HF98: 97.83 | HG98: 92.82 | HH98: 98.18 | HI98: 101.62 | HJ98: 96.31 | HK98: 97.77 | HL98: 97.96 | HM98: 96.72 | HN98: 96 | HO98: 95.74 | HP98: 98.34 | HQ98: 99.63 | HR98: 99.72 | HS98: 100.65 | HT98: 101.79 | HU98: 100.86 | HV98: 97.31 | HW98: 97.49 | HX98: 96.98 | HY98: 96.98 | HZ98: 98.72 | IA98: 98.72 | IB98: 95.05 | IC98: 98.92 | ID98: 102.41 | IE98: 97.24 | IF98: 102.74 | IG98: 91.77 | IH98: 97.27 | II98: 98.62 | IJ98: 96.67 | IK98: 105.41 | IL98: 99.51 | IM98: 111.69 | IN98: 100.83 | IO98: 98.35 | IP98: 94.73 | IQ98: 101.49
A99: 45658 | B99: 97.76 | C99: 98.18 | D99: 101.16 | E99: 101.25 | F99: 100.85 | G99: 102.47 | H99: 101.31 | I99: 98.45 | J99: 95.23 | K99: 100.01 | L99: 90.49 | M99: 102.12 | N99: 101 | O99: 100.26 | P99: 98.21 | Q99: 97.56 | R99: 100.59 | S99: 96.59 | T99: 101.03 | U99: 102.36 | V99: 99.87 | W99: 98.87 | X99: 94.25 | Y99: 97.76 | Z99: 100.2 | AA99: 101.22 | AB99: 97.45 | AC99: 101.32 | AD99: 97.02 | AE99: 88.2 | AF99: 99.39 | AG99: 96.83 | AH99: 97.13 | AI99: 96.41 | AJ99: 97.14 | AK99: 98.75 | AL99: 98.41 | AM99: 99.25 | AN99: 98.41 | AO99: 92.95 | AP99: 92.95 | AQ99: 95.39 | AR99: 96.28 | AS99: 98.88 | AT99: 95.95 | AU99: 93.78 | AV99: 96.07 | AW99: 98.2 | AX99: 93.86 | AY99: 102.91 | AZ99: 93.21 | BA99: 93.08 | BB99: 94.64 | BC99: 96.58 | BD99: 97.8 | BE99: 97.8 | BF99: 98.03 | BG99: 98.03 | BH99: 97.04 | BI99: 98.32 | BJ99: 94.65 | BK99: 90.94 | BL99: 99.99 | BM99: 88.39 | BN99: 94.47 | BO99: 97.97 | BP99: 97.45 | BQ99: 97.85 | BR99: 95.89 | BS99: 94.7 | BT99: 94.7 | BU99: 100.2 | BV99: 97.71 | BW99: 101.17 | BX99: 100.63 | BY99: 101.8 | BZ99: 99.67 | CA99: 98.78 | CB99: 99.44 | CC99: 100 | CD99: 96.54 | CE99: 92.37 | CF99: 98.75 | CG99: 99.6 | CH99: 98.09 | CI99: 104.07 | CJ99: 104.97 | CK99: 97.81 | CL99: 97.1 | CM99: 97.15 | CN99: 96.69 | CO99: 98.89 | CP99: 99 | CQ99: 99.43 | CR99: 101.47 | CS99: 99.42 | CT99: 97.34 | CU99: 97.92 | CV99: 96.4 | CW99: 96.4 | CX99: 98.33 | CY99: 98.33 | CZ99: 95.03 | DA99: 98.54 | DB99: 99.55 | DC99: 94.01 | DD99: 96.48 | DE99: 91.47 | DF99: 96.82 | DG99: 104.59 | DH99: 94.16 | DI99: 101.43 | DJ99: 107.58 | DK99: 95.51 | DL99: 99.4 | DM99: 100.78 | DN99: 101.54 | DO99: 102.77 | DP99: 96.49 | DQ99: 96.71 | DR99: 100.37 | DS99: 94.8 | DT99: 94.8 | DU99: 93.67 | DV99: 93.97 | DW99: 96.6 | DX99: 98.85 | DY99: 101.45 | DZ99: 101.45 | EA99: 98.14 | EB99: 95.99 | EC99: 98.34 | ED99: 98.25 | EE99: 98.32 | EF99: 101.04 | EG99: 101.14 | EH99: 100.87 | EI99: 101.8 | EJ99: 100.92 | EK99: 98.04 | EL99: 94.36 | EM99: 100.27 | EN99: 89.65 | EO99: 102 | EP99: 100.94 | EQ99: 99.79 | ER99: 98.16 | ES99: 97.1 | ET99: 100.64 | EU99: 96.92 | EV99: 100 | EW99: 100.13 | EX99: 99.92 | EY99: 98.84 | EZ99: 94.5 | FA99: 97.58 | FB99: 100.16 | FC99: 101.12 | FD99: 97.49 | FE99: 101.26 | FF99: 96.51 | FG99: 88.29 | FH99: 99.49 | FI99: 97.52 | FJ99: 98.01 | FK99: 96.89 | FL99: 96.43 | FM99: 99.13 | FN99: 97.3 | FO99: 100.7 | FP99: 98.78 | FQ99: 90.58 | FR99: 90.58 | FS99: 95.46 | FT99: 96.54 | FU99: 98.63 | FV99: 96.52 | FW99: 92.86 | FX99: 95.59 | FY99: 101.93 | FZ99: 89.46 | GA99: 107.98 | GB99: 92.87 | GC99: 92.39 | GD99: 98.05 | GE99: 98.11 | GF99: 97.62 | GG99: 97.62 | GH99: 98.46 | GI99: 98.46 | GJ99: 96.32 | GK99: 98.5 | GL99: 93.74 | GM99: 99.62 | GN99: 96.98 | GO99: 108.1 | GP99: 92.84 | GQ99: 98.44 | GR99: 97.3 | GS99: 97.02 | GT99: 98.75 | GU99: 96.48 | GV99: 96.48 | GW99: 98.72 | GX99: 98.56 | GY99: 99.08 | GZ99: 99.4 | HA99: 97.74 | HB99: 100 | HC99: 98.73 | HD99: 99.74 | HE99: 100.41 | HF99: 97.89 | HG99: 92.45 | HH99: 98.53 | HI99: 101.66 | HJ99: 99.46 | HK99: 102.46 | HL99: 103.17 | HM99: 98.4 | HN99: 98.82 | HO99: 98.88 | HP99: 98.31 | HQ99: 99.48 | HR99: 99.47 | HS99: 100.84 | HT99: 101.1 | HU99: 99.78 | HV99: 97.53 | HW99: 97.53 | HX99: 99.95 | HY99: 99.95 | HZ99: 98.37 | IA99: 98.37 | IB99: 95.03 | IC99: 98.54 | ID99: 99.86 | IE99: 96.22 | IF99: 100.73 | IG99: 91.75 | IH99: 96.82 | II99: 101.89 | IJ99: 94.59 | IK99: 100.66 | IL99: 108.13 | IM99: 92.69 | IN99: 100.73 | IO99: 96.8 | IP99: 102.32 | IQ99: 102.64
A100: 45689 | B100: 97.69 | C100: 98.07 | D100: 99.76 | E100: 100.96 | F100: 98.58 | G100: 99.94 | H100: 99.96 | I100: 98.55 | J100: 94.07 | K100: 100.25 | L100: 91.97 | M100: 101.92 | N100: 102.01 | O100: 100.05 | P100: 97.32 | Q100: 96.77 | R100: 100.19 | S100: 95.11 | T100: 100.12 | U100: 100.58 | V100: 99.72 | W100: 97.59 | X100: 94.27 | Y100: 97.14 | Z100: 99.73 | AA100: 101.15 | AB100: 94.96 | AC100: 100.83 | AD100: 99.32 | AE100: 89.82 | AF100: 101.87 | AG100: 97.16 | AH100: 97.3 | AI100: 96.97 | AJ100: 98.37 | AK100: 100.15 | AL100: 100.99 | AM100: 99.52 | AN100: 100.42 | AO100: 93.72 | AP100: 93.72 | AQ100: 97.71 | AR100: 100.04 | AS100: 101.57 | AT100: 100.86 | AU100: 94.77 | AV100: 100.44 | AW100: 105.77 | AX100: 97.82 | AY100: 105.28 | AZ100: 91.53 | BA100: 91.27 | BB100: 94.44 | BC100: 96.67 | BD100: 98.13 | BE100: 98.13 | BF100: 97.99 | BG100: 97.99 | BH100: 96.89 | BI100: 98.09 | BJ100: 94.65 | BK100: 91.05 | BL100: 99.99 | BM100: 88.53 | BN100: 94.47 | BO100: 99.19 | BP100: 103.54 | BQ100: 104.61 | BR100: 99.29 | BS100: 99.32 | BT100: 99.32 | BU100: 99.79 | BV100: 97.62 | BW100: 101.81 | BX100: 100.18 | BY100: 100.54 | BZ100: 99.45 | CA100: 99.14 | CB100: 99.19 | CC100: 99.7 | CD100: 96.65 | CE100: 93.09 | CF100: 98.8 | CG100: 98.86 | CH100: 97.99 | CI100: 104.11 | CJ100: 105.34 | CK100: 95.56 | CL100: 96.98 | CM100: 97.02 | CN100: 96.7 | CO100: 99.35 | CP100: 99.49 | CQ100: 100 | CR100: 101.8 | CS100: 100.32 | CT100: 97.34 | CU100: 97.98 | CV100: 96.4 | CW100: 96.4 | CX100: 99.07 | CY100: 99.07 | CZ100: 96.36 | DA100: 99.23 | DB100: 94.64 | DC100: 94.97 | DD100: 97.74 | DE100: 92.13 | DF100: 97.96 | DG100: 103.17 | DH100: 96.18 | DI100: 91.59 | DJ100: 94.28 | DK100: 89 | DL100: 99.61 | DM100: 100.84 | DN100: 100.65 | DO100: 100.91 | DP100: 97.56 | DQ100: 97.64 | DR100: 101.01 | DS100: 99.57 | DT100: 99.57 | DU100: 98.77 | DV100: 100 | DW100: 99.56 | DX100: 98.85 | DY100: 101.36 | DZ100: 101.36 | EA100: 98.17 | EB100: 96.32 | EC100: 98.34 | ED100: 98.1 | EE100: 98.16 | EF100: 99.82 | EG100: 100.97 | EH100: 98.73 | EI100: 100.16 | EJ100: 100 | EK100: 98.22 | EL100: 93.68 | EM100: 100.49 | EN100: 90.21 | EO100: 101.98 | EP100: 102.24 | EQ100: 99.8 | ER100: 97.5 | ES100: 96.74 | ET100: 100.25 | EU100: 95.57 | EV100: 99.61 | EW100: 99.2 | EX100: 99.9 | EY100: 97.49 | EZ100: 94.63 | FA100: 97.22 | FB100: 99.66 | FC100: 101.09 | FD100: 94.82 | FE100: 100.68 | FF100: 98.38 | FG100: 89.85 | FH100: 101.47 | FI100: 97.67 | FJ100: 98.08 | FK100: 97.14 | FL100: 96.37 | FM100: 98.78 | FN100: 99.35 | FO100: 96.82 | FP100: 100.08 | FQ100: 91.16 | FR100: 91.16 | FS100: 98.11 | FT100: 99.9 | FU100: 100.36 | FV100: 102.04 | FW100: 92.81 | FX100: 101.34 | FY100: 107.17 | FZ100: 96.01 | GA100: 111.19 | GB100: 92.11 | GC100: 91.48 | GD100: 98.86 | GE100: 97.37 | GF100: 98.07 | GG100: 98.07 | GH100: 98.15 | GI100: 98.15 | GJ100: 96.27 | GK100: 98.41 | GL100: 93.74 | GM100: 96.02 | GN100: 96.98 | GO100: 98.67 | GP100: 93.1 | GQ100: 98.94 | GR100: 99.82 | GS100: 100.14 | GT100: 98.16 | GU100: 101.78 | GV100: 101.78 | GW100: 98.55 | GX100: 99.33 | GY100: 100.88 | GZ100: 98.33 | HA100: 95.75 | HB100: 99.7 | HC100: 98.96 | HD100: 99.14 | HE100: 100.25 | HF100: 97.33 | HG100: 91.91 | HH100: 98 | HI100: 101.06 | HJ100: 99.49 | HK100: 103.4 | HL100: 104.24 | HM100: 98.59 | HN100: 98.66 | HO100: 98.65 | HP100: 98.77 | HQ100: 99.95 | HR100: 99.95 | HS100: 100.65 | HT100: 102.55 | HU100: 100.89 | HV100: 98.17 | HW100: 97.47 | HX100: 99.95 | HY100: 99.95 | HZ100: 99.09 | IA100: 99.09 | IB100: 96.36 | IC100: 99.24 | ID100: 96.38 | IE100: 96.72 | IF100: 101.26 | IG100: 92.21 | IH100: 98.8 | II100: 102.25 | IJ100: 97.27 | IK100: 92.34 | IL100: 95.7 | IM100: 88.75 | IN100: 102.26 | IO100: 99.14 | IP100: 101.44 | IQ100: 100.98
A101: 45717 | B101: 98.09 | C101: 98.72 | D101: 100.57 | E101: 101.1 | F101: 99.87 | G101: 101.09 | H101: 101.04 | I101: 98.61 | J101: 95.99 | K101: 100.98 | L101: 90.6 | M101: 101.57 | N101: 102.19 | O101: 99.05 | P101: 98.43 | Q101: 97.01 | R101: 101.02 | S101: 97.49 | T101: 102.78 | U101: 102.87 | V101: 102.69 | W101: 97.75 | X101: 95.4 | Y101: 97.87 | Z101: 99.65 | AA101: 99.22 | AB101: 95.7 | AC101: 100.55 | AD101: 100.04 | AE101: 90 | AF101: 102.73 | AG101: 97.49 | AH101: 97.55 | AI101: 97.39 | AJ101: 99.14 | AK101: 100.78 | AL101: 100.91 | AM101: 101.63 | AN101: 99.93 | AO101: 94.88 | AP101: 94.88 | AQ101: 94.42 | AR101: 96.86 | AS101: 98.86 | AT101: 96.73 | AU101: 94.5 | AV101: 97.87 | AW101: 100.55 | AX101: 94.97 | AY101: 107.01 | AZ101: 87.66 | BA101: 86.96 | BB101: 95.45 | BC101: 97.32 | BD101: 98.36 | BE101: 98.36 | BF101: 98.54 | BG101: 98.54 | BH101: 97.19 | BI101: 98.55 | BJ101: 94.65 | BK101: 93.01 | BL101: 99.99 | BM101: 91.28 | BN101: 94.47 | BO101: 98.97 | BP101: 102.31 | BQ101: 103.14 | BR101: 99 | BS101: 102.15 | BT101: 102.15 | BU101: 98.36 | BV101: 97.15 | BW101: 100.4 | BX101: 95.76 | BY101: 100.8 | BZ101: 99.53 | CA101: 99.34 | CB101: 98.93 | CC101: 99.99 | CD101: 96.76 | CE101: 93.22 | CF101: 98.96 | CG101: 98.86 | CH101: 98.31 | CI101: 103.58 | CJ101: 104.67 | CK101: 96.02 | CL101: 97.44 | CM101: 97.55 | CN101: 96.58 | CO101: 100.43 | CP101: 100.61 | CQ101: 100.08 | CR101: 103.79 | CS101: 103.41 | CT101: 97.81 | CU101: 98.04 | CV101: 96.45 | CW101: 96.45 | CX101: 98.93 | CY101: 98.93 | CZ101: 96.76 | DA101: 99.06 | DB101: 95.21 | DC101: 95.51 | DD101: 97.76 | DE101: 93.19 | DF101: 96.59 | DG101: 98.64 | DH101: 95.89 | DI101: 93.12 | DJ101: 96.6 | DK101: 89.78 | DL101: 98.68 | DM101: 98.74 | DN101: 98.2 | DO101: 100.89 | DP101: 98.08 | DQ101: 98.01 | DR101: 99.17 | DS101: 99.58 | DT101: 99.58 | DU101: 98.8 | DV101: 100 | DW101: 99.56 | DX101: 99.05 | DY101: 100.03 | DZ101: 100.03 | EA101: 98.79 | EB101: 98.47 | EC101: 98.82 | ED101: 98.03 | EE101: 98.79 | EF101: 100.55 | EG101: 101.01 | EH101: 100.03 | EI101: 100.89 | EJ101: 100.82 | EK101: 98.25 | EL101: 95.6 | EM101: 101.06 | EN101: 89.25 | EO101: 101.48 | EP101: 102.35 | EQ101: 98.64 | ER101: 98.44 | ES101: 96.94 | ET101: 101.04 | EU101: 97.66 | EV101: 102.52 | EW101: 101.93 | EX101: 102.94 | EY101: 97.76 | EZ101: 96.06 | FA101: 97.75 | FB101: 99.6 | FC101: 99.21 | FD101: 95.76 | FE101: 100.55 | FF101: 99.37 | FG101: 90.12 | FH101: 102.72 | FI101: 97.86 | FJ101: 98.13 | FK101: 97.52 | FL101: 97.13 | FM101: 99.33 | FN101: 99.48 | FO101: 99.53 | FP101: 99.11 | FQ101: 92.35 | FR101: 92.35 | FS101: 94.32 | FT101: 97.26 | FU101: 97.21 | FV101: 99.2 | FW101: 91.61 | FX101: 97.71 | FY101: 100.88 | FZ101: 93.4 | GA101: 110.03 | GB101: 85.55 | GC101: 84.26 | GD101: 99.51 | GE101: 96.99 | GF101: 98.37 | GG101: 98.37 | GH101: 96.73 | GI101: 96.73 | GJ101: 96.49 | GK101: 98.82 | GL101: 93.74 | GM101: 96.02 | GN101: 96.98 | GO101: 98.67 | GP101: 93.1 | GQ101: 98.81 | GR101: 99.05 | GS101: 99.17 | GT101: 98.38 | GU101: 101.87 | GV101: 101.87 | GW101: 96.67 | GX101: 97.31 | GY101: 98.29 | GZ101: 93.83 | HA101: 97.59 | HB101: 99.84 | HC101: 99.37 | HD101: 99.4 | HE101: 100.25 | HF101: 98.28 | HG101: 94.57 | HH101: 98.11 | HI101: 101.64 | HJ101: 99.13 | HK101: 102.91 | HL101: 103.68 | HM101: 98.59 | HN101: 98.32 | HO101: 98.27 | HP101: 98.77 | HQ101: 98.91 | HR101: 98.88 | HS101: 101.04 | HT101: 103.49 | HU101: 96.54 | HV101: 98.17 | HW101: 97.5 | HX101: 99.84 | HY101: 99.84 | HZ101: 98.95 | IA101: 98.95 | IB101: 96.76 | IC101: 99.07 | ID101: 97.29 | IE101: 97.75 | IF101: 102.31 | IG101: 93.21 | IH101: 98.06 | II101: 101.99 | IJ101: 96.32 | IK101: 95.15 | IL101: 102 | IM101: 87.86 | IN101: 100.31 | IO101: 98.19 | IP101: 99.25 | IQ101: 100.76
... A111: 46023 | B111: 101.61 | C111: 101.55 | D111: 102.05 | E111: 101.63 | F111: 102.71 | G111: 104.74 | H111: 99.67 | I111: 101.92 | J111: 105.29 | K111: 100.64 | L111: 98.47 | M111: 100.97 | N111: 102.62 | O111: 101.84 | P111: 100.88 | Q111: 101.59 | R111: 100.82 | S111: 100.12 | T111: 102.88 | U111: 104.37 | V111: 101.58 | W111: 101.85 | X111: 97.29 | Y111: 101.1 | Z111: 101.35 | AA111: 98.77 | AB111: 103.09 | AC111: 102.61 | AD111: 100 | AE111: 100.31 | AF111: 99.92 | AG111: 101.25 | AH111: 101.84 | AI111: 100.41 | AJ111: 101.22 | AK111: 100.91 | AL111: 100.76 | AM111: 100.31 | AN111: 101.53 | AO111: 102.03 | AP111: 102.03 | AQ111: 101.37 | AR111: 100.49 | AS111: 101.06 | AT111: 100.18 | AU111: 100.87 | AV111: 98.27 | AW111: 103.08 | AX111: 95.97 | AY111: 102.31 | AZ111: 104.68 | BA111: 105.01 | BB111: 100.99 | BC111: 103.33 | BD111: 101.15 | BE111: 101.15 | BF111: 101.12 | BG111: 101.12 | BH111: 100.71 | BI111: 101.1 | BJ111: 100 | BK111: 114.29 | BL111: 119.4 | BM111: 115.58 | BN111: 102.71 | BO111: 99.32 | BP111: 96.31 | BQ111: 95.53 | BR111: 99.42 | BS111: 93.7 | BT111: 93.7 | BU111: 98.88 | BV111: 96.87 | BW111: 100.11 | BX111: 100.37 | BY111: 98.91 | BZ111: 99.48 | CA111: 100.02 | CB111: 100.75 | CC111: 98.47 | CD111: 101.73 | CE111: 102.73 | CF111: 101.11 | CG111: 101.14 | CH111: 101.42 | CI111: 102.34 | CJ111: 102.74 | CK111: 99.6 | CL111: 101.27 | CM111: 101.37 | CN111: 100.49 | CO111: 99.71 | CP111: 99.7 | CQ111: 101.78 | CR111: 101.87 | CS111: 94.84 | CT111: 102.12 | CU111: 100.05 | CV111: 99.98 | CW111: 99.98 | CX111: 99.72 | CY111: 99.72 | CZ111: 100.78 | DA111: 99.65 | DB111: 103.11 | DC111: 99.75 | DD111: 98.58 | DE111: 100.94 | DF111: 99.21 | DG111: 104.17 | DH111: 97.51 | DI111: 104.4 | DJ111: 112.4 | DK111: 96.7 | DL111: 103.03 | DM111: 102.09 | DN111: 104.07 | DO111: 102.7 | DP111: 101.9 | DQ111: 101.37 | DR111: 105.29 | DS111: 99.98 | DT111: 99.98 | DU111: 99.91 | DV111: 100 | DW111: 100 | DX111: 101.24 | DY111: 103.66 | DZ111: 103.66 | EA111: 100.57 | EB111: 99.96 | EC111: 100.63 | ED111: 101.45 | EE111: 101.41 | EF111: 102 | EG111: 101.68 | EH111: 102.56 | EI111: 104.48 | EJ111: 99.82 | EK111: 102.13 | EL111: 105.4 | EM111: 101.27 | EN111: 99.38 | EO111: 100.62 | EP111: 103.06 | EQ111: 101.81 | ER111: 100.75 | ES111: 101 | ET111: 100.91 | EU111: 100.26 | EV111: 101.86 | EW111: 101.54 | EX111: 102.09 | EY111: 101.64 | EZ111: 96.23 | FA111: 101.14 | FB111: 101.53 | FC111: 98.11 | FD111: 103.05 | FE111: 102.58 | FF111: 99.98 | FG111: 100.41 | FH111: 99.83 | FI111: 101.21 | FJ111: 100.8 | FK111: 101.74 | FL111: 101.05 | FM111: 100.48 | FN111: 100.74 | FO111: 100.86 | FP111: 100.05 | FQ111: 102.28 | FR111: 102.28 | FS111: 100.07 | FT111: 100.14 | FU111: 101.01 | FV111: 100.97 | FW111: 96.16 | FX111: 96.93 | FY111: 101.59 | FZ111: 91.96 | GA111: 108.28 | GB111: 101.66 | GC111: 101.73 | GD111: 100.99 | GE111: 102.43 | GF111: 100.84 | GG111: 100.84 | GH111: 101.28 | GI111: 101.28 | GJ111: 100.81 | GK111: 101.49 | GL111: 100 | GM111: 107.81 | GN111: 100 | GO111: 121.55 | GP111: 98.39 | GQ111: 98.99 | GR111: 94.48 | GS111: 93.49 | GT111: 99.75 | GU111: 96.6 | GV111: 96.6 | GW111: 98.57 | GX111: 98.79 | GY111: 96.8 | GZ111: 100.13 | HA111: 98.39 | HB111: 99.63 | HC111: 100.12 | HD111: 100.63 | HE111: 98.79 | HF111: 101.89 | HG111: 101.27 | HH111: 101.73 | HI111: 102.63 | HJ111: 102.18 | HK111: 102.33 | HL111: 103.21 | HM111: 97.4 | HN111: 102.15 | HO111: 102.26 | HP111: 101.08 | HQ111: 100.61 | HR111: 101.34 | HS111: 101.54 | HT111: 98.97 | HU111: 101.02 | HV111: 102.26 | HW111: 101.45 | HX111: 78.45 | HY111: 78.45 | HZ111: 99.71 | IA111: 99.71 | IB111: 100.78 | IC111: 99.66 | ID111: 103.34 | IE111: 101.51 | IF111: 102.14 | IG111: 100.9 | IH111: 100.29 | II111: 103.8 | IJ111: 98.74 | IK111: 105.32 | IL111: 114.68 | IM111: 95.34 | IN111: 101.49 | IO111: 97.23 | IP111: 105.13 | IQ111: 102.59

Sheet Data2
